Workbook
Name LISTA_ACAO_FUTURA: REGRAS!$B$114:$B$120
Name LISTA_ATIVO_RECEPTIVO: REGRAS!$B$100:$B$101
Name LISTA_CONSULTOR: REGRAS!$A$88:$A$91
Name LISTA_CURVA_ABC: REGRAS!$B$102:$B$104
Name LISTA_FASE: REGRAS!$B$51:$B$59
Name LISTA_GRUPO_DASH: REGRAS!$B$111:$B$113
Name LISTA_MOTIVO: REGRAS!$B$28:$B$37
Name LISTA_RESULTADO: REGRAS!$B$2:$B$13
Name LISTA_SIM_NAO: REGRAS!$B$95:$B$96
Name LISTA_SIM_NAO_NA: REGRAS!$B$97:$B$99
Name LISTA_SINALEIRO: REGRAS!$A$72:$A$75
Name LISTA_SITUACAO: REGRAS!$B$41:$B$47
Name LISTA_TENTATIVA: REGRAS!$B$63:$B$68
Name LISTA_TIPO_CLIENTE: REGRAS!$B$105:$B$110
Name LISTA_TIPO_CONTATO: REGRAS!$B$18:$B$24

Sheet REGRAS
A1: # | B1: RESULTADO | C1: FOLLOW-UP (DIAS) | D1: GRUPO DASH | E1: QUANDO USAR
A2: 1 | B2: EM ATENDIMENTO | C2: 2 | D2: FUNIL | E2: Negociação ativa
A3: 2 | B3: ORÇAMENTO | C3: 1 | D3: FUNIL | E3: Proposta enviada
A4: 3 | B4: CADASTRO | C4: 2 | D4: FUNIL | E4: Cliente novo em cadastro
A5: 4 | B5: VENDA / PEDIDO | C5: 45 | D5: FUNIL | E5: Pedido fechado
A6: 5 | B6: RELACIONAMENTO | C6: 7 | D6: RELAC. | E6: Contato pós-venda/CS
A7: 6 | B7: FOLLOW UP 7 | C7: 7 | D7: RELAC. | E7: Retomar em 1 semana
A8: 7 | B8: FOLLOW UP 15 | C8: 15 | D8: RELAC. | E8: Retomar em 2 semanas
A9: 8 | B9: SUPORTE | C9: 0 | D9: RELAC. | E9: Problema resolvido
A10: 9 | B10: NÃO ATENDE | C10: 1 | D10: NÃO VENDA | E10: Ligou sem resposta
A11: 10 | B11: NÃO RESPONDE | C11: 1 | D11: NÃO VENDA | E11: WhatsApp sem resposta
A12: 11 | B12: RECUSOU LIGAÇÃO | C12: 2 | D12: NÃO VENDA | E12: Rejeitou chamada
A13: 12 | B13: PERDA / FECHOU LOJA | C13: 0 | D13: NÃO VENDA | E13: Cliente perdido
A17: # | B17: TIPO DO CONTATO | C17: QUANDO USAR
A18: 1 | B18: PROSPECÇÃO | C18: Primeiro contato com prospect/lead que nunca comprou
A19: 2 | B19: NEGOCIAÇÃO | C19: Cliente demonstrou interesse, está em fase de proposta/orçamento
A20: 3 | B20: FOLLOW UP | C20: Retomada de contato agendado (follow-up 7d ou 15d)
A21: 4 | B21: ATEND. CLIENTES ATIVOS | C21: Manutenção de clientes ATIVOS (ciclo de recompra, pós-venda)
A22: 5 | B22: ATEND. CLIENTES INATIVOS | C22: Reativação de INAT.REC ou INAT.ANT (não compra há 60+ dias)
A23: 6 | B23: PÓS-VENDA / RELACIONAMENTO | C23: Contato de relacionamento após venda (satisfação, CS, suporte)
A24: 7 | B24: PERDA / NUTRIÇÃO | C24: Cliente perdido ou em nutrição (fechou loja, sem interesse)
A27: # | B27: MOTIVO | C27: DONO DA AÇÃO
A28: 1 | B28: AINDA TEM ESTOQUE | C28: Normal
A29: 2 | B29: PRODUTO NÃO VENDEU / SEM GIRO | C29: DIRETORIA / FÁBRICA
A30: 3 | B30: LOJA ANEXO/PROXIMO - SM | C30: COMERCIAL
A31: 4 | B31: SÓ QUER COMPRAR GRANEL | C31: COMERCIAL / MKT
A32: 5 | B32: PROBLEMA LOGÍSTICO / ENTREGA | C32: LOGÍSTICA
A33: 6 | B33: PROBLEMA FINANCEIRO / CRÉDITO | C33: FINANCEIRO
A34: 7 | B34: PROPRIETARIO / INDISPONÍVEL | C34: Normal
A35: 8 | B35: FECHANDO / FECHOU LOJA | C35: PERDA
A36: 9 | B36: SEM INTERESSE NO MOMENTO | C36: NUTRIÇÃO
A37: 10 | B37: PRIMEIRO CONTATO / SEM RESPOSTA | C37: Normal
A40: DIAS | B40: SITUAÇÃO | C40: COR HEX
A41: ≤ 50 | B41: ATIVO | C41: #00B050
A42: 51-60 | B42: EM RISCO | C42: #FFC000
A43: 61-90 | B43: INAT.REC | C43: #FFC000
A44: > 90 | B44: INAT.ANT | C44: #FF0000
A45: Nunca comprou + cadastro | B45: NOVO | C45: #0070C0
A46: Nunca comprou | B46: PROSPECT | C46: #7B2FF2
A47: Manual (Daiane) | B47: LEAD | C47: #7B2FF2
A50: # | B50: FASE | C50: DESCRIÇÃO
A51: 1 | B51: PÓS-VENDA
A52: 2 | B52: CS
A53: 3 | B53: RECOMPRA
A54: 4 | B54: SALVAMENTO
A55: 5 | B55: RECUPERAÇÃO
A56: 6 | B56: PROSPECÇÃO
A57: 7 | B57: NUTRIÇÃO
A58: 8 | B58: EM ATENDIMENTO
A59: 9 | B59: ORÇAMENTO
A62: # | B62: TENTATIVA | C62: CANAL | D62: INTERVALO
A63: 1 | B63: T1 | C63: WhatsApp | D63: Dia 0
A64: 2 | B64: T2 | C64: Ligação | D64: +1 dia
A65: 3 | B65: T3 | C65: WhatsApp | D65: +2 dias
A66: 4 | B66: T4 | C66: Ligação final | D66: +2 dias
A67: 5 | B67: NUTRIÇÃO | C67: Email+WhatsApp | D67: Ciclo 15d
A68: 6 | B68: RESET | C68: Qualquer | D68: Quando responde
A71: SINALEIRO | B71: CONDIÇÃO
A72: 🟢 | B72: Dias ≤ Ciclo Médio
A73: 🟡 | B73: Dias ≤ Ciclo+30
A74: 🔴 | B74: Dias > Ciclo+30
A75: 🟣 | B75: Nunca comprou
A78: # | B78: TIPO CLIENTE | C78: CRITÉRIO
A79: 1 | B79: NOVO | C79: 1ª compra
A80: 2 | B80: EM DESENVOLVIMENTO | C80: 2-3 compras
A81: 3 | B81: RECORRENTE | C81: 4+ compras 3+ meses
A82: 4 | B82: FIDELIZADO | C82: 6+ compras 6+ meses
A83: 5 | B83: PROSPECT | C83: Nunca comprou
A84: 6 | B84: LEAD | C84: Manual Daiane
A87: CONSULTOR | B87: TERRITÓRIO
A88: MANU DITZEL | B88: SC/PR/RS
A89: LARISSA PADILHA | B89: Resto do Brasil
A90: JULIO GADRET | B90: CIA DA SAUDE / FITLAND
A91: DAIANE STAVICKI | B91: Redes de Franquia
A94: LISTA | B94: VALORES
A95: SIM_NAO | B95: SIM
B96: NÃO
A97: SIM_NAO_NA | B97: SIM
B98: NÃO
B99: N/A
A100: ATIVO_RECEPTIVO | B100: ATIVO
B101: RECEPTIVO
A102: CURVA_ABC | B102: A
B103: B
B104: C
A105: TIPO_CLIENTE | B105: NOVO
B106: EM DESENVOLVIMENTO
B107: RECORRENTE
B108: FIDELIZADO
B109: PROSPECT
B110: LEAD
A111: GRUPO_DASH | B111: FUNIL
B112: RELAC.
B113: NÃO VENDA
A114: ACAO_FUTURA | B114: RECOMPRA
B115: PÓS-VENDA
B116: CS
B117: REATIVAÇÃO
B118: PROSPECÇÃO
B119: NUTRIÇÃO
...

Sheet CARTEIRA
A1: 🟣 MERCOS | AR1: 🔵 FUNIL | BJ1: ⚫ SAP | BU1: 🟢 ACOMPANHAMENTO | BV1: Q1 | BW1: JAN | CC1: 100% | CD1: =SUBTOTAL(109,CD4:CD5000) -> 0 | CE1: =SUBTOTAL(109,CE4:CE5000) -> 0 | CL1: FEV | CR1: 100% | CS1: =SUBTOTAL(109,CS4:CS5000) -> 0 | CT1: =SUBTOTAL(109,CT4:CT5000) -> 0 | DA1: MAR | DG1: 100% | DH1: =SUBTOTAL(109,DH4:DH5000) -> 0 | DI1: =SUBTOTAL(109,DI4:DI5000) -> 0 | DP1: Q2 | DQ1: ABR | DW1: 100% | DX1: =SUBTOTAL(109,DX4:DX5000) -> 0 | DY1: =SUBTOTAL(109,DY4:DY5000) -> 0 | EF1: MAI | EL1: 100% | EM1: =SUBTOTAL(109,EM4:EM5000) -> 0 | EN1: =SUBTOTAL(109,EN4:EN5000) -> 0 | EU1: JUN | FA1: 100% | FB1: =SUBTOTAL(109,FB4:FB5000) -> 0 | FC1: =SUBTOTAL(109,FC4:FC5000) -> 0 | FJ1: Q3 | FK1: JUL | FQ1: 100% | FR1: =SUBTOTAL(109,FR4:FR5000) -> 0 | FS1: =SUBTOTAL(109,FS4:FS5000) -> 0 | FZ1: AGO | GF1: 100% | GG1: =SUBTOTAL(109,GG4:GG5000) -> 0 | GH1: =SUBTOTAL(109,GH4:GH5000) -> 0 | GO1: SET | GU1: 100% | GV1: =SUBTOTAL(109,GV4:GV5000) -> 0 | GW1: =SUBTOTAL(109,GW4:GW5000) -> 0 | HD1: Q4 | HE1: OUT | HK1: 100% | HL1: =SUBTOTAL(109,HL4:HL5000) -> 0 | HM1: =SUBTOTAL(109,HM4:HM5000) -> 0 | HT1: NOV | HZ1: 100% | IA1: =SUBTOTAL(109,IA4:IA5000) -> 0 | IB1: =SUBTOTAL(109,IB4:IB5000) -> 0 | II1: DEZ | IO1: 100% | IP1: =SUBTOTAL(109,IP4:IP5000) -> 0 | IQ1: =SUBTOTAL(109,IQ4:IQ5000) -> 0
A2: ANCORA | B2: IDENTIDADE | C2: IDENTIDADE | D2: IDENTIDADE | E2: IDENTIDADE | F2: IDENTIDADE | G2: IDENTIDADE | H2: IDENTIDADE | I2: REDE | J2: REDE | K2: REDE | L2: EQUIPE | M2: EQUIPE | N2: STATUS | O2: STATUS | P2: COMPRA | Q2: COMPRA | R2: COMPRA | S2: ECOMMERCE | T2: ECOMMERCE | U2: ECOMMERCE | V2: ECOMMERCE | W2: ECOMMERCE | X2: ECOMMERCE | Y2: VENDAS | Z2: VENDAS | AA2: VENDAS | AB2: VENDAS | AC2: VENDAS | AD2: VENDAS | AE2: VENDAS | AF2: VENDAS | AG2: VENDAS | AH2: VENDAS | AI2: VENDAS | AJ2: VENDAS | AK2: RECORRÊNCIA | AL2: RECORRÊNCIA | AM2: RECORRÊNCIA | AN2: RECORRÊNCIA | AO2: RECORRÊNCIA | AP2: RECORRÊNCIA | AQ2: RECORRÊNCIA | AR2: ANCORA | AS2: PIPELINE | AT2: PIPELINE | AU2: PIPELINE | AV2: PIPELINE | AW2: PERFIL | AX2: PERFIL | AY2: MATURIDADE | AZ2: MATURIDADE | BA2: CONVERSÃO | BB2: CONVERSÃO | BC2: CONVERSÃO | BD2: CONVERSÃO | BE2: CONVERSÃO | BF2: CONVERSÃO | BG2: AÇÃO | BH2: AÇÃO | BI2: SINAL | BJ2: DADOS SAP | BK2: SAP | BL2: SAP | BM2: SAP | BN2: SAP | BO2: SAP | BP2: SAP | BQ2: SAP | BR2: SAP | BS2: SAP | BT2: SAP | BW2: YTD | BZ2: TRI | CC2: MÊS | CL2: YTD | CO2: TRI | CR2: MÊS | DA2: YTD | DD2: TRI | DG2: MÊS | DQ2: YTD | DT2: TRI | DW2: MÊS | EF2: YTD | EI2: TRI | EL2: MÊS | EU2: YTD | EX2: TRI | FA2: MÊS | FK2: YTD | FN2: TRI | FQ2: MÊS | FZ2: YTD | GC2: TRI | GF2: MÊS | GO2: YTD | GR2: TRI | GU2: MÊS | HE2: YTD | HH2: TRI | HK2: MÊS | HT2: YTD | HW2: TRI | HZ2: MÊS | II2: YTD | IL2: TRI | IO2: MÊS
A3: NOME FANTASIA | B3: CNPJ | C3: RAZÃO SOCIAL | D3: UF | E3: CIDADE | F3: EMAIL | G3: TELEFONE | H3: DATA CADASTRO | I3: REDE / REGIONAL | K3: ÚLT. REGISTRO MERCOS | L3: CONSULTOR | M3: VENDEDOR ÚLTIMO PEDIDO | N3: SITUAÇÃO | O3: PRIORIDADE | P3: DIAS SEM COMPRA | Q3: DATA ÚLTIMO PEDIDO | R3: VALOR ÚLTIMO PEDIDO | S3: 📊 ACESSOS SEMANA | T3: ACESSO B2B | U3: ACESSOS PORTAL | V3: ITENS CARRINHO | W3: VALOR B2B | X3: OPORTUNIDADE | Y3: TOTAL PERÍODO | Z3: MAR/25 | AA3: ABR/25 | AB3: MAI/25 | AC3: JUN/25 | AD3: JUL/25 | AE3: AGO/25 | AF3: SET/25 | AG3: OUT/25 | AH3: NOV/25 | AI3: DEZ/25 | AJ3: JAN/26 | AK3: CICLO MÉDIO | AL3: Nº COMPRAS | AM3: CURVA ABC | AN3: MESES POSITIVADO | AO3: MÉDIA MENSAL | AP3: TICKET MÉDIO | AQ3: MESES LISTA | AR3: ESTÁGIO FUNIL | AS3: PRÓX. FOLLOW-UP | AT3: DATA ÚLT.ATENDIMENTO | AU3: ÚLTIMO RESULTADO | AV3: MOTIVO | AW3: TIPO CLIENTE | AX3: TENTATIVA | AY3: FASE | AZ3: ÚLTIMA RECOMPRA | BA3: 🔥 TEMPERATURA | BB3: DIAS ATÉ CONVERSÃO | BC3: DATA 1º CONTATO | BD3: DATA 1º ORÇAMENTO | BE3: DATA 1ª VENDA | BF3: TOTAL TENTATIVAS | BG3: PRÓX. AÇÃO | BH3: AÇÃO DETALHADA | BI3: 🚦 SINALEIRO | BJ3: CÓDIGO DO CLIENTE | BK3: DESCRIÇÃO GRUPO CLIENTE | BL3: ZP NOME GERENTE NACIONAL | BM3: ZR NOME REPRESENTANTE | BN3: ZV NOME VEND. INTERNO | BO3: 01 NOME DO CANAL | BP3: 02 NOME TIPO CLIENTE | BQ3: 03 NOME MACROREGIÃO | BR3: 04 NOME MICROREGIÃO | BS3: 06 NOME GRUPO CHAVE | BT3: VENDA | BU3: % ATING. | BV3: % Q1 | BW3: % YTD | BX3: META | BY3: REALIZADO | BZ3: % TRI | CA3: META | CB3: REALIZADO | CC3: % MÊS | CD3: META | CE3: REALIZADO | CF3: DATA PEDIDO | CG3: JUSTIFICATIVA SEMANA 1 | CH3: JUSTIFICATIVA SEMANA 2 | CI3: JUSTIFICATIVA SEMANA 3 | CJ3: JUSTIFICATIVA SEMANA 4 | CK3: JUSTIFICATIVA MENSAL | CL3: % YTD | CM3: META | CN3: REALIZADO | CO3: % TRI | CP3: META | CQ3: REALIZADO | CR3: % MÊS | CS3: META | CT3: REALIZADO | CU3: DATA PEDIDO | CV3: JUSTIFICATIVA SEMANA 1 | CW3: JUSTIFICATIVA SEMANA 2 | CX3: JUSTIFICATIVA SEMANA 3 | CY3: JUSTIFICATIVA SEMANA 4 | CZ3: JUSTIFICATIVA MENSAL | DA3: % YTD | DB3: META | DC3: REALIZADO | DD3: % TRI | DE3: META | DF3: REALIZADO | DG3: % MÊS | DH3: META | DI3: REALIZADO | DJ3: DATA PEDIDO | DK3: JUSTIFICATIVA SEMANA 1 | DL3: JUSTIFICATIVA SEMANA 2 | DM3: JUSTIFICATIVA SEMANA 3 | DN3: JUSTIFICATIVA SEMANA 4 | DO3: JUSTIFICATIVA MENSAL | DP3: % Q2 | DQ3: % YTD | DR3: META | DS3: REALIZADO | DT3: % TRI | DU3: META | DV3: REALIZADO | DW3: % MÊS | DX3: META | DY3: REALIZADO | DZ3: DATA PEDIDO | EA3: JUSTIFICATIVA SEMANA 1 | EB3: JUSTIFICATIVA SEMANA 2 | EC3: JUSTIFICATIVA SEMANA 3 | ED3: JUSTIFICATIVA SEMANA 4 | EE3: JUSTIFICATIVA MENSAL | EF3: % YTD | EG3: META | EH3: REALIZADO | EI3: % TRI | EJ3: META | EK3: REALIZADO | EL3: % MÊS | EM3: META | EN3: REALIZADO | EO3: DATA PEDIDO | EP3: JUSTIFICATIVA SEMANA 1 | EQ3: JUSTIFICATIVA SEMANA 2 | ER3: JUSTIFICATIVA SEMANA 3 | ES3: JUSTIFICATIVA SEMANA 4 | ET3: JUSTIFICATIVA MENSAL | EU3: % YTD | EV3: META | EW3: REALIZADO | EX3: % TRI | EY3: META | EZ3: REALIZADO | FA3: % MÊS | FB3: META | FC3: REALIZADO | FD3: DATA PEDIDO | FE3: JUSTIFICATIVA SEMANA 1 | FF3: JUSTIFICATIVA SEMANA 2 | FG3: JUSTIFICATIVA SEMANA 3 | FH3: JUSTIFICATIVA SEMANA 4 | FI3: JUSTIFICATIVA MENSAL | FJ3: % Q3 | FK3: % YTD | FL3: META | FM3: REALIZADO | FN3: % TRI | FO3: META | FP3: REALIZADO | FQ3: % MÊS | FR3: META | FS3: REALIZADO | FT3: DATA PEDIDO | FU3: JUSTIFICATIVA SEMANA 1 | FV3: JUSTIFICATIVA SEMANA 2 | FW3: JUSTIFICATIVA SEMANA 3 | FX3: JUSTIFICATIVA SEMANA 4 | FY3: JUSTIFICATIVA MENSAL | FZ3: % YTD | GA3: META | GB3: REALIZADO | GC3: % TRI | GD3: META | GE3: REALIZADO | GF3: % MÊS | GG3: META | GH3: REALIZADO | GI3: DATA PEDIDO | GJ3: JUSTIFICATIVA SEMANA 1 | GK3: JUSTIFICATIVA SEMANA 2 | GL3: JUSTIFICATIVA SEMANA 3 | GM3: JUSTIFICATIVA SEMANA 4 | GN3: JUSTIFICATIVA MENSAL | GO3: % YTD | GP3: META | GQ3: REALIZADO | GR3: % TRI | GS3: META | GT3: REALIZADO | GU3: % MÊS | GV3: META | GW3: REALIZADO | GX3: DATA PEDIDO | GY3: JUSTIFICATIVA SEMANA 1 | GZ3: JUSTIFICATIVA SEMANA 2 | HA3: JUSTIFICATIVA SEMANA 3 | HB3: JUSTIFICATIVA SEMANA 4 | HC3: JUSTIFICATIVA MENSAL | HD3: % Q4 | HE3: % YTD | HF3: META | HG3: REALIZADO | HH3: % TRI | HI3: META | HJ3: REALIZADO | HK3: % MÊS | HL3: META | HM3: REALIZADO | HN3: DATA PEDIDO | HO3: JUSTIFICATIVA SEMANA 1 | HP3: JUSTIFICATIVA SEMANA 2 | HQ3: JUSTIFICATIVA SEMANA 3 | HR3: JUSTIFICATIVA SEMANA 4 | HS3: JUSTIFICATIVA MENSAL | HT3: % YTD | HU3: META | HV3: REALIZADO | HW3: % TRI | HX3: META | HY3: REALIZADO | HZ3: % MÊS | IA3: META | IB3: REALIZADO | IC3: DATA PEDIDO | ID3: JUSTIFICATIVA SEMANA 1 | IE3: JUSTIFICATIVA SEMANA 2 | IF3: JUSTIFICATIVA SEMANA 3 | IG3: JUSTIFICATIVA SEMANA 4 | IH3: JUSTIFICATIVA MENSAL | II3: % YTD | IJ3: META | IK3: REALIZADO | IL3: % TRI | IM3: META | IN3: REALIZADO | IO3: % MÊS | IP3: META | IQ3: REALIZADO | IR3: DATA PEDIDO | IS3: JUSTIFICATIVA SEMANA 1 | IT3: JUSTIFICATIVA SEMANA 2 | IU3: JUSTIFICATIVA SEMANA 3 | IV3: JUSTIFICATIVA SEMANA 4 | IW3: JUSTIFICATIVA MENSAL
A4: =IFERROR(INDEX('DRAFT 1'!$A:$A,MATCH($B4,'DRAFT 1'!$B:$B,0)),"") | B4: 32828171000108 | C4: =IFERROR(INDEX('DRAFT 1'!$C:$C,MATCH($B4,'DRAFT 1'!$B:$B,0)),"") | D4: =IFERROR(INDEX('DRAFT 1'!$D:$D,MATCH($B4,'DRAFT 1'!$B:$B,0)),"") | E4: =IFERROR(INDEX('DRAFT 1'!$E:$E,MATCH($B4,'DRAFT 1'!$B:$B,0)),"") | F4: =IFERROR(INDEX('DRAFT 1'!$F:$F,MATCH($B4,'DRAFT 1'!$B:$B,0)),"") | G4: =IFERROR(INDEX('DRAFT 1'!$G:$G,MATCH($B4,'DRAFT 1'!$B:$B,0)),"") | H4: =IFERROR(INDEX('DRAFT 1'!$H:$H,MATCH($B4,'DRAFT 1'!$B:$B,0)),"") | I4: MUNDO VERDE | K4: =IFERROR(INDEX('DRAFT 1'!$AL:$AL,MATCH($B4,'DRAFT 1'!$B:$B,0)),"") | L4: =IFERROR(INDEX('DRAFT 1'!$J:$J,MATCH($B4,'DRAFT 1'!$B:$B,0)),"") | M4: =IFERROR(INDEX('DRAFT 1'!$K:$K,MATCH($B4,'DRAFT 1'!$B:$B,0)),"") | N4: EM RISCO | O4: =IF(N4="EM RISCO",1,IF(N4="INAT.REC",2,IF(N4="ATIVO",3,IF(N4="INAT.ANT",4,5)))) -> 1 | P4: =IFERROR(INDEX('DRAFT 1'!$L:$L,MATCH($B4,'DRAFT 1'!$B:$B,0)),"") | Q4: =IFERROR(INDEX('DRAFT 1'!$M:$M,MATCH($B4,'DRAFT 1'!$B:$B,0)),"") | R4: =IFERROR(INDEX('DRAFT 1'!$N:$N,MATCH($B4,'DRAFT 1'!$B:$B,0)),"") | S4: =IFERROR(INDEX('DRAFT 1'!$O:$O,MATCH($B4,'DRAFT 1'!$B:$B,0)),"") | T4: =IFERROR(INDEX('DRAFT 1'!$P:$P,MATCH($B4,'DRAFT 1'!$B:$B,0)),"") | U4: =IFERROR(INDEX('DRAFT 1'!$Q:$Q,MATCH($B4,'DRAFT 1'!$B:$B,0)),"") | V4: =IFERROR(INDEX('DRAFT 1'!$R:$R,MATCH($B4,'DRAFT 1'!$B:$B,0)),"") | W4: =IFERROR(INDEX('DRAFT 1'!$S:$S,MATCH($B4,'DRAFT 1'!$B:$B,0)),"") | X4: =IFERROR(INDEX('DRAFT 1'!$T:$T,MATCH($B4,'DRAFT 1'!$B:$B,0)),"") | Y4: =SUM(Z4:AJ4) -> 0 | Z4: =IFERROR(INDEX('DRAFT 1'!$U:$U,MATCH($B4,'DRAFT 1'!$B:$B,0)),"") | AA4: =IFERROR(INDEX('DRAFT 1'!$V:$V,MATCH($B4,'DRAFT 1'!$B:$B,0)),"") | AB4: =IFERROR(INDEX('DRAFT 1'!$W:$W,MATCH($B4,'DRAFT 1'!$B:$B,0)),"") | AC4: =IFERROR(INDEX('DRAFT 1'!$X:$X,MATCH($B4,'DRAFT 1'!$B:$B,0)),"") | AD4: =IFERROR(INDEX('DRAFT 1'!$Y:$Y,MATCH($B4,'DRAFT 1'!$B:$B,0)),"") | AE4: =IFERROR(INDEX('DRAFT 1'!$Z:$Z,MATCH($B4,'DRAFT 1'!$B:$B,0)),"") | AF4: =IFERROR(INDEX('DRAFT 1'!$AA:$AA,MATCH($B4,'DRAFT 1'!$B:$B,0)),"") | AG4: =IFERROR(INDEX('DRAFT 1'!$AB:$AB,MATCH($B4,'DRAFT 1'!$B:$B,0)),"") | AH4: =IFERROR(INDEX('DRAFT 1'!$AC:$AC,MATCH($B4,'DRAFT 1'!$B:$B,0)),"") | AI4: =IFERROR(INDEX('DRAFT 1'!$AD:$AD,MATCH($B4,'DRAFT 1'!$B:$B,0)),"") | AJ4: =IFERROR(INDEX('DRAFT 1'!$AE:$AE,MATCH($B4,'DRAFT 1'!$B:$B,0)),"") | AK4: =IFERROR(INDEX('DRAFT 1'!$AG:$AG,MATCH($B4,'DRAFT 1'!$B:$B,0)),"") | AL4: =IFERROR(INDEX('DRAFT 1'!$AH:$AH,MATCH($B4,'DRAFT 1'!$B:$B,0)),"") | AM4: =IFERROR(INDEX('DRAFT 1'!$AI:$AI,MATCH($B4,'DRAFT 1'!$B:$B,0)),"") | AN4: =IFERROR(INDEX('DRAFT 1'!$AJ:$AJ,MATCH($B4,'DRAFT 1'!$B:$B,0)),"") | AO4: =IFERROR(Y4/AN4,0) -> 0 | AP4: =IFERROR(INDEX('DRAFT 1'!$AK:$AK,MATCH($B4,'DRAFT 1'!$B:$B,0)),"") | AR4: RECOMPRA | AS4: =IFERROR(LOOKUP(2,1/('DRAFT 2'!$D:$D=$B4),'DRAFT 2'!$T:$T),"") | AT4: =IFERROR(LOOKUP(2,1/('DRAFT 2'!$D:$D=$B4),'DRAFT 2'!$A:$A),"") | AU4: =IFERROR(LOOKUP(2,1/('DRAFT 2'!$D:$D=$B4),'DRAFT 2'!$R:$R),"") | AV4: =IFERROR(LOOKUP(2,1/('DRAFT 2'!$D:$D=$B4),'DRAFT 2'!$S:$S),"") | AW4: PROSPECT | AX4: =IFERROR(LOOKUP(2,1/('DRAFT 2'!$D:$D=$B4),'DRAFT 2'!$M:$M),"") | AY4: =IFERROR(LOOKUP(2,1/('DRAFT 2'!$D:$D=$B4),'DRAFT 2'!$K:$K),"") | BA4: =IF(N4="PROSPECT","❄️ FRIO",IF(OR(AR4="ORÇAMENTO",AR4="NEGOCIAÇÃO",AR4="CADASTRO"),"🔥 QUENTE",IF(OR(AR4="FOLLOW UP 7",AR4="FOLLOW UP 15",AR4="ATENDIMENTO"),"⚡ MORNO","❄️ FRIO"))) -> ❄️ FRIO | BB4: =IF(BE4="","",BE4-BC4) | BG4: =IFERROR(LOOKUP(2,1/('DRAFT 2'!$D:$D=$B4),'DRAFT 2'!$U:$U),"") | BH4: =IFERROR(LOOKUP(2,1/('DRAFT 2'!$D:$D=$B4),'DRAFT 2'!$V:$V),"") | BI4: =IF(Q4="","🟣",IF(P4<=IF(AK4="",45,AK4),"🟢",IF(P4<=IF(AK4="",45,AK4)+30,"🟡","🔴"))) -> 🟣 | BJ4: SAP001 | BU4: =CR4 -> 1 | BV4: =AVERAGE(CC4,CR4,DG4) -> 1 | BW4: =IF(BX4=0,1,BY4/BX4) -> 1 | BZ4: =IF(CA4=0,1,CB4/CA4) -> 1 | CC4: =IF(CD4=0,1,CE4/CD4) -> 1 | CE4: =IFERROR(AJ4,0) | CF4: =IFERROR(LOOKUP(2,1/('DRAFT 2'!$D:$D=$B4)*('DRAFT 2'!$A:$A>=DATE(2026,1,1))*('DRAFT 2'!$A:$A<DATE(2026,IF(1=12,1+1,1+1),1)),'DRAFT 2'!$A:$A),"") | CG4: =COUNTIFS('DRAFT 2'!$D:$D,$B4,'DRAFT 2'!$A:$A,">="&DATE(2026,1,1),'DRAFT 2'!$A:$A,"<="&DATE(2026,1,7)) -> 0 | CH4: =COUNTIFS('DRAFT 2'!$D:$D,$B4,'DRAFT 2'!$A:$A,">="&DATE(2026,1,8),'DRAFT 2'!$A:$A,"<="&DATE(2026,1,14)) -> 0 | CI4: =COUNTIFS('DRAFT 2'!$D:$D,$B4,'DRAFT 2'!$A:$A,">="&DATE(2026,1,15),'DRAFT 2'!$A:$A,"<="&DATE(2026,1,21)) -> 0 | CJ4: =COUNTIFS('DRAFT 2'!$D:$D,$B4,'DRAFT 2'!$A:$A,">="&DATE(2026,1,22),'DRAFT 2'!$A:$A,"<"&DATE(2026,IF(1=12,1+1,1+1),1)) -> 0 | CK4: =SUM(CG4:CJ4) -> 0 | CL4: =IF(CM4=0,1,CN4/CM4) -> 1 | CO4: =IF(CP4=0,1,CQ4/CP4) -> 1 | CR4: =IF(CS4=0,1,CT4/CS4) -> 1 | CT4: 0 | CU4: =IFERROR(LOOKUP(2,1/('DRAFT 2'!$D:$D=$B4)*('DRAFT 2'!$A:$A>=DATE(2026,2,1))*('DRAFT 2'!$A:$A<DATE(2026,IF(2=12,2+1,2+1),1)),'DRAFT 2'!$A:$A),"") | CV4: =COUNTIFS('DRAFT 2'!$D:$D,$B4,'DRAFT 2'!$A:$A,">="&DATE(2026,2,1),'DRAFT 2'!$A:$A,"<="&DATE(2026,2,7)) -> 0 | CW4: =COUNTIFS('DRAFT 2'!$D:$D,$B4,'DRAFT 2'!$A:$A,">="&DATE(2026,2,8),'DRAFT 2'!$A:$A,"<="&DATE(2026,2,14)) -> 0 | CX4: =COUNTIFS('DRAFT 2'!$D:$D,$B4,'DRAFT 2'!$A:$A,">="&DATE(2026,2,15),'DRAFT 2'!$A:$A,"<="&DATE(2026,2,21)) -> 0 | CY4: =COUNTIFS('DRAFT 2'!$D:$D,$B4,'DRAFT 2'!$A:$A,">="&DATE(2026,2,22),'DRAFT 2'!$A:$A,"<"&DATE(2026,IF(2=12,2+1,2+1),1)) -> 0 | CZ4: =SUM(CV4:CY4) -> 0 | DA4: =IF(DB4=0,1,DC4/DB4) -> 1 | DD4: =IF(DE4=0,1,DF4/DE4) -> 1 | DG4: =IF(DH4=0,1,DI4/DH4) -> 1 | DJ4: =IFERROR(LOOKUP(2,1/('DRAFT 2'!$D:$D=$B4)*('DRAFT 2'!$A:$A>=DATE(2026,3,1))*('DRAFT 2'!$A:$A<DATE(2026,IF(3=12,3+1,3+1),1)),'DRAFT 2'!$A:$A),"") | DK4: =COUNTIFS('DRAFT 2'!$D:$D,$B4,'DRAFT 2'!$A:$A,">="&DATE(2026,3,1),'DRAFT 2'!$A:$A,"<="&DATE(2026,3,7)) -> 0 | DL4: =COUNTIFS('DRAFT 2'!$D:$D,$B4,'DRAFT 2'!$A:$A,">="&DATE(2026,3,8),'DRAFT 2'!$A:$A,"<="&DATE(2026,3,14)) -> 0 | DM4: =COUNTIFS('DRAFT 2'!$D:$D,$B4,'DRAFT 2'!$A:$A,">="&DATE(2026,3,15),'DRAFT 2'!$A:$A,"<="&DATE(2026,3,21)) -> 0 | DN4: =COUNTIFS('DRAFT 2'!$D:$D,$B4,'DRAFT 2'!$A:$A,">="&DATE(2026,3,22),'DRAFT 2'!$A:$A,"<"&DATE(2026,IF(3=12,3+1,3+1),1)) -> 0 | DO4: =SUM(DK4:DN4) -> 0 | DP4: =AVERAGE(DW4,EL4,FA4) -> 1 | DQ4: =IF(DR4=0,1,DS4/DR4) -> 1 | DT4: =IF(DU4=0,1,DV4/DU4) -> 1 | DW4: =IF(DX4=0,1,DY4/DX4) -> 1 | DZ4: =IFERROR(LOOKUP(2,1/('DRAFT 2'!$D:$D=$B4)*('DRAFT 2'!$A:$A>=DATE(2026,4,1))*('DRAFT 2'!$A:$A<DATE(2026,IF(4=12,4+1,4+1),1)),'DRAFT 2'!$A:$A),"") | EA4: =COUNTIFS('DRAFT 2'!$D:$D,$B4,'DRAFT 2'!$A:$A,">="&DATE(2026,4,1),'DRAFT 2'!$A:$A,"<="&DATE(2026,4,7)) -> 0 | EB4: =COUNTIFS('DRAFT 2'!$D:$D,$B4,'DRAFT 2'!$A:$A,">="&DATE(2026,4,8),'DRAFT 2'!$A:$A,"<="&DATE(2026,4,14)) -> 0 | EC4: =COUNTIFS('DRAFT 2'!$D:$D,$B4,'DRAFT 2'!$A:$A,">="&DATE(2026,4,15),'DRAFT 2'!$A:$A,"<="&DATE(2026,4,21)) -> 0 | ED4: =COUNTIFS('DRAFT 2'!$D:$D,$B4,'DRAFT 2'!$A:$A,">="&DATE(2026,4,22),'DRAFT 2'!$A:$A,"<"&DATE(2026,IF(4=12,4+1,4+1),1)) -> 0 | EE4: =SUM(EA4:ED4) -> 0 | EF4: =IF(EG4=0,1,EH4/EG4) -> 1 | EI4: =IF(EJ4=0,1,EK4/EJ4) -> 1 | EL4: =IF(EM4=0,1,EN4/EM4) -> 1 | EO4: =IFERROR(LOOKUP(2,1/('DRAFT 2'!$D:$D=$B4)*('DRAFT 2'!$A:$A>=DATE(2026,5,1))*('DRAFT 2'!$A:$A<DATE(2026,IF(5=12,5+1,5+1),1)),'DRAFT 2'!$A:$A),"") | EP4: =COUNTIFS('DRAFT 2'!$D:$D,$B4,'DRAFT 2'!$A:$A,">="&DATE(2026,5,1),'DRAFT 2'!$A:$A,"<="&DATE(2026,5,7)) -> 0 | EQ4: =COUNTIFS('DRAFT 2'!$D:$D,$B4,'DRAFT 2'!$A:$A,">="&DATE(2026,5,8),'DRAFT 2'!$A:$A,"<="&DATE(2026,5,14)) -> 0 | ER4: =COUNTIFS('DRAFT 2'!$D:$D,$B4,'DRAFT 2'!$A:$A,">="&DATE(2026,5,15),'DRAFT 2'!$A:$A,"<="&DATE(2026,5,21)) -> 0 | ES4: =COUNTIFS('DRAFT 2'!$D:$D,$B4,'DRAFT 2'!$A:$A,">="&DATE(2026,5,22),'DRAFT 2'!$A:$A,"<"&DATE(2026,IF(5=12,5+1,5+1),1)) -> 0 | ET4: =SUM(EP4:ES4) -> 0 | EU4: =IF(EV4=0,1,EW4/EV4) -> 1 | EX4: =IF(EY4=0,1,EZ4/EY4) -> 1 | FA4: =IF(FB4=0,1,FC4/FB4) -> 1 | FD4: =IFERROR(LOOKUP(2,1/('DRAFT 2'!$D:$D=$B4)*('DRAFT 2'!$A:$A>=DATE(2026,6,1))*('DRAFT 2'!$A:$A<DATE(2026,IF(6=12,6+1,6+1),1)),'DRAFT 2'!$A:$A),"") | FE4: =COUNTIFS('DRAFT 2'!$D:$D,$B4,'DRAFT 2'!$A:$A,">="&DATE(2026,6,1),'DRAFT 2'!$A:$A,"<="&DATE(2026,6,7)) -> 0 | FF4: =COUNTIFS('DRAFT 2'!$D:$D,$B4,'DRAFT 2'!$A:$A,">="&DATE(2026,6,8),'DRAFT 2'!$A:$A,"<="&DATE(2026,6,14)) -> 0 | FG4: =COUNTIFS('DRAFT 2'!$D:$D,$B4,'DRAFT 2'!$A:$A,">="&DATE(2026,6,15),'DRAFT 2'!$A:$A,"<="&DATE(2026,6,21)) -> 0 | FH4: =COUNTIFS('DRAFT 2'!$D:$D,$B4,'DRAFT 2'!$A:$A,">="&DATE(2026,6,22),'DRAFT 2'!$A:$A,"<"&DATE(2026,IF(6=12,6+1,6+1),1)) -> 0 | FI4: =SUM(FE4:FH4) -> 0 | FJ4: =AVERAGE(FQ4,GF4,GU4) -> 1 | FK4: =IF(FL4=0,1,FM4/FL4) -> 1 | FN4: =IF(FO4=0,1,FP4/FO4) -> 1 | FQ4: =IF(FR4=0,1,FS4/FR4) -> 1 | FT4: =IFERROR(LOOKUP(2,1/('DRAFT 2'!$D:$D=$B4)*('DRAFT 2'!$A:$A>=DATE(2026,7,1))*('DRAFT 2'!$A:$A<DATE(2026,IF(7=12,7+1,7+1),1)),'DRAFT 2'!$A:$A),"") | FU4: =COUNTIFS('DRAFT 2'!$D:$D,$B4,'DRAFT 2'!$A:$A,">="&DATE(2026,7,1),'DRAFT 2'!$A:$A,"<="&DATE(2026,7,7)) -> 0 | FV4: =COUNTIFS('DRAFT 2'!$D:$D,$B4,'DRAFT 2'!$A:$A,">="&DATE(2026,7,8),'DRAFT 2'!$A:$A,"<="&DATE(2026,7,14)) -> 0 | FW4: =COUNTIFS('DRAFT 2'!$D:$D,$B4,'DRAFT 2'!$A:$A,">="&DATE(2026,7,15),'DRAFT 2'!$A:$A,"<="&DATE(2026,7,21)) -> 0 | FX4: =COUNTIFS('DRAFT 2'!$D:$D,$B4,'DRAFT 2'!$A:$A,">="&DATE(2026,7,22),'DRAFT 2'!$A:$A,"<"&DATE(2026,IF(7=12,7+1,7+1),1)) -> 0 | FY4: =SUM(FU4:FX4) -> 0 | FZ4: =IF(GA4=0,1,GB4/GA4) -> 1 | GC4: =IF(GD4=0,1,GE4/GD4) -> 1 | GF4: =IF(GG4=0,1,GH4/GG4) -> 1 | GI4: =IFERROR(LOOKUP(2,1/('DRAFT 2'!$D:$D=$B4)*('DRAFT 2'!$A:$A>=DATE(2026,8,1))*('DRAFT 2'!$A:$A<DATE(2026,IF(8=12,8+1,8+1),1)),'DRAFT 2'!$A:$A),"") | GJ4: =COUNTIFS('DRAFT 2'!$D:$D,$B4,'DRAFT 2'!$A:$A,">="&DATE(2026,8,1),'DRAFT 2'!$A:$A,"<="&DATE(2026,8,7)) -> 0 | GK4: =COUNTIFS('DRAFT 2'!$D:$D,$B4,'DRAFT 2'!$A:$A,">="&DATE(2026,8,8),'DRAFT 2'!$A:$A,"<="&DATE(2026,8,14)) -> 0 | GL4: =COUNTIFS('DRAFT 2'!$D:$D,$B4,'DRAFT 2'!$A:$A,">="&DATE(2026,8,15),'DRAFT 2'!$A:$A,"<="&DATE(2026,8,21)) -> 0 | GM4: =COUNTIFS('DRAFT 2'!$D:$D,$B4,'DRAFT 2'!$A:$A,">="&DATE(2026,8,22),'DRAFT 2'!$A:$A,"<"&DATE(2026,IF(8=12,8+1,8+1),1)) -> 0 | GN4: =SUM(GJ4:GM4) -> 0 | GO4: =IF(GP4=0,1,GQ4/GP4) -> 1 | GR4: =IF(GS4=0,1,GT4/GS4) -> 1 | GU4: =IF(GV4=0,1,GW4/GV4) -> 1 | GX4: =IFERROR(LOOKUP(2,1/('DRAFT 2'!$D:$D=$B4)*('DRAFT 2'!$A:$A>=DATE(2026,9,1))*('DRAFT 2'!$A:$A<DATE(2026,IF(9=12,9+1,9+1),1)),'DRAFT 2'!$A:$A),"") | GY4: =COUNTIFS('DRAFT 2'!$D:$D,$B4,'DRAFT 2'!$A:$A,">="&DATE(2026,9,1),'DRAFT 2'!$A:$A,"<="&DATE(2026,9,7)) -> 0 | GZ4: =COUNTIFS('DRAFT 2'!$D:$D,$B4,'DRAFT 2'!$A:$A,">="&DATE(2026,9,8),'DRAFT 2'!$A:$A,"<="&DATE(2026,9,14)) -> 0 | HA4: =COUNTIFS('DRAFT 2'!$D:$D,$B4,'DRAFT 2'!$A:$A,">="&DATE(2026,9,15),'DRAFT 2'!$A:$A,"<="&DATE(2026,9,21)) -> 0 | HB4: =COUNTIFS('DRAFT 2'!$D:$D,$B4,'DRAFT 2'!$A:$A,">="&DATE(2026,9,22),'DRAFT 2'!$A:$A,"<"&DATE(2026,IF(9=12,9+1,9+1),1)) -> 0 | HC4: =SUM(GY4:HB4) -> 0 | HD4: =AVERAGE(HK4,HZ4,IO4) -> 1 | HE4: =IF(HF4=0,1,HG4/HF4) -> 1 | HH4: =IF(HI4=0,1,HJ4/HI4) -> 1 | HK4: =IF(HL4=0,1,HM4/HL4) -> 1 | HN4: =IFERROR(LOOKUP(2,1/('DRAFT 2'!$D:$D=$B4)*('DRAFT 2'!$A:$A>=DATE(2026,10,1))*('DRAFT 2'!$A:$A<DATE(2026,IF(10=12,10+1,10+1),1)),'DRAFT 2'!$A:$A),"") | HO4: =COUNTIFS('DRAFT 2'!$D:$D,$B4,'DRAFT 2'!$A:$A,">="&DATE(2026,10,1),'DRAFT 2'!$A:$A,"<="&DATE(2026,10,7)) -> 0 | HP4: =COUNTIFS('DRAFT 2'!$D:$D,$B4,'DRAFT 2'!$A:$A,">="&DATE(2026,10,8),'DRAFT 2'!$A:$A,"<="&DATE(2026,10,14)) -> 0 | HQ4: =COUNTIFS('DRAFT 2'!$D:$D,$B4,'DRAFT 2'!$A:$A,">="&DATE(2026,10,15),'DRAFT 2'!$A:$A,"<="&DATE(2026,10,21)) -> 0 | HR4: =COUNTIFS('DRAFT 2'!$D:$D,$B4,'DRAFT 2'!$A:$A,">="&DATE(2026,10,22),'DRAFT 2'!$A:$A,"<"&DATE(2026,IF(10=12,10+1,10+1),1)) -> 0 | HS4: =SUM(HO4:HR4) -> 0 | HT4: =IF(HU4=0,1,HV4/HU4) -> 1 | HW4: =IF(HX4=0,1,HY4/HX4) -> 1 | HZ4: =IF(IA4=0,1,IB4/IA4) -> 1 | IC4: =IFERROR(LOOKUP(2,1/('DRAFT 2'!$D:$D=$B4)*('DRAFT 2'!$A:$A>=DATE(2026,11,1))*('DRAFT 2'!$A:$A<DATE(2026,IF(11=12,11+1,11+1),1)),'DRAFT 2'!$A:$A),"") | ID4: =COUNTIFS('DRAFT 2'!$D:$D,$B4,'DRAFT 2'!$A:$A,">="&DATE(2026,11,1),'DRAFT 2'!$A:$A,"<="&DATE(2026,11,7)) -> 0 | IE4: =COUNTIFS('DRAFT 2'!$D:$D,$B4,'DRAFT 2'!$A:$A,">="&DATE(2026,11,8),'DRAFT 2'!$A:$A,"<="&DATE(2026,11,14)) -> 0 | IF4: =COUNTIFS('DRAFT 2'!$D:$D,$B4,'DRAFT 2'!$A:$A,">="&DATE(2026,11,15),'DRAFT 2'!$A:$A,"<="&DATE(2026,11,21)) -> 0 | IG4: =COUNTIFS('DRAFT 2'!$D:$D,$B4,'DRAFT 2'!$A:$A,">="&DATE(2026,11,22),'DRAFT 2'!$A:$A,"<"&DATE(2026,IF(11=12,11+1,11+1),1)) -> 0 | IH4: =SUM(ID4:IG4) -> 0 | II4: =IF(IJ4=0,1,IK4/IJ4) -> 1 | IL4: =IF(IM4=0,1,IN4/IM4) -> 1 | IO4: =IF(IP4=0,1,IQ4/IP4) -> 1 | IR4: =IFERROR(LOOKUP(2,1/('DRAFT 2'!$D:$D=$B4)*('DRAFT 2'!$A:$A>=DATE(2026,12,1))*('DRAFT 2'!$A:$A<DATE(2026,IF(12=12,12+1,12+1),1)),'DRAFT 2'!$A:$A),"") | IS4: =COUNTIFS('DRAFT 2'!$D:$D,$B4,'DRAFT 2'!$A:$A,">="&DATE(2026,12,1),'DRAFT 2'!$A:$A,"<="&DATE(2026,12,7)) -> 0 | IT4: =COUNTIFS('DRAFT 2'!$D:$D,$B4,'DRAFT 2'!$A:$A,">="&DATE(2026,12,8),'DRAFT 2'!$A:$A,"<="&DATE(2026,12,14)) -> 0 | IU4: =COUNTIFS('DRAFT 2'!$D:$D,$B4,'DRAFT 2'!$A:$A,">="&DATE(2026,12,15),'DRAFT 2'!$A:$A,"<="&DATE(2026,12,21)) -> 0 | IV4: =COUNTIFS('DRAFT 2'!$D:$D,$B4,'DRAFT 2'!$A:$A,">="&DATE(2026,12,22),'DRAFT 2'!$A:$A,"<"&DATE(2026,IF(12=12,12+1,12+1),1)) -> 0 | IW4: =SUM(IS4:IV4) -> 0
A5: =IFERROR(INDEX('DRAFT 1'!$A:$A,MATCH($B5,'DRAFT 1'!$B:$B,0)),"") | B5: 41626544000140 | C5: =IFERROR(INDEX('DRAFT 1'!$C:$C,MATCH($B5,'DRAFT 1'!$B:$B,0)),"") | D5: =IFERROR(INDEX('DRAFT 1'!$D:$D,MATCH($B5,'DRAFT 1'!$B:$B,0)),"") | E5: =IFERROR(INDEX('DRAFT 1'!$E:$E,MATCH($B5,'DRAFT 1'!$B:$B,0)),"") | F5: =IFERROR(INDEX('DRAFT 1'!$F:$F,MATCH($B5,'DRAFT 1'!$B:$B,0)),"") | G5: =IFERROR(INDEX('DRAFT 1'!$G:$G,MATCH($B5,'DRAFT 1'!$B:$B,0)),"") | H5: =IFERROR(INDEX('DRAFT 1'!$H:$H,MATCH($B5,'DRAFT 1'!$B:$B,0)),"") | I5: FIT LAND | K5: =IFERROR(INDEX('DRAFT 1'!$AL:$AL,MATCH($B5,'DRAFT 1'!$B:$B,0)),"") | L5: =IFERROR(INDEX('DRAFT 1'!$J:$J,MATCH($B5,'DRAFT 1'!$B:$B,0)),"") | M5: =IFERROR(INDEX('DRAFT 1'!$K:$K,MATCH($B5,'DRAFT 1'!$B:$B,0)),"") | N5: EM RISCO | O5: =IF(N5="EM RISCO",1,IF(N5="INAT.REC",2,IF(N5="ATIVO",3,IF(N5="INAT.ANT",4,5)))) -> 1 | P5: =IFERROR(INDEX('DRAFT 1'!$L:$L,MATCH($B5,'DRAFT 1'!$B:$B,0)),"") | Q5: =IFERROR(INDEX('DRAFT 1'!$M:$M,MATCH($B5,'DRAFT 1'!$B:$B,0)),"") | R5: =IFERROR(INDEX('DRAFT 1'!$N:$N,MATCH($B5,'DRAFT 1'!$B:$B,0)),"") | S5: =IFERROR(INDEX('DRAFT 1'!$O:$O,MATCH($B5,'DRAFT 1'!$B:$B,0)),"") | T5: =IFERROR(INDEX('DRAFT 1'!$P:$P,MATCH($B5,'DRAFT 1'!$B:$B,0)),"") | U5: =IFERROR(INDEX('DRAFT 1'!$Q:$Q,MATCH($B5,'DRAFT 1'!$B:$B,0)),"") | V5: =IFERROR(INDEX('DRAFT 1'!$R:$R,MATCH($B5,'DRAFT 1'!$B:$B,0)),"") | W5: =IFERROR(INDEX('DRAFT 1'!$S:$S,MATCH($B5,'DRAFT 1'!$B:$B,0)),"") | X5: =IFERROR(INDEX('DRAFT 1'!$T:$T,MATCH($B5,'DRAFT 1'!$B:$B,0)),"") | Y5: =SUM(Z5:AJ5) -> 0 | Z5: =IFERROR(INDEX('DRAFT 1'!$U:$U,MATCH($B5,'DRAFT 1'!$B:$B,0)),"") | AA5: =IFERROR(INDEX('DRAFT 1'!$V:$V,MATCH($B5,'DRAFT 1'!$B:$B,0)),"") | AB5: =IFERROR(INDEX('DRAFT 1'!$W:$W,MATCH($B5,'DRAFT 1'!$B:$B,0)),"") | AC5: =IFERROR(INDEX('DRAFT 1'!$X:$X,MATCH($B5,'DRAFT 1'!$B:$B,0)),"") | AD5: =IFERROR(INDEX('DRAFT 1'!$Y:$Y,MATCH($B5,'DRAFT 1'!$B:$B,0)),"") | AE5: =IFERROR(INDEX('DRAFT 1'!$Z:$Z,MATCH($B5,'DRAFT 1'!$B:$B,0)),"") | AF5: =IFERROR(INDEX('DRAFT 1'!$AA:$AA,MATCH($B5,'DRAFT 1'!$B:$B,0)),"") | AG5: =IFERROR(INDEX('DRAFT 1'!$AB:$AB,MATCH($B5,'DRAFT 1'!$B:$B,0)),"") | AH5: =IFERROR(INDEX('DRAFT 1'!$AC:$AC,MATCH($B5,'DRAFT 1'!$B:$B,0)),"") | AI5: =IFERROR(INDEX('DRAFT 1'!$AD:$AD,MATCH($B5,'DRAFT 1'!$B:$B,0)),"") | AJ5: =IFERROR(INDEX('DRAFT 1'!$AE:$AE,MATCH($B5,'DRAFT 1'!$B:$B,0)),"") | AK5: =IFERROR(INDEX('DRAFT 1'!$AG:$AG,MATCH($B5,'DRAFT 1'!$B:$B,0)),"") | AL5: =IFERROR(INDEX('DRAFT 1'!$AH:$AH,MATCH($B5,'DRAFT 1'!$B:$B,0)),"") | AM5: =IFERROR(INDEX('DRAFT 1'!$AI:$AI,MATCH($B5,'DRAFT 1'!$B:$B,0)),"") | AN5: =IFERROR(INDEX('DRAFT 1'!$AJ:$AJ,MATCH($B5,'DRAFT 1'!$B:$B,0)),"") | AO5: =IFERROR(Y5/AN5,0) -> 0 | AP5: =IFERROR(INDEX('DRAFT 1'!$AK:$AK,MATCH($B5,'DRAFT 1'!$B:$B,0)),"") | AR5: PÓS-VENDA | AS5: =IFERROR(LOOKUP(2,1/('DRAFT 2'!$D:$D=$B5),'DRAFT 2'!$T:$T),"") | AT5: =IFERROR(LOOKUP(2,1/('DRAFT 2'!$D:$D=$B5),'DRAFT 2'!$A:$A),"") | AU5: =IFERROR(LOOKUP(2,1/('DRAFT 2'!$D:$D=$B5),'DRAFT 2'!$R:$R),"") | AV5: =IFERROR(LOOKUP(2,1/('DRAFT 2'!$D:$D=$B5),'DRAFT 2'!$S:$S),"") | AW5: LEAD | AX5: =IFERROR(LOOKUP(2,1/('DRAFT 2'!$D:$D=$B5),'DRAFT 2'!$M:$M),"") | AY5: =IFERROR(LOOKUP(2,1/('DRAFT 2'!$D:$D=$B5),'DRAFT 2'!$K:$K),"") | BA5: =IF(N5="PROSPECT","❄️ FRIO",IF(OR(AR5="ORÇAMENTO",AR5="NEGOCIAÇÃO",AR5="CADASTRO"),"🔥 QUENTE",IF(OR(AR5="FOLLOW UP 7",AR5="FOLLOW UP 15",AR5="ATENDIMENTO"),"⚡ MORNO","❄️ FRIO"))) -> ❄️ FRIO | BB5: =IF(BE5="","",BE5-BC5) | BG5: =IFERROR(LOOKUP(2,1/('DRAFT 2'!$D:$D=$B5),'DRAFT 2'!$U:$U),"") | BH5: =IFERROR(LOOKUP(2,1/('DRAFT 2'!$D:$D=$B5),'DRAFT 2'!$V:$V),"") | BI5: =IF(Q5="","🟣",IF(P5<=IF(AK5="",45,AK5),"🟢",IF(P5<=IF(AK5="",45,AK5)+30,"🟡","🔴"))) -> 🟣 | BJ5: SAP002 | BU5: =CR5 -> 1 | BV5: =AVERAGE(CC5,CR5,DG5) -> 1 | BW5: =IF(BX5=0,1,BY5/BX5) -> 1 | BZ5: =IF(CA5=0,1,CB5/CA5) -> 1 | CC5: =IF(CD5=0,1,CE5/CD5) -> 1 | CE5: =IFERROR(AJ5,0) | CF5: =IFERROR(LOOKUP(2,1/('DRAFT 2'!$D:$D=$B5)*('DRAFT 2'!$A:$A>=DATE(2026,1,1))*('DRAFT 2'!$A:$A<DATE(2026,IF(1=12,1+1,1+1),1)),'DRAFT 2'!$A:$A),"") | CG5: =COUNTIFS('DRAFT 2'!$D:$D,$B5,'DRAFT 2'!$A:$A,">="&DATE(2026,1,1),'DRAFT 2'!$A:$A,"<="&DATE(2026,1,7)) -> 0 | CH5: =COUNTIFS('DRAFT 2'!$D:$D,$B5,'DRAFT 2'!$A:$A,">="&DATE(2026,1,8),'DRAFT 2'!$A:$A,"<="&DATE(2026,1,14)) -> 0 | CI5: =COUNTIFS('DRAFT 2'!$D:$D,$B5,'DRAFT 2'!$A:$A,">="&DATE(2026,1,15),'DRAFT 2'!$A:$A,"<="&DATE(2026,1,21)) -> 0 | CJ5: =COUNTIFS('DRAFT 2'!$D:$D,$B5,'DRAFT 2'!$A:$A,">="&DATE(2026,1,22),'DRAFT 2'!$A:$A,"<"&DATE(2026,IF(1=12,1+1,1+1),1)) -> 0 | CK5: =SUM(CG5:CJ5) -> 0 | CL5: =IF(CM5=0,1,CN5/CM5) -> 1 | CO5: =IF(CP5=0,1,CQ5/CP5) -> 1 | CR5: =IF(CS5=0,1,CT5/CS5) -> 1 | CT5: 0 | CU5: =IFERROR(LOOKUP(2,1/('DRAFT 2'!$D:$D=$B5)*('DRAFT 2'!$A:$A>=DATE(2026,2,1))*('DRAFT 2'!$A:$A<DATE(2026,IF(2=12,2+1,2+1),1)),'DRAFT 2'!$A:$A),"") | CV5: =COUNTIFS('DRAFT 2'!$D:$D,$B5,'DRAFT 2'!$A:$A,">="&DATE(2026,2,1),'DRAFT 2'!$A:$A,"<="&DATE(2026,2,7)) -> 0 | CW5: =COUNTIFS('DRAFT 2'!$D:$D,$B5,'DRAFT 2'!$A:$A,">="&DATE(2026,2,8),'DRAFT 2'!$A:$A,"<="&DATE(2026,2,14)) -> 0 | CX5: =COUNTIFS('DRAFT 2'!$D:$D,$B5,'DRAFT 2'!$A:$A,">="&DATE(2026,2,15),'DRAFT 2'!$A:$A,"<="&DATE(2026,2,21)) -> 0 | CY5: =COUNTIFS('DRAFT 2'!$D:$D,$B5,'DRAFT 2'!$A:$A,">="&DATE(2026,2,22),'DRAFT 2'!$A:$A,"<"&DATE(2026,IF(2=12,2+1,2+1),1)) -> 0 | CZ5: =SUM(CV5:CY5) -> 0 | DA5: =IF(DB5=0,1,DC5/DB5) -> 1 | DD5: =IF(DE5=0,1,DF5/DE5) -> 1 | DG5: =IF(DH5=0,1,DI5/DH5) -> 1 | DJ5: =IFERROR(LOOKUP(2,1/('DRAFT 2'!$D:$D=$B5)*('DRAFT 2'!$A:$A>=DATE(2026,3,1))*('DRAFT 2'!$A:$A<DATE(2026,IF(3=12,3+1,3+1),1)),'DRAFT 2'!$A:$A),"") | DK5: =COUNTIFS('DRAFT 2'!$D:$D,$B5,'DRAFT 2'!$A:$A,">="&DATE(2026,3,1),'DRAFT 2'!$A:$A,"<="&DATE(2026,3,7)) -> 0 | DL5: =COUNTIFS('DRAFT 2'!$D:$D,$B5,'DRAFT 2'!$A:$A,">="&DATE(2026,3,8),'DRAFT 2'!$A:$A,"<="&DATE(2026,3,14)) -> 0 | DM5: =COUNTIFS('DRAFT 2'!$D:$D,$B5,'DRAFT 2'!$A:$A,">="&DATE(2026,3,15),'DRAFT 2'!$A:$A,"<="&DATE(2026,3,21)) -> 0 | DN5: =COUNTIFS('DRAFT 2'!$D:$D,$B5,'DRAFT 2'!$A:$A,">="&DATE(2026,3,22),'DRAFT 2'!$A:$A,"<"&DATE(2026,IF(3=12,3+1,3+1),1)) -> 0 | DO5: =SUM(DK5:DN5) -> 0 | DP5: =AVERAGE(DW5,EL5,FA5) -> 1 | DQ5: =IF(DR5=0,1,DS5/DR5) -> 1 | DT5: =IF(DU5=0,1,DV5/DU5) -> 1 | DW5: =IF(DX5=0,1,DY5/DX5) -> 1 | DZ5: =IFERROR(LOOKUP(2,1/('DRAFT 2'!$D:$D=$B5)*('DRAFT 2'!$A:$A>=DATE(2026,4,1))*('DRAFT 2'!$A:$A<DATE(2026,IF(4=12,4+1,4+1),1)),'DRAFT 2'!$A:$A),"") | EA5: =COUNTIFS('DRAFT 2'!$D:$D,$B5,'DRAFT 2'!$A:$A,">="&DATE(2026,4,1),'DRAFT 2'!$A:$A,"<="&DATE(2026,4,7)) -> 0 | EB5: =COUNTIFS('DRAFT 2'!$D:$D,$B5,'DRAFT 2'!$A:$A,">="&DATE(2026,4,8),'DRAFT 2'!$A:$A,"<="&DATE(2026,4,14)) -> 0 | EC5: =COUNTIFS('DRAFT 2'!$D:$D,$B5,'DRAFT 2'!$A:$A,">="&DATE(2026,4,15),'DRAFT 2'!$A:$A,"<="&DATE(2026,4,21)) -> 0 | ED5: =COUNTIFS('DRAFT 2'!$D:$D,$B5,'DRAFT 2'!$A:$A,">="&DATE(2026,4,22),'DRAFT 2'!$A:$A,"<"&DATE(2026,IF(4=12,4+1,4+1),1)) -> 0 | EE5: =SUM(EA5:ED5) -> 0 | EF5: =IF(EG5=0,1,EH5/EG5) -> 1 | EI5: =IF(EJ5=0,1,EK5/EJ5) -> 1 | EL5: =IF(EM5=0,1,EN5/EM5) -> 1 | EO5: =IFERROR(LOOKUP(2,1/('DRAFT 2'!$D:$D=$B5)*('DRAFT 2'!$A:$A>=DATE(2026,5,1))*('DRAFT 2'!$A:$A<DATE(2026,IF(5=12,5+1,5+1),1)),'DRAFT 2'!$A:$A),"") | EP5: =COUNTIFS('DRAFT 2'!$D:$D,$B5,'DRAFT 2'!$A:$A,">="&DATE(2026,5,1),'DRAFT 2'!$A:$A,"<="&DATE(2026,5,7)) -> 0 | EQ5: =COUNTIFS('DRAFT 2'!$D:$D,$B5,'DRAFT 2'!$A:$A,">="&DATE(2026,5,8),'DRAFT 2'!$A:$A,"<="&DATE(2026,5,14)) -> 0 | ER5: =COUNTIFS('DRAFT 2'!$D:$D,$B5,'DRAFT 2'!$A:$A,">="&DATE(2026,5,15),'DRAFT 2'!$A:$A,"<="&DATE(2026,5,21)) -> 0 | ES5: =COUNTIFS('DRAFT 2'!$D:$D,$B5,'DRAFT 2'!$A:$A,">="&DATE(2026,5,22),'DRAFT 2'!$A:$A,"<"&DATE(2026,IF(5=12,5+1,5+1),1)) -> 0 | ET5: =SUM(EP5:ES5) -> 0 | EU5: =IF(EV5=0,1,EW5/EV5) -> 1 | EX5: =IF(EY5=0,1,EZ5/EY5) -> 1 | FA5: =IF(FB5=0,1,FC5/FB5) -> 1 | FD5: =IFERROR(LOOKUP(2,1/('DRAFT 2'!$D:$D=$B5)*('DRAFT 2'!$A:$A>=DATE(2026,6,1))*('DRAFT 2'!$A:$A<DATE(2026,IF(6=12,6+1,6+1),1)),'DRAFT 2'!$A:$A),"") | FE5: =COUNTIFS('DRAFT 2'!$D:$D,$B5,'DRAFT 2'!$A:$A,">="&DATE(2026,6,1),'DRAFT 2'!$A:$A,"<="&DATE(2026,6,7)) -> 0 | FF5: =COUNTIFS('DRAFT 2'!$D:$D,$B5,'DRAFT 2'!$A:$A,">="&DATE(2026,6,8),'DRAFT 2'!$A:$A,"<="&DATE(2026,6,14)) -> 0 | FG5: =COUNTIFS('DRAFT 2'!$D:$D,$B5,'DRAFT 2'!$A:$A,">="&DATE(2026,6,15),'DRAFT 2'!$A:$A,"<="&DATE(2026,6,21)) -> 0 | FH5: =COUNTIFS('DRAFT 2'!$D:$D,$B5,'DRAFT 2'!$A:$A,">="&DATE(2026,6,22),'DRAFT 2'!$A:$A,"<"&DATE(2026,IF(6=12,6+1,6+1),1)) -> 0 | FI5: =SUM(FE5:FH5) -> 0 | FJ5: =AVERAGE(FQ5,GF5,GU5) -> 1 | FK5: =IF(FL5=0,1,FM5/FL5) -> 1 | FN5: =IF(FO5=0,1,FP5/FO5) -> 1 | FQ5: =IF(FR5=0,1,FS5/FR5) -> 1 | FT5: =IFERROR(LOOKUP(2,1/('DRAFT 2'!$D:$D=$B5)*('DRAFT 2'!$A:$A>=DATE(2026,7,1))*('DRAFT 2'!$A:$A<DATE(2026,IF(7=12,7+1,7+1),1)),'DRAFT 2'!$A:$A),"") | FU5: =COUNTIFS('DRAFT 2'!$D:$D,$B5,'DRAFT 2'!$A:$A,">="&DATE(2026,7,1),'DRAFT 2'!$A:$A,"<="&DATE(2026,7,7)) -> 0 | FV5: =COUNTIFS('DRAFT 2'!$D:$D,$B5,'DRAFT 2'!$A:$A,">="&DATE(2026,7,8),'DRAFT 2'!$A:$A,"<="&DATE(2026,7,14)) -> 0 | FW5: =COUNTIFS('DRAFT 2'!$D:$D,$B5,'DRAFT 2'!$A:$A,">="&DATE(2026,7,15),'DRAFT 2'!$A:$A,"<="&DATE(2026,7,21)) -> 0 | FX5: =COUNTIFS('DRAFT 2'!$D:$D,$B5,'DRAFT 2'!$A:$A,">="&DATE(2026,7,22),'DRAFT 2'!$A:$A,"<"&DATE(2026,IF(7=12,7+1,7+1),1)) -> 0 | FY5: =SUM(FU5:FX5) -> 0 | FZ5: =IF(GA5=0,1,GB5/GA5) -> 1 | GC5: =IF(GD5=0,1,GE5/GD5) -> 1 | GF5: =IF(GG5=0,1,GH5/GG5) -> 1 | GI5: =IFERROR(LOOKUP(2,1/('DRAFT 2'!$D:$D=$B5)*('DRAFT 2'!$A:$A>=DATE(2026,8,1))*('DRAFT 2'!$A:$A<DATE(2026,IF(8=12,8+1,8+1),1)),'DRAFT 2'!$A:$A),"") | GJ5: =COUNTIFS('DRAFT 2'!$D:$D,$B5,'DRAFT 2'!$A:$A,">="&DATE(2026,8,1),'DRAFT 2'!$A:$A,"<="&DATE(2026,8,7)) -> 0 | GK5: =COUNTIFS('DRAFT 2'!$D:$D,$B5,'DRAFT 2'!$A:$A,">="&DATE(2026,8,8),'DRAFT 2'!$A:$A,"<="&DATE(2026,8,14)) -> 0 | GL5: =COUNTIFS('DRAFT 2'!$D:$D,$B5,'DRAFT 2'!$A:$A,">="&DATE(2026,8,15),'DRAFT 2'!$A:$A,"<="&DATE(2026,8,21)) -> 0 | GM5: =COUNTIFS('DRAFT 2'!$D:$D,$B5,'DRAFT 2'!$A:$A,">="&DATE(2026,8,22),'DRAFT 2'!$A:$A,"<"&DATE(2026,IF(8=12,8+1,8+1),1)) -> 0 | GN5: =SUM(GJ5:GM5) -> 0 | GO5: =IF(GP5=0,1,GQ5/GP5) -> 1 | GR5: =IF(GS5=0,1,GT5/GS5) -> 1 | GU5: =IF(GV5=0,1,GW5/GV5) -> 1 | GX5: =IFERROR(LOOKUP(2,1/('DRAFT 2'!$D:$D=$B5)*('DRAFT 2'!$A:$A>=DATE(2026,9,1))*('DRAFT 2'!$A:$A<DATE(2026,IF(9=12,9+1,9+1),1)),'DRAFT 2'!$A:$A),"") | GY5: =COUNTIFS('DRAFT 2'!$D:$D,$B5,'DRAFT 2'!$A:$A,">="&DATE(2026,9,1),'DRAFT 2'!$A:$A,"<="&DATE(2026,9,7)) -> 0 | GZ5: =COUNTIFS('DRAFT 2'!$D:$D,$B5,'DRAFT 2'!$A:$A,">="&DATE(2026,9,8),'DRAFT 2'!$A:$A,"<="&DATE(2026,9,14)) -> 0 | HA5: =COUNTIFS('DRAFT 2'!$D:$D,$B5,'DRAFT 2'!$A:$A,">="&DATE(2026,9,15),'DRAFT 2'!$A:$A,"<="&DATE(2026,9,21)) -> 0 | HB5: =COUNTIFS('DRAFT 2'!$D:$D,$B5,'DRAFT 2'!$A:$A,">="&DATE(2026,9,22),'DRAFT 2'!$A:$A,"<"&DATE(2026,IF(9=12,9+1,9+1),1)) -> 0 | HC5: =SUM(GY5:HB5) -> 0 | HD5: =AVERAGE(HK5,HZ5,IO5) -> 1 | HE5: =IF(HF5=0,1,HG5/HF5) -> 1 | HH5: =IF(HI5=0,1,HJ5/HI5) -> 1 | HK5: =IF(HL5=0,1,HM5/HL5) -> 1 | HN5: =IFERROR(LOOKUP(2,1/('DRAFT 2'!$D:$D=$B5)*('DRAFT 2'!$A:$A>=DATE(2026,10,1))*('DRAFT 2'!$A:$A<DATE(2026,IF(10=12,10+1,10+1),1)),'DRAFT 2'!$A:$A),"") | HO5: =COUNTIFS('DRAFT 2'!$D:$D,$B5,'DRAFT 2'!$A:$A,">="&DATE(2026,10,1),'DRAFT 2'!$A:$A,"<="&DATE(2026,10,7)) -> 0 | HP5: =COUNTIFS('DRAFT 2'!$D:$D,$B5,'DRAFT 2'!$A:$A,">="&DATE(2026,10,8),'DRAFT 2'!$A:$A,"<="&DATE(2026,10,14)) -> 0 | HQ5: =COUNTIFS('DRAFT 2'!$D:$D,$B5,'DRAFT 2'!$A:$A,">="&DATE(2026,10,15),'DRAFT 2'!$A:$A,"<="&DATE(2026,10,21)) -> 0 | HR5: =COUNTIFS('DRAFT 2'!$D:$D,$B5,'DRAFT 2'!$A:$A,">="&DATE(2026,10,22),'DRAFT 2'!$A:$A,"<"&DATE(2026,IF(10=12,10+1,10+1),1)) -> 0 | HS5: =SUM(HO5:HR5) -> 0 | HT5: =IF(HU5=0,1,HV5/HU5) -> 1 | HW5: =IF(HX5=0,1,HY5/HX5) -> 1 | HZ5: =IF(IA5=0,1,IB5/IA5) -> 1 | IC5: =IFERROR(LOOKUP(2,1/('DRAFT 2'!$D:$D=$B5)*('DRAFT 2'!$A:$A>=DATE(2026,11,1))*('DRAFT 2'!$A:$A<DATE(2026,IF(11=12,11+1,11+1),1)),'DRAFT 2'!$A:$A),"") | ID5: =COUNTIFS('DRAFT 2'!$D:$D,$B5,'DRAFT 2'!$A:$A,">="&DATE(2026,11,1),'DRAFT 2'!$A:$A,"<="&DATE(2026,11,7)) -> 0 | IE5: =COUNTIFS('DRAFT 2'!$D:$D,$B5,'DRAFT 2'!$A:$A,">="&DATE(2026,11,8),'DRAFT 2'!$A:$A,"<="&DATE(2026,11,14)) -> 0 | IF5: =COUNTIFS('DRAFT 2'!$D:$D,$B5,'DRAFT 2'!$A:$A,">="&DATE(2026,11,15),'DRAFT 2'!$A:$A,"<="&DATE(2026,11,21)) -> 0 | IG5: =COUNTIFS('DRAFT 2'!$D:$D,$B5,'DRAFT 2'!$A:$A,">="&DATE(2026,11,22),'DRAFT 2'!$A:$A,"<"&DATE(2026,IF(11=12,11+1,11+1),1)) -> 0 | IH5: =SUM(ID5:IG5) -> 0 | II5: =IF(IJ5=0,1,IK5/IJ5) -> 1 | IL5: =IF(IM5=0,1,IN5/IM5) -> 1 | IO5: =IF(IP5=0,1,IQ5/IP5) -> 1 | IR5: =IFERROR(LOOKUP(2,1/('DRAFT 2'!$D:$D=$B5)*('DRAFT 2'!$A:$A>=DATE(2026,12,1))*('DRAFT 2'!$A:$A<DATE(2026,IF(12=12,12+1,12+1),1)),'DRAFT 2'!$A:$A),"") | IS5: =COUNTIFS('DRAFT 2'!$D:$D,$B5,'DRAFT 2'!$A:$A,">="&DATE(2026,12,1),'DRAFT 2'!$A:$A,"<="&DATE(2026,12,7)) -> 0 | IT5: =COUNTIFS('DRAFT 2'!$D:$D,$B5,'DRAFT 2'!$A:$A,">="&DATE(2026,12,8),'DRAFT 2'!$A:$A,"<="&DATE(2026,12,14)) -> 0 | IU5: =COUNTIFS('DRAFT 2'!$D:$D,$B5,'DRAFT 2'!$A:$A,">="&DATE(2026,12,15),'DRAFT 2'!$A:$A,"<="&DATE(2026,12,21)) -> 0 | IV5: =COUNTIFS('DRAFT 2'!$D:$D,$B5,'DRAFT 2'!$A:$A,">="&DATE(2026,12,22),'DRAFT 2'!$A:$A,"<"&DATE(2026,IF(12=12,12+1,12+1),1)) -> 0 | IW5: =SUM(IS5:IV5) -> 0
A6: =IFERROR(INDEX('DRAFT 1'!$A:$A,MATCH($B6,'DRAFT 1'!$B:$B,0)),"") | B6: 12345678000199 | C6: =IFERROR(INDEX('DRAFT 1'!$C:$C,MATCH($B6,'DRAFT 1'!$B:$B,0)),"") | D6: =IFERROR(INDEX('DRAFT 1'!$D:$D,MATCH($B6,'DRAFT 1'!$B:$B,0)),"") | E6: =IFERROR(INDEX('DRAFT 1'!$E:$E,MATCH($B6,'DRAFT 1'!$B:$B,0)),"") | F6: =IFERROR(INDEX('DRAFT 1'!$F:$F,MATCH($B6,'DRAFT 1'!$B:$B,0)),"") | G6: =IFERROR(INDEX('DRAFT 1'!$G:$G,MATCH($B6,'DRAFT 1'!$B:$B,0)),"") | H6: =IFERROR(INDEX('DRAFT 1'!$H:$H,MATCH($B6,'DRAFT 1'!$B:$B,0)),"") | I6: BIOMUNDO | K6: =IFERROR(INDEX('DRAFT 1'!$AL:$AL,MATCH($B6,'DRAFT 1'!$B:$B,0)),"") | L6: =IFERROR(INDEX('DRAFT 1'!$J:$J,MATCH($B6,'DRAFT 1'!$B:$B,0)),"") | M6: =IFERROR(INDEX('DRAFT 1'!$K:$K,MATCH($B6,'DRAFT 1'!$B:$B,0)),"") | N6: INAT.ANT | O6: =IF(N6="EM RISCO",1,IF(N6="INAT.REC",2,IF(N6="ATIVO",3,IF(N6="INAT.ANT",4,5)))) -> 4 | P6: =IFERROR(INDEX('DRAFT 1'!$L:$L,MATCH($B6,'DRAFT 1'!$B:$B,0)),"") | Q6: =IFERROR(INDEX('DRAFT 1'!$M:$M,MATCH($B6,'DRAFT 1'!$B:$B,0)),"") | R6: =IFERROR(INDEX('DRAFT 1'!$N:$N,MATCH($B6,'DRAFT 1'!$B:$B,0)),"") | S6: =IFERROR(INDEX('DRAFT 1'!$O:$O,MATCH($B6,'DRAFT 1'!$B:$B,0)),"") | T6: =IFERROR(INDEX('DRAFT 1'!$P:$P,MATCH($B6,'DRAFT 1'!$B:$B,0)),"") | U6: =IFERROR(INDEX('DRAFT 1'!$Q:$Q,MATCH($B6,'DRAFT 1'!$B:$B,0)),"") | V6: =IFERROR(INDEX('DRAFT 1'!$R:$R,MATCH($B6,'DRAFT 1'!$B:$B,0)),"") | W6: =IFERROR(INDEX('DRAFT 1'!$S:$S,MATCH($B6,'DRAFT 1'!$B:$B,0)),"") | X6: =IFERROR(INDEX('DRAFT 1'!$T:$T,MATCH($B6,'DRAFT 1'!$B:$B,0)),"") | Y6: =SUM(Z6:AJ6) -> 0 | Z6: =IFERROR(INDEX('DRAFT 1'!$U:$U,MATCH($B6,'DRAFT 1'!$B:$B,0)),"") | AA6: =IFERROR(INDEX('DRAFT 1'!$V:$V,MATCH($B6,'DRAFT 1'!$B:$B,0)),"") | AB6: =IFERROR(INDEX('DRAFT 1'!$W:$W,MATCH($B6,'DRAFT 1'!$B:$B,0)),"") | AC6: =IFERROR(INDEX('DRAFT 1'!$X:$X,MATCH($B6,'DRAFT 1'!$B:$B,0)),"") | AD6: =IFERROR(INDEX('DRAFT 1'!$Y:$Y,MATCH($B6,'DRAFT 1'!$B:$B,0)),"") | AE6: =IFERROR(INDEX('DRAFT 1'!$Z:$Z,MATCH($B6,'DRAFT 1'!$B:$B,0)),"") | AF6: =IFERROR(INDEX('DRAFT 1'!$AA:$AA,MATCH($B6,'DRAFT 1'!$B:$B,0)),"") | AG6: =IFERROR(INDEX('DRAFT 1'!$AB:$AB,MATCH($B6,'DRAFT 1'!$B:$B,0)),"") | AH6: =IFERROR(INDEX('DRAFT 1'!$AC:$AC,MATCH($B6,'DRAFT 1'!$B:$B,0)),"") | AI6: =IFERROR(INDEX('DRAFT 1'!$AD:$AD,MATCH($B6,'DRAFT 1'!$B:$B,0)),"") | AJ6: =IFERROR(INDEX('DRAFT 1'!$AE:$AE,MATCH($B6,'DRAFT 1'!$B:$B,0)),"") | AK6: =IFERROR(INDEX('DRAFT 1'!$AG:$AG,MATCH($B6,'DRAFT 1'!$B:$B,0)),"") | AL6: =IFERROR(INDEX('DRAFT 1'!$AH:$AH,MATCH($B6,'DRAFT 1'!$B:$B,0)),"") | AM6: =IFERROR(INDEX('DRAFT 1'!$AI:$AI,MATCH($B6,'DRAFT 1'!$B:$B,0)),"") | AN6: =IFERROR(INDEX('DRAFT 1'!$AJ:$AJ,MATCH($B6,'DRAFT 1'!$B:$B,0)),"") | AO6: =IFERROR(Y6/AN6,0) -> 0 | AP6: =IFERROR(INDEX('DRAFT 1'!$AK:$AK,MATCH($B6,'DRAFT 1'!$B:$B,0)),"") | AR6: EM ATENDIMENTO | AS6: =IFERROR(LOOKUP(2,1/('DRAFT 2'!$D:$D=$B6),'DRAFT 2'!$T:$T),"") | AT6: =IFERROR(LOOKUP(2,1/('DRAFT 2'!$D:$D=$B6),'DRAFT 2'!$A:$A),"") | AU6: =IFERROR(LOOKUP(2,1/('DRAFT 2'!$D:$D=$B6),'DRAFT 2'!$R:$R),"") | AV6: =IFERROR(LOOKUP(2,1/('DRAFT 2'!$D:$D=$B6),'DRAFT 2'!$S:$S),"") | AW6: LEAD | AX6: =IFERROR(LOOKUP(2,1/('DRAFT 2'!$D:$D=$B6),'DRAFT 2'!$M:$M),"") | AY6: =IFERROR(LOOKUP(2,1/('DRAFT 2'!$D:$D=$B6),'DRAFT 2'!$K:$K),"") | BA6: =IF(N6="PROSPECT","❄️ FRIO",IF(OR(AR6="ORÇAMENTO",AR6="NEGOCIAÇÃO",AR6="CADASTRO"),"🔥 QUENTE",IF(OR(AR6="FOLLOW UP 7",AR6="FOLLOW UP 15",AR6="ATENDIMENTO"),"⚡ MORNO","❄️ FRIO"))) -> ❄️ FRIO | BB6: =IF(BE6="","",BE6-BC6) | BG6: =IFERROR(LOOKUP(2,1/('DRAFT 2'!$D:$D=$B6),'DRAFT 2'!$U:$U),"") | BH6: =IFERROR(LOOKUP(2,1/('DRAFT 2'!$D:$D=$B6),'DRAFT 2'!$V:$V),"") | BI6: =IF(Q6="","🟣",IF(P6<=IF(AK6="",45,AK6),"🟢",IF(P6<=IF(AK6="",45,AK6)+30,"🟡","🔴"))) -> 🟣 | BJ6: SAP003 | BU6: =CR6 -> 1 | BV6: =AVERAGE(CC6,CR6,DG6) -> 1 | BW6: =IF(BX6=0,1,BY6/BX6) -> 1 | BZ6: =IF(CA6=0,1,CB6/CA6) -> 1 | CC6: =IF(CD6=0,1,CE6/CD6) -> 1 | CE6: =IFERROR(AJ6,0) | CF6: =IFERROR(LOOKUP(2,1/('DRAFT 2'!$D:$D=$B6)*('DRAFT 2'!$A:$A>=DATE(2026,1,1))*('DRAFT 2'!$A:$A<DATE(2026,IF(1=12,1+1,1+1),1)),'DRAFT 2'!$A:$A),"") | CG6: =COUNTIFS('DRAFT 2'!$D:$D,$B6,'DRAFT 2'!$A:$A,">="&DATE(2026,1,1),'DRAFT 2'!$A:$A,"<="&DATE(2026,1,7)) -> 0 | CH6: =COUNTIFS('DRAFT 2'!$D:$D,$B6,'DRAFT 2'!$A:$A,">="&DATE(2026,1,8),'DRAFT 2'!$A:$A,"<="&DATE(2026,1,14)) -> 0 | CI6: =COUNTIFS('DRAFT 2'!$D:$D,$B6,'DRAFT 2'!$A:$A,">="&DATE(2026,1,15),'DRAFT 2'!$A:$A,"<="&DATE(2026,1,21)) -> 0 | CJ6: =COUNTIFS('DRAFT 2'!$D:$D,$B6,'DRAFT 2'!$A:$A,">="&DATE(2026,1,22),'DRAFT 2'!$A:$A,"<"&DATE(2026,IF(1=12,1+1,1+1),1)) -> 0 | CK6: =SUM(CG6:CJ6) -> 0 | CL6: =IF(CM6=0,1,CN6/CM6) -> 1 | CO6: =IF(CP6=0,1,CQ6/CP6) -> 1 | CR6: =IF(CS6=0,1,CT6/CS6) -> 1 | CT6: 0 | CU6: =IFERROR(LOOKUP(2,1/('DRAFT 2'!$D:$D=$B6)*('DRAFT 2'!$A:$A>=DATE(2026,2,1))*('DRAFT 2'!$A:$A<DATE(2026,IF(2=12,2+1,2+1),1)),'DRAFT 2'!$A:$A),"") | CV6: =COUNTIFS('DRAFT 2'!$D:$D,$B6,'DRAFT 2'!$A:$A,">="&DATE(2026,2,1),'DRAFT 2'!$A:$A,"<="&DATE(2026,2,7)) -> 0 | CW6: =COUNTIFS('DRAFT 2'!$D:$D,$B6,'DRAFT 2'!$A:$A,">="&DATE(2026,2,8),'DRAFT 2'!$A:$A,"<="&DATE(2026,2,14)) -> 0 | CX6: =COUNTIFS('DRAFT 2'!$D:$D,$B6,'DRAFT 2'!$A:$A,">="&DATE(2026,2,15),'DRAFT 2'!$A:$A,"<="&DATE(2026,2,21)) -> 0 | CY6: =COUNTIFS('DRAFT 2'!$D:$D,$B6,'DRAFT 2'!$A:$A,">="&DATE(2026,2,22),'DRAFT 2'!$A:$A,"<"&DATE(2026,IF(2=12,2+1,2+1),1)) -> 0 | CZ6: =SUM(CV6:CY6) -> 0 | DA6: =IF(DB6=0,1,DC6/DB6) -> 1 | DD6: =IF(DE6=0,1,DF6/DE6) -> 1 | DG6: =IF(DH6=0,1,DI6/DH6) -> 1 | DJ6: =IFERROR(LOOKUP(2,1/('DRAFT 2'!$D:$D=$B6)*('DRAFT 2'!$A:$A>=DATE(2026,3,1))*('DRAFT 2'!$A:$A<DATE(2026,IF(3=12,3+1,3+1),1)),'DRAFT 2'!$A:$A),"") | DK6: =COUNTIFS('DRAFT 2'!$D:$D,$B6,'DRAFT 2'!$A:$A,">="&DATE(2026,3,1),'DRAFT 2'!$A:$A,"<="&DATE(2026,3,7)) -> 0 | DL6: =COUNTIFS('DRAFT 2'!$D:$D,$B6,'DRAFT 2'!$A:$A,">="&DATE(2026,3,8),'DRAFT 2'!$A:$A,"<="&DATE(2026,3,14)) -> 0 | DM6: =COUNTIFS('DRAFT 2'!$D:$D,$B6,'DRAFT 2'!$A:$A,">="&DATE(2026,3,15),'DRAFT 2'!$A:$A,"<="&DATE(2026,3,21)) -> 0 | DN6: =COUNTIFS('DRAFT 2'!$D:$D,$B6,'DRAFT 2'!$A:$A,">="&DATE(2026,3,22),'DRAFT 2'!$A:$A,"<"&DATE(2026,IF(3=12,3+1,3+1),1)) -> 0 | DO6: =SUM(DK6:DN6) -> 0 | DP6: =AVERAGE(DW6,EL6,FA6) -> 1 | DQ6: =IF(DR6=0,1,DS6/DR6) -> 1 | DT6: =IF(DU6=0,1,DV6/DU6) -> 1 | DW6: =IF(DX6=0,1,DY6/DX6) -> 1 | DZ6: =IFERROR(LOOKUP(2,1/('DRAFT 2'!$D:$D=$B6)*('DRAFT 2'!$A:$A>=DATE(2026,4,1))*('DRAFT 2'!$A:$A<DATE(2026,IF(4=12,4+1,4+1),1)),'DRAFT 2'!$A:$A),"") | EA6: =COUNTIFS('DRAFT 2'!$D:$D,$B6,'DRAFT 2'!$A:$A,">="&DATE(2026,4,1),'DRAFT 2'!$A:$A,"<="&DATE(2026,4,7)) -> 0 | EB6: =COUNTIFS('DRAFT 2'!$D:$D,$B6,'DRAFT 2'!$A:$A,">="&DATE(2026,4,8),'DRAFT 2'!$A:$A,"<="&DATE(2026,4,14)) -> 0 | EC6: =COUNTIFS('DRAFT 2'!$D:$D,$B6,'DRAFT 2'!$A:$A,">="&DATE(2026,4,15),'DRAFT 2'!$A:$A,"<="&DATE(2026,4,21)) -> 0 | ED6: =COUNTIFS('DRAFT 2'!$D:$D,$B6,'DRAFT 2'!$A:$A,">="&DATE(2026,4,22),'DRAFT 2'!$A:$A,"<"&DATE(2026,IF(4=12,4+1,4+1),1)) -> 0 | EE6: =SUM(EA6:ED6) -> 0 | EF6: =IF(EG6=0,1,EH6/EG6) -> 1 | EI6: =IF(EJ6=0,1,EK6/EJ6) -> 1 | EL6: =IF(EM6=0,1,EN6/EM6) -> 1 | EO6: =IFERROR(LOOKUP(2,1/('DRAFT 2'!$D:$D=$B6)*('DRAFT 2'!$A:$A>=DATE(2026,5,1))*('DRAFT 2'!$A:$A<DATE(2026,IF(5=12,5+1,5+1),1)),'DRAFT 2'!$A:$A),"") | EP6: =COUNTIFS('DRAFT 2'!$D:$D,$B6,'DRAFT 2'!$A:$A,">="&DATE(2026,5,1),'DRAFT 2'!$A:$A,"<="&DATE(2026,5,7)) -> 0 | EQ6: =COUNTIFS('DRAFT 2'!$D:$D,$B6,'DRAFT 2'!$A:$A,">="&DATE(2026,5,8),'DRAFT 2'!$A:$A,"<="&DATE(2026,5,14)) -> 0 | ER6: =COUNTIFS('DRAFT 2'!$D:$D,$B6,'DRAFT 2'!$A:$A,">="&DATE(2026,5,15),'DRAFT 2'!$A:$A,"<="&DATE(2026,5,21)) -> 0 | ES6: =COUNTIFS('DRAFT 2'!$D:$D,$B6,'DRAFT 2'!$A:$A,">="&DATE(2026,5,22),'DRAFT 2'!$A:$A,"<"&DATE(2026,IF(5=12,5+1,5+1),1)) -> 0 | ET6: =SUM(EP6:ES6) -> 0 | EU6: =IF(EV6=0,1,EW6/EV6) -> 1 | EX6: =IF(EY6=0,1,EZ6/EY6) -> 1 | FA6: =IF(FB6=0,1,FC6/FB6) -> 1 | FD6: =IFERROR(LOOKUP(2,1/('DRAFT 2'!$D:$D=$B6)*('DRAFT 2'!$A:$A>=DATE(2026,6,1))*('DRAFT 2'!$A:$A<DATE(2026,IF(6=12,6+1,6+1),1)),'DRAFT 2'!$A:$A),"") | FE6: =COUNTIFS('DRAFT 2'!$D:$D,$B6,'DRAFT 2'!$A:$A,">="&DATE(2026,6,1),'DRAFT 2'!$A:$A,"<="&DATE(2026,6,7)) -> 0 | FF6: =COUNTIFS('DRAFT 2'!$D:$D,$B6,'DRAFT 2'!$A:$A,">="&DATE(2026,6,8),'DRAFT 2'!$A:$A,"<="&DATE(2026,6,14)) -> 0 | FG6: =COUNTIFS('DRAFT 2'!$D:$D,$B6,'DRAFT 2'!$A:$A,">="&DATE(2026,6,15),'DRAFT 2'!$A:$A,"<="&DATE(2026,6,21)) -> 0 | FH6: =COUNTIFS('DRAFT 2'!$D:$D,$B6,'DRAFT 2'!$A:$A,">="&DATE(2026,6,22),'DRAFT 2'!$A:$A,"<"&DATE(2026,IF(6=12,6+1,6+1),1)) -> 0 | FI6: =SUM(FE6:FH6) -> 0 | FJ6: =AVERAGE(FQ6,GF6,GU6) -> 1 | FK6: =IF(FL6=0,1,FM6/FL6) -> 1 | FN6: =IF(FO6=0,1,FP6/FO6) -> 1 | FQ6: =IF(FR6=0,1,FS6/FR6) -> 1 | FT6: =IFERROR(LOOKUP(2,1/('DRAFT 2'!$D:$D=$B6)*('DRAFT 2'!$A:$A>=DATE(2026,7,1))*('DRAFT 2'!$A:$A<DATE(2026,IF(7=12,7+1,7+1),1)),'DRAFT 2'!$A:$A),"") | FU6: =COUNTIFS('DRAFT 2'!$D:$D,$B6,'DRAFT 2'!$A:$A,">="&DATE(2026,7,1),'DRAFT 2'!$A:$A,"<="&DATE(2026,7,7)) -> 0 | FV6: =COUNTIFS('DRAFT 2'!$D:$D,$B6,'DRAFT 2'!$A:$A,">="&DATE(2026,7,8),'DRAFT 2'!$A:$A,"<="&DATE(2026,7,14)) -> 0 | FW6: =COUNTIFS('DRAFT 2'!$D:$D,$B6,'DRAFT 2'!$A:$A,">="&DATE(2026,7,15),'DRAFT 2'!$A:$A,"<="&DATE(2026,7,21)) -> 0 | FX6: =COUNTIFS('DRAFT 2'!$D:$D,$B6,'DRAFT 2'!$A:$A,">="&DATE(2026,7,22),'DRAFT 2'!$A:$A,"<"&DATE(2026,IF(7=12,7+1,7+1),1)) -> 0 | FY6: =SUM(FU6:FX6) -> 0 | FZ6: =IF(GA6=0,1,GB6/GA6) -> 1 | GC6: =IF(GD6=0,1,GE6/GD6) -> 1 | GF6: =IF(GG6=0,1,GH6/GG6) -> 1 | GI6: =IFERROR(LOOKUP(2,1/('DRAFT 2'!$D:$D=$B6)*('DRAFT 2'!$A:$A>=DATE(2026,8,1))*('DRAFT 2'!$A:$A<DATE(2026,IF(8=12,8+1,8+1),1)),'DRAFT 2'!$A:$A),"") | GJ6: =COUNTIFS('DRAFT 2'!$D:$D,$B6,'DRAFT 2'!$A:$A,">="&DATE(2026,8,1),'DRAFT 2'!$A:$A,"<="&DATE(2026,8,7)) -> 0 | GK6: =COUNTIFS('DRAFT 2'!$D:$D,$B6,'DRAFT 2'!$A:$A,">="&DATE(2026,8,8),'DRAFT 2'!$A:$A,"<="&DATE(2026,8,14)) -> 0 | GL6: =COUNTIFS('DRAFT 2'!$D:$D,$B6,'DRAFT 2'!$A:$A,">="&DATE(2026,8,15),'DRAFT 2'!$A:$A,"<="&DATE(2026,8,21)) -> 0 | GM6: =COUNTIFS('DRAFT 2'!$D:$D,$B6,'DRAFT 2'!$A:$A,">="&DATE(2026,8,22),'DRAFT 2'!$A:$A,"<"&DATE(2026,IF(8=12,8+1,8+1),1)) -> 0 | GN6: =SUM(GJ6:GM6) -> 0 | GO6: =IF(GP6=0,1,GQ6/GP6) -> 1 | GR6: =IF(GS6=0,1,GT6/GS6) -> 1 | GU6: =IF(GV6=0,1,GW6/GV6) -> 1 | GX6: =IFERROR(LOOKUP(2,1/('DRAFT 2'!$D:$D=$B6)*('DRAFT 2'!$A:$A>=DATE(2026,9,1))*('DRAFT 2'!$A:$A<DATE(2026,IF(9=12,9+1,9+1),1)),'DRAFT 2'!$A:$A),"") | GY6: =COUNTIFS('DRAFT 2'!$D:$D,$B6,'DRAFT 2'!$A:$A,">="&DATE(2026,9,1),'DRAFT 2'!$A:$A,"<="&DATE(2026,9,7)) -> 0 | GZ6: =COUNTIFS('DRAFT 2'!$D:$D,$B6,'DRAFT 2'!$A:$A,">="&DATE(2026,9,8),'DRAFT 2'!$A:$A,"<="&DATE(2026,9,14)) -> 0 | HA6: =COUNTIFS('DRAFT 2'!$D:$D,$B6,'DRAFT 2'!$A:$A,">="&DATE(2026,9,15),'DRAFT 2'!$A:$A,"<="&DATE(2026,9,21)) -> 0 | HB6: =COUNTIFS('DRAFT 2'!$D:$D,$B6,'DRAFT 2'!$A:$A,">="&DATE(2026,9,22),'DRAFT 2'!$A:$A,"<"&DATE(2026,IF(9=12,9+1,9+1),1)) -> 0 | HC6: =SUM(GY6:HB6) -> 0 | HD6: =AVERAGE(HK6,HZ6,IO6) -> 1 | HE6: =IF(HF6=0,1,HG6/HF6) -> 1 | HH6: =IF(HI6=0,1,HJ6/HI6) -> 1 | HK6: =IF(HL6=0,1,HM6/HL6) -> 1 | HN6: =IFERROR(LOOKUP(2,1/('DRAFT 2'!$D:$D=$B6)*('DRAFT 2'!$A:$A>=DATE(2026,10,1))*('DRAFT 2'!$A:$A<DATE(2026,IF(10=12,10+1,10+1),1)),'DRAFT 2'!$A:$A),"") | HO6: =COUNTIFS('DRAFT 2'!$D:$D,$B6,'DRAFT 2'!$A:$A,">="&DATE(2026,10,1),'DRAFT 2'!$A:$A,"<="&DATE(2026,10,7)) -> 0 | HP6: =COUNTIFS('DRAFT 2'!$D:$D,$B6,'DRAFT 2'!$A:$A,">="&DATE(2026,10,8),'DRAFT 2'!$A:$A,"<="&DATE(2026,10,14)) -> 0 | HQ6: =COUNTIFS('DRAFT 2'!$D:$D,$B6,'DRAFT 2'!$A:$A,">="&DATE(2026,10,15),'DRAFT 2'!$A:$A,"<="&DATE(2026,10,21)) -> 0 | HR6: =COUNTIFS('DRAFT 2'!$D:$D,$B6,'DRAFT 2'!$A:$A,">="&DATE(2026,10,22),'DRAFT 2'!$A:$A,"<"&DATE(2026,IF(10=12,10+1,10+1),1)) -> 0 | HS6: =SUM(HO6:HR6) -> 0 | HT6: =IF(HU6=0,1,HV6/HU6) -> 1 | HW6: =IF(HX6=0,1,HY6/HX6) -> 1 | HZ6: =IF(IA6=0,1,IB6/IA6) -> 1 | IC6: =IFERROR(LOOKUP(2,1/('DRAFT 2'!$D:$D=$B6)*('DRAFT 2'!$A:$A>=DATE(2026,11,1))*('DRAFT 2'!$A:$A<DATE(2026,IF(11=12,11+1,11+1),1)),'DRAFT 2'!$A:$A),"") | ID6: =COUNTIFS('DRAFT 2'!$D:$D,$B6,'DRAFT 2'!$A:$A,">="&DATE(2026,11,1),'DRAFT 2'!$A:$A,"<="&DATE(2026,11,7)) -> 0 | IE6: =COUNTIFS('DRAFT 2'!$D:$D,$B6,'DRAFT 2'!$A:$A,">="&DATE(2026,11,8),'DRAFT 2'!$A:$A,"<="&DATE(2026,11,14)) -> 0 | IF6: =COUNTIFS('DRAFT 2'!$D:$D,$B6,'DRAFT 2'!$A:$A,">="&DATE(2026,11,15),'DRAFT 2'!$A:$A,"<="&DATE(2026,11,21)) -> 0 | IG6: =COUNTIFS('DRAFT 2'!$D:$D,$B6,'DRAFT 2'!$A:$A,">="&DATE(2026,11,22),'DRAFT 2'!$A:$A,"<"&DATE(2026,IF(11=12,11+1,11+1),1)) -> 0 | IH6: =SUM(ID6:IG6) -> 0 | II6: =IF(IJ6=0,1,IK6/IJ6) -> 1 | IL6: =IF(IM6=0,1,IN6/IM6) -> 1 | IO6: =IF(IP6=0,1,IQ6/IP6) -> 1 | IR6: =IFERROR(LOOKUP(2,1/('DRAFT 2'!$D:$D=$B6)*('DRAFT 2'!$A:$A>=DATE(2026,12,1))*('DRAFT 2'!$A:$A<DATE(2026,IF(12=12,12+1,12+1),1)),'DRAFT 2'!$A:$A),"") | IS6: =COUNTIFS('DRAFT 2'!$D:$D,$B6,'DRAFT 2'!$A:$A,">="&DATE(2026,12,1),'DRAFT 2'!$A:$A,"<="&DATE(2026,12,7)) -> 0 | IT6: =COUNTIFS('DRAFT 2'!$D:$D,$B6,'DRAFT 2'!$A:$A,">="&DATE(2026,12,8),'DRAFT 2'!$A:$A,"<="&DATE(2026,12,14)) -> 0 | IU6: =COUNTIFS('DRAFT 2'!$D:$D,$B6,'DRAFT 2'!$A:$A,">="&DATE(2026,12,15),'DRAFT 2'!$A:$A,"<="&DATE(2026,12,21)) -> 0 | IV6: =COUNTIFS('DRAFT 2'!$D:$D,$B6,'DRAFT 2'!$A:$A,">="&DATE(2026,12,22),'DRAFT 2'!$A:$A,"<"&DATE(2026,IF(12=12,12+1,12+1),1)) -> 0 | IW6: =SUM(IS6:IV6) -> 0
A7: =IFERROR(INDEX('DRAFT 1'!$A:$A,MATCH($B7,'DRAFT 1'!$B:$B,0)),"") | B7: 98765432000188 | C7: =IFERROR(INDEX('DRAFT 1'!$C:$C,MATCH($B7,'DRAFT 1'!$B:$B,0)),"") | D7: =IFERROR(INDEX('DRAFT 1'!$D:$D,MATCH($B7,'DRAFT 1'!$B:$B,0)),"") | E7: =IFERROR(INDEX('DRAFT 1'!$E:$E,MATCH($B7,'DRAFT 1'!$B:$B,0)),"") | F7: =IFERROR(INDEX('DRAFT 1'!$F:$F,MATCH($B7,'DRAFT 1'!$B:$B,0)),"") | G7: =IFERROR(INDEX('DRAFT 1'!$G:$G,MATCH($B7,'DRAFT 1'!$B:$B,0)),"") | H7: =IFERROR(INDEX('DRAFT 1'!$H:$H,MATCH($B7,'DRAFT 1'!$B:$B,0)),"") | I7: DEMAIS CLIENTES | K7: =IFERROR(INDEX('DRAFT 1'!$AL:$AL,MATCH($B7,'DRAFT 1'!$B:$B,0)),"") | L7: =IFERROR(INDEX('DRAFT 1'!$J:$J,MATCH($B7,'DRAFT 1'!$B:$B,0)),"") | M7: =IFERROR(INDEX('DRAFT 1'!$K:$K,MATCH($B7,'DRAFT 1'!$B:$B,0)),"") | N7: PROSPECT | O7: =IF(N7="EM RISCO",1,IF(N7="INAT.REC",2,IF(N7="ATIVO",3,IF(N7="INAT.ANT",4,5)))) -> 5 | P7: =IFERROR(INDEX('DRAFT 1'!$L:$L,MATCH($B7,'DRAFT 1'!$B:$B,0)),"") | Q7: =IFERROR(INDEX('DRAFT 1'!$M:$M,MATCH($B7,'DRAFT 1'!$B:$B,0)),"") | R7: =IFERROR(INDEX('DRAFT 1'!$N:$N,MATCH($B7,'DRAFT 1'!$B:$B,0)),"") | S7: =IFERROR(INDEX('DRAFT 1'!$O:$O,MATCH($B7,'DRAFT 1'!$B:$B,0)),"") | T7: =IFERROR(INDEX('DRAFT 1'!$P:$P,MATCH($B7,'DRAFT 1'!$B:$B,0)),"") | U7: =IFERROR(INDEX('DRAFT 1'!$Q:$Q,MATCH($B7,'DRAFT 1'!$B:$B,0)),"") | V7: =IFERROR(INDEX('DRAFT 1'!$R:$R,MATCH($B7,'DRAFT 1'!$B:$B,0)),"") | W7: =IFERROR(INDEX('DRAFT 1'!$S:$S,MATCH($B7,'DRAFT 1'!$B:$B,0)),"") | X7: =IFERROR(INDEX('DRAFT 1'!$T:$T,MATCH($B7,'DRAFT 1'!$B:$B,0)),"") | Y7: =SUM(Z7:AJ7) -> 0 | Z7: =IFERROR(INDEX('DRAFT 1'!$U:$U,MATCH($B7,'DRAFT 1'!$B:$B,0)),"") | AA7: =IFERROR(INDEX('DRAFT 1'!$V:$V,MATCH($B7,'DRAFT 1'!$B:$B,0)),"") | AB7: =IFERROR(INDEX('DRAFT 1'!$W:$W,MATCH($B7,'DRAFT 1'!$B:$B,0)),"") | AC7: =IFERROR(INDEX('DRAFT 1'!$X:$X,MATCH($B7,'DRAFT 1'!$B:$B,0)),"") | AD7: =IFERROR(INDEX('DRAFT 1'!$Y:$Y,MATCH($B7,'DRAFT 1'!$B:$B,0)),"") | AE7: =IFERROR(INDEX('DRAFT 1'!$Z:$Z,MATCH($B7,'DRAFT 1'!$B:$B,0)),"") | AF7: =IFERROR(INDEX('DRAFT 1'!$AA:$AA,MATCH($B7,'DRAFT 1'!$B:$B,0)),"") | AG7: =IFERROR(INDEX('DRAFT 1'!$AB:$AB,MATCH($B7,'DRAFT 1'!$B:$B,0)),"") | AH7: =IFERROR(INDEX('DRAFT 1'!$AC:$AC,MATCH($B7,'DRAFT 1'!$B:$B,0)),"") | AI7: =IFERROR(INDEX('DRAFT 1'!$AD:$AD,MATCH($B7,'DRAFT 1'!$B:$B,0)),"") | AJ7: =IFERROR(INDEX('DRAFT 1'!$AE:$AE,MATCH($B7,'DRAFT 1'!$B:$B,0)),"") | AK7: =IFERROR(INDEX('DRAFT 1'!$AG:$AG,MATCH($B7,'DRAFT 1'!$B:$B,0)),"") | AL7: =IFERROR(INDEX('DRAFT 1'!$AH:$AH,MATCH($B7,'DRAFT 1'!$B:$B,0)),"") | AM7: =IFERROR(INDEX('DRAFT 1'!$AI:$AI,MATCH($B7,'DRAFT 1'!$B:$B,0)),"") | AN7: =IFERROR(INDEX('DRAFT 1'!$AJ:$AJ,MATCH($B7,'DRAFT 1'!$B:$B,0)),"") | AO7: =IFERROR(Y7/AN7,0) -> 0 | AP7: =IFERROR(INDEX('DRAFT 1'!$AK:$AK,MATCH($B7,'DRAFT 1'!$B:$B,0)),"") | AR7: EM ATENDIMENTO | AS7: =IFERROR(LOOKUP(2,1/('DRAFT 2'!$D:$D=$B7),'DRAFT 2'!$T:$T),"") | AT7: =IFERROR(LOOKUP(2,1/('DRAFT 2'!$D:$D=$B7),'DRAFT 2'!$A:$A),"") | AU7: =IFERROR(LOOKUP(2,1/('DRAFT 2'!$D:$D=$B7),'DRAFT 2'!$R:$R),"") | AV7: =IFERROR(LOOKUP(2,1/('DRAFT 2'!$D:$D=$B7),'DRAFT 2'!$S:$S),"") | AW7: EM DESENVOLVIMENTO | AX7: =IFERROR(LOOKUP(2,1/('DRAFT 2'!$D:$D=$B7),'DRAFT 2'!$M:$M),"") | AY7: =IFERROR(LOOKUP(2,1/('DRAFT 2'!$D:$D=$B7),'DRAFT 2'!$K:$K),"") | BA7: =IF(N7="PROSPECT","❄️ FRIO",IF(OR(AR7="ORÇAMENTO",AR7="NEGOCIAÇÃO",AR7="CADASTRO"),"🔥 QUENTE",IF(OR(AR7="FOLLOW UP 7",AR7="FOLLOW UP 15",AR7="ATENDIMENTO"),"⚡ MORNO","❄️ FRIO"))) -> ❄️ FRIO | BB7: =IF(BE7="","",BE7-BC7) | BG7: =IFERROR(LOOKUP(2,1/('DRAFT 2'!$D:$D=$B7),'DRAFT 2'!$U:$U),"") | BH7: =IFERROR(LOOKUP(2,1/('DRAFT 2'!$D:$D=$B7),'DRAFT 2'!$V:$V),"") | BI7: =IF(Q7="","🟣",IF(P7<=IF(AK7="",45,AK7),"🟢",IF(P7<=IF(AK7="",45,AK7)+30,"🟡","🔴"))) -> 🟣 | BJ7: SAP004 | BU7: =CR7 -> 1 | BV7: =AVERAGE(CC7,CR7,DG7) -> 1 | BW7: =IF(BX7=0,1,BY7/BX7) -> 1 | BZ7: =IF(CA7=0,1,CB7/CA7) -> 1 | CC7: =IF(CD7=0,1,CE7/CD7) -> 1 | CE7: =IFERROR(AJ7,0) | CF7: =IFERROR(LOOKUP(2,1/('DRAFT 2'!$D:$D=$B7)*('DRAFT 2'!$A:$A>=DATE(2026,1,1))*('DRAFT 2'!$A:$A<DATE(2026,IF(1=12,1+1,1+1),1)),'DRAFT 2'!$A:$A),"") | CG7: =COUNTIFS('DRAFT 2'!$D:$D,$B7,'DRAFT 2'!$A:$A,">="&DATE(2026,1,1),'DRAFT 2'!$A:$A,"<="&DATE(2026,1,7)) -> 0 | CH7: =COUNTIFS('DRAFT 2'!$D:$D,$B7,'DRAFT 2'!$A:$A,">="&DATE(2026,1,8),'DRAFT 2'!$A:$A,"<="&DATE(2026,1,14)) -> 0 | CI7: =COUNTIFS('DRAFT 2'!$D:$D,$B7,'DRAFT 2'!$A:$A,">="&DATE(2026,1,15),'DRAFT 2'!$A:$A,"<="&DATE(2026,1,21)) -> 0 | CJ7: =COUNTIFS('DRAFT 2'!$D:$D,$B7,'DRAFT 2'!$A:$A,">="&DATE(2026,1,22),'DRAFT 2'!$A:$A,"<"&DATE(2026,IF(1=12,1+1,1+1),1)) -> 0 | CK7: =SUM(CG7:CJ7) -> 0 | CL7: =IF(CM7=0,1,CN7/CM7) -> 1 | CO7: =IF(CP7=0,1,CQ7/CP7) -> 1 | CR7: =IF(CS7=0,1,CT7/CS7) -> 1 | CT7: 0 | CU7: =IFERROR(LOOKUP(2,1/('DRAFT 2'!$D:$D=$B7)*('DRAFT 2'!$A:$A>=DATE(2026,2,1))*('DRAFT 2'!$A:$A<DATE(2026,IF(2=12,2+1,2+1),1)),'DRAFT 2'!$A:$A),"") | CV7: =COUNTIFS('DRAFT 2'!$D:$D,$B7,'DRAFT 2'!$A:$A,">="&DATE(2026,2,1),'DRAFT 2'!$A:$A,"<="&DATE(2026,2,7)) -> 0 | CW7: =COUNTIFS('DRAFT 2'!$D:$D,$B7,'DRAFT 2'!$A:$A,">="&DATE(2026,2,8),'DRAFT 2'!$A:$A,"<="&DATE(2026,2,14)) -> 0 | CX7: =COUNTIFS('DRAFT 2'!$D:$D,$B7,'DRAFT 2'!$A:$A,">="&DATE(2026,2,15),'DRAFT 2'!$A:$A,"<="&DATE(2026,2,21)) -> 0 | CY7: =COUNTIFS('DRAFT 2'!$D:$D,$B7,'DRAFT 2'!$A:$A,">="&DATE(2026,2,22),'DRAFT 2'!$A:$A,"<"&DATE(2026,IF(2=12,2+1,2+1),1)) -> 0 | CZ7: =SUM(CV7:CY7) -> 0 | DA7: =IF(DB7=0,1,DC7/DB7) -> 1 | DD7: =IF(DE7=0,1,DF7/DE7) -> 1 | DG7: =IF(DH7=0,1,DI7/DH7) -> 1 | DJ7: =IFERROR(LOOKUP(2,1/('DRAFT 2'!$D:$D=$B7)*('DRAFT 2'!$A:$A>=DATE(2026,3,1))*('DRAFT 2'!$A:$A<DATE(2026,IF(3=12,3+1,3+1),1)),'DRAFT 2'!$A:$A),"") | DK7: =COUNTIFS('DRAFT 2'!$D:$D,$B7,'DRAFT 2'!$A:$A,">="&DATE(2026,3,1),'DRAFT 2'!$A:$A,"<="&DATE(2026,3,7)) -> 0 | DL7: =COUNTIFS('DRAFT 2'!$D:$D,$B7,'DRAFT 2'!$A:$A,">="&DATE(2026,3,8),'DRAFT 2'!$A:$A,"<="&DATE(2026,3,14)) -> 0 | DM7: =COUNTIFS('DRAFT 2'!$D:$D,$B7,'DRAFT 2'!$A:$A,">="&DATE(2026,3,15),'DRAFT 2'!$A:$A,"<="&DATE(2026,3,21)) -> 0 | DN7: =COUNTIFS('DRAFT 2'!$D:$D,$B7,'DRAFT 2'!$A:$A,">="&DATE(2026,3,22),'DRAFT 2'!$A:$A,"<"&DATE(2026,IF(3=12,3+1,3+1),1)) -> 0 | DO7: =SUM(DK7:DN7) -> 0 | DP7: =AVERAGE(DW7,EL7,FA7) -> 1 | DQ7: =IF(DR7=0,1,DS7/DR7) -> 1 | DT7: =IF(DU7=0,1,DV7/DU7) -> 1 | DW7: =IF(DX7=0,1,DY7/DX7) -> 1 | DZ7: =IFERROR(LOOKUP(2,1/('DRAFT 2'!$D:$D=$B7)*('DRAFT 2'!$A:$A>=DATE(2026,4,1))*('DRAFT 2'!$A:$A<DATE(2026,IF(4=12,4+1,4+1),1)),'DRAFT 2'!$A:$A),"") | EA7: =COUNTIFS('DRAFT 2'!$D:$D,$B7,'DRAFT 2'!$A:$A,">="&DATE(2026,4,1),'DRAFT 2'!$A:$A,"<="&DATE(2026,4,7)) -> 0 | EB7: =COUNTIFS('DRAFT 2'!$D:$D,$B7,'DRAFT 2'!$A:$A,">="&DATE(2026,4,8),'DRAFT 2'!$A:$A,"<="&DATE(2026,4,14)) -> 0 | EC7: =COUNTIFS('DRAFT 2'!$D:$D,$B7,'DRAFT 2'!$A:$A,">="&DATE(2026,4,15),'DRAFT 2'!$A:$A,"<="&DATE(2026,4,21)) -> 0 | ED7: =COUNTIFS('DRAFT 2'!$D:$D,$B7,'DRAFT 2'!$A:$A,">="&DATE(2026,4,22),'DRAFT 2'!$A:$A,"<"&DATE(2026,IF(4=12,4+1,4+1),1)) -> 0 | EE7: =SUM(EA7:ED7) -> 0 | EF7: =IF(EG7=0,1,EH7/EG7) -> 1 | EI7: =IF(EJ7=0,1,EK7/EJ7) -> 1 | EL7: =IF(EM7=0,1,EN7/EM7) -> 1 | EO7: =IFERROR(LOOKUP(2,1/('DRAFT 2'!$D:$D=$B7)*('DRAFT 2'!$A:$A>=DATE(2026,5,1))*('DRAFT 2'!$A:$A<DATE(2026,IF(5=12,5+1,5+1),1)),'DRAFT 2'!$A:$A),"") | EP7: =COUNTIFS('DRAFT 2'!$D:$D,$B7,'DRAFT 2'!$A:$A,">="&DATE(2026,5,1),'DRAFT 2'!$A:$A,"<="&DATE(2026,5,7)) -> 0 | EQ7: =COUNTIFS('DRAFT 2'!$D:$D,$B7,'DRAFT 2'!$A:$A,">="&DATE(2026,5,8),'DRAFT 2'!$A:$A,"<="&DATE(2026,5,14)) -> 0 | ER7: =COUNTIFS('DRAFT 2'!$D:$D,$B7,'DRAFT 2'!$A:$A,">="&DATE(2026,5,15),'DRAFT 2'!$A:$A,"<="&DATE(2026,5,21)) -> 0 | ES7: =COUNTIFS('DRAFT 2'!$D:$D,$B7,'DRAFT 2'!$A:$A,">="&DATE(2026,5,22),'DRAFT 2'!$A:$A,"<"&DATE(2026,IF(5=12,5+1,5+1),1)) -> 0 | ET7: =SUM(EP7:ES7) -> 0 | EU7: =IF(EV7=0,1,EW7/EV7) -> 1 | EX7: =IF(EY7=0,1,EZ7/EY7) -> 1 | FA7: =IF(FB7=0,1,FC7/FB7) -> 1 | FD7: =IFERROR(LOOKUP(2,1/('DRAFT 2'!$D:$D=$B7)*('DRAFT 2'!$A:$A>=DATE(2026,6,1))*('DRAFT 2'!$A:$A<DATE(2026,IF(6=12,6+1,6+1),1)),'DRAFT 2'!$A:$A),"") | FE7: =COUNTIFS('DRAFT 2'!$D:$D,$B7,'DRAFT 2'!$A:$A,">="&DATE(2026,6,1),'DRAFT 2'!$A:$A,"<="&DATE(2026,6,7)) -> 0 | FF7: =COUNTIFS('DRAFT 2'!$D:$D,$B7,'DRAFT 2'!$A:$A,">="&DATE(2026,6,8),'DRAFT 2'!$A:$A,"<="&DATE(2026,6,14)) -> 0 | FG7: =COUNTIFS('DRAFT 2'!$D:$D,$B7,'DRAFT 2'!$A:$A,">="&DATE(2026,6,15),'DRAFT 2'!$A:$A,"<="&DATE(2026,6,21)) -> 0 | FH7: =COUNTIFS('DRAFT 2'!$D:$D,$B7,'DRAFT 2'!$A:$A,">="&DATE(2026,6,22),'DRAFT 2'!$A:$A,"<"&DATE(2026,IF(6=12,6+1,6+1),1)) -> 0 | FI7: =SUM(FE7:FH7) -> 0 | FJ7: =AVERAGE(FQ7,GF7,GU7) -> 1 | FK7: =IF(FL7=0,1,FM7/FL7) -> 1 | FN7: =IF(FO7=0,1,FP7/FO7) -> 1 | FQ7: =IF(FR7=0,1,FS7/FR7) -> 1 | FT7: =IFERROR(LOOKUP(2,1/('DRAFT 2'!$D:$D=$B7)*('DRAFT 2'!$A:$A>=DATE(2026,7,1))*('DRAFT 2'!$A:$A<DATE(2026,IF(7=12,7+1,7+1),1)),'DRAFT 2'!$A:$A),"") | FU7: =COUNTIFS('DRAFT 2'!$D:$D,$B7,'DRAFT 2'!$A:$A,">="&DATE(2026,7,1),'DRAFT 2'!$A:$A,"<="&DATE(2026,7,7)) -> 0 | FV7: =COUNTIFS('DRAFT 2'!$D:$D,$B7,'DRAFT 2'!$A:$A,">="&DATE(2026,7,8),'DRAFT 2'!$A:$A,"<="&DATE(2026,7,14)) -> 0 | FW7: =COUNTIFS('DRAFT 2'!$D:$D,$B7,'DRAFT 2'!$A:$A,">="&DATE(2026,7,15),'DRAFT 2'!$A:$A,"<="&DATE(2026,7,21)) -> 0 | FX7: =COUNTIFS('DRAFT 2'!$D:$D,$B7,'DRAFT 2'!$A:$A,">="&DATE(2026,7,22),'DRAFT 2'!$A:$A,"<"&DATE(2026,IF(7=12,7+1,7+1),1)) -> 0 | FY7: =SUM(FU7:FX7) -> 0 | FZ7: =IF(GA7=0,1,GB7/GA7) -> 1 | GC7: =IF(GD7=0,1,GE7/GD7) -> 1 | GF7: =IF(GG7=0,1,GH7/GG7) -> 1 | GI7: =IFERROR(LOOKUP(2,1/('DRAFT 2'!$D:$D=$B7)*('DRAFT 2'!$A:$A>=DATE(2026,8,1))*('DRAFT 2'!$A:$A<DATE(2026,IF(8=12,8+1,8+1),1)),'DRAFT 2'!$A:$A),"") | GJ7: =COUNTIFS('DRAFT 2'!$D:$D,$B7,'DRAFT 2'!$A:$A,">="&DATE(2026,8,1),'DRAFT 2'!$A:$A,"<="&DATE(2026,8,7)) -> 0 | GK7: =COUNTIFS('DRAFT 2'!$D:$D,$B7,'DRAFT 2'!$A:$A,">="&DATE(2026,8,8),'DRAFT 2'!$A:$A,"<="&DATE(2026,8,14)) -> 0 | GL7: =COUNTIFS('DRAFT 2'!$D:$D,$B7,'DRAFT 2'!$A:$A,">="&DATE(2026,8,15),'DRAFT 2'!$A:$A,"<="&DATE(2026,8,21)) -> 0 | GM7: =COUNTIFS('DRAFT 2'!$D:$D,$B7,'DRAFT 2'!$A:$A,">="&DATE(2026,8,22),'DRAFT 2'!$A:$A,"<"&DATE(2026,IF(8=12,8+1,8+1),1)) -> 0 | GN7: =SUM(GJ7:GM7) -> 0 | GO7: =IF(GP7=0,1,GQ7/GP7) -> 1 | GR7: =IF(GS7=0,1,GT7/GS7) -> 1 | GU7: =IF(GV7=0,1,GW7/GV7) -> 1 | GX7: =IFERROR(LOOKUP(2,1/('DRAFT 2'!$D:$D=$B7)*('DRAFT 2'!$A:$A>=DATE(2026,9,1))*('DRAFT 2'!$A:$A<DATE(2026,IF(9=12,9+1,9+1),1)),'DRAFT 2'!$A:$A),"") | GY7: =COUNTIFS('DRAFT 2'!$D:$D,$B7,'DRAFT 2'!$A:$A,">="&DATE(2026,9,1),'DRAFT 2'!$A:$A,"<="&DATE(2026,9,7)) -> 0 | GZ7: =COUNTIFS('DRAFT 2'!$D:$D,$B7,'DRAFT 2'!$A:$A,">="&DATE(2026,9,8),'DRAFT 2'!$A:$A,"<="&DATE(2026,9,14)) -> 0 | HA7: =COUNTIFS('DRAFT 2'!$D:$D,$B7,'DRAFT 2'!$A:$A,">="&DATE(2026,9,15),'DRAFT 2'!$A:$A,"<="&DATE(2026,9,21)) -> 0 | HB7: =COUNTIFS('DRAFT 2'!$D:$D,$B7,'DRAFT 2'!$A:$A,">="&DATE(2026,9,22),'DRAFT 2'!$A:$A,"<"&DATE(2026,IF(9=12,9+1,9+1),1)) -> 0 | HC7: =SUM(GY7:HB7) -> 0 | HD7: =AVERAGE(HK7,HZ7,IO7) -> 1 | HE7: =IF(HF7=0,1,HG7/HF7) -> 1 | HH7: =IF(HI7=0,1,HJ7/HI7) -> 1 | HK7: =IF(HL7=0,1,HM7/HL7) -> 1 | HN7: =IFERROR(LOOKUP(2,1/('DRAFT 2'!$D:$D=$B7)*('DRAFT 2'!$A:$A>=DATE(2026,10,1))*('DRAFT 2'!$A:$A<DATE(2026,IF(10=12,10+1,10+1),1)),'DRAFT 2'!$A:$A),"") | HO7: =COUNTIFS('DRAFT 2'!$D:$D,$B7,'DRAFT 2'!$A:$A,">="&DATE(2026,10,1),'DRAFT 2'!$A:$A,"<="&DATE(2026,10,7)) -> 0 | HP7: =COUNTIFS('DRAFT 2'!$D:$D,$B7,'DRAFT 2'!$A:$A,">="&DATE(2026,10,8),'DRAFT 2'!$A:$A,"<="&DATE(2026,10,14)) -> 0 | HQ7: =COUNTIFS('DRAFT 2'!$D:$D,$B7,'DRAFT 2'!$A:$A,">="&DATE(2026,10,15),'DRAFT 2'!$A:$A,"<="&DATE(2026,10,21)) -> 0 | HR7: =COUNTIFS('DRAFT 2'!$D:$D,$B7,'DRAFT 2'!$A:$A,">="&DATE(2026,10,22),'DRAFT 2'!$A:$A,"<"&DATE(2026,IF(10=12,10+1,10+1),1)) -> 0 | HS7: =SUM(HO7:HR7) -> 0 | HT7: =IF(HU7=0,1,HV7/HU7) -> 1 | HW7: =IF(HX7=0,1,HY7/HX7) -> 1 | HZ7: =IF(IA7=0,1,IB7/IA7) -> 1 | IC7: =IFERROR(LOOKUP(2,1/('DRAFT 2'!$D:$D=$B7)*('DRAFT 2'!$A:$A>=DATE(2026,11,1))*('DRAFT 2'!$A:$A<DATE(2026,IF(11=12,11+1,11+1),1)),'DRAFT 2'!$A:$A),"") | ID7: =COUNTIFS('DRAFT 2'!$D:$D,$B7,'DRAFT 2'!$A:$A,">="&DATE(2026,11,1),'DRAFT 2'!$A:$A,"<="&DATE(2026,11,7)) -> 0 | IE7: =COUNTIFS('DRAFT 2'!$D:$D,$B7,'DRAFT 2'!$A:$A,">="&DATE(2026,11,8),'DRAFT 2'!$A:$A,"<="&DATE(2026,11,14)) -> 0 | IF7: =COUNTIFS('DRAFT 2'!$D:$D,$B7,'DRAFT 2'!$A:$A,">="&DATE(2026,11,15),'DRAFT 2'!$A:$A,"<="&DATE(2026,11,21)) -> 0 | IG7: =COUNTIFS('DRAFT 2'!$D:$D,$B7,'DRAFT 2'!$A:$A,">="&DATE(2026,11,22),'DRAFT 2'!$A:$A,"<"&DATE(2026,IF(11=12,11+1,11+1),1)) -> 0 | IH7: =SUM(ID7:IG7) -> 0 | II7: =IF(IJ7=0,1,IK7/IJ7) -> 1 | IL7: =IF(IM7=0,1,IN7/IM7) -> 1 | IO7: =IF(IP7=0,1,IQ7/IP7) -> 1 | IR7: =IFERROR(LOOKUP(2,1/('DRAFT 2'!$D:$D=$B7)*('DRAFT 2'!$A:$A>=DATE(2026,12,1))*('DRAFT 2'!$A:$A<DATE(2026,IF(12=12,12+1,12+1),1)),'DRAFT 2'!$A:$A),"") | IS7: =COUNTIFS('DRAFT 2'!$D:$D,$B7,'DRAFT 2'!$A:$A,">="&DATE(2026,12,1),'DRAFT 2'!$A:$A,"<="&DATE(2026,12,7)) -> 0 | IT7: =COUNTIFS('DRAFT 2'!$D:$D,$B7,'DRAFT 2'!$A:$A,">="&DATE(2026,12,8),'DRAFT 2'!$A:$A,"<="&DATE(2026,12,14)) -> 0 | IU7: =COUNTIFS('DRAFT 2'!$D:$D,$B7,'DRAFT 2'!$A:$A,">="&DATE(2026,12,15),'DRAFT 2'!$A:$A,"<="&DATE(2026,12,21)) -> 0 | IV7: =COUNTIFS('DRAFT 2'!$D:$D,$B7,'DRAFT 2'!$A:$A,">="&DATE(2026,12,22),'DRAFT 2'!$A:$A,"<"&DATE(2026,IF(12=12,12+1,12+1),1)) -> 0 | IW7: =SUM(IS7:IV7) -> 0
A8: =IFERROR(INDEX('DRAFT 1'!$A:$A,MATCH($B8,'DRAFT 1'!$B:$B,0)),"") | B8: 55566677000122 | C8: =IFERROR(INDEX('DRAFT 1'!$C:$C,MATCH($B8,'DRAFT 1'!$B:$B,0)),"") | D8: =IFERROR(INDEX('DRAFT 1'!$D:$D,MATCH($B8,'DRAFT 1'!$B:$B,0)),"") | E8: =IFERROR(INDEX('DRAFT 1'!$E:$E,MATCH($B8,'DRAFT 1'!$B:$B,0)),"") | F8: =IFERROR(INDEX('DRAFT 1'!$F:$F,MATCH($B8,'DRAFT 1'!$B:$B,0)),"") | G8: =IFERROR(INDEX('DRAFT 1'!$G:$G,MATCH($B8,'DRAFT 1'!$B:$B,0)),"") | H8: =IFERROR(INDEX('DRAFT 1'!$H:$H,MATCH($B8,'DRAFT 1'!$B:$B,0)),"") | I8: DEMAIS CLIENTES | K8: =IFERROR(INDEX('DRAFT 1'!$AL:$AL,MATCH($B8,'DRAFT 1'!$B:$B,0)),"") | L8: =IFERROR(INDEX('DRAFT 1'!$J:$J,MATCH($B8,'DRAFT 1'!$B:$B,0)),"") | M8: =IFERROR(INDEX('DRAFT 1'!$K:$K,MATCH($B8,'DRAFT 1'!$B:$B,0)),"") | N8: INAT.ANT | O8: =IF(N8="EM RISCO",1,IF(N8="INAT.REC",2,IF(N8="ATIVO",3,IF(N8="INAT.ANT",4,5)))) -> 4 | P8: =IFERROR(INDEX('DRAFT 1'!$L:$L,MATCH($B8,'DRAFT 1'!$B:$B,0)),"") | Q8: =IFERROR(INDEX('DRAFT 1'!$M:$M,MATCH($B8,'DRAFT 1'!$B:$B,0)),"") | R8: =IFERROR(INDEX('DRAFT 1'!$N:$N,MATCH($B8,'DRAFT 1'!$B:$B,0)),"") | S8: =IFERROR(INDEX('DRAFT 1'!$O:$O,MATCH($B8,'DRAFT 1'!$B:$B,0)),"") | T8: =IFERROR(INDEX('DRAFT 1'!$P:$P,MATCH($B8,'DRAFT 1'!$B:$B,0)),"") | U8: =IFERROR(INDEX('DRAFT 1'!$Q:$Q,MATCH($B8,'DRAFT 1'!$B:$B,0)),"") | V8: =IFERROR(INDEX('DRAFT 1'!$R:$R,MATCH($B8,'DRAFT 1'!$B:$B,0)),"") | W8: =IFERROR(INDEX('DRAFT 1'!$S:$S,MATCH($B8,'DRAFT 1'!$B:$B,0)),"") | X8: =IFERROR(INDEX('DRAFT 1'!$T:$T,MATCH($B8,'DRAFT 1'!$B:$B,0)),"") | Y8: =SUM(Z8:AJ8) -> 0 | Z8: =IFERROR(INDEX('DRAFT 1'!$U:$U,MATCH($B8,'DRAFT 1'!$B:$B,0)),"") | AA8: =IFERROR(INDEX('DRAFT 1'!$V:$V,MATCH($B8,'DRAFT 1'!$B:$B,0)),"") | AB8: =IFERROR(INDEX('DRAFT 1'!$W:$W,MATCH($B8,'DRAFT 1'!$B:$B,0)),"") | AC8: =IFERROR(INDEX('DRAFT 1'!$X:$X,MATCH($B8,'DRAFT 1'!$B:$B,0)),"") | AD8: =IFERROR(INDEX('DRAFT 1'!$Y:$Y,MATCH($B8,'DRAFT 1'!$B:$B,0)),"") | AE8: =IFERROR(INDEX('DRAFT 1'!$Z:$Z,MATCH($B8,'DRAFT 1'!$B:$B,0)),"") | AF8: =IFERROR(INDEX('DRAFT 1'!$AA:$AA,MATCH($B8,'DRAFT 1'!$B:$B,0)),"") | AG8: =IFERROR(INDEX('DRAFT 1'!$AB:$AB,MATCH($B8,'DRAFT 1'!$B:$B,0)),"") | AH8: =IFERROR(INDEX('DRAFT 1'!$AC:$AC,MATCH($B8,'DRAFT 1'!$B:$B,0)),"") | AI8: =IFERROR(INDEX('DRAFT 1'!$AD:$AD,MATCH($B8,'DRAFT 1'!$B:$B,0)),"") | AJ8: =IFERROR(INDEX('DRAFT 1'!$AE:$AE,MATCH($B8,'DRAFT 1'!$B:$B,0)),"") | AK8: =IFERROR(INDEX('DRAFT 1'!$AG:$AG,MATCH($B8,'DRAFT 1'!$B:$B,0)),"") | AL8: =IFERROR(INDEX('DRAFT 1'!$AH:$AH,MATCH($B8,'DRAFT 1'!$B:$B,0)),"") | AM8: =IFERROR(INDEX('DRAFT 1'!$AI:$AI,MATCH($B8,'DRAFT 1'!$B:$B,0)),"") | AN8: =IFERROR(INDEX('DRAFT 1'!$AJ:$AJ,MATCH($B8,'DRAFT 1'!$B:$B,0)),"") | AO8: =IFERROR(Y8/AN8,0) -> 0 | AP8: =IFERROR(INDEX('DRAFT 1'!$AK:$AK,MATCH($B8,'DRAFT 1'!$B:$B,0)),"") | AR8: PROSPECÇÃO | AS8: =IFERROR(LOOKUP(2,1/('DRAFT 2'!$D:$D=$B8),'DRAFT 2'!$T:$T),"") | AT8: =IFERROR(LOOKUP(2,1/('DRAFT 2'!$D:$D=$B8),'DRAFT 2'!$A:$A),"") | AU8: =IFERROR(LOOKUP(2,1/('DRAFT 2'!$D:$D=$B8),'DRAFT 2'!$R:$R),"") | AV8: =IFERROR(LOOKUP(2,1/('DRAFT 2'!$D:$D=$B8),'DRAFT 2'!$S:$S),"") | AW8: PROSPECT | AX8: =IFERROR(LOOKUP(2,1/('DRAFT 2'!$D:$D=$B8),'DRAFT 2'!$M:$M),"") | AY8: =IFERROR(LOOKUP(2,1/('DRAFT 2'!$D:$D=$B8),'DRAFT 2'!$K:$K),"") | BA8: =IF(N8="PROSPECT","❄️ FRIO",IF(OR(AR8="ORÇAMENTO",AR8="NEGOCIAÇÃO",AR8="CADASTRO"),"🔥 QUENTE",IF(OR(AR8="FOLLOW UP 7",AR8="FOLLOW UP 15",AR8="ATENDIMENTO"),"⚡ MORNO","❄️ FRIO"))) -> ❄️ FRIO | BB8: =IF(BE8="","",BE8-BC8) | BG8: =IFERROR(LOOKUP(2,1/('DRAFT 2'!$D:$D=$B8),'DRAFT 2'!$U:$U),"") | BH8: =IFERROR(LOOKUP(2,1/('DRAFT 2'!$D:$D=$B8),'DRAFT 2'!$V:$V),"") | BI8: =IF(Q8="","🟣",IF(P8<=IF(AK8="",45,AK8),"🟢",IF(P8<=IF(AK8="",45,AK8)+30,"🟡","🔴"))) -> 🟣 | BU8: =CR8 -> 1 | BV8: =AVERAGE(CC8,CR8,DG8) -> 1 | BW8: =IF(BX8=0,1,BY8/BX8) -> 1 | BZ8: =IF(CA8=0,1,CB8/CA8) -> 1 | CC8: =IF(CD8=0,1,CE8/CD8) -> 1 | CE8: =IFERROR(AJ8,0) | CF8: =IFERROR(LOOKUP(2,1/('DRAFT 2'!$D:$D=$B8)*('DRAFT 2'!$A:$A>=DATE(2026,1,1))*('DRAFT 2'!$A:$A<DATE(2026,IF(1=12,1+1,1+1),1)),'DRAFT 2'!$A:$A),"") | CG8: =COUNTIFS('DRAFT 2'!$D:$D,$B8,'DRAFT 2'!$A:$A,">="&DATE(2026,1,1),'DRAFT 2'!$A:$A,"<="&DATE(2026,1,7)) -> 0 | CH8: =COUNTIFS('DRAFT 2'!$D:$D,$B8,'DRAFT 2'!$A:$A,">="&DATE(2026,1,8),'DRAFT 2'!$A:$A,"<="&DATE(2026,1,14)) -> 0 | CI8: =COUNTIFS('DRAFT 2'!$D:$D,$B8,'DRAFT 2'!$A:$A,">="&DATE(2026,1,15),'DRAFT 2'!$A:$A,"<="&DATE(2026,1,21)) -> 0 | CJ8: =COUNTIFS('DRAFT 2'!$D:$D,$B8,'DRAFT 2'!$A:$A,">="&DATE(2026,1,22),'DRAFT 2'!$A:$A,"<"&DATE(2026,IF(1=12,1+1,1+1),1)) -> 0 | CK8: =SUM(CG8:CJ8) -> 0 | CL8: =IF(CM8=0,1,CN8/CM8) -> 1 | CO8: =IF(CP8=0,1,CQ8/CP8) -> 1 | CR8: =IF(CS8=0,1,CT8/CS8) -> 1 | CT8: 0 | CU8: =IFERROR(LOOKUP(2,1/('DRAFT 2'!$D:$D=$B8)*('DRAFT 2'!$A:$A>=DATE(2026,2,1))*('DRAFT 2'!$A:$A<DATE(2026,IF(2=12,2+1,2+1),1)),'DRAFT 2'!$A:$A),"") | CV8: =COUNTIFS('DRAFT 2'!$D:$D,$B8,'DRAFT 2'!$A:$A,">="&DATE(2026,2,1),'DRAFT 2'!$A:$A,"<="&DATE(2026,2,7)) -> 0 | CW8: =COUNTIFS('DRAFT 2'!$D:$D,$B8,'DRAFT 2'!$A:$A,">="&DATE(2026,2,8),'DRAFT 2'!$A:$A,"<="&DATE(2026,2,14)) -> 0 | CX8: =COUNTIFS('DRAFT 2'!$D:$D,$B8,'DRAFT 2'!$A:$A,">="&DATE(2026,2,15),'DRAFT 2'!$A:$A,"<="&DATE(2026,2,21)) -> 0 | CY8: =COUNTIFS('DRAFT 2'!$D:$D,$B8,'DRAFT 2'!$A:$A,">="&DATE(2026,2,22),'DRAFT 2'!$A:$A,"<"&DATE(2026,IF(2=12,2+1,2+1),1)) -> 0 | CZ8: =SUM(CV8:CY8) -> 0 | DA8: =IF(DB8=0,1,DC8/DB8) -> 1 | DD8: =IF(DE8=0,1,DF8/DE8) -> 1 | DG8: =IF(DH8=0,1,DI8/DH8) -> 1 | DJ8: =IFERROR(LOOKUP(2,1/('DRAFT 2'!$D:$D=$B8)*('DRAFT 2'!$A:$A>=DATE(2026,3,1))*('DRAFT 2'!$A:$A<DATE(2026,IF(3=12,3+1,3+1),1)),'DRAFT 2'!$A:$A),"") | DK8: =COUNTIFS('DRAFT 2'!$D:$D,$B8,'DRAFT 2'!$A:$A,">="&DATE(2026,3,1),'DRAFT 2'!$A:$A,"<="&DATE(2026,3,7)) -> 0 | DL8: =COUNTIFS('DRAFT 2'!$D:$D,$B8,'DRAFT 2'!$A:$A,">="&DATE(2026,3,8),'DRAFT 2'!$A:$A,"<="&DATE(2026,3,14)) -> 0 | DM8: =COUNTIFS('DRAFT 2'!$D:$D,$B8,'DRAFT 2'!$A:$A,">="&DATE(2026,3,15),'DRAFT 2'!$A:$A,"<="&DATE(2026,3,21)) -> 0 | DN8: =COUNTIFS('DRAFT 2'!$D:$D,$B8,'DRAFT 2'!$A:$A,">="&DATE(2026,3,22),'DRAFT 2'!$A:$A,"<"&DATE(2026,IF(3=12,3+1,3+1),1)) -> 0 | DO8: =SUM(DK8:DN8) -> 0 | DP8: =AVERAGE(DW8,EL8,FA8) -> 1 | DQ8: =IF(DR8=0,1,DS8/DR8) -> 1 | DT8: =IF(DU8=0,1,DV8/DU8) -> 1 | DW8: =IF(DX8=0,1,DY8/DX8) -> 1 | DZ8: =IFERROR(LOOKUP(2,1/('DRAFT 2'!$D:$D=$B8)*('DRAFT 2'!$A:$A>=DATE(2026,4,1))*('DRAFT 2'!$A:$A<DATE(2026,IF(4=12,4+1,4+1),1)),'DRAFT 2'!$A:$A),"") | EA8: =COUNTIFS('DRAFT 2'!$D:$D,$B8,'DRAFT 2'!$A:$A,">="&DATE(2026,4,1),'DRAFT 2'!$A:$A,"<="&DATE(2026,4,7)) -> 0 | EB8: =COUNTIFS('DRAFT 2'!$D:$D,$B8,'DRAFT 2'!$A:$A,">="&DATE(2026,4,8),'DRAFT 2'!$A:$A,"<="&DATE(2026,4,14)) -> 0 | EC8: =COUNTIFS('DRAFT 2'!$D:$D,$B8,'DRAFT 2'!$A:$A,">="&DATE(2026,4,15),'DRAFT 2'!$A:$A,"<="&DATE(2026,4,21)) -> 0 | ED8: =COUNTIFS('DRAFT 2'!$D:$D,$B8,'DRAFT 2'!$A:$A,">="&DATE(2026,4,22),'DRAFT 2'!$A:$A,"<"&DATE(2026,IF(4=12,4+1,4+1),1)) -> 0 | EE8: =SUM(EA8:ED8) -> 0 | EF8: =IF(EG8=0,1,EH8/EG8) -> 1 | EI8: =IF(EJ8=0,1,EK8/EJ8) -> 1 | EL8: =IF(EM8=0,1,EN8/EM8) -> 1 | EO8: =IFERROR(LOOKUP(2,1/('DRAFT 2'!$D:$D=$B8)*('DRAFT 2'!$A:$A>=DATE(2026,5,1))*('DRAFT 2'!$A:$A<DATE(2026,IF(5=12,5+1,5+1),1)),'DRAFT 2'!$A:$A),"") | EP8: =COUNTIFS('DRAFT 2'!$D:$D,$B8,'DRAFT 2'!$A:$A,">="&DATE(2026,5,1),'DRAFT 2'!$A:$A,"<="&DATE(2026,5,7)) -> 0 | EQ8: =COUNTIFS('DRAFT 2'!$D:$D,$B8,'DRAFT 2'!$A:$A,">="&DATE(2026,5,8),'DRAFT 2'!$A:$A,"<="&DATE(2026,5,14)) -> 0 | ER8: =COUNTIFS('DRAFT 2'!$D:$D,$B8,'DRAFT 2'!$A:$A,">="&DATE(2026,5,15),'DRAFT 2'!$A:$A,"<="&DATE(2026,5,21)) -> 0 | ES8: =COUNTIFS('DRAFT 2'!$D:$D,$B8,'DRAFT 2'!$A:$A,">="&DATE(2026,5,22),'DRAFT 2'!$A:$A,"<"&DATE(2026,IF(5=12,5+1,5+1),1)) -> 0 | ET8: =SUM(EP8:ES8) -> 0 | EU8: =IF(EV8=0,1,EW8/EV8) -> 1 | EX8: =IF(EY8=0,1,EZ8/EY8) -> 1 | FA8: =IF(FB8=0,1,FC8/FB8) -> 1 | FD8: =IFERROR(LOOKUP(2,1/('DRAFT 2'!$D:$D=$B8)*('DRAFT 2'!$A:$A>=DATE(2026,6,1))*('DRAFT 2'!$A:$A<DATE(2026,IF(6=12,6+1,6+1),1)),'DRAFT 2'!$A:$A),"") | FE8: =COUNTIFS('DRAFT 2'!$D:$D,$B8,'DRAFT 2'!$A:$A,">="&DATE(2026,6,1),'DRAFT 2'!$A:$A,"<="&DATE(2026,6,7)) -> 0 | FF8: =COUNTIFS('DRAFT 2'!$D:$D,$B8,'DRAFT 2'!$A:$A,">="&DATE(2026,6,8),'DRAFT 2'!$A:$A,"<="&DATE(2026,6,14)) -> 0 | FG8: =COUNTIFS('DRAFT 2'!$D:$D,$B8,'DRAFT 2'!$A:$A,">="&DATE(2026,6,15),'DRAFT 2'!$A:$A,"<="&DATE(2026,6,21)) -> 0 | FH8: =COUNTIFS('DRAFT 2'!$D:$D,$B8,'DRAFT 2'!$A:$A,">="&DATE(2026,6,22),'DRAFT 2'!$A:$A,"<"&DATE(2026,IF(6=12,6+1,6+1),1)) -> 0 | FI8: =SUM(FE8:FH8) -> 0 | FJ8: =AVERAGE(FQ8,GF8,GU8) -> 1 | FK8: =IF(FL8=0,1,FM8/FL8) -> 1 | FN8: =IF(FO8=0,1,FP8/FO8) -> 1 | FQ8: =IF(FR8=0,1,FS8/FR8) -> 1 | FT8: =IFERROR(LOOKUP(2,1/('DRAFT 2'!$D:$D=$B8)*('DRAFT 2'!$A:$A>=DATE(2026,7,1))*('DRAFT 2'!$A:$A<DATE(2026,IF(7=12,7+1,7+1),1)),'DRAFT 2'!$A:$A),"") | FU8: =COUNTIFS('DRAFT 2'!$D:$D,$B8,'DRAFT 2'!$A:$A,">="&DATE(2026,7,1),'DRAFT 2'!$A:$A,"<="&DATE(2026,7,7)) -> 0 | FV8: =COUNTIFS('DRAFT 2'!$D:$D,$B8,'DRAFT 2'!$A:$A,">="&DATE(2026,7,8),'DRAFT 2'!$A:$A,"<="&DATE(2026,7,14)) -> 0 | FW8: =COUNTIFS('DRAFT 2'!$D:$D,$B8,'DRAFT 2'!$A:$A,">="&DATE(2026,7,15),'DRAFT 2'!$A:$A,"<="&DATE(2026,7,21)) -> 0 | FX8: =COUNTIFS('DRAFT 2'!$D:$D,$B8,'DRAFT 2'!$A:$A,">="&DATE(2026,7,22),'DRAFT 2'!$A:$A,"<"&DATE(2026,IF(7=12,7+1,7+1),1)) -> 0 | FY8: =SUM(FU8:FX8) -> 0 | FZ8: =IF(GA8=0,1,GB8/GA8) -> 1 | GC8: =IF(GD8=0,1,GE8/GD8) -> 1 | GF8: =IF(GG8=0,1,GH8/GG8) -> 1 | GI8: =IFERROR(LOOKUP(2,1/('DRAFT 2'!$D:$D=$B8)*('DRAFT 2'!$A:$A>=DATE(2026,8,1))*('DRAFT 2'!$A:$A<DATE(2026,IF(8=12,8+1,8+1),1)),'DRAFT 2'!$A:$A),"") | GJ8: =COUNTIFS('DRAFT 2'!$D:$D,$B8,'DRAFT 2'!$A:$A,">="&DATE(2026,8,1),'DRAFT 2'!$A:$A,"<="&DATE(2026,8,7)) -> 0 | GK8: =COUNTIFS('DRAFT 2'!$D:$D,$B8,'DRAFT 2'!$A:$A,">="&DATE(2026,8,8),'DRAFT 2'!$A:$A,"<="&DATE(2026,8,14)) -> 0 | GL8: =COUNTIFS('DRAFT 2'!$D:$D,$B8,'DRAFT 2'!$A:$A,">="&DATE(2026,8,15),'DRAFT 2'!$A:$A,"<="&DATE(2026,8,21)) -> 0 | GM8: =COUNTIFS('DRAFT 2'!$D:$D,$B8,'DRAFT 2'!$A:$A,">="&DATE(2026,8,22),'DRAFT 2'!$A:$A,"<"&DATE(2026,IF(8=12,8+1,8+1),1)) -> 0 | GN8: =SUM(GJ8:GM8) -> 0 | GO8: =IF(GP8=0,1,GQ8/GP8) -> 1 | GR8: =IF(GS8=0,1,GT8/GS8) -> 1 | GU8: =IF(GV8=0,1,GW8/GV8) -> 1 | GX8: =IFERROR(LOOKUP(2,1/('DRAFT 2'!$D:$D=$B8)*('DRAFT 2'!$A:$A>=DATE(2026,9,1))*('DRAFT 2'!$A:$A<DATE(2026,IF(9=12,9+1,9+1),1)),'DRAFT 2'!$A:$A),"") | GY8: =COUNTIFS('DRAFT 2'!$D:$D,$B8,'DRAFT 2'!$A:$A,">="&DATE(2026,9,1),'DRAFT 2'!$A:$A,"<="&DATE(2026,9,7)) -> 0 | GZ8: =COUNTIFS('DRAFT 2'!$D:$D,$B8,'DRAFT 2'!$A:$A,">="&DATE(2026,9,8),'DRAFT 2'!$A:$A,"<="&DATE(2026,9,14)) -> 0 | HA8: =COUNTIFS('DRAFT 2'!$D:$D,$B8,'DRAFT 2'!$A:$A,">="&DATE(2026,9,15),'DRAFT 2'!$A:$A,"<="&DATE(2026,9,21)) -> 0 | HB8: =COUNTIFS('DRAFT 2'!$D:$D,$B8,'DRAFT 2'!$A:$A,">="&DATE(2026,9,22),'DRAFT 2'!$A:$A,"<"&DATE(2026,IF(9=12,9+1,9+1),1)) -> 0 | HC8: =SUM(GY8:HB8) -> 0 | HD8: =AVERAGE(HK8,HZ8,IO8) -> 1 | HE8: =IF(HF8=0,1,HG8/HF8) -> 1 | HH8: =IF(HI8=0,1,HJ8/HI8) -> 1 | HK8: =IF(HL8=0,1,HM8/HL8) -> 1 | HN8: =IFERROR(LOOKUP(2,1/('DRAFT 2'!$D:$D=$B8)*('DRAFT 2'!$A:$A>=DATE(2026,10,1))*('DRAFT 2'!$A:$A<DATE(2026,IF(10=12,10+1,10+1),1)),'DRAFT 2'!$A:$A),"") | HO8: =COUNTIFS('DRAFT 2'!$D:$D,$B8,'DRAFT 2'!$A:$A,">="&DATE(2026,10,1),'DRAFT 2'!$A:$A,"<="&DATE(2026,10,7)) -> 0 | HP8: =COUNTIFS('DRAFT 2'!$D:$D,$B8,'DRAFT 2'!$A:$A,">="&DATE(2026,10,8),'DRAFT 2'!$A:$A,"<="&DATE(2026,10,14)) -> 0 | HQ8: =COUNTIFS('DRAFT 2'!$D:$D,$B8,'DRAFT 2'!$A:$A,">="&DATE(2026,10,15),'DRAFT 2'!$A:$A,"<="&DATE(2026,10,21)) -> 0 | HR8: =COUNTIFS('DRAFT 2'!$D:$D,$B8,'DRAFT 2'!$A:$A,">="&DATE(2026,10,22),'DRAFT 2'!$A:$A,"<"&DATE(2026,IF(10=12,10+1,10+1),1)) -> 0 | HS8: =SUM(HO8:HR8) -> 0 | HT8: =IF(HU8=0,1,HV8/HU8) -> 1 | HW8: =IF(HX8=0,1,HY8/HX8) -> 1 | HZ8: =IF(IA8=0,1,IB8/IA8) -> 1 | IC8: =IFERROR(LOOKUP(2,1/('DRAFT 2'!$D:$D=$B8)*('DRAFT 2'!$A:$A>=DATE(2026,11,1))*('DRAFT 2'!$A:$A<DATE(2026,IF(11=12,11+1,11+1),1)),'DRAFT 2'!$A:$A),"") | ID8: =COUNTIFS('DRAFT 2'!$D:$D,$B8,'DRAFT 2'!$A:$A,">="&DATE(2026,11,1),'DRAFT 2'!$A:$A,"<="&DATE(2026,11,7)) -> 0 | IE8: =COUNTIFS('DRAFT 2'!$D:$D,$B8,'DRAFT 2'!$A:$A,">="&DATE(2026,11,8),'DRAFT 2'!$A:$A,"<="&DATE(2026,11,14)) -> 0 | IF8: =COUNTIFS('DRAFT 2'!$D:$D,$B8,'DRAFT 2'!$A:$A,">="&DATE(2026,11,15),'DRAFT 2'!$A:$A,"<="&DATE(2026,11,21)) -> 0 | IG8: =COUNTIFS('DRAFT 2'!$D:$D,$B8,'DRAFT 2'!$A:$A,">="&DATE(2026,11,22),'DRAFT 2'!$A:$A,"<"&DATE(2026,IF(11=12,11+1,11+1),1)) -> 0 | IH8: =SUM(ID8:IG8) -> 0 | II8: =IF(IJ8=0,1,IK8/IJ8) -> 1 | IL8: =IF(IM8=0,1,IN8/IM8) -> 1 | IO8: =IF(IP8=0,1,IQ8/IP8) -> 1 | IR8: =IFERROR(LOOKUP(2,1/('DRAFT 2'!$D:$D=$B8)*('DRAFT 2'!$A:$A>=DATE(2026,12,1))*('DRAFT 2'!$A:$A<DATE(2026,IF(12=12,12+1,12+1),1)),'DRAFT 2'!$A:$A),"") | IS8: =COUNTIFS('DRAFT 2'!$D:$D,$B8,'DRAFT 2'!$A:$A,">="&DATE(2026,12,1),'DRAFT 2'!$A:$A,"<="&DATE(2026,12,7)) -> 0 | IT8: =COUNTIFS('DRAFT 2'!$D:$D,$B8,'DRAFT 2'!$A:$A,">="&DATE(2026,12,8),'DRAFT 2'!$A:$A,"<="&DATE(2026,12,14)) -> 0 | IU8: =COUNTIFS('DRAFT 2'!$D:$D,$B8,'DRAFT 2'!$A:$A,">="&DATE(2026,12,15),'DRAFT 2'!$A:$A,"<="&DATE(2026,12,21)) -> 0 | IV8: =COUNTIFS('DRAFT 2'!$D:$D,$B8,'DRAFT 2'!$A:$A,">="&DATE(2026,12,22),'DRAFT 2'!$A:$A,"<"&DATE(2026,IF(12=12,12+1,12+1),1)) -> 0 | IW8: =SUM(IS8:IV8) -> 0
A9: =IFERROR(INDEX('DRAFT 1'!$A:$A,MATCH($B9,'DRAFT 1'!$B:$B,0)),"") | C9: =IFERROR(INDEX('DRAFT 1'!$C:$C,MATCH($B9,'DRAFT 1'!$B:$B,0)),"") | D9: =IFERROR(INDEX('DRAFT 1'!$D:$D,MATCH($B9,'DRAFT 1'!$B:$B,0)),"") | E9: =IFERROR(INDEX('DRAFT 1'!$E:$E,MATCH($B9,'DRAFT 1'!$B:$B,0)),"") | F9: =IFERROR(INDEX('DRAFT 1'!$F:$F,MATCH($B9,'DRAFT 1'!$B:$B,0)),"") | G9: =IFERROR(INDEX('DRAFT 1'!$G:$G,MATCH($B9,'DRAFT 1'!$B:$B,0)),"") | H9: =IFERROR(INDEX('DRAFT 1'!$H:$H,MATCH($B9,'DRAFT 1'!$B:$B,0)),"") | I9: CIA DA SAUDE | K9: =IFERROR(INDEX('DRAFT 1'!$AL:$AL,MATCH($B9,'DRAFT 1'!$B:$B,0)),"") | L9: =IFERROR(INDEX('DRAFT 1'!$J:$J,MATCH($B9,'DRAFT 1'!$B:$B,0)),"") | M9: =IFERROR(INDEX('DRAFT 1'!$K:$K,MATCH($B9,'DRAFT 1'!$B:$B,0)),"") | N9: EM RISCO | P9: =IFERROR(INDEX('DRAFT 1'!$L:$L,MATCH($B9,'DRAFT 1'!$B:$B,0)),"") | Q9: =IFERROR(INDEX('DRAFT 1'!$M:$M,MATCH($B9,'DRAFT 1'!$B:$B,0)),"") | R9: =IFERROR(INDEX('DRAFT 1'!$N:$N,MATCH($B9,'DRAFT 1'!$B:$B,0)),"") | S9: =IFERROR(INDEX('DRAFT 1'!$O:$O,MATCH($B9,'DRAFT 1'!$B:$B,0)),"") | T9: =IFERROR(INDEX('DRAFT 1'!$P:$P,MATCH($B9,'DRAFT 1'!$B:$B,0)),"") | U9: =IFERROR(INDEX('DRAFT 1'!$Q:$Q,MATCH($B9,'DRAFT 1'!$B:$B,0)),"") | V9: =IFERROR(INDEX('DRAFT 1'!$R:$R,MATCH($B9,'DRAFT 1'!$B:$B,0)),"") | W9: =IFERROR(INDEX('DRAFT 1'!$S:$S,MATCH($B9,'DRAFT 1'!$B:$B,0)),"") | X9: =IFERROR(INDEX('DRAFT 1'!$T:$T,MATCH($B9,'DRAFT 1'!$B:$B,0)),"") | Z9: =IFERROR(INDEX('DRAFT 1'!$U:$U,MATCH($B9,'DRAFT 1'!$B:$B,0)),"") | AA9: =IFERROR(INDEX('DRAFT 1'!$V:$V,MATCH($B9,'DRAFT 1'!$B:$B,0)),"") | AB9: =IFERROR(INDEX('DRAFT 1'!$W:$W,MATCH($B9,'DRAFT 1'!$B:$B,0)),"") | AC9: =IFERROR(INDEX('DRAFT 1'!$X:$X,MATCH($B9,'DRAFT 1'!$B:$B,0)),"") | AD9: =IFERROR(INDEX('DRAFT 1'!$Y:$Y,MATCH($B9,'DRAFT 1'!$B:$B,0)),"") | AE9: =IFERROR(INDEX('DRAFT 1'!$Z:$Z,MATCH($B9,'DRAFT 1'!$B:$B,0)),"") | AF9: =IFERROR(INDEX('DRAFT 1'!$AA:$AA,MATCH($B9,'DRAFT 1'!$B:$B,0)),"") | AG9: =IFERROR(INDEX('DRAFT 1'!$AB:$AB,MATCH($B9,'DRAFT 1'!$B:$B,0)),"") | AH9: =IFERROR(INDEX('DRAFT 1'!$AC:$AC,MATCH($B9,'DRAFT 1'!$B:$B,0)),"") | AI9: =IFERROR(INDEX('DRAFT 1'!$AD:$AD,MATCH($B9,'DRAFT 1'!$B:$B,0)),"") | AJ9: =IFERROR(INDEX('DRAFT 1'!$AE:$AE,MATCH($B9,'DRAFT 1'!$B:$B,0)),"") | AK9: =IFERROR(INDEX('DRAFT 1'!$AG:$AG,MATCH($B9,'DRAFT 1'!$B:$B,0)),"") | AL9: =IFERROR(INDEX('DRAFT 1'!$AH:$AH,MATCH($B9,'DRAFT 1'!$B:$B,0)),"") | AM9: =IFERROR(INDEX('DRAFT 1'!$AI:$AI,MATCH($B9,'DRAFT 1'!$B:$B,0)),"") | AN9: =IFERROR(INDEX('DRAFT 1'!$AJ:$AJ,MATCH($B9,'DRAFT 1'!$B:$B,0)),"") | AO9: =IFERROR(Y9/AN9,0) -> 0 | AP9: =IFERROR(INDEX('DRAFT 1'!$AK:$AK,MATCH($B9,'DRAFT 1'!$B:$B,0)),"") | AR9: PROSPECÇÃO | AS9: =IFERROR(LOOKUP(2,1/('DRAFT 2'!$D:$D=$B9),'DRAFT 2'!$T:$T),"") -> 0 | AT9: =IFERROR(LOOKUP(2,1/('DRAFT 2'!$D:$D=$B9),'DRAFT 2'!$A:$A),"") -> 0 | AU9: =IFERROR(LOOKUP(2,1/('DRAFT 2'!$D:$D=$B9),'DRAFT 2'!$R:$R),"") -> 0 | AV9: =IFERROR(LOOKUP(2,1/('DRAFT 2'!$D:$D=$B9),'DRAFT 2'!$S:$S),"") -> 0 | AW9: LEAD | AX9: =IFERROR(LOOKUP(2,1/('DRAFT 2'!$D:$D=$B9),'DRAFT 2'!$M:$M),"") -> 0 | AY9: =IFERROR(LOOKUP(2,1/('DRAFT 2'!$D:$D=$B9),'DRAFT 2'!$K:$K),"") -> 0 | BG9: =IFERROR(LOOKUP(2,1/('DRAFT 2'!$D:$D=$B9),'DRAFT 2'!$U:$U),"") -> 0 | BH9: =IFERROR(LOOKUP(2,1/('DRAFT 2'!$D:$D=$B9),'DRAFT 2'!$V:$V),"") -> 0 | CE9: =IFERROR(AJ9,0) | CF9: =IFERROR(LOOKUP(2,1/('DRAFT 2'!$D:$D=$B9)*('DRAFT 2'!$A:$A>=DATE(2026,1,1))*('DRAFT 2'!$A:$A<DATE(2026,IF(1=12,1+1,1+1),1)),'DRAFT 2'!$A:$A),"") -> 0 | CG9: =COUNTIFS('DRAFT 2'!$D:$D,$B9,'DRAFT 2'!$A:$A,">="&DATE(2026,1,1),'DRAFT 2'!$A:$A,"<="&DATE(2026,1,7)) -> 0 | CH9: =COUNTIFS('DRAFT 2'!$D:$D,$B9,'DRAFT 2'!$A:$A,">="&DATE(2026,1,8),'DRAFT 2'!$A:$A,"<="&DATE(2026,1,14)) -> 0 | CI9: =COUNTIFS('DRAFT 2'!$D:$D,$B9,'DRAFT 2'!$A:$A,">="&DATE(2026,1,15),'DRAFT 2'!$A:$A,"<="&DATE(2026,1,21)) -> 0 | CJ9: =COUNTIFS('DRAFT 2'!$D:$D,$B9,'DRAFT 2'!$A:$A,">="&DATE(2026,1,22),'DRAFT 2'!$A:$A,"<"&DATE(2026,IF(1=12,1+1,1+1),1)) -> 0 | CK9: =SUM(CG9:CJ9) -> 0 | CT9: 0 | CU9: =IFERROR(LOOKUP(2,1/('DRAFT 2'!$D:$D=$B9)*('DRAFT 2'!$A:$A>=DATE(2026,2,1))*('DRAFT 2'!$A:$A<DATE(2026,IF(2=12,2+1,2+1),1)),'DRAFT 2'!$A:$A),"") -> 0 | CV9: =COUNTIFS('DRAFT 2'!$D:$D,$B9,'DRAFT 2'!$A:$A,">="&DATE(2026,2,1),'DRAFT 2'!$A:$A,"<="&DATE(2026,2,7)) -> 0 | CW9: =COUNTIFS('DRAFT 2'!$D:$D,$B9,'DRAFT 2'!$A:$A,">="&DATE(2026,2,8),'DRAFT 2'!$A:$A,"<="&DATE(2026,2,14)) -> 0 | CX9: =COUNTIFS('DRAFT 2'!$D:$D,$B9,'DRAFT 2'!$A:$A,">="&DATE(2026,2,15),'DRAFT 2'!$A:$A,"<="&DATE(2026,2,21)) -> 0 | CY9: =COUNTIFS('DRAFT 2'!$D:$D,$B9,'DRAFT 2'!$A:$A,">="&DATE(2026,2,22),'DRAFT 2'!$A:$A,"<"&DATE(2026,IF(2=12,2+1,2+1),1)) -> 0 | CZ9: =SUM(CV9:CY9) -> 0 | DJ9: =IFERROR(LOOKUP(2,1/('DRAFT 2'!$D:$D=$B9)*('DRAFT 2'!$A:$A>=DATE(2026,3,1))*('DRAFT 2'!$A:$A<DATE(2026,IF(3=12,3+1,3+1),1)),'DRAFT 2'!$A:$A),"") -> 0 | DK9: =COUNTIFS('DRAFT 2'!$D:$D,$B9,'DRAFT 2'!$A:$A,">="&DATE(2026,3,1),'DRAFT 2'!$A:$A,"<="&DATE(2026,3,7)) -> 0 | DL9: =COUNTIFS('DRAFT 2'!$D:$D,$B9,'DRAFT 2'!$A:$A,">="&DATE(2026,3,8),'DRAFT 2'!$A:$A,"<="&DATE(2026,3,14)) -> 0 | DM9: =COUNTIFS('DRAFT 2'!$D:$D,$B9,'DRAFT 2'!$A:$A,">="&DATE(2026,3,15),'DRAFT 2'!$A:$A,"<="&DATE(2026,3,21)) -> 0 | DN9: =COUNTIFS('DRAFT 2'!$D:$D,$B9,'DRAFT 2'!$A:$A,">="&DATE(2026,3,22),'DRAFT 2'!$A:$A,"<"&DATE(2026,IF(3=12,3+1,3+1),1)) -> 0 | DO9: =SUM(DK9:DN9) -> 0 | DZ9: =IFERROR(LOOKUP(2,1/('DRAFT 2'!$D:$D=$B9)*('DRAFT 2'!$A:$A>=DATE(2026,4,1))*('DRAFT 2'!$A:$A<DATE(2026,IF(4=12,4+1,4+1),1)),'DRAFT 2'!$A:$A),"") -> 0 | EA9: =COUNTIFS('DRAFT 2'!$D:$D,$B9,'DRAFT 2'!$A:$A,">="&DATE(2026,4,1),'DRAFT 2'!$A:$A,"<="&DATE(2026,4,7)) -> 0 | EB9: =COUNTIFS('DRAFT 2'!$D:$D,$B9,'DRAFT 2'!$A:$A,">="&DATE(2026,4,8),'DRAFT 2'!$A:$A,"<="&DATE(2026,4,14)) -> 0 | EC9: =COUNTIFS('DRAFT 2'!$D:$D,$B9,'DRAFT 2'!$A:$A,">="&DATE(2026,4,15),'DRAFT 2'!$A:$A,"<="&DATE(2026,4,21)) -> 0 | ED9: =COUNTIFS('DRAFT 2'!$D:$D,$B9,'DRAFT 2'!$A:$A,">="&DATE(2026,4,22),'DRAFT 2'!$A:$A,"<"&DATE(2026,IF(4=12,4+1,4+1),1)) -> 0 | EE9: =SUM(EA9:ED9) -> 0 | EO9: =IFERROR(LOOKUP(2,1/('DRAFT 2'!$D:$D=$B9)*('DRAFT 2'!$A:$A>=DATE(2026,5,1))*('DRAFT 2'!$A:$A<DATE(2026,IF(5=12,5+1,5+1),1)),'DRAFT 2'!$A:$A),"") -> 0 | EP9: =COUNTIFS('DRAFT 2'!$D:$D,$B9,'DRAFT 2'!$A:$A,">="&DATE(2026,5,1),'DRAFT 2'!$A:$A,"<="&DATE(2026,5,7)) -> 0 | EQ9: =COUNTIFS('DRAFT 2'!$D:$D,$B9,'DRAFT 2'!$A:$A,">="&DATE(2026,5,8),'DRAFT 2'!$A:$A,"<="&DATE(2026,5,14)) -> 0 | ER9: =COUNTIFS('DRAFT 2'!$D:$D,$B9,'DRAFT 2'!$A:$A,">="&DATE(2026,5,15),'DRAFT 2'!$A:$A,"<="&DATE(2026,5,21)) -> 0 | ES9: =COUNTIFS('DRAFT 2'!$D:$D,$B9,'DRAFT 2'!$A:$A,">="&DATE(2026,5,22),'DRAFT 2'!$A:$A,"<"&DATE(2026,IF(5=12,5+1,5+1),1)) -> 0 | ET9: =SUM(EP9:ES9) -> 0 | FD9: =IFERROR(LOOKUP(2,1/('DRAFT 2'!$D:$D=$B9)*('DRAFT 2'!$A:$A>=DATE(2026,6,1))*('DRAFT 2'!$A:$A<DATE(2026,IF(6=12,6+1,6+1),1)),'DRAFT 2'!$A:$A),"") -> 0 | FE9: =COUNTIFS('DRAFT 2'!$D:$D,$B9,'DRAFT 2'!$A:$A,">="&DATE(2026,6,1),'DRAFT 2'!$A:$A,"<="&DATE(2026,6,7)) -> 0 | FF9: =COUNTIFS('DRAFT 2'!$D:$D,$B9,'DRAFT 2'!$A:$A,">="&DATE(2026,6,8),'DRAFT 2'!$A:$A,"<="&DATE(2026,6,14)) -> 0 | FG9: =COUNTIFS('DRAFT 2'!$D:$D,$B9,'DRAFT 2'!$A:$A,">="&DATE(2026,6,15),'DRAFT 2'!$A:$A,"<="&DATE(2026,6,21)) -> 0 | FH9: =COUNTIFS('DRAFT 2'!$D:$D,$B9,'DRAFT 2'!$A:$A,">="&DATE(2026,6,22),'DRAFT 2'!$A:$A,"<"&DATE(2026,IF(6=12,6+1,6+1),1)) -> 0 | FI9: =SUM(FE9:FH9) -> 0 | FT9: =IFERROR(LOOKUP(2,1/('DRAFT 2'!$D:$D=$B9)*('DRAFT 2'!$A:$A>=DATE(2026,7,1))*('DRAFT 2'!$A:$A<DATE(2026,IF(7=12,7+1,7+1),1)),'DRAFT 2'!$A:$A),"") -> 0 | FU9: =COUNTIFS('DRAFT 2'!$D:$D,$B9,'DRAFT 2'!$A:$A,">="&DATE(2026,7,1),'DRAFT 2'!$A:$A,"<="&DATE(2026,7,7)) -> 0 | FV9: =COUNTIFS('DRAFT 2'!$D:$D,$B9,'DRAFT 2'!$A:$A,">="&DATE(2026,7,8),'DRAFT 2'!$A:$A,"<="&DATE(2026,7,14)) -> 0 | FW9: =COUNTIFS('DRAFT 2'!$D:$D,$B9,'DRAFT 2'!$A:$A,">="&DATE(2026,7,15),'DRAFT 2'!$A:$A,"<="&DATE(2026,7,21)) -> 0 | FX9: =COUNTIFS('DRAFT 2'!$D:$D,$B9,'DRAFT 2'!$A:$A,">="&DATE(2026,7,22),'DRAFT 2'!$A:$A,"<"&DATE(2026,IF(7=12,7+1,7+1),1)) -> 0 | FY9: =SUM(FU9:FX9) -> 0 | GI9: =IFERROR(LOOKUP(2,1/('DRAFT 2'!$D:$D=$B9)*('DRAFT 2'!$A:$A>=DATE(2026,8,1))*('DRAFT 2'!$A:$A<DATE(2026,IF(8=12,8+1,8+1),1)),'DRAFT 2'!$A:$A),"") -> 0 | GJ9: =COUNTIFS('DRAFT 2'!$D:$D,$B9,'DRAFT 2'!$A:$A,">="&DATE(2026,8,1),'DRAFT 2'!$A:$A,"<="&DATE(2026,8,7)) -> 0 | GK9: =COUNTIFS('DRAFT 2'!$D:$D,$B9,'DRAFT 2'!$A:$A,">="&DATE(2026,8,8),'DRAFT 2'!$A:$A,"<="&DATE(2026,8,14)) -> 0 | GL9: =COUNTIFS('DRAFT 2'!$D:$D,$B9,'DRAFT 2'!$A:$A,">="&DATE(2026,8,15),'DRAFT 2'!$A:$A,"<="&DATE(2026,8,21)) -> 0 | GM9: =COUNTIFS('DRAFT 2'!$D:$D,$B9,'DRAFT 2'!$A:$A,">="&DATE(2026,8,22),'DRAFT 2'!$A:$A,"<"&DATE(2026,IF(8=12,8+1,8+1),1)) -> 0 | GN9: =SUM(GJ9:GM9) -> 0 | GX9: =IFERROR(LOOKUP(2,1/('DRAFT 2'!$D:$D=$B9)*('DRAFT 2'!$A:$A>=DATE(2026,9,1))*('DRAFT 2'!$A:$A<DATE(2026,IF(9=12,9+1,9+1),1)),'DRAFT 2'!$A:$A),"") -> 0 | GY9: =COUNTIFS('DRAFT 2'!$D:$D,$B9,'DRAFT 2'!$A:$A,">="&DATE(2026,9,1),'DRAFT 2'!$A:$A,"<="&DATE(2026,9,7)) -> 0 | GZ9: =COUNTIFS('DRAFT 2'!$D:$D,$B9,'DRAFT 2'!$A:$A,">="&DATE(2026,9,8),'DRAFT 2'!$A:$A,"<="&DATE(2026,9,14)) -> 0 | HA9: =COUNTIFS('DRAFT 2'!$D:$D,$B9,'DRAFT 2'!$A:$A,">="&DATE(2026,9,15),'DRAFT 2'!$A:$A,"<="&DATE(2026,9,21)) -> 0 | HB9: =COUNTIFS('DRAFT 2'!$D:$D,$B9,'DRAFT 2'!$A:$A,">="&DATE(2026,9,22),'DRAFT 2'!$A:$A,"<"&DATE(2026,IF(9=12,9+1,9+1),1)) -> 0 | HC9: =SUM(GY9:HB9) -> 0 | HN9: =IFERROR(LOOKUP(2,1/('DRAFT 2'!$D:$D=$B9)*('DRAFT 2'!$A:$A>=DATE(2026,10,1))*('DRAFT 2'!$A:$A<DATE(2026,IF(10=12,10+1,10+1),1)),'DRAFT 2'!$A:$A),"") -> 0 | HO9: =COUNTIFS('DRAFT 2'!$D:$D,$B9,'DRAFT 2'!$A:$A,">="&DATE(2026,10,1),'DRAFT 2'!$A:$A,"<="&DATE(2026,10,7)) -> 0 | HP9: =COUNTIFS('DRAFT 2'!$D:$D,$B9,'DRAFT 2'!$A:$A,">="&DATE(2026,10,8),'DRAFT 2'!$A:$A,"<="&DATE(2026,10,14)) -> 0 | HQ9: =COUNTIFS('DRAFT 2'!$D:$D,$B9,'DRAFT 2'!$A:$A,">="&DATE(2026,10,15),'DRAFT 2'!$A:$A,"<="&DATE(2026,10,21)) -> 0 | HR9: =COUNTIFS('DRAFT 2'!$D:$D,$B9,'DRAFT 2'!$A:$A,">="&DATE(2026,10,22),'DRAFT 2'!$A:$A,"<"&DATE(2026,IF(10=12,10+1,10+1),1)) -> 0 | HS9: =SUM(HO9:HR9) -> 0 | IC9: =IFERROR(LOOKUP(2,1/('DRAFT 2'!$D:$D=$B9)*('DRAFT 2'!$A:$A>=DATE(2026,11,1))*('DRAFT 2'!$A:$A<DATE(2026,IF(11=12,11+1,11+1),1)),'DRAFT 2'!$A:$A),"") -> 0 | ID9: =COUNTIFS('DRAFT 2'!$D:$D,$B9,'DRAFT 2'!$A:$A,">="&DATE(2026,11,1),'DRAFT 2'!$A:$A,"<="&DATE(2026,11,7)) -> 0 | IE9: =COUNTIFS('DRAFT 2'!$D:$D,$B9,'DRAFT 2'!$A:$A,">="&DATE(2026,11,8),'DRAFT 2'!$A:$A,"<="&DATE(2026,11,14)) -> 0 | IF9: =COUNTIFS('DRAFT 2'!$D:$D,$B9,'DRAFT 2'!$A:$A,">="&DATE(2026,11,15),'DRAFT 2'!$A:$A,"<="&DATE(2026,11,21)) -> 0 | IG9: =COUNTIFS('DRAFT 2'!$D:$D,$B9,'DRAFT 2'!$A:$A,">="&DATE(2026,11,22),'DRAFT 2'!$A:$A,"<"&DATE(2026,IF(11=12,11+1,11+1),1)) -> 0 | IH9: =SUM(ID9:IG9) -> 0 | IR9: =IFERROR(LOOKUP(2,1/('DRAFT 2'!$D:$D=$B9)*('DRAFT 2'!$A:$A>=DATE(2026,12,1))*('DRAFT 2'!$A:$A<DATE(2026,IF(12=12,12+1,12+1),1)),'DRAFT 2'!$A:$A),"") -> 0 | IS9: =COUNTIFS('DRAFT 2'!$D:$D,$B9,'DRAFT 2'!$A:$A,">="&DATE(2026,12,1),'DRAFT 2'!$A:$A,"<="&DATE(2026,12,7)) -> 0 | IT9: =COUNTIFS('DRAFT 2'!$D:$D,$B9,'DRAFT 2'!$A:$A,">="&DATE(2026,12,8),'DRAFT 2'!$A:$A,"<="&DATE(2026,12,14)) -> 0 | IU9: =COUNTIFS('DRAFT 2'!$D:$D,$B9,'DRAFT 2'!$A:$A,">="&DATE(2026,12,15),'DRAFT 2'!$A:$A,"<="&DATE(2026,12,21)) -> 0 | IV9: =COUNTIFS('DRAFT 2'!$D:$D,$B9,'DRAFT 2'!$A:$A,">="&DATE(2026,12,22),'DRAFT 2'!$A:$A,"<"&DATE(2026,IF(12=12,12+1,12+1),1)) -> 0 | IW9: =SUM(IS9:IV9) -> 0
A10: =IFERROR(INDEX('DRAFT 1'!$A:$A,MATCH($B10,'DRAFT 1'!$B:$B,0)),"") | C10: =IFERROR(INDEX('DRAFT 1'!$C:$C,MATCH($B10,'DRAFT 1'!$B:$B,0)),"") | D10: =IFERROR(INDEX('DRAFT 1'!$D:$D,MATCH($B10,'DRAFT 1'!$B:$B,0)),"") | E10: =IFERROR(INDEX('DRAFT 1'!$E:$E,MATCH($B10,'DRAFT 1'!$B:$B,0)),"") | F10: =IFERROR(INDEX('DRAFT 1'!$F:$F,MATCH($B10,'DRAFT 1'!$B:$B,0)),"") | G10: =IFERROR(INDEX('DRAFT 1'!$G:$G,MATCH($B10,'DRAFT 1'!$B:$B,0)),"") | H10: =IFERROR(INDEX('DRAFT 1'!$H:$H,MATCH($B10,'DRAFT 1'!$B:$B,0)),"") | I10: VIDA LEVE | K10: =IFERROR(INDEX('DRAFT 1'!$AL:$AL,MATCH($B10,'DRAFT 1'!$B:$B,0)),"") | L10: =IFERROR(INDEX('DRAFT 1'!$J:$J,MATCH($B10,'DRAFT 1'!$B:$B,0)),"") | M10: =IFERROR(INDEX('DRAFT 1'!$K:$K,MATCH($B10,'DRAFT 1'!$B:$B,0)),"") | N10: ATIVO | P10: =IFERROR(INDEX('DRAFT 1'!$L:$L,MATCH($B10,'DRAFT 1'!$B:$B,0)),"") | Q10: =IFERROR(INDEX('DRAFT 1'!$M:$M,MATCH($B10,'DRAFT 1'!$B:$B,0)),"") | R10: =IFERROR(INDEX('DRAFT 1'!$N:$N,MATCH($B10,'DRAFT 1'!$B:$B,0)),"") | S10: =IFERROR(INDEX('DRAFT 1'!$O:$O,MATCH($B10,'DRAFT 1'!$B:$B,0)),"") | T10: =IFERROR(INDEX('DRAFT 1'!$P:$P,MATCH($B10,'DRAFT 1'!$B:$B,0)),"") | U10: =IFERROR(INDEX('DRAFT 1'!$Q:$Q,MATCH($B10,'DRAFT 1'!$B:$B,0)),"") | V10: =IFERROR(INDEX('DRAFT 1'!$R:$R,MATCH($B10,'DRAFT 1'!$B:$B,0)),"") | W10: =IFERROR(INDEX('DRAFT 1'!$S:$S,MATCH($B10,'DRAFT 1'!$B:$B,0)),"") | X10: =IFERROR(INDEX('DRAFT 1'!$T:$T,MATCH($B10,'DRAFT 1'!$B:$B,0)),"") | Z10: =IFERROR(INDEX('DRAFT 1'!$U:$U,MATCH($B10,'DRAFT 1'!$B:$B,0)),"") | AA10: =IFERROR(INDEX('DRAFT 1'!$V:$V,MATCH($B10,'DRAFT 1'!$B:$B,0)),"") | AB10: =IFERROR(INDEX('DRAFT 1'!$W:$W,MATCH($B10,'DRAFT 1'!$B:$B,0)),"") | AC10: =IFERROR(INDEX('DRAFT 1'!$X:$X,MATCH($B10,'DRAFT 1'!$B:$B,0)),"") | AD10: =IFERROR(INDEX('DRAFT 1'!$Y:$Y,MATCH($B10,'DRAFT 1'!$B:$B,0)),"") | AE10: =IFERROR(INDEX('DRAFT 1'!$Z:$Z,MATCH($B10,'DRAFT 1'!$B:$B,0)),"") | AF10: =IFERROR(INDEX('DRAFT 1'!$AA:$AA,MATCH($B10,'DRAFT 1'!$B:$B,0)),"") | AG10: =IFERROR(INDEX('DRAFT 1'!$AB:$AB,MATCH($B10,'DRAFT 1'!$B:$B,0)),"") | AH10: =IFERROR(INDEX('DRAFT 1'!$AC:$AC,MATCH($B10,'DRAFT 1'!$B:$B,0)),"") | AI10: =IFERROR(INDEX('DRAFT 1'!$AD:$AD,MATCH($B10,'DRAFT 1'!$B:$B,0)),"") | AJ10: =IFERROR(INDEX('DRAFT 1'!$AE:$AE,MATCH($B10,'DRAFT 1'!$B:$B,0)),"") | AK10: =IFERROR(INDEX('DRAFT 1'!$AG:$AG,MATCH($B10,'DRAFT 1'!$B:$B,0)),"") | AL10: =IFERROR(INDEX('DRAFT 1'!$AH:$AH,MATCH($B10,'DRAFT 1'!$B:$B,0)),"") | AM10: =IFERROR(INDEX('DRAFT 1'!$AI:$AI,MATCH($B10,'DRAFT 1'!$B:$B,0)),"") | AN10: =IFERROR(INDEX('DRAFT 1'!$AJ:$AJ,MATCH($B10,'DRAFT 1'!$B:$B,0)),"") | AO10: =IFERROR(Y10/AN10,0) -> 0 | AP10: =IFERROR(INDEX('DRAFT 1'!$AK:$AK,MATCH($B10,'DRAFT 1'!$B:$B,0)),"") | AR10: RECOMPRA | AS10: =IFERROR(LOOKUP(2,1/('DRAFT 2'!$D:$D=$B10),'DRAFT 2'!$T:$T),"") -> 0 | AT10: =IFERROR(LOOKUP(2,1/('DRAFT 2'!$D:$D=$B10),'DRAFT 2'!$A:$A),"") -> 0 | AU10: =IFERROR(LOOKUP(2,1/('DRAFT 2'!$D:$D=$B10),'DRAFT 2'!$R:$R),"") -> 0 | AV10: =IFERROR(LOOKUP(2,1/('DRAFT 2'!$D:$D=$B10),'DRAFT 2'!$S:$S),"") -> 0 | AW10: NOVO | AX10: =IFERROR(LOOKUP(2,1/('DRAFT 2'!$D:$D=$B10),'DRAFT 2'!$M:$M),"") -> 0 | AY10: =IFERROR(LOOKUP(2,1/('DRAFT 2'!$D:$D=$B10),'DRAFT 2'!$K:$K),"") -> 0 | BG10: =IFERROR(LOOKUP(2,1/('DRAFT 2'!$D:$D=$B10),'DRAFT 2'!$U:$U),"") -> 0 | BH10: =IFERROR(LOOKUP(2,1/('DRAFT 2'!$D:$D=$B10),'DRAFT 2'!$V:$V),"") -> 0 | CE10: =IFERROR(AJ10,0) | CF10: =IFERROR(LOOKUP(2,1/('DRAFT 2'!$D:$D=$B10)*('DRAFT 2'!$A:$A>=DATE(2026,1,1))*('DRAFT 2'!$A:$A<DATE(2026,IF(1=12,1+1,1+1),1)),'DRAFT 2'!$A:$A),"") -> 0 | CG10: =COUNTIFS('DRAFT 2'!$D:$D,$B10,'DRAFT 2'!$A:$A,">="&DATE(2026,1,1),'DRAFT 2'!$A:$A,"<="&DATE(2026,1,7)) -> 0 | CH10: =COUNTIFS('DRAFT 2'!$D:$D,$B10,'DRAFT 2'!$A:$A,">="&DATE(2026,1,8),'DRAFT 2'!$A:$A,"<="&DATE(2026,1,14)) -> 0 | CI10: =COUNTIFS('DRAFT 2'!$D:$D,$B10,'DRAFT 2'!$A:$A,">="&DATE(2026,1,15),'DRAFT 2'!$A:$A,"<="&DATE(2026,1,21)) -> 0 | CJ10: =COUNTIFS('DRAFT 2'!$D:$D,$B10,'DRAFT 2'!$A:$A,">="&DATE(2026,1,22),'DRAFT 2'!$A:$A,"<"&DATE(2026,IF(1=12,1+1,1+1),1)) -> 0 | CK10: =SUM(CG10:CJ10) -> 0 | CT10: 0 | CU10: =IFERROR(LOOKUP(2,1/('DRAFT 2'!$D:$D=$B10)*('DRAFT 2'!$A:$A>=DATE(2026,2,1))*('DRAFT 2'!$A:$A<DATE(2026,IF(2=12,2+1,2+1),1)),'DRAFT 2'!$A:$A),"") -> 0 | CV10: =COUNTIFS('DRAFT 2'!$D:$D,$B10,'DRAFT 2'!$A:$A,">="&DATE(2026,2,1),'DRAFT 2'!$A:$A,"<="&DATE(2026,2,7)) -> 0 | CW10: =COUNTIFS('DRAFT 2'!$D:$D,$B10,'DRAFT 2'!$A:$A,">="&DATE(2026,2,8),'DRAFT 2'!$A:$A,"<="&DATE(2026,2,14)) -> 0 | CX10: =COUNTIFS('DRAFT 2'!$D:$D,$B10,'DRAFT 2'!$A:$A,">="&DATE(2026,2,15),'DRAFT 2'!$A:$A,"<="&DATE(2026,2,21)) -> 0 | CY10: =COUNTIFS('DRAFT 2'!$D:$D,$B10,'DRAFT 2'!$A:$A,">="&DATE(2026,2,22),'DRAFT 2'!$A:$A,"<"&DATE(2026,IF(2=12,2+1,2+1),1)) -> 0 | CZ10: =SUM(CV10:CY10) -> 0 | DJ10: =IFERROR(LOOKUP(2,1/('DRAFT 2'!$D:$D=$B10)*('DRAFT 2'!$A:$A>=DATE(2026,3,1))*('DRAFT 2'!$A:$A<DATE(2026,IF(3=12,3+1,3+1),1)),'DRAFT 2'!$A:$A),"") -> 0 | DK10: =COUNTIFS('DRAFT 2'!$D:$D,$B10,'DRAFT 2'!$A:$A,">="&DATE(2026,3,1),'DRAFT 2'!$A:$A,"<="&DATE(2026,3,7)) -> 0 | DL10: =COUNTIFS('DRAFT 2'!$D:$D,$B10,'DRAFT 2'!$A:$A,">="&DATE(2026,3,8),'DRAFT 2'!$A:$A,"<="&DATE(2026,3,14)) -> 0 | DM10: =COUNTIFS('DRAFT 2'!$D:$D,$B10,'DRAFT 2'!$A:$A,">="&DATE(2026,3,15),'DRAFT 2'!$A:$A,"<="&DATE(2026,3,21)) -> 0 | DN10: =COUNTIFS('DRAFT 2'!$D:$D,$B10,'DRAFT 2'!$A:$A,">="&DATE(2026,3,22),'DRAFT 2'!$A:$A,"<"&DATE(2026,IF(3=12,3+1,3+1),1)) -> 0 | DO10: =SUM(DK10:DN10) -> 0 | DZ10: =IFERROR(LOOKUP(2,1/('DRAFT 2'!$D:$D=$B10)*('DRAFT 2'!$A:$A>=DATE(2026,4,1))*('DRAFT 2'!$A:$A<DATE(2026,IF(4=12,4+1,4+1),1)),'DRAFT 2'!$A:$A),"") -> 0 | EA10: =COUNTIFS('DRAFT 2'!$D:$D,$B10,'DRAFT 2'!$A:$A,">="&DATE(2026,4,1),'DRAFT 2'!$A:$A,"<="&DATE(2026,4,7)) -> 0 | EB10: =COUNTIFS('DRAFT 2'!$D:$D,$B10,'DRAFT 2'!$A:$A,">="&DATE(2026,4,8),'DRAFT 2'!$A:$A,"<="&DATE(2026,4,14)) -> 0 | EC10: =COUNTIFS('DRAFT 2'!$D:$D,$B10,'DRAFT 2'!$A:$A,">="&DATE(2026,4,15),'DRAFT 2'!$A:$A,"<="&DATE(2026,4,21)) -> 0 | ED10: =COUNTIFS('DRAFT 2'!$D:$D,$B10,'DRAFT 2'!$A:$A,">="&DATE(2026,4,22),'DRAFT 2'!$A:$A,"<"&DATE(2026,IF(4=12,4+1,4+1),1)) -> 0 | EE10: =SUM(EA10:ED10) -> 0 | EO10: =IFERROR(LOOKUP(2,1/('DRAFT 2'!$D:$D=$B10)*('DRAFT 2'!$A:$A>=DATE(2026,5,1))*('DRAFT 2'!$A:$A<DATE(2026,IF(5=12,5+1,5+1),1)),'DRAFT 2'!$A:$A),"") -> 0 | EP10: =COUNTIFS('DRAFT 2'!$D:$D,$B10,'DRAFT 2'!$A:$A,">="&DATE(2026,5,1),'DRAFT 2'!$A:$A,"<="&DATE(2026,5,7)) -> 0 | EQ10: =COUNTIFS('DRAFT 2'!$D:$D,$B10,'DRAFT 2'!$A:$A,">="&DATE(2026,5,8),'DRAFT 2'!$A:$A,"<="&DATE(2026,5,14)) -> 0 | ER10: =COUNTIFS('DRAFT 2'!$D:$D,$B10,'DRAFT 2'!$A:$A,">="&DATE(2026,5,15),'DRAFT 2'!$A:$A,"<="&DATE(2026,5,21)) -> 0 | ES10: =COUNTIFS('DRAFT 2'!$D:$D,$B10,'DRAFT 2'!$A:$A,">="&DATE(2026,5,22),'DRAFT 2'!$A:$A,"<"&DATE(2026,IF(5=12,5+1,5+1),1)) -> 0 | ET10: =SUM(EP10:ES10) -> 0 | FD10: =IFERROR(LOOKUP(2,1/('DRAFT 2'!$D:$D=$B10)*('DRAFT 2'!$A:$A>=DATE(2026,6,1))*('DRAFT 2'!$A:$A<DATE(2026,IF(6=12,6+1,6+1),1)),'DRAFT 2'!$A:$A),"") -> 0 | FE10: =COUNTIFS('DRAFT 2'!$D:$D,$B10,'DRAFT 2'!$A:$A,">="&DATE(2026,6,1),'DRAFT 2'!$A:$A,"<="&DATE(2026,6,7)) -> 0 | FF10: =COUNTIFS('DRAFT 2'!$D:$D,$B10,'DRAFT 2'!$A:$A,">="&DATE(2026,6,8),'DRAFT 2'!$A:$A,"<="&DATE(2026,6,14)) -> 0 | FG10: =COUNTIFS('DRAFT 2'!$D:$D,$B10,'DRAFT 2'!$A:$A,">="&DATE(2026,6,15),'DRAFT 2'!$A:$A,"<="&DATE(2026,6,21)) -> 0 | FH10: =COUNTIFS('DRAFT 2'!$D:$D,$B10,'DRAFT 2'!$A:$A,">="&DATE(2026,6,22),'DRAFT 2'!$A:$A,"<"&DATE(2026,IF(6=12,6+1,6+1),1)) -> 0 | FI10: =SUM(FE10:FH10) -> 0 | FT10: =IFERROR(LOOKUP(2,1/('DRAFT 2'!$D:$D=$B10)*('DRAFT 2'!$A:$A>=DATE(2026,7,1))*('DRAFT 2'!$A:$A<DATE(2026,IF(7=12,7+1,7+1),1)),'DRAFT 2'!$A:$A),"") -> 0 | FU10: =COUNTIFS('DRAFT 2'!$D:$D,$B10,'DRAFT 2'!$A:$A,">="&DATE(2026,7,1),'DRAFT 2'!$A:$A,"<="&DATE(2026,7,7)) -> 0 | FV10: =COUNTIFS('DRAFT 2'!$D:$D,$B10,'DRAFT 2'!$A:$A,">="&DATE(2026,7,8),'DRAFT 2'!$A:$A,"<="&DATE(2026,7,14)) -> 0 | FW10: =COUNTIFS('DRAFT 2'!$D:$D,$B10,'DRAFT 2'!$A:$A,">="&DATE(2026,7,15),'DRAFT 2'!$A:$A,"<="&DATE(2026,7,21)) -> 0 | FX10: =COUNTIFS('DRAFT 2'!$D:$D,$B10,'DRAFT 2'!$A:$A,">="&DATE(2026,7,22),'DRAFT 2'!$A:$A,"<"&DATE(2026,IF(7=12,7+1,7+1),1)) -> 0 | FY10: =SUM(FU10:FX10) -> 0 | GI10: =IFERROR(LOOKUP(2,1/('DRAFT 2'!$D:$D=$B10)*('DRAFT 2'!$A:$A>=DATE(2026,8,1))*('DRAFT 2'!$A:$A<DATE(2026,IF(8=12,8+1,8+1),1)),'DRAFT 2'!$A:$A),"") -> 0 | GJ10: =COUNTIFS('DRAFT 2'!$D:$D,$B10,'DRAFT 2'!$A:$A,">="&DATE(2026,8,1),'DRAFT 2'!$A:$A,"<="&DATE(2026,8,7)) -> 0 | GK10: =COUNTIFS('DRAFT 2'!$D:$D,$B10,'DRAFT 2'!$A:$A,">="&DATE(2026,8,8),'DRAFT 2'!$A:$A,"<="&DATE(2026,8,14)) -> 0 | GL10: =COUNTIFS('DRAFT 2'!$D:$D,$B10,'DRAFT 2'!$A:$A,">="&DATE(2026,8,15),'DRAFT 2'!$A:$A,"<="&DATE(2026,8,21)) -> 0 | GM10: =COUNTIFS('DRAFT 2'!$D:$D,$B10,'DRAFT 2'!$A:$A,">="&DATE(2026,8,22),'DRAFT 2'!$A:$A,"<"&DATE(2026,IF(8=12,8+1,8+1),1)) -> 0 | GN10: =SUM(GJ10:GM10) -> 0 | GX10: =IFERROR(LOOKUP(2,1/('DRAFT 2'!$D:$D=$B10)*('DRAFT 2'!$A:$A>=DATE(2026,9,1))*('DRAFT 2'!$A:$A<DATE(2026,IF(9=12,9+1,9+1),1)),'DRAFT 2'!$A:$A),"") -> 0 | GY10: =COUNTIFS('DRAFT 2'!$D:$D,$B10,'DRAFT 2'!$A:$A,">="&DATE(2026,9,1),'DRAFT 2'!$A:$A,"<="&DATE(2026,9,7)) -> 0 | GZ10: =COUNTIFS('DRAFT 2'!$D:$D,$B10,'DRAFT 2'!$A:$A,">="&DATE(2026,9,8),'DRAFT 2'!$A:$A,"<="&DATE(2026,9,14)) -> 0 | HA10: =COUNTIFS('DRAFT 2'!$D:$D,$B10,'DRAFT 2'!$A:$A,">="&DATE(2026,9,15),'DRAFT 2'!$A:$A,"<="&DATE(2026,9,21)) -> 0 | HB10: =COUNTIFS('DRAFT 2'!$D:$D,$B10,'DRAFT 2'!$A:$A,">="&DATE(2026,9,22),'DRAFT 2'!$A:$A,"<"&DATE(2026,IF(9=12,9+1,9+1),1)) -> 0 | HC10: =SUM(GY10:HB10) -> 0 | HN10: =IFERROR(LOOKUP(2,1/('DRAFT 2'!$D:$D=$B10)*('DRAFT 2'!$A:$A>=DATE(2026,10,1))*('DRAFT 2'!$A:$A<DATE(2026,IF(10=12,10+1,10+1),1)),'DRAFT 2'!$A:$A),"") -> 0 | HO10: =COUNTIFS('DRAFT 2'!$D:$D,$B10,'DRAFT 2'!$A:$A,">="&DATE(2026,10,1),'DRAFT 2'!$A:$A,"<="&DATE(2026,10,7)) -> 0 | HP10: =COUNTIFS('DRAFT 2'!$D:$D,$B10,'DRAFT 2'!$A:$A,">="&DATE(2026,10,8),'DRAFT 2'!$A:$A,"<="&DATE(2026,10,14)) -> 0 | HQ10: =COUNTIFS('DRAFT 2'!$D:$D,$B10,'DRAFT 2'!$A:$A,">="&DATE(2026,10,15),'DRAFT 2'!$A:$A,"<="&DATE(2026,10,21)) -> 0 | HR10: =COUNTIFS('DRAFT 2'!$D:$D,$B10,'DRAFT 2'!$A:$A,">="&DATE(2026,10,22),'DRAFT 2'!$A:$A,"<"&DATE(2026,IF(10=12,10+1,10+1),1)) -> 0 | HS10: =SUM(HO10:HR10) -> 0 | IC10: =IFERROR(LOOKUP(2,1/('DRAFT 2'!$D:$D=$B10)*('DRAFT 2'!$A:$A>=DATE(2026,11,1))*('DRAFT 2'!$A:$A<DATE(2026,IF(11=12,11+1,11+1),1)),'DRAFT 2'!$A:$A),"") -> 0 | ID10: =COUNTIFS('DRAFT 2'!$D:$D,$B10,'DRAFT 2'!$A:$A,">="&DATE(2026,11,1),'DRAFT 2'!$A:$A,"<="&DATE(2026,11,7)) -> 0 | IE10: =COUNTIFS('DRAFT 2'!$D:$D,$B10,'DRAFT 2'!$A:$A,">="&DATE(2026,11,8),'DRAFT 2'!$A:$A,"<="&DATE(2026,11,14)) -> 0 | IF10: =COUNTIFS('DRAFT 2'!$D:$D,$B10,'DRAFT 2'!$A:$A,">="&DATE(2026,11,15),'DRAFT 2'!$A:$A,"<="&DATE(2026,11,21)) -> 0 | IG10: =COUNTIFS('DRAFT 2'!$D:$D,$B10,'DRAFT 2'!$A:$A,">="&DATE(2026,11,22),'DRAFT 2'!$A:$A,"<"&DATE(2026,IF(11=12,11+1,11+1),1)) -> 0 | IH10: =SUM(ID10:IG10) -> 0 | IR10: =IFERROR(LOOKUP(2,1/('DRAFT 2'!$D:$D=$B10)*('DRAFT 2'!$A:$A>=DATE(2026,12,1))*('DRAFT 2'!$A:$A<DATE(2026,IF(12=12,12+1,12+1),1)),'DRAFT 2'!$A:$A),"") -> 0 | IS10: =COUNTIFS('DRAFT 2'!$D:$D,$B10,'DRAFT 2'!$A:$A,">="&DATE(2026,12,1),'DRAFT 2'!$A:$A,"<="&DATE(2026,12,7)) -> 0 | IT10: =COUNTIFS('DRAFT 2'!$D:$D,$B10,'DRAFT 2'!$A:$A,">="&DATE(2026,12,8),'DRAFT 2'!$A:$A,"<="&DATE(2026,12,14)) -> 0 | IU10: =COUNTIFS('DRAFT 2'!$D:$D,$B10,'DRAFT 2'!$A:$A,">="&DATE(2026,12,15),'DRAFT 2'!$A:$A,"<="&DATE(2026,12,21)) -> 0 | IV10: =COUNTIFS('DRAFT 2'!$D:$D,$B10,'DRAFT 2'!$A:$A,">="&DATE(2026,12,22),'DRAFT 2'!$A:$A,"<"&DATE(2026,IF(12=12,12+1,12+1),1)) -> 0 | IW10: =SUM(IS10:IV10) -> 0
A11: =IFERROR(INDEX('DRAFT 1'!$A:$A,MATCH($B11,'DRAFT 1'!$B:$B,0)),"") | C11: =IFERROR(INDEX('DRAFT 1'!$C:$C,MATCH($B11,'DRAFT 1'!$B:$B,0)),"") | D11: =IFERROR(INDEX('DRAFT 1'!$D:$D,MATCH($B11,'DRAFT 1'!$B:$B,0)),"") | E11: =IFERROR(INDEX('DRAFT 1'!$E:$E,MATCH($B11,'DRAFT 1'!$B:$B,0)),"") | F11: =IFERROR(INDEX('DRAFT 1'!$F:$F,MATCH($B11,'DRAFT 1'!$B:$B,0)),"") | G11: =IFERROR(INDEX('DRAFT 1'!$G:$G,MATCH($B11,'DRAFT 1'!$B:$B,0)),"") | H11: =IFERROR(INDEX('DRAFT 1'!$H:$H,MATCH($B11,'DRAFT 1'!$B:$B,0)),"") | I11: DEMAIS CLIENTES | K11: =IFERROR(INDEX('DRAFT 1'!$AL:$AL,MATCH($B11,'DRAFT 1'!$B:$B,0)),"") | L11: =IFERROR(INDEX('DRAFT 1'!$J:$J,MATCH($B11,'DRAFT 1'!$B:$B,0)),"") | M11: =IFERROR(INDEX('DRAFT 1'!$K:$K,MATCH($B11,'DRAFT 1'!$B:$B,0)),"") | N11: INAT.ANT | P11: =IFERROR(INDEX('DRAFT 1'!$L:$L,MATCH($B11,'DRAFT 1'!$B:$B,0)),"") | Q11: =IFERROR(INDEX('DRAFT 1'!$M:$M,MATCH($B11,'DRAFT 1'!$B:$B,0)),"") | R11: =IFERROR(INDEX('DRAFT 1'!$N:$N,MATCH($B11,'DRAFT 1'!$B:$B,0)),"") | S11: =IFERROR(INDEX('DRAFT 1'!$O:$O,MATCH($B11,'DRAFT 1'!$B:$B,0)),"") | T11: =IFERROR(INDEX('DRAFT 1'!$P:$P,MATCH($B11,'DRAFT 1'!$B:$B,0)),"") | U11: =IFERROR(INDEX('DRAFT 1'!$Q:$Q,MATCH($B11,'DRAFT 1'!$B:$B,0)),"") | V11: =IFERROR(INDEX('DRAFT 1'!$R:$R,MATCH($B11,'DRAFT 1'!$B:$B,0)),"") | W11: =IFERROR(INDEX('DRAFT 1'!$S:$S,MATCH($B11,'DRAFT 1'!$B:$B,0)),"") | X11: =IFERROR(INDEX('DRAFT 1'!$T:$T,MATCH($B11,'DRAFT 1'!$B:$B,0)),"") | Z11: =IFERROR(INDEX('DRAFT 1'!$U:$U,MATCH($B11,'DRAFT 1'!$B:$B,0)),"") | AA11: =IFERROR(INDEX('DRAFT 1'!$V:$V,MATCH($B11,'DRAFT 1'!$B:$B,0)),"") | AB11: =IFERROR(INDEX('DRAFT 1'!$W:$W,MATCH($B11,'DRAFT 1'!$B:$B,0)),"") | AC11: =IFERROR(INDEX('DRAFT 1'!$X:$X,MATCH($B11,'DRAFT 1'!$B:$B,0)),"") | AD11: =IFERROR(INDEX('DRAFT 1'!$Y:$Y,MATCH($B11,'DRAFT 1'!$B:$B,0)),"") | AE11: =IFERROR(INDEX('DRAFT 1'!$Z:$Z,MATCH($B11,'DRAFT 1'!$B:$B,0)),"") | AF11: =IFERROR(INDEX('DRAFT 1'!$AA:$AA,MATCH($B11,'DRAFT 1'!$B:$B,0)),"") | AG11: =IFERROR(INDEX('DRAFT 1'!$AB:$AB,MATCH($B11,'DRAFT 1'!$B:$B,0)),"") | AH11: =IFERROR(INDEX('DRAFT 1'!$AC:$AC,MATCH($B11,'DRAFT 1'!$B:$B,0)),"") | AI11: =IFERROR(INDEX('DRAFT 1'!$AD:$AD,MATCH($B11,'DRAFT 1'!$B:$B,0)),"") | AJ11: =IFERROR(INDEX('DRAFT 1'!$AE:$AE,MATCH($B11,'DRAFT 1'!$B:$B,0)),"") | AK11: =IFERROR(INDEX('DRAFT 1'!$AG:$AG,MATCH($B11,'DRAFT 1'!$B:$B,0)),"") | AL11: =IFERROR(INDEX('DRAFT 1'!$AH:$AH,MATCH($B11,'DRAFT 1'!$B:$B,0)),"") | AM11: =IFERROR(INDEX('DRAFT 1'!$AI:$AI,MATCH($B11,'DRAFT 1'!$B:$B,0)),"") | AN11: =IFERROR(INDEX('DRAFT 1'!$AJ:$AJ,MATCH($B11,'DRAFT 1'!$B:$B,0)),"") | AO11: =IFERROR(Y11/AN11,0) -> 0 | AP11: =IFERROR(INDEX('DRAFT 1'!$AK:$AK,MATCH($B11,'DRAFT 1'!$B:$B,0)),"") | AR11: SALVAMENTO | AS11: =IFERROR(LOOKUP(2,1/('DRAFT 2'!$D:$D=$B11),'DRAFT 2'!$T:$T),"") -> 0 | AT11: =IFERROR(LOOKUP(2,1/('DRAFT 2'!$D:$D=$B11),'DRAFT 2'!$A:$A),"") -> 0 | AU11: =IFERROR(LOOKUP(2,1/('DRAFT 2'!$D:$D=$B11),'DRAFT 2'!$R:$R),"") -> 0 | AV11: =IFERROR(LOOKUP(2,1/('DRAFT 2'!$D:$D=$B11),'DRAFT 2'!$S:$S),"") -> 0 | AW11: EM DESENVOLVIMENTO | AX11: =IFERROR(LOOKUP(2,1/('DRAFT 2'!$D:$D=$B11),'DRAFT 2'!$M:$M),"") -> 0 | AY11: =IFERROR(LOOKUP(2,1/('DRAFT 2'!$D:$D=$B11),'DRAFT 2'!$K:$K),"") -> 0 | BG11: =IFERROR(LOOKUP(2,1/('DRAFT 2'!$D:$D=$B11),'DRAFT 2'!$U:$U),"") -> 0 | BH11: =IFERROR(LOOKUP(2,1/('DRAFT 2'!$D:$D=$B11),'DRAFT 2'!$V:$V),"") -> 0 | CE11: =IFERROR(AJ11,0) | CF11: =IFERROR(LOOKUP(2,1/('DRAFT 2'!$D:$D=$B11)*('DRAFT 2'!$A:$A>=DATE(2026,1,1))*('DRAFT 2'!$A:$A<DATE(2026,IF(1=12,1+1,1+1),1)),'DRAFT 2'!$A:$A),"") -> 0 | CG11: =COUNTIFS('DRAFT 2'!$D:$D,$B11,'DRAFT 2'!$A:$A,">="&DATE(2026,1,1),'DRAFT 2'!$A:$A,"<="&DATE(2026,1,7)) -> 0 | CH11: =COUNTIFS('DRAFT 2'!$D:$D,$B11,'DRAFT 2'!$A:$A,">="&DATE(2026,1,8),'DRAFT 2'!$A:$A,"<="&DATE(2026,1,14)) -> 0 | CI11: =COUNTIFS('DRAFT 2'!$D:$D,$B11,'DRAFT 2'!$A:$A,">="&DATE(2026,1,15),'DRAFT 2'!$A:$A,"<="&DATE(2026,1,21)) -> 0 | CJ11: =COUNTIFS('DRAFT 2'!$D:$D,$B11,'DRAFT 2'!$A:$A,">="&DATE(2026,1,22),'DRAFT 2'!$A:$A,"<"&DATE(2026,IF(1=12,1+1,1+1),1)) -> 0 | CK11: =SUM(CG11:CJ11) -> 0 | CT11: 0 | CU11: =IFERROR(LOOKUP(2,1/('DRAFT 2'!$D:$D=$B11)*('DRAFT 2'!$A:$A>=DATE(2026,2,1))*('DRAFT 2'!$A:$A<DATE(2026,IF(2=12,2+1,2+1),1)),'DRAFT 2'!$A:$A),"") -> 0 | CV11: =COUNTIFS('DRAFT 2'!$D:$D,$B11,'DRAFT 2'!$A:$A,">="&DATE(2026,2,1),'DRAFT 2'!$A:$A,"<="&DATE(2026,2,7)) -> 0 | CW11: =COUNTIFS('DRAFT 2'!$D:$D,$B11,'DRAFT 2'!$A:$A,">="&DATE(2026,2,8),'DRAFT 2'!$A:$A,"<="&DATE(2026,2,14)) -> 0 | CX11: =COUNTIFS('DRAFT 2'!$D:$D,$B11,'DRAFT 2'!$A:$A,">="&DATE(2026,2,15),'DRAFT 2'!$A:$A,"<="&DATE(2026,2,21)) -> 0 | CY11: =COUNTIFS('DRAFT 2'!$D:$D,$B11,'DRAFT 2'!$A:$A,">="&DATE(2026,2,22),'DRAFT 2'!$A:$A,"<"&DATE(2026,IF(2=12,2+1,2+1),1)) -> 0 | CZ11: =SUM(CV11:CY11) -> 0 | DJ11: =IFERROR(LOOKUP(2,1/('DRAFT 2'!$D:$D=$B11)*('DRAFT 2'!$A:$A>=DATE(2026,3,1))*('DRAFT 2'!$A:$A<DATE(2026,IF(3=12,3+1,3+1),1)),'DRAFT 2'!$A:$A),"") -> 0 | DK11: =COUNTIFS('DRAFT 2'!$D:$D,$B11,'DRAFT 2'!$A:$A,">="&DATE(2026,3,1),'DRAFT 2'!$A:$A,"<="&DATE(2026,3,7)) -> 0 | DL11: =COUNTIFS('DRAFT 2'!$D:$D,$B11,'DRAFT 2'!$A:$A,">="&DATE(2026,3,8),'DRAFT 2'!$A:$A,"<="&DATE(2026,3,14)) -> 0 | DM11: =COUNTIFS('DRAFT 2'!$D:$D,$B11,'DRAFT 2'!$A:$A,">="&DATE(2026,3,15),'DRAFT 2'!$A:$A,"<="&DATE(2026,3,21)) -> 0 | DN11: =COUNTIFS('DRAFT 2'!$D:$D,$B11,'DRAFT 2'!$A:$A,">="&DATE(2026,3,22),'DRAFT 2'!$A:$A,"<"&DATE(2026,IF(3=12,3+1,3+1),1)) -> 0 | DO11: =SUM(DK11:DN11) -> 0 | DZ11: =IFERROR(LOOKUP(2,1/('DRAFT 2'!$D:$D=$B11)*('DRAFT 2'!$A:$A>=DATE(2026,4,1))*('DRAFT 2'!$A:$A<DATE(2026,IF(4=12,4+1,4+1),1)),'DRAFT 2'!$A:$A),"") -> 0 | EA11: =COUNTIFS('DRAFT 2'!$D:$D,$B11,'DRAFT 2'!$A:$A,">="&DATE(2026,4,1),'DRAFT 2'!$A:$A,"<="&DATE(2026,4,7)) -> 0 | EB11: =COUNTIFS('DRAFT 2'!$D:$D,$B11,'DRAFT 2'!$A:$A,">="&DATE(2026,4,8),'DRAFT 2'!$A:$A,"<="&DATE(2026,4,14)) -> 0 | EC11: =COUNTIFS('DRAFT 2'!$D:$D,$B11,'DRAFT 2'!$A:$A,">="&DATE(2026,4,15),'DRAFT 2'!$A:$A,"<="&DATE(2026,4,21)) -> 0 | ED11: =COUNTIFS('DRAFT 2'!$D:$D,$B11,'DRAFT 2'!$A:$A,">="&DATE(2026,4,22),'DRAFT 2'!$A:$A,"<"&DATE(2026,IF(4=12,4+1,4+1),1)) -> 0 | EE11: =SUM(EA11:ED11) -> 0 | EO11: =IFERROR(LOOKUP(2,1/('DRAFT 2'!$D:$D=$B11)*('DRAFT 2'!$A:$A>=DATE(2026,5,1))*('DRAFT 2'!$A:$A<DATE(2026,IF(5=12,5+1,5+1),1)),'DRAFT 2'!$A:$A),"") -> 0 | EP11: =COUNTIFS('DRAFT 2'!$D:$D,$B11,'DRAFT 2'!$A:$A,">="&DATE(2026,5,1),'DRAFT 2'!$A:$A,"<="&DATE(2026,5,7)) -> 0 | EQ11: =COUNTIFS('DRAFT 2'!$D:$D,$B11,'DRAFT 2'!$A:$A,">="&DATE(2026,5,8),'DRAFT 2'!$A:$A,"<="&DATE(2026,5,14)) -> 0 | ER11: =COUNTIFS('DRAFT 2'!$D:$D,$B11,'DRAFT 2'!$A:$A,">="&DATE(2026,5,15),'DRAFT 2'!$A:$A,"<="&DATE(2026,5,21)) -> 0 | ES11: =COUNTIFS('DRAFT 2'!$D:$D,$B11,'DRAFT 2'!$A:$A,">="&DATE(2026,5,22),'DRAFT 2'!$A:$A,"<"&DATE(2026,IF(5=12,5+1,5+1),1)) -> 0 | ET11: =SUM(EP11:ES11) -> 0 | FD11: =IFERROR(LOOKUP(2,1/('DRAFT 2'!$D:$D=$B11)*('DRAFT 2'!$A:$A>=DATE(2026,6,1))*('DRAFT 2'!$A:$A<DATE(2026,IF(6=12,6+1,6+1),1)),'DRAFT 2'!$A:$A),"") -> 0 | FE11: =COUNTIFS('DRAFT 2'!$D:$D,$B11,'DRAFT 2'!$A:$A,">="&DATE(2026,6,1),'DRAFT 2'!$A:$A,"<="&DATE(2026,6,7)) -> 0 | FF11: =COUNTIFS('DRAFT 2'!$D:$D,$B11,'DRAFT 2'!$A:$A,">="&DATE(2026,6,8),'DRAFT 2'!$A:$A,"<="&DATE(2026,6,14)) -> 0 | FG11: =COUNTIFS('DRAFT 2'!$D:$D,$B11,'DRAFT 2'!$A:$A,">="&DATE(2026,6,15),'DRAFT 2'!$A:$A,"<="&DATE(2026,6,21)) -> 0 | FH11: =COUNTIFS('DRAFT 2'!$D:$D,$B11,'DRAFT 2'!$A:$A,">="&DATE(2026,6,22),'DRAFT 2'!$A:$A,"<"&DATE(2026,IF(6=12,6+1,6+1),1)) -> 0 | FI11: =SUM(FE11:FH11) -> 0 | FT11: =IFERROR(LOOKUP(2,1/('DRAFT 2'!$D:$D=$B11)*('DRAFT 2'!$A:$A>=DATE(2026,7,1))*('DRAFT 2'!$A:$A<DATE(2026,IF(7=12,7+1,7+1),1)),'DRAFT 2'!$A:$A),"") -> 0 | FU11: =COUNTIFS('DRAFT 2'!$D:$D,$B11,'DRAFT 2'!$A:$A,">="&DATE(2026,7,1),'DRAFT 2'!$A:$A,"<="&DATE(2026,7,7)) -> 0 | FV11: =COUNTIFS('DRAFT 2'!$D:$D,$B11,'DRAFT 2'!$A:$A,">="&DATE(2026,7,8),'DRAFT 2'!$A:$A,"<="&DATE(2026,7,14)) -> 0 | FW11: =COUNTIFS('DRAFT 2'!$D:$D,$B11,'DRAFT 2'!$A:$A,">="&DATE(2026,7,15),'DRAFT 2'!$A:$A,"<="&DATE(2026,7,21)) -> 0 | FX11: =COUNTIFS('DRAFT 2'!$D:$D,$B11,'DRAFT 2'!$A:$A,">="&DATE(2026,7,22),'DRAFT 2'!$A:$A,"<"&DATE(2026,IF(7=12,7+1,7+1),1)) -> 0 | FY11: =SUM(FU11:FX11) -> 0 | GI11: =IFERROR(LOOKUP(2,1/('DRAFT 2'!$D:$D=$B11)*('DRAFT 2'!$A:$A>=DATE(2026,8,1))*('DRAFT 2'!$A:$A<DATE(2026,IF(8=12,8+1,8+1),1)),'DRAFT 2'!$A:$A),"") -> 0 | GJ11: =COUNTIFS('DRAFT 2'!$D:$D,$B11,'DRAFT 2'!$A:$A,">="&DATE(2026,8,1),'DRAFT 2'!$A:$A,"<="&DATE(2026,8,7)) -> 0 | GK11: =COUNTIFS('DRAFT 2'!$D:$D,$B11,'DRAFT 2'!$A:$A,">="&DATE(2026,8,8),'DRAFT 2'!$A:$A,"<="&DATE(2026,8,14)) -> 0 | GL11: =COUNTIFS('DRAFT 2'!$D:$D,$B11,'DRAFT 2'!$A:$A,">="&DATE(2026,8,15),'DRAFT 2'!$A:$A,"<="&DATE(2026,8,21)) -> 0 | GM11: =COUNTIFS('DRAFT 2'!$D:$D,$B11,'DRAFT 2'!$A:$A,">="&DATE(2026,8,22),'DRAFT 2'!$A:$A,"<"&DATE(2026,IF(8=12,8+1,8+1),1)) -> 0 | GN11: =SUM(GJ11:GM11) -> 0 | GX11: =IFERROR(LOOKUP(2,1/('DRAFT 2'!$D:$D=$B11)*('DRAFT 2'!$A:$A>=DATE(2026,9,1))*('DRAFT 2'!$A:$A<DATE(2026,IF(9=12,9+1,9+1),1)),'DRAFT 2'!$A:$A),"") -> 0 | GY11: =COUNTIFS('DRAFT 2'!$D:$D,$B11,'DRAFT 2'!$A:$A,">="&DATE(2026,9,1),'DRAFT 2'!$A:$A,"<="&DATE(2026,9,7)) -> 0 | GZ11: =COUNTIFS('DRAFT 2'!$D:$D,$B11,'DRAFT 2'!$A:$A,">="&DATE(2026,9,8),'DRAFT 2'!$A:$A,"<="&DATE(2026,9,14)) -> 0 | HA11: =COUNTIFS('DRAFT 2'!$D:$D,$B11,'DRAFT 2'!$A:$A,">="&DATE(2026,9,15),'DRAFT 2'!$A:$A,"<="&DATE(2026,9,21)) -> 0 | HB11: =COUNTIFS('DRAFT 2'!$D:$D,$B11,'DRAFT 2'!$A:$A,">="&DATE(2026,9,22),'DRAFT 2'!$A:$A,"<"&DATE(2026,IF(9=12,9+1,9+1),1)) -> 0 | HC11: =SUM(GY11:HB11) -> 0 | HN11: =IFERROR(LOOKUP(2,1/('DRAFT 2'!$D:$D=$B11)*('DRAFT 2'!$A:$A>=DATE(2026,10,1))*('DRAFT 2'!$A:$A<DATE(2026,IF(10=12,10+1,10+1),1)),'DRAFT 2'!$A:$A),"") -> 0 | HO11: =COUNTIFS('DRAFT 2'!$D:$D,$B11,'DRAFT 2'!$A:$A,">="&DATE(2026,10,1),'DRAFT 2'!$A:$A,"<="&DATE(2026,10,7)) -> 0 | HP11: =COUNTIFS('DRAFT 2'!$D:$D,$B11,'DRAFT 2'!$A:$A,">="&DATE(2026,10,8),'DRAFT 2'!$A:$A,"<="&DATE(2026,10,14)) -> 0 | HQ11: =COUNTIFS('DRAFT 2'!$D:$D,$B11,'DRAFT 2'!$A:$A,">="&DATE(2026,10,15),'DRAFT 2'!$A:$A,"<="&DATE(2026,10,21)) -> 0 | HR11: =COUNTIFS('DRAFT 2'!$D:$D,$B11,'DRAFT 2'!$A:$A,">="&DATE(2026,10,22),'DRAFT 2'!$A:$A,"<"&DATE(2026,IF(10=12,10+1,10+1),1)) -> 0 | HS11: =SUM(HO11:HR11) -> 0 | IC11: =IFERROR(LOOKUP(2,1/('DRAFT 2'!$D:$D=$B11)*('DRAFT 2'!$A:$A>=DATE(2026,11,1))*('DRAFT 2'!$A:$A<DATE(2026,IF(11=12,11+1,11+1),1)),'DRAFT 2'!$A:$A),"") -> 0 | ID11: =COUNTIFS('DRAFT 2'!$D:$D,$B11,'DRAFT 2'!$A:$A,">="&DATE(2026,11,1),'DRAFT 2'!$A:$A,"<="&DATE(2026,11,7)) -> 0 | IE11: =COUNTIFS('DRAFT 2'!$D:$D,$B11,'DRAFT 2'!$A:$A,">="&DATE(2026,11,8),'DRAFT 2'!$A:$A,"<="&DATE(2026,11,14)) -> 0 | IF11: =COUNTIFS('DRAFT 2'!$D:$D,$B11,'DRAFT 2'!$A:$A,">="&DATE(2026,11,15),'DRAFT 2'!$A:$A,"<="&DATE(2026,11,21)) -> 0 | IG11: =COUNTIFS('DRAFT 2'!$D:$D,$B11,'DRAFT 2'!$A:$A,">="&DATE(2026,11,22),'DRAFT 2'!$A:$A,"<"&DATE(2026,IF(11=12,11+1,11+1),1)) -> 0 | IH11: =SUM(ID11:IG11) -> 0 | IR11: =IFERROR(LOOKUP(2,1/('DRAFT 2'!$D:$D=$B11)*('DRAFT 2'!$A:$A>=DATE(2026,12,1))*('DRAFT 2'!$A:$A<DATE(2026,IF(12=12,12+1,12+1),1)),'DRAFT 2'!$A:$A),"") -> 0 | IS11: =COUNTIFS('DRAFT 2'!$D:$D,$B11,'DRAFT 2'!$A:$A,">="&DATE(2026,12,1),'DRAFT 2'!$A:$A,"<="&DATE(2026,12,7)) -> 0 | IT11: =COUNTIFS('DRAFT 2'!$D:$D,$B11,'DRAFT 2'!$A:$A,">="&DATE(2026,12,8),'DRAFT 2'!$A:$A,"<="&DATE(2026,12,14)) -> 0 | IU11: =COUNTIFS('DRAFT 2'!$D:$D,$B11,'DRAFT 2'!$A:$A,">="&DATE(2026,12,15),'DRAFT 2'!$A:$A,"<="&DATE(2026,12,21)) -> 0 | IV11: =COUNTIFS('DRAFT 2'!$D:$D,$B11,'DRAFT 2'!$A:$A,">="&DATE(2026,12,22),'DRAFT 2'!$A:$A,"<"&DATE(2026,IF(12=12,12+1,12+1),1)) -> 0 | IW11: =SUM(IS11:IV11) -> 0
A12: =IFERROR(INDEX('DRAFT 1'!$A:$A,MATCH($B12,'DRAFT 1'!$B:$B,0)),"") | C12: =IFERROR(INDEX('DRAFT 1'!$C:$C,MATCH($B12,'DRAFT 1'!$B:$B,0)),"") | D12: =IFERROR(INDEX('DRAFT 1'!$D:$D,MATCH($B12,'DRAFT 1'!$B:$B,0)),"") | E12: =IFERROR(INDEX('DRAFT 1'!$E:$E,MATCH($B12,'DRAFT 1'!$B:$B,0)),"") | F12: =IFERROR(INDEX('DRAFT 1'!$F:$F,MATCH($B12,'DRAFT 1'!$B:$B,0)),"") | G12: =IFERROR(INDEX('DRAFT 1'!$G:$G,MATCH($B12,'DRAFT 1'!$B:$B,0)),"") | H12: =IFERROR(INDEX('DRAFT 1'!$H:$H,MATCH($B12,'DRAFT 1'!$B:$B,0)),"") | I12: CIA DA SAUDE | K12: =IFERROR(INDEX('DRAFT 1'!$AL:$AL,MATCH($B12,'DRAFT 1'!$B:$B,0)),"") | L12: =IFERROR(INDEX('DRAFT 1'!$J:$J,MATCH($B12,'DRAFT 1'!$B:$B,0)),"") | M12: =IFERROR(INDEX('DRAFT 1'!$K:$K,MATCH($B12,'DRAFT 1'!$B:$B,0)),"") | N12: NOVO | P12: =IFERROR(INDEX('DRAFT 1'!$L:$L,MATCH($B12,'DRAFT 1'!$B:$B,0)),"") | Q12: =IFERROR(INDEX('DRAFT 1'!$M:$M,MATCH($B12,'DRAFT 1'!$B:$B,0)),"") | R12: =IFERROR(INDEX('DRAFT 1'!$N:$N,MATCH($B12,'DRAFT 1'!$B:$B,0)),"") | S12: =IFERROR(INDEX('DRAFT 1'!$O:$O,MATCH($B12,'DRAFT 1'!$B:$B,0)),"") | T12: =IFERROR(INDEX('DRAFT 1'!$P:$P,MATCH($B12,'DRAFT 1'!$B:$B,0)),"") | U12: =IFERROR(INDEX('DRAFT 1'!$Q:$Q,MATCH($B12,'DRAFT 1'!$B:$B,0)),"") | V12: =IFERROR(INDEX('DRAFT 1'!$R:$R,MATCH($B12,'DRAFT 1'!$B:$B,0)),"") | W12: =IFERROR(INDEX('DRAFT 1'!$S:$S,MATCH($B12,'DRAFT 1'!$B:$B,0)),"") | X12: =IFERROR(INDEX('DRAFT 1'!$T:$T,MATCH($B12,'DRAFT 1'!$B:$B,0)),"") | Z12: =IFERROR(INDEX('DRAFT 1'!$U:$U,MATCH($B12,'DRAFT 1'!$B:$B,0)),"") | AA12: =IFERROR(INDEX('DRAFT 1'!$V:$V,MATCH($B12,'DRAFT 1'!$B:$B,0)),"") | AB12: =IFERROR(INDEX('DRAFT 1'!$W:$W,MATCH($B12,'DRAFT 1'!$B:$B,0)),"") | AC12: =IFERROR(INDEX('DRAFT 1'!$X:$X,MATCH($B12,'DRAFT 1'!$B:$B,0)),"") | AD12: =IFERROR(INDEX('DRAFT 1'!$Y:$Y,MATCH($B12,'DRAFT 1'!$B:$B,0)),"") | AE12: =IFERROR(INDEX('DRAFT 1'!$Z:$Z,MATCH($B12,'DRAFT 1'!$B:$B,0)),"") | AF12: =IFERROR(INDEX('DRAFT 1'!$AA:$AA,MATCH($B12,'DRAFT 1'!$B:$B,0)),"") | AG12: =IFERROR(INDEX('DRAFT 1'!$AB:$AB,MATCH($B12,'DRAFT 1'!$B:$B,0)),"") | AH12: =IFERROR(INDEX('DRAFT 1'!$AC:$AC,MATCH($B12,'DRAFT 1'!$B:$B,0)),"") | AI12: =IFERROR(INDEX('DRAFT 1'!$AD:$AD,MATCH($B12,'DRAFT 1'!$B:$B,0)),"") | AJ12: =IFERROR(INDEX('DRAFT 1'!$AE:$AE,MATCH($B12,'DRAFT 1'!$B:$B,0)),"") | AK12: =IFERROR(INDEX('DRAFT 1'!$AG:$AG,MATCH($B12,'DRAFT 1'!$B:$B,0)),"") | AL12: =IFERROR(INDEX('DRAFT 1'!$AH:$AH,MATCH($B12,'DRAFT 1'!$B:$B,0)),"") | AM12: =IFERROR(INDEX('DRAFT 1'!$AI:$AI,MATCH($B12,'DRAFT 1'!$B:$B,0)),"") | AN12: =IFERROR(INDEX('DRAFT 1'!$AJ:$AJ,MATCH($B12,'DRAFT 1'!$B:$B,0)),"") | AO12: =IFERROR(Y12/AN12,0) -> 0 | AP12: =IFERROR(INDEX('DRAFT 1'!$AK:$AK,MATCH($B12,'DRAFT 1'!$B:$B,0)),"") | AR12: SALVAMENTO | AS12: =IFERROR(LOOKUP(2,1/('DRAFT 2'!$D:$D=$B12),'DRAFT 2'!$T:$T),"") -> 0 | AT12: =IFERROR(LOOKUP(2,1/('DRAFT 2'!$D:$D=$B12),'DRAFT 2'!$A:$A),"") -> 0 | AU12: =IFERROR(LOOKUP(2,1/('DRAFT 2'!$D:$D=$B12),'DRAFT 2'!$R:$R),"") -> 0 | AV12: =IFERROR(LOOKUP(2,1/('DRAFT 2'!$D:$D=$B12),'DRAFT 2'!$S:$S),"") -> 0 | AW12: PROSPECT | AX12: =IFERROR(LOOKUP(2,1/('DRAFT 2'!$D:$D=$B12),'DRAFT 2'!$M:$M),"") -> 0 | AY12: =IFERROR(LOOKUP(2,1/('DRAFT 2'!$D:$D=$B12),'DRAFT 2'!$K:$K),"") -> 0 | BG12: =IFERROR(LOOKUP(2,1/('DRAFT 2'!$D:$D=$B12),'DRAFT 2'!$U:$U),"") -> 0 | BH12: =IFERROR(LOOKUP(2,1/('DRAFT 2'!$D:$D=$B12),'DRAFT 2'!$V:$V),"") -> 0 | CE12: =IFERROR(AJ12,0) | CF12: =IFERROR(LOOKUP(2,1/('DRAFT 2'!$D:$D=$B12)*('DRAFT 2'!$A:$A>=DATE(2026,1,1))*('DRAFT 2'!$A:$A<DATE(2026,IF(1=12,1+1,1+1),1)),'DRAFT 2'!$A:$A),"") -> 0 | CG12: =COUNTIFS('DRAFT 2'!$D:$D,$B12,'DRAFT 2'!$A:$A,">="&DATE(2026,1,1),'DRAFT 2'!$A:$A,"<="&DATE(2026,1,7)) -> 0 | CH12: =COUNTIFS('DRAFT 2'!$D:$D,$B12,'DRAFT 2'!$A:$A,">="&DATE(2026,1,8),'DRAFT 2'!$A:$A,"<="&DATE(2026,1,14)) -> 0 | CI12: =COUNTIFS('DRAFT 2'!$D:$D,$B12,'DRAFT 2'!$A:$A,">="&DATE(2026,1,15),'DRAFT 2'!$A:$A,"<="&DATE(2026,1,21)) -> 0 | CJ12: =COUNTIFS('DRAFT 2'!$D:$D,$B12,'DRAFT 2'!$A:$A,">="&DATE(2026,1,22),'DRAFT 2'!$A:$A,"<"&DATE(2026,IF(1=12,1+1,1+1),1)) -> 0 | CK12: =SUM(CG12:CJ12) -> 0 | CT12: 0 | CU12: =IFERROR(LOOKUP(2,1/('DRAFT 2'!$D:$D=$B12)*('DRAFT 2'!$A:$A>=DATE(2026,2,1))*('DRAFT 2'!$A:$A<DATE(2026,IF(2=12,2+1,2+1),1)),'DRAFT 2'!$A:$A),"") -> 0 | CV12: =COUNTIFS('DRAFT 2'!$D:$D,$B12,'DRAFT 2'!$A:$A,">="&DATE(2026,2,1),'DRAFT 2'!$A:$A,"<="&DATE(2026,2,7)) -> 0 | CW12: =COUNTIFS('DRAFT 2'!$D:$D,$B12,'DRAFT 2'!$A:$A,">="&DATE(2026,2,8),'DRAFT 2'!$A:$A,"<="&DATE(2026,2,14)) -> 0 | CX12: =COUNTIFS('DRAFT 2'!$D:$D,$B12,'DRAFT 2'!$A:$A,">="&DATE(2026,2,15),'DRAFT 2'!$A:$A,"<="&DATE(2026,2,21)) -> 0 | CY12: =COUNTIFS('DRAFT 2'!$D:$D,$B12,'DRAFT 2'!$A:$A,">="&DATE(2026,2,22),'DRAFT 2'!$A:$A,"<"&DATE(2026,IF(2=12,2+1,2+1),1)) -> 0 | CZ12: =SUM(CV12:CY12) -> 0 | DJ12: =IFERROR(LOOKUP(2,1/('DRAFT 2'!$D:$D=$B12)*('DRAFT 2'!$A:$A>=DATE(2026,3,1))*('DRAFT 2'!$A:$A<DATE(2026,IF(3=12,3+1,3+1),1)),'DRAFT 2'!$A:$A),"") -> 0 | DK12: =COUNTIFS('DRAFT 2'!$D:$D,$B12,'DRAFT 2'!$A:$A,">="&DATE(2026,3,1),'DRAFT 2'!$A:$A,"<="&DATE(2026,3,7)) -> 0 | DL12: =COUNTIFS('DRAFT 2'!$D:$D,$B12,'DRAFT 2'!$A:$A,">="&DATE(2026,3,8),'DRAFT 2'!$A:$A,"<="&DATE(2026,3,14)) -> 0 | DM12: =COUNTIFS('DRAFT 2'!$D:$D,$B12,'DRAFT 2'!$A:$A,">="&DATE(2026,3,15),'DRAFT 2'!$A:$A,"<="&DATE(2026,3,21)) -> 0 | DN12: =COUNTIFS('DRAFT 2'!$D:$D,$B12,'DRAFT 2'!$A:$A,">="&DATE(2026,3,22),'DRAFT 2'!$A:$A,"<"&DATE(2026,IF(3=12,3+1,3+1),1)) -> 0 | DO12: =SUM(DK12:DN12) -> 0 | DZ12: =IFERROR(LOOKUP(2,1/('DRAFT 2'!$D:$D=$B12)*('DRAFT 2'!$A:$A>=DATE(2026,4,1))*('DRAFT 2'!$A:$A<DATE(2026,IF(4=12,4+1,4+1),1)),'DRAFT 2'!$A:$A),"") -> 0 | EA12: =COUNTIFS('DRAFT 2'!$D:$D,$B12,'DRAFT 2'!$A:$A,">="&DATE(2026,4,1),'DRAFT 2'!$A:$A,"<="&DATE(2026,4,7)) -> 0 | EB12: =COUNTIFS('DRAFT 2'!$D:$D,$B12,'DRAFT 2'!$A:$A,">="&DATE(2026,4,8),'DRAFT 2'!$A:$A,"<="&DATE(2026,4,14)) -> 0 | EC12: =COUNTIFS('DRAFT 2'!$D:$D,$B12,'DRAFT 2'!$A:$A,">="&DATE(2026,4,15),'DRAFT 2'!$A:$A,"<="&DATE(2026,4,21)) -> 0 | ED12: =COUNTIFS('DRAFT 2'!$D:$D,$B12,'DRAFT 2'!$A:$A,">="&DATE(2026,4,22),'DRAFT 2'!$A:$A,"<"&DATE(2026,IF(4=12,4+1,4+1),1)) -> 0 | EE12: =SUM(EA12:ED12) -> 0 | EO12: =IFERROR(LOOKUP(2,1/('DRAFT 2'!$D:$D=$B12)*('DRAFT 2'!$A:$A>=DATE(2026,5,1))*('DRAFT 2'!$A:$A<DATE(2026,IF(5=12,5+1,5+1),1)),'DRAFT 2'!$A:$A),"") -> 0 | EP12: =COUNTIFS('DRAFT 2'!$D:$D,$B12,'DRAFT 2'!$A:$A,">="&DATE(2026,5,1),'DRAFT 2'!$A:$A,"<="&DATE(2026,5,7)) -> 0 | EQ12: =COUNTIFS('DRAFT 2'!$D:$D,$B12,'DRAFT 2'!$A:$A,">="&DATE(2026,5,8),'DRAFT 2'!$A:$A,"<="&DATE(2026,5,14)) -> 0 | ER12: =COUNTIFS('DRAFT 2'!$D:$D,$B12,'DRAFT 2'!$A:$A,">="&DATE(2026,5,15),'DRAFT 2'!$A:$A,"<="&DATE(2026,5,21)) -> 0 | ES12: =COUNTIFS('DRAFT 2'!$D:$D,$B12,'DRAFT 2'!$A:$A,">="&DATE(2026,5,22),'DRAFT 2'!$A:$A,"<"&DATE(2026,IF(5=12,5+1,5+1),1)) -> 0 | ET12: =SUM(EP12:ES12) -> 0 | FD12: =IFERROR(LOOKUP(2,1/('DRAFT 2'!$D:$D=$B12)*('DRAFT 2'!$A:$A>=DATE(2026,6,1))*('DRAFT 2'!$A:$A<DATE(2026,IF(6=12,6+1,6+1),1)),'DRAFT 2'!$A:$A),"") -> 0 | FE12: =COUNTIFS('DRAFT 2'!$D:$D,$B12,'DRAFT 2'!$A:$A,">="&DATE(2026,6,1),'DRAFT 2'!$A:$A,"<="&DATE(2026,6,7)) -> 0 | FF12: =COUNTIFS('DRAFT 2'!$D:$D,$B12,'DRAFT 2'!$A:$A,">="&DATE(2026,6,8),'DRAFT 2'!$A:$A,"<="&DATE(2026,6,14)) -> 0 | FG12: =COUNTIFS('DRAFT 2'!$D:$D,$B12,'DRAFT 2'!$A:$A,">="&DATE(2026,6,15),'DRAFT 2'!$A:$A,"<="&DATE(2026,6,21)) -> 0 | FH12: =COUNTIFS('DRAFT 2'!$D:$D,$B12,'DRAFT 2'!$A:$A,">="&DATE(2026,6,22),'DRAFT 2'!$A:$A,"<"&DATE(2026,IF(6=12,6+1,6+1),1)) -> 0 | FI12: =SUM(FE12:FH12) -> 0 | FT12: =IFERROR(LOOKUP(2,1/('DRAFT 2'!$D:$D=$B12)*('DRAFT 2'!$A:$A>=DATE(2026,7,1))*('DRAFT 2'!$A:$A<DATE(2026,IF(7=12,7+1,7+1),1)),'DRAFT 2'!$A:$A),"") -> 0 | FU12: =COUNTIFS('DRAFT 2'!$D:$D,$B12,'DRAFT 2'!$A:$A,">="&DATE(2026,7,1),'DRAFT 2'!$A:$A,"<="&DATE(2026,7,7)) -> 0 | FV12: =COUNTIFS('DRAFT 2'!$D:$D,$B12,'DRAFT 2'!$A:$A,">="&DATE(2026,7,8),'DRAFT 2'!$A:$A,"<="&DATE(2026,7,14)) -> 0 | FW12: =COUNTIFS('DRAFT 2'!$D:$D,$B12,'DRAFT 2'!$A:$A,">="&DATE(2026,7,15),'DRAFT 2'!$A:$A,"<="&DATE(2026,7,21)) -> 0 | FX12: =COUNTIFS('DRAFT 2'!$D:$D,$B12,'DRAFT 2'!$A:$A,">="&DATE(2026,7,22),'DRAFT 2'!$A:$A,"<"&DATE(2026,IF(7=12,7+1,7+1),1)) -> 0 | FY12: =SUM(FU12:FX12) -> 0 | GI12: =IFERROR(LOOKUP(2,1/('DRAFT 2'!$D:$D=$B12)*('DRAFT 2'!$A:$A>=DATE(2026,8,1))*('DRAFT 2'!$A:$A<DATE(2026,IF(8=12,8+1,8+1),1)),'DRAFT 2'!$A:$A),"") -> 0 | GJ12: =COUNTIFS('DRAFT 2'!$D:$D,$B12,'DRAFT 2'!$A:$A,">="&DATE(2026,8,1),'DRAFT 2'!$A:$A,"<="&DATE(2026,8,7)) -> 0 | GK12: =COUNTIFS('DRAFT 2'!$D:$D,$B12,'DRAFT 2'!$A:$A,">="&DATE(2026,8,8),'DRAFT 2'!$A:$A,"<="&DATE(2026,8,14)) -> 0 | GL12: =COUNTIFS('DRAFT 2'!$D:$D,$B12,'DRAFT 2'!$A:$A,">="&DATE(2026,8,15),'DRAFT 2'!$A:$A,"<="&DATE(2026,8,21)) -> 0 | GM12: =COUNTIFS('DRAFT 2'!$D:$D,$B12,'DRAFT 2'!$A:$A,">="&DATE(2026,8,22),'DRAFT 2'!$A:$A,"<"&DATE(2026,IF(8=12,8+1,8+1),1)) -> 0 | GN12: =SUM(GJ12:GM12) -> 0 | GX12: =IFERROR(LOOKUP(2,1/('DRAFT 2'!$D:$D=$B12)*('DRAFT 2'!$A:$A>=DATE(2026,9,1))*('DRAFT 2'!$A:$A<DATE(2026,IF(9=12,9+1,9+1),1)),'DRAFT 2'!$A:$A),"") -> 0 | GY12: =COUNTIFS('DRAFT 2'!$D:$D,$B12,'DRAFT 2'!$A:$A,">="&DATE(2026,9,1),'DRAFT 2'!$A:$A,"<="&DATE(2026,9,7)) -> 0 | GZ12: =COUNTIFS('DRAFT 2'!$D:$D,$B12,'DRAFT 2'!$A:$A,">="&DATE(2026,9,8),'DRAFT 2'!$A:$A,"<="&DATE(2026,9,14)) -> 0 | HA12: =COUNTIFS('DRAFT 2'!$D:$D,$B12,'DRAFT 2'!$A:$A,">="&DATE(2026,9,15),'DRAFT 2'!$A:$A,"<="&DATE(2026,9,21)) -> 0 | HB12: =COUNTIFS('DRAFT 2'!$D:$D,$B12,'DRAFT 2'!$A:$A,">="&DATE(2026,9,22),'DRAFT 2'!$A:$A,"<"&DATE(2026,IF(9=12,9+1,9+1),1)) -> 0 | HC12: =SUM(GY12:HB12) -> 0 | HN12: =IFERROR(LOOKUP(2,1/('DRAFT 2'!$D:$D=$B12)*('DRAFT 2'!$A:$A>=DATE(2026,10,1))*('DRAFT 2'!$A:$A<DATE(2026,IF(10=12,10+1,10+1),1)),'DRAFT 2'!$A:$A),"") -> 0 | HO12: =COUNTIFS('DRAFT 2'!$D:$D,$B12,'DRAFT 2'!$A:$A,">="&DATE(2026,10,1),'DRAFT 2'!$A:$A,"<="&DATE(2026,10,7)) -> 0 | HP12: =COUNTIFS('DRAFT 2'!$D:$D,$B12,'DRAFT 2'!$A:$A,">="&DATE(2026,10,8),'DRAFT 2'!$A:$A,"<="&DATE(2026,10,14)) -> 0 | HQ12: =COUNTIFS('DRAFT 2'!$D:$D,$B12,'DRAFT 2'!$A:$A,">="&DATE(2026,10,15),'DRAFT 2'!$A:$A,"<="&DATE(2026,10,21)) -> 0 | HR12: =COUNTIFS('DRAFT 2'!$D:$D,$B12,'DRAFT 2'!$A:$A,">="&DATE(2026,10,22),'DRAFT 2'!$A:$A,"<"&DATE(2026,IF(10=12,10+1,10+1),1)) -> 0 | HS12: =SUM(HO12:HR12) -> 0 | IC12: =IFERROR(LOOKUP(2,1/('DRAFT 2'!$D:$D=$B12)*('DRAFT 2'!$A:$A>=DATE(2026,11,1))*('DRAFT 2'!$A:$A<DATE(2026,IF(11=12,11+1,11+1),1)),'DRAFT 2'!$A:$A),"") -> 0 | ID12: =COUNTIFS('DRAFT 2'!$D:$D,$B12,'DRAFT 2'!$A:$A,">="&DATE(2026,11,1),'DRAFT 2'!$A:$A,"<="&DATE(2026,11,7)) -> 0 | IE12: =COUNTIFS('DRAFT 2'!$D:$D,$B12,'DRAFT 2'!$A:$A,">="&DATE(2026,11,8),'DRAFT 2'!$A:$A,"<="&DATE(2026,11,14)) -> 0 | IF12: =COUNTIFS('DRAFT 2'!$D:$D,$B12,'DRAFT 2'!$A:$A,">="&DATE(2026,11,15),'DRAFT 2'!$A:$A,"<="&DATE(2026,11,21)) -> 0 | IG12: =COUNTIFS('DRAFT 2'!$D:$D,$B12,'DRAFT 2'!$A:$A,">="&DATE(2026,11,22),'DRAFT 2'!$A:$A,"<"&DATE(2026,IF(11=12,11+1,11+1),1)) -> 0 | IH12: =SUM(ID12:IG12) -> 0 | IR12: =IFERROR(LOOKUP(2,1/('DRAFT 2'!$D:$D=$B12)*('DRAFT 2'!$A:$A>=DATE(2026,12,1))*('DRAFT 2'!$A:$A<DATE(2026,IF(12=12,12+1,12+1),1)),'DRAFT 2'!$A:$A),"") -> 0 | IS12: =COUNTIFS('DRAFT 2'!$D:$D,$B12,'DRAFT 2'!$A:$A,">="&DATE(2026,12,1),'DRAFT 2'!$A:$A,"<="&DATE(2026,12,7)) -> 0 | IT12: =COUNTIFS('DRAFT 2'!$D:$D,$B12,'DRAFT 2'!$A:$A,">="&DATE(2026,12,8),'DRAFT 2'!$A:$A,"<="&DATE(2026,12,14)) -> 0 | IU12: =COUNTIFS('DRAFT 2'!$D:$D,$B12,'DRAFT 2'!$A:$A,">="&DATE(2026,12,15),'DRAFT 2'!$A:$A,"<="&DATE(2026,12,21)) -> 0 | IV12: =COUNTIFS('DRAFT 2'!$D:$D,$B12,'DRAFT 2'!$A:$A,">="&DATE(2026,12,22),'DRAFT 2'!$A:$A,"<"&DATE(2026,IF(12=12,12+1,12+1),1)) -> 0 | IW12: =SUM(IS12:IV12) -> 0
A13: =IFERROR(INDEX('DRAFT 1'!$A:$A,MATCH($B13,'DRAFT 1'!$B:$B,0)),"") | C13: =IFERROR(INDEX('DRAFT 1'!$C:$C,MATCH($B13,'DRAFT 1'!$B:$B,0)),"") | D13: =IFERROR(INDEX('DRAFT 1'!$D:$D,MATCH($B13,'DRAFT 1'!$B:$B,0)),"") | E13: =IFERROR(INDEX('DRAFT 1'!$E:$E,MATCH($B13,'DRAFT 1'!$B:$B,0)),"") | F13: =IFERROR(INDEX('DRAFT 1'!$F:$F,MATCH($B13,'DRAFT 1'!$B:$B,0)),"") | G13: =IFERROR(INDEX('DRAFT 1'!$G:$G,MATCH($B13,'DRAFT 1'!$B:$B,0)),"") | H13: =IFERROR(INDEX('DRAFT 1'!$H:$H,MATCH($B13,'DRAFT 1'!$B:$B,0)),"") | I13: DEMAIS CLIENTES | K13: =IFERROR(INDEX('DRAFT 1'!$AL:$AL,MATCH($B13,'DRAFT 1'!$B:$B,0)),"") | L13: =IFERROR(INDEX('DRAFT 1'!$J:$J,MATCH($B13,'DRAFT 1'!$B:$B,0)),"") | M13: =IFERROR(INDEX('DRAFT 1'!$K:$K,MATCH($B13,'DRAFT 1'!$B:$B,0)),"") | N13: ATIVO | P13: =IFERROR(INDEX('DRAFT 1'!$L:$L,MATCH($B13,'DRAFT 1'!$B:$B,0)),"") | Q13: =IFERROR(INDEX('DRAFT 1'!$M:$M,MATCH($B13,'DRAFT 1'!$B:$B,0)),"") | R13: =IFERROR(INDEX('DRAFT 1'!$N:$N,MATCH($B13,'DRAFT 1'!$B:$B,0)),"") | S13: =IFERROR(INDEX('DRAFT 1'!$O:$O,MATCH($B13,'DRAFT 1'!$B:$B,0)),"") | T13: =IFERROR(INDEX('DRAFT 1'!$P:$P,MATCH($B13,'DRAFT 1'!$B:$B,0)),"") | U13: =IFERROR(INDEX('DRAFT 1'!$Q:$Q,MATCH($B13,'DRAFT 1'!$B:$B,0)),"") | V13: =IFERROR(INDEX('DRAFT 1'!$R:$R,MATCH($B13,'DRAFT 1'!$B:$B,0)),"") | W13: =IFERROR(INDEX('DRAFT 1'!$S:$S,MATCH($B13,'DRAFT 1'!$B:$B,0)),"") | X13: =IFERROR(INDEX('DRAFT 1'!$T:$T,MATCH($B13,'DRAFT 1'!$B:$B,0)),"") | Z13: =IFERROR(INDEX('DRAFT 1'!$U:$U,MATCH($B13,'DRAFT 1'!$B:$B,0)),"") | AA13: =IFERROR(INDEX('DRAFT 1'!$V:$V,MATCH($B13,'DRAFT 1'!$B:$B,0)),"") | AB13: =IFERROR(INDEX('DRAFT 1'!$W:$W,MATCH($B13,'DRAFT 1'!$B:$B,0)),"") | AC13: =IFERROR(INDEX('DRAFT 1'!$X:$X,MATCH($B13,'DRAFT 1'!$B:$B,0)),"") | AD13: =IFERROR(INDEX('DRAFT 1'!$Y:$Y,MATCH($B13,'DRAFT 1'!$B:$B,0)),"") | AE13: =IFERROR(INDEX('DRAFT 1'!$Z:$Z,MATCH($B13,'DRAFT 1'!$B:$B,0)),"") | AF13: =IFERROR(INDEX('DRAFT 1'!$AA:$AA,MATCH($B13,'DRAFT 1'!$B:$B,0)),"") | AG13: =IFERROR(INDEX('DRAFT 1'!$AB:$AB,MATCH($B13,'DRAFT 1'!$B:$B,0)),"") | AH13: =IFERROR(INDEX('DRAFT 1'!$AC:$AC,MATCH($B13,'DRAFT 1'!$B:$B,0)),"") | AI13: =IFERROR(INDEX('DRAFT 1'!$AD:$AD,MATCH($B13,'DRAFT 1'!$B:$B,0)),"") | AJ13: =IFERROR(INDEX('DRAFT 1'!$AE:$AE,MATCH($B13,'DRAFT 1'!$B:$B,0)),"") | AK13: =IFERROR(INDEX('DRAFT 1'!$AG:$AG,MATCH($B13,'DRAFT 1'!$B:$B,0)),"") | AL13: =IFERROR(INDEX('DRAFT 1'!$AH:$AH,MATCH($B13,'DRAFT 1'!$B:$B,0)),"") | AM13: =IFERROR(INDEX('DRAFT 1'!$AI:$AI,MATCH($B13,'DRAFT 1'!$B:$B,0)),"") | AN13: =IFERROR(INDEX('DRAFT 1'!$AJ:$AJ,MATCH($B13,'DRAFT 1'!$B:$B,0)),"") | AO13: =IFERROR(Y13/AN13,0) -> 0 | AP13: =IFERROR(INDEX('DRAFT 1'!$AK:$AK,MATCH($B13,'DRAFT 1'!$B:$B,0)),"") | AR13: RECOMPRA | AS13: =IFERROR(LOOKUP(2,1/('DRAFT 2'!$D:$D=$B13),'DRAFT 2'!$T:$T),"") -> 0 | AT13: =IFERROR(LOOKUP(2,1/('DRAFT 2'!$D:$D=$B13),'DRAFT 2'!$A:$A),"") -> 0 | AU13: =IFERROR(LOOKUP(2,1/('DRAFT 2'!$D:$D=$B13),'DRAFT 2'!$R:$R),"") -> 0 | AV13: =IFERROR(LOOKUP(2,1/('DRAFT 2'!$D:$D=$B13),'DRAFT 2'!$S:$S),"") -> 0 | AW13: EM DESENVOLVIMENTO | AX13: =IFERROR(LOOKUP(2,1/('DRAFT 2'!$D:$D=$B13),'DRAFT 2'!$M:$M),"") -> 0 | AY13: =IFERROR(LOOKUP(2,1/('DRAFT 2'!$D:$D=$B13),'DRAFT 2'!$K:$K),"") -> 0 | BG13: =IFERROR(LOOKUP(2,1/('DRAFT 2'!$D:$D=$B13),'DRAFT 2'!$U:$U),"") -> 0 | BH13: =IFERROR(LOOKUP(2,1/('DRAFT 2'!$D:$D=$B13),'DRAFT 2'!$V:$V),"") -> 0 | CE13: =IFERROR(AJ13,0) | CF13: =IFERROR(LOOKUP(2,1/('DRAFT 2'!$D:$D=$B13)*('DRAFT 2'!$A:$A>=DATE(2026,1,1))*('DRAFT 2'!$A:$A<DATE(2026,IF(1=12,1+1,1+1),1)),'DRAFT 2'!$A:$A),"") -> 0 | CG13: =COUNTIFS('DRAFT 2'!$D:$D,$B13,'DRAFT 2'!$A:$A,">="&DATE(2026,1,1),'DRAFT 2'!$A:$A,"<="&DATE(2026,1,7)) -> 0 | CH13: =COUNTIFS('DRAFT 2'!$D:$D,$B13,'DRAFT 2'!$A:$A,">="&DATE(2026,1,8),'DRAFT 2'!$A:$A,"<="&DATE(2026,1,14)) -> 0 | CI13: =COUNTIFS('DRAFT 2'!$D:$D,$B13,'DRAFT 2'!$A:$A,">="&DATE(2026,1,15),'DRAFT 2'!$A:$A,"<="&DATE(2026,1,21)) -> 0 | CJ13: =COUNTIFS('DRAFT 2'!$D:$D,$B13,'DRAFT 2'!$A:$A,">="&DATE(2026,1,22),'DRAFT 2'!$A:$A,"<"&DATE(2026,IF(1=12,1+1,1+1),1)) -> 0 | CK13: =SUM(CG13:CJ13) -> 0 | CT13: 0 | CU13: =IFERROR(LOOKUP(2,1/('DRAFT 2'!$D:$D=$B13)*('DRAFT 2'!$A:$A>=DATE(2026,2,1))*('DRAFT 2'!$A:$A<DATE(2026,IF(2=12,2+1,2+1),1)),'DRAFT 2'!$A:$A),"") -> 0 | CV13: =COUNTIFS('DRAFT 2'!$D:$D,$B13,'DRAFT 2'!$A:$A,">="&DATE(2026,2,1),'DRAFT 2'!$A:$A,"<="&DATE(2026,2,7)) -> 0 | CW13: =COUNTIFS('DRAFT 2'!$D:$D,$B13,'DRAFT 2'!$A:$A,">="&DATE(2026,2,8),'DRAFT 2'!$A:$A,"<="&DATE(2026,2,14)) -> 0 | CX13: =COUNTIFS('DRAFT 2'!$D:$D,$B13,'DRAFT 2'!$A:$A,">="&DATE(2026,2,15),'DRAFT 2'!$A:$A,"<="&DATE(2026,2,21)) -> 0 | CY13: =COUNTIFS('DRAFT 2'!$D:$D,$B13,'DRAFT 2'!$A:$A,">="&DATE(2026,2,22),'DRAFT 2'!$A:$A,"<"&DATE(2026,IF(2=12,2+1,2+1),1)) -> 0 | CZ13: =SUM(CV13:CY13) -> 0 | DJ13: =IFERROR(LOOKUP(2,1/('DRAFT 2'!$D:$D=$B13)*('DRAFT 2'!$A:$A>=DATE(2026,3,1))*('DRAFT 2'!$A:$A<DATE(2026,IF(3=12,3+1,3+1),1)),'DRAFT 2'!$A:$A),"") -> 0 | DK13: =COUNTIFS('DRAFT 2'!$D:$D,$B13,'DRAFT 2'!$A:$A,">="&DATE(2026,3,1),'DRAFT 2'!$A:$A,"<="&DATE(2026,3,7)) -> 0 | DL13: =COUNTIFS('DRAFT 2'!$D:$D,$B13,'DRAFT 2'!$A:$A,">="&DATE(2026,3,8),'DRAFT 2'!$A:$A,"<="&DATE(2026,3,14)) -> 0 | DM13: =COUNTIFS('DRAFT 2'!$D:$D,$B13,'DRAFT 2'!$A:$A,">="&DATE(2026,3,15),'DRAFT 2'!$A:$A,"<="&DATE(2026,3,21)) -> 0 | DN13: =COUNTIFS('DRAFT 2'!$D:$D,$B13,'DRAFT 2'!$A:$A,">="&DATE(2026,3,22),'DRAFT 2'!$A:$A,"<"&DATE(2026,IF(3=12,3+1,3+1),1)) -> 0 | DO13: =SUM(DK13:DN13) -> 0 | DZ13: =IFERROR(LOOKUP(2,1/('DRAFT 2'!$D:$D=$B13)*('DRAFT 2'!$A:$A>=DATE(2026,4,1))*('DRAFT 2'!$A:$A<DATE(2026,IF(4=12,4+1,4+1),1)),'DRAFT 2'!$A:$A),"") -> 0 | EA13: =COUNTIFS('DRAFT 2'!$D:$D,$B13,'DRAFT 2'!$A:$A,">="&DATE(2026,4,1),'DRAFT 2'!$A:$A,"<="&DATE(2026,4,7)) -> 0 | EB13: =COUNTIFS('DRAFT 2'!$D:$D,$B13,'DRAFT 2'!$A:$A,">="&DATE(2026,4,8),'DRAFT 2'!$A:$A,"<="&DATE(2026,4,14)) -> 0 | EC13: =COUNTIFS('DRAFT 2'!$D:$D,$B13,'DRAFT 2'!$A:$A,">="&DATE(2026,4,15),'DRAFT 2'!$A:$A,"<="&DATE(2026,4,21)) -> 0 | ED13: =COUNTIFS('DRAFT 2'!$D:$D,$B13,'DRAFT 2'!$A:$A,">="&DATE(2026,4,22),'DRAFT 2'!$A:$A,"<"&DATE(2026,IF(4=12,4+1,4+1),1)) -> 0 | EE13: =SUM(EA13:ED13) -> 0 | EO13: =IFERROR(LOOKUP(2,1/('DRAFT 2'!$D:$D=$B13)*('DRAFT 2'!$A:$A>=DATE(2026,5,1))*('DRAFT 2'!$A:$A<DATE(2026,IF(5=12,5+1,5+1),1)),'DRAFT 2'!$A:$A),"") -> 0 | EP13: =COUNTIFS('DRAFT 2'!$D:$D,$B13,'DRAFT 2'!$A:$A,">="&DATE(2026,5,1),'DRAFT 2'!$A:$A,"<="&DATE(2026,5,7)) -> 0 | EQ13: =COUNTIFS('DRAFT 2'!$D:$D,$B13,'DRAFT 2'!$A:$A,">="&DATE(2026,5,8),'DRAFT 2'!$A:$A,"<="&DATE(2026,5,14)) -> 0 | ER13: =COUNTIFS('DRAFT 2'!$D:$D,$B13,'DRAFT 2'!$A:$A,">="&DATE(2026,5,15),'DRAFT 2'!$A:$A,"<="&DATE(2026,5,21)) -> 0 | ES13: =COUNTIFS('DRAFT 2'!$D:$D,$B13,'DRAFT 2'!$A:$A,">="&DATE(2026,5,22),'DRAFT 2'!$A:$A,"<"&DATE(2026,IF(5=12,5+1,5+1),1)) -> 0 | ET13: =SUM(EP13:ES13) -> 0 | FD13: =IFERROR(LOOKUP(2,1/('DRAFT 2'!$D:$D=$B13)*('DRAFT 2'!$A:$A>=DATE(2026,6,1))*('DRAFT 2'!$A:$A<DATE(2026,IF(6=12,6+1,6+1),1)),'DRAFT 2'!$A:$A),"") -> 0 | FE13: =COUNTIFS('DRAFT 2'!$D:$D,$B13,'DRAFT 2'!$A:$A,">="&DATE(2026,6,1),'DRAFT 2'!$A:$A,"<="&DATE(2026,6,7)) -> 0 | FF13: =COUNTIFS('DRAFT 2'!$D:$D,$B13,'DRAFT 2'!$A:$A,">="&DATE(2026,6,8),'DRAFT 2'!$A:$A,"<="&DATE(2026,6,14)) -> 0 | FG13: =COUNTIFS('DRAFT 2'!$D:$D,$B13,'DRAFT 2'!$A:$A,">="&DATE(2026,6,15),'DRAFT 2'!$A:$A,"<="&DATE(2026,6,21)) -> 0 | FH13: =COUNTIFS('DRAFT 2'!$D:$D,$B13,'DRAFT 2'!$A:$A,">="&DATE(2026,6,22),'DRAFT 2'!$A:$A,"<"&DATE(2026,IF(6=12,6+1,6+1),1)) -> 0 | FI13: =SUM(FE13:FH13) -> 0 | FT13: =IFERROR(LOOKUP(2,1/('DRAFT 2'!$D:$D=$B13)*('DRAFT 2'!$A:$A>=DATE(2026,7,1))*('DRAFT 2'!$A:$A<DATE(2026,IF(7=12,7+1,7+1),1)),'DRAFT 2'!$A:$A),"") -> 0 | FU13: =COUNTIFS('DRAFT 2'!$D:$D,$B13,'DRAFT 2'!$A:$A,">="&DATE(2026,7,1),'DRAFT 2'!$A:$A,"<="&DATE(2026,7,7)) -> 0 | FV13: =COUNTIFS('DRAFT 2'!$D:$D,$B13,'DRAFT 2'!$A:$A,">="&DATE(2026,7,8),'DRAFT 2'!$A:$A,"<="&DATE(2026,7,14)) -> 0 | FW13: =COUNTIFS('DRAFT 2'!$D:$D,$B13,'DRAFT 2'!$A:$A,">="&DATE(2026,7,15),'DRAFT 2'!$A:$A,"<="&DATE(2026,7,21)) -> 0 | FX13: =COUNTIFS('DRAFT 2'!$D:$D,$B13,'DRAFT 2'!$A:$A,">="&DATE(2026,7,22),'DRAFT 2'!$A:$A,"<"&DATE(2026,IF(7=12,7+1,7+1),1)) -> 0 | FY13: =SUM(FU13:FX13) -> 0 | GI13: =IFERROR(LOOKUP(2,1/('DRAFT 2'!$D:$D=$B13)*('DRAFT 2'!$A:$A>=DATE(2026,8,1))*('DRAFT 2'!$A:$A<DATE(2026,IF(8=12,8+1,8+1),1)),'DRAFT 2'!$A:$A),"") -> 0 | GJ13: =COUNTIFS('DRAFT 2'!$D:$D,$B13,'DRAFT 2'!$A:$A,">="&DATE(2026,8,1),'DRAFT 2'!$A:$A,"<="&DATE(2026,8,7)) -> 0 | GK13: =COUNTIFS('DRAFT 2'!$D:$D,$B13,'DRAFT 2'!$A:$A,">="&DATE(2026,8,8),'DRAFT 2'!$A:$A,"<="&DATE(2026,8,14)) -> 0 | GL13: =COUNTIFS('DRAFT 2'!$D:$D,$B13,'DRAFT 2'!$A:$A,">="&DATE(2026,8,15),'DRAFT 2'!$A:$A,"<="&DATE(2026,8,21)) -> 0 | GM13: =COUNTIFS('DRAFT 2'!$D:$D,$B13,'DRAFT 2'!$A:$A,">="&DATE(2026,8,22),'DRAFT 2'!$A:$A,"<"&DATE(2026,IF(8=12,8+1,8+1),1)) -> 0 | GN13: =SUM(GJ13:GM13) -> 0 | GX13: =IFERROR(LOOKUP(2,1/('DRAFT 2'!$D:$D=$B13)*('DRAFT 2'!$A:$A>=DATE(2026,9,1))*('DRAFT 2'!$A:$A<DATE(2026,IF(9=12,9+1,9+1),1)),'DRAFT 2'!$A:$A),"") -> 0 | GY13: =COUNTIFS('DRAFT 2'!$D:$D,$B13,'DRAFT 2'!$A:$A,">="&DATE(2026,9,1),'DRAFT 2'!$A:$A,"<="&DATE(2026,9,7)) -> 0 | GZ13: =COUNTIFS('DRAFT 2'!$D:$D,$B13,'DRAFT 2'!$A:$A,">="&DATE(2026,9,8),'DRAFT 2'!$A:$A,"<="&DATE(2026,9,14)) -> 0 | HA13: =COUNTIFS('DRAFT 2'!$D:$D,$B13,'DRAFT 2'!$A:$A,">="&DATE(2026,9,15),'DRAFT 2'!$A:$A,"<="&DATE(2026,9,21)) -> 0 | HB13: =COUNTIFS('DRAFT 2'!$D:$D,$B13,'DRAFT 2'!$A:$A,">="&DATE(2026,9,22),'DRAFT 2'!$A:$A,"<"&DATE(2026,IF(9=12,9+1,9+1),1)) -> 0 | HC13: =SUM(GY13:HB13) -> 0 | HN13: =IFERROR(LOOKUP(2,1/('DRAFT 2'!$D:$D=$B13)*('DRAFT 2'!$A:$A>=DATE(2026,10,1))*('DRAFT 2'!$A:$A<DATE(2026,IF(10=12,10+1,10+1),1)),'DRAFT 2'!$A:$A),"") -> 0 | HO13: =COUNTIFS('DRAFT 2'!$D:$D,$B13,'DRAFT 2'!$A:$A,">="&DATE(2026,10,1),'DRAFT 2'!$A:$A,"<="&DATE(2026,10,7)) -> 0 | HP13: =COUNTIFS('DRAFT 2'!$D:$D,$B13,'DRAFT 2'!$A:$A,">="&DATE(2026,10,8),'DRAFT 2'!$A:$A,"<="&DATE(2026,10,14)) -> 0 | HQ13: =COUNTIFS('DRAFT 2'!$D:$D,$B13,'DRAFT 2'!$A:$A,">="&DATE(2026,10,15),'DRAFT 2'!$A:$A,"<="&DATE(2026,10,21)) -> 0 | HR13: =COUNTIFS('DRAFT 2'!$D:$D,$B13,'DRAFT 2'!$A:$A,">="&DATE(2026,10,22),'DRAFT 2'!$A:$A,"<"&DATE(2026,IF(10=12,10+1,10+1),1)) -> 0 | HS13: =SUM(HO13:HR13) -> 0 | IC13: =IFERROR(LOOKUP(2,1/('DRAFT 2'!$D:$D=$B13)*('DRAFT 2'!$A:$A>=DATE(2026,11,1))*('DRAFT 2'!$A:$A<DATE(2026,IF(11=12,11+1,11+1),1)),'DRAFT 2'!$A:$A),"") -> 0 | ID13: =COUNTIFS('DRAFT 2'!$D:$D,$B13,'DRAFT 2'!$A:$A,">="&DATE(2026,11,1),'DRAFT 2'!$A:$A,"<="&DATE(2026,11,7)) -> 0 | IE13: =COUNTIFS('DRAFT 2'!$D:$D,$B13,'DRAFT 2'!$A:$A,">="&DATE(2026,11,8),'DRAFT 2'!$A:$A,"<="&DATE(2026,11,14)) -> 0 | IF13: =COUNTIFS('DRAFT 2'!$D:$D,$B13,'DRAFT 2'!$A:$A,">="&DATE(2026,11,15),'DRAFT 2'!$A:$A,"<="&DATE(2026,11,21)) -> 0 | IG13: =COUNTIFS('DRAFT 2'!$D:$D,$B13,'DRAFT 2'!$A:$A,">="&DATE(2026,11,22),'DRAFT 2'!$A:$A,"<"&DATE(2026,IF(11=12,11+1,11+1),1)) -> 0 | IH13: =SUM(ID13:IG13) -> 0 | IR13: =IFERROR(LOOKUP(2,1/('DRAFT 2'!$D:$D=$B13)*('DRAFT 2'!$A:$A>=DATE(2026,12,1))*('DRAFT 2'!$A:$A<DATE(2026,IF(12=12,12+1,12+1),1)),'DRAFT 2'!$A:$A),"") -> 0 | IS13: =COUNTIFS('DRAFT 2'!$D:$D,$B13,'DRAFT 2'!$A:$A,">="&DATE(2026,12,1),'DRAFT 2'!$A:$A,"<="&DATE(2026,12,7)) -> 0 | IT13: =COUNTIFS('DRAFT 2'!$D:$D,$B13,'DRAFT 2'!$A:$A,">="&DATE(2026,12,8),'DRAFT 2'!$A:$A,"<="&DATE(2026,12,14)) -> 0 | IU13: =COUNTIFS('DRAFT 2'!$D:$D,$B13,'DRAFT 2'!$A:$A,">="&DATE(2026,12,15),'DRAFT 2'!$A:$A,"<="&DATE(2026,12,21)) -> 0 | IV13: =COUNTIFS('DRAFT 2'!$D:$D,$B13,'DRAFT 2'!$A:$A,">="&DATE(2026,12,22),'DRAFT 2'!$A:$A,"<"&DATE(2026,IF(12=12,12+1,12+1),1)) -> 0 | IW13: =SUM(IS13:IV13) -> 0
A14: =IFERROR(INDEX('DRAFT 1'!$A:$A,MATCH($B14,'DRAFT 1'!$B:$B,0)),"") | C14: =IFERROR(INDEX('DRAFT 1'!$C:$C,MATCH($B14,'DRAFT 1'!$B:$B,0)),"") | D14: =IFERROR(INDEX('DRAFT 1'!$D:$D,MATCH($B14,'DRAFT 1'!$B:$B,0)),"") | E14: =IFERROR(INDEX('DRAFT 1'!$E:$E,MATCH($B14,'DRAFT 1'!$B:$B,0)),"") | F14: =IFERROR(INDEX('DRAFT 1'!$F:$F,MATCH($B14,'DRAFT 1'!$B:$B,0)),"") | G14: =IFERROR(INDEX('DRAFT 1'!$G:$G,MATCH($B14,'DRAFT 1'!$B:$B,0)),"") | H14: =IFERROR(INDEX('DRAFT 1'!$H:$H,MATCH($B14,'DRAFT 1'!$B:$B,0)),"") | I14: DEMAIS CLIENTES | K14: =IFERROR(INDEX('DRAFT 1'!$AL:$AL,MATCH($B14,'DRAFT 1'!$B:$B,0)),"") | L14: =IFERROR(INDEX('DRAFT 1'!$J:$J,MATCH($B14,'DRAFT 1'!$B:$B,0)),"") | M14: =IFERROR(INDEX('DRAFT 1'!$K:$K,MATCH($B14,'DRAFT 1'!$B:$B,0)),"") | N14: PROSPECT | P14: =IFERROR(INDEX('DRAFT 1'!$L:$L,MATCH($B14,'DRAFT 1'!$B:$B,0)),"") | Q14: =IFERROR(INDEX('DRAFT 1'!$M:$M,MATCH($B14,'DRAFT 1'!$B:$B,0)),"") | R14: =IFERROR(INDEX('DRAFT 1'!$N:$N,MATCH($B14,'DRAFT 1'!$B:$B,0)),"") | S14: =IFERROR(INDEX('DRAFT 1'!$O:$O,MATCH($B14,'DRAFT 1'!$B:$B,0)),"") | T14: =IFERROR(INDEX('DRAFT 1'!$P:$P,MATCH($B14,'DRAFT 1'!$B:$B,0)),"") | U14: =IFERROR(INDEX('DRAFT 1'!$Q:$Q,MATCH($B14,'DRAFT 1'!$B:$B,0)),"") | V14: =IFERROR(INDEX('DRAFT 1'!$R:$R,MATCH($B14,'DRAFT 1'!$B:$B,0)),"") | W14: =IFERROR(INDEX('DRAFT 1'!$S:$S,MATCH($B14,'DRAFT 1'!$B:$B,0)),"") | X14: =IFERROR(INDEX('DRAFT 1'!$T:$T,MATCH($B14,'DRAFT 1'!$B:$B,0)),"") | Z14: =IFERROR(INDEX('DRAFT 1'!$U:$U,MATCH($B14,'DRAFT 1'!$B:$B,0)),"") | AA14: =IFERROR(INDEX('DRAFT 1'!$V:$V,MATCH($B14,'DRAFT 1'!$B:$B,0)),"") | AB14: =IFERROR(INDEX('DRAFT 1'!$W:$W,MATCH($B14,'DRAFT 1'!$B:$B,0)),"") | AC14: =IFERROR(INDEX('DRAFT 1'!$X:$X,MATCH($B14,'DRAFT 1'!$B:$B,0)),"") | AD14: =IFERROR(INDEX('DRAFT 1'!$Y:$Y,MATCH($B14,'DRAFT 1'!$B:$B,0)),"") | AE14: =IFERROR(INDEX('DRAFT 1'!$Z:$Z,MATCH($B14,'DRAFT 1'!$B:$B,0)),"") | AF14: =IFERROR(INDEX('DRAFT 1'!$AA:$AA,MATCH($B14,'DRAFT 1'!$B:$B,0)),"") | AG14: =IFERROR(INDEX('DRAFT 1'!$AB:$AB,MATCH($B14,'DRAFT 1'!$B:$B,0)),"") | AH14: =IFERROR(INDEX('DRAFT 1'!$AC:$AC,MATCH($B14,'DRAFT 1'!$B:$B,0)),"") | AI14: =IFERROR(INDEX('DRAFT 1'!$AD:$AD,MATCH($B14,'DRAFT 1'!$B:$B,0)),"") | AJ14: =IFERROR(INDEX('DRAFT 1'!$AE:$AE,MATCH($B14,'DRAFT 1'!$B:$B,0)),"") | AK14: =IFERROR(INDEX('DRAFT 1'!$AG:$AG,MATCH($B14,'DRAFT 1'!$B:$B,0)),"") | AL14: =IFERROR(INDEX('DRAFT 1'!$AH:$AH,MATCH($B14,'DRAFT 1'!$B:$B,0)),"") | AM14: =IFERROR(INDEX('DRAFT 1'!$AI:$AI,MATCH($B14,'DRAFT 1'!$B:$B,0)),"") | AN14: =IFERROR(INDEX('DRAFT 1'!$AJ:$AJ,MATCH($B14,'DRAFT 1'!$B:$B,0)),"") | AO14: =IFERROR(Y14/AN14,0) -> 0 | AP14: =IFERROR(INDEX('DRAFT 1'!$AK:$AK,MATCH($B14,'DRAFT 1'!$B:$B,0)),"") | AR14: RECOMPRA | AS14: =IFERROR(LOOKUP(2,1/('DRAFT 2'!$D:$D=$B14),'DRAFT 2'!$T:$T),"") -> 0 | AT14: =IFERROR(LOOKUP(2,1/('DRAFT 2'!$D:$D=$B14),'DRAFT 2'!$A:$A),"") -> 0 | AU14: =IFERROR(LOOKUP(2,1/('DRAFT 2'!$D:$D=$B14),'DRAFT 2'!$R:$R),"") -> 0 | AV14: =IFERROR(LOOKUP(2,1/('DRAFT 2'!$D:$D=$B14),'DRAFT 2'!$S:$S),"") -> 0 | AW14: NOVO | AX14: =IFERROR(LOOKUP(2,1/('DRAFT 2'!$D:$D=$B14),'DRAFT 2'!$M:$M),"") -> 0 | AY14: =IFERROR(LOOKUP(2,1/('DRAFT 2'!$D:$D=$B14),'DRAFT 2'!$K:$K),"") -> 0 | BG14: =IFERROR(LOOKUP(2,1/('DRAFT 2'!$D:$D=$B14),'DRAFT 2'!$U:$U),"") -> 0 | BH14: =IFERROR(LOOKUP(2,1/('DRAFT 2'!$D:$D=$B14),'DRAFT 2'!$V:$V),"") -> 0 | CE14: =IFERROR(AJ14,0) | CF14: =IFERROR(LOOKUP(2,1/('DRAFT 2'!$D:$D=$B14)*('DRAFT 2'!$A:$A>=DATE(2026,1,1))*('DRAFT 2'!$A:$A<DATE(2026,IF(1=12,1+1,1+1),1)),'DRAFT 2'!$A:$A),"") -> 0 | CG14: =COUNTIFS('DRAFT 2'!$D:$D,$B14,'DRAFT 2'!$A:$A,">="&DATE(2026,1,1),'DRAFT 2'!$A:$A,"<="&DATE(2026,1,7)) -> 0 | CH14: =COUNTIFS('DRAFT 2'!$D:$D,$B14,'DRAFT 2'!$A:$A,">="&DATE(2026,1,8),'DRAFT 2'!$A:$A,"<="&DATE(2026,1,14)) -> 0 | CI14: =COUNTIFS('DRAFT 2'!$D:$D,$B14,'DRAFT 2'!$A:$A,">="&DATE(2026,1,15),'DRAFT 2'!$A:$A,"<="&DATE(2026,1,21)) -> 0 | CJ14: =COUNTIFS('DRAFT 2'!$D:$D,$B14,'DRAFT 2'!$A:$A,">="&DATE(2026,1,22),'DRAFT 2'!$A:$A,"<"&DATE(2026,IF(1=12,1+1,1+1),1)) -> 0 | CK14: =SUM(CG14:CJ14) -> 0 | CT14: 0 | CU14: =IFERROR(LOOKUP(2,1/('DRAFT 2'!$D:$D=$B14)*('DRAFT 2'!$A:$A>=DATE(2026,2,1))*('DRAFT 2'!$A:$A<DATE(2026,IF(2=12,2+1,2+1),1)),'DRAFT 2'!$A:$A),"") -> 0 | CV14: =COUNTIFS('DRAFT 2'!$D:$D,$B14,'DRAFT 2'!$A:$A,">="&DATE(2026,2,1),'DRAFT 2'!$A:$A,"<="&DATE(2026,2,7)) -> 0 | CW14: =COUNTIFS('DRAFT 2'!$D:$D,$B14,'DRAFT 2'!$A:$A,">="&DATE(2026,2,8),'DRAFT 2'!$A:$A,"<="&DATE(2026,2,14)) -> 0 | CX14: =COUNTIFS('DRAFT 2'!$D:$D,$B14,'DRAFT 2'!$A:$A,">="&DATE(2026,2,15),'DRAFT 2'!$A:$A,"<="&DATE(2026,2,21)) -> 0 | CY14: =COUNTIFS('DRAFT 2'!$D:$D,$B14,'DRAFT 2'!$A:$A,">="&DATE(2026,2,22),'DRAFT 2'!$A:$A,"<"&DATE(2026,IF(2=12,2+1,2+1),1)) -> 0 | CZ14: =SUM(CV14:CY14) -> 0 | DJ14: =IFERROR(LOOKUP(2,1/('DRAFT 2'!$D:$D=$B14)*('DRAFT 2'!$A:$A>=DATE(2026,3,1))*('DRAFT 2'!$A:$A<DATE(2026,IF(3=12,3+1,3+1),1)),'DRAFT 2'!$A:$A),"") -> 0 | DK14: =COUNTIFS('DRAFT 2'!$D:$D,$B14,'DRAFT 2'!$A:$A,">="&DATE(2026,3,1),'DRAFT 2'!$A:$A,"<="&DATE(2026,3,7)) -> 0 | DL14: =COUNTIFS('DRAFT 2'!$D:$D,$B14,'DRAFT 2'!$A:$A,">="&DATE(2026,3,8),'DRAFT 2'!$A:$A,"<="&DATE(2026,3,14)) -> 0 | DM14: =COUNTIFS('DRAFT 2'!$D:$D,$B14,'DRAFT 2'!$A:$A,">="&DATE(2026,3,15),'DRAFT 2'!$A:$A,"<="&DATE(2026,3,21)) -> 0 | DN14: =COUNTIFS('DRAFT 2'!$D:$D,$B14,'DRAFT 2'!$A:$A,">="&DATE(2026,3,22),'DRAFT 2'!$A:$A,"<"&DATE(2026,IF(3=12,3+1,3+1),1)) -> 0 | DO14: =SUM(DK14:DN14) -> 0 | DZ14: =IFERROR(LOOKUP(2,1/('DRAFT 2'!$D:$D=$B14)*('DRAFT 2'!$A:$A>=DATE(2026,4,1))*('DRAFT 2'!$A:$A<DATE(2026,IF(4=12,4+1,4+1),1)),'DRAFT 2'!$A:$A),"") -> 0 | EA14: =COUNTIFS('DRAFT 2'!$D:$D,$B14,'DRAFT 2'!$A:$A,">="&DATE(2026,4,1),'DRAFT 2'!$A:$A,"<="&DATE(2026,4,7)) -> 0 | EB14: =COUNTIFS('DRAFT 2'!$D:$D,$B14,'DRAFT 2'!$A:$A,">="&DATE(2026,4,8),'DRAFT 2'!$A:$A,"<="&DATE(2026,4,14)) -> 0 | EC14: =COUNTIFS('DRAFT 2'!$D:$D,$B14,'DRAFT 2'!$A:$A,">="&DATE(2026,4,15),'DRAFT 2'!$A:$A,"<="&DATE(2026,4,21)) -> 0 | ED14: =COUNTIFS('DRAFT 2'!$D:$D,$B14,'DRAFT 2'!$A:$A,">="&DATE(2026,4,22),'DRAFT 2'!$A:$A,"<"&DATE(2026,IF(4=12,4+1,4+1),1)) -> 0 | EE14: =SUM(EA14:ED14) -> 0 | EO14: =IFERROR(LOOKUP(2,1/('DRAFT 2'!$D:$D=$B14)*('DRAFT 2'!$A:$A>=DATE(2026,5,1))*('DRAFT 2'!$A:$A<DATE(2026,IF(5=12,5+1,5+1),1)),'DRAFT 2'!$A:$A),"") -> 0 | EP14: =COUNTIFS('DRAFT 2'!$D:$D,$B14,'DRAFT 2'!$A:$A,">="&DATE(2026,5,1),'DRAFT 2'!$A:$A,"<="&DATE(2026,5,7)) -> 0 | EQ14: =COUNTIFS('DRAFT 2'!$D:$D,$B14,'DRAFT 2'!$A:$A,">="&DATE(2026,5,8),'DRAFT 2'!$A:$A,"<="&DATE(2026,5,14)) -> 0 | ER14: =COUNTIFS('DRAFT 2'!$D:$D,$B14,'DRAFT 2'!$A:$A,">="&DATE(2026,5,15),'DRAFT 2'!$A:$A,"<="&DATE(2026,5,21)) -> 0 | ES14: =COUNTIFS('DRAFT 2'!$D:$D,$B14,'DRAFT 2'!$A:$A,">="&DATE(2026,5,22),'DRAFT 2'!$A:$A,"<"&DATE(2026,IF(5=12,5+1,5+1),1)) -> 0 | ET14: =SUM(EP14:ES14) -> 0 | FD14: =IFERROR(LOOKUP(2,1/('DRAFT 2'!$D:$D=$B14)*('DRAFT 2'!$A:$A>=DATE(2026,6,1))*('DRAFT 2'!$A:$A<DATE(2026,IF(6=12,6+1,6+1),1)),'DRAFT 2'!$A:$A),"") -> 0 | FE14: =COUNTIFS('DRAFT 2'!$D:$D,$B14,'DRAFT 2'!$A:$A,">="&DATE(2026,6,1),'DRAFT 2'!$A:$A,"<="&DATE(2026,6,7)) -> 0 | FF14: =COUNTIFS('DRAFT 2'!$D:$D,$B14,'DRAFT 2'!$A:$A,">="&DATE(2026,6,8),'DRAFT 2'!$A:$A,"<="&DATE(2026,6,14)) -> 0 | FG14: =COUNTIFS('DRAFT 2'!$D:$D,$B14,'DRAFT 2'!$A:$A,">="&DATE(2026,6,15),'DRAFT 2'!$A:$A,"<="&DATE(2026,6,21)) -> 0 | FH14: =COUNTIFS('DRAFT 2'!$D:$D,$B14,'DRAFT 2'!$A:$A,">="&DATE(2026,6,22),'DRAFT 2'!$A:$A,"<"&DATE(2026,IF(6=12,6+1,6+1),1)) -> 0 | FI14: =SUM(FE14:FH14) -> 0 | FT14: =IFERROR(LOOKUP(2,1/('DRAFT 2'!$D:$D=$B14)*('DRAFT 2'!$A:$A>=DATE(2026,7,1))*('DRAFT 2'!$A:$A<DATE(2026,IF(7=12,7+1,7+1),1)),'DRAFT 2'!$A:$A),"") -> 0 | FU14: =COUNTIFS('DRAFT 2'!$D:$D,$B14,'DRAFT 2'!$A:$A,">="&DATE(2026,7,1),'DRAFT 2'!$A:$A,"<="&DATE(2026,7,7)) -> 0 | FV14: =COUNTIFS('DRAFT 2'!$D:$D,$B14,'DRAFT 2'!$A:$A,">="&DATE(2026,7,8),'DRAFT 2'!$A:$A,"<="&DATE(2026,7,14)) -> 0 | FW14: =COUNTIFS('DRAFT 2'!$D:$D,$B14,'DRAFT 2'!$A:$A,">="&DATE(2026,7,15),'DRAFT 2'!$A:$A,"<="&DATE(2026,7,21)) -> 0 | FX14: =COUNTIFS('DRAFT 2'!$D:$D,$B14,'DRAFT 2'!$A:$A,">="&DATE(2026,7,22),'DRAFT 2'!$A:$A,"<"&DATE(2026,IF(7=12,7+1,7+1),1)) -> 0 | FY14: =SUM(FU14:FX14) -> 0 | GI14: =IFERROR(LOOKUP(2,1/('DRAFT 2'!$D:$D=$B14)*('DRAFT 2'!$A:$A>=DATE(2026,8,1))*('DRAFT 2'!$A:$A<DATE(2026,IF(8=12,8+1,8+1),1)),'DRAFT 2'!$A:$A),"") -> 0 | GJ14: =COUNTIFS('DRAFT 2'!$D:$D,$B14,'DRAFT 2'!$A:$A,">="&DATE(2026,8,1),'DRAFT 2'!$A:$A,"<="&DATE(2026,8,7)) -> 0 | GK14: =COUNTIFS('DRAFT 2'!$D:$D,$B14,'DRAFT 2'!$A:$A,">="&DATE(2026,8,8),'DRAFT 2'!$A:$A,"<="&DATE(2026,8,14)) -> 0 | GL14: =COUNTIFS('DRAFT 2'!$D:$D,$B14,'DRAFT 2'!$A:$A,">="&DATE(2026,8,15),'DRAFT 2'!$A:$A,"<="&DATE(2026,8,21)) -> 0 | GM14: =COUNTIFS('DRAFT 2'!$D:$D,$B14,'DRAFT 2'!$A:$A,">="&DATE(2026,8,22),'DRAFT 2'!$A:$A,"<"&DATE(2026,IF(8=12,8+1,8+1),1)) -> 0 | GN14: =SUM(GJ14:GM14) -> 0 | GX14: =IFERROR(LOOKUP(2,1/('DRAFT 2'!$D:$D=$B14)*('DRAFT 2'!$A:$A>=DATE(2026,9,1))*('DRAFT 2'!$A:$A<DATE(2026,IF(9=12,9+1,9+1),1)),'DRAFT 2'!$A:$A),"") -> 0 | GY14: =COUNTIFS('DRAFT 2'!$D:$D,$B14,'DRAFT 2'!$A:$A,">="&DATE(2026,9,1),'DRAFT 2'!$A:$A,"<="&DATE(2026,9,7)) -> 0 | GZ14: =COUNTIFS('DRAFT 2'!$D:$D,$B14,'DRAFT 2'!$A:$A,">="&DATE(2026,9,8),'DRAFT 2'!$A:$A,"<="&DATE(2026,9,14)) -> 0 | HA14: =COUNTIFS('DRAFT 2'!$D:$D,$B14,'DRAFT 2'!$A:$A,">="&DATE(2026,9,15),'DRAFT 2'!$A:$A,"<="&DATE(2026,9,21)) -> 0 | HB14: =COUNTIFS('DRAFT 2'!$D:$D,$B14,'DRAFT 2'!$A:$A,">="&DATE(2026,9,22),'DRAFT 2'!$A:$A,"<"&DATE(2026,IF(9=12,9+1,9+1),1)) -> 0 | HC14: =SUM(GY14:HB14) -> 0 | HN14: =IFERROR(LOOKUP(2,1/('DRAFT 2'!$D:$D=$B14)*('DRAFT 2'!$A:$A>=DATE(2026,10,1))*('DRAFT 2'!$A:$A<DATE(2026,IF(10=12,10+1,10+1),1)),'DRAFT 2'!$A:$A),"") -> 0 | HO14: =COUNTIFS('DRAFT 2'!$D:$D,$B14,'DRAFT 2'!$A:$A,">="&DATE(2026,10,1),'DRAFT 2'!$A:$A,"<="&DATE(2026,10,7)) -> 0 | HP14: =COUNTIFS('DRAFT 2'!$D:$D,$B14,'DRAFT 2'!$A:$A,">="&DATE(2026,10,8),'DRAFT 2'!$A:$A,"<="&DATE(2026,10,14)) -> 0 | HQ14: =COUNTIFS('DRAFT 2'!$D:$D,$B14,'DRAFT 2'!$A:$A,">="&DATE(2026,10,15),'DRAFT 2'!$A:$A,"<="&DATE(2026,10,21)) -> 0 | HR14: =COUNTIFS('DRAFT 2'!$D:$D,$B14,'DRAFT 2'!$A:$A,">="&DATE(2026,10,22),'DRAFT 2'!$A:$A,"<"&DATE(2026,IF(10=12,10+1,10+1),1)) -> 0 | HS14: =SUM(HO14:HR14) -> 0 | IC14: =IFERROR(LOOKUP(2,1/('DRAFT 2'!$D:$D=$B14)*('DRAFT 2'!$A:$A>=DATE(2026,11,1))*('DRAFT 2'!$A:$A<DATE(2026,IF(11=12,11+1,11+1),1)),'DRAFT 2'!$A:$A),"") -> 0 | ID14: =COUNTIFS('DRAFT 2'!$D:$D,$B14,'DRAFT 2'!$A:$A,">="&DATE(2026,11,1),'DRAFT 2'!$A:$A,"<="&DATE(2026,11,7)) -> 0 | IE14: =COUNTIFS('DRAFT 2'!$D:$D,$B14,'DRAFT 2'!$A:$A,">="&DATE(2026,11,8),'DRAFT 2'!$A:$A,"<="&DATE(2026,11,14)) -> 0 | IF14: =COUNTIFS('DRAFT 2'!$D:$D,$B14,'DRAFT 2'!$A:$A,">="&DATE(2026,11,15),'DRAFT 2'!$A:$A,"<="&DATE(2026,11,21)) -> 0 | IG14: =COUNTIFS('DRAFT 2'!$D:$D,$B14,'DRAFT 2'!$A:$A,">="&DATE(2026,11,22),'DRAFT 2'!$A:$A,"<"&DATE(2026,IF(11=12,11+1,11+1),1)) -> 0 | IH14: =SUM(ID14:IG14) -> 0 | IR14: =IFERROR(LOOKUP(2,1/('DRAFT 2'!$D:$D=$B14)*('DRAFT 2'!$A:$A>=DATE(2026,12,1))*('DRAFT 2'!$A:$A<DATE(2026,IF(12=12,12+1,12+1),1)),'DRAFT 2'!$A:$A),"") -> 0 | IS14: =COUNTIFS('DRAFT 2'!$D:$D,$B14,'DRAFT 2'!$A:$A,">="&DATE(2026,12,1),'DRAFT 2'!$A:$A,"<="&DATE(2026,12,7)) -> 0 | IT14: =COUNTIFS('DRAFT 2'!$D:$D,$B14,'DRAFT 2'!$A:$A,">="&DATE(2026,12,8),'DRAFT 2'!$A:$A,"<="&DATE(2026,12,14)) -> 0 | IU14: =COUNTIFS('DRAFT 2'!$D:$D,$B14,'DRAFT 2'!$A:$A,">="&DATE(2026,12,15),'DRAFT 2'!$A:$A,"<="&DATE(2026,12,21)) -> 0 | IV14: =COUNTIFS('DRAFT 2'!$D:$D,$B14,'DRAFT 2'!$A:$A,">="&DATE(2026,12,22),'DRAFT 2'!$A:$A,"<"&DATE(2026,IF(12=12,12+1,12+1),1)) -> 0 | IW14: =SUM(IS14:IV14) -> 0
A15: =IFERROR(INDEX('DRAFT 1'!$A:$A,MATCH($B15,'DRAFT 1'!$B:$B,0)),"") | C15: =IFERROR(INDEX('DRAFT 1'!$C:$C,MATCH($B15,'DRAFT 1'!$B:$B,0)),"") | D15: =IFERROR(INDEX('DRAFT 1'!$D:$D,MATCH($B15,'DRAFT 1'!$B:$B,0)),"") | E15: =IFERROR(INDEX('DRAFT 1'!$E:$E,MATCH($B15,'DRAFT 1'!$B:$B,0)),"") | F15: =IFERROR(INDEX('DRAFT 1'!$F:$F,MATCH($B15,'DRAFT 1'!$B:$B,0)),"") | G15: =IFERROR(INDEX('DRAFT 1'!$G:$G,MATCH($B15,'DRAFT 1'!$B:$B,0)),"") | H15: =IFERROR(INDEX('DRAFT 1'!$H:$H,MATCH($B15,'DRAFT 1'!$B:$B,0)),"") | I15: BIOMUNDO | K15: =IFERROR(INDEX('DRAFT 1'!$AL:$AL,MATCH($B15,'DRAFT 1'!$B:$B,0)),"") | L15: =IFERROR(INDEX('DRAFT 1'!$J:$J,MATCH($B15,'DRAFT 1'!$B:$B,0)),"") | M15: =IFERROR(INDEX('DRAFT 1'!$K:$K,MATCH($B15,'DRAFT 1'!$B:$B,0)),"") | N15: INAT.REC | P15: =IFERROR(INDEX('DRAFT 1'!$L:$L,MATCH($B15,'DRAFT 1'!$B:$B,0)),"") | Q15: =IFERROR(INDEX('DRAFT 1'!$M:$M,MATCH($B15,'DRAFT 1'!$B:$B,0)),"") | R15: =IFERROR(INDEX('DRAFT 1'!$N:$N,MATCH($B15,'DRAFT 1'!$B:$B,0)),"") | S15: =IFERROR(INDEX('DRAFT 1'!$O:$O,MATCH($B15,'DRAFT 1'!$B:$B,0)),"") | T15: =IFERROR(INDEX('DRAFT 1'!$P:$P,MATCH($B15,'DRAFT 1'!$B:$B,0)),"") | U15: =IFERROR(INDEX('DRAFT 1'!$Q:$Q,MATCH($B15,'DRAFT 1'!$B:$B,0)),"") | V15: =IFERROR(INDEX('DRAFT 1'!$R:$R,MATCH($B15,'DRAFT 1'!$B:$B,0)),"") | W15: =IFERROR(INDEX('DRAFT 1'!$S:$S,MATCH($B15,'DRAFT 1'!$B:$B,0)),"") | X15: =IFERROR(INDEX('DRAFT 1'!$T:$T,MATCH($B15,'DRAFT 1'!$B:$B,0)),"") | Z15: =IFERROR(INDEX('DRAFT 1'!$U:$U,MATCH($B15,'DRAFT 1'!$B:$B,0)),"") | AA15: =IFERROR(INDEX('DRAFT 1'!$V:$V,MATCH($B15,'DRAFT 1'!$B:$B,0)),"") | AB15: =IFERROR(INDEX('DRAFT 1'!$W:$W,MATCH($B15,'DRAFT 1'!$B:$B,0)),"") | AC15: =IFERROR(INDEX('DRAFT 1'!$X:$X,MATCH($B15,'DRAFT 1'!$B:$B,0)),"") | AD15: =IFERROR(INDEX('DRAFT 1'!$Y:$Y,MATCH($B15,'DRAFT 1'!$B:$B,0)),"") | AE15: =IFERROR(INDEX('DRAFT 1'!$Z:$Z,MATCH($B15,'DRAFT 1'!$B:$B,0)),"") | AF15: =IFERROR(INDEX('DRAFT 1'!$AA:$AA,MATCH($B15,'DRAFT 1'!$B:$B,0)),"") | AG15: =IFERROR(INDEX('DRAFT 1'!$AB:$AB,MATCH($B15,'DRAFT 1'!$B:$B,0)),"") | AH15: =IFERROR(INDEX('DRAFT 1'!$AC:$AC,MATCH($B15,'DRAFT 1'!$B:$B,0)),"") | AI15: =IFERROR(INDEX('DRAFT 1'!$AD:$AD,MATCH($B15,'DRAFT 1'!$B:$B,0)),"") | AJ15: =IFERROR(INDEX('DRAFT 1'!$AE:$AE,MATCH($B15,'DRAFT 1'!$B:$B,0)),"") | AK15: =IFERROR(INDEX('DRAFT 1'!$AG:$AG,MATCH($B15,'DRAFT 1'!$B:$B,0)),"") | AL15: =IFERROR(INDEX('DRAFT 1'!$AH:$AH,MATCH($B15,'DRAFT 1'!$B:$B,0)),"") | AM15: =IFERROR(INDEX('DRAFT 1'!$AI:$AI,MATCH($B15,'DRAFT 1'!$B:$B,0)),"") | AN15: =IFERROR(INDEX('DRAFT 1'!$AJ:$AJ,MATCH($B15,'DRAFT 1'!$B:$B,0)),"") | AO15: =IFERROR(Y15/AN15,0) -> 0 | AP15: =IFERROR(INDEX('DRAFT 1'!$AK:$AK,MATCH($B15,'DRAFT 1'!$B:$B,0)),"") | AR15: CS | AS15: =IFERROR(LOOKUP(2,1/('DRAFT 2'!$D:$D=$B15),'DRAFT 2'!$T:$T),"") -> 0 | AT15: =IFERROR(LOOKUP(2,1/('DRAFT 2'!$D:$D=$B15),'DRAFT 2'!$A:$A),"") -> 0 | AU15: =IFERROR(LOOKUP(2,1/('DRAFT 2'!$D:$D=$B15),'DRAFT 2'!$R:$R),"") -> 0 | AV15: =IFERROR(LOOKUP(2,1/('DRAFT 2'!$D:$D=$B15),'DRAFT 2'!$S:$S),"") -> 0 | AW15: RECORRENTE | AX15: =IFERROR(LOOKUP(2,1/('DRAFT 2'!$D:$D=$B15),'DRAFT 2'!$M:$M),"") -> 0 | AY15: =IFERROR(LOOKUP(2,1/('DRAFT 2'!$D:$D=$B15),'DRAFT 2'!$K:$K),"") -> 0 | BG15: =IFERROR(LOOKUP(2,1/('DRAFT 2'!$D:$D=$B15),'DRAFT 2'!$U:$U),"") -> 0 | BH15: =IFERROR(LOOKUP(2,1/('DRAFT 2'!$D:$D=$B15),'DRAFT 2'!$V:$V),"") -> 0 | CE15: =IFERROR(AJ15,0) | CF15: =IFERROR(LOOKUP(2,1/('DRAFT 2'!$D:$D=$B15)*('DRAFT 2'!$A:$A>=DATE(2026,1,1))*('DRAFT 2'!$A:$A<DATE(2026,IF(1=12,1+1,1+1),1)),'DRAFT 2'!$A:$A),"") -> 0 | CG15: =COUNTIFS('DRAFT 2'!$D:$D,$B15,'DRAFT 2'!$A:$A,">="&DATE(2026,1,1),'DRAFT 2'!$A:$A,"<="&DATE(2026,1,7)) -> 0 | CH15: =COUNTIFS('DRAFT 2'!$D:$D,$B15,'DRAFT 2'!$A:$A,">="&DATE(2026,1,8),'DRAFT 2'!$A:$A,"<="&DATE(2026,1,14)) -> 0 | CI15: =COUNTIFS('DRAFT 2'!$D:$D,$B15,'DRAFT 2'!$A:$A,">="&DATE(2026,1,15),'DRAFT 2'!$A:$A,"<="&DATE(2026,1,21)) -> 0 | CJ15: =COUNTIFS('DRAFT 2'!$D:$D,$B15,'DRAFT 2'!$A:$A,">="&DATE(2026,1,22),'DRAFT 2'!$A:$A,"<"&DATE(2026,IF(1=12,1+1,1+1),1)) -> 0 | CK15: =SUM(CG15:CJ15) -> 0 | CT15: 0 | CU15: =IFERROR(LOOKUP(2,1/('DRAFT 2'!$D:$D=$B15)*('DRAFT 2'!$A:$A>=DATE(2026,2,1))*('DRAFT 2'!$A:$A<DATE(2026,IF(2=12,2+1,2+1),1)),'DRAFT 2'!$A:$A),"") -> 0 | CV15: =COUNTIFS('DRAFT 2'!$D:$D,$B15,'DRAFT 2'!$A:$A,">="&DATE(2026,2,1),'DRAFT 2'!$A:$A,"<="&DATE(2026,2,7)) -> 0 | CW15: =COUNTIFS('DRAFT 2'!$D:$D,$B15,'DRAFT 2'!$A:$A,">="&DATE(2026,2,8),'DRAFT 2'!$A:$A,"<="&DATE(2026,2,14)) -> 0 | CX15: =COUNTIFS('DRAFT 2'!$D:$D,$B15,'DRAFT 2'!$A:$A,">="&DATE(2026,2,15),'DRAFT 2'!$A:$A,"<="&DATE(2026,2,21)) -> 0 | CY15: =COUNTIFS('DRAFT 2'!$D:$D,$B15,'DRAFT 2'!$A:$A,">="&DATE(2026,2,22),'DRAFT 2'!$A:$A,"<"&DATE(2026,IF(2=12,2+1,2+1),1)) -> 0 | CZ15: =SUM(CV15:CY15) -> 0 | DJ15: =IFERROR(LOOKUP(2,1/('DRAFT 2'!$D:$D=$B15)*('DRAFT 2'!$A:$A>=DATE(2026,3,1))*('DRAFT 2'!$A:$A<DATE(2026,IF(3=12,3+1,3+1),1)),'DRAFT 2'!$A:$A),"") -> 0 | DK15: =COUNTIFS('DRAFT 2'!$D:$D,$B15,'DRAFT 2'!$A:$A,">="&DATE(2026,3,1),'DRAFT 2'!$A:$A,"<="&DATE(2026,3,7)) -> 0 | DL15: =COUNTIFS('DRAFT 2'!$D:$D,$B15,'DRAFT 2'!$A:$A,">="&DATE(2026,3,8),'DRAFT 2'!$A:$A,"<="&DATE(2026,3,14)) -> 0 | DM15: =COUNTIFS('DRAFT 2'!$D:$D,$B15,'DRAFT 2'!$A:$A,">="&DATE(2026,3,15),'DRAFT 2'!$A:$A,"<="&DATE(2026,3,21)) -> 0 | DN15: =COUNTIFS('DRAFT 2'!$D:$D,$B15,'DRAFT 2'!$A:$A,">="&DATE(2026,3,22),'DRAFT 2'!$A:$A,"<"&DATE(2026,IF(3=12,3+1,3+1),1)) -> 0 | DO15: =SUM(DK15:DN15) -> 0 | DZ15: =IFERROR(LOOKUP(2,1/('DRAFT 2'!$D:$D=$B15)*('DRAFT 2'!$A:$A>=DATE(2026,4,1))*('DRAFT 2'!$A:$A<DATE(2026,IF(4=12,4+1,4+1),1)),'DRAFT 2'!$A:$A),"") -> 0 | EA15: =COUNTIFS('DRAFT 2'!$D:$D,$B15,'DRAFT 2'!$A:$A,">="&DATE(2026,4,1),'DRAFT 2'!$A:$A,"<="&DATE(2026,4,7)) -> 0 | EB15: =COUNTIFS('DRAFT 2'!$D:$D,$B15,'DRAFT 2'!$A:$A,">="&DATE(2026,4,8),'DRAFT 2'!$A:$A,"<="&DATE(2026,4,14)) -> 0 | EC15: =COUNTIFS('DRAFT 2'!$D:$D,$B15,'DRAFT 2'!$A:$A,">="&DATE(2026,4,15),'DRAFT 2'!$A:$A,"<="&DATE(2026,4,21)) -> 0 | ED15: =COUNTIFS('DRAFT 2'!$D:$D,$B15,'DRAFT 2'!$A:$A,">="&DATE(2026,4,22),'DRAFT 2'!$A:$A,"<"&DATE(2026,IF(4=12,4+1,4+1),1)) -> 0 | EE15: =SUM(EA15:ED15) -> 0 | EO15: =IFERROR(LOOKUP(2,1/('DRAFT 2'!$D:$D=$B15)*('DRAFT 2'!$A:$A>=DATE(2026,5,1))*('DRAFT 2'!$A:$A<DATE(2026,IF(5=12,5+1,5+1),1)),'DRAFT 2'!$A:$A),"") -> 0 | EP15: =COUNTIFS('DRAFT 2'!$D:$D,$B15,'DRAFT 2'!$A:$A,">="&DATE(2026,5,1),'DRAFT 2'!$A:$A,"<="&DATE(2026,5,7)) -> 0 | EQ15: =COUNTIFS('DRAFT 2'!$D:$D,$B15,'DRAFT 2'!$A:$A,">="&DATE(2026,5,8),'DRAFT 2'!$A:$A,"<="&DATE(2026,5,14)) -> 0 | ER15: =COUNTIFS('DRAFT 2'!$D:$D,$B15,'DRAFT 2'!$A:$A,">="&DATE(2026,5,15),'DRAFT 2'!$A:$A,"<="&DATE(2026,5,21)) -> 0 | ES15: =COUNTIFS('DRAFT 2'!$D:$D,$B15,'DRAFT 2'!$A:$A,">="&DATE(2026,5,22),'DRAFT 2'!$A:$A,"<"&DATE(2026,IF(5=12,5+1,5+1),1)) -> 0 | ET15: =SUM(EP15:ES15) -> 0 | FD15: =IFERROR(LOOKUP(2,1/('DRAFT 2'!$D:$D=$B15)*('DRAFT 2'!$A:$A>=DATE(2026,6,1))*('DRAFT 2'!$A:$A<DATE(2026,IF(6=12,6+1,6+1),1)),'DRAFT 2'!$A:$A),"") -> 0 | FE15: =COUNTIFS('DRAFT 2'!$D:$D,$B15,'DRAFT 2'!$A:$A,">="&DATE(2026,6,1),'DRAFT 2'!$A:$A,"<="&DATE(2026,6,7)) -> 0 | FF15: =COUNTIFS('DRAFT 2'!$D:$D,$B15,'DRAFT 2'!$A:$A,">="&DATE(2026,6,8),'DRAFT 2'!$A:$A,"<="&DATE(2026,6,14)) -> 0 | FG15: =COUNTIFS('DRAFT 2'!$D:$D,$B15,'DRAFT 2'!$A:$A,">="&DATE(2026,6,15),'DRAFT 2'!$A:$A,"<="&DATE(2026,6,21)) -> 0 | FH15: =COUNTIFS('DRAFT 2'!$D:$D,$B15,'DRAFT 2'!$A:$A,">="&DATE(2026,6,22),'DRAFT 2'!$A:$A,"<"&DATE(2026,IF(6=12,6+1,6+1),1)) -> 0 | FI15: =SUM(FE15:FH15) -> 0 | FT15: =IFERROR(LOOKUP(2,1/('DRAFT 2'!$D:$D=$B15)*('DRAFT 2'!$A:$A>=DATE(2026,7,1))*('DRAFT 2'!$A:$A<DATE(2026,IF(7=12,7+1,7+1),1)),'DRAFT 2'!$A:$A),"") -> 0 | FU15: =COUNTIFS('DRAFT 2'!$D:$D,$B15,'DRAFT 2'!$A:$A,">="&DATE(2026,7,1),'DRAFT 2'!$A:$A,"<="&DATE(2026,7,7)) -> 0 | FV15: =COUNTIFS('DRAFT 2'!$D:$D,$B15,'DRAFT 2'!$A:$A,">="&DATE(2026,7,8),'DRAFT 2'!$A:$A,"<="&DATE(2026,7,14)) -> 0 | FW15: =COUNTIFS('DRAFT 2'!$D:$D,$B15,'DRAFT 2'!$A:$A,">="&DATE(2026,7,15),'DRAFT 2'!$A:$A,"<="&DATE(2026,7,21)) -> 0 | FX15: =COUNTIFS('DRAFT 2'!$D:$D,$B15,'DRAFT 2'!$A:$A,">="&DATE(2026,7,22),'DRAFT 2'!$A:$A,"<"&DATE(2026,IF(7=12,7+1,7+1),1)) -> 0 | FY15: =SUM(FU15:FX15) -> 0 | GI15: =IFERROR(LOOKUP(2,1/('DRAFT 2'!$D:$D=$B15)*('DRAFT 2'!$A:$A>=DATE(2026,8,1))*('DRAFT 2'!$A:$A<DATE(2026,IF(8=12,8+1,8+1),1)),'DRAFT 2'!$A:$A),"") -> 0 | GJ15: =COUNTIFS('DRAFT 2'!$D:$D,$B15,'DRAFT 2'!$A:$A,">="&DATE(2026,8,1),'DRAFT 2'!$A:$A,"<="&DATE(2026,8,7)) -> 0 | GK15: =COUNTIFS('DRAFT 2'!$D:$D,$B15,'DRAFT 2'!$A:$A,">="&DATE(2026,8,8),'DRAFT 2'!$A:$A,"<="&DATE(2026,8,14)) -> 0 | GL15: =COUNTIFS('DRAFT 2'!$D:$D,$B15,'DRAFT 2'!$A:$A,">="&DATE(2026,8,15),'DRAFT 2'!$A:$A,"<="&DATE(2026,8,21)) -> 0 | GM15: =COUNTIFS('DRAFT 2'!$D:$D,$B15,'DRAFT 2'!$A:$A,">="&DATE(2026,8,22),'DRAFT 2'!$A:$A,"<"&DATE(2026,IF(8=12,8+1,8+1),1)) -> 0 | GN15: =SUM(GJ15:GM15) -> 0 | GX15: =IFERROR(LOOKUP(2,1/('DRAFT 2'!$D:$D=$B15)*('DRAFT 2'!$A:$A>=DATE(2026,9,1))*('DRAFT 2'!$A:$A<DATE(2026,IF(9=12,9+1,9+1),1)),'DRAFT 2'!$A:$A),"") -> 0 | GY15: =COUNTIFS('DRAFT 2'!$D:$D,$B15,'DRAFT 2'!$A:$A,">="&DATE(2026,9,1),'DRAFT 2'!$A:$A,"<="&DATE(2026,9,7)) -> 0 | GZ15: =COUNTIFS('DRAFT 2'!$D:$D,$B15,'DRAFT 2'!$A:$A,">="&DATE(2026,9,8),'DRAFT 2'!$A:$A,"<="&DATE(2026,9,14)) -> 0 | HA15: =COUNTIFS('DRAFT 2'!$D:$D,$B15,'DRAFT 2'!$A:$A,">="&DATE(2026,9,15),'DRAFT 2'!$A:$A,"<="&DATE(2026,9,21)) -> 0 | HB15: =COUNTIFS('DRAFT 2'!$D:$D,$B15,'DRAFT 2'!$A:$A,">="&DATE(2026,9,22),'DRAFT 2'!$A:$A,"<"&DATE(2026,IF(9=12,9+1,9+1),1)) -> 0 | HC15: =SUM(GY15:HB15) -> 0 | HN15: =IFERROR(LOOKUP(2,1/('DRAFT 2'!$D:$D=$B15)*('DRAFT 2'!$A:$A>=DATE(2026,10,1))*('DRAFT 2'!$A:$A<DATE(2026,IF(10=12,10+1,10+1),1)),'DRAFT 2'!$A:$A),"") -> 0 | HO15: =COUNTIFS('DRAFT 2'!$D:$D,$B15,'DRAFT 2'!$A:$A,">="&DATE(2026,10,1),'DRAFT 2'!$A:$A,"<="&DATE(2026,10,7)) -> 0 | HP15: =COUNTIFS('DRAFT 2'!$D:$D,$B15,'DRAFT 2'!$A:$A,">="&DATE(2026,10,8),'DRAFT 2'!$A:$A,"<="&DATE(2026,10,14)) -> 0 | HQ15: =COUNTIFS('DRAFT 2'!$D:$D,$B15,'DRAFT 2'!$A:$A,">="&DATE(2026,10,15),'DRAFT 2'!$A:$A,"<="&DATE(2026,10,21)) -> 0 | HR15: =COUNTIFS('DRAFT 2'!$D:$D,$B15,'DRAFT 2'!$A:$A,">="&DATE(2026,10,22),'DRAFT 2'!$A:$A,"<"&DATE(2026,IF(10=12,10+1,10+1),1)) -> 0 | HS15: =SUM(HO15:HR15) -> 0 | IC15: =IFERROR(LOOKUP(2,1/('DRAFT 2'!$D:$D=$B15)*('DRAFT 2'!$A:$A>=DATE(2026,11,1))*('DRAFT 2'!$A:$A<DATE(2026,IF(11=12,11+1,11+1),1)),'DRAFT 2'!$A:$A),"") -> 0 | ID15: =COUNTIFS('DRAFT 2'!$D:$D,$B15,'DRAFT 2'!$A:$A,">="&DATE(2026,11,1),'DRAFT 2'!$A:$A,"<="&DATE(2026,11,7)) -> 0 | IE15: =COUNTIFS('DRAFT 2'!$D:$D,$B15,'DRAFT 2'!$A:$A,">="&DATE(2026,11,8),'DRAFT 2'!$A:$A,"<="&DATE(2026,11,14)) -> 0 | IF15: =COUNTIFS('DRAFT 2'!$D:$D,$B15,'DRAFT 2'!$A:$A,">="&DATE(2026,11,15),'DRAFT 2'!$A:$A,"<="&DATE(2026,11,21)) -> 0 | IG15: =COUNTIFS('DRAFT 2'!$D:$D,$B15,'DRAFT 2'!$A:$A,">="&DATE(2026,11,22),'DRAFT 2'!$A:$A,"<"&DATE(2026,IF(11=12,11+1,11+1),1)) -> 0 | IH15: =SUM(ID15:IG15) -> 0 | IR15: =IFERROR(LOOKUP(2,1/('DRAFT 2'!$D:$D=$B15)*('DRAFT 2'!$A:$A>=DATE(2026,12,1))*('DRAFT 2'!$A:$A<DATE(2026,IF(12=12,12+1,12+1),1)),'DRAFT 2'!$A:$A),"") -> 0 | IS15: =COUNTIFS('DRAFT 2'!$D:$D,$B15,'DRAFT 2'!$A:$A,">="&DATE(2026,12,1),'DRAFT 2'!$A:$A,"<="&DATE(2026,12,7)) -> 0 | IT15: =COUNTIFS('DRAFT 2'!$D:$D,$B15,'DRAFT 2'!$A:$A,">="&DATE(2026,12,8),'DRAFT 2'!$A:$A,"<="&DATE(2026,12,14)) -> 0 | IU15: =COUNTIFS('DRAFT 2'!$D:$D,$B15,'DRAFT 2'!$A:$A,">="&DATE(2026,12,15),'DRAFT 2'!$A:$A,"<="&DATE(2026,12,21)) -> 0 | IV15: =COUNTIFS('DRAFT 2'!$D:$D,$B15,'DRAFT 2'!$A:$A,">="&DATE(2026,12,22),'DRAFT 2'!$A:$A,"<"&DATE(2026,IF(12=12,12+1,12+1),1)) -> 0 | IW15: =SUM(IS15:IV15) -> 0
A16: =IFERROR(INDEX('DRAFT 1'!$A:$A,MATCH($B16,'DRAFT 1'!$B:$B,0)),"") | C16: =IFERROR(INDEX('DRAFT 1'!$C:$C,MATCH($B16,'DRAFT 1'!$B:$B,0)),"") | D16: =IFERROR(INDEX('DRAFT 1'!$D:$D,MATCH($B16,'DRAFT 1'!$B:$B,0)),"") | E16: =IFERROR(INDEX('DRAFT 1'!$E:$E,MATCH($B16,'DRAFT 1'!$B:$B,0)),"") | F16: =IFERROR(INDEX('DRAFT 1'!$F:$F,MATCH($B16,'DRAFT 1'!$B:$B,0)),"") | G16: =IFERROR(INDEX('DRAFT 1'!$G:$G,MATCH($B16,'DRAFT 1'!$B:$B,0)),"") | H16: =IFERROR(INDEX('DRAFT 1'!$H:$H,MATCH($B16,'DRAFT 1'!$B:$B,0)),"") | I16: TUDO EM GRAOS | K16: =IFERROR(INDEX('DRAFT 1'!$AL:$AL,MATCH($B16,'DRAFT 1'!$B:$B,0)),"") | L16: =IFERROR(INDEX('DRAFT 1'!$J:$J,MATCH($B16,'DRAFT 1'!$B:$B,0)),"") | M16: =IFERROR(INDEX('DRAFT 1'!$K:$K,MATCH($B16,'DRAFT 1'!$B:$B,0)),"") | N16: ATIVO | P16: =IFERROR(INDEX('DRAFT 1'!$L:$L,MATCH($B16,'DRAFT 1'!$B:$B,0)),"") | Q16: =IFERROR(INDEX('DRAFT 1'!$M:$M,MATCH($B16,'DRAFT 1'!$B:$B,0)),"") | R16: =IFERROR(INDEX('DRAFT 1'!$N:$N,MATCH($B16,'DRAFT 1'!$B:$B,0)),"") | S16: =IFERROR(INDEX('DRAFT 1'!$O:$O,MATCH($B16,'DRAFT 1'!$B:$B,0)),"") | T16: =IFERROR(INDEX('DRAFT 1'!$P:$P,MATCH($B16,'DRAFT 1'!$B:$B,0)),"") | U16: =IFERROR(INDEX('DRAFT 1'!$Q:$Q,MATCH($B16,'DRAFT 1'!$B:$B,0)),"") | V16: =IFERROR(INDEX('DRAFT 1'!$R:$R,MATCH($B16,'DRAFT 1'!$B:$B,0)),"") | W16: =IFERROR(INDEX('DRAFT 1'!$S:$S,MATCH($B16,'DRAFT 1'!$B:$B,0)),"") | X16: =IFERROR(INDEX('DRAFT 1'!$T:$T,MATCH($B16,'DRAFT 1'!$B:$B,0)),"") | Z16: =IFERROR(INDEX('DRAFT 1'!$U:$U,MATCH($B16,'DRAFT 1'!$B:$B,0)),"") | AA16: =IFERROR(INDEX('DRAFT 1'!$V:$V,MATCH($B16,'DRAFT 1'!$B:$B,0)),"") | AB16: =IFERROR(INDEX('DRAFT 1'!$W:$W,MATCH($B16,'DRAFT 1'!$B:$B,0)),"") | AC16: =IFERROR(INDEX('DRAFT 1'!$X:$X,MATCH($B16,'DRAFT 1'!$B:$B,0)),"") | AD16: =IFERROR(INDEX('DRAFT 1'!$Y:$Y,MATCH($B16,'DRAFT 1'!$B:$B,0)),"") | AE16: =IFERROR(INDEX('DRAFT 1'!$Z:$Z,MATCH($B16,'DRAFT 1'!$B:$B,0)),"") | AF16: =IFERROR(INDEX('DRAFT 1'!$AA:$AA,MATCH($B16,'DRAFT 1'!$B:$B,0)),"") | AG16: =IFERROR(INDEX('DRAFT 1'!$AB:$AB,MATCH($B16,'DRAFT 1'!$B:$B,0)),"") | AH16: =IFERROR(INDEX('DRAFT 1'!$AC:$AC,MATCH($B16,'DRAFT 1'!$B:$B,0)),"") | AI16: =IFERROR(INDEX('DRAFT 1'!$AD:$AD,MATCH($B16,'DRAFT 1'!$B:$B,0)),"") | AJ16: =IFERROR(INDEX('DRAFT 1'!$AE:$AE,MATCH($B16,'DRAFT 1'!$B:$B,0)),"") | AK16: =IFERROR(INDEX('DRAFT 1'!$AG:$AG,MATCH($B16,'DRAFT 1'!$B:$B,0)),"") | AL16: =IFERROR(INDEX('DRAFT 1'!$AH:$AH,MATCH($B16,'DRAFT 1'!$B:$B,0)),"") | AM16: =IFERROR(INDEX('DRAFT 1'!$AI:$AI,MATCH($B16,'DRAFT 1'!$B:$B,0)),"") | AN16: =IFERROR(INDEX('DRAFT 1'!$AJ:$AJ,MATCH($B16,'DRAFT 1'!$B:$B,0)),"") | AO16: =IFERROR(Y16/AN16,0) -> 0 | AP16: =IFERROR(INDEX('DRAFT 1'!$AK:$AK,MATCH($B16,'DRAFT 1'!$B:$B,0)),"") | AR16: PROSPECÇÃO | AS16: =IFERROR(LOOKUP(2,1/('DRAFT 2'!$D:$D=$B16),'DRAFT 2'!$T:$T),"") -> 0 | AT16: =IFERROR(LOOKUP(2,1/('DRAFT 2'!$D:$D=$B16),'DRAFT 2'!$A:$A),"") -> 0 | AU16: =IFERROR(LOOKUP(2,1/('DRAFT 2'!$D:$D=$B16),'DRAFT 2'!$R:$R),"") -> 0 | AV16: =IFERROR(LOOKUP(2,1/('DRAFT 2'!$D:$D=$B16),'DRAFT 2'!$S:$S),"") -> 0 | AW16: NOVO | AX16: =IFERROR(LOOKUP(2,1/('DRAFT 2'!$D:$D=$B16),'DRAFT 2'!$M:$M),"") -> 0 | AY16: =IFERROR(LOOKUP(2,1/('DRAFT 2'!$D:$D=$B16),'DRAFT 2'!$K:$K),"") -> 0 | BG16: =IFERROR(LOOKUP(2,1/('DRAFT 2'!$D:$D=$B16),'DRAFT 2'!$U:$U),"") -> 0 | BH16: =IFERROR(LOOKUP(2,1/('DRAFT 2'!$D:$D=$B16),'DRAFT 2'!$V:$V),"") -> 0 | CE16: =IFERROR(AJ16,0) | CF16: =IFERROR(LOOKUP(2,1/('DRAFT 2'!$D:$D=$B16)*('DRAFT 2'!$A:$A>=DATE(2026,1,1))*('DRAFT 2'!$A:$A<DATE(2026,IF(1=12,1+1,1+1),1)),'DRAFT 2'!$A:$A),"") -> 0 | CG16: =COUNTIFS('DRAFT 2'!$D:$D,$B16,'DRAFT 2'!$A:$A,">="&DATE(2026,1,1),'DRAFT 2'!$A:$A,"<="&DATE(2026,1,7)) -> 0 | CH16: =COUNTIFS('DRAFT 2'!$D:$D,$B16,'DRAFT 2'!$A:$A,">="&DATE(2026,1,8),'DRAFT 2'!$A:$A,"<="&DATE(2026,1,14)) -> 0 | CI16: =COUNTIFS('DRAFT 2'!$D:$D,$B16,'DRAFT 2'!$A:$A,">="&DATE(2026,1,15),'DRAFT 2'!$A:$A,"<="&DATE(2026,1,21)) -> 0 | CJ16: =COUNTIFS('DRAFT 2'!$D:$D,$B16,'DRAFT 2'!$A:$A,">="&DATE(2026,1,22),'DRAFT 2'!$A:$A,"<"&DATE(2026,IF(1=12,1+1,1+1),1)) -> 0 | CK16: =SUM(CG16:CJ16) -> 0 | CT16: 0 | CU16: =IFERROR(LOOKUP(2,1/('DRAFT 2'!$D:$D=$B16)*('DRAFT 2'!$A:$A>=DATE(2026,2,1))*('DRAFT 2'!$A:$A<DATE(2026,IF(2=12,2+1,2+1),1)),'DRAFT 2'!$A:$A),"") -> 0 | CV16: =COUNTIFS('DRAFT 2'!$D:$D,$B16,'DRAFT 2'!$A:$A,">="&DATE(2026,2,1),'DRAFT 2'!$A:$A,"<="&DATE(2026,2,7)) -> 0 | CW16: =COUNTIFS('DRAFT 2'!$D:$D,$B16,'DRAFT 2'!$A:$A,">="&DATE(2026,2,8),'DRAFT 2'!$A:$A,"<="&DATE(2026,2,14)) -> 0 | CX16: =COUNTIFS('DRAFT 2'!$D:$D,$B16,'DRAFT 2'!$A:$A,">="&DATE(2026,2,15),'DRAFT 2'!$A:$A,"<="&DATE(2026,2,21)) -> 0 | CY16: =COUNTIFS('DRAFT 2'!$D:$D,$B16,'DRAFT 2'!$A:$A,">="&DATE(2026,2,22),'DRAFT 2'!$A:$A,"<"&DATE(2026,IF(2=12,2+1,2+1),1)) -> 0 | CZ16: =SUM(CV16:CY16) -> 0 | DJ16: =IFERROR(LOOKUP(2,1/('DRAFT 2'!$D:$D=$B16)*('DRAFT 2'!$A:$A>=DATE(2026,3,1))*('DRAFT 2'!$A:$A<DATE(2026,IF(3=12,3+1,3+1),1)),'DRAFT 2'!$A:$A),"") -> 0 | DK16: =COUNTIFS('DRAFT 2'!$D:$D,$B16,'DRAFT 2'!$A:$A,">="&DATE(2026,3,1),'DRAFT 2'!$A:$A,"<="&DATE(2026,3,7)) -> 0 | DL16: =COUNTIFS('DRAFT 2'!$D:$D,$B16,'DRAFT 2'!$A:$A,">="&DATE(2026,3,8),'DRAFT 2'!$A:$A,"<="&DATE(2026,3,14)) -> 0 | DM16: =COUNTIFS('DRAFT 2'!$D:$D,$B16,'DRAFT 2'!$A:$A,">="&DATE(2026,3,15),'DRAFT 2'!$A:$A,"<="&DATE(2026,3,21)) -> 0 | DN16: =COUNTIFS('DRAFT 2'!$D:$D,$B16,'DRAFT 2'!$A:$A,">="&DATE(2026,3,22),'DRAFT 2'!$A:$A,"<"&DATE(2026,IF(3=12,3+1,3+1),1)) -> 0 | DO16: =SUM(DK16:DN16) -> 0 | DZ16: =IFERROR(LOOKUP(2,1/('DRAFT 2'!$D:$D=$B16)*('DRAFT 2'!$A:$A>=DATE(2026,4,1))*('DRAFT 2'!$A:$A<DATE(2026,IF(4=12,4+1,4+1),1)),'DRAFT 2'!$A:$A),"") -> 0 | EA16: =COUNTIFS('DRAFT 2'!$D:$D,$B16,'DRAFT 2'!$A:$A,">="&DATE(2026,4,1),'DRAFT 2'!$A:$A,"<="&DATE(2026,4,7)) -> 0 | EB16: =COUNTIFS('DRAFT 2'!$D:$D,$B16,'DRAFT 2'!$A:$A,">="&DATE(2026,4,8),'DRAFT 2'!$A:$A,"<="&DATE(2026,4,14)) -> 0 | EC16: =COUNTIFS('DRAFT 2'!$D:$D,$B16,'DRAFT 2'!$A:$A,">="&DATE(2026,4,15),'DRAFT 2'!$A:$A,"<="&DATE(2026,4,21)) -> 0 | ED16: =COUNTIFS('DRAFT 2'!$D:$D,$B16,'DRAFT 2'!$A:$A,">="&DATE(2026,4,22),'DRAFT 2'!$A:$A,"<"&DATE(2026,IF(4=12,4+1,4+1),1)) -> 0 | EE16: =SUM(EA16:ED16) -> 0 | EO16: =IFERROR(LOOKUP(2,1/('DRAFT 2'!$D:$D=$B16)*('DRAFT 2'!$A:$A>=DATE(2026,5,1))*('DRAFT 2'!$A:$A<DATE(2026,IF(5=12,5+1,5+1),1)),'DRAFT 2'!$A:$A),"") -> 0 | EP16: =COUNTIFS('DRAFT 2'!$D:$D,$B16,'DRAFT 2'!$A:$A,">="&DATE(2026,5,1),'DRAFT 2'!$A:$A,"<="&DATE(2026,5,7)) -> 0 | EQ16: =COUNTIFS('DRAFT 2'!$D:$D,$B16,'DRAFT 2'!$A:$A,">="&DATE(2026,5,8),'DRAFT 2'!$A:$A,"<="&DATE(2026,5,14)) -> 0 | ER16: =COUNTIFS('DRAFT 2'!$D:$D,$B16,'DRAFT 2'!$A:$A,">="&DATE(2026,5,15),'DRAFT 2'!$A:$A,"<="&DATE(2026,5,21)) -> 0 | ES16: =COUNTIFS('DRAFT 2'!$D:$D,$B16,'DRAFT 2'!$A:$A,">="&DATE(2026,5,22),'DRAFT 2'!$A:$A,"<"&DATE(2026,IF(5=12,5+1,5+1),1)) -> 0 | ET16: =SUM(EP16:ES16) -> 0 | FD16: =IFERROR(LOOKUP(2,1/('DRAFT 2'!$D:$D=$B16)*('DRAFT 2'!$A:$A>=DATE(2026,6,1))*('DRAFT 2'!$A:$A<DATE(2026,IF(6=12,6+1,6+1),1)),'DRAFT 2'!$A:$A),"") -> 0 | FE16: =COUNTIFS('DRAFT 2'!$D:$D,$B16,'DRAFT 2'!$A:$A,">="&DATE(2026,6,1),'DRAFT 2'!$A:$A,"<="&DATE(2026,6,7)) -> 0 | FF16: =COUNTIFS('DRAFT 2'!$D:$D,$B16,'DRAFT 2'!$A:$A,">="&DATE(2026,6,8),'DRAFT 2'!$A:$A,"<="&DATE(2026,6,14)) -> 0 | FG16: =COUNTIFS('DRAFT 2'!$D:$D,$B16,'DRAFT 2'!$A:$A,">="&DATE(2026,6,15),'DRAFT 2'!$A:$A,"<="&DATE(2026,6,21)) -> 0 | FH16: =COUNTIFS('DRAFT 2'!$D:$D,$B16,'DRAFT 2'!$A:$A,">="&DATE(2026,6,22),'DRAFT 2'!$A:$A,"<"&DATE(2026,IF(6=12,6+1,6+1),1)) -> 0 | FI16: =SUM(FE16:FH16) -> 0 | FT16: =IFERROR(LOOKUP(2,1/('DRAFT 2'!$D:$D=$B16)*('DRAFT 2'!$A:$A>=DATE(2026,7,1))*('DRAFT 2'!$A:$A<DATE(2026,IF(7=12,7+1,7+1),1)),'DRAFT 2'!$A:$A),"") -> 0 | FU16: =COUNTIFS('DRAFT 2'!$D:$D,$B16,'DRAFT 2'!$A:$A,">="&DATE(2026,7,1),'DRAFT 2'!$A:$A,"<="&DATE(2026,7,7)) -> 0 | FV16: =COUNTIFS('DRAFT 2'!$D:$D,$B16,'DRAFT 2'!$A:$A,">="&DATE(2026,7,8),'DRAFT 2'!$A:$A,"<="&DATE(2026,7,14)) -> 0 | FW16: =COUNTIFS('DRAFT 2'!$D:$D,$B16,'DRAFT 2'!$A:$A,">="&DATE(2026,7,15),'DRAFT 2'!$A:$A,"<="&DATE(2026,7,21)) -> 0 | FX16: =COUNTIFS('DRAFT 2'!$D:$D,$B16,'DRAFT 2'!$A:$A,">="&DATE(2026,7,22),'DRAFT 2'!$A:$A,"<"&DATE(2026,IF(7=12,7+1,7+1),1)) -> 0 | FY16: =SUM(FU16:FX16) -> 0 | GI16: =IFERROR(LOOKUP(2,1/('DRAFT 2'!$D:$D=$B16)*('DRAFT 2'!$A:$A>=DATE(2026,8,1))*('DRAFT 2'!$A:$A<DATE(2026,IF(8=12,8+1,8+1),1)),'DRAFT 2'!$A:$A),"") -> 0 | GJ16: =COUNTIFS('DRAFT 2'!$D:$D,$B16,'DRAFT 2'!$A:$A,">="&DATE(2026,8,1),'DRAFT 2'!$A:$A,"<="&DATE(2026,8,7)) -> 0 | GK16: =COUNTIFS('DRAFT 2'!$D:$D,$B16,'DRAFT 2'!$A:$A,">="&DATE(2026,8,8),'DRAFT 2'!$A:$A,"<="&DATE(2026,8,14)) -> 0 | GL16: =COUNTIFS('DRAFT 2'!$D:$D,$B16,'DRAFT 2'!$A:$A,">="&DATE(2026,8,15),'DRAFT 2'!$A:$A,"<="&DATE(2026,8,21)) -> 0 | GM16: =COUNTIFS('DRAFT 2'!$D:$D,$B16,'DRAFT 2'!$A:$A,">="&DATE(2026,8,22),'DRAFT 2'!$A:$A,"<"&DATE(2026,IF(8=12,8+1,8+1),1)) -> 0 | GN16: =SUM(GJ16:GM16) -> 0 | GX16: =IFERROR(LOOKUP(2,1/('DRAFT 2'!$D:$D=$B16)*('DRAFT 2'!$A:$A>=DATE(2026,9,1))*('DRAFT 2'!$A:$A<DATE(2026,IF(9=12,9+1,9+1),1)),'DRAFT 2'!$A:$A),"") -> 0 | GY16: =COUNTIFS('DRAFT 2'!$D:$D,$B16,'DRAFT 2'!$A:$A,">="&DATE(2026,9,1),'DRAFT 2'!$A:$A,"<="&DATE(2026,9,7)) -> 0 | GZ16: =COUNTIFS('DRAFT 2'!$D:$D,$B16,'DRAFT 2'!$A:$A,">="&DATE(2026,9,8),'DRAFT 2'!$A:$A,"<="&DATE(2026,9,14)) -> 0 | HA16: =COUNTIFS('DRAFT 2'!$D:$D,$B16,'DRAFT 2'!$A:$A,">="&DATE(2026,9,15),'DRAFT 2'!$A:$A,"<="&DATE(2026,9,21)) -> 0 | HB16: =COUNTIFS('DRAFT 2'!$D:$D,$B16,'DRAFT 2'!$A:$A,">="&DATE(2026,9,22),'DRAFT 2'!$A:$A,"<"&DATE(2026,IF(9=12,9+1,9+1),1)) -> 0 | HC16: =SUM(GY16:HB16) -> 0 | HN16: =IFERROR(LOOKUP(2,1/('DRAFT 2'!$D:$D=$B16)*('DRAFT 2'!$A:$A>=DATE(2026,10,1))*('DRAFT 2'!$A:$A<DATE(2026,IF(10=12,10+1,10+1),1)),'DRAFT 2'!$A:$A),"") -> 0 | HO16: =COUNTIFS('DRAFT 2'!$D:$D,$B16,'DRAFT 2'!$A:$A,">="&DATE(2026,10,1),'DRAFT 2'!$A:$A,"<="&DATE(2026,10,7)) -> 0 | HP16: =COUNTIFS('DRAFT 2'!$D:$D,$B16,'DRAFT 2'!$A:$A,">="&DATE(2026,10,8),'DRAFT 2'!$A:$A,"<="&DATE(2026,10,14)) -> 0 | HQ16: =COUNTIFS('DRAFT 2'!$D:$D,$B16,'DRAFT 2'!$A:$A,">="&DATE(2026,10,15),'DRAFT 2'!$A:$A,"<="&DATE(2026,10,21)) -> 0 | HR16: =COUNTIFS('DRAFT 2'!$D:$D,$B16,'DRAFT 2'!$A:$A,">="&DATE(2026,10,22),'DRAFT 2'!$A:$A,"<"&DATE(2026,IF(10=12,10+1,10+1),1)) -> 0 | HS16: =SUM(HO16:HR16) -> 0 | IC16: =IFERROR(LOOKUP(2,1/('DRAFT 2'!$D:$D=$B16)*('DRAFT 2'!$A:$A>=DATE(2026,11,1))*('DRAFT 2'!$A:$A<DATE(2026,IF(11=12,11+1,11+1),1)),'DRAFT 2'!$A:$A),"") -> 0 | ID16: =COUNTIFS('DRAFT 2'!$D:$D,$B16,'DRAFT 2'!$A:$A,">="&DATE(2026,11,1),'DRAFT 2'!$A:$A,"<="&DATE(2026,11,7)) -> 0 | IE16: =COUNTIFS('DRAFT 2'!$D:$D,$B16,'DRAFT 2'!$A:$A,">="&DATE(2026,11,8),'DRAFT 2'!$A:$A,"<="&DATE(2026,11,14)) -> 0 | IF16: =COUNTIFS('DRAFT 2'!$D:$D,$B16,'DRAFT 2'!$A:$A,">="&DATE(2026,11,15),'DRAFT 2'!$A:$A,"<="&DATE(2026,11,21)) -> 0 | IG16: =COUNTIFS('DRAFT 2'!$D:$D,$B16,'DRAFT 2'!$A:$A,">="&DATE(2026,11,22),'DRAFT 2'!$A:$A,"<"&DATE(2026,IF(11=12,11+1,11+1),1)) -> 0 | IH16: =SUM(ID16:IG16) -> 0 | IR16: =IFERROR(LOOKUP(2,1/('DRAFT 2'!$D:$D=$B16)*('DRAFT 2'!$A:$A>=DATE(2026,12,1))*('DRAFT 2'!$A:$A<DATE(2026,IF(12=12,12+1,12+1),1)),'DRAFT 2'!$A:$A),"") -> 0 | IS16: =COUNTIFS('DRAFT 2'!$D:$D,$B16,'DRAFT 2'!$A:$A,">="&DATE(2026,12,1),'DRAFT 2'!$A:$A,"<="&DATE(2026,12,7)) -> 0 | IT16: =COUNTIFS('DRAFT 2'!$D:$D,$B16,'DRAFT 2'!$A:$A,">="&DATE(2026,12,8),'DRAFT 2'!$A:$A,"<="&DATE(2026,12,14)) -> 0 | IU16: =COUNTIFS('DRAFT 2'!$D:$D,$B16,'DRAFT 2'!$A:$A,">="&DATE(2026,12,15),'DRAFT 2'!$A:$A,"<="&DATE(2026,12,21)) -> 0 | IV16: =COUNTIFS('DRAFT 2'!$D:$D,$B16,'DRAFT 2'!$A:$A,">="&DATE(2026,12,22),'DRAFT 2'!$A:$A,"<"&DATE(2026,IF(12=12,12+1,12+1),1)) -> 0 | IW16: =SUM(IS16:IV16) -> 0
A17: =IFERROR(INDEX('DRAFT 1'!$A:$A,MATCH($B17,'DRAFT 1'!$B:$B,0)),"") | C17: =IFERROR(INDEX('DRAFT 1'!$C:$C,MATCH($B17,'DRAFT 1'!$B:$B,0)),"") | D17: =IFERROR(INDEX('DRAFT 1'!$D:$D,MATCH($B17,'DRAFT 1'!$B:$B,0)),"") | E17: =IFERROR(INDEX('DRAFT 1'!$E:$E,MATCH($B17,'DRAFT 1'!$B:$B,0)),"") | F17: =IFERROR(INDEX('DRAFT 1'!$F:$F,MATCH($B17,'DRAFT 1'!$B:$B,0)),"") | G17: =IFERROR(INDEX('DRAFT 1'!$G:$G,MATCH($B17,'DRAFT 1'!$B:$B,0)),"") | H17: =IFERROR(INDEX('DRAFT 1'!$H:$H,MATCH($B17,'DRAFT 1'!$B:$B,0)),"") | I17: CIA DA SAUDE | K17: =IFERROR(INDEX('DRAFT 1'!$AL:$AL,MATCH($B17,'DRAFT 1'!$B:$B,0)),"") | L17: =IFERROR(INDEX('DRAFT 1'!$J:$J,MATCH($B17,'DRAFT 1'!$B:$B,0)),"") | M17: =IFERROR(INDEX('DRAFT 1'!$K:$K,MATCH($B17,'DRAFT 1'!$B:$B,0)),"") | N17: NOVO | P17: =IFERROR(INDEX('DRAFT 1'!$L:$L,MATCH($B17,'DRAFT 1'!$B:$B,0)),"") | Q17: =IFERROR(INDEX('DRAFT 1'!$M:$M,MATCH($B17,'DRAFT 1'!$B:$B,0)),"") | R17: =IFERROR(INDEX('DRAFT 1'!$N:$N,MATCH($B17,'DRAFT 1'!$B:$B,0)),"") | S17: =IFERROR(INDEX('DRAFT 1'!$O:$O,MATCH($B17,'DRAFT 1'!$B:$B,0)),"") | T17: =IFERROR(INDEX('DRAFT 1'!$P:$P,MATCH($B17,'DRAFT 1'!$B:$B,0)),"") | U17: =IFERROR(INDEX('DRAFT 1'!$Q:$Q,MATCH($B17,'DRAFT 1'!$B:$B,0)),"") | V17: =IFERROR(INDEX('DRAFT 1'!$R:$R,MATCH($B17,'DRAFT 1'!$B:$B,0)),"") | W17: =IFERROR(INDEX('DRAFT 1'!$S:$S,MATCH($B17,'DRAFT 1'!$B:$B,0)),"") | X17: =IFERROR(INDEX('DRAFT 1'!$T:$T,MATCH($B17,'DRAFT 1'!$B:$B,0)),"") | Z17: =IFERROR(INDEX('DRAFT 1'!$U:$U,MATCH($B17,'DRAFT 1'!$B:$B,0)),"") | AA17: =IFERROR(INDEX('DRAFT 1'!$V:$V,MATCH($B17,'DRAFT 1'!$B:$B,0)),"") | AB17: =IFERROR(INDEX('DRAFT 1'!$W:$W,MATCH($B17,'DRAFT 1'!$B:$B,0)),"") | AC17: =IFERROR(INDEX('DRAFT 1'!$X:$X,MATCH($B17,'DRAFT 1'!$B:$B,0)),"") | AD17: =IFERROR(INDEX('DRAFT 1'!$Y:$Y,MATCH($B17,'DRAFT 1'!$B:$B,0)),"") | AE17: =IFERROR(INDEX('DRAFT 1'!$Z:$Z,MATCH($B17,'DRAFT 1'!$B:$B,0)),"") | AF17: =IFERROR(INDEX('DRAFT 1'!$AA:$AA,MATCH($B17,'DRAFT 1'!$B:$B,0)),"") | AG17: =IFERROR(INDEX('DRAFT 1'!$AB:$AB,MATCH($B17,'DRAFT 1'!$B:$B,0)),"") | AH17: =IFERROR(INDEX('DRAFT 1'!$AC:$AC,MATCH($B17,'DRAFT 1'!$B:$B,0)),"") | AI17: =IFERROR(INDEX('DRAFT 1'!$AD:$AD,MATCH($B17,'DRAFT 1'!$B:$B,0)),"") | AJ17: =IFERROR(INDEX('DRAFT 1'!$AE:$AE,MATCH($B17,'DRAFT 1'!$B:$B,0)),"") | AK17: =IFERROR(INDEX('DRAFT 1'!$AG:$AG,MATCH($B17,'DRAFT 1'!$B:$B,0)),"") | AL17: =IFERROR(INDEX('DRAFT 1'!$AH:$AH,MATCH($B17,'DRAFT 1'!$B:$B,0)),"") | AM17: =IFERROR(INDEX('DRAFT 1'!$AI:$AI,MATCH($B17,'DRAFT 1'!$B:$B,0)),"") | AN17: =IFERROR(INDEX('DRAFT 1'!$AJ:$AJ,MATCH($B17,'DRAFT 1'!$B:$B,0)),"") | AO17: =IFERROR(Y17/AN17,0) -> 0 | AP17: =IFERROR(INDEX('DRAFT 1'!$AK:$AK,MATCH($B17,'DRAFT 1'!$B:$B,0)),"") | AR17: CS | AS17: =IFERROR(LOOKUP(2,1/('DRAFT 2'!$D:$D=$B17),'DRAFT 2'!$T:$T),"") -> 0 | AT17: =IFERROR(LOOKUP(2,1/('DRAFT 2'!$D:$D=$B17),'DRAFT 2'!$A:$A),"") -> 0 | AU17: =IFERROR(LOOKUP(2,1/('DRAFT 2'!$D:$D=$B17),'DRAFT 2'!$R:$R),"") -> 0 | AV17: =IFERROR(LOOKUP(2,1/('DRAFT 2'!$D:$D=$B17),'DRAFT 2'!$S:$S),"") -> 0 | AW17: EM DESENVOLVIMENTO | AX17: =IFERROR(LOOKUP(2,1/('DRAFT 2'!$D:$D=$B17),'DRAFT 2'!$M:$M),"") -> 0 | AY17: =IFERROR(LOOKUP(2,1/('DRAFT 2'!$D:$D=$B17),'DRAFT 2'!$K:$K),"") -> 0 | BG17: =IFERROR(LOOKUP(2,1/('DRAFT 2'!$D:$D=$B17),'DRAFT 2'!$U:$U),"") -> 0 | BH17: =IFERROR(LOOKUP(2,1/('DRAFT 2'!$D:$D=$B17),'DRAFT 2'!$V:$V),"") -> 0 | CE17: =IFERROR(AJ17,0) | CF17: =IFERROR(LOOKUP(2,1/('DRAFT 2'!$D:$D=$B17)*('DRAFT 2'!$A:$A>=DATE(2026,1,1))*('DRAFT 2'!$A:$A<DATE(2026,IF(1=12,1+1,1+1),1)),'DRAFT 2'!$A:$A),"") -> 0 | CG17: =COUNTIFS('DRAFT 2'!$D:$D,$B17,'DRAFT 2'!$A:$A,">="&DATE(2026,1,1),'DRAFT 2'!$A:$A,"<="&DATE(2026,1,7)) -> 0 | CH17: =COUNTIFS('DRAFT 2'!$D:$D,$B17,'DRAFT 2'!$A:$A,">="&DATE(2026,1,8),'DRAFT 2'!$A:$A,"<="&DATE(2026,1,14)) -> 0 | CI17: =COUNTIFS('DRAFT 2'!$D:$D,$B17,'DRAFT 2'!$A:$A,">="&DATE(2026,1,15),'DRAFT 2'!$A:$A,"<="&DATE(2026,1,21)) -> 0 | CJ17: =COUNTIFS('DRAFT 2'!$D:$D,$B17,'DRAFT 2'!$A:$A,">="&DATE(2026,1,22),'DRAFT 2'!$A:$A,"<"&DATE(2026,IF(1=12,1+1,1+1),1)) -> 0 | CK17: =SUM(CG17:CJ17) -> 0 | CT17: 0 | CU17: =IFERROR(LOOKUP(2,1/('DRAFT 2'!$D:$D=$B17)*('DRAFT 2'!$A:$A>=DATE(2026,2,1))*('DRAFT 2'!$A:$A<DATE(2026,IF(2=12,2+1,2+1),1)),'DRAFT 2'!$A:$A),"") -> 0 | CV17: =COUNTIFS('DRAFT 2'!$D:$D,$B17,'DRAFT 2'!$A:$A,">="&DATE(2026,2,1),'DRAFT 2'!$A:$A,"<="&DATE(2026,2,7)) -> 0 | CW17: =COUNTIFS('DRAFT 2'!$D:$D,$B17,'DRAFT 2'!$A:$A,">="&DATE(2026,2,8),'DRAFT 2'!$A:$A,"<="&DATE(2026,2,14)) -> 0 | CX17: =COUNTIFS('DRAFT 2'!$D:$D,$B17,'DRAFT 2'!$A:$A,">="&DATE(2026,2,15),'DRAFT 2'!$A:$A,"<="&DATE(2026,2,21)) -> 0 | CY17: =COUNTIFS('DRAFT 2'!$D:$D,$B17,'DRAFT 2'!$A:$A,">="&DATE(2026,2,22),'DRAFT 2'!$A:$A,"<"&DATE(2026,IF(2=12,2+1,2+1),1)) -> 0 | CZ17: =SUM(CV17:CY17) -> 0 | DJ17: =IFERROR(LOOKUP(2,1/('DRAFT 2'!$D:$D=$B17)*('DRAFT 2'!$A:$A>=DATE(2026,3,1))*('DRAFT 2'!$A:$A<DATE(2026,IF(3=12,3+1,3+1),1)),'DRAFT 2'!$A:$A),"") -> 0 | DK17: =COUNTIFS('DRAFT 2'!$D:$D,$B17,'DRAFT 2'!$A:$A,">="&DATE(2026,3,1),'DRAFT 2'!$A:$A,"<="&DATE(2026,3,7)) -> 0 | DL17: =COUNTIFS('DRAFT 2'!$D:$D,$B17,'DRAFT 2'!$A:$A,">="&DATE(2026,3,8),'DRAFT 2'!$A:$A,"<="&DATE(2026,3,14)) -> 0 | DM17: =COUNTIFS('DRAFT 2'!$D:$D,$B17,'DRAFT 2'!$A:$A,">="&DATE(2026,3,15),'DRAFT 2'!$A:$A,"<="&DATE(2026,3,21)) -> 0 | DN17: =COUNTIFS('DRAFT 2'!$D:$D,$B17,'DRAFT 2'!$A:$A,">="&DATE(2026,3,22),'DRAFT 2'!$A:$A,"<"&DATE(2026,IF(3=12,3+1,3+1),1)) -> 0 | DO17: =SUM(DK17:DN17) -> 0 | DZ17: =IFERROR(LOOKUP(2,1/('DRAFT 2'!$D:$D=$B17)*('DRAFT 2'!$A:$A>=DATE(2026,4,1))*('DRAFT 2'!$A:$A<DATE(2026,IF(4=12,4+1,4+1),1)),'DRAFT 2'!$A:$A),"") -> 0 | EA17: =COUNTIFS('DRAFT 2'!$D:$D,$B17,'DRAFT 2'!$A:$A,">="&DATE(2026,4,1),'DRAFT 2'!$A:$A,"<="&DATE(2026,4,7)) -> 0 | EB17: =COUNTIFS('DRAFT 2'!$D:$D,$B17,'DRAFT 2'!$A:$A,">="&DATE(2026,4,8),'DRAFT 2'!$A:$A,"<="&DATE(2026,4,14)) -> 0 | EC17: =COUNTIFS('DRAFT 2'!$D:$D,$B17,'DRAFT 2'!$A:$A,">="&DATE(2026,4,15),'DRAFT 2'!$A:$A,"<="&DATE(2026,4,21)) -> 0 | ED17: =COUNTIFS('DRAFT 2'!$D:$D,$B17,'DRAFT 2'!$A:$A,">="&DATE(2026,4,22),'DRAFT 2'!$A:$A,"<"&DATE(2026,IF(4=12,4+1,4+1),1)) -> 0 | EE17: =SUM(EA17:ED17) -> 0 | EO17: =IFERROR(LOOKUP(2,1/('DRAFT 2'!$D:$D=$B17)*('DRAFT 2'!$A:$A>=DATE(2026,5,1))*('DRAFT 2'!$A:$A<DATE(2026,IF(5=12,5+1,5+1),1)),'DRAFT 2'!$A:$A),"") -> 0 | EP17: =COUNTIFS('DRAFT 2'!$D:$D,$B17,'DRAFT 2'!$A:$A,">="&DATE(2026,5,1),'DRAFT 2'!$A:$A,"<="&DATE(2026,5,7)) -> 0 | EQ17: =COUNTIFS('DRAFT 2'!$D:$D,$B17,'DRAFT 2'!$A:$A,">="&DATE(2026,5,8),'DRAFT 2'!$A:$A,"<="&DATE(2026,5,14)) -> 0 | ER17: =COUNTIFS('DRAFT 2'!$D:$D,$B17,'DRAFT 2'!$A:$A,">="&DATE(2026,5,15),'DRAFT 2'!$A:$A,"<="&DATE(2026,5,21)) -> 0 | ES17: =COUNTIFS('DRAFT 2'!$D:$D,$B17,'DRAFT 2'!$A:$A,">="&DATE(2026,5,22),'DRAFT 2'!$A:$A,"<"&DATE(2026,IF(5=12,5+1,5+1),1)) -> 0 | ET17: =SUM(EP17:ES17) -> 0 | FD17: =IFERROR(LOOKUP(2,1/('DRAFT 2'!$D:$D=$B17)*('DRAFT 2'!$A:$A>=DATE(2026,6,1))*('DRAFT 2'!$A:$A<DATE(2026,IF(6=12,6+1,6+1),1)),'DRAFT 2'!$A:$A),"") -> 0 | FE17: =COUNTIFS('DRAFT 2'!$D:$D,$B17,'DRAFT 2'!$A:$A,">="&DATE(2026,6,1),'DRAFT 2'!$A:$A,"<="&DATE(2026,6,7)) -> 0 | FF17: =COUNTIFS('DRAFT 2'!$D:$D,$B17,'DRAFT 2'!$A:$A,">="&DATE(2026,6,8),'DRAFT 2'!$A:$A,"<="&DATE(2026,6,14)) -> 0 | FG17: =COUNTIFS('DRAFT 2'!$D:$D,$B17,'DRAFT 2'!$A:$A,">="&DATE(2026,6,15),'DRAFT 2'!$A:$A,"<="&DATE(2026,6,21)) -> 0 | FH17: =COUNTIFS('DRAFT 2'!$D:$D,$B17,'DRAFT 2'!$A:$A,">="&DATE(2026,6,22),'DRAFT 2'!$A:$A,"<"&DATE(2026,IF(6=12,6+1,6+1),1)) -> 0 | FI17: =SUM(FE17:FH17) -> 0 | FT17: =IFERROR(LOOKUP(2,1/('DRAFT 2'!$D:$D=$B17)*('DRAFT 2'!$A:$A>=DATE(2026,7,1))*('DRAFT 2'!$A:$A<DATE(2026,IF(7=12,7+1,7+1),1)),'DRAFT 2'!$A:$A),"") -> 0 | FU17: =COUNTIFS('DRAFT 2'!$D:$D,$B17,'DRAFT 2'!$A:$A,">="&DATE(2026,7,1),'DRAFT 2'!$A:$A,"<="&DATE(2026,7,7)) -> 0 | FV17: =COUNTIFS('DRAFT 2'!$D:$D,$B17,'DRAFT 2'!$A:$A,">="&DATE(2026,7,8),'DRAFT 2'!$A:$A,"<="&DATE(2026,7,14)) -> 0 | FW17: =COUNTIFS('DRAFT 2'!$D:$D,$B17,'DRAFT 2'!$A:$A,">="&DATE(2026,7,15),'DRAFT 2'!$A:$A,"<="&DATE(2026,7,21)) -> 0 | FX17: =COUNTIFS('DRAFT 2'!$D:$D,$B17,'DRAFT 2'!$A:$A,">="&DATE(2026,7,22),'DRAFT 2'!$A:$A,"<"&DATE(2026,IF(7=12,7+1,7+1),1)) -> 0 | FY17: =SUM(FU17:FX17) -> 0 | GI17: =IFERROR(LOOKUP(2,1/('DRAFT 2'!$D:$D=$B17)*('DRAFT 2'!$A:$A>=DATE(2026,8,1))*('DRAFT 2'!$A:$A<DATE(2026,IF(8=12,8+1,8+1),1)),'DRAFT 2'!$A:$A),"") -> 0 | GJ17: =COUNTIFS('DRAFT 2'!$D:$D,$B17,'DRAFT 2'!$A:$A,">="&DATE(2026,8,1),'DRAFT 2'!$A:$A,"<="&DATE(2026,8,7)) -> 0 | GK17: =COUNTIFS('DRAFT 2'!$D:$D,$B17,'DRAFT 2'!$A:$A,">="&DATE(2026,8,8),'DRAFT 2'!$A:$A,"<="&DATE(2026,8,14)) -> 0 | GL17: =COUNTIFS('DRAFT 2'!$D:$D,$B17,'DRAFT 2'!$A:$A,">="&DATE(2026,8,15),'DRAFT 2'!$A:$A,"<="&DATE(2026,8,21)) -> 0 | GM17: =COUNTIFS('DRAFT 2'!$D:$D,$B17,'DRAFT 2'!$A:$A,">="&DATE(2026,8,22),'DRAFT 2'!$A:$A,"<"&DATE(2026,IF(8=12,8+1,8+1),1)) -> 0 | GN17: =SUM(GJ17:GM17) -> 0 | GX17: =IFERROR(LOOKUP(2,1/('DRAFT 2'!$D:$D=$B17)*('DRAFT 2'!$A:$A>=DATE(2026,9,1))*('DRAFT 2'!$A:$A<DATE(2026,IF(9=12,9+1,9+1),1)),'DRAFT 2'!$A:$A),"") -> 0 | GY17: =COUNTIFS('DRAFT 2'!$D:$D,$B17,'DRAFT 2'!$A:$A,">="&DATE(2026,9,1),'DRAFT 2'!$A:$A,"<="&DATE(2026,9,7)) -> 0 | GZ17: =COUNTIFS('DRAFT 2'!$D:$D,$B17,'DRAFT 2'!$A:$A,">="&DATE(2026,9,8),'DRAFT 2'!$A:$A,"<="&DATE(2026,9,14)) -> 0 | HA17: =COUNTIFS('DRAFT 2'!$D:$D,$B17,'DRAFT 2'!$A:$A,">="&DATE(2026,9,15),'DRAFT 2'!$A:$A,"<="&DATE(2026,9,21)) -> 0 | HB17: =COUNTIFS('DRAFT 2'!$D:$D,$B17,'DRAFT 2'!$A:$A,">="&DATE(2026,9,22),'DRAFT 2'!$A:$A,"<"&DATE(2026,IF(9=12,9+1,9+1),1)) -> 0 | HC17: =SUM(GY17:HB17) -> 0 | HN17: =IFERROR(LOOKUP(2,1/('DRAFT 2'!$D:$D=$B17)*('DRAFT 2'!$A:$A>=DATE(2026,10,1))*('DRAFT 2'!$A:$A<DATE(2026,IF(10=12,10+1,10+1),1)),'DRAFT 2'!$A:$A),"") -> 0 | HO17: =COUNTIFS('DRAFT 2'!$D:$D,$B17,'DRAFT 2'!$A:$A,">="&DATE(2026,10,1),'DRAFT 2'!$A:$A,"<="&DATE(2026,10,7)) -> 0 | HP17: =COUNTIFS('DRAFT 2'!$D:$D,$B17,'DRAFT 2'!$A:$A,">="&DATE(2026,10,8),'DRAFT 2'!$A:$A,"<="&DATE(2026,10,14)) -> 0 | HQ17: =COUNTIFS('DRAFT 2'!$D:$D,$B17,'DRAFT 2'!$A:$A,">="&DATE(2026,10,15),'DRAFT 2'!$A:$A,"<="&DATE(2026,10,21)) -> 0 | HR17: =COUNTIFS('DRAFT 2'!$D:$D,$B17,'DRAFT 2'!$A:$A,">="&DATE(2026,10,22),'DRAFT 2'!$A:$A,"<"&DATE(2026,IF(10=12,10+1,10+1),1)) -> 0 | HS17: =SUM(HO17:HR17) -> 0 | IC17: =IFERROR(LOOKUP(2,1/('DRAFT 2'!$D:$D=$B17)*('DRAFT 2'!$A:$A>=DATE(2026,11,1))*('DRAFT 2'!$A:$A<DATE(2026,IF(11=12,11+1,11+1),1)),'DRAFT 2'!$A:$A),"") -> 0 | ID17: =COUNTIFS('DRAFT 2'!$D:$D,$B17,'DRAFT 2'!$A:$A,">="&DATE(2026,11,1),'DRAFT 2'!$A:$A,"<="&DATE(2026,11,7)) -> 0 | IE17: =COUNTIFS('DRAFT 2'!$D:$D,$B17,'DRAFT 2'!$A:$A,">="&DATE(2026,11,8),'DRAFT 2'!$A:$A,"<="&DATE(2026,11,14)) -> 0 | IF17: =COUNTIFS('DRAFT 2'!$D:$D,$B17,'DRAFT 2'!$A:$A,">="&DATE(2026,11,15),'DRAFT 2'!$A:$A,"<="&DATE(2026,11,21)) -> 0 | IG17: =COUNTIFS('DRAFT 2'!$D:$D,$B17,'DRAFT 2'!$A:$A,">="&DATE(2026,11,22),'DRAFT 2'!$A:$A,"<"&DATE(2026,IF(11=12,11+1,11+1),1)) -> 0 | IH17: =SUM(ID17:IG17) -> 0 | IR17: =IFERROR(LOOKUP(2,1/('DRAFT 2'!$D:$D=$B17)*('DRAFT 2'!$A:$A>=DATE(2026,12,1))*('DRAFT 2'!$A:$A<DATE(2026,IF(12=12,12+1,12+1),1)),'DRAFT 2'!$A:$A),"") -> 0 | IS17: =COUNTIFS('DRAFT 2'!$D:$D,$B17,'DRAFT 2'!$A:$A,">="&DATE(2026,12,1),'DRAFT 2'!$A:$A,"<="&DATE(2026,12,7)) -> 0 | IT17: =COUNTIFS('DRAFT 2'!$D:$D,$B17,'DRAFT 2'!$A:$A,">="&DATE(2026,12,8),'DRAFT 2'!$A:$A,"<="&DATE(2026,12,14)) -> 0 | IU17: =COUNTIFS('DRAFT 2'!$D:$D,$B17,'DRAFT 2'!$A:$A,">="&DATE(2026,12,15),'DRAFT 2'!$A:$A,"<="&DATE(2026,12,21)) -> 0 | IV17: =COUNTIFS('DRAFT 2'!$D:$D,$B17,'DRAFT 2'!$A:$A,">="&DATE(2026,12,22),'DRAFT 2'!$A:$A,"<"&DATE(2026,IF(12=12,12+1,12+1),1)) -> 0 | IW17: =SUM(IS17:IV17) -> 0
A18: =IFERROR(INDEX('DRAFT 1'!$A:$A,MATCH($B18,'DRAFT 1'!$B:$B,0)),"") | C18: =IFERROR(INDEX('DRAFT 1'!$C:$C,MATCH($B18,'DRAFT 1'!$B:$B,0)),"") | D18: =IFERROR(INDEX('DRAFT 1'!$D:$D,MATCH($B18,'DRAFT 1'!$B:$B,0)),"") | E18: =IFERROR(INDEX('DRAFT 1'!$E:$E,MATCH($B18,'DRAFT 1'!$B:$B,0)),"") | F18: =IFERROR(INDEX('DRAFT 1'!$F:$F,MATCH($B18,'DRAFT 1'!$B:$B,0)),"") | G18: =IFERROR(INDEX('DRAFT 1'!$G:$G,MATCH($B18,'DRAFT 1'!$B:$B,0)),"") | H18: =IFERROR(INDEX('DRAFT 1'!$H:$H,MATCH($B18,'DRAFT 1'!$B:$B,0)),"") | I18: DIVINA TERRA | K18: =IFERROR(INDEX('DRAFT 1'!$AL:$AL,MATCH($B18,'DRAFT 1'!$B:$B,0)),"") | L18: =IFERROR(INDEX('DRAFT 1'!$J:$J,MATCH($B18,'DRAFT 1'!$B:$B,0)),"") | M18: =IFERROR(INDEX('DRAFT 1'!$K:$K,MATCH($B18,'DRAFT 1'!$B:$B,0)),"") | N18: INAT.ANT | P18: =IFERROR(INDEX('DRAFT 1'!$L:$L,MATCH($B18,'DRAFT 1'!$B:$B,0)),"") | Q18: =IFERROR(INDEX('DRAFT 1'!$M:$M,MATCH($B18,'DRAFT 1'!$B:$B,0)),"") | R18: =IFERROR(INDEX('DRAFT 1'!$N:$N,MATCH($B18,'DRAFT 1'!$B:$B,0)),"") | S18: =IFERROR(INDEX('DRAFT 1'!$O:$O,MATCH($B18,'DRAFT 1'!$B:$B,0)),"") | T18: =IFERROR(INDEX('DRAFT 1'!$P:$P,MATCH($B18,'DRAFT 1'!$B:$B,0)),"") | U18: =IFERROR(INDEX('DRAFT 1'!$Q:$Q,MATCH($B18,'DRAFT 1'!$B:$B,0)),"") | V18: =IFERROR(INDEX('DRAFT 1'!$R:$R,MATCH($B18,'DRAFT 1'!$B:$B,0)),"") | W18: =IFERROR(INDEX('DRAFT 1'!$S:$S,MATCH($B18,'DRAFT 1'!$B:$B,0)),"") | X18: =IFERROR(INDEX('DRAFT 1'!$T:$T,MATCH($B18,'DRAFT 1'!$B:$B,0)),"") | Z18: =IFERROR(INDEX('DRAFT 1'!$U:$U,MATCH($B18,'DRAFT 1'!$B:$B,0)),"") | AA18: =IFERROR(INDEX('DRAFT 1'!$V:$V,MATCH($B18,'DRAFT 1'!$B:$B,0)),"") | AB18: =IFERROR(INDEX('DRAFT 1'!$W:$W,MATCH($B18,'DRAFT 1'!$B:$B,0)),"") | AC18: =IFERROR(INDEX('DRAFT 1'!$X:$X,MATCH($B18,'DRAFT 1'!$B:$B,0)),"") | AD18: =IFERROR(INDEX('DRAFT 1'!$Y:$Y,MATCH($B18,'DRAFT 1'!$B:$B,0)),"") | AE18: =IFERROR(INDEX('DRAFT 1'!$Z:$Z,MATCH($B18,'DRAFT 1'!$B:$B,0)),"") | AF18: =IFERROR(INDEX('DRAFT 1'!$AA:$AA,MATCH($B18,'DRAFT 1'!$B:$B,0)),"") | AG18: =IFERROR(INDEX('DRAFT 1'!$AB:$AB,MATCH($B18,'DRAFT 1'!$B:$B,0)),"") | AH18: =IFERROR(INDEX('DRAFT 1'!$AC:$AC,MATCH($B18,'DRAFT 1'!$B:$B,0)),"") | AI18: =IFERROR(INDEX('DRAFT 1'!$AD:$AD,MATCH($B18,'DRAFT 1'!$B:$B,0)),"") | AJ18: =IFERROR(INDEX('DRAFT 1'!$AE:$AE,MATCH($B18,'DRAFT 1'!$B:$B,0)),"") | AK18: =IFERROR(INDEX('DRAFT 1'!$AG:$AG,MATCH($B18,'DRAFT 1'!$B:$B,0)),"") | AL18: =IFERROR(INDEX('DRAFT 1'!$AH:$AH,MATCH($B18,'DRAFT 1'!$B:$B,0)),"") | AM18: =IFERROR(INDEX('DRAFT 1'!$AI:$AI,MATCH($B18,'DRAFT 1'!$B:$B,0)),"") | AN18: =IFERROR(INDEX('DRAFT 1'!$AJ:$AJ,MATCH($B18,'DRAFT 1'!$B:$B,0)),"") | AO18: =IFERROR(Y18/AN18,0) -> 0 | AP18: =IFERROR(INDEX('DRAFT 1'!$AK:$AK,MATCH($B18,'DRAFT 1'!$B:$B,0)),"") | AR18: PROSPECÇÃO | AS18: =IFERROR(LOOKUP(2,1/('DRAFT 2'!$D:$D=$B18),'DRAFT 2'!$T:$T),"") -> 0 | AT18: =IFERROR(LOOKUP(2,1/('DRAFT 2'!$D:$D=$B18),'DRAFT 2'!$A:$A),"") -> 0 | AU18: =IFERROR(LOOKUP(2,1/('DRAFT 2'!$D:$D=$B18),'DRAFT 2'!$R:$R),"") -> 0 | AV18: =IFERROR(LOOKUP(2,1/('DRAFT 2'!$D:$D=$B18),'DRAFT 2'!$S:$S),"") -> 0 | AW18: RECORRENTE | AX18: =IFERROR(LOOKUP(2,1/('DRAFT 2'!$D:$D=$B18),'DRAFT 2'!$M:$M),"") -> 0 | AY18: =IFERROR(LOOKUP(2,1/('DRAFT 2'!$D:$D=$B18),'DRAFT 2'!$K:$K),"") -> 0 | BG18: =IFERROR(LOOKUP(2,1/('DRAFT 2'!$D:$D=$B18),'DRAFT 2'!$U:$U),"") -> 0 | BH18: =IFERROR(LOOKUP(2,1/('DRAFT 2'!$D:$D=$B18),'DRAFT 2'!$V:$V),"") -> 0 | CE18: =IFERROR(AJ18,0) | CF18: =IFERROR(LOOKUP(2,1/('DRAFT 2'!$D:$D=$B18)*('DRAFT 2'!$A:$A>=DATE(2026,1,1))*('DRAFT 2'!$A:$A<DATE(2026,IF(1=12,1+1,1+1),1)),'DRAFT 2'!$A:$A),"") -> 0 | CG18: =COUNTIFS('DRAFT 2'!$D:$D,$B18,'DRAFT 2'!$A:$A,">="&DATE(2026,1,1),'DRAFT 2'!$A:$A,"<="&DATE(2026,1,7)) -> 0 | CH18: =COUNTIFS('DRAFT 2'!$D:$D,$B18,'DRAFT 2'!$A:$A,">="&DATE(2026,1,8),'DRAFT 2'!$A:$A,"<="&DATE(2026,1,14)) -> 0 | CI18: =COUNTIFS('DRAFT 2'!$D:$D,$B18,'DRAFT 2'!$A:$A,">="&DATE(2026,1,15),'DRAFT 2'!$A:$A,"<="&DATE(2026,1,21)) -> 0 | CJ18: =COUNTIFS('DRAFT 2'!$D:$D,$B18,'DRAFT 2'!$A:$A,">="&DATE(2026,1,22),'DRAFT 2'!$A:$A,"<"&DATE(2026,IF(1=12,1+1,1+1),1)) -> 0 | CK18: =SUM(CG18:CJ18) -> 0 | CT18: 0 | CU18: =IFERROR(LOOKUP(2,1/('DRAFT 2'!$D:$D=$B18)*('DRAFT 2'!$A:$A>=DATE(2026,2,1))*('DRAFT 2'!$A:$A<DATE(2026,IF(2=12,2+1,2+1),1)),'DRAFT 2'!$A:$A),"") -> 0 | CV18: =COUNTIFS('DRAFT 2'!$D:$D,$B18,'DRAFT 2'!$A:$A,">="&DATE(2026,2,1),'DRAFT 2'!$A:$A,"<="&DATE(2026,2,7)) -> 0 | CW18: =COUNTIFS('DRAFT 2'!$D:$D,$B18,'DRAFT 2'!$A:$A,">="&DATE(2026,2,8),'DRAFT 2'!$A:$A,"<="&DATE(2026,2,14)) -> 0 | CX18: =COUNTIFS('DRAFT 2'!$D:$D,$B18,'DRAFT 2'!$A:$A,">="&DATE(2026,2,15),'DRAFT 2'!$A:$A,"<="&DATE(2026,2,21)) -> 0 | CY18: =COUNTIFS('DRAFT 2'!$D:$D,$B18,'DRAFT 2'!$A:$A,">="&DATE(2026,2,22),'DRAFT 2'!$A:$A,"<"&DATE(2026,IF(2=12,2+1,2+1),1)) -> 0 | CZ18: =SUM(CV18:CY18) -> 0 | DJ18: =IFERROR(LOOKUP(2,1/('DRAFT 2'!$D:$D=$B18)*('DRAFT 2'!$A:$A>=DATE(2026,3,1))*('DRAFT 2'!$A:$A<DATE(2026,IF(3=12,3+1,3+1),1)),'DRAFT 2'!$A:$A),"") -> 0 | DK18: =COUNTIFS('DRAFT 2'!$D:$D,$B18,'DRAFT 2'!$A:$A,">="&DATE(2026,3,1),'DRAFT 2'!$A:$A,"<="&DATE(2026,3,7)) -> 0 | DL18: =COUNTIFS('DRAFT 2'!$D:$D,$B18,'DRAFT 2'!$A:$A,">="&DATE(2026,3,8),'DRAFT 2'!$A:$A,"<="&DATE(2026,3,14)) -> 0 | DM18: =COUNTIFS('DRAFT 2'!$D:$D,$B18,'DRAFT 2'!$A:$A,">="&DATE(2026,3,15),'DRAFT 2'!$A:$A,"<="&DATE(2026,3,21)) -> 0 | DN18: =COUNTIFS('DRAFT 2'!$D:$D,$B18,'DRAFT 2'!$A:$A,">="&DATE(2026,3,22),'DRAFT 2'!$A:$A,"<"&DATE(2026,IF(3=12,3+1,3+1),1)) -> 0 | DO18: =SUM(DK18:DN18) -> 0 | DZ18: =IFERROR(LOOKUP(2,1/('DRAFT 2'!$D:$D=$B18)*('DRAFT 2'!$A:$A>=DATE(2026,4,1))*('DRAFT 2'!$A:$A<DATE(2026,IF(4=12,4+1,4+1),1)),'DRAFT 2'!$A:$A),"") -> 0 | EA18: =COUNTIFS('DRAFT 2'!$D:$D,$B18,'DRAFT 2'!$A:$A,">="&DATE(2026,4,1),'DRAFT 2'!$A:$A,"<="&DATE(2026,4,7)) -> 0 | EB18: =COUNTIFS('DRAFT 2'!$D:$D,$B18,'DRAFT 2'!$A:$A,">="&DATE(2026,4,8),'DRAFT 2'!$A:$A,"<="&DATE(2026,4,14)) -> 0 | EC18: =COUNTIFS('DRAFT 2'!$D:$D,$B18,'DRAFT 2'!$A:$A,">="&DATE(2026,4,15),'DRAFT 2'!$A:$A,"<="&DATE(2026,4,21)) -> 0 | ED18: =COUNTIFS('DRAFT 2'!$D:$D,$B18,'DRAFT 2'!$A:$A,">="&DATE(2026,4,22),'DRAFT 2'!$A:$A,"<"&DATE(2026,IF(4=12,4+1,4+1),1)) -> 0 | EE18: =SUM(EA18:ED18) -> 0 | EO18: =IFERROR(LOOKUP(2,1/('DRAFT 2'!$D:$D=$B18)*('DRAFT 2'!$A:$A>=DATE(2026,5,1))*('DRAFT 2'!$A:$A<DATE(2026,IF(5=12,5+1,5+1),1)),'DRAFT 2'!$A:$A),"") -> 0 | EP18: =COUNTIFS('DRAFT 2'!$D:$D,$B18,'DRAFT 2'!$A:$A,">="&DATE(2026,5,1),'DRAFT 2'!$A:$A,"<="&DATE(2026,5,7)) -> 0 | EQ18: =COUNTIFS('DRAFT 2'!$D:$D,$B18,'DRAFT 2'!$A:$A,">="&DATE(2026,5,8),'DRAFT 2'!$A:$A,"<="&DATE(2026,5,14)) -> 0 | ER18: =COUNTIFS('DRAFT 2'!$D:$D,$B18,'DRAFT 2'!$A:$A,">="&DATE(2026,5,15),'DRAFT 2'!$A:$A,"<="&DATE(2026,5,21)) -> 0 | ES18: =COUNTIFS('DRAFT 2'!$D:$D,$B18,'DRAFT 2'!$A:$A,">="&DATE(2026,5,22),'DRAFT 2'!$A:$A,"<"&DATE(2026,IF(5=12,5+1,5+1),1)) -> 0 | ET18: =SUM(EP18:ES18) -> 0 | FD18: =IFERROR(LOOKUP(2,1/('DRAFT 2'!$D:$D=$B18)*('DRAFT 2'!$A:$A>=DATE(2026,6,1))*('DRAFT 2'!$A:$A<DATE(2026,IF(6=12,6+1,6+1),1)),'DRAFT 2'!$A:$A),"") -> 0 | FE18: =COUNTIFS('DRAFT 2'!$D:$D,$B18,'DRAFT 2'!$A:$A,">="&DATE(2026,6,1),'DRAFT 2'!$A:$A,"<="&DATE(2026,6,7)) -> 0 | FF18: =COUNTIFS('DRAFT 2'!$D:$D,$B18,'DRAFT 2'!$A:$A,">="&DATE(2026,6,8),'DRAFT 2'!$A:$A,"<="&DATE(2026,6,14)) -> 0 | FG18: =COUNTIFS('DRAFT 2'!$D:$D,$B18,'DRAFT 2'!$A:$A,">="&DATE(2026,6,15),'DRAFT 2'!$A:$A,"<="&DATE(2026,6,21)) -> 0 | FH18: =COUNTIFS('DRAFT 2'!$D:$D,$B18,'DRAFT 2'!$A:$A,">="&DATE(2026,6,22),'DRAFT 2'!$A:$A,"<"&DATE(2026,IF(6=12,6+1,6+1),1)) -> 0 | FI18: =SUM(FE18:FH18) -> 0 | FT18: =IFERROR(LOOKUP(2,1/('DRAFT 2'!$D:$D=$B18)*('DRAFT 2'!$A:$A>=DATE(2026,7,1))*('DRAFT 2'!$A:$A<DATE(2026,IF(7=12,7+1,7+1),1)),'DRAFT 2'!$A:$A),"") -> 0 | FU18: =COUNTIFS('DRAFT 2'!$D:$D,$B18,'DRAFT 2'!$A:$A,">="&DATE(2026,7,1),'DRAFT 2'!$A:$A,"<="&DATE(2026,7,7)) -> 0 | FV18: =COUNTIFS('DRAFT 2'!$D:$D,$B18,'DRAFT 2'!$A:$A,">="&DATE(2026,7,8),'DRAFT 2'!$A:$A,"<="&DATE(2026,7,14)) -> 0 | FW18: =COUNTIFS('DRAFT 2'!$D:$D,$B18,'DRAFT 2'!$A:$A,">="&DATE(2026,7,15),'DRAFT 2'!$A:$A,"<="&DATE(2026,7,21)) -> 0 | FX18: =COUNTIFS('DRAFT 2'!$D:$D,$B18,'DRAFT 2'!$A:$A,">="&DATE(2026,7,22),'DRAFT 2'!$A:$A,"<"&DATE(2026,IF(7=12,7+1,7+1),1)) -> 0 | FY18: =SUM(FU18:FX18) -> 0 | GI18: =IFERROR(LOOKUP(2,1/('DRAFT 2'!$D:$D=$B18)*('DRAFT 2'!$A:$A>=DATE(2026,8,1))*('DRAFT 2'!$A:$A<DATE(2026,IF(8=12,8+1,8+1),1)),'DRAFT 2'!$A:$A),"") -> 0 | GJ18: =COUNTIFS('DRAFT 2'!$D:$D,$B18,'DRAFT 2'!$A:$A,">="&DATE(2026,8,1),'DRAFT 2'!$A:$A,"<="&DATE(2026,8,7)) -> 0 | GK18: =COUNTIFS('DRAFT 2'!$D:$D,$B18,'DRAFT 2'!$A:$A,">="&DATE(2026,8,8),'DRAFT 2'!$A:$A,"<="&DATE(2026,8,14)) -> 0 | GL18: =COUNTIFS('DRAFT 2'!$D:$D,$B18,'DRAFT 2'!$A:$A,">="&DATE(2026,8,15),'DRAFT 2'!$A:$A,"<="&DATE(2026,8,21)) -> 0 | GM18: =COUNTIFS('DRAFT 2'!$D:$D,$B18,'DRAFT 2'!$A:$A,">="&DATE(2026,8,22),'DRAFT 2'!$A:$A,"<"&DATE(2026,IF(8=12,8+1,8+1),1)) -> 0 | GN18: =SUM(GJ18:GM18) -> 0 | GX18: =IFERROR(LOOKUP(2,1/('DRAFT 2'!$D:$D=$B18)*('DRAFT 2'!$A:$A>=DATE(2026,9,1))*('DRAFT 2'!$A:$A<DATE(2026,IF(9=12,9+1,9+1),1)),'DRAFT 2'!$A:$A),"") -> 0 | GY18: =COUNTIFS('DRAFT 2'!$D:$D,$B18,'DRAFT 2'!$A:$A,">="&DATE(2026,9,1),'DRAFT 2'!$A:$A,"<="&DATE(2026,9,7)) -> 0 | GZ18: =COUNTIFS('DRAFT 2'!$D:$D,$B18,'DRAFT 2'!$A:$A,">="&DATE(2026,9,8),'DRAFT 2'!$A:$A,"<="&DATE(2026,9,14)) -> 0 | HA18: =COUNTIFS('DRAFT 2'!$D:$D,$B18,'DRAFT 2'!$A:$A,">="&DATE(2026,9,15),'DRAFT 2'!$A:$A,"<="&DATE(2026,9,21)) -> 0 | HB18: =COUNTIFS('DRAFT 2'!$D:$D,$B18,'DRAFT 2'!$A:$A,">="&DATE(2026,9,22),'DRAFT 2'!$A:$A,"<"&DATE(2026,IF(9=12,9+1,9+1),1)) -> 0 | HC18: =SUM(GY18:HB18) -> 0 | HN18: =IFERROR(LOOKUP(2,1/('DRAFT 2'!$D:$D=$B18)*('DRAFT 2'!$A:$A>=DATE(2026,10,1))*('DRAFT 2'!$A:$A<DATE(2026,IF(10=12,10+1,10+1),1)),'DRAFT 2'!$A:$A),"") -> 0 | HO18: =COUNTIFS('DRAFT 2'!$D:$D,$B18,'DRAFT 2'!$A:$A,">="&DATE(2026,10,1),'DRAFT 2'!$A:$A,"<="&DATE(2026,10,7)) -> 0 | HP18: =COUNTIFS('DRAFT 2'!$D:$D,$B18,'DRAFT 2'!$A:$A,">="&DATE(2026,10,8),'DRAFT 2'!$A:$A,"<="&DATE(2026,10,14)) -> 0 | HQ18: =COUNTIFS('DRAFT 2'!$D:$D,$B18,'DRAFT 2'!$A:$A,">="&DATE(2026,10,15),'DRAFT 2'!$A:$A,"<="&DATE(2026,10,21)) -> 0 | HR18: =COUNTIFS('DRAFT 2'!$D:$D,$B18,'DRAFT 2'!$A:$A,">="&DATE(2026,10,22),'DRAFT 2'!$A:$A,"<"&DATE(2026,IF(10=12,10+1,10+1),1)) -> 0 | HS18: =SUM(HO18:HR18) -> 0 | IC18: =IFERROR(LOOKUP(2,1/('DRAFT 2'!$D:$D=$B18)*('DRAFT 2'!$A:$A>=DATE(2026,11,1))*('DRAFT 2'!$A:$A<DATE(2026,IF(11=12,11+1,11+1),1)),'DRAFT 2'!$A:$A),"") -> 0 | ID18: =COUNTIFS('DRAFT 2'!$D:$D,$B18,'DRAFT 2'!$A:$A,">="&DATE(2026,11,1),'DRAFT 2'!$A:$A,"<="&DATE(2026,11,7)) -> 0 | IE18: =COUNTIFS('DRAFT 2'!$D:$D,$B18,'DRAFT 2'!$A:$A,">="&DATE(2026,11,8),'DRAFT 2'!$A:$A,"<="&DATE(2026,11,14)) -> 0 | IF18: =COUNTIFS('DRAFT 2'!$D:$D,$B18,'DRAFT 2'!$A:$A,">="&DATE(2026,11,15),'DRAFT 2'!$A:$A,"<="&DATE(2026,11,21)) -> 0 | IG18: =COUNTIFS('DRAFT 2'!$D:$D,$B18,'DRAFT 2'!$A:$A,">="&DATE(2026,11,22),'DRAFT 2'!$A:$A,"<"&DATE(2026,IF(11=12,11+1,11+1),1)) -> 0 | IH18: =SUM(ID18:IG18) -> 0 | IR18: =IFERROR(LOOKUP(2,1/('DRAFT 2'!$D:$D=$B18)*('DRAFT 2'!$A:$A>=DATE(2026,12,1))*('DRAFT 2'!$A:$A<DATE(2026,IF(12=12,12+1,12+1),1)),'DRAFT 2'!$A:$A),"") -> 0 | IS18: =COUNTIFS('DRAFT 2'!$D:$D,$B18,'DRAFT 2'!$A:$A,">="&DATE(2026,12,1),'DRAFT 2'!$A:$A,"<="&DATE(2026,12,7)) -> 0 | IT18: =COUNTIFS('DRAFT 2'!$D:$D,$B18,'DRAFT 2'!$A:$A,">="&DATE(2026,12,8),'DRAFT 2'!$A:$A,"<="&DATE(2026,12,14)) -> 0 | IU18: =COUNTIFS('DRAFT 2'!$D:$D,$B18,'DRAFT 2'!$A:$A,">="&DATE(2026,12,15),'DRAFT 2'!$A:$A,"<="&DATE(2026,12,21)) -> 0 | IV18: =COUNTIFS('DRAFT 2'!$D:$D,$B18,'DRAFT 2'!$A:$A,">="&DATE(2026,12,22),'DRAFT 2'!$A:$A,"<"&DATE(2026,IF(12=12,12+1,12+1),1)) -> 0 | IW18: =SUM(IS18:IV18) -> 0
