Workbook

Sheet PROJEÇÃO
A1: PROJEÇÃO — META SAP + SINALEIRO DE ATINGIMENTO | AS1: 🏪 SINALEIRO REDES DE FRANQUIAS | BB1: META CLIENTE IGUALITÁRIA | BH1: ⚡ ATIVAR SLICERS: Inserir > Segmentação de Dados > marcar: UF, CONSULTOR, SEMÁFORO, TIPO CARTEIRA, REDE | BP1: META COMPENSADA DINÂMICA
A2: IDENTIFICAÇÃO | E2: LOCALIZAÇÃO | F2: SINALEIRO REDE | L2: META MENSAL (SAP) | Z2: REALIZADO MENSAL | AN2: INDICADORES | AS2: GRUPO | AT2: CLIENTES | AU2: C/ VENDA | AV2: META R$ | AW2: FAT. REAL R$ | AX2: SINALEIRO % | AY2: COR | AZ2: AÇÃO | BB2: META POR CLIENTE (Ticket Médio) | BO2: . | BP2: ⚡ META COMPENSADA (Dinâmica) | CC2: FILTROS SLICER
A3: CNPJ | B3: NOME FANTASIA | C3: REDE / GRUPO CHAVE | D3: CONSULTOR | E3: UF | F3: TOTAL LOJAS | G3: SINALEIRO % | H3: COR SINALEIRO | I3: AÇÃO GRUPO | J3: _sep_10 | K3: REGIÃO | L3: META ANUAL | M3: META JAN | N3: META FEV | O3: META MAR | P3: META ABR | Q3: META MAI | R3: META JUN | S3: META JUL | T3: META AGO | U3: META SET | V3: META OUT | W3: META NOV | X3: META DEZ | Y3: _sep_25 | Z3: REAL ANUAL | AA3: REAL JAN | AB3: REAL FEV | AC3: REAL MAR | AD3: REAL ABR | AE3: REAL MAI | AF3: REAL JUN | AG3: REAL JUL | AH3: REAL AGO | AI3: REAL SET | AJ3: REAL OUT | AK3: REAL NOV | AL3: REAL DEZ | AM3: _sep_39 | AN3: % YTD | AO3: 🚦 SINAL META | AP3: GAP | AQ3: RANKING | AR3: _sep_44 | AS3: FITLAND | AT3: =COUNTIF(C$4:C$503,AS3) -> 44 | AU3: =COUNTIFS(C$4:C$503,AS3,Z$4:Z$503,">0") -> 44 | AV3: =SUMIF(C$4:C$503,AS3,L$4:L$503) -> 321337.45 | AW3: =SUMIF(C$4:C$503,AS3,Z$4:Z$503) -> 159653.14 | AX3: =IF(AV3=0,0,AW3/AV3) -> 0.49683951 | AY3: =IF(AX3>=0.6,"🟢 VERDE",IF(AX3>=0.4,"🟡 AMARELO",IF(AX3>=0.01,"🔴 VERMELHO","🟣 ROXO"))) -> 🟡 AMARELO | AZ3: =IF(AX3>=0.6,"JBP",IF(AX3>=0.4,"Sell Out",IF(AX3>=0.1,"Positivação + Expandir",IF(AX3>=0.01,"Ativar + Prospectar","Mapear + Prospectar")))) -> Sell Out | BA3: . | BB3: DIST ANUAL | BC3: DIST JAN | BD3: DIST FEV | BE3: DIST MAR | BF3: DIST ABR | BG3: DIST MAI | BH3: DIST JUN | BI3: DIST JUL | BJ3: DIST AGO | BK3: DIST SET | BL3: DIST OUT | BM3: DIST NOV | BN3: DIST DEZ | BO3: ._67 | BP3: COMP ANUAL | BQ3: COMP JAN | BR3: COMP FEV | BS3: COMP MAR | BT3: COMP ABR | BU3: COMP MAI | BV3: COMP JUN | BW3: COMP JUL | BX3: COMP AGO | BY3: COMP SET | BZ3: COMP OUT | CA3: COMP NOV | CB3: COMP DEZ | CC3: SEMÁFORO | CD3: TIPO CARTEIRA | CE3: REDE
A4: 23014826000105 | B4: TROPICAL SUPERMERCADOS LTDA | C4: CENTRO OESTE | D4: LARISSA PADILHA | E4: MT | F4: =IFERROR(VLOOKUP(C4,$AS$3:$AT$10,2,FALSE()),IFERROR(VLOOKUP(C4,$AS$15:$AT$22,2,FALSE()),"")) -> 33 | G4: =IFERROR(VLOOKUP(C4,$AS$3:$AX$10,6,FALSE()),IFERROR(VLOOKUP(C4,$AS$15:$AX$22,6,FALSE()),"")) -> 0.34149404 | H4: =IFERROR(VLOOKUP(C4,$AS$3:$AY$10,7,FALSE()),IFERROR(VLOOKUP(C4,$AS$15:$AY$22,7,FALSE()),"")) -> 🔴 VERMELHO | I4: =IFERROR(VLOOKUP(C4,$AS$3:$AZ$10,8,FALSE()),IFERROR(VLOOKUP(C4,$AS$15:$AZ$22,8,FALSE()),"")) -> Positivação + Expandir | K4: CENTRO OESTE | L4: 249796.02 | M4: 17553.92 | N4: 18343.21 | O4: 18785.22 | P4: 19274.58 | Q4: 19906.01 | R4: 20426.95 | S4: 21216.24 | T4: 21737.18 | U4: 22226.54 | V4: 22779.05 | W4: 23378.91 | X4: 24168.21 | Y4: . | Z4: =SUM(AA4:AL4) -> 52292.36 | AF4: 6442.21 | AG4: 4099.98 | AH4: 8406.63 | AI4: 5299.97 | AK4: 14998.98 | AL4: 13044.59 | AM4: . | AN4: =IF(L4=0,0,Z4/L4) -> 0.20934024 | AO4: =IF(AN4="","",IF(AN4>=0.9,"🟢",IF(AN4>=0.7,"🟡",IF(AN4>=0.5,"🟠","🔴")))) -> 🔴 | AP4: =IF(L4=0,0,L4-Z4) -> 197503.66 | AQ4: =IF(AP4=0,"",RANK(AP4,AP$4:AP$503,0)) -> 1 | AR4: . | AS4: CIA DA SAUDE | AT4: =COUNTIF(C$4:C$503,AS4) -> 21 | AU4: =COUNTIFS(C$4:C$503,AS4,Z$4:Z$503,">0") -> 19 | AV4: =SUMIF(C$4:C$503,AS4,L$4:L$503) -> 90676.46 | AW4: =SUMIF(C$4:C$503,AS4,Z$4:Z$503) -> 44568.8 | AX4: =IF(AV4=0,0,AW4/AV4) -> 0.49151456 | AY4: =IF(AX4>=0.6,"🟢 VERDE",IF(AX4>=0.4,"🟡 AMARELO",IF(AX4>=0.01,"🔴 VERMELHO","🟣 ROXO"))) -> 🟡 AMARELO | AZ4: =IF(AX4>=0.6,"JBP",IF(AX4>=0.4,"Sell Out",IF(AX4>=0.1,"Positivação + Expandir",IF(AX4>=0.01,"Ativar + Prospectar","Mapear + Prospectar")))) -> Sell Out | BA4: . | BB4: =SUM(L$4:L$503)/COUNTA(A$4:A$503) -> 9494.3999 | BC4: =SUM(M$4:M$503)/COUNTA(A$4:A$503) -> 667.20008 | BD4: =SUM(N$4:N$503)/COUNTA(A$4:A$503) -> 697.19996 | BE4: =SUM(O$4:O$503)/COUNTA(A$4:A$503) -> 713.9999 | BF4: =SUM(P$4:P$503)/COUNTA(A$4:A$503) -> 732.59984 | BG4: =SUM(Q$4:Q$503)/COUNTA(A$4:A$503) -> 756.59992 | BH4: =SUM(R$4:R$503)/COUNTA(A$4:A$503) -> 776.40004 | BI4: =SUM(S$4:S$503)/COUNTA(A$4:A$503) -> 806.40012 | BJ4: =SUM(T$4:T$503)/COUNTA(A$4:A$503) -> 826.1999 | BK4: =SUM(U$4:U$503)/COUNTA(A$4:A$503) -> 844.8002 | BL4: =SUM(V$4:V$503)/COUNTA(A$4:A$503) -> 865.7998 | BM4: =SUM(W$4:W$503)/COUNTA(A$4:A$503) -> 888.59982 | BN4: =SUM(X$4:X$503)/COUNTA(A$4:A$503) -> 918.60034 | BO4: . | BP4: =IF(Z4>=BB4,0,IFERROR(BB4+(SUMPRODUCT((Z$4:Z$503>=BB$4:BB$503)*(Z$4:Z$503-BB$4:BB$503))/MAX(1,COUNTIF(Z$4:Z$503,"<"&BB4+0.01))),BB4)) -> 0 | BQ4: =IF(AA4>=BC4,0,IFERROR(BC4+SUMPRODUCT((AA$4:AA$503>=BC$4:BC$503)*(AA$4:AA$503-BC$4:BC$503))/MAX(1,COUNTIF(AA$4:AA$503,"<"&BC4+0.01)),BC4)) -> 2238.4659 | BR4: =IF(AB4>=BD4,0,IFERROR(BD4+SUMPRODUCT((AB$4:AB$503>=BD$4:BD$503)*(AB$4:AB$503-BD$4:BD$503))/MAX(1,COUNTIF(AB$4:AB$503,"<"&BD4+0.01)),BD4)) -> 3335.2938 | BS4: =IF(AC4>=BE4,0,IFERROR(BE4+SUMPRODUCT((AC$4:AC$503>=BE$4:BE$503)*(AC$4:AC$503-BE$4:BE$503))/MAX(1,COUNTIF(AC$4:AC$503,"<"&BE4+0.01)),BE4)) -> 6188.7335 | BT4: =IF(AD4>=BF4,0,IFERROR(BF4+SUMPRODUCT((AD$4:AD$503>=BF$4:BF$503)*(AD$4:AD$503-BF$4:BF$503))/MAX(1,COUNTIF(AD$4:AD$503,"<"&BF4+0.01)),BF4)) -> 11354.354 | BU4: =IF(AE4>=BG4,0,IFERROR(BG4+SUMPRODUCT((AE$4:AE$503>=BG$4:BG$503)*(AE$4:AE$503-BG$4:BG$503))/MAX(1,COUNTIF(AE$4:AE$503,"<"&BG4+0.01)),BG4)) -> 7704.8592 | BV4: =IF(AF4>=BH4,0,IFERROR(BH4+SUMPRODUCT((AF$4:AF$503>=BH$4:BH$503)*(AF$4:AF$503-BH$4:BH$503))/MAX(1,COUNTIF(AF$4:AF$503,"<"&BH4+0.01)),BH4)) -> 0 | BW4: =IF(AG4>=BI4,0,IFERROR(BI4+SUMPRODUCT((AG$4:AG$503>=BI$4:BI$503)*(AG$4:AG$503-BI$4:BI$503))/MAX(1,COUNTIF(AG$4:AG$503,"<"&BI4+0.01)),BI4)) -> 0 | BX4: =IF(AH4>=BJ4,0,IFERROR(BJ4+SUMPRODUCT((AH$4:AH$503>=BJ$4:BJ$503)*(AH$4:AH$503-BJ$4:BJ$503))/MAX(1,COUNTIF(AH$4:AH$503,"<"&BJ4+0.01)),BJ4)) -> 0 | ... CB4: =IF(AL4>=BN4,0,IFERROR(BN4+SUMPRODUCT((AL$4:AL$503>=BN$4:BN$503)*(AL$4:AL$503-BN$4:BN$503))/MAX(1,COUNTIF(AL$4:AL$503,"<"&BN4+0.01)),BN4)) -> 0 | CC4: =IF(AO4="🟢","VERDE",IF(AO4="🟡","AMARELO",IF(AO4="🟠","VERMELHO",IF(AO4="🔴","VERMELHO","ROXO")))) -> VERMELHO | CD4: 🌎 REGIÕES | CE4: SEM REDE
A5: 59673556000191 | B5: SHS IMPORTACAO E EXPORTACAO DE ARTIGOS D | C5: SUL | D5: HEMANUELE DITZEL (MANU) | E5: PR | F5: =IFERROR(VLOOKUP(C5,$AS$3:$AT$10,2,FALSE()),IFERROR(VLOOKUP(C5,$AS$15:$AT$22,2,FALSE()),"")) -> 132 | G5: =IFERROR(VLOOKUP(C5,$AS$3:$AX$10,6,FALSE()),IFERROR(VLOOKUP(C5,$AS$15:$AX$22,6,FALSE()),"")) -> 0.46819018 | H5: =IFERROR(VLOOKUP(C5,$AS$3:$AY$10,7,FALSE()),IFERROR(VLOOKUP(C5,$AS$15:$AY$22,7,FALSE()),"")) -> 🟡 AMARELO | I5: =IFERROR(VLOOKUP(C5,$AS$3:$AZ$10,8,FALSE()),IFERROR(VLOOKUP(C5,$AS$15:$AZ$22,8,FALSE()),"")) -> Sell Out | K5: SUL | L5: 162422.58 | M5: 11413.92 | N5: 11927.14 | O5: 12214.54 | P5: 12532.73 | Q5: 12943.31 | R5: 13282.03 | S5: 13795.24 | T5: 14133.97 | U5: 14452.16 | V5: 14811.41 | W5: 15201.46 | X5: 15714.67 | Y5: . | Z5: =SUM(AA5:AL5) -> 65318.4 | AC5: 10611.2 | AD5: 54707.2 | AM5: . | AN5: =IF(L5=0,0,Z5/L5) -> 0.40215098 | AO5: =IF(AN5="","",IF(AN5>=0.9,"🟢",IF(AN5>=0.7,"🟡",IF(AN5>=0.5,"🟠","🔴")))) -> 🔴 | AP5: =IF(L5=0,0,L5-Z5) -> 97104.18 | AQ5: =IF(AP5=0,"",RANK(AP5,AP$4:AP$503,0)) -> 2 | AR5: . | AS5: DIVINA TERRA | AT5: =COUNTIF(C$4:C$503,AS5) -> 15 | AU5: =COUNTIFS(C$4:C$503,AS5,Z$4:Z$503,">0") -> 12 | AV5: =SUMIF(C$4:C$503,AS5,L$4:L$503) -> 54466.5 | AW5: =SUMIF(C$4:C$503,AS5,Z$4:Z$503) -> 33829.79 | AX5: =IF(AV5=0,0,AW5/AV5) -> 0.62111188 | AY5: =IF(AX5>=0.6,"🟢 VERDE",IF(AX5>=0.4,"🟡 AMARELO",IF(AX5>=0.01,"🔴 VERMELHO","🟣 ROXO"))) -> 🟢 VERDE | AZ5: =IF(AX5>=0.6,"JBP",IF(AX5>=0.4,"Sell Out",IF(AX5>=0.1,"Positivação + Expandir",IF(AX5>=0.01,"Ativar + Prospectar","Mapear + Prospectar")))) -> JBP | BA5: . | BB5: =SUM(L$4:L$503)/COUNTA(A$4:A$503) -> 9494.3999 | BC5: =SUM(M$4:M$503)/COUNTA(A$4:A$503) -> 667.20008 | BD5: =SUM(N$4:N$503)/COUNTA(A$4:A$503) -> 697.19996 | BE5: =SUM(O$4:O$503)/COUNTA(A$4:A$503) -> 713.9999 | BF5: =SUM(P$4:P$503)/COUNTA(A$4:A$503) -> 732.59984 | BG5: =SUM(Q$4:Q$503)/COUNTA(A$4:A$503) -> 756.59992 | BH5: =SUM(R$4:R$503)/COUNTA(A$4:A$503) -> 776.40004 | BI5: =SUM(S$4:S$503)/COUNTA(A$4:A$503) -> 806.40012 | BJ5: =SUM(T$4:T$503)/COUNTA(A$4:A$503) -> 826.1999 | BK5: =SUM(U$4:U$503)/COUNTA(A$4:A$503) -> 844.8002 | BL5: =SUM(V$4:V$503)/COUNTA(A$4:A$503) -> 865.7998 | BM5: =SUM(W$4:W$503)/COUNTA(A$4:A$503) -> 888.59982 | BN5: =SUM(X$4:X$503)/COUNTA(A$4:A$503) -> 918.60034 | BO5: . | BP5: =IF(Z5>=BB5,0,IFERROR(BB5+(SUMPRODUCT((Z$4:Z$503>=BB$4:BB$503)*(Z$4:Z$503-BB$4:BB$503))/MAX(1,COUNTIF(Z$4:Z$503,"<"&BB5+0.01))),BB5)) -> 0 | BQ5: =IF(AA5>=BC5,0,IFERROR(BC5+SUMPRODUCT((AA$4:AA$503>=BC$4:BC$503)*(AA$4:AA$503-BC$4:BC$503))/MAX(1,COUNTIF(AA$4:AA$503,"<"&BC5+0.01)),BC5)) -> 2238.4659 | BR5: =IF(AB5>=BD5,0,IFERROR(BD5+SUMPRODUCT((AB$4:AB$503>=BD$4:BD$503)*(AB$4:AB$503-BD$4:BD$503))/MAX(1,COUNTIF(AB$4:AB$503,"<"&BD5+0.01)),BD5)) -> 3335.2938 | BS5: =IF(AC5>=BE5,0,IFERROR(BE5+SUMPRODUCT((AC$4:AC$503>=BE$4:BE$503)*(AC$4:AC$503-BE$4:BE$503))/MAX(1,COUNTIF(AC$4:AC$503,"<"&BE5+0.01)),BE5)) -> 0 | BT5: =IF(AD5>=BF5,0,IFERROR(BF5+SUMPRODUCT((AD$4:AD$503>=BF$4:BF$503)*(AD$4:AD$503-BF$4:BF$503))/MAX(1,COUNTIF(AD$4:AD$503,"<"&BF5+0.01)),BF5)) -> 0 | BU5: =IF(AE5>=BG5,0,IFERROR(BG5+SUMPRODUCT((AE$4:AE$503>=BG$4:BG$503)*(AE$4:AE$503-BG$4:BG$503))/MAX(1,COUNTIF(AE$4:AE$503,"<"&BG5+0.01)),BG5)) -> 7704.8592 | BV5: =IF(AF5>=BH5,0,IFERROR(BH5+SUMPRODUCT((AF$4:AF$503>=BH$4:BH$503)*(AF$4:AF$503-BH$4:BH$503))/MAX(1,COUNTIF(AF$4:AF$503,"<"&BH5+0.01)),BH5)) -> 9942.6504 | BW5: =IF(AG5>=BI5,0,IFERROR(BI5+SUMPRODUCT((AG$4:AG$503>=BI$4:BI$503)*(AG$4:AG$503-BI$4:BI$503))/MAX(1,COUNTIF(AG$4:AG$503,"<"&BI5+0.01)),BI5)) -> 9142.1587 | BX5: =IF(AH5>=BJ5,0,IFERROR(BJ5+SUMPRODUCT((AH$4:AH$503>=BJ$4:BJ$503)*(AH$4:AH$503-BJ$4:BJ$503))/MAX(1,COUNTIF(AH$4:AH$503,"<"&BJ5+0.01)),BJ5)) -> 5621.5026 | ... CB5: =IF(AL5>=BN5,0,IFERROR(BN5+SUMPRODUCT((AL$4:AL$503>=BN$4:BN$503)*(AL$4:AL$503-BN$4:BN$503))/MAX(1,COUNTIF(AL$4:AL$503,"<"&BN5+0.01)),BN5)) -> 3597.2615 | CC5: =IF(AO5="🟢","VERDE",IF(AO5="🟡","AMARELO",IF(AO5="🟠","VERMELHO",IF(AO5="🔴","VERMELHO","ROXO")))) -> VERMELHO | CD5: 🌎 REGIÕES | CE5: SEM REDE
A6: 42535786000191 | B6: BEVILACQUA CEREAIS LTDA - EPP | C6: RJ + ES + MG | D6: LARISSA PADILHA | E6: MG | F6: =IFERROR(VLOOKUP(C6,$AS$3:$AT$10,2,FALSE()),IFERROR(VLOOKUP(C6,$AS$15:$AT$22,2,FALSE()),"")) -> 49 | G6: =IFERROR(VLOOKUP(C6,$AS$3:$AX$10,6,FALSE()),IFERROR(VLOOKUP(C6,$AS$15:$AX$22,6,FALSE()),"")) -> 0.46396509 | H6: =IFERROR(VLOOKUP(C6,$AS$3:$AY$10,7,FALSE()),IFERROR(VLOOKUP(C6,$AS$15:$AY$22,7,FALSE()),"")) -> 🟡 AMARELO | I6: =IFERROR(VLOOKUP(C6,$AS$3:$AZ$10,8,FALSE()),IFERROR(VLOOKUP(C6,$AS$15:$AZ$22,8,FALSE()),"")) -> Sell Out | K6: RJ + ES + MG | L6: 125085.15 | M6: 8790.11 | N6: 9185.35 | O6: 9406.68 | P6: 9651.73 | Q6: 9967.92 | R6: 10228.78 | S6: 10624.02 | T6: 10884.87 | U6: 11129.92 | V6: 11406.59 | W6: 11706.97 | X6: 12102.21 | Y6: . | Z6: =SUM(AA6:AL6) -> 61002.61 | AD6: 10984.56 | AE6: 40838.05 | AH6: 9180 | AM6: . | AN6: =IF(L6=0,0,Z6/L6) -> 0.48768867 | AO6: =IF(AN6="","",IF(AN6>=0.9,"🟢",IF(AN6>=0.7,"🟡",IF(AN6>=0.5,"🟠","🔴")))) -> 🔴 | AP6: =IF(L6=0,0,L6-Z6) -> 64082.54 | AQ6: =IF(AP6=0,"",RANK(AP6,AP$4:AP$503,0)) -> 3 | AR6: . | AS6: VIDA LEVE | AT6: =COUNTIF(C$4:C$503,AS6) -> 25 | AU6: =COUNTIFS(C$4:C$503,AS6,Z$4:Z$503,">0") -> 24 | AV6: =SUMIF(C$4:C$503,AS6,L$4:L$503) -> 108083.15 | AW6: =SUMIF(C$4:C$503,AS6,Z$4:Z$503) -> 58013.82 | AX6: =IF(AV6=0,0,AW6/AV6) -> 0.53675175 | AY6: =IF(AX6>=0.6,"🟢 VERDE",IF(AX6>=0.4,"🟡 AMARELO",IF(AX6>=0.01,"🔴 VERMELHO","🟣 ROXO"))) -> 🟡 AMARELO | AZ6: =IF(AX6>=0.6,"JBP",IF(AX6>=0.4,"Sell Out",IF(AX6>=0.1,"Positivação + Expandir",IF(AX6>=0.01,"Ativar + Prospectar","Mapear + Prospectar")))) -> Sell Out | BA6: . | BB6: =SUM(L$4:L$503)/COUNTA(A$4:A$503) -> 9494.3999 | BC6: =SUM(M$4:M$503)/COUNTA(A$4:A$503) -> 667.20008 | BD6: =SUM(N$4:N$503)/COUNTA(A$4:A$503) -> 697.19996 | BE6: =SUM(O$4:O$503)/COUNTA(A$4:A$503) -> 713.9999 | BF6: =SUM(P$4:P$503)/COUNTA(A$4:A$503) -> 732.59984 | BG6: =SUM(Q$4:Q$503)/COUNTA(A$4:A$503) -> 756.59992 | BH6: =SUM(R$4:R$503)/COUNTA(A$4:A$503) -> 776.40004 | BI6: =SUM(S$4:S$503)/COUNTA(A$4:A$503) -> 806.40012 | BJ6: =SUM(T$4:T$503)/COUNTA(A$4:A$503) -> 826.1999 | BK6: =SUM(U$4:U$503)/COUNTA(A$4:A$503) -> 844.8002 | BL6: =SUM(V$4:V$503)/COUNTA(A$4:A$503) -> 865.7998 | BM6: =SUM(W$4:W$503)/COUNTA(A$4:A$503) -> 888.59982 | BN6: =SUM(X$4:X$503)/COUNTA(A$4:A$503) -> 918.60034 | BO6: . | BP6: =IF(Z6>=BB6,0,IFERROR(BB6+(SUMPRODUCT((Z$4:Z$503>=BB$4:BB$503)*(Z$4:Z$503-BB$4:BB$503))/MAX(1,COUNTIF(Z$4:Z$503,"<"&BB6+0.01))),BB6)) -> 0 | BQ6: =IF(AA6>=BC6,0,IFERROR(BC6+SUMPRODUCT((AA$4:AA$503>=BC$4:BC$503)*(AA$4:AA$503-BC$4:BC$503))/MAX(1,COUNTIF(AA$4:AA$503,"<"&BC6+0.01)),BC6)) -> 2238.4659 | BR6: =IF(AB6>=BD6,0,IFERROR(BD6+SUMPRODUCT((AB$4:AB$503>=BD$4:BD$503)*(AB$4:AB$503-BD$4:BD$503))/MAX(1,COUNTIF(AB$4:AB$503,"<"&BD6+0.01)),BD6)) -> 3335.2938 | BS6: =IF(AC6>=BE6,0,IFERROR(BE6+SUMPRODUCT((AC$4:AC$503>=BE$4:BE$503)*(AC$4:AC$503-BE$4:BE$503))/MAX(1,COUNTIF(AC$4:AC$503,"<"&BE6+0.01)),BE6)) -> 6188.7335 | BT6: =IF(AD6>=BF6,0,IFERROR(BF6+SUMPRODUCT((AD$4:AD$503>=BF$4:BF$503)*(AD$4:AD$503-BF$4:BF$503))/MAX(1,COUNTIF(AD$4:AD$503,"<"&BF6+0.01)),BF6)) -> 0 | BU6: =IF(AE6>=BG6,0,IFERROR(BG6+SUMPRODUCT((AE$4:AE$503>=BG$4:BG$503)*(AE$4:AE$503-BG$4:BG$503))/MAX(1,COUNTIF(AE$4:AE$503,"<"&BG6+0.01)),BG6)) -> 0 | BV6: =IF(AF6>=BH6,0,IFERROR(BH6+SUMPRODUCT((AF$4:AF$503>=BH$4:BH$503)*(AF$4:AF$503-BH$4:BH$503))/MAX(1,COUNTIF(AF$4:AF$503,"<"&BH6+0.01)),BH6)) -> 9942.6504 | BW6: =IF(AG6>=BI6,0,IFERROR(BI6+SUMPRODUCT((AG$4:AG$503>=BI$4:BI$503)*(AG$4:AG$503-BI$4:BI$503))/MAX(1,COUNTIF(AG$4:AG$503,"<"&BI6+0.01)),BI6)) -> 9142.1587 | BX6: =IF(AH6>=BJ6,0,IFERROR(BJ6+SUMPRODUCT((AH$4:AH$503>=BJ$4:BJ$503)*(AH$4:AH$503-BJ$4:BJ$503))/MAX(1,COUNTIF(AH$4:AH$503,"<"&BJ6+0.01)),BJ6)) -> 0 | ... CB6: =IF(AL6>=BN6,0,IFERROR(BN6+SUMPRODUCT((AL$4:AL$503>=BN$4:BN$503)*(AL$4:AL$503-BN$4:BN$503))/MAX(1,COUNTIF(AL$4:AL$503,"<"&BN6+0.01)),BN6)) -> 3597.2615 | CC6: =IF(AO6="🟢","VERDE",IF(AO6="🟡","AMARELO",IF(AO6="🟠","VERMELHO",IF(AO6="🔴","VERMELHO","ROXO")))) -> VERMELHO | CD6: 🌎 REGIÕES | CE6: SEM REDE
A7: 41418074000120 | B7: SIMPLES E SAUDAVEL COMERCIO PRODUTOS NAT | C7: SP INTERIOR | D7: LARISSA PADILHA | E7: SP | F7: =IFERROR(VLOOKUP(C7,$AS$3:$AT$10,2,FALSE()),IFERROR(VLOOKUP(C7,$AS$15:$AT$22,2,FALSE()),"")) -> 42 | G7: =IFERROR(VLOOKUP(C7,$AS$3:$AX$10,6,FALSE()),IFERROR(VLOOKUP(C7,$AS$15:$AX$22,6,FALSE()),"")) -> 0.42487208 | H7: =IFERROR(VLOOKUP(C7,$AS$3:$AY$10,7,FALSE()),IFERROR(VLOOKUP(C7,$AS$15:$AY$22,7,FALSE()),"")) -> 🟡 AMARELO | I7: =IFERROR(VLOOKUP(C7,$AS$3:$AZ$10,8,FALSE()),IFERROR(VLOOKUP(C7,$AS$15:$AZ$22,8,FALSE()),"")) -> Sell Out | K7: SP INTERIOR | L7: 103481.47 | M7: 7271.95 | N7: 7598.93 | O7: 7782.04 | P7: 7984.76 | Q7: 8246.34 | R7: 8462.15 | S7: 8789.12 | T7: 9004.93 | U7: 9207.65 | V7: 9436.54 | W7: 9685.04 | X7: 10012.02 | Y7: . | Z7: =SUM(AA7:AL7) -> 43134.58 | AA7: 3845.66 | AB7: 3430.8 | AC7: 4796.88 | AD7: 3290.88 | AE7: 4094.88 | AG7: 4541.91 | AH7: 5337.2 | AI7: 6672 | AJ7: 7124.37 | AM7: . | AN7: =IF(L7=0,0,Z7/L7) -> 0.41683385 | AO7: =IF(AN7="","",IF(AN7>=0.9,"🟢",IF(AN7>=0.7,"🟡",IF(AN7>=0.5,"🟠","🔴")))) -> 🔴 | AP7: =IF(L7=0,0,L7-Z7) -> 60346.89 | AQ7: =IF(AP7=0,"",RANK(AP7,AP$4:AP$503,0)) -> 4 | AR7: . | AS7: MUNDO VERDE | AT7: =COUNTIF(C$4:C$503,AS7) -> 4 | AU7: =COUNTIFS(C$4:C$503,AS7,Z$4:Z$503,">0") -> 4 | AV7: =SUMIF(C$4:C$503,AS7,L$4:L$503) -> 36754.96 | AW7: =SUMIF(C$4:C$503,AS7,Z$4:Z$503) -> 19117.46 | AX7: =IF(AV7=0,0,AW7/AV7) -> 0.52013279 | AY7: =IF(AX7>=0.6,"🟢 VERDE",IF(AX7>=0.4,"🟡 AMARELO",IF(AX7>=0.01,"🔴 VERMELHO","🟣 ROXO"))) -> 🟡 AMARELO | AZ7: =IF(AX7>=0.6,"JBP",IF(AX7>=0.4,"Sell Out",IF(AX7>=0.1,"Positivação + Expandir",IF(AX7>=0.01,"Ativar + Prospectar","Mapear + Prospectar")))) -> Sell Out | BA7: . | BB7: =SUM(L$4:L$503)/COUNTA(A$4:A$503) -> 9494.3999 | BC7: =SUM(M$4:M$503)/COUNTA(A$4:A$503) -> 667.20008 | BD7: =SUM(N$4:N$503)/COUNTA(A$4:A$503) -> 697.19996 | BE7: =SUM(O$4:O$503)/COUNTA(A$4:A$503) -> 713.9999 | BF7: =SUM(P$4:P$503)/COUNTA(A$4:A$503) -> 732.59984 | BG7: =SUM(Q$4:Q$503)/COUNTA(A$4:A$503) -> 756.59992 | BH7: =SUM(R$4:R$503)/COUNTA(A$4:A$503) -> 776.40004 | BI7: =SUM(S$4:S$503)/COUNTA(A$4:A$503) -> 806.40012 | BJ7: =SUM(T$4:T$503)/COUNTA(A$4:A$503) -> 826.1999 | BK7: =SUM(U$4:U$503)/COUNTA(A$4:A$503) -> 844.8002 | BL7: =SUM(V$4:V$503)/COUNTA(A$4:A$503) -> 865.7998 | BM7: =SUM(W$4:W$503)/COUNTA(A$4:A$503) -> 888.59982 | BN7: =SUM(X$4:X$503)/COUNTA(A$4:A$503) -> 918.60034 | BO7: . | BP7: =IF(Z7>=BB7,0,IFERROR(BB7+(SUMPRODUCT((Z$4:Z$503>=BB$4:BB$503)*(Z$4:Z$503-BB$4:BB$503))/MAX(1,COUNTIF(Z$4:Z$503,"<"&BB7+0.01))),BB7)) -> 0 | BQ7: =IF(AA7>=BC7,0,IFERROR(BC7+SUMPRODUCT((AA$4:AA$503>=BC$4:BC$503)*(AA$4:AA$503-BC$4:BC$503))/MAX(1,COUNTIF(AA$4:AA$503,"<"&BC7+0.01)),BC7)) -> 0 | BR7: =IF(AB7>=BD7,0,IFERROR(BD7+SUMPRODUCT((AB$4:AB$503>=BD$4:BD$503)*(AB$4:AB$503-BD$4:BD$503))/MAX(1,COUNTIF(AB$4:AB$503,"<"&BD7+0.01)),BD7)) -> 0 | BS7: =IF(AC7>=BE7,0,IFERROR(BE7+SUMPRODUCT((AC$4:AC$503>=BE$4:BE$503)*(AC$4:AC$503-BE$4:BE$503))/MAX(1,COUNTIF(AC$4:AC$503,"<"&BE7+0.01)),BE7)) -> 0 | BT7: =IF(AD7>=BF7,0,IFERROR(BF7+SUMPRODUCT((AD$4:AD$503>=BF$4:BF$503)*(AD$4:AD$503-BF$4:BF$503))/MAX(1,COUNTIF(AD$4:AD$503,"<"&BF7+0.01)),BF7)) -> 0 | BU7: =IF(AE7>=BG7,0,IFERROR(BG7+SUMPRODUCT((AE$4:AE$503>=BG$4:BG$503)*(AE$4:AE$503-BG$4:BG$503))/MAX(1,COUNTIF(AE$4:AE$503,"<"&BG7+0.01)),BG7)) -> 0 | BV7: =IF(AF7>=BH7,0,IFERROR(BH7+SUMPRODUCT((AF$4:AF$503>=BH$4:BH$503)*(AF$4:AF$503-BH$4:BH$503))/MAX(1,COUNTIF(AF$4:AF$503,"<"&BH7+0.01)),BH7)) -> 9942.6504 | BW7: =IF(AG7>=BI7,0,IFERROR(BI7+SUMPRODUCT((AG$4:AG$503>=BI$4:BI$503)*(AG$4:AG$503-BI$4:BI$503))/MAX(1,COUNTIF(AG$4:AG$503,"<"&BI7+0.01)),BI7)) -> 0 | BX7: =IF(AH7>=BJ7,0,IFERROR(BJ7+SUMPRODUCT((AH$4:AH$503>=BJ$4:BJ$503)*(AH$4:AH$503-BJ$4:BJ$503))/MAX(1,COUNTIF(AH$4:AH$503,"<"&BJ7+0.01)),BJ7)) -> 0 | ... CB7: =IF(AL7>=BN7,0,IFERROR(BN7+SUMPRODUCT((AL$4:AL$503>=BN$4:BN$503)*(AL$4:AL$503-BN$4:BN$503))/MAX(1,COUNTIF(AL$4:AL$503,"<"&BN7+0.01)),BN7)) -> 3597.2615 | CC7: =IF(AO7="🟢","VERDE",IF(AO7="🟡","AMARELO",IF(AO7="🟠","VERMELHO",IF(AO7="🔴","VERMELHO","ROXO")))) -> VERMELHO | CD7: 🌎 REGIÕES | CE7: SEM REDE
A8: 00939085000178 | B8: PORT-GALI HOTELARIA E TURISMO LTDA | C8: SEM GRUPO | D8: LARISSA PADILHA | E8: . | F8: =IFERROR(VLOOKUP(C8,$AS$3:$AT$10,2,FALSE()),IFERROR(VLOOKUP(C8,$AS$15:$AT$22,2,FALSE()),"")) -> 49 | G8: =IFERROR(VLOOKUP(C8,$AS$3:$AX$10,6,FALSE()),IFERROR(VLOOKUP(C8,$AS$15:$AX$22,6,FALSE()),"")) -> 0.43639135 | H8: =IFERROR(VLOOKUP(C8,$AS$3:$AY$10,7,FALSE()),IFERROR(VLOOKUP(C8,$AS$15:$AY$22,7,FALSE()),"")) -> 🟡 AMARELO | I8: =IFERROR(VLOOKUP(C8,$AS$3:$AZ$10,8,FALSE()),IFERROR(VLOOKUP(C8,$AS$15:$AZ$22,8,FALSE()),"")) -> Sell Out | K8: . | L8: 96766.44 | M8: 6800.07 | N8: 7105.83 | O8: 7277.05 | P8: 7466.62 | Q8: 7711.23 | R8: 7913.03 | S8: 8218.79 | T8: 8420.59 | U8: 8610.16 | V8: 8824.19 | W8: 9056.56 | X8: 9362.32 | Y8: . | Z8: =SUM(AA8:AL8) -> 40115.33 | AD8: 5026.2 | AF8: 5040 | AI8: 5260.84 | AJ8: 10920 | AK8: 5490.9 | AL8: 8377.39 | AM8: . | AN8: =IF(L8=0,0,Z8/L8) -> 0.41455829 | AO8: =IF(AN8="","",IF(AN8>=0.9,"🟢",IF(AN8>=0.7,"🟡",IF(AN8>=0.5,"🟠","🔴")))) -> 🔴 | AP8: =IF(L8=0,0,L8-Z8) -> 56651.11 | AQ8: =IF(AP8=0,"",RANK(AP8,AP$4:AP$503,0)) -> 5 | AR8: . | AS8: BIO MUNDO | AT8: =COUNTIF(C$4:C$503,AS8) -> 7 | AU8: =COUNTIFS(C$4:C$503,AS8,Z$4:Z$503,">0") -> 4 | AV8: =SUMIF(C$4:C$503,AS8,L$4:L$503) -> 29621.13 | AW8: =SUMIF(C$4:C$503,AS8,Z$4:Z$503) -> 12480.52 | AX8: =IF(AV8=0,0,AW8/AV8) -> 0.42133842 | AY8: =IF(AX8>=0.6,"🟢 VERDE",IF(AX8>=0.4,"🟡 AMARELO",IF(AX8>=0.01,"🔴 VERMELHO","🟣 ROXO"))) -> 🟡 AMARELO | AZ8: =IF(AX8>=0.6,"JBP",IF(AX8>=0.4,"Sell Out",IF(AX8>=0.1,"Positivação + Expandir",IF(AX8>=0.01,"Ativar + Prospectar","Mapear + Prospectar")))) -> Sell Out | BA8: . | BB8: =SUM(L$4:L$503)/COUNTA(A$4:A$503) -> 9494.3999 | BC8: =SUM(M$4:M$503)/COUNTA(A$4:A$503) -> 667.20008 | BD8: =SUM(N$4:N$503)/COUNTA(A$4:A$503) -> 697.19996 | BE8: =SUM(O$4:O$503)/COUNTA(A$4:A$503) -> 713.9999 | BF8: =SUM(P$4:P$503)/COUNTA(A$4:A$503) -> 732.59984 | BG8: =SUM(Q$4:Q$503)/COUNTA(A$4:A$503) -> 756.59992 | BH8: =SUM(R$4:R$503)/COUNTA(A$4:A$503) -> 776.40004 | BI8: =SUM(S$4:S$503)/COUNTA(A$4:A$503) -> 806.40012 | BJ8: =SUM(T$4:T$503)/COUNTA(A$4:A$503) -> 826.1999 | BK8: =SUM(U$4:U$503)/COUNTA(A$4:A$503) -> 844.8002 | BL8: =SUM(V$4:V$503)/COUNTA(A$4:A$503) -> 865.7998 | BM8: =SUM(W$4:W$503)/COUNTA(A$4:A$503) -> 888.59982 | BN8: =SUM(X$4:X$503)/COUNTA(A$4:A$503) -> 918.60034 | BO8: . | BP8: =IF(Z8>=BB8,0,IFERROR(BB8+(SUMPRODUCT((Z$4:Z$503>=BB$4:BB$503)*(Z$4:Z$503-BB$4:BB$503))/MAX(1,COUNTIF(Z$4:Z$503,"<"&BB8+0.01))),BB8)) -> 0 | BQ8: =IF(AA8>=BC8,0,IFERROR(BC8+SUMPRODUCT((AA$4:AA$503>=BC$4:BC$503)*(AA$4:AA$503-BC$4:BC$503))/MAX(1,COUNTIF(AA$4:AA$503,"<"&BC8+0.01)),BC8)) -> 2238.4659 | BR8: =IF(AB8>=BD8,0,IFERROR(BD8+SUMPRODUCT((AB$4:AB$503>=BD$4:BD$503)*(AB$4:AB$503-BD$4:BD$503))/MAX(1,COUNTIF(AB$4:AB$503,"<"&BD8+0.01)),BD8)) -> 3335.2938 | BS8: =IF(AC8>=BE8,0,IFERROR(BE8+SUMPRODUCT((AC$4:AC$503>=BE$4:BE$503)*(AC$4:AC$503-BE$4:BE$503))/MAX(1,COUNTIF(AC$4:AC$503,"<"&BE8+0.01)),BE8)) -> 6188.7335 | BT8: =IF(AD8>=BF8,0,IFERROR(BF8+SUMPRODUCT((AD$4:AD$503>=BF$4:BF$503)*(AD$4:AD$503-BF$4:BF$503))/MAX(1,COUNTIF(AD$4:AD$503,"<"&BF8+0.01)),BF8)) -> 0 | BU8: =IF(AE8>=BG8,0,IFERROR(BG8+SUMPRODUCT((AE$4:AE$503>=BG$4:BG$503)*(AE$4:AE$503-BG$4:BG$503))/MAX(1,COUNTIF(AE$4:AE$503,"<"&BG8+0.01)),BG8)) -> 7704.8592 | BV8: =IF(AF8>=BH8,0,IFERROR(BH8+SUMPRODUCT((AF$4:AF$503>=BH$4:BH$503)*(AF$4:AF$503-BH$4:BH$503))/MAX(1,COUNTIF(AF$4:AF$503,"<"&BH8+0.01)),BH8)) -> 0 | BW8: =IF(AG8>=BI8,0,IFERROR(BI8+SUMPRODUCT((AG$4:AG$503>=BI$4:BI$503)*(AG$4:AG$503-BI$4:BI$503))/MAX(1,COUNTIF(AG$4:AG$503,"<"&BI8+0.01)),BI8)) -> 9142.1587 | BX8: =IF(AH8>=BJ8,0,IFERROR(BJ8+SUMPRODUCT((AH$4:AH$503>=BJ$4:BJ$503)*(AH$4:AH$503-BJ$4:BJ$503))/MAX(1,COUNTIF(AH$4:AH$503,"<"&BJ8+0.01)),BJ8)) -> 5621.5026 | ... CB8: =IF(AL8>=BN8,0,IFERROR(BN8+SUMPRODUCT((AL$4:AL$503>=BN$4:BN$503)*(AL$4:AL$503-BN$4:BN$503))/MAX(1,COUNTIF(AL$4:AL$503,"<"&BN8+0.01)),BN8)) -> 0 | CC8: =IF(AO8="🟢","VERDE",IF(AO8="🟡","AMARELO",IF(AO8="🟠","VERMELHO",IF(AO8="🔴","VERMELHO","ROXO")))) -> VERMELHO | CD8: 🌎 REGIÕES | CE8: SEM REDE
A9: 15265760000106 | B9: A CEREALISSIMA COMERCIO DE PRODUTOS NATU | C9: CENTRO OESTE | D9: LARISSA PADILHA | E9: GO | F9: =IFERROR(VLOOKUP(C9,$AS$3:$AT$10,2,FALSE()),IFERROR(VLOOKUP(C9,$AS$15:$AT$22,2,FALSE()),"")) -> 33 | G9: =IFERROR(VLOOKUP(C9,$AS$3:$AX$10,6,FALSE()),IFERROR(VLOOKUP(C9,$AS$15:$AX$22,6,FALSE()),"")) -> 0.34149404 | H9: =IFERROR(VLOOKUP(C9,$AS$3:$AY$10,7,FALSE()),IFERROR(VLOOKUP(C9,$AS$15:$AY$22,7,FALSE()),"")) -> 🔴 VERMELHO | I9: =IFERROR(VLOOKUP(C9,$AS$3:$AZ$10,8,FALSE()),IFERROR(VLOOKUP(C9,$AS$15:$AZ$22,8,FALSE()),"")) -> Positivação + Expandir | K9: CENTRO OESTE | L9: 83332.29 | M9: 5856.01 | N9: 6119.32 | O9: 6266.77 | P9: 6430.03 | Q9: 6640.67 | R9: 6814.46 | S9: 7077.77 | T9: 7251.55 | U9: 7414.8 | V9: 7599.12 | W9: 7799.24 | X9: 8062.55 | Y9: . | Z9: =SUM(AA9:AL9) -> 33079.94 | AC9: 2991.96 | AF9: 3054.38 | AG9: 3778.78 | AH9: 5097.2 | AI9: 5983.46 | AJ9: 3773.16 | AK9: 8401 | AM9: . | AN9: =IF(L9=0,0,Z9/L9) -> 0.39696425 | AO9: =IF(AN9="","",IF(AN9>=0.9,"🟢",IF(AN9>=0.7,"🟡",IF(AN9>=0.5,"🟠","🔴")))) -> 🔴 | AP9: =IF(L9=0,0,L9-Z9) -> 50252.35 | AQ9: =IF(AP9=0,"",RANK(AP9,AP$4:AP$503,0)) -> 6 | AR9: . | AS9: TUDO EM GRAOS | AT9: =COUNTIF(C$4:C$503,AS9) -> 3 | AU9: =COUNTIFS(C$4:C$503,AS9,Z$4:Z$503,">0") -> 2 | AV9: =SUMIF(C$4:C$503,AS9,L$4:L$503) -> 20677.87 | AW9: =SUMIF(C$4:C$503,AS9,Z$4:Z$503) -> 8579.2 | AX9: =IF(AV9=0,0,AW9/AV9) -> 0.41489767 | AY9: =IF(AX9>=0.6,"🟢 VERDE",IF(AX9>=0.4,"🟡 AMARELO",IF(AX9>=0.01,"🔴 VERMELHO","🟣 ROXO"))) -> 🟡 AMARELO | AZ9: =IF(AX9>=0.6,"JBP",IF(AX9>=0.4,"Sell Out",IF(AX9>=0.1,"Positivação + Expandir",IF(AX9>=0.01,"Ativar + Prospectar","Mapear + Prospectar")))) -> Sell Out | BA9: . | BB9: =SUM(L$4:L$503)/COUNTA(A$4:A$503) -> 9494.3999 | BC9: =SUM(M$4:M$503)/COUNTA(A$4:A$503) -> 667.20008 | BD9: =SUM(N$4:N$503)/COUNTA(A$4:A$503) -> 697.19996 | BE9: =SUM(O$4:O$503)/COUNTA(A$4:A$503) -> 713.9999 | BF9: =SUM(P$4:P$503)/COUNTA(A$4:A$503) -> 732.59984 | BG9: =SUM(Q$4:Q$503)/COUNTA(A$4:A$503) -> 756.59992 | BH9: =SUM(R$4:R$503)/COUNTA(A$4:A$503) -> 776.40004 | BI9: =SUM(S$4:S$503)/COUNTA(A$4:A$503) -> 806.40012 | BJ9: =SUM(T$4:T$503)/COUNTA(A$4:A$503) -> 826.1999 | BK9: =SUM(U$4:U$503)/COUNTA(A$4:A$503) -> 844.8002 | BL9: =SUM(V$4:V$503)/COUNTA(A$4:A$503) -> 865.7998 | BM9: =SUM(W$4:W$503)/COUNTA(A$4:A$503) -> 888.59982 | BN9: =SUM(X$4:X$503)/COUNTA(A$4:A$503) -> 918.60034 | BO9: . | BP9: =IF(Z9>=BB9,0,IFERROR(BB9+(SUMPRODUCT((Z$4:Z$503>=BB$4:BB$503)*(Z$4:Z$503-BB$4:BB$503))/MAX(1,COUNTIF(Z$4:Z$503,"<"&BB9+0.01))),BB9)) -> 0 | BQ9: =IF(AA9>=BC9,0,IFERROR(BC9+SUMPRODUCT((AA$4:AA$503>=BC$4:BC$503)*(AA$4:AA$503-BC$4:BC$503))/MAX(1,COUNTIF(AA$4:AA$503,"<"&BC9+0.01)),BC9)) -> 2238.4659 | BR9: =IF(AB9>=BD9,0,IFERROR(BD9+SUMPRODUCT((AB$4:AB$503>=BD$4:BD$503)*(AB$4:AB$503-BD$4:BD$503))/MAX(1,COUNTIF(AB$4:AB$503,"<"&BD9+0.01)),BD9)) -> 3335.2938 | BS9: =IF(AC9>=BE9,0,IFERROR(BE9+SUMPRODUCT((AC$4:AC$503>=BE$4:BE$503)*(AC$4:AC$503-BE$4:BE$503))/MAX(1,COUNTIF(AC$4:AC$503,"<"&BE9+0.01)),BE9)) -> 0 | BT9: =IF(AD9>=BF9,0,IFERROR(BF9+SUMPRODUCT((AD$4:AD$503>=BF$4:BF$503)*(AD$4:AD$503-BF$4:BF$503))/MAX(1,COUNTIF(AD$4:AD$503,"<"&BF9+0.01)),BF9)) -> 11354.354 | BU9: =IF(AE9>=BG9,0,IFERROR(BG9+SUMPRODUCT((AE$4:AE$503>=BG$4:BG$503)*(AE$4:AE$503-BG$4:BG$503))/MAX(1,COUNTIF(AE$4:AE$503,"<"&BG9+0.01)),BG9)) -> 7704.8592 | BV9: =IF(AF9>=BH9,0,IFERROR(BH9+SUMPRODUCT((AF$4:AF$503>=BH$4:BH$503)*(AF$4:AF$503-BH$4:BH$503))/MAX(1,COUNTIF(AF$4:AF$503,"<"&BH9+0.01)),BH9)) -> 0 | BW9: =IF(AG9>=BI9,0,IFERROR(BI9+SUMPRODUCT((AG$4:AG$503>=BI$4:BI$503)*(AG$4:AG$503-BI$4:BI$503))/MAX(1,COUNTIF(AG$4:AG$503,"<"&BI9+0.01)),BI9)) -> 0 | BX9: =IF(AH9>=BJ9,0,IFERROR(BJ9+SUMPRODUCT((AH$4:AH$503>=BJ$4:BJ$503)*(AH$4:AH$503-BJ$4:BJ$503))/MAX(1,COUNTIF(AH$4:AH$503,"<"&BJ9+0.01)),BJ9)) -> 0 | ... CB9: =IF(AL9>=BN9,0,IFERROR(BN9+SUMPRODUCT((AL$4:AL$503>=BN$4:BN$503)*(AL$4:AL$503-BN$4:BN$503))/MAX(1,COUNTIF(AL$4:AL$503,"<"&BN9+0.01)),BN9)) -> 3597.2615 | CC9: =IF(AO9="🟢","VERDE",IF(AO9="🟡","AMARELO",IF(AO9="🟠","VERMELHO",IF(AO9="🔴","VERMELHO","ROXO")))) -> VERMELHO | CD9: 🌎 REGIÕES | CE9: SEM REDE
A10: 08895369000111 | B10: ROTTA DO SOL HOTELARIA E TURISMO LTDA | C10: SEM GRUPO | D10: LARISSA PADILHA | E10: . | F10: =IFERROR(VLOOKUP(C10,$AS$3:$AT$10,2,FALSE()),IFERROR(VLOOKUP(C10,$AS$15:$AT$22,2,FALSE()),"")) -> 49 | G10: =IFERROR(VLOOKUP(C10,$AS$3:$AX$10,6,FALSE()),IFERROR(VLOOKUP(C10,$AS$15:$AX$22,6,FALSE()),"")) -> 0.43639135 | H10: =IFERROR(VLOOKUP(C10,$AS$3:$AY$10,7,FALSE()),IFERROR(VLOOKUP(C10,$AS$15:$AY$22,7,FALSE()),"")) -> 🟡 AMARELO | I10: =IFERROR(VLOOKUP(C10,$AS$3:$AZ$10,8,FALSE()),IFERROR(VLOOKUP(C10,$AS$15:$AZ$22,8,FALSE()),"")) -> Sell Out | K10: . | L10: 75249.03 | M10: 5287.98 | N10: 5525.74 | O10: 5658.89 | P10: 5806.31 | Q10: 5996.53 | R10: 6153.45 | S10: 6391.22 | T10: 6548.15 | U10: 6695.57 | V10: 6862 | W10: 7042.71 | X10: 7280.48 | Y10: . | Z10: =SUM(AA10:AL10) -> 30618.45 | AD10: 6846 | AE10: 3780 | AG10: 7118.85 | AI10: 5970 | AK10: 6903.6 | AM10: . | AN10: =IF(L10=0,0,Z10/L10) -> 0.40689495 | AO10: =IF(AN10="","",IF(AN10>=0.9,"🟢",IF(AN10>=0.7,"🟡",IF(AN10>=0.5,"🟠","🔴")))) -> 🔴 | AP10: =IF(L10=0,0,L10-Z10) -> 44630.58 | AQ10: =IF(AP10=0,"",RANK(AP10,AP$4:AP$503,0)) -> 7 | AR10: . | AS10: ARMAZEM FITSTORE | AT10: =COUNTIF(C$4:C$503,AS10) -> 0 | AU10: =COUNTIFS(C$4:C$503,AS10,Z$4:Z$503,">0") -> 0 | AV10: =SUMIF(C$4:C$503,AS10,L$4:L$503) -> 0 | AW10: =SUMIF(C$4:C$503,AS10,Z$4:Z$503) -> 0 | AX10: =IF(AV10=0,0,AW10/AV10) -> 0 | AY10: =IF(AX10>=0.6,"🟢 VERDE",IF(AX10>=0.4,"🟡 AMARELO",IF(AX10>=0.01,"🔴 VERMELHO","🟣 ROXO"))) -> 🟣 ROXO | AZ10: =IF(AX10>=0.6,"JBP",IF(AX10>=0.4,"Sell Out",IF(AX10>=0.1,"Positivação + Expandir",IF(AX10>=0.01,"Ativar + Prospectar","Mapear + Prospectar")))) -> Mapear + Prospectar | BA10: . | BB10: =SUM(L$4:L$503)/COUNTA(A$4:A$503) -> 9494.3999 | BC10: =SUM(M$4:M$503)/COUNTA(A$4:A$503) -> 667.20008 | BD10: =SUM(N$4:N$503)/COUNTA(A$4:A$503) -> 697.19996 | BE10: =SUM(O$4:O$503)/COUNTA(A$4:A$503) -> 713.9999 | BF10: =SUM(P$4:P$503)/COUNTA(A$4:A$503) -> 732.59984 | BG10: =SUM(Q$4:Q$503)/COUNTA(A$4:A$503) -> 756.59992 | BH10: =SUM(R$4:R$503)/COUNTA(A$4:A$503) -> 776.40004 | BI10: =SUM(S$4:S$503)/COUNTA(A$4:A$503) -> 806.40012 | BJ10: =SUM(T$4:T$503)/COUNTA(A$4:A$503) -> 826.1999 | BK10: =SUM(U$4:U$503)/COUNTA(A$4:A$503) -> 844.8002 | BL10: =SUM(V$4:V$503)/COUNTA(A$4:A$503) -> 865.7998 | BM10: =SUM(W$4:W$503)/COUNTA(A$4:A$503) -> 888.59982 | BN10: =SUM(X$4:X$503)/COUNTA(A$4:A$503) -> 918.60034 | BO10: . | BP10: =IF(Z10>=BB10,0,IFERROR(BB10+(SUMPRODUCT((Z$4:Z$503>=BB$4:BB$503)*(Z$4:Z$503-BB$4:BB$503))/MAX(1,COUNTIF(Z$4:Z$503,"<"&BB10+0.01))),BB10)) -> 0 | BQ10: =IF(AA10>=BC10,0,IFERROR(BC10+SUMPRODUCT((AA$4:AA$503>=BC$4:BC$503)*(AA$4:AA$503-BC$4:BC$503))/MAX(1,COUNTIF(AA$4:AA$503,"<"&BC10+0.01)),BC10)) -> 2238.4659 | BR10: =IF(AB10>=BD10,0,IFERROR(BD10+SUMPRODUCT((AB$4:AB$503>=BD$4:BD$503)*(AB$4:AB$503-BD$4:BD$503))/MAX(1,COUNTIF(AB$4:AB$503,"<"&BD10+0.01)),BD10)) -> 3335.2938 | BS10: =IF(AC10>=BE10,0,IFERROR(BE10+SUMPRODUCT((AC$4:AC$503>=BE$4:BE$503)*(AC$4:AC$503-BE$4:BE$503))/MAX(1,COUNTIF(AC$4:AC$503,"<"&BE10+0.01)),BE10)) -> 6188.7335 | BT10: =IF(AD10>=BF10,0,IFERROR(BF10+SUMPRODUCT((AD$4:AD$503>=BF$4:BF$503)*(AD$4:AD$503-BF$4:BF$503))/MAX(1,COUNTIF(AD$4:AD$503,"<"&BF10+0.01)),BF10)) -> 0 | BU10: =IF(AE10>=BG10,0,IFERROR(BG10+SUMPRODUCT((AE$4:AE$503>=BG$4:BG$503)*(AE$4:AE$503-BG$4:BG$503))/MAX(1,COUNTIF(AE$4:AE$503,"<"&BG10+0.01)),BG10)) -> 0 | BV10: =IF(AF10>=BH10,0,IFERROR(BH10+SUMPRODUCT((AF$4:AF$503>=BH$4:BH$503)*(AF$4:AF$503-BH$4:BH$503))/MAX(1,COUNTIF(AF$4:AF$503,"<"&BH10+0.01)),BH10)) -> 9942.6504 | BW10: =IF(AG10>=BI10,0,IFERROR(BI10+SUMPRODUCT((AG$4:AG$503>=BI$4:BI$503)*(AG$4:AG$503-BI$4:BI$503))/MAX(1,COUNTIF(AG$4:AG$503,"<"&BI10+0.01)),BI10)) -> 0 | BX10: =IF(AH10>=BJ10,0,IFERROR(BJ10+SUMPRODUCT((AH$4:AH$503>=BJ$4:BJ$503)*(AH$4:AH$503-BJ$4:BJ$503))/MAX(1,COUNTIF(AH$4:AH$503,"<"&BJ10+0.01)),BJ10)) -> 5621.5026 | ... CB10: =IF(AL10>=BN10,0,IFERROR(BN10+SUMPRODUCT((AL$4:AL$503>=BN$4:BN$503)*(AL$4:AL$503-BN$4:BN$503))/MAX(1,COUNTIF(AL$4:AL$503,"<"&BN10+0.01)),BN10)) -> 3597.2615 | CC10: =IF(AO10="🟢","VERDE",IF(AO10="🟡","AMARELO",IF(AO10="🟠","VERMELHO",IF(AO10="🔴","VERMELHO","ROXO")))) -> VERMELHO | CD10: 🌎 REGIÕES | CE10: SEM REDE
A11: 55615538000283 | B11: COMERCIAL TICAZO HIRATA SA | C11: SP INTERIOR | D11: LARISSA PADILHA | E11: SP | F11: =IFERROR(VLOOKUP(C11,$AS$3:$AT$10,2,FALSE()),IFERROR(VLOOKUP(C11,$AS$15:$AT$22,2,FALSE()),"")) -> 42 | G11: =IFERROR(VLOOKUP(C11,$AS$3:$AX$10,6,FALSE()),IFERROR(VLOOKUP(C11,$AS$15:$AX$22,6,FALSE()),"")) -> 0.42487208 | H11: =IFERROR(VLOOKUP(C11,$AS$3:$AY$10,7,FALSE()),IFERROR(VLOOKUP(C11,$AS$15:$AY$22,7,FALSE()),"")) -> 🟡 AMARELO | I11: =IFERROR(VLOOKUP(C11,$AS$3:$AZ$10,8,FALSE()),IFERROR(VLOOKUP(C11,$AS$15:$AZ$22,8,FALSE()),"")) -> Sell Out | K11: SP INTERIOR | L11: 64642.76 | M11: 4542.64 | N11: 4746.9 | O11: 4861.28 | P11: 4987.92 | Q11: 5151.32 | R11: 5286.13 | S11: 5490.39 | T11: 5625.19 | U11: 5751.83 | V11: 5894.81 | W11: 6050.05 | X11: 6254.3 | Y11: . | Z11: =SUM(AA11:AL11) -> 27305.35 | AC11: 4155.84 | AD11: 3082.89 | AE11: 5621.77 | AG11: 4988.89 | AH11: 2571.82 | AJ11: 4770.31 | AK11: 2113.83 | AM11: . | AN11: =IF(L11=0,0,Z11/L11) -> 0.42240384 | AO11: =IF(AN11="","",IF(AN11>=0.9,"🟢",IF(AN11>=0.7,"🟡",IF(AN11>=0.5,"🟠","🔴")))) -> 🔴 | AP11: =IF(L11=0,0,L11-Z11) -> 37337.41 | AQ11: =IF(AP11=0,"",RANK(AP11,AP$4:AP$503,0)) -> 8 | AR11: . | AS11: TOTAL REDES | AU11: =SUM(AU3:AU10) -> 109 | AV11: =SUM(AV3:AV10) -> 661617.52 | AW11: =SUM(AW3:AW10) -> 336242.73 | AX11: =IF(AV11=0,0,AW11/AV11) -> 0.50821316 | BA11: . | BB11: =SUM(L$4:L$503)/COUNTA(A$4:A$503) -> 9494.3999 | BC11: =SUM(M$4:M$503)/COUNTA(A$4:A$503) -> 667.20008 | BD11: =SUM(N$4:N$503)/COUNTA(A$4:A$503) -> 697.19996 | BE11: =SUM(O$4:O$503)/COUNTA(A$4:A$503) -> 713.9999 | BF11: =SUM(P$4:P$503)/COUNTA(A$4:A$503) -> 732.59984 | BG11: =SUM(Q$4:Q$503)/COUNTA(A$4:A$503) -> 756.59992 | BH11: =SUM(R$4:R$503)/COUNTA(A$4:A$503) -> 776.40004 | BI11: =SUM(S$4:S$503)/COUNTA(A$4:A$503) -> 806.40012 | BJ11: =SUM(T$4:T$503)/COUNTA(A$4:A$503) -> 826.1999 | BK11: =SUM(U$4:U$503)/COUNTA(A$4:A$503) -> 844.8002 | BL11: =SUM(V$4:V$503)/COUNTA(A$4:A$503) -> 865.7998 | BM11: =SUM(W$4:W$503)/COUNTA(A$4:A$503) -> 888.59982 | BN11: =SUM(X$4:X$503)/COUNTA(A$4:A$503) -> 918.60034 | BO11: . | BP11: =IF(Z11>=BB11,0,IFERROR(BB11+(SUMPRODUCT((Z$4:Z$503>=BB$4:BB$503)*(Z$4:Z$503-BB$4:BB$503))/MAX(1,COUNTIF(Z$4:Z$503,"<"&BB11+0.01))),BB11)) -> 0 | BQ11: =IF(AA11>=BC11,0,IFERROR(BC11+SUMPRODUCT((AA$4:AA$503>=BC$4:BC$503)*(AA$4:AA$503-BC$4:BC$503))/MAX(1,COUNTIF(AA$4:AA$503,"<"&BC11+0.01)),BC11)) -> 2238.4659 | BR11: =IF(AB11>=BD11,0,IFERROR(BD11+SUMPRODUCT((AB$4:AB$503>=BD$4:BD$503)*(AB$4:AB$503-BD$4:BD$503))/MAX(1,COUNTIF(AB$4:AB$503,"<"&BD11+0.01)),BD11)) -> 3335.2938 | BS11: =IF(AC11>=BE11,0,IFERROR(BE11+SUMPRODUCT((AC$4:AC$503>=BE$4:BE$503)*(AC$4:AC$503-BE$4:BE$503))/MAX(1,COUNTIF(AC$4:AC$503,"<"&BE11+0.01)),BE11)) -> 0 | BT11: =IF(AD11>=BF11,0,IFERROR(BF11+SUMPRODUCT((AD$4:AD$503>=BF$4:BF$503)*(AD$4:AD$503-BF$4:BF$503))/MAX(1,COUNTIF(AD$4:AD$503,"<"&BF11+0.01)),BF11)) -> 0 | BU11: =IF(AE11>=BG11,0,IFERROR(BG11+SUMPRODUCT((AE$4:AE$503>=BG$4:BG$503)*(AE$4:AE$503-BG$4:BG$503))/MAX(1,COUNTIF(AE$4:AE$503,"<"&BG11+0.01)),BG11)) -> 0 | BV11: =IF(AF11>=BH11,0,IFERROR(BH11+SUMPRODUCT((AF$4:AF$503>=BH$4:BH$503)*(AF$4:AF$503-BH$4:BH$503))/MAX(1,COUNTIF(AF$4:AF$503,"<"&BH11+0.01)),BH11)) -> 9942.6504 | BW11: =IF(AG11>=BI11,0,IFERROR(BI11+SUMPRODUCT((AG$4:AG$503>=BI$4:BI$503)*(AG$4:AG$503-BI$4:BI$503))/MAX(1,COUNTIF(AG$4:AG$503,"<"&BI11+0.01)),BI11)) -> 0 | BX11: =IF(AH11>=BJ11,0,IFERROR(BJ11+SUMPRODUCT((AH$4:AH$503>=BJ$4:BJ$503)*(AH$4:AH$503-BJ$4:BJ$503))/MAX(1,COUNTIF(AH$4:AH$503,"<"&BJ11+0.01)),BJ11)) -> 0 | ... CB11: =IF(AL11>=BN11,0,IFERROR(BN11+SUMPRODUCT((AL$4:AL$503>=BN$4:BN$503)*(AL$4:AL$503-BN$4:BN$503))/MAX(1,COUNTIF(AL$4:AL$503,"<"&BN11+0.01)),BN11)) -> 3597.2615 | CC11: =IF(AO11="🟢","VERDE",IF(AO11="🟡","AMARELO",IF(AO11="🟠","VERMELHO",IF(AO11="🔴","VERMELHO","ROXO")))) -> VERMELHO | CD11: 🌎 REGIÕES | CE11: SEM REDE
A12: 34924371000181 | B12: SOARES DISTRIBUIDORA DE PRODUTOS EM GERA | C12: SUL | D12: HEMANUELE DITZEL (MANU) | E12: PR | F12: =IFERROR(VLOOKUP(C12,$AS$3:$AT$10,2,FALSE()),IFERROR(VLOOKUP(C12,$AS$15:$AT$22,2,FALSE()),"")) -> 132 | G12: =IFERROR(VLOOKUP(C12,$AS$3:$AX$10,6,FALSE()),IFERROR(VLOOKUP(C12,$AS$15:$AX$22,6,FALSE()),"")) -> 0.46819018 | H12: =IFERROR(VLOOKUP(C12,$AS$3:$AY$10,7,FALSE()),IFERROR(VLOOKUP(C12,$AS$15:$AY$22,7,FALSE()),"")) -> 🟡 AMARELO | I12: =IFERROR(VLOOKUP(C12,$AS$3:$AZ$10,8,FALSE()),IFERROR(VLOOKUP(C12,$AS$15:$AZ$22,8,FALSE()),"")) -> Sell Out | K12: SUL | L12: 64453.39 | M12: 4529.33 | N12: 4732.99 | O12: 4847.04 | P12: 4973.31 | Q12: 5136.23 | R12: 5270.65 | S12: 5474.3 | T12: 5608.72 | U12: 5734.98 | V12: 5877.54 | W12: 6032.32 | X12: 6235.98 | Y12: . | Z12: =SUM(AA12:AL12) -> 27788.43 | AF12: 27788.43 | AM12: . | AN12: =IF(L12=0,0,Z12/L12) -> 0.43113993 | AO12: =IF(AN12="","",IF(AN12>=0.9,"🟢",IF(AN12>=0.7,"🟡",IF(AN12>=0.5,"🟠","🔴")))) -> 🔴 | AP12: =IF(L12=0,0,L12-Z12) -> 36664.96 | AQ12: =IF(AP12=0,"",RANK(AP12,AP$4:AP$503,0)) -> 9 | AR12: . | BA12: . | BB12: =SUM(L$4:L$503)/COUNTA(A$4:A$503) -> 9494.3999 | BC12: =SUM(M$4:M$503)/COUNTA(A$4:A$503) -> 667.20008 | BD12: =SUM(N$4:N$503)/COUNTA(A$4:A$503) -> 697.19996 | BE12: =SUM(O$4:O$503)/COUNTA(A$4:A$503) -> 713.9999 | BF12: =SUM(P$4:P$503)/COUNTA(A$4:A$503) -> 732.59984 | BG12: =SUM(Q$4:Q$503)/COUNTA(A$4:A$503) -> 756.59992 | BH12: =SUM(R$4:R$503)/COUNTA(A$4:A$503) -> 776.40004 | BI12: =SUM(S$4:S$503)/COUNTA(A$4:A$503) -> 806.40012 | BJ12: =SUM(T$4:T$503)/COUNTA(A$4:A$503) -> 826.1999 | BK12: =SUM(U$4:U$503)/COUNTA(A$4:A$503) -> 844.8002 | BL12: =SUM(V$4:V$503)/COUNTA(A$4:A$503) -> 865.7998 | BM12: =SUM(W$4:W$503)/COUNTA(A$4:A$503) -> 888.59982 | BN12: =SUM(X$4:X$503)/COUNTA(A$4:A$503) -> 918.60034 | BO12: . | BP12: =IF(Z12>=BB12,0,IFERROR(BB12+(SUMPRODUCT((Z$4:Z$503>=BB$4:BB$503)*(Z$4:Z$503-BB$4:BB$503))/MAX(1,COUNTIF(Z$4:Z$503,"<"&BB12+0.01))),BB12)) -> 0 | BQ12: =IF(AA12>=BC12,0,IFERROR(BC12+SUMPRODUCT((AA$4:AA$503>=BC$4:BC$503)*(AA$4:AA$503-BC$4:BC$503))/MAX(1,COUNTIF(AA$4:AA$503,"<"&BC12+0.01)),BC12)) -> 2238.4659 | BR12: =IF(AB12>=BD12,0,IFERROR(BD12+SUMPRODUCT((AB$4:AB$503>=BD$4:BD$503)*(AB$4:AB$503-BD$4:BD$503))/MAX(1,COUNTIF(AB$4:AB$503,"<"&BD12+0.01)),BD12)) -> 3335.2938 | BS12: =IF(AC12>=BE12,0,IFERROR(BE12+SUMPRODUCT((AC$4:AC$503>=BE$4:BE$503)*(AC$4:AC$503-BE$4:BE$503))/MAX(1,COUNTIF(AC$4:AC$503,"<"&BE12+0.01)),BE12)) -> 6188.7335 | BT12: =IF(AD12>=BF12,0,IFERROR(BF12+SUMPRODUCT((AD$4:AD$503>=BF$4:BF$503)*(AD$4:AD$503-BF$4:BF$503))/MAX(1,COUNTIF(AD$4:AD$503,"<"&BF12+0.01)),BF12)) -> 11354.354 | BU12: =IF(AE12>=BG12,0,IFERROR(BG12+SUMPRODUCT((AE$4:AE$503>=BG$4:BG$503)*(AE$4:AE$503-BG$4:BG$503))/MAX(1,COUNTIF(AE$4:AE$503,"<"&BG12+0.01)),BG12)) -> 7704.8592 | BV12: =IF(AF12>=BH12,0,IFERROR(BH12+SUMPRODUCT((AF$4:AF$503>=BH$4:BH$503)*(AF$4:AF$503-BH$4:BH$503))/MAX(1,COUNTIF(AF$4:AF$503,"<"&BH12+0.01)),BH12)) -> 0 | BW12: =IF(AG12>=BI12,0,IFERROR(BI12+SUMPRODUCT((AG$4:AG$503>=BI$4:BI$503)*(AG$4:AG$503-BI$4:BI$503))/MAX(1,COUNTIF(AG$4:AG$503,"<"&BI12+0.01)),BI12)) -> 9142.1587 | BX12: =IF(AH12>=BJ12,0,IFERROR(BJ12+SUMPRODUCT((AH$4:AH$503>=BJ$4:BJ$503)*(AH$4:AH$503-BJ$4:BJ$503))/MAX(1,COUNTIF(AH$4:AH$503,"<"&BJ12+0.01)),BJ12)) -> 5621.5026 | ... CB12: =IF(AL12>=BN12,0,IFERROR(BN12+SUMPRODUCT((AL$4:AL$503>=BN$4:BN$503)*(AL$4:AL$503-BN$4:BN$503))/MAX(1,COUNTIF(AL$4:AL$503,"<"&BN12+0.01)),BN12)) -> 3597.2615 | CC12: =IF(AO12="🟢","VERDE",IF(AO12="🟡","AMARELO",IF(AO12="🟠","VERMELHO",IF(AO12="🔴","VERMELHO","ROXO")))) -> VERMELHO | CD12: 🌎 REGIÕES | CE12: SEM REDE
A13: 41887017000190 | B13: CHOKOLATEN ALIMENTOS INDUSTRIA E COMERCI | C13: SUL | D13: HEMANUELE DITZEL (MANU) | E13: SC | F13: =IFERROR(VLOOKUP(C13,$AS$3:$AT$10,2,FALSE()),IFERROR(VLOOKUP(C13,$AS$15:$AT$22,2,FALSE()),"")) -> 132 | G13: =IFERROR(VLOOKUP(C13,$AS$3:$AX$10,6,FALSE()),IFERROR(VLOOKUP(C13,$AS$15:$AX$22,6,FALSE()),"")) -> 0.46819018 | H13: =IFERROR(VLOOKUP(C13,$AS$3:$AY$10,7,FALSE()),IFERROR(VLOOKUP(C13,$AS$15:$AY$22,7,FALSE()),"")) -> 🟡 AMARELO | I13: =IFERROR(VLOOKUP(C13,$AS$3:$AZ$10,8,FALSE()),IFERROR(VLOOKUP(C13,$AS$15:$AZ$22,8,FALSE()),"")) -> Sell Out | K13: SUL | L13: 57545.51 | M13: 4043.9 | N13: 4225.72 | O13: 4327.55 | P13: 4440.28 | Q13: 4585.75 | R13: 4705.76 | S13: 4887.59 | T13: 5007.59 | U13: 5120.33 | V13: 5247.61 | W13: 5385.8 | X13: 5567.63 | Y13: . | Z13: =SUM(AA13:AL13) -> 35439.82 | AG13: 3467.83 | AI13: 12654.14 | AJ13: 9729.07 | AK13: 9588.78 | AM13: . | AN13: =IF(L13=0,0,Z13/L13) -> 0.61585726 | AO13: =IF(AN13="","",IF(AN13>=0.9,"🟢",IF(AN13>=0.7,"🟡",IF(AN13>=0.5,"🟠","🔴")))) -> 🟠 | AP13: =IF(L13=0,0,L13-Z13) -> 22105.69 | AQ13: =IF(AP13=0,"",RANK(AP13,AP$4:AP$503,0)) -> 17 | AR13: . | AS13: 🌎 SINALEIRO REGIÕES | BA13: . | BB13: =SUM(L$4:L$503)/COUNTA(A$4:A$503) -> 9494.3999 | BC13: =SUM(M$4:M$503)/COUNTA(A$4:A$503) -> 667.20008 | BD13: =SUM(N$4:N$503)/COUNTA(A$4:A$503) -> 697.19996 | BE13: =SUM(O$4:O$503)/COUNTA(A$4:A$503) -> 713.9999 | BF13: =SUM(P$4:P$503)/COUNTA(A$4:A$503) -> 732.59984 | BG13: =SUM(Q$4:Q$503)/COUNTA(A$4:A$503) -> 756.59992 | BH13: =SUM(R$4:R$503)/COUNTA(A$4:A$503) -> 776.40004 | BI13: =SUM(S$4:S$503)/COUNTA(A$4:A$503) -> 806.40012 | BJ13: =SUM(T$4:T$503)/COUNTA(A$4:A$503) -> 826.1999 | BK13: =SUM(U$4:U$503)/COUNTA(A$4:A$503) -> 844.8002 | BL13: =SUM(V$4:V$503)/COUNTA(A$4:A$503) -> 865.7998 | BM13: =SUM(W$4:W$503)/COUNTA(A$4:A$503) -> 888.59982 | BN13: =SUM(X$4:X$503)/COUNTA(A$4:A$503) -> 918.60034 | BO13: . | BP13: =IF(Z13>=BB13,0,IFERROR(BB13+(SUMPRODUCT((Z$4:Z$503>=BB$4:BB$503)*(Z$4:Z$503-BB$4:BB$503))/MAX(1,COUNTIF(Z$4:Z$503,"<"&BB13+0.01))),BB13)) -> 0 | BQ13: =IF(AA13>=BC13,0,IFERROR(BC13+SUMPRODUCT((AA$4:AA$503>=BC$4:BC$503)*(AA$4:AA$503-BC$4:BC$503))/MAX(1,COUNTIF(AA$4:AA$503,"<"&BC13+0.01)),BC13)) -> 2238.4659 | BR13: =IF(AB13>=BD13,0,IFERROR(BD13+SUMPRODUCT((AB$4:AB$503>=BD$4:BD$503)*(AB$4:AB$503-BD$4:BD$503))/MAX(1,COUNTIF(AB$4:AB$503,"<"&BD13+0.01)),BD13)) -> 3335.2938 | BS13: =IF(AC13>=BE13,0,IFERROR(BE13+SUMPRODUCT((AC$4:AC$503>=BE$4:BE$503)*(AC$4:AC$503-BE$4:BE$503))/MAX(1,COUNTIF(AC$4:AC$503,"<"&BE13+0.01)),BE13)) -> 6188.7335 | BT13: =IF(AD13>=BF13,0,IFERROR(BF13+SUMPRODUCT((AD$4:AD$503>=BF$4:BF$503)*(AD$4:AD$503-BF$4:BF$503))/MAX(1,COUNTIF(AD$4:AD$503,"<"&BF13+0.01)),BF13)) -> 11354.354 | BU13: =IF(AE13>=BG13,0,IFERROR(BG13+SUMPRODUCT((AE$4:AE$503>=BG$4:BG$503)*(AE$4:AE$503-BG$4:BG$503))/MAX(1,COUNTIF(AE$4:AE$503,"<"&BG13+0.01)),BG13)) -> 7704.8592 | BV13: =IF(AF13>=BH13,0,IFERROR(BH13+SUMPRODUCT((AF$4:AF$503>=BH$4:BH$503)*(AF$4:AF$503-BH$4:BH$503))/MAX(1,COUNTIF(AF$4:AF$503,"<"&BH13+0.01)),BH13)) -> 9942.6504 | BW13: =IF(AG13>=BI13,0,IFERROR(BI13+SUMPRODUCT((AG$4:AG$503>=BI$4:BI$503)*(AG$4:AG$503-BI$4:BI$503))/MAX(1,COUNTIF(AG$4:AG$503,"<"&BI13+0.01)),BI13)) -> 0 | BX13: =IF(AH13>=BJ13,0,IFERROR(BJ13+SUMPRODUCT((AH$4:AH$503>=BJ$4:BJ$503)*(AH$4:AH$503-BJ$4:BJ$503))/MAX(1,COUNTIF(AH$4:AH$503,"<"&BJ13+0.01)),BJ13)) -> 5621.5026 | ... CB13: =IF(AL13>=BN13,0,IFERROR(BN13+SUMPRODUCT((AL$4:AL$503>=BN$4:BN$503)*(AL$4:AL$503-BN$4:BN$503))/MAX(1,COUNTIF(AL$4:AL$503,"<"&BN13+0.01)),BN13)) -> 3597.2615 | CC13: =IF(AO13="🟢","VERDE",IF(AO13="🟡","AMARELO",IF(AO13="🟠","VERMELHO",IF(AO13="🔴","VERMELHO","ROXO")))) -> VERMELHO | CD13: 🌎 REGIÕES | CE13: SEM REDE
A14: 31545180000110 | B14: NATURALIS PRODUTOS NATURAIS LTDA - EPP | C14: SUL | D14: HEMANUELE DITZEL (MANU) | E14: SC | F14: =IFERROR(VLOOKUP(C14,$AS$3:$AT$10,2,FALSE()),IFERROR(VLOOKUP(C14,$AS$15:$AT$22,2,FALSE()),"")) -> 132 | G14: =IFERROR(VLOOKUP(C14,$AS$3:$AX$10,6,FALSE()),IFERROR(VLOOKUP(C14,$AS$15:$AX$22,6,FALSE()),"")) -> 0.46819018 | H14: =IFERROR(VLOOKUP(C14,$AS$3:$AY$10,7,FALSE()),IFERROR(VLOOKUP(C14,$AS$15:$AY$22,7,FALSE()),"")) -> 🟡 AMARELO | I14: =IFERROR(VLOOKUP(C14,$AS$3:$AZ$10,8,FALSE()),IFERROR(VLOOKUP(C14,$AS$15:$AZ$22,8,FALSE()),"")) -> Sell Out | K14: SUL | L14: 55925.26 | M14: 3930.04 | N14: 4106.75 | O14: 4205.7 | P14: 4315.26 | Q14: 4456.63 | R14: 4573.26 | S14: 4749.97 | T14: 4866.6 | U14: 4976.16 | V14: 5099.86 | W14: 5234.16 | X14: 5410.87 | Y14: . | Z14: =SUM(AA14:AL14) -> 22963.56 | AB14: 1512 | AD14: 4899.73 | AE14: 2635.53 | AH14: 5094 | AI14: 1188.55 | AJ14: 3502.75 | AL14: 4131 | AM14: . | AN14: =IF(L14=0,0,Z14/L14) -> 0.41061159 | AO14: =IF(AN14="","",IF(AN14>=0.9,"🟢",IF(AN14>=0.7,"🟡",IF(AN14>=0.5,"🟠","🔴")))) -> 🔴 | AP14: =IF(L14=0,0,L14-Z14) -> 32961.7 | AQ14: =IF(AP14=0,"",RANK(AP14,AP$4:AP$503,0)) -> 10 | AR14: . | AS14: GRUPO | AT14: CLIENTES | AU14: C/ VENDA | AV14: META R$ | AW14: FAT. REAL R$ | AX14: SINALEIRO % | AY14: COR | AZ14: AÇÃO | BA14: . | BB14: =SUM(L$4:L$503)/COUNTA(A$4:A$503) -> 9494.3999 | BC14: =SUM(M$4:M$503)/COUNTA(A$4:A$503) -> 667.20008 | BD14: =SUM(N$4:N$503)/COUNTA(A$4:A$503) -> 697.19996 | BE14: =SUM(O$4:O$503)/COUNTA(A$4:A$503) -> 713.9999 | BF14: =SUM(P$4:P$503)/COUNTA(A$4:A$503) -> 732.59984 | BG14: =SUM(Q$4:Q$503)/COUNTA(A$4:A$503) -> 756.59992 | BH14: =SUM(R$4:R$503)/COUNTA(A$4:A$503) -> 776.40004 | BI14: =SUM(S$4:S$503)/COUNTA(A$4:A$503) -> 806.40012 | BJ14: =SUM(T$4:T$503)/COUNTA(A$4:A$503) -> 826.1999 | BK14: =SUM(U$4:U$503)/COUNTA(A$4:A$503) -> 844.8002 | BL14: =SUM(V$4:V$503)/COUNTA(A$4:A$503) -> 865.7998 | BM14: =SUM(W$4:W$503)/COUNTA(A$4:A$503) -> 888.59982 | BN14: =SUM(X$4:X$503)/COUNTA(A$4:A$503) -> 918.60034 | BO14: . | BP14: =IF(Z14>=BB14,0,IFERROR(BB14+(SUMPRODUCT((Z$4:Z$503>=BB$4:BB$503)*(Z$4:Z$503-BB$4:BB$503))/MAX(1,COUNTIF(Z$4:Z$503,"<"&BB14+0.01))),BB14)) -> 0 | BQ14: =IF(AA14>=BC14,0,IFERROR(BC14+SUMPRODUCT((AA$4:AA$503>=BC$4:BC$503)*(AA$4:AA$503-BC$4:BC$503))/MAX(1,COUNTIF(AA$4:AA$503,"<"&BC14+0.01)),BC14)) -> 2238.4659 | BR14: =IF(AB14>=BD14,0,IFERROR(BD14+SUMPRODUCT((AB$4:AB$503>=BD$4:BD$503)*(AB$4:AB$503-BD$4:BD$503))/MAX(1,COUNTIF(AB$4:AB$503,"<"&BD14+0.01)),BD14)) -> 0 | BS14: =IF(AC14>=BE14,0,IFERROR(BE14+SUMPRODUCT((AC$4:AC$503>=BE$4:BE$503)*(AC$4:AC$503-BE$4:BE$503))/MAX(1,COUNTIF(AC$4:AC$503,"<"&BE14+0.01)),BE14)) -> 6188.7335 | BT14: =IF(AD14>=BF14,0,IFERROR(BF14+SUMPRODUCT((AD$4:AD$503>=BF$4:BF$503)*(AD$4:AD$503-BF$4:BF$503))/MAX(1,COUNTIF(AD$4:AD$503,"<"&BF14+0.01)),BF14)) -> 0 | BU14: =IF(AE14>=BG14,0,IFERROR(BG14+SUMPRODUCT((AE$4:AE$503>=BG$4:BG$503)*(AE$4:AE$503-BG$4:BG$503))/MAX(1,COUNTIF(AE$4:AE$503,"<"&BG14+0.01)),BG14)) -> 0 | BV14: =IF(AF14>=BH14,0,IFERROR(BH14+SUMPRODUCT((AF$4:AF$503>=BH$4:BH$503)*(AF$4:AF$503-BH$4:BH$503))/MAX(1,COUNTIF(AF$4:AF$503,"<"&BH14+0.01)),BH14)) -> 9942.6504 | BW14: =IF(AG14>=BI14,0,IFERROR(BI14+SUMPRODUCT((AG$4:AG$503>=BI$4:BI$503)*(AG$4:AG$503-BI$4:BI$503))/MAX(1,COUNTIF(AG$4:AG$503,"<"&BI14+0.01)),BI14)) -> 9142.1587 | BX14: =IF(AH14>=BJ14,0,IFERROR(BJ14+SUMPRODUCT((AH$4:AH$503>=BJ$4:BJ$503)*(AH$4:AH$503-BJ$4:BJ$503))/MAX(1,COUNTIF(AH$4:AH$503,"<"&BJ14+0.01)),BJ14)) -> 0 | ... CB14: =IF(AL14>=BN14,0,IFERROR(BN14+SUMPRODUCT((AL$4:AL$503>=BN$4:BN$503)*(AL$4:AL$503-BN$4:BN$503))/MAX(1,COUNTIF(AL$4:AL$503,"<"&BN14+0.01)),BN14)) -> 0 | CC14: =IF(AO14="🟢","VERDE",IF(AO14="🟡","AMARELO",IF(AO14="🟠","VERMELHO",IF(AO14="🔴","VERMELHO","ROXO")))) -> VERMELHO | CD14: 🌎 REGIÕES | CE14: SEM REDE
A15: 34901637000170 | B15: MERCANTIL SALES LTDA - ME | C15: NORTE + MA | D15: LARISSA PADILHA | E15: PA | F15: =IFERROR(VLOOKUP(C15,$AS$3:$AT$10,2,FALSE()),IFERROR(VLOOKUP(C15,$AS$15:$AT$22,2,FALSE()),"")) -> 10 | G15: =IFERROR(VLOOKUP(C15,$AS$3:$AX$10,6,FALSE()),IFERROR(VLOOKUP(C15,$AS$15:$AX$22,6,FALSE()),"")) -> 0.45643525 | H15: =IFERROR(VLOOKUP(C15,$AS$3:$AY$10,7,FALSE()),IFERROR(VLOOKUP(C15,$AS$15:$AY$22,7,FALSE()),"")) -> 🟡 AMARELO | I15: =IFERROR(VLOOKUP(C15,$AS$3:$AZ$10,8,FALSE()),IFERROR(VLOOKUP(C15,$AS$15:$AZ$22,8,FALSE()),"")) -> Sell Out | K15: NORTE + MA | L15: 54236.21 | M15: 3811.34 | N15: 3982.72 | O15: 4078.68 | P15: 4184.94 | Q15: 4322.03 | R15: 4435.14 | S15: 4606.51 | T15: 4719.62 | U15: 4825.87 | V15: 4945.83 | W15: 5076.08 | X15: 5247.45 | Y15: . | Z15: =SUM(AA15:AL15) -> 26817.41 | AA15: 5364.79 | AC15: 4625.46 | AE15: 2713 | AF15: 4506.85 | AH15: 3280.39 | AI15: 3792.14 | AK15: 2534.78 | AM15: . | AN15: =IF(L15=0,0,Z15/L15) -> 0.49445583 | AO15: =IF(AN15="","",IF(AN15>=0.9,"🟢",IF(AN15>=0.7,"🟡",IF(AN15>=0.5,"🟠","🔴")))) -> 🔴 | AP15: =IF(L15=0,0,L15-Z15) -> 27418.8 | AQ15: =IF(AP15=0,"",RANK(AP15,AP$4:AP$503,0)) -> 11 | AR15: . | AS15: SUL | AT15: =COUNTIF(C$4:C$503,AS15) -> 132 | AU15: =COUNTIFS(C$4:C$503,AS15,Z$4:Z$503,">0") -> 131 | AV15: =SUMIF(C$4:C$503,AS15,L$4:L$503) -> 1152066.6 | AW15: =SUMIF(C$4:C$503,AS15,Z$4:Z$503) -> 539386.25 | AX15: =IF(AV15=0,0,AW15/AV15) -> 0.46819018 | AY15: =IF(AX15>=0.6,"🟢 VERDE",IF(AX15>=0.4,"🟡 AMARELO",IF(AX15>=0.01,"🔴 VERMELHO","🟣 ROXO"))) -> 🟡 AMARELO | AZ15: =IF(AX15>=0.6,"JBP",IF(AX15>=0.4,"Sell Out",IF(AX15>=0.1,"Positivação + Expandir",IF(AX15>=0.01,"Ativar + Prospectar","Mapear + Prospectar")))) -> Sell Out | BA15: . | BB15: =SUM(L$4:L$503)/COUNTA(A$4:A$503) -> 9494.3999 | BC15: =SUM(M$4:M$503)/COUNTA(A$4:A$503) -> 667.20008 | BD15: =SUM(N$4:N$503)/COUNTA(A$4:A$503) -> 697.19996 | BE15: =SUM(O$4:O$503)/COUNTA(A$4:A$503) -> 713.9999 | BF15: =SUM(P$4:P$503)/COUNTA(A$4:A$503) -> 732.59984 | BG15: =SUM(Q$4:Q$503)/COUNTA(A$4:A$503) -> 756.59992 | BH15: =SUM(R$4:R$503)/COUNTA(A$4:A$503) -> 776.40004 | BI15: =SUM(S$4:S$503)/COUNTA(A$4:A$503) -> 806.40012 | BJ15: =SUM(T$4:T$503)/COUNTA(A$4:A$503) -> 826.1999 | BK15: =SUM(U$4:U$503)/COUNTA(A$4:A$503) -> 844.8002 | BL15: =SUM(V$4:V$503)/COUNTA(A$4:A$503) -> 865.7998 | BM15: =SUM(W$4:W$503)/COUNTA(A$4:A$503) -> 888.59982 | BN15: =SUM(X$4:X$503)/COUNTA(A$4:A$503) -> 918.60034 | BO15: . | BP15: =IF(Z15>=BB15,0,IFERROR(BB15+(SUMPRODUCT((Z$4:Z$503>=BB$4:BB$503)*(Z$4:Z$503-BB$4:BB$503))/MAX(1,COUNTIF(Z$4:Z$503,"<"&BB15+0.01))),BB15)) -> 0 | BQ15: =IF(AA15>=BC15,0,IFERROR(BC15+SUMPRODUCT((AA$4:AA$503>=BC$4:BC$503)*(AA$4:AA$503-BC$4:BC$503))/MAX(1,COUNTIF(AA$4:AA$503,"<"&BC15+0.01)),BC15)) -> 0 | BR15: =IF(AB15>=BD15,0,IFERROR(BD15+SUMPRODUCT((AB$4:AB$503>=BD$4:BD$503)*(AB$4:AB$503-BD$4:BD$503))/MAX(1,COUNTIF(AB$4:AB$503,"<"&BD15+0.01)),BD15)) -> 3335.2938 | BS15: =IF(AC15>=BE15,0,IFERROR(BE15+SUMPRODUCT((AC$4:AC$503>=BE$4:BE$503)*(AC$4:AC$503-BE$4:BE$503))/MAX(1,COUNTIF(AC$4:AC$503,"<"&BE15+0.01)),BE15)) -> 0 | BT15: =IF(AD15>=BF15,0,IFERROR(BF15+SUMPRODUCT((AD$4:AD$503>=BF$4:BF$503)*(AD$4:AD$503-BF$4:BF$503))/MAX(1,COUNTIF(AD$4:AD$503,"<"&BF15+0.01)),BF15)) -> 11354.354 | BU15: =IF(AE15>=BG15,0,IFERROR(BG15+SUMPRODUCT((AE$4:AE$503>=BG$4:BG$503)*(AE$4:AE$503-BG$4:BG$503))/MAX(1,COUNTIF(AE$4:AE$503,"<"&BG15+0.01)),BG15)) -> 0 | BV15: =IF(AF15>=BH15,0,IFERROR(BH15+SUMPRODUCT((AF$4:AF$503>=BH$4:BH$503)*(AF$4:AF$503-BH$4:BH$503))/MAX(1,COUNTIF(AF$4:AF$503,"<"&BH15+0.01)),BH15)) -> 0 | BW15: =IF(AG15>=BI15,0,IFERROR(BI15+SUMPRODUCT((AG$4:AG$503>=BI$4:BI$503)*(AG$4:AG$503-BI$4:BI$503))/MAX(1,COUNTIF(AG$4:AG$503,"<"&BI15+0.01)),BI15)) -> 9142.1587 | BX15: =IF(AH15>=BJ15,0,IFERROR(BJ15+SUMPRODUCT((AH$4:AH$503>=BJ$4:BJ$503)*(AH$4:AH$503-BJ$4:BJ$503))/MAX(1,COUNTIF(AH$4:AH$503,"<"&BJ15+0.01)),BJ15)) -> 0 | ... CB15: =IF(AL15>=BN15,0,IFERROR(BN15+SUMPRODUCT((AL$4:AL$503>=BN$4:BN$503)*(AL$4:AL$503-BN$4:BN$503))/MAX(1,COUNTIF(AL$4:AL$503,"<"&BN15+0.01)),BN15)) -> 3597.2615 | CC15: =IF(AO15="🟢","VERDE",IF(AO15="🟡","AMARELO",IF(AO15="🟠","VERMELHO",IF(AO15="🔴","VERMELHO","ROXO")))) -> VERMELHO | CD15: 🌎 REGIÕES | CE15: SEM REDE
A16: 14133092000192 | B16: BESCO INDUSTRIAL DE ALIMENTOS LTDA - ME | C16: SUL | D16: HEMANUELE DITZEL (MANU) | E16: SC | F16: =IFERROR(VLOOKUP(C16,$AS$3:$AT$10,2,FALSE()),IFERROR(VLOOKUP(C16,$AS$15:$AT$22,2,FALSE()),"")) -> 132 | G16: =IFERROR(VLOOKUP(C16,$AS$3:$AX$10,6,FALSE()),IFERROR(VLOOKUP(C16,$AS$15:$AX$22,6,FALSE()),"")) -> 0.46819018 | H16: =IFERROR(VLOOKUP(C16,$AS$3:$AY$10,7,FALSE()),IFERROR(VLOOKUP(C16,$AS$15:$AY$22,7,FALSE()),"")) -> 🟡 AMARELO | I16: =IFERROR(VLOOKUP(C16,$AS$3:$AZ$10,8,FALSE()),IFERROR(VLOOKUP(C16,$AS$15:$AZ$22,8,FALSE()),"")) -> Sell Out | K16: SUL | L16: 53677.08 | M16: 3772.05 | N16: 3941.66 | O16: 4036.64 | P16: 4141.79 | Q16: 4277.48 | R16: 4389.42 | S16: 4559.02 | T16: 4670.96 | U16: 4776.12 | V16: 4894.84 | W16: 5023.75 | X16: 5193.35 | Y16: . | Z16: =SUM(AA16:AL16) -> 26818.32 | AE16: 8607.14 | AF16: 12740.35 | AG16: 5470.83 | AM16: . | AN16: =IF(L16=0,0,Z16/L16) -> 0.4996233 | AO16: =IF(AN16="","",IF(AN16>=0.9,"🟢",IF(AN16>=0.7,"🟡",IF(AN16>=0.5,"🟠","🔴")))) -> 🔴 | AP16: =IF(L16=0,0,L16-Z16) -> 26858.76 | AQ16: =IF(AP16=0,"",RANK(AP16,AP$4:AP$503,0)) -> 13 | AR16: . | AS16: SP CAPITAL | AT16: =COUNTIF(C$4:C$503,AS16) -> 29 | AU16: =COUNTIFS(C$4:C$503,AS16,Z$4:Z$503,">0") -> 29 | AV16: =SUMIF(C$4:C$503,AS16,L$4:L$503) -> 239355.48 | AW16: =SUMIF(C$4:C$503,AS16,Z$4:Z$503) -> 101928.35 | AX16: =IF(AV16=0,0,AW16/AV16) -> 0.42584507 | AY16: =IF(AX16>=0.6,"🟢 VERDE",IF(AX16>=0.4,"🟡 AMARELO",IF(AX16>=0.01,"🔴 VERMELHO","🟣 ROXO"))) -> 🟡 AMARELO | AZ16: =IF(AX16>=0.6,"JBP",IF(AX16>=0.4,"Sell Out",IF(AX16>=0.1,"Positivação + Expandir",IF(AX16>=0.01,"Ativar + Prospectar","Mapear + Prospectar")))) -> Sell Out | BA16: . | BB16: =SUM(L$4:L$503)/COUNTA(A$4:A$503) -> 9494.3999 | BC16: =SUM(M$4:M$503)/COUNTA(A$4:A$503) -> 667.20008 | BD16: =SUM(N$4:N$503)/COUNTA(A$4:A$503) -> 697.19996 | BE16: =SUM(O$4:O$503)/COUNTA(A$4:A$503) -> 713.9999 | BF16: =SUM(P$4:P$503)/COUNTA(A$4:A$503) -> 732.59984 | BG16: =SUM(Q$4:Q$503)/COUNTA(A$4:A$503) -> 756.59992 | BH16: =SUM(R$4:R$503)/COUNTA(A$4:A$503) -> 776.40004 | BI16: =SUM(S$4:S$503)/COUNTA(A$4:A$503) -> 806.40012 | BJ16: =SUM(T$4:T$503)/COUNTA(A$4:A$503) -> 826.1999 | BK16: =SUM(U$4:U$503)/COUNTA(A$4:A$503) -> 844.8002 | BL16: =SUM(V$4:V$503)/COUNTA(A$4:A$503) -> 865.7998 | BM16: =SUM(W$4:W$503)/COUNTA(A$4:A$503) -> 888.59982 | BN16: =SUM(X$4:X$503)/COUNTA(A$4:A$503) -> 918.60034 | BO16: . | BP16: =IF(Z16>=BB16,0,IFERROR(BB16+(SUMPRODUCT((Z$4:Z$503>=BB$4:BB$503)*(Z$4:Z$503-BB$4:BB$503))/MAX(1,COUNTIF(Z$4:Z$503,"<"&BB16+0.01))),BB16)) -> 0 | BQ16: =IF(AA16>=BC16,0,IFERROR(BC16+SUMPRODUCT((AA$4:AA$503>=BC$4:BC$503)*(AA$4:AA$503-BC$4:BC$503))/MAX(1,COUNTIF(AA$4:AA$503,"<"&BC16+0.01)),BC16)) -> 2238.4659 | BR16: =IF(AB16>=BD16,0,IFERROR(BD16+SUMPRODUCT((AB$4:AB$503>=BD$4:BD$503)*(AB$4:AB$503-BD$4:BD$503))/MAX(1,COUNTIF(AB$4:AB$503,"<"&BD16+0.01)),BD16)) -> 3335.2938 | BS16: =IF(AC16>=BE16,0,IFERROR(BE16+SUMPRODUCT((AC$4:AC$503>=BE$4:BE$503)*(AC$4:AC$503-BE$4:BE$503))/MAX(1,COUNTIF(AC$4:AC$503,"<"&BE16+0.01)),BE16)) -> 6188.7335 | BT16: =IF(AD16>=BF16,0,IFERROR(BF16+SUMPRODUCT((AD$4:AD$503>=BF$4:BF$503)*(AD$4:AD$503-BF$4:BF$503))/MAX(1,COUNTIF(AD$4:AD$503,"<"&BF16+0.01)),BF16)) -> 11354.354 | BU16: =IF(AE16>=BG16,0,IFERROR(BG16+SUMPRODUCT((AE$4:AE$503>=BG$4:BG$503)*(AE$4:AE$503-BG$4:BG$503))/MAX(1,COUNTIF(AE$4:AE$503,"<"&BG16+0.01)),BG16)) -> 0 | BV16: =IF(AF16>=BH16,0,IFERROR(BH16+SUMPRODUCT((AF$4:AF$503>=BH$4:BH$503)*(AF$4:AF$503-BH$4:BH$503))/MAX(1,COUNTIF(AF$4:AF$503,"<"&BH16+0.01)),BH16)) -> 0 | BW16: =IF(AG16>=BI16,0,IFERROR(BI16+SUMPRODUCT((AG$4:AG$503>=BI$4:BI$503)*(AG$4:AG$503-BI$4:BI$503))/MAX(1,COUNTIF(AG$4:AG$503,"<"&BI16+0.01)),BI16)) -> 0 | BX16: =IF(AH16>=BJ16,0,IFERROR(BJ16+SUMPRODUCT((AH$4:AH$503>=BJ$4:BJ$503)*(AH$4:AH$503-BJ$4:BJ$503))/MAX(1,COUNTIF(AH$4:AH$503,"<"&BJ16+0.01)),BJ16)) -> 5621.5026 | ... CB16: =IF(AL16>=BN16,0,IFERROR(BN16+SUMPRODUCT((AL$4:AL$503>=BN$4:BN$503)*(AL$4:AL$503-BN$4:BN$503))/MAX(1,COUNTIF(AL$4:AL$503,"<"&BN16+0.01)),BN16)) -> 3597.2615 | CC16: =IF(AO16="🟢","VERDE",IF(AO16="🟡","AMARELO",IF(AO16="🟠","VERMELHO",IF(AO16="🔴","VERMELHO","ROXO")))) -> VERMELHO | CD16: 🌎 REGIÕES | CE16: SEM REDE
A17: 80230774000148 | B17: COOP. CENTRAL CREDITO, POUPANCA E INVEST | C17: SUL | D17: HEMANUELE DITZEL (MANU) | E17: PR | F17: =IFERROR(VLOOKUP(C17,$AS$3:$AT$10,2,FALSE()),IFERROR(VLOOKUP(C17,$AS$15:$AT$22,2,FALSE()),"")) -> 132 | G17: =IFERROR(VLOOKUP(C17,$AS$3:$AX$10,6,FALSE()),IFERROR(VLOOKUP(C17,$AS$15:$AX$22,6,FALSE()),"")) -> 0.46819018 | H17: =IFERROR(VLOOKUP(C17,$AS$3:$AY$10,7,FALSE()),IFERROR(VLOOKUP(C17,$AS$15:$AY$22,7,FALSE()),"")) -> 🟡 AMARELO | I17: =IFERROR(VLOOKUP(C17,$AS$3:$AZ$10,8,FALSE()),IFERROR(VLOOKUP(C17,$AS$15:$AZ$22,8,FALSE()),"")) -> Sell Out | K17: SUL | L17: 45011.85 | M17: 3163.12 | N17: 3305.34 | O17: 3384.99 | P17: 3473.17 | Q17: 3586.95 | R17: 3680.82 | S17: 3823.05 | T17: 3916.92 | U17: 4005.1 | V17: 4104.66 | W17: 4212.75 | X17: 4354.98 | Y17: . | Z17: =SUM(AA17:AL17) -> 18101.56 | AB17: 2831.96 | AD17: 2297.2 | AE17: 2297.2 | AG17: 2001.6 | AH17: 2001.6 | AI17: 3336 | AJ17: 3336 | AM17: . | AN17: =IF(L17=0,0,Z17/L17) -> 0.40215099 | AO17: =IF(AN17="","",IF(AN17>=0.9,"🟢",IF(AN17>=0.7,"🟡",IF(AN17>=0.5,"🟠","🔴")))) -> 🔴 | AP17: =IF(L17=0,0,L17-Z17) -> 26910.29 | AQ17: =IF(AP17=0,"",RANK(AP17,AP$4:AP$503,0)) -> 12 | AR17: . | AS17: SP INTERIOR | AT17: =COUNTIF(C$4:C$503,AS17) -> 42 | AU17: =COUNTIFS(C$4:C$503,AS17,Z$4:Z$503,">0") -> 42 | AV17: =SUMIF(C$4:C$503,AS17,L$4:L$503) -> 438148.58 | AW17: =SUMIF(C$4:C$503,AS17,Z$4:Z$503) -> 186157.1 | AX17: =IF(AV17=0,0,AW17/AV17) -> 0.42487208 | AY17: =IF(AX17>=0.6,"🟢 VERDE",IF(AX17>=0.4,"🟡 AMARELO",IF(AX17>=0.01,"🔴 VERMELHO","🟣 ROXO"))) -> 🟡 AMARELO | AZ17: =IF(AX17>=0.6,"JBP",IF(AX17>=0.4,"Sell Out",IF(AX17>=0.1,"Positivação + Expandir",IF(AX17>=0.01,"Ativar + Prospectar","Mapear + Prospectar")))) -> Sell Out | BA17: . | BB17: =SUM(L$4:L$503)/COUNTA(A$4:A$503) -> 9494.3999 | BC17: =SUM(M$4:M$503)/COUNTA(A$4:A$503) -> 667.20008 | BD17: =SUM(N$4:N$503)/COUNTA(A$4:A$503) -> 697.19996 | BE17: =SUM(O$4:O$503)/COUNTA(A$4:A$503) -> 713.9999 | BF17: =SUM(P$4:P$503)/COUNTA(A$4:A$503) -> 732.59984 | BG17: =SUM(Q$4:Q$503)/COUNTA(A$4:A$503) -> 756.59992 | BH17: =SUM(R$4:R$503)/COUNTA(A$4:A$503) -> 776.40004 | BI17: =SUM(S$4:S$503)/COUNTA(A$4:A$503) -> 806.40012 | BJ17: =SUM(T$4:T$503)/COUNTA(A$4:A$503) -> 826.1999 | BK17: =SUM(U$4:U$503)/COUNTA(A$4:A$503) -> 844.8002 | BL17: =SUM(V$4:V$503)/COUNTA(A$4:A$503) -> 865.7998 | BM17: =SUM(W$4:W$503)/COUNTA(A$4:A$503) -> 888.59982 | BN17: =SUM(X$4:X$503)/COUNTA(A$4:A$503) -> 918.60034 | BO17: . | BP17: =IF(Z17>=BB17,0,IFERROR(BB17+(SUMPRODUCT((Z$4:Z$503>=BB$4:BB$503)*(Z$4:Z$503-BB$4:BB$503))/MAX(1,COUNTIF(Z$4:Z$503,"<"&BB17+0.01))),BB17)) -> 0 | BQ17: =IF(AA17>=BC17,0,IFERROR(BC17+SUMPRODUCT((AA$4:AA$503>=BC$4:BC$503)*(AA$4:AA$503-BC$4:BC$503))/MAX(1,COUNTIF(AA$4:AA$503,"<"&BC17+0.01)),BC17)) -> 2238.4659 | BR17: =IF(AB17>=BD17,0,IFERROR(BD17+SUMPRODUCT((AB$4:AB$503>=BD$4:BD$503)*(AB$4:AB$503-BD$4:BD$503))/MAX(1,COUNTIF(AB$4:AB$503,"<"&BD17+0.01)),BD17)) -> 0 | BS17: =IF(AC17>=BE17,0,IFERROR(BE17+SUMPRODUCT((AC$4:AC$503>=BE$4:BE$503)*(AC$4:AC$503-BE$4:BE$503))/MAX(1,COUNTIF(AC$4:AC$503,"<"&BE17+0.01)),BE17)) -> 6188.7335 | BT17: =IF(AD17>=BF17,0,IFERROR(BF17+SUMPRODUCT((AD$4:AD$503>=BF$4:BF$503)*(AD$4:AD$503-BF$4:BF$503))/MAX(1,COUNTIF(AD$4:AD$503,"<"&BF17+0.01)),BF17)) -> 0 | BU17: =IF(AE17>=BG17,0,IFERROR(BG17+SUMPRODUCT((AE$4:AE$503>=BG$4:BG$503)*(AE$4:AE$503-BG$4:BG$503))/MAX(1,COUNTIF(AE$4:AE$503,"<"&BG17+0.01)),BG17)) -> 0 | BV17: =IF(AF17>=BH17,0,IFERROR(BH17+SUMPRODUCT((AF$4:AF$503>=BH$4:BH$503)*(AF$4:AF$503-BH$4:BH$503))/MAX(1,COUNTIF(AF$4:AF$503,"<"&BH17+0.01)),BH17)) -> 9942.6504 | BW17: =IF(AG17>=BI17,0,IFERROR(BI17+SUMPRODUCT((AG$4:AG$503>=BI$4:BI$503)*(AG$4:AG$503-BI$4:BI$503))/MAX(1,COUNTIF(AG$4:AG$503,"<"&BI17+0.01)),BI17)) -> 0 | BX17: =IF(AH17>=BJ17,0,IFERROR(BJ17+SUMPRODUCT((AH$4:AH$503>=BJ$4:BJ$503)*(AH$4:AH$503-BJ$4:BJ$503))/MAX(1,COUNTIF(AH$4:AH$503,"<"&BJ17+0.01)),BJ17)) -> 0 | ... CB17: =IF(AL17>=BN17,0,IFERROR(BN17+SUMPRODUCT((AL$4:AL$503>=BN$4:BN$503)*(AL$4:AL$503-BN$4:BN$503))/MAX(1,COUNTIF(AL$4:AL$503,"<"&BN17+0.01)),BN17)) -> 3597.2615 | CC17: =IF(AO17="🟢","VERDE",IF(AO17="🟡","AMARELO",IF(AO17="🟠","VERMELHO",IF(AO17="🔴","VERMELHO","ROXO")))) -> VERMELHO | CD17: 🌎 REGIÕES | CE17: SEM REDE
A18: 31599810000130 | B18: ALANA GARCIA MOREIRA SUARES DA SILVA - M | C18: SP INTERIOR | D18: LARISSA PADILHA | E18: SP | F18: =IFERROR(VLOOKUP(C18,$AS$3:$AT$10,2,FALSE()),IFERROR(VLOOKUP(C18,$AS$15:$AT$22,2,FALSE()),"")) -> 42 | G18: =IFERROR(VLOOKUP(C18,$AS$3:$AX$10,6,FALSE()),IFERROR(VLOOKUP(C18,$AS$15:$AX$22,6,FALSE()),"")) -> 0.42487208 | H18: =IFERROR(VLOOKUP(C18,$AS$3:$AY$10,7,FALSE()),IFERROR(VLOOKUP(C18,$AS$15:$AY$22,7,FALSE()),"")) -> 🟡 AMARELO | I18: =IFERROR(VLOOKUP(C18,$AS$3:$AZ$10,8,FALSE()),IFERROR(VLOOKUP(C18,$AS$15:$AZ$22,8,FALSE()),"")) -> Sell Out | K18: SP INTERIOR | L18: 43421.47 | M18: 3051.36 | N18: 3188.56 | O18: 3265.39 | P18: 3350.46 | Q18: 3460.22 | R18: 3550.77 | S18: 3687.97 | T18: 3778.52 | U18: 3863.59 | V18: 3959.63 | W18: 4063.9 | X18: 4201.1 | Y18: . | Z18: =SUM(AA18:AL18) -> 18175.27 | AE18: 1710.88 | AF18: 4099.8 | AG18: 7115.96 | AJ18: 3508.11 | AL18: 1740.52 | AM18: . | AN18: =IF(L18=0,0,Z18/L18) -> 0.41857795 | AO18: =IF(AN18="","",IF(AN18>=0.9,"🟢",IF(AN18>=0.7,"🟡",IF(AN18>=0.5,"🟠","🔴")))) -> 🔴 | AP18: =IF(L18=0,0,L18-Z18) -> 25246.2 | AQ18: =IF(AP18=0,"",RANK(AP18,AP$4:AP$503,0)) -> 14 | AR18: . | AS18: RJ + ES + MG | AT18: =COUNTIF(C$4:C$503,AS18) -> 49 | AU18: =COUNTIFS(C$4:C$503,AS18,Z$4:Z$503,">0") -> 46 | AV18: =SUMIF(C$4:C$503,AS18,L$4:L$503) -> 494616.14 | AW18: =SUMIF(C$4:C$503,AS18,Z$4:Z$503) -> 229484.62 | AX18: =IF(AV18=0,0,AW18/AV18) -> 0.46396509 | AY18: =IF(AX18>=0.6,"🟢 VERDE",IF(AX18>=0.4,"🟡 AMARELO",IF(AX18>=0.01,"🔴 VERMELHO","🟣 ROXO"))) -> 🟡 AMARELO | AZ18: =IF(AX18>=0.6,"JBP",IF(AX18>=0.4,"Sell Out",IF(AX18>=0.1,"Positivação + Expandir",IF(AX18>=0.01,"Ativar + Prospectar","Mapear + Prospectar")))) -> Sell Out | BA18: . | BB18: =SUM(L$4:L$503)/COUNTA(A$4:A$503) -> 9494.3999 | BC18: =SUM(M$4:M$503)/COUNTA(A$4:A$503) -> 667.20008 | BD18: =SUM(N$4:N$503)/COUNTA(A$4:A$503) -> 697.19996 | BE18: =SUM(O$4:O$503)/COUNTA(A$4:A$503) -> 713.9999 | BF18: =SUM(P$4:P$503)/COUNTA(A$4:A$503) -> 732.59984 | BG18: =SUM(Q$4:Q$503)/COUNTA(A$4:A$503) -> 756.59992 | BH18: =SUM(R$4:R$503)/COUNTA(A$4:A$503) -> 776.40004 | BI18: =SUM(S$4:S$503)/COUNTA(A$4:A$503) -> 806.40012 | BJ18: =SUM(T$4:T$503)/COUNTA(A$4:A$503) -> 826.1999 | BK18: =SUM(U$4:U$503)/COUNTA(A$4:A$503) -> 844.8002 | BL18: =SUM(V$4:V$503)/COUNTA(A$4:A$503) -> 865.7998 | BM18: =SUM(W$4:W$503)/COUNTA(A$4:A$503) -> 888.59982 | BN18: =SUM(X$4:X$503)/COUNTA(A$4:A$503) -> 918.60034 | BO18: . | BP18: =IF(Z18>=BB18,0,IFERROR(BB18+(SUMPRODUCT((Z$4:Z$503>=BB$4:BB$503)*(Z$4:Z$503-BB$4:BB$503))/MAX(1,COUNTIF(Z$4:Z$503,"<"&BB18+0.01))),BB18)) -> 0 | BQ18: =IF(AA18>=BC18,0,IFERROR(BC18+SUMPRODUCT((AA$4:AA$503>=BC$4:BC$503)*(AA$4:AA$503-BC$4:BC$503))/MAX(1,COUNTIF(AA$4:AA$503,"<"&BC18+0.01)),BC18)) -> 2238.4659 | BR18: =IF(AB18>=BD18,0,IFERROR(BD18+SUMPRODUCT((AB$4:AB$503>=BD$4:BD$503)*(AB$4:AB$503-BD$4:BD$503))/MAX(1,COUNTIF(AB$4:AB$503,"<"&BD18+0.01)),BD18)) -> 3335.2938 | BS18: =IF(AC18>=BE18,0,IFERROR(BE18+SUMPRODUCT((AC$4:AC$503>=BE$4:BE$503)*(AC$4:AC$503-BE$4:BE$503))/MAX(1,COUNTIF(AC$4:AC$503,"<"&BE18+0.01)),BE18)) -> 6188.7335 | BT18: =IF(AD18>=BF18,0,IFERROR(BF18+SUMPRODUCT((AD$4:AD$503>=BF$4:BF$503)*(AD$4:AD$503-BF$4:BF$503))/MAX(1,COUNTIF(AD$4:AD$503,"<"&BF18+0.01)),BF18)) -> 11354.354 | BU18: =IF(AE18>=BG18,0,IFERROR(BG18+SUMPRODUCT((AE$4:AE$503>=BG$4:BG$503)*(AE$4:AE$503-BG$4:BG$503))/MAX(1,COUNTIF(AE$4:AE$503,"<"&BG18+0.01)),BG18)) -> 0 | BV18: =IF(AF18>=BH18,0,IFERROR(BH18+SUMPRODUCT((AF$4:AF$503>=BH$4:BH$503)*(AF$4:AF$503-BH$4:BH$503))/MAX(1,COUNTIF(AF$4:AF$503,"<"&BH18+0.01)),BH18)) -> 0 | BW18: =IF(AG18>=BI18,0,IFERROR(BI18+SUMPRODUCT((AG$4:AG$503>=BI$4:BI$503)*(AG$4:AG$503-BI$4:BI$503))/MAX(1,COUNTIF(AG$4:AG$503,"<"&BI18+0.01)),BI18)) -> 0 | BX18: =IF(AH18>=BJ18,0,IFERROR(BJ18+SUMPRODUCT((AH$4:AH$503>=BJ$4:BJ$503)*(AH$4:AH$503-BJ$4:BJ$503))/MAX(1,COUNTIF(AH$4:AH$503,"<"&BJ18+0.01)),BJ18)) -> 5621.5026 | ... CB18: =IF(AL18>=BN18,0,IFERROR(BN18+SUMPRODUCT((AL$4:AL$503>=BN$4:BN$503)*(AL$4:AL$503-BN$4:BN$503))/MAX(1,COUNTIF(AL$4:AL$503,"<"&BN18+0.01)),BN18)) -> 0 | CC18: =IF(AO18="🟢","VERDE",IF(AO18="🟡","AMARELO",IF(AO18="🟠","VERMELHO",IF(AO18="🔴","VERMELHO","ROXO")))) -> VERMELHO | CD18: 🌎 REGIÕES | CE18: SEM REDE
A19: 05382867000253 | B19: SUPERMERCADO MERCOCENTRO LTDA | C19: SEM GRUPO | D19: HEMANUELE DITZEL (MANU) | E19: . | F19: =IFERROR(VLOOKUP(C19,$AS$3:$AT$10,2,FALSE()),IFERROR(VLOOKUP(C19,$AS$15:$AT$22,2,FALSE()),"")) -> 49 | G19: =IFERROR(VLOOKUP(C19,$AS$3:$AX$10,6,FALSE()),IFERROR(VLOOKUP(C19,$AS$15:$AX$22,6,FALSE()),"")) -> 0.43639135 | H19: =IFERROR(VLOOKUP(C19,$AS$3:$AY$10,7,FALSE()),IFERROR(VLOOKUP(C19,$AS$15:$AY$22,7,FALSE()),"")) -> 🟡 AMARELO | I19: =IFERROR(VLOOKUP(C19,$AS$3:$AZ$10,8,FALSE()),IFERROR(VLOOKUP(C19,$AS$15:$AZ$22,8,FALSE()),"")) -> Sell Out | K19: . | L19: 41090.39 | M19: 2887.54 | N19: 3017.38 | O19: 3090.09 | P19: 3170.59 | Q19: 3274.46 | R19: 3360.15 | S19: 3489.98 | T19: 3575.67 | U19: 3656.17 | V19: 3747.06 | W19: 3845.73 | X19: 3975.57 | Y19: . | Z19: =SUM(AA19:AL19) -> 19357.05 | AG19: 3314.24 | AH19: 1148.79 | AI19: 5698.98 | AJ19: 2464.38 | AK19: 2024.55 | AL19: 4706.11 | AM19: . | AN19: =IF(L19=0,0,Z19/L19) -> 0.4710846 | AO19: =IF(AN19="","",IF(AN19>=0.9,"🟢",IF(AN19>=0.7,"🟡",IF(AN19>=0.5,"🟠","🔴")))) -> 🔴 | AP19: =IF(L19=0,0,L19-Z19) -> 21733.34 | AQ19: =IF(AP19=0,"",RANK(AP19,AP$4:AP$503,0)) -> 19 | AR19: . | AS19: CENTRO OESTE | AT19: =COUNTIF(C$4:C$503,AS19) -> 33 | AU19: =COUNTIFS(C$4:C$503,AS19,Z$4:Z$503,">0") -> 33 | AV19: =SUMIF(C$4:C$503,AS19,L$4:L$503) -> 591578.79 | AW19: =SUMIF(C$4:C$503,AS19,Z$4:Z$503) -> 202020.63 | AX19: =IF(AV19=0,0,AW19/AV19) -> 0.34149404 | AY19: =IF(AX19>=0.6,"🟢 VERDE",IF(AX19>=0.4,"🟡 AMARELO",IF(AX19>=0.01,"🔴 VERMELHO","🟣 ROXO"))) -> 🔴 VERMELHO | AZ19: =IF(AX19>=0.6,"JBP",IF(AX19>=0.4,"Sell Out",IF(AX19>=0.1,"Positivação + Expandir",IF(AX19>=0.01,"Ativar + Prospectar","Mapear + Prospectar")))) -> Positivação + Expandir | BA19: . | BB19: =SUM(L$4:L$503)/COUNTA(A$4:A$503) -> 9494.3999 | BC19: =SUM(M$4:M$503)/COUNTA(A$4:A$503) -> 667.20008 | BD19: =SUM(N$4:N$503)/COUNTA(A$4:A$503) -> 697.19996 | BE19: =SUM(O$4:O$503)/COUNTA(A$4:A$503) -> 713.9999 | BF19: =SUM(P$4:P$503)/COUNTA(A$4:A$503) -> 732.59984 | BG19: =SUM(Q$4:Q$503)/COUNTA(A$4:A$503) -> 756.59992 | BH19: =SUM(R$4:R$503)/COUNTA(A$4:A$503) -> 776.40004 | BI19: =SUM(S$4:S$503)/COUNTA(A$4:A$503) -> 806.40012 | BJ19: =SUM(T$4:T$503)/COUNTA(A$4:A$503) -> 826.1999 | BK19: =SUM(U$4:U$503)/COUNTA(A$4:A$503) -> 844.8002 | BL19: =SUM(V$4:V$503)/COUNTA(A$4:A$503) -> 865.7998 | BM19: =SUM(W$4:W$503)/COUNTA(A$4:A$503) -> 888.59982 | BN19: =SUM(X$4:X$503)/COUNTA(A$4:A$503) -> 918.60034 | BO19: . | BP19: =IF(Z19>=BB19,0,IFERROR(BB19+(SUMPRODUCT((Z$4:Z$503>=BB$4:BB$503)*(Z$4:Z$503-BB$4:BB$503))/MAX(1,COUNTIF(Z$4:Z$503,"<"&BB19+0.01))),BB19)) -> 0 | BQ19: =IF(AA19>=BC19,0,IFERROR(BC19+SUMPRODUCT((AA$4:AA$503>=BC$4:BC$503)*(AA$4:AA$503-BC$4:BC$503))/MAX(1,COUNTIF(AA$4:AA$503,"<"&BC19+0.01)),BC19)) -> 2238.4659 | BR19: =IF(AB19>=BD19,0,IFERROR(BD19+SUMPRODUCT((AB$4:AB$503>=BD$4:BD$503)*(AB$4:AB$503-BD$4:BD$503))/MAX(1,COUNTIF(AB$4:AB$503,"<"&BD19+0.01)),BD19)) -> 3335.2938 | BS19: =IF(AC19>=BE19,0,IFERROR(BE19+SUMPRODUCT((AC$4:AC$503>=BE$4:BE$503)*(AC$4:AC$503-BE$4:BE$503))/MAX(1,COUNTIF(AC$4:AC$503,"<"&BE19+0.01)),BE19)) -> 6188.7335 | BT19: =IF(AD19>=BF19,0,IFERROR(BF19+SUMPRODUCT((AD$4:AD$503>=BF$4:BF$503)*(AD$4:AD$503-BF$4:BF$503))/MAX(1,COUNTIF(AD$4:AD$503,"<"&BF19+0.01)),BF19)) -> 11354.354 | BU19: =IF(AE19>=BG19,0,IFERROR(BG19+SUMPRODUCT((AE$4:AE$503>=BG$4:BG$503)*(AE$4:AE$503-BG$4:BG$503))/MAX(1,COUNTIF(AE$4:AE$503,"<"&BG19+0.01)),BG19)) -> 7704.8592 | BV19: =IF(AF19>=BH19,0,IFERROR(BH19+SUMPRODUCT((AF$4:AF$503>=BH$4:BH$503)*(AF$4:AF$503-BH$4:BH$503))/MAX(1,COUNTIF(AF$4:AF$503,"<"&BH19+0.01)),BH19)) -> 9942.6504 | BW19: =IF(AG19>=BI19,0,IFERROR(BI19+SUMPRODUCT((AG$4:AG$503>=BI$4:BI$503)*(AG$4:AG$503-BI$4:BI$503))/MAX(1,COUNTIF(AG$4:AG$503,"<"&BI19+0.01)),BI19)) -> 0 | BX19: =IF(AH19>=BJ19,0,IFERROR(BJ19+SUMPRODUCT((AH$4:AH$503>=BJ$4:BJ$503)*(AH$4:AH$503-BJ$4:BJ$503))/MAX(1,COUNTIF(AH$4:AH$503,"<"&BJ19+0.01)),BJ19)) -> 0 | ... CB19: =IF(AL19>=BN19,0,IFERROR(BN19+SUMPRODUCT((AL$4:AL$503>=BN$4:BN$503)*(AL$4:AL$503-BN$4:BN$503))/MAX(1,COUNTIF(AL$4:AL$503,"<"&BN19+0.01)),BN19)) -> 0 | CC19: =IF(AO19="🟢","VERDE",IF(AO19="🟡","AMARELO",IF(AO19="🟠","VERMELHO",IF(AO19="🔴","VERMELHO","ROXO")))) -> VERMELHO | CD19: 🌎 REGIÕES | CE19: SEM REDE
A20: 54211982000190 | B20: MAGOGA HORTIFRUTI LTDA - EPP | C20: SP INTERIOR | D20: LARISSA PADILHA | E20: SP | F20: =IFERROR(VLOOKUP(C20,$AS$3:$AT$10,2,FALSE()),IFERROR(VLOOKUP(C20,$AS$15:$AT$22,2,FALSE()),"")) -> 42 | G20: =IFERROR(VLOOKUP(C20,$AS$3:$AX$10,6,FALSE()),IFERROR(VLOOKUP(C20,$AS$15:$AX$22,6,FALSE()),"")) -> 0.42487208 | H20: =IFERROR(VLOOKUP(C20,$AS$3:$AY$10,7,FALSE()),IFERROR(VLOOKUP(C20,$AS$15:$AY$22,7,FALSE()),"")) -> 🟡 AMARELO | I20: =IFERROR(VLOOKUP(C20,$AS$3:$AZ$10,8,FALSE()),IFERROR(VLOOKUP(C20,$AS$15:$AZ$22,8,FALSE()),"")) -> Sell Out | K20: SP INTERIOR | L20: 40182.04 | M20: 2823.71 | N20: 2950.68 | O20: 3021.78 | P20: 3100.5 | Q20: 3202.07 | R20: 3285.87 | S20: 3412.83 | T20: 3496.63 | U20: 3575.35 | V20: 3664.22 | W20: 3760.72 | X20: 3887.68 | Y20: . | Z20: =SUM(AA20:AL20) -> 17607.36 | AD20: 4357.86 | AE20: 5371.12 | AF20: 2564.4 | AG20: 2406.47 | AI20: 1879.39 | AL20: 1028.12 | AM20: . | AN20: =IF(L20=0,0,Z20/L20) -> 0.4381898 | AO20: =IF(AN20="","",IF(AN20>=0.9,"🟢",IF(AN20>=0.7,"🟡",IF(AN20>=0.5,"🟠","🔴")))) -> 🔴 | AP20: =IF(L20=0,0,L20-Z20) -> 22574.68 | AQ20: =IF(AP20=0,"",RANK(AP20,AP$4:AP$503,0)) -> 15 | AR20: . | AS20: NORDESTE (SEM MA) | AT20: =COUNTIF(C$4:C$503,AS20) -> 29 | AU20: =COUNTIFS(C$4:C$503,AS20,Z$4:Z$503,">0") -> 29 | AV20: =SUMIF(C$4:C$503,AS20,L$4:L$503) -> 239240.09 | AW20: =SUMIF(C$4:C$503,AS20,Z$4:Z$503) -> 109706.91 | AX20: =IF(AV20=0,0,AW20/AV20) -> 0.45856407 | AY20: =IF(AX20>=0.6,"🟢 VERDE",IF(AX20>=0.4,"🟡 AMARELO",IF(AX20>=0.01,"🔴 VERMELHO","🟣 ROXO"))) -> 🟡 AMARELO | AZ20: =IF(AX20>=0.6,"JBP",IF(AX20>=0.4,"Sell Out",IF(AX20>=0.1,"Positivação + Expandir",IF(AX20>=0.01,"Ativar + Prospectar","Mapear + Prospectar")))) -> Sell Out | BA20: . | BB20: =SUM(L$4:L$503)/COUNTA(A$4:A$503) -> 9494.3999 | BC20: =SUM(M$4:M$503)/COUNTA(A$4:A$503) -> 667.20008 | BD20: =SUM(N$4:N$503)/COUNTA(A$4:A$503) -> 697.19996 | BE20: =SUM(O$4:O$503)/COUNTA(A$4:A$503) -> 713.9999 | BF20: =SUM(P$4:P$503)/COUNTA(A$4:A$503) -> 732.59984 | BG20: =SUM(Q$4:Q$503)/COUNTA(A$4:A$503) -> 756.59992 | BH20: =SUM(R$4:R$503)/COUNTA(A$4:A$503) -> 776.40004 | BI20: =SUM(S$4:S$503)/COUNTA(A$4:A$503) -> 806.40012 | BJ20: =SUM(T$4:T$503)/COUNTA(A$4:A$503) -> 826.1999 | BK20: =SUM(U$4:U$503)/COUNTA(A$4:A$503) -> 844.8002 | BL20: =SUM(V$4:V$503)/COUNTA(A$4:A$503) -> 865.7998 | BM20: =SUM(W$4:W$503)/COUNTA(A$4:A$503) -> 888.59982 | BN20: =SUM(X$4:X$503)/COUNTA(A$4:A$503) -> 918.60034 | BO20: . | BP20: =IF(Z20>=BB20,0,IFERROR(BB20+(SUMPRODUCT((Z$4:Z$503>=BB$4:BB$503)*(Z$4:Z$503-BB$4:BB$503))/MAX(1,COUNTIF(Z$4:Z$503,"<"&BB20+0.01))),BB20)) -> 0 | BQ20: =IF(AA20>=BC20,0,IFERROR(BC20+SUMPRODUCT((AA$4:AA$503>=BC$4:BC$503)*(AA$4:AA$503-BC$4:BC$503))/MAX(1,COUNTIF(AA$4:AA$503,"<"&BC20+0.01)),BC20)) -> 2238.4659 | BR20: =IF(AB20>=BD20,0,IFERROR(BD20+SUMPRODUCT((AB$4:AB$503>=BD$4:BD$503)*(AB$4:AB$503-BD$4:BD$503))/MAX(1,COUNTIF(AB$4:AB$503,"<"&BD20+0.01)),BD20)) -> 3335.2938 | BS20: =IF(AC20>=BE20,0,IFERROR(BE20+SUMPRODUCT((AC$4:AC$503>=BE$4:BE$503)*(AC$4:AC$503-BE$4:BE$503))/MAX(1,COUNTIF(AC$4:AC$503,"<"&BE20+0.01)),BE20)) -> 6188.7335 | BT20: =IF(AD20>=BF20,0,IFERROR(BF20+SUMPRODUCT((AD$4:AD$503>=BF$4:BF$503)*(AD$4:AD$503-BF$4:BF$503))/MAX(1,COUNTIF(AD$4:AD$503,"<"&BF20+0.01)),BF20)) -> 0 | BU20: =IF(AE20>=BG20,0,IFERROR(BG20+SUMPRODUCT((AE$4:AE$503>=BG$4:BG$503)*(AE$4:AE$503-BG$4:BG$503))/MAX(1,COUNTIF(AE$4:AE$503,"<"&BG20+0.01)),BG20)) -> 0 | BV20: =IF(AF20>=BH20,0,IFERROR(BH20+SUMPRODUCT((AF$4:AF$503>=BH$4:BH$503)*(AF$4:AF$503-BH$4:BH$503))/MAX(1,COUNTIF(AF$4:AF$503,"<"&BH20+0.01)),BH20)) -> 0 | BW20: =IF(AG20>=BI20,0,IFERROR(BI20+SUMPRODUCT((AG$4:AG$503>=BI$4:BI$503)*(AG$4:AG$503-BI$4:BI$503))/MAX(1,COUNTIF(AG$4:AG$503,"<"&BI20+0.01)),BI20)) -> 0 | BX20: =IF(AH20>=BJ20,0,IFERROR(BJ20+SUMPRODUCT((AH$4:AH$503>=BJ$4:BJ$503)*(AH$4:AH$503-BJ$4:BJ$503))/MAX(1,COUNTIF(AH$4:AH$503,"<"&BJ20+0.01)),BJ20)) -> 5621.5026 | ... CB20: =IF(AL20>=BN20,0,IFERROR(BN20+SUMPRODUCT((AL$4:AL$503>=BN$4:BN$503)*(AL$4:AL$503-BN$4:BN$503))/MAX(1,COUNTIF(AL$4:AL$503,"<"&BN20+0.01)),BN20)) -> 0 | CC20: =IF(AO20="🟢","VERDE",IF(AO20="🟡","AMARELO",IF(AO20="🟠","VERMELHO",IF(AO20="🔴","VERMELHO","ROXO")))) -> VERMELHO | CD20: 🌎 REGIÕES | CE20: SEM REDE
A21: 01005782000114 | B21: ORGANIZACAO BARATELLA E BALTAZAR EVENTOS | C21: SEM GRUPO | D21: LARISSA PADILHA | E21: . | F21: =IFERROR(VLOOKUP(C21,$AS$3:$AT$10,2,FALSE()),IFERROR(VLOOKUP(C21,$AS$15:$AT$22,2,FALSE()),"")) -> 49 | G21: =IFERROR(VLOOKUP(C21,$AS$3:$AX$10,6,FALSE()),IFERROR(VLOOKUP(C21,$AS$15:$AX$22,6,FALSE()),"")) -> 0.43639135 | H21: =IFERROR(VLOOKUP(C21,$AS$3:$AY$10,7,FALSE()),IFERROR(VLOOKUP(C21,$AS$15:$AY$22,7,FALSE()),"")) -> 🟡 AMARELO | I21: =IFERROR(VLOOKUP(C21,$AS$3:$AZ$10,8,FALSE()),IFERROR(VLOOKUP(C21,$AS$15:$AZ$22,8,FALSE()),"")) -> Sell Out | K21: . | L21: 38724.51 | M21: 2721.29 | N21: 2843.65 | O21: 2912.17 | P21: 2988.03 | Q21: 3085.92 | R21: 3166.68 | S21: 3289.04 | T21: 3369.8 | U21: 3445.66 | V21: 3531.31 | W21: 3624.3 | X21: 3746.66 | Y21: . | Z21: =SUM(AA21:AL21) -> 16230.4 | AI21: 16230.4 | AM21: . | AN21: =IF(L21=0,0,Z21/L21) -> 0.41912474 | AO21: =IF(AN21="","",IF(AN21>=0.9,"🟢",IF(AN21>=0.7,"🟡",IF(AN21>=0.5,"🟠","🔴")))) -> 🔴 | AP21: =IF(L21=0,0,L21-Z21) -> 22494.11 | AQ21: =IF(AP21=0,"",RANK(AP21,AP$4:AP$503,0)) -> 16 | AR21: . | AS21: NORTE + MA | AT21: =COUNTIF(C$4:C$503,AS21) -> 10 | AU21: =COUNTIFS(C$4:C$503,AS21,Z$4:Z$503,">0") -> 10 | AV21: =SUMIF(C$4:C$503,AS21,L$4:L$503) -> 146882.63 | AW21: =SUMIF(C$4:C$503,AS21,Z$4:Z$503) -> 67042.41 | AX21: =IF(AV21=0,0,AW21/AV21) -> 0.45643525 | AY21: =IF(AX21>=0.6,"🟢 VERDE",IF(AX21>=0.4,"🟡 AMARELO",IF(AX21>=0.01,"🔴 VERMELHO","🟣 ROXO"))) -> 🟡 AMARELO | AZ21: =IF(AX21>=0.6,"JBP",IF(AX21>=0.4,"Sell Out",IF(AX21>=0.1,"Positivação + Expandir",IF(AX21>=0.01,"Ativar + Prospectar","Mapear + Prospectar")))) -> Sell Out | BA21: . | BB21: =SUM(L$4:L$503)/COUNTA(A$4:A$503) -> 9494.3999 | BC21: =SUM(M$4:M$503)/COUNTA(A$4:A$503) -> 667.20008 | BD21: =SUM(N$4:N$503)/COUNTA(A$4:A$503) -> 697.19996 | BE21: =SUM(O$4:O$503)/COUNTA(A$4:A$503) -> 713.9999 | BF21: =SUM(P$4:P$503)/COUNTA(A$4:A$503) -> 732.59984 | BG21: =SUM(Q$4:Q$503)/COUNTA(A$4:A$503) -> 756.59992 | BH21: =SUM(R$4:R$503)/COUNTA(A$4:A$503) -> 776.40004 | BI21: =SUM(S$4:S$503)/COUNTA(A$4:A$503) -> 806.40012 | BJ21: =SUM(T$4:T$503)/COUNTA(A$4:A$503) -> 826.1999 | BK21: =SUM(U$4:U$503)/COUNTA(A$4:A$503) -> 844.8002 | BL21: =SUM(V$4:V$503)/COUNTA(A$4:A$503) -> 865.7998 | BM21: =SUM(W$4:W$503)/COUNTA(A$4:A$503) -> 888.59982 | BN21: =SUM(X$4:X$503)/COUNTA(A$4:A$503) -> 918.60034 | BO21: . | BP21: =IF(Z21>=BB21,0,IFERROR(BB21+(SUMPRODUCT((Z$4:Z$503>=BB$4:BB$503)*(Z$4:Z$503-BB$4:BB$503))/MAX(1,COUNTIF(Z$4:Z$503,"<"&BB21+0.01))),BB21)) -> 0 | BQ21: =IF(AA21>=BC21,0,IFERROR(BC21+SUMPRODUCT((AA$4:AA$503>=BC$4:BC$503)*(AA$4:AA$503-BC$4:BC$503))/MAX(1,COUNTIF(AA$4:AA$503,"<"&BC21+0.01)),BC21)) -> 2238.4659 | BR21: =IF(AB21>=BD21,0,IFERROR(BD21+SUMPRODUCT((AB$4:AB$503>=BD$4:BD$503)*(AB$4:AB$503-BD$4:BD$503))/MAX(1,COUNTIF(AB$4:AB$503,"<"&BD21+0.01)),BD21)) -> 3335.2938 | BS21: =IF(AC21>=BE21,0,IFERROR(BE21+SUMPRODUCT((AC$4:AC$503>=BE$4:BE$503)*(AC$4:AC$503-BE$4:BE$503))/MAX(1,COUNTIF(AC$4:AC$503,"<"&BE21+0.01)),BE21)) -> 6188.7335 | BT21: =IF(AD21>=BF21,0,IFERROR(BF21+SUMPRODUCT((AD$4:AD$503>=BF$4:BF$503)*(AD$4:AD$503-BF$4:BF$503))/MAX(1,COUNTIF(AD$4:AD$503,"<"&BF21+0.01)),BF21)) -> 11354.354 | BU21: =IF(AE21>=BG21,0,IFERROR(BG21+SUMPRODUCT((AE$4:AE$503>=BG$4:BG$503)*(AE$4:AE$503-BG$4:BG$503))/MAX(1,COUNTIF(AE$4:AE$503,"<"&BG21+0.01)),BG21)) -> 7704.8592 | BV21: =IF(AF21>=BH21,0,IFERROR(BH21+SUMPRODUCT((AF$4:AF$503>=BH$4:BH$503)*(AF$4:AF$503-BH$4:BH$503))/MAX(1,COUNTIF(AF$4:AF$503,"<"&BH21+0.01)),BH21)) -> 9942.6504 | BW21: =IF(AG21>=BI21,0,IFERROR(BI21+SUMPRODUCT((AG$4:AG$503>=BI$4:BI$503)*(AG$4:AG$503-BI$4:BI$503))/MAX(1,COUNTIF(AG$4:AG$503,"<"&BI21+0.01)),BI21)) -> 9142.1587 | BX21: =IF(AH21>=BJ21,0,IFERROR(BJ21+SUMPRODUCT((AH$4:AH$503>=BJ$4:BJ$503)*(AH$4:AH$503-BJ$4:BJ$503))/MAX(1,COUNTIF(AH$4:AH$503,"<"&BJ21+0.01)),BJ21)) -> 5621.5026 | ... CB21: =IF(AL21>=BN21,0,IFERROR(BN21+SUMPRODUCT((AL$4:AL$503>=BN$4:BN$503)*(AL$4:AL$503-BN$4:BN$503))/MAX(1,COUNTIF(AL$4:AL$503,"<"&BN21+0.01)),BN21)) -> 3597.2615 | CC21: =IF(AO21="🟢","VERDE",IF(AO21="🟡","AMARELO",IF(AO21="🟠","VERMELHO",IF(AO21="🔴","VERMELHO","ROXO")))) -> VERMELHO | CD21: 🌎 REGIÕES | CE21: SEM REDE
A22: 37370567000160 | B22: KAROLINE SABINO DA SILVA - ME | C22: SP CAPITAL | D22: LARISSA PADILHA | E22: SP | F22: =IFERROR(VLOOKUP(C22,$AS$3:$AT$10,2,FALSE()),IFERROR(VLOOKUP(C22,$AS$15:$AT$22,2,FALSE()),"")) -> 29 | G22: =IFERROR(VLOOKUP(C22,$AS$3:$AX$10,6,FALSE()),IFERROR(VLOOKUP(C22,$AS$15:$AX$22,6,FALSE()),"")) -> 0.42584507 | H22: =IFERROR(VLOOKUP(C22,$AS$3:$AY$10,7,FALSE()),IFERROR(VLOOKUP(C22,$AS$15:$AY$22,7,FALSE()),"")) -> 🟡 AMARELO | I22: =IFERROR(VLOOKUP(C22,$AS$3:$AZ$10,8,FALSE()),IFERROR(VLOOKUP(C22,$AS$15:$AZ$22,8,FALSE()),"")) -> Sell Out | K22: SP CAPITAL | L22: 37991.86 | M22: 2669.8 | N22: 2789.85 | O22: 2857.07 | P22: 2931.5 | Q22: 3027.54 | R22: 3106.77 | S22: 3226.81 | T22: 3306.04 | U22: 3380.47 | V22: 3464.5 | W22: 3555.73 | X22: 3675.78 | Y22: . | Z22: =SUM(AA22:AL22) -> 16082.67 | AG22: 2058.07 | AH22: 3448 | AI22: 3231.74 | AJ22: 3672.43 | AL22: 3672.43 | AM22: . | AN22: =IF(L22=0,0,Z22/L22) -> 0.42331884 | AO22: =IF(AN22="","",IF(AN22>=0.9,"🟢",IF(AN22>=0.7,"🟡",IF(AN22>=0.5,"🟠","🔴")))) -> 🔴 | AP22: =IF(L22=0,0,L22-Z22) -> 21909.19 | AQ22: =IF(AP22=0,"",RANK(AP22,AP$4:AP$503,0)) -> 18 | AR22: . | AS22: SEM GRUPO | AT22: =COUNTIF(C$4:C$503,AS22) -> 49 | AU22: =COUNTIFS(C$4:C$503,AS22,Z$4:Z$503,">0") -> 49 | AV22: =SUMIF(C$4:C$503,AS22,L$4:L$503) -> 652295.05 | AW22: =SUMIF(C$4:C$503,AS22,Z$4:Z$503) -> 284655.92 | AX22: =IF(AV22=0,0,AW22/AV22) -> 0.43639135 | AY22: =IF(AX22>=0.6,"🟢 VERDE",IF(AX22>=0.4,"🟡 AMARELO",IF(AX22>=0.01,"🔴 VERMELHO","🟣 ROXO"))) -> 🟡 AMARELO | AZ22: =IF(AX22>=0.6,"JBP",IF(AX22>=0.4,"Sell Out",IF(AX22>=0.1,"Positivação + Expandir",IF(AX22>=0.01,"Ativar + Prospectar","Mapear + Prospectar")))) -> Sell Out | BA22: . | BB22: =SUM(L$4:L$503)/COUNTA(A$4:A$503) -> 9494.3999 | BC22: =SUM(M$4:M$503)/COUNTA(A$4:A$503) -> 667.20008 | BD22: =SUM(N$4:N$503)/COUNTA(A$4:A$503) -> 697.19996 | BE22: =SUM(O$4:O$503)/COUNTA(A$4:A$503) -> 713.9999 | BF22: =SUM(P$4:P$503)/COUNTA(A$4:A$503) -> 732.59984 | BG22: =SUM(Q$4:Q$503)/COUNTA(A$4:A$503) -> 756.59992 | BH22: =SUM(R$4:R$503)/COUNTA(A$4:A$503) -> 776.40004 | BI22: =SUM(S$4:S$503)/COUNTA(A$4:A$503) -> 806.40012 | BJ22: =SUM(T$4:T$503)/COUNTA(A$4:A$503) -> 826.1999 | BK22: =SUM(U$4:U$503)/COUNTA(A$4:A$503) -> 844.8002 | BL22: =SUM(V$4:V$503)/COUNTA(A$4:A$503) -> 865.7998 | BM22: =SUM(W$4:W$503)/COUNTA(A$4:A$503) -> 888.59982 | BN22: =SUM(X$4:X$503)/COUNTA(A$4:A$503) -> 918.60034 | BO22: . | BP22: =IF(Z22>=BB22,0,IFERROR(BB22+(SUMPRODUCT((Z$4:Z$503>=BB$4:BB$503)*(Z$4:Z$503-BB$4:BB$503))/MAX(1,COUNTIF(Z$4:Z$503,"<"&BB22+0.01))),BB22)) -> 0 | BQ22: =IF(AA22>=BC22,0,IFERROR(BC22+SUMPRODUCT((AA$4:AA$503>=BC$4:BC$503)*(AA$4:AA$503-BC$4:BC$503))/MAX(1,COUNTIF(AA$4:AA$503,"<"&BC22+0.01)),BC22)) -> 2238.4659 | BR22: =IF(AB22>=BD22,0,IFERROR(BD22+SUMPRODUCT((AB$4:AB$503>=BD$4:BD$503)*(AB$4:AB$503-BD$4:BD$503))/MAX(1,COUNTIF(AB$4:AB$503,"<"&BD22+0.01)),BD22)) -> 3335.2938 | BS22: =IF(AC22>=BE22,0,IFERROR(BE22+SUMPRODUCT((AC$4:AC$503>=BE$4:BE$503)*(AC$4:AC$503-BE$4:BE$503))/MAX(1,COUNTIF(AC$4:AC$503,"<"&BE22+0.01)),BE22)) -> 6188.7335 | BT22: =IF(AD22>=BF22,0,IFERROR(BF22+SUMPRODUCT((AD$4:AD$503>=BF$4:BF$503)*(AD$4:AD$503-BF$4:BF$503))/MAX(1,COUNTIF(AD$4:AD$503,"<"&BF22+0.01)),BF22)) -> 11354.354 | BU22: =IF(AE22>=BG22,0,IFERROR(BG22+SUMPRODUCT((AE$4:AE$503>=BG$4:BG$503)*(AE$4:AE$503-BG$4:BG$503))/MAX(1,COUNTIF(AE$4:AE$503,"<"&BG22+0.01)),BG22)) -> 7704.8592 | BV22: =IF(AF22>=BH22,0,IFERROR(BH22+SUMPRODUCT((AF$4:AF$503>=BH$4:BH$503)*(AF$4:AF$503-BH$4:BH$503))/MAX(1,COUNTIF(AF$4:AF$503,"<"&BH22+0.01)),BH22)) -> 9942.6504 | BW22: =IF(AG22>=BI22,0,IFERROR(BI22+SUMPRODUCT((AG$4:AG$503>=BI$4:BI$503)*(AG$4:AG$503-BI$4:BI$503))/MAX(1,COUNTIF(AG$4:AG$503,"<"&BI22+0.01)),BI22)) -> 0 | BX22: =IF(AH22>=BJ22,0,IFERROR(BJ22+SUMPRODUCT((AH$4:AH$503>=BJ$4:BJ$503)*(AH$4:AH$503-BJ$4:BJ$503))/MAX(1,COUNTIF(AH$4:AH$503,"<"&BJ22+0.01)),BJ22)) -> 0 | ... CB22: =IF(AL22>=BN22,0,IFERROR(BN22+SUMPRODUCT((AL$4:AL$503>=BN$4:BN$503)*(AL$4:AL$503-BN$4:BN$503))/MAX(1,COUNTIF(AL$4:AL$503,"<"&BN22+0.01)),BN22)) -> 0 | CC22: =IF(AO22="🟢","VERDE",IF(AO22="🟡","AMARELO",IF(AO22="🟠","VERMELHO",IF(AO22="🔴","VERMELHO","ROXO")))) -> VERMELHO | CD22: 🌎 REGIÕES | CE22: SEM REDE
A23: 13495805000103 | B23: E-LABORE COMERCIO DE PRODUTOS ALIMENTICI | C23: SUL | D23: HEMANUELE DITZEL (MANU) | E23: SC | F23: =IFERROR(VLOOKUP(C23,$AS$3:$AT$10,2,FALSE()),IFERROR(VLOOKUP(C23,$AS$15:$AT$22,2,FALSE()),"")) -> 132 | G23: =IFERROR(VLOOKUP(C23,$AS$3:$AX$10,6,FALSE()),IFERROR(VLOOKUP(C23,$AS$15:$AX$22,6,FALSE()),"")) -> 0.46819018 | H23: =IFERROR(VLOOKUP(C23,$AS$3:$AY$10,7,FALSE()),IFERROR(VLOOKUP(C23,$AS$15:$AY$22,7,FALSE()),"")) -> 🟡 AMARELO | I23: =IFERROR(VLOOKUP(C23,$AS$3:$AZ$10,8,FALSE()),IFERROR(VLOOKUP(C23,$AS$15:$AZ$22,8,FALSE()),"")) -> Sell Out | K23: SUL | L23: 37194.54 | M23: 2613.77 | N23: 2731.3 | O23: 2797.11 | P23: 2869.98 | Q23: 2964 | R23: 3041.57 | S23: 3159.09 | T23: 3236.66 | U23: 3309.52 | V23: 3391.79 | W23: 3481.11 | X23: 3598.64 | Y23: . | Z23: =SUM(AA23:AL23) -> 16169.2 | AD23: 929.57 | AE23: 917.33 | AF23: 6483.44 | AH23: 7838.86 | AM23: . | AN23: =IF(L23=0,0,Z23/L23) -> 0.43471972 | AO23: =IF(AN23="","",IF(AN23>=0.9,"🟢",IF(AN23>=0.7,"🟡",IF(AN23>=0.5,"🟠","🔴")))) -> 🔴 | AP23: =IF(L23=0,0,L23-Z23) -> 21025.34 | AQ23: =IF(AP23=0,"",RANK(AP23,AP$4:AP$503,0)) -> 21 | AR23: . | AS23: TOTAL REGIÕES | AU23: =SUM(AU15:AU22) -> 369 | AV23: =SUM(AV15:AV22) -> 3954183.3 | AW23: =SUM(AW15:AW22) -> 1720382.2 | AX23: =IF(AV23=0,0,AW23/AV23) -> 0.43507902 | BA23: . | BB23: =SUM(L$4:L$503)/COUNTA(A$4:A$503) -> 9494.3999 | BC23: =SUM(M$4:M$503)/COUNTA(A$4:A$503) -> 667.20008 | BD23: =SUM(N$4:N$503)/COUNTA(A$4:A$503) -> 697.19996 | BE23: =SUM(O$4:O$503)/COUNTA(A$4:A$503) -> 713.9999 | BF23: =SUM(P$4:P$503)/COUNTA(A$4:A$503) -> 732.59984 | BG23: =SUM(Q$4:Q$503)/COUNTA(A$4:A$503) -> 756.59992 | BH23: =SUM(R$4:R$503)/COUNTA(A$4:A$503) -> 776.40004 | BI23: =SUM(S$4:S$503)/COUNTA(A$4:A$503) -> 806.40012 | BJ23: =SUM(T$4:T$503)/COUNTA(A$4:A$503) -> 826.1999 | BK23: =SUM(U$4:U$503)/COUNTA(A$4:A$503) -> 844.8002 | BL23: =SUM(V$4:V$503)/COUNTA(A$4:A$503) -> 865.7998 | BM23: =SUM(W$4:W$503)/COUNTA(A$4:A$503) -> 888.59982 | BN23: =SUM(X$4:X$503)/COUNTA(A$4:A$503) -> 918.60034 | BO23: . | BP23: =IF(Z23>=BB23,0,IFERROR(BB23+(SUMPRODUCT((Z$4:Z$503>=BB$4:BB$503)*(Z$4:Z$503-BB$4:BB$503))/MAX(1,COUNTIF(Z$4:Z$503,"<"&BB23+0.01))),BB23)) -> 0 | BQ23: =IF(AA23>=BC23,0,IFERROR(BC23+SUMPRODUCT((AA$4:AA$503>=BC$4:BC$503)*(AA$4:AA$503-BC$4:BC$503))/MAX(1,COUNTIF(AA$4:AA$503,"<"&BC23+0.01)),BC23)) -> 2238.4659 | BR23: =IF(AB23>=BD23,0,IFERROR(BD23+SUMPRODUCT((AB$4:AB$503>=BD$4:BD$503)*(AB$4:AB$503-BD$4:BD$503))/MAX(1,COUNTIF(AB$4:AB$503,"<"&BD23+0.01)),BD23)) -> 3335.2938 | BS23: =IF(AC23>=BE23,0,IFERROR(BE23+SUMPRODUCT((AC$4:AC$503>=BE$4:BE$503)*(AC$4:AC$503-BE$4:BE$503))/MAX(1,COUNTIF(AC$4:AC$503,"<"&BE23+0.01)),BE23)) -> 6188.7335 | BT23: =IF(AD23>=BF23,0,IFERROR(BF23+SUMPRODUCT((AD$4:AD$503>=BF$4:BF$503)*(AD$4:AD$503-BF$4:BF$503))/MAX(1,COUNTIF(AD$4:AD$503,"<"&BF23+0.01)),BF23)) -> 0 | BU23: =IF(AE23>=BG23,0,IFERROR(BG23+SUMPRODUCT((AE$4:AE$503>=BG$4:BG$503)*(AE$4:AE$503-BG$4:BG$503))/MAX(1,COUNTIF(AE$4:AE$503,"<"&BG23+0.01)),BG23)) -> 0 | BV23: =IF(AF23>=BH23,0,IFERROR(BH23+SUMPRODUCT((AF$4:AF$503>=BH$4:BH$503)*(AF$4:AF$503-BH$4:BH$503))/MAX(1,COUNTIF(AF$4:AF$503,"<"&BH23+0.01)),BH23)) -> 0 | BW23: =IF(AG23>=BI23,0,IFERROR(BI23+SUMPRODUCT((AG$4:AG$503>=BI$4:BI$503)*(AG$4:AG$503-BI$4:BI$503))/MAX(1,COUNTIF(AG$4:AG$503,"<"&BI23+0.01)),BI23)) -> 9142.1587 | BX23: =IF(AH23>=BJ23,0,IFERROR(BJ23+SUMPRODUCT((AH$4:AH$503>=BJ$4:BJ$503)*(AH$4:AH$503-BJ$4:BJ$503))/MAX(1,COUNTIF(AH$4:AH$503,"<"&BJ23+0.01)),BJ23)) -> 0 | ... CB23: =IF(AL23>=BN23,0,IFERROR(BN23+SUMPRODUCT((AL$4:AL$503>=BN$4:BN$503)*(AL$4:AL$503-BN$4:BN$503))/MAX(1,COUNTIF(AL$4:AL$503,"<"&BN23+0.01)),BN23)) -> 3597.2615 | CC23: =IF(AO23="🟢","VERDE",IF(AO23="🟡","AMARELO",IF(AO23="🟠","VERMELHO",IF(AO23="🔴","VERMELHO","ROXO")))) -> VERMELHO | CD23: 🌎 REGIÕES | CE23: SEM REDE
A24: 35751273000152 | B24: SR A GRANEL - PRODUTOS NATURAIS LTDA - E | C24: RJ + ES + MG | D24: LARISSA PADILHA | E24: MG | F24: =IFERROR(VLOOKUP(C24,$AS$3:$AT$10,2,FALSE()),IFERROR(VLOOKUP(C24,$AS$15:$AT$22,2,FALSE()),"")) -> 49 | G24: =IFERROR(VLOOKUP(C24,$AS$3:$AX$10,6,FALSE()),IFERROR(VLOOKUP(C24,$AS$15:$AX$22,6,FALSE()),"")) -> 0.46396509 | H24: =IFERROR(VLOOKUP(C24,$AS$3:$AY$10,7,FALSE()),IFERROR(VLOOKUP(C24,$AS$15:$AY$22,7,FALSE()),"")) -> 🟡 AMARELO | I24: =IFERROR(VLOOKUP(C24,$AS$3:$AZ$10,8,FALSE()),IFERROR(VLOOKUP(C24,$AS$15:$AZ$22,8,FALSE()),"")) -> Sell Out | K24: RJ + ES + MG | L24: 34853.92 | M24: 2449.29 | N24: 2559.42 | O24: 2621.09 | P24: 2689.37 | Q24: 2777.48 | R24: 2850.16 | S24: 2960.29 | T24: 3032.98 | U24: 3101.26 | V24: 3178.35 | W24: 3262.05 | X24: 3372.18 | Y24: . | Z24: =SUM(AA24:AL24) -> 16603.35 | AA24: 1253.39 | AD24: 3714.41 | AH24: 6768.79 | AK24: 4866.76 | AM24: . | AN24: =IF(L24=0,0,Z24/L24) -> 0.47636966 | AO24: =IF(AN24="","",IF(AN24>=0.9,"🟢",IF(AN24>=0.7,"🟡",IF(AN24>=0.5,"🟠","🔴")))) -> 🔴 | AP24: =IF(L24=0,0,L24-Z24) -> 18250.57 | AQ24: =IF(AP24=0,"",RANK(AP24,AP$4:AP$503,0)) -> 27 | AR24: . | BA24: . | BB24: =SUM(L$4:L$503)/COUNTA(A$4:A$503) -> 9494.3999 | BC24: =SUM(M$4:M$503)/COUNTA(A$4:A$503) -> 667.20008 | BD24: =SUM(N$4:N$503)/COUNTA(A$4:A$503) -> 697.19996 | BE24: =SUM(O$4:O$503)/COUNTA(A$4:A$503) -> 713.9999 | BF24: =SUM(P$4:P$503)/COUNTA(A$4:A$503) -> 732.59984 | BG24: =SUM(Q$4:Q$503)/COUNTA(A$4:A$503) -> 756.59992 | BH24: =SUM(R$4:R$503)/COUNTA(A$4:A$503) -> 776.40004 | BI24: =SUM(S$4:S$503)/COUNTA(A$4:A$503) -> 806.40012 | BJ24: =SUM(T$4:T$503)/COUNTA(A$4:A$503) -> 826.1999 | BK24: =SUM(U$4:U$503)/COUNTA(A$4:A$503) -> 844.8002 | BL24: =SUM(V$4:V$503)/COUNTA(A$4:A$503) -> 865.7998 | BM24: =SUM(W$4:W$503)/COUNTA(A$4:A$503) -> 888.59982 | BN24: =SUM(X$4:X$503)/COUNTA(A$4:A$503) -> 918.60034 | BO24: . | BP24: =IF(Z24>=BB24,0,IFERROR(BB24+(SUMPRODUCT((Z$4:Z$503>=BB$4:BB$503)*(Z$4:Z$503-BB$4:BB$503))/MAX(1,COUNTIF(Z$4:Z$503,"<"&BB24+0.01))),BB24)) -> 0 | BQ24: =IF(AA24>=BC24,0,IFERROR(BC24+SUMPRODUCT((AA$4:AA$503>=BC$4:BC$503)*(AA$4:AA$503-BC$4:BC$503))/MAX(1,COUNTIF(AA$4:AA$503,"<"&BC24+0.01)),BC24)) -> 0 | BR24: =IF(AB24>=BD24,0,IFERROR(BD24+SUMPRODUCT((AB$4:AB$503>=BD$4:BD$503)*(AB$4:AB$503-BD$4:BD$503))/MAX(1,COUNTIF(AB$4:AB$503,"<"&BD24+0.01)),BD24)) -> 3335.2938 | BS24: =IF(AC24>=BE24,0,IFERROR(BE24+SUMPRODUCT((AC$4:AC$503>=BE$4:BE$503)*(AC$4:AC$503-BE$4:BE$503))/MAX(1,COUNTIF(AC$4:AC$503,"<"&BE24+0.01)),BE24)) -> 6188.7335 | BT24: =IF(AD24>=BF24,0,IFERROR(BF24+SUMPRODUCT((AD$4:AD$503>=BF$4:BF$503)*(AD$4:AD$503-BF$4:BF$503))/MAX(1,COUNTIF(AD$4:AD$503,"<"&BF24+0.01)),BF24)) -> 0 | BU24: =IF(AE24>=BG24,0,IFERROR(BG24+SUMPRODUCT((AE$4:AE$503>=BG$4:BG$503)*(AE$4:AE$503-BG$4:BG$503))/MAX(1,COUNTIF(AE$4:AE$503,"<"&BG24+0.01)),BG24)) -> 7704.8592 | BV24: =IF(AF24>=BH24,0,IFERROR(BH24+SUMPRODUCT((AF$4:AF$503>=BH$4:BH$503)*(AF$4:AF$503-BH$4:BH$503))/MAX(1,COUNTIF(AF$4:AF$503,"<"&BH24+0.01)),BH24)) -> 9942.6504 | BW24: =IF(AG24>=BI24,0,IFERROR(BI24+SUMPRODUCT((AG$4:AG$503>=BI$4:BI$503)*(AG$4:AG$503-BI$4:BI$503))/MAX(1,COUNTIF(AG$4:AG$503,"<"&BI24+0.01)),BI24)) -> 9142.1587 | BX24: =IF(AH24>=BJ24,0,IFERROR(BJ24+SUMPRODUCT((AH$4:AH$503>=BJ$4:BJ$503)*(AH$4:AH$503-BJ$4:BJ$503))/MAX(1,COUNTIF(AH$4:AH$503,"<"&BJ24+0.01)),BJ24)) -> 0 | ... CB24: =IF(AL24>=BN24,0,IFERROR(BN24+SUMPRODUCT((AL$4:AL$503>=BN$4:BN$503)*(AL$4:AL$503-BN$4:BN$503))/MAX(1,COUNTIF(AL$4:AL$503,"<"&BN24+0.01)),BN24)) -> 3597.2615 | CC24: =IF(AO24="🟢","VERDE",IF(AO24="🟡","AMARELO",IF(AO24="🟠","VERMELHO",IF(AO24="🔴","VERMELHO","ROXO")))) -> VERMELHO | CD24: 🌎 REGIÕES | CE24: SEM REDE
A25: 24337192000194 | B25: ATLAS BRASIL COMERCIALIZADORA DE ENERGIA | C25: SP CAPITAL | D25: LARISSA PADILHA | E25: SP | F25: =IFERROR(VLOOKUP(C25,$AS$3:$AT$10,2,FALSE()),IFERROR(VLOOKUP(C25,$AS$15:$AT$22,2,FALSE()),"")) -> 29 | G25: =IFERROR(VLOOKUP(C25,$AS$3:$AX$10,6,FALSE()),IFERROR(VLOOKUP(C25,$AS$15:$AX$22,6,FALSE()),"")) -> 0.42584507 | H25: =IFERROR(VLOOKUP(C25,$AS$3:$AY$10,7,FALSE()),IFERROR(VLOOKUP(C25,$AS$15:$AY$22,7,FALSE()),"")) -> 🟡 AMARELO | I25: =IFERROR(VLOOKUP(C25,$AS$3:$AZ$10,8,FALSE()),IFERROR(VLOOKUP(C25,$AS$15:$AZ$22,8,FALSE()),"")) -> Sell Out | K25: SP CAPITAL | L25: 33886.15 | M25: 2381.28 | N25: 2488.35 | O25: 2548.31 | P25: 2614.7 | Q25: 2700.36 | R25: 2771.02 | S25: 2878.1 | T25: 2948.76 | U25: 3015.15 | V25: 3090.1 | W25: 3171.47 | X25: 3278.55 | Y25: . | Z25: =SUM(AA25:AL25) -> 13627.53 | AA25: 5530.63 | AC25: 4586.52 | AF25: 3510.38 | AM25: . | AN25: =IF(L25=0,0,Z25/L25) -> 0.40215634 | AO25: =IF(AN25="","",IF(AN25>=0.9,"🟢",IF(AN25>=0.7,"🟡",IF(AN25>=0.5,"🟠","🔴")))) -> 🔴 | AP25: =IF(L25=0,0,L25-Z25) -> 20258.62 | AQ25: =IF(AP25=0,"",RANK(AP25,AP$4:AP$503,0)) -> 22 | AR25: . | AS25: 👤 SINALEIRO CONSULTORES | BA25: . | BB25: =SUM(L$4:L$503)/COUNTA(A$4:A$503) -> 9494.3999 | BC25: =SUM(M$4:M$503)/COUNTA(A$4:A$503) -> 667.20008 | BD25: =SUM(N$4:N$503)/COUNTA(A$4:A$503) -> 697.19996 | BE25: =SUM(O$4:O$503)/COUNTA(A$4:A$503) -> 713.9999 | BF25: =SUM(P$4:P$503)/COUNTA(A$4:A$503) -> 732.59984 | BG25: =SUM(Q$4:Q$503)/COUNTA(A$4:A$503) -> 756.59992 | BH25: =SUM(R$4:R$503)/COUNTA(A$4:A$503) -> 776.40004 | BI25: =SUM(S$4:S$503)/COUNTA(A$4:A$503) -> 806.40012 | BJ25: =SUM(T$4:T$503)/COUNTA(A$4:A$503) -> 826.1999 | BK25: =SUM(U$4:U$503)/COUNTA(A$4:A$503) -> 844.8002 | BL25: =SUM(V$4:V$503)/COUNTA(A$4:A$503) -> 865.7998 | BM25: =SUM(W$4:W$503)/COUNTA(A$4:A$503) -> 888.59982 | BN25: =SUM(X$4:X$503)/COUNTA(A$4:A$503) -> 918.60034 | BO25: . | BP25: =IF(Z25>=BB25,0,IFERROR(BB25+(SUMPRODUCT((Z$4:Z$503>=BB$4:BB$503)*(Z$4:Z$503-BB$4:BB$503))/MAX(1,COUNTIF(Z$4:Z$503,"<"&BB25+0.01))),BB25)) -> 0 | BQ25: =IF(AA25>=BC25,0,IFERROR(BC25+SUMPRODUCT((AA$4:AA$503>=BC$4:BC$503)*(AA$4:AA$503-BC$4:BC$503))/MAX(1,COUNTIF(AA$4:AA$503,"<"&BC25+0.01)),BC25)) -> 0 | BR25: =IF(AB25>=BD25,0,IFERROR(BD25+SUMPRODUCT((AB$4:AB$503>=BD$4:BD$503)*(AB$4:AB$503-BD$4:BD$503))/MAX(1,COUNTIF(AB$4:AB$503,"<"&BD25+0.01)),BD25)) -> 3335.2938 | BS25: =IF(AC25>=BE25,0,IFERROR(BE25+SUMPRODUCT((AC$4:AC$503>=BE$4:BE$503)*(AC$4:AC$503-BE$4:BE$503))/MAX(1,COUNTIF(AC$4:AC$503,"<"&BE25+0.01)),BE25)) -> 0 | BT25: =IF(AD25>=BF25,0,IFERROR(BF25+SUMPRODUCT((AD$4:AD$503>=BF$4:BF$503)*(AD$4:AD$503-BF$4:BF$503))/MAX(1,COUNTIF(AD$4:AD$503,"<"&BF25+0.01)),BF25)) -> 11354.354 | BU25: =IF(AE25>=BG25,0,IFERROR(BG25+SUMPRODUCT((AE$4:AE$503>=BG$4:BG$503)*(AE$4:AE$503-BG$4:BG$503))/MAX(1,COUNTIF(AE$4:AE$503,"<"&BG25+0.01)),BG25)) -> 7704.8592 | BV25: =IF(AF25>=BH25,0,IFERROR(BH25+SUMPRODUCT((AF$4:AF$503>=BH$4:BH$503)*(AF$4:AF$503-BH$4:BH$503))/MAX(1,COUNTIF(AF$4:AF$503,"<"&BH25+0.01)),BH25)) -> 0 | BW25: =IF(AG25>=BI25,0,IFERROR(BI25+SUMPRODUCT((AG$4:AG$503>=BI$4:BI$503)*(AG$4:AG$503-BI$4:BI$503))/MAX(1,COUNTIF(AG$4:AG$503,"<"&BI25+0.01)),BI25)) -> 9142.1587 | BX25: =IF(AH25>=BJ25,0,IFERROR(BJ25+SUMPRODUCT((AH$4:AH$503>=BJ$4:BJ$503)*(AH$4:AH$503-BJ$4:BJ$503))/MAX(1,COUNTIF(AH$4:AH$503,"<"&BJ25+0.01)),BJ25)) -> 5621.5026 | ... CB25: =IF(AL25>=BN25,0,IFERROR(BN25+SUMPRODUCT((AL$4:AL$503>=BN$4:BN$503)*(AL$4:AL$503-BN$4:BN$503))/MAX(1,COUNTIF(AL$4:AL$503,"<"&BN25+0.01)),BN25)) -> 3597.2615 | CC25: =IF(AO25="🟢","VERDE",IF(AO25="🟡","AMARELO",IF(AO25="🟠","VERMELHO",IF(AO25="🔴","VERMELHO","ROXO")))) -> VERMELHO | CD25: 🌎 REGIÕES | CE25: SEM REDE
A26: 34060666000157 | B26: WILSON DE REZENDE PENHA - ME | C26: SP INTERIOR | D26: LARISSA PADILHA | E26: SP | F26: =IFERROR(VLOOKUP(C26,$AS$3:$AT$10,2,FALSE()),IFERROR(VLOOKUP(C26,$AS$15:$AT$22,2,FALSE()),"")) -> 42 | G26: =IFERROR(VLOOKUP(C26,$AS$3:$AX$10,6,FALSE()),IFERROR(VLOOKUP(C26,$AS$15:$AX$22,6,FALSE()),"")) -> 0.42487208 | H26: =IFERROR(VLOOKUP(C26,$AS$3:$AY$10,7,FALSE()),IFERROR(VLOOKUP(C26,$AS$15:$AY$22,7,FALSE()),"")) -> 🟡 AMARELO | I26: =IFERROR(VLOOKUP(C26,$AS$3:$AZ$10,8,FALSE()),IFERROR(VLOOKUP(C26,$AS$15:$AZ$22,8,FALSE()),"")) -> Sell Out | K26: SP INTERIOR | L26: 33248.35 | M26: 2336.46 | N26: 2441.52 | O26: 2500.35 | P26: 2565.48 | Q26: 2649.53 | R26: 2718.87 | S26: 2823.92 | T26: 2893.26 | U26: 2958.4 | V26: 3031.94 | W26: 3111.78 | X26: 3216.84 | Y26: . | Z26: =SUM(AA26:AL26) -> 11839.47 | AF26: 838.52 | AG26: 3851.22 | AH26: 1068.6 | AI26: 1781.13 | AK26: 4300 | AM26: . | AN26: =IF(L26=0,0,Z26/L26) -> 0.35609196 | AO26: =IF(AN26="","",IF(AN26>=0.9,"🟢",IF(AN26>=0.7,"🟡",IF(AN26>=0.5,"🟠","🔴")))) -> 🔴 | AP26: =IF(L26=0,0,L26-Z26) -> 21408.88 | AQ26: =IF(AP26=0,"",RANK(AP26,AP$4:AP$503,0)) -> 20 | AR26: . | AS26: GRUPO | AT26: CLIENTES | AU26: C/ VENDA | AV26: META R$ | AW26: FAT. REAL R$ | AX26: SINALEIRO % | AY26: COR | AZ26: AÇÃO | BA26: . | BB26: =SUM(L$4:L$503)/COUNTA(A$4:A$503) -> 9494.3999 | BC26: =SUM(M$4:M$503)/COUNTA(A$4:A$503) -> 667.20008 | BD26: =SUM(N$4:N$503)/COUNTA(A$4:A$503) -> 697.19996 | BE26: =SUM(O$4:O$503)/COUNTA(A$4:A$503) -> 713.9999 | BF26: =SUM(P$4:P$503)/COUNTA(A$4:A$503) -> 732.59984 | BG26: =SUM(Q$4:Q$503)/COUNTA(A$4:A$503) -> 756.59992 | BH26: =SUM(R$4:R$503)/COUNTA(A$4:A$503) -> 776.40004 | BI26: =SUM(S$4:S$503)/COUNTA(A$4:A$503) -> 806.40012 | BJ26: =SUM(T$4:T$503)/COUNTA(A$4:A$503) -> 826.1999 | BK26: =SUM(U$4:U$503)/COUNTA(A$4:A$503) -> 844.8002 | BL26: =SUM(V$4:V$503)/COUNTA(A$4:A$503) -> 865.7998 | BM26: =SUM(W$4:W$503)/COUNTA(A$4:A$503) -> 888.59982 | BN26: =SUM(X$4:X$503)/COUNTA(A$4:A$503) -> 918.60034 | BO26: . | BP26: =IF(Z26>=BB26,0,IFERROR(BB26+(SUMPRODUCT((Z$4:Z$503>=BB$4:BB$503)*(Z$4:Z$503-BB$4:BB$503))/MAX(1,COUNTIF(Z$4:Z$503,"<"&BB26+0.01))),BB26)) -> 0 | BQ26: =IF(AA26>=BC26,0,IFERROR(BC26+SUMPRODUCT((AA$4:AA$503>=BC$4:BC$503)*(AA$4:AA$503-BC$4:BC$503))/MAX(1,COUNTIF(AA$4:AA$503,"<"&BC26+0.01)),BC26)) -> 2238.4659 | BR26: =IF(AB26>=BD26,0,IFERROR(BD26+SUMPRODUCT((AB$4:AB$503>=BD$4:BD$503)*(AB$4:AB$503-BD$4:BD$503))/MAX(1,COUNTIF(AB$4:AB$503,"<"&BD26+0.01)),BD26)) -> 3335.2938 | BS26: =IF(AC26>=BE26,0,IFERROR(BE26+SUMPRODUCT((AC$4:AC$503>=BE$4:BE$503)*(AC$4:AC$503-BE$4:BE$503))/MAX(1,COUNTIF(AC$4:AC$503,"<"&BE26+0.01)),BE26)) -> 6188.7335 | BT26: =IF(AD26>=BF26,0,IFERROR(BF26+SUMPRODUCT((AD$4:AD$503>=BF$4:BF$503)*(AD$4:AD$503-BF$4:BF$503))/MAX(1,COUNTIF(AD$4:AD$503,"<"&BF26+0.01)),BF26)) -> 11354.354 | BU26: =IF(AE26>=BG26,0,IFERROR(BG26+SUMPRODUCT((AE$4:AE$503>=BG$4:BG$503)*(AE$4:AE$503-BG$4:BG$503))/MAX(1,COUNTIF(AE$4:AE$503,"<"&BG26+0.01)),BG26)) -> 7704.8592 | BV26: =IF(AF26>=BH26,0,IFERROR(BH26+SUMPRODUCT((AF$4:AF$503>=BH$4:BH$503)*(AF$4:AF$503-BH$4:BH$503))/MAX(1,COUNTIF(AF$4:AF$503,"<"&BH26+0.01)),BH26)) -> 0 | BW26: =IF(AG26>=BI26,0,IFERROR(BI26+SUMPRODUCT((AG$4:AG$503>=BI$4:BI$503)*(AG$4:AG$503-BI$4:BI$503))/MAX(1,COUNTIF(AG$4:AG$503,"<"&BI26+0.01)),BI26)) -> 0 | BX26: =IF(AH26>=BJ26,0,IFERROR(BJ26+SUMPRODUCT((AH$4:AH$503>=BJ$4:BJ$503)*(AH$4:AH$503-BJ$4:BJ$503))/MAX(1,COUNTIF(AH$4:AH$503,"<"&BJ26+0.01)),BJ26)) -> 0 | ... CB26: =IF(AL26>=BN26,0,IFERROR(BN26+SUMPRODUCT((AL$4:AL$503>=BN$4:BN$503)*(AL$4:AL$503-BN$4:BN$503))/MAX(1,COUNTIF(AL$4:AL$503,"<"&BN26+0.01)),BN26)) -> 3597.2615 | CC26: =IF(AO26="🟢","VERDE",IF(AO26="🟡","AMARELO",IF(AO26="🟠","VERMELHO",IF(AO26="🔴","VERMELHO","ROXO")))) -> VERMELHO | CD26: 🌎 REGIÕES | CE26: SEM REDE
A27: 45161877000100 | B27: JANAINA GREICE VANDERLINDE - ME | C27: CIA DA SAUDE | D27: JULIO GADRET | E27: SC | F27: =IFERROR(VLOOKUP(C27,$AS$3:$AT$10,2,FALSE()),IFERROR(VLOOKUP(C27,$AS$15:$AT$22,2,FALSE()),"")) -> 21 | G27: =IFERROR(VLOOKUP(C27,$AS$3:$AX$10,6,FALSE()),IFERROR(VLOOKUP(C27,$AS$15:$AX$22,6,FALSE()),"")) -> 0.49151456 | H27: =IFERROR(VLOOKUP(C27,$AS$3:$AY$10,7,FALSE()),IFERROR(VLOOKUP(C27,$AS$15:$AY$22,7,FALSE()),"")) -> 🟡 AMARELO | I27: =IFERROR(VLOOKUP(C27,$AS$3:$AZ$10,8,FALSE()),IFERROR(VLOOKUP(C27,$AS$15:$AZ$22,8,FALSE()),"")) -> Sell Out | K27: SUL | L27: 33031.62 | M27: 2321.23 | N27: 2425.6 | O27: 2484.05 | P27: 2548.76 | Q27: 2632.26 | R27: 2701.15 | S27: 2805.52 | T27: 2874.4 | U27: 2939.11 | V27: 3012.17 | W27: 3091.5 | X27: 3195.87 | Y27: . | Z27: =SUM(AA27:AL27) -> 13124.56 | AA27: 1360.8 | AD27: 4544.43 | AF27: 912.37 | AG27: 6306.96 | AM27: . | AN27: =IF(L27=0,0,Z27/L27) -> 0.39733322 | AO27: =IF(AN27="","",IF(AN27>=0.9,"🟢",IF(AN27>=0.7,"🟡",IF(AN27>=0.5,"🟠","🔴")))) -> 🔴 | AP27: =IF(L27=0,0,L27-Z27) -> 19907.06 | AQ27: =IF(AP27=0,"",RANK(AP27,AP$4:AP$503,0)) -> 23 | AR27: . | AS27: HEMANUELE DITZEL (MANU) | AT27: =COUNTIF(D$4:D$503,AS27) -> 170 | AU27: =COUNTIFS(D$4:D$503,AS27,Z$4:Z$503,">0") -> 169 | AV27: =SUMIF(D$4:D$503,AS27,L$4:L$503) -> 1552436.9 | AW27: =SUMIF(D$4:D$503,AS27,Z$4:Z$503) -> 752403.06 | AX27: =IF(AV27=0,0,AW27/AV27) -> 0.48465934 | AY27: =IF(AX27>=0.6,"🟢 VERDE",IF(AX27>=0.4,"🟡 AMARELO",IF(AX27>=0.01,"🔴 VERMELHO","🟣 ROXO"))) -> 🟡 AMARELO | AZ27: =IF(AX27>=0.6,"JBP",IF(AX27>=0.4,"Sell Out",IF(AX27>=0.1,"Positivação + Expandir",IF(AX27>=0.01,"Ativar + Prospectar","Mapear + Prospectar")))) -> Sell Out | BA27: . | BB27: =SUM(L$4:L$503)/COUNTA(A$4:A$503) -> 9494.3999 | BC27: =SUM(M$4:M$503)/COUNTA(A$4:A$503) -> 667.20008 | BD27: =SUM(N$4:N$503)/COUNTA(A$4:A$503) -> 697.19996 | BE27: =SUM(O$4:O$503)/COUNTA(A$4:A$503) -> 713.9999 | BF27: =SUM(P$4:P$503)/COUNTA(A$4:A$503) -> 732.59984 | BG27: =SUM(Q$4:Q$503)/COUNTA(A$4:A$503) -> 756.59992 | BH27: =SUM(R$4:R$503)/COUNTA(A$4:A$503) -> 776.40004 | BI27: =SUM(S$4:S$503)/COUNTA(A$4:A$503) -> 806.40012 | BJ27: =SUM(T$4:T$503)/COUNTA(A$4:A$503) -> 826.1999 | BK27: =SUM(U$4:U$503)/COUNTA(A$4:A$503) -> 844.8002 | BL27: =SUM(V$4:V$503)/COUNTA(A$4:A$503) -> 865.7998 | BM27: =SUM(W$4:W$503)/COUNTA(A$4:A$503) -> 888.59982 | BN27: =SUM(X$4:X$503)/COUNTA(A$4:A$503) -> 918.60034 | BO27: . | BP27: =IF(Z27>=BB27,0,IFERROR(BB27+(SUMPRODUCT((Z$4:Z$503>=BB$4:BB$503)*(Z$4:Z$503-BB$4:BB$503))/MAX(1,COUNTIF(Z$4:Z$503,"<"&BB27+0.01))),BB27)) -> 0 | BQ27: =IF(AA27>=BC27,0,IFERROR(BC27+SUMPRODUCT((AA$4:AA$503>=BC$4:BC$503)*(AA$4:AA$503-BC$4:BC$503))/MAX(1,COUNTIF(AA$4:AA$503,"<"&BC27+0.01)),BC27)) -> 0 | BR27: =IF(AB27>=BD27,0,IFERROR(BD27+SUMPRODUCT((AB$4:AB$503>=BD$4:BD$503)*(AB$4:AB$503-BD$4:BD$503))/MAX(1,COUNTIF(AB$4:AB$503,"<"&BD27+0.01)),BD27)) -> 3335.2938 | BS27: =IF(AC27>=BE27,0,IFERROR(BE27+SUMPRODUCT((AC$4:AC$503>=BE$4:BE$503)*(AC$4:AC$503-BE$4:BE$503))/MAX(1,COUNTIF(AC$4:AC$503,"<"&BE27+0.01)),BE27)) -> 6188.7335 | BT27: =IF(AD27>=BF27,0,IFERROR(BF27+SUMPRODUCT((AD$4:AD$503>=BF$4:BF$503)*(AD$4:AD$503-BF$4:BF$503))/MAX(1,COUNTIF(AD$4:AD$503,"<"&BF27+0.01)),BF27)) -> 0 | BU27: =IF(AE27>=BG27,0,IFERROR(BG27+SUMPRODUCT((AE$4:AE$503>=BG$4:BG$503)*(AE$4:AE$503-BG$4:BG$503))/MAX(1,COUNTIF(AE$4:AE$503,"<"&BG27+0.01)),BG27)) -> 7704.8592 | BV27: =IF(AF27>=BH27,0,IFERROR(BH27+SUMPRODUCT((AF$4:AF$503>=BH$4:BH$503)*(AF$4:AF$503-BH$4:BH$503))/MAX(1,COUNTIF(AF$4:AF$503,"<"&BH27+0.01)),BH27)) -> 0 | BW27: =IF(AG27>=BI27,0,IFERROR(BI27+SUMPRODUCT((AG$4:AG$503>=BI$4:BI$503)*(AG$4:AG$503-BI$4:BI$503))/MAX(1,COUNTIF(AG$4:AG$503,"<"&BI27+0.01)),BI27)) -> 0 | BX27: =IF(AH27>=BJ27,0,IFERROR(BJ27+SUMPRODUCT((AH$4:AH$503>=BJ$4:BJ$503)*(AH$4:AH$503-BJ$4:BJ$503))/MAX(1,COUNTIF(AH$4:AH$503,"<"&BJ27+0.01)),BJ27)) -> 5621.5026 | ... CB27: =IF(AL27>=BN27,0,IFERROR(BN27+SUMPRODUCT((AL$4:AL$503>=BN$4:BN$503)*(AL$4:AL$503-BN$4:BN$503))/MAX(1,COUNTIF(AL$4:AL$503,"<"&BN27+0.01)),BN27)) -> 3597.2615 | CC27: =IF(AO27="🟢","VERDE",IF(AO27="🟡","AMARELO",IF(AO27="🟠","VERMELHO",IF(AO27="🔴","VERMELHO","ROXO")))) -> VERMELHO | CD27: 🏪 REDES | CE27: CIA DA SAUDE
A28: 46814160000175 | B28: NATURE COMERCIO E DISTRIBUICAO - ME | C28: NORTE + MA | D28: LARISSA PADILHA | E28: PA | F28: =IFERROR(VLOOKUP(C28,$AS$3:$AT$10,2,FALSE()),IFERROR(VLOOKUP(C28,$AS$15:$AT$22,2,FALSE()),"")) -> 10 | G28: =IFERROR(VLOOKUP(C28,$AS$3:$AX$10,6,FALSE()),IFERROR(VLOOKUP(C28,$AS$15:$AX$22,6,FALSE()),"")) -> 0.45643525 | H28: =IFERROR(VLOOKUP(C28,$AS$3:$AY$10,7,FALSE()),IFERROR(VLOOKUP(C28,$AS$15:$AY$22,7,FALSE()),"")) -> 🟡 AMARELO | I28: =IFERROR(VLOOKUP(C28,$AS$3:$AZ$10,8,FALSE()),IFERROR(VLOOKUP(C28,$AS$15:$AZ$22,8,FALSE()),"")) -> Sell Out | K28: NORTE + MA | L28: 32055.28 | M28: 2252.62 | N28: 2353.91 | O28: 2410.63 | P28: 2473.43 | Q28: 2554.46 | R28: 2621.3 | S28: 2722.59 | T28: 2789.44 | U28: 2852.24 | V28: 2923.14 | W28: 3000.12 | X28: 3101.4 | Y28: . | Z28: =SUM(AA28:AL28) -> 12891.06 | AC28: 5836.68 | AG28: 7054.38 | AM28: . | AN28: =IF(L28=0,0,Z28/L28) -> 0.40215091 | AO28: =IF(AN28="","",IF(AN28>=0.9,"🟢",IF(AN28>=0.7,"🟡",IF(AN28>=0.5,"🟠","🔴")))) -> 🔴 | AP28: =IF(L28=0,0,L28-Z28) -> 19164.22 | AQ28: =IF(AP28=0,"",RANK(AP28,AP$4:AP$503,0)) -> 24 | AR28: . | AS28: LARISSA PADILHA | AT28: =COUNTIF(D$4:D$503,AS28) -> 211 | AU28: =COUNTIFS(D$4:D$503,AS28,Z$4:Z$503,">0") -> 208 | AV28: =SUMIF(D$4:D$503,AS28,L$4:L$503) -> 2533145.5 | AW28: =SUMIF(D$4:D$503,AS28,Z$4:Z$503) -> 1060743.3 | AX28: =IF(AV28=0,0,AW28/AV28) -> 0.41874551 | AY28: =IF(AX28>=0.6,"🟢 VERDE",IF(AX28>=0.4,"🟡 AMARELO",IF(AX28>=0.01,"🔴 VERMELHO","🟣 ROXO"))) -> 🟡 AMARELO | AZ28: =IF(AX28>=0.6,"JBP",IF(AX28>=0.4,"Sell Out",IF(AX28>=0.1,"Positivação + Expandir",IF(AX28>=0.01,"Ativar + Prospectar","Mapear + Prospectar")))) -> Sell Out | BA28: . | BB28: =SUM(L$4:L$503)/COUNTA(A$4:A$503) -> 9494.3999 | BC28: =SUM(M$4:M$503)/COUNTA(A$4:A$503) -> 667.20008 | BD28: =SUM(N$4:N$503)/COUNTA(A$4:A$503) -> 697.19996 | BE28: =SUM(O$4:O$503)/COUNTA(A$4:A$503) -> 713.9999 | BF28: =SUM(P$4:P$503)/COUNTA(A$4:A$503) -> 732.59984 | BG28: =SUM(Q$4:Q$503)/COUNTA(A$4:A$503) -> 756.59992 | BH28: =SUM(R$4:R$503)/COUNTA(A$4:A$503) -> 776.40004 | BI28: =SUM(S$4:S$503)/COUNTA(A$4:A$503) -> 806.40012 | BJ28: =SUM(T$4:T$503)/COUNTA(A$4:A$503) -> 826.1999 | BK28: =SUM(U$4:U$503)/COUNTA(A$4:A$503) -> 844.8002 | BL28: =SUM(V$4:V$503)/COUNTA(A$4:A$503) -> 865.7998 | BM28: =SUM(W$4:W$503)/COUNTA(A$4:A$503) -> 888.59982 | BN28: =SUM(X$4:X$503)/COUNTA(A$4:A$503) -> 918.60034 | BO28: . | BP28: =IF(Z28>=BB28,0,IFERROR(BB28+(SUMPRODUCT((Z$4:Z$503>=BB$4:BB$503)*(Z$4:Z$503-BB$4:BB$503))/MAX(1,COUNTIF(Z$4:Z$503,"<"&BB28+0.01))),BB28)) -> 0 | BQ28: =IF(AA28>=BC28,0,IFERROR(BC28+SUMPRODUCT((AA$4:AA$503>=BC$4:BC$503)*(AA$4:AA$503-BC$4:BC$503))/MAX(1,COUNTIF(AA$4:AA$503,"<"&BC28+0.01)),BC28)) -> 2238.4659 | BR28: =IF(AB28>=BD28,0,IFERROR(BD28+SUMPRODUCT((AB$4:AB$503>=BD$4:BD$503)*(AB$4:AB$503-BD$4:BD$503))/MAX(1,COUNTIF(AB$4:AB$503,"<"&BD28+0.01)),BD28)) -> 3335.2938 | BS28: =IF(AC28>=BE28,0,IFERROR(BE28+SUMPRODUCT((AC$4:AC$503>=BE$4:BE$503)*(AC$4:AC$503-BE$4:BE$503))/MAX(1,COUNTIF(AC$4:AC$503,"<"&BE28+0.01)),BE28)) -> 0 | BT28: =IF(AD28>=BF28,0,IFERROR(BF28+SUMPRODUCT((AD$4:AD$503>=BF$4:BF$503)*(AD$4:AD$503-BF$4:BF$503))/MAX(1,COUNTIF(AD$4:AD$503,"<"&BF28+0.01)),BF28)) -> 11354.354 | BU28: =IF(AE28>=BG28,0,IFERROR(BG28+SUMPRODUCT((AE$4:AE$503>=BG$4:BG$503)*(AE$4:AE$503-BG$4:BG$503))/MAX(1,COUNTIF(AE$4:AE$503,"<"&BG28+0.01)),BG28)) -> 7704.8592 | BV28: =IF(AF28>=BH28,0,IFERROR(BH28+SUMPRODUCT((AF$4:AF$503>=BH$4:BH$503)*(AF$4:AF$503-BH$4:BH$503))/MAX(1,COUNTIF(AF$4:AF$503,"<"&BH28+0.01)),BH28)) -> 9942.6504 | BW28: =IF(AG28>=BI28,0,IFERROR(BI28+SUMPRODUCT((AG$4:AG$503>=BI$4:BI$503)*(AG$4:AG$503-BI$4:BI$503))/MAX(1,COUNTIF(AG$4:AG$503,"<"&BI28+0.01)),BI28)) -> 0 | BX28: =IF(AH28>=BJ28,0,IFERROR(BJ28+SUMPRODUCT((AH$4:AH$503>=BJ$4:BJ$503)*(AH$4:AH$503-BJ$4:BJ$503))/MAX(1,COUNTIF(AH$4:AH$503,"<"&BJ28+0.01)),BJ28)) -> 5621.5026 | ... CB28: =IF(AL28>=BN28,0,IFERROR(BN28+SUMPRODUCT((AL$4:AL$503>=BN$4:BN$503)*(AL$4:AL$503-BN$4:BN$503))/MAX(1,COUNTIF(AL$4:AL$503,"<"&BN28+0.01)),BN28)) -> 3597.2615 | CC28: =IF(AO28="🟢","VERDE",IF(AO28="🟡","AMARELO",IF(AO28="🟠","VERMELHO",IF(AO28="🔴","VERMELHO","ROXO")))) -> VERMELHO | CD28: 🌎 REGIÕES | CE28: SEM REDE
A29: 60502242000105 | B29: ASSOCIACAO DE PAIS E AMIGOS DOSEXCEPCION | C29: SP CAPITAL | D29: LARISSA PADILHA | E29: SP | F29: =IFERROR(VLOOKUP(C29,$AS$3:$AT$10,2,FALSE()),IFERROR(VLOOKUP(C29,$AS$15:$AT$22,2,FALSE()),"")) -> 29 | G29: =IFERROR(VLOOKUP(C29,$AS$3:$AX$10,6,FALSE()),IFERROR(VLOOKUP(C29,$AS$15:$AX$22,6,FALSE()),"")) -> 0.42584507 | H29: =IFERROR(VLOOKUP(C29,$AS$3:$AY$10,7,FALSE()),IFERROR(VLOOKUP(C29,$AS$15:$AY$22,7,FALSE()),"")) -> 🟡 AMARELO | I29: =IFERROR(VLOOKUP(C29,$AS$3:$AZ$10,8,FALSE()),IFERROR(VLOOKUP(C29,$AS$15:$AZ$22,8,FALSE()),"")) -> Sell Out | K29: SP CAPITAL | L29: 31371.3 | M29: 2204.56 | N29: 2303.68 | O29: 2359.19 | P29: 2420.65 | Q29: 2499.95 | R29: 2565.37 | S29: 2664.5 | T29: 2729.92 | U29: 2791.38 | V29: 2860.77 | W29: 2936.1 | X29: 3035.23 | Y29: . | Z29: =SUM(AA29:AL29) -> 12616 | AA29: 2760 | AC29: 1122 | AE29: 1734 | AH29: 2040 | AJ29: 1200 | AK29: 2760 | AL29: 1000 | AM29: . | AN29: =IF(L29=0,0,Z29/L29) -> 0.40215101 | AO29: =IF(AN29="","",IF(AN29>=0.9,"🟢",IF(AN29>=0.7,"🟡",IF(AN29>=0.5,"🟠","🔴")))) -> 🔴 | AP29: =IF(L29=0,0,L29-Z29) -> 18755.3 | AQ29: =IF(AP29=0,"",RANK(AP29,AP$4:AP$503,0)) -> 25 | AR29: . | AS29: JULIO GADRET | AT29: =COUNTIF(D$4:D$503,AS29) -> 65 | AU29: =COUNTIFS(D$4:D$503,AS29,Z$4:Z$503,">0") -> 63 | AV29: =SUMIF(D$4:D$503,AS29,L$4:L$503) -> 412013.91 | AW29: =SUMIF(D$4:D$503,AS29,Z$4:Z$503) -> 204221.94 | AX29: =IF(AV29=0,0,AW29/AV29) -> 0.49566759 | AY29: =IF(AX29>=0.6,"🟢 VERDE",IF(AX29>=0.4,"🟡 AMARELO",IF(AX29>=0.01,"🔴 VERMELHO","🟣 ROXO"))) -> 🟡 AMARELO | AZ29: =IF(AX29>=0.6,"JBP",IF(AX29>=0.4,"Sell Out",IF(AX29>=0.1,"Positivação + Expandir",IF(AX29>=0.01,"Ativar + Prospectar","Mapear + Prospectar")))) -> Sell Out | BA29: . | BB29: =SUM(L$4:L$503)/COUNTA(A$4:A$503) -> 9494.3999 | BC29: =SUM(M$4:M$503)/COUNTA(A$4:A$503) -> 667.20008 | BD29: =SUM(N$4:N$503)/COUNTA(A$4:A$503) -> 697.19996 | BE29: =SUM(O$4:O$503)/COUNTA(A$4:A$503) -> 713.9999 | BF29: =SUM(P$4:P$503)/COUNTA(A$4:A$503) -> 732.59984 | BG29: =SUM(Q$4:Q$503)/COUNTA(A$4:A$503) -> 756.59992 | BH29: =SUM(R$4:R$503)/COUNTA(A$4:A$503) -> 776.40004 | BI29: =SUM(S$4:S$503)/COUNTA(A$4:A$503) -> 806.40012 | BJ29: =SUM(T$4:T$503)/COUNTA(A$4:A$503) -> 826.1999 | BK29: =SUM(U$4:U$503)/COUNTA(A$4:A$503) -> 844.8002 | BL29: =SUM(V$4:V$503)/COUNTA(A$4:A$503) -> 865.7998 | BM29: =SUM(W$4:W$503)/COUNTA(A$4:A$503) -> 888.59982 | BN29: =SUM(X$4:X$503)/COUNTA(A$4:A$503) -> 918.60034 | BO29: . | BP29: =IF(Z29>=BB29,0,IFERROR(BB29+(SUMPRODUCT((Z$4:Z$503>=BB$4:BB$503)*(Z$4:Z$503-BB$4:BB$503))/MAX(1,COUNTIF(Z$4:Z$503,"<"&BB29+0.01))),BB29)) -> 0 | BQ29: =IF(AA29>=BC29,0,IFERROR(BC29+SUMPRODUCT((AA$4:AA$503>=BC$4:BC$503)*(AA$4:AA$503-BC$4:BC$503))/MAX(1,COUNTIF(AA$4:AA$503,"<"&BC29+0.01)),BC29)) -> 0 | BR29: =IF(AB29>=BD29,0,IFERROR(BD29+SUMPRODUCT((AB$4:AB$503>=BD$4:BD$503)*(AB$4:AB$503-BD$4:BD$503))/MAX(1,COUNTIF(AB$4:AB$503,"<"&BD29+0.01)),BD29)) -> 3335.2938 | BS29: =IF(AC29>=BE29,0,IFERROR(BE29+SUMPRODUCT((AC$4:AC$503>=BE$4:BE$503)*(AC$4:AC$503-BE$4:BE$503))/MAX(1,COUNTIF(AC$4:AC$503,"<"&BE29+0.01)),BE29)) -> 0 | BT29: =IF(AD29>=BF29,0,IFERROR(BF29+SUMPRODUCT((AD$4:AD$503>=BF$4:BF$503)*(AD$4:AD$503-BF$4:BF$503))/MAX(1,COUNTIF(AD$4:AD$503,"<"&BF29+0.01)),BF29)) -> 11354.354 | BU29: =IF(AE29>=BG29,0,IFERROR(BG29+SUMPRODUCT((AE$4:AE$503>=BG$4:BG$503)*(AE$4:AE$503-BG$4:BG$503))/MAX(1,COUNTIF(AE$4:AE$503,"<"&BG29+0.01)),BG29)) -> 0 | BV29: =IF(AF29>=BH29,0,IFERROR(BH29+SUMPRODUCT((AF$4:AF$503>=BH$4:BH$503)*(AF$4:AF$503-BH$4:BH$503))/MAX(1,COUNTIF(AF$4:AF$503,"<"&BH29+0.01)),BH29)) -> 9942.6504 | BW29: =IF(AG29>=BI29,0,IFERROR(BI29+SUMPRODUCT((AG$4:AG$503>=BI$4:BI$503)*(AG$4:AG$503-BI$4:BI$503))/MAX(1,COUNTIF(AG$4:AG$503,"<"&BI29+0.01)),BI29)) -> 9142.1587 | BX29: =IF(AH29>=BJ29,0,IFERROR(BJ29+SUMPRODUCT((AH$4:AH$503>=BJ$4:BJ$503)*(AH$4:AH$503-BJ$4:BJ$503))/MAX(1,COUNTIF(AH$4:AH$503,"<"&BJ29+0.01)),BJ29)) -> 0 | ... CB29: =IF(AL29>=BN29,0,IFERROR(BN29+SUMPRODUCT((AL$4:AL$503>=BN$4:BN$503)*(AL$4:AL$503-BN$4:BN$503))/MAX(1,COUNTIF(AL$4:AL$503,"<"&BN29+0.01)),BN29)) -> 0 | CC29: =IF(AO29="🟢","VERDE",IF(AO29="🟡","AMARELO",IF(AO29="🟠","VERMELHO",IF(AO29="🔴","VERMELHO","ROXO")))) -> VERMELHO | CD29: 🌎 REGIÕES | CE29: SEM REDE
A30: 09185428000473 | B30: NATURVIDA MERCADO SAUDAVEL LTDA - ME | C30: NATURVIDA | D30: HEMANUELE DITZEL (MANU) | E30: . | F30: =IFERROR(VLOOKUP(C30,$AS$3:$AT$10,2,FALSE()),IFERROR(VLOOKUP(C30,$AS$15:$AT$22,2,FALSE()),"")) | G30: =IFERROR(VLOOKUP(C30,$AS$3:$AX$10,6,FALSE()),IFERROR(VLOOKUP(C30,$AS$15:$AX$22,6,FALSE()),"")) | H30: =IFERROR(VLOOKUP(C30,$AS$3:$AY$10,7,FALSE()),IFERROR(VLOOKUP(C30,$AS$15:$AY$22,7,FALSE()),"")) | I30: =IFERROR(VLOOKUP(C30,$AS$3:$AZ$10,8,FALSE()),IFERROR(VLOOKUP(C30,$AS$15:$AZ$22,8,FALSE()),"")) | K30: . | L30: 30766.47 | M30: 2162.05 | N30: 2259.27 | O30: 2313.71 | P30: 2373.98 | Q30: 2451.75 | R30: 2515.91 | S30: 2613.13 | T30: 2677.29 | U30: 2737.56 | V30: 2805.61 | W30: 2879.5 | X30: 2976.71 | Y30: . | Z30: =SUM(AA30:AL30) -> 12372.77 | AF30: 1133.54 | AH30: 5292.9 | AI30: 1217.95 | AJ30: 3585.58 | AL30: 1142.8 | AM30: . | AN30: =IF(L30=0,0,Z30/L30) -> 0.40215111 | AO30: =IF(AN30="","",IF(AN30>=0.9,"🟢",IF(AN30>=0.7,"🟡",IF(AN30>=0.5,"🟠","🔴")))) -> 🔴 | AP30: =IF(L30=0,0,L30-Z30) -> 18393.7 | AQ30: =IF(AP30=0,"",RANK(AP30,AP$4:AP$503,0)) -> 26 | AR30: . | AS30: DAIANE STAVICKI | AT30: =COUNTIF(D$4:D$503,AS30) -> 54 | AU30: =COUNTIFS(D$4:D$503,AS30,Z$4:Z$503,">0") -> 46 | AV30: =SUMIF(D$4:D$503,AS30,L$4:L$503) -> 249603.61 | AW30: =SUMIF(D$4:D$503,AS30,Z$4:Z$503) -> 132020.79 | AX30: =IF(AV30=0,0,AW30/AV30) -> 0.5289218 | AY30: =IF(AX30>=0.6,"🟢 VERDE",IF(AX30>=0.4,"🟡 AMARELO",IF(AX30>=0.01,"🔴 VERMELHO","🟣 ROXO"))) -> 🟡 AMARELO | AZ30: =IF(AX30>=0.6,"JBP",IF(AX30>=0.4,"Sell Out",IF(AX30>=0.1,"Positivação + Expandir",IF(AX30>=0.01,"Ativar + Prospectar","Mapear + Prospectar")))) -> Sell Out | BA30: . | BB30: =SUM(L$4:L$503)/COUNTA(A$4:A$503) -> 9494.3999 | BC30: =SUM(M$4:M$503)/COUNTA(A$4:A$503) -> 667.20008 | BD30: =SUM(N$4:N$503)/COUNTA(A$4:A$503) -> 697.19996 | BE30: =SUM(O$4:O$503)/COUNTA(A$4:A$503) -> 713.9999 | BF30: =SUM(P$4:P$503)/COUNTA(A$4:A$503) -> 732.59984 | BG30: =SUM(Q$4:Q$503)/COUNTA(A$4:A$503) -> 756.59992 | BH30: =SUM(R$4:R$503)/COUNTA(A$4:A$503) -> 776.40004 | BI30: =SUM(S$4:S$503)/COUNTA(A$4:A$503) -> 806.40012 | BJ30: =SUM(T$4:T$503)/COUNTA(A$4:A$503) -> 826.1999 | BK30: =SUM(U$4:U$503)/COUNTA(A$4:A$503) -> 844.8002 | BL30: =SUM(V$4:V$503)/COUNTA(A$4:A$503) -> 865.7998 | BM30: =SUM(W$4:W$503)/COUNTA(A$4:A$503) -> 888.59982 | BN30: =SUM(X$4:X$503)/COUNTA(A$4:A$503) -> 918.60034 | BO30: . | BP30: =IF(Z30>=BB30,0,IFERROR(BB30+(SUMPRODUCT((Z$4:Z$503>=BB$4:BB$503)*(Z$4:Z$503-BB$4:BB$503))/MAX(1,COUNTIF(Z$4:Z$503,"<"&BB30+0.01))),BB30)) -> 0 | BQ30: =IF(AA30>=BC30,0,IFERROR(BC30+SUMPRODUCT((AA$4:AA$503>=BC$4:BC$503)*(AA$4:AA$503-BC$4:BC$503))/MAX(1,COUNTIF(AA$4:AA$503,"<"&BC30+0.01)),BC30)) -> 2238.4659 | BR30: =IF(AB30>=BD30,0,IFERROR(BD30+SUMPRODUCT((AB$4:AB$503>=BD$4:BD$503)*(AB$4:AB$503-BD$4:BD$503))/MAX(1,COUNTIF(AB$4:AB$503,"<"&BD30+0.01)),BD30)) -> 3335.2938 | BS30: =IF(AC30>=BE30,0,IFERROR(BE30+SUMPRODUCT((AC$4:AC$503>=BE$4:BE$503)*(AC$4:AC$503-BE$4:BE$503))/MAX(1,COUNTIF(AC$4:AC$503,"<"&BE30+0.01)),BE30)) -> 6188.7335 | BT30: =IF(AD30>=BF30,0,IFERROR(BF30+SUMPRODUCT((AD$4:AD$503>=BF$4:BF$503)*(AD$4:AD$503-BF$4:BF$503))/MAX(1,COUNTIF(AD$4:AD$503,"<"&BF30+0.01)),BF30)) -> 11354.354 | BU30: =IF(AE30>=BG30,0,IFERROR(BG30+SUMPRODUCT((AE$4:AE$503>=BG$4:BG$503)*(AE$4:AE$503-BG$4:BG$503))/MAX(1,COUNTIF(AE$4:AE$503,"<"&BG30+0.01)),BG30)) -> 7704.8592 | BV30: =IF(AF30>=BH30,0,IFERROR(BH30+SUMPRODUCT((AF$4:AF$503>=BH$4:BH$503)*(AF$4:AF$503-BH$4:BH$503))/MAX(1,COUNTIF(AF$4:AF$503,"<"&BH30+0.01)),BH30)) -> 0 | BW30: =IF(AG30>=BI30,0,IFERROR(BI30+SUMPRODUCT((AG$4:AG$503>=BI$4:BI$503)*(AG$4:AG$503-BI$4:BI$503))/MAX(1,COUNTIF(AG$4:AG$503,"<"&BI30+0.01)),BI30)) -> 9142.1587 | BX30: =IF(AH30>=BJ30,0,IFERROR(BJ30+SUMPRODUCT((AH$4:AH$503>=BJ$4:BJ$503)*(AH$4:AH$503-BJ$4:BJ$503))/MAX(1,COUNTIF(AH$4:AH$503,"<"&BJ30+0.01)),BJ30)) -> 0 | ... CB30: =IF(AL30>=BN30,0,IFERROR(BN30+SUMPRODUCT((AL$4:AL$503>=BN$4:BN$503)*(AL$4:AL$503-BN$4:BN$503))/MAX(1,COUNTIF(AL$4:AL$503,"<"&BN30+0.01)),BN30)) -> 0 | CC30: =IF(AO30="🟢","VERDE",IF(AO30="🟡","AMARELO",IF(AO30="🟠","VERMELHO",IF(AO30="🔴","VERMELHO","ROXO")))) -> VERMELHO | CD30: 🏪 REDES | CE30: NATURVIDA
A31: 42045188000134 | B31: K V DE CARLI MARTINS COMERCIO DE ALIMENT | C31: NORDESTE (SEM MA) | D31: LARISSA PADILHA | E31: PE | F31: =IFERROR(VLOOKUP(C31,$AS$3:$AT$10,2,FALSE()),IFERROR(VLOOKUP(C31,$AS$15:$AT$22,2,FALSE()),"")) -> 29 | G31: =IFERROR(VLOOKUP(C31,$AS$3:$AX$10,6,FALSE()),IFERROR(VLOOKUP(C31,$AS$15:$AX$22,6,FALSE()),"")) -> 0.45856407 | H31: =IFERROR(VLOOKUP(C31,$AS$3:$AY$10,7,FALSE()),IFERROR(VLOOKUP(C31,$AS$15:$AY$22,7,FALSE()),"")) -> 🟡 AMARELO | I31: =IFERROR(VLOOKUP(C31,$AS$3:$AZ$10,8,FALSE()),IFERROR(VLOOKUP(C31,$AS$15:$AZ$22,8,FALSE()),"")) -> Sell Out | K31: NORDESTE (SEM MA) | L31: 30700.2 | M31: 2157.4 | N31: 2254.4 | O31: 2308.72 | P31: 2368.87 | Q31: 2446.47 | R31: 2510.49 | S31: 2607.5 | T31: 2671.52 | U31: 2731.67 | V31: 2799.57 | W31: 2873.29 | X31: 2970.3 | Y31: . | Z31: =SUM(AA31:AL31) -> 15270.16 | AC31: 3097.52 | AD31: 3750.38 | AE31: 2607.9 | AG31: 2744.45 | AJ31: 3069.91 | AM31: . | AN31: =IF(L31=0,0,Z31/L31) -> 0.49739611 | AO31: =IF(AN31="","",IF(AN31>=0.9,"🟢",IF(AN31>=0.7,"🟡",IF(AN31>=0.5,"🟠","🔴")))) -> 🔴 | AP31: =IF(L31=0,0,L31-Z31) -> 15430.04 | AQ31: =IF(AP31=0,"",RANK(AP31,AP$4:AP$503,0)) -> 31 | AR31: . | AS31: TOTAL EQUIPE | AU31: =SUM(AU27:AU30) -> 486 | AV31: =SUM(AV27:AV30) -> 4747200 | AW31: =SUM(AW27:AW30) -> 2149389.1 | AX31: =IF(AV31=0,0,AW31/AV31) -> 0.45276987 | BA31: . | BB31: =SUM(L$4:L$503)/COUNTA(A$4:A$503) -> 9494.3999 | BC31: =SUM(M$4:M$503)/COUNTA(A$4:A$503) -> 667.20008 | BD31: =SUM(N$4:N$503)/COUNTA(A$4:A$503) -> 697.19996 | BE31: =SUM(O$4:O$503)/COUNTA(A$4:A$503) -> 713.9999 | BF31: =SUM(P$4:P$503)/COUNTA(A$4:A$503) -> 732.59984 | BG31: =SUM(Q$4:Q$503)/COUNTA(A$4:A$503) -> 756.59992 | BH31: =SUM(R$4:R$503)/COUNTA(A$4:A$503) -> 776.40004 | BI31: =SUM(S$4:S$503)/COUNTA(A$4:A$503) -> 806.40012 | BJ31: =SUM(T$4:T$503)/COUNTA(A$4:A$503) -> 826.1999 | BK31: =SUM(U$4:U$503)/COUNTA(A$4:A$503) -> 844.8002 | BL31: =SUM(V$4:V$503)/COUNTA(A$4:A$503) -> 865.7998 | BM31: =SUM(W$4:W$503)/COUNTA(A$4:A$503) -> 888.59982 | BN31: =SUM(X$4:X$503)/COUNTA(A$4:A$503) -> 918.60034 | BO31: . | BP31: =IF(Z31>=BB31,0,IFERROR(BB31+(SUMPRODUCT((Z$4:Z$503>=BB$4:BB$503)*(Z$4:Z$503-BB$4:BB$503))/MAX(1,COUNTIF(Z$4:Z$503,"<"&BB31+0.01))),BB31)) -> 0 | BQ31: =IF(AA31>=BC31,0,IFERROR(BC31+SUMPRODUCT((AA$4:AA$503>=BC$4:BC$503)*(AA$4:AA$503-BC$4:BC$503))/MAX(1,COUNTIF(AA$4:AA$503,"<"&BC31+0.01)),BC31)) -> 2238.4659 | BR31: =IF(AB31>=BD31,0,IFERROR(BD31+SUMPRODUCT((AB$4:AB$503>=BD$4:BD$503)*(AB$4:AB$503-BD$4:BD$503))/MAX(1,COUNTIF(AB$4:AB$503,"<"&BD31+0.01)),BD31)) -> 3335.2938 | BS31: =IF(AC31>=BE31,0,IFERROR(BE31+SUMPRODUCT((AC$4:AC$503>=BE$4:BE$503)*(AC$4:AC$503-BE$4:BE$503))/MAX(1,COUNTIF(AC$4:AC$503,"<"&BE31+0.01)),BE31)) -> 0 | BT31: =IF(AD31>=BF31,0,IFERROR(BF31+SUMPRODUCT((AD$4:AD$503>=BF$4:BF$503)*(AD$4:AD$503-BF$4:BF$503))/MAX(1,COUNTIF(AD$4:AD$503,"<"&BF31+0.01)),BF31)) -> 0 | BU31: =IF(AE31>=BG31,0,IFERROR(BG31+SUMPRODUCT((AE$4:AE$503>=BG$4:BG$503)*(AE$4:AE$503-BG$4:BG$503))/MAX(1,COUNTIF(AE$4:AE$503,"<"&BG31+0.01)),BG31)) -> 0 | BV31: =IF(AF31>=BH31,0,IFERROR(BH31+SUMPRODUCT((AF$4:AF$503>=BH$4:BH$503)*(AF$4:AF$503-BH$4:BH$503))/MAX(1,COUNTIF(AF$4:AF$503,"<"&BH31+0.01)),BH31)) -> 9942.6504 | BW31: =IF(AG31>=BI31,0,IFERROR(BI31+SUMPRODUCT((AG$4:AG$503>=BI$4:BI$503)*(AG$4:AG$503-BI$4:BI$503))/MAX(1,COUNTIF(AG$4:AG$503,"<"&BI31+0.01)),BI31)) -> 0 | BX31: =IF(AH31>=BJ31,0,IFERROR(BJ31+SUMPRODUCT((AH$4:AH$503>=BJ$4:BJ$503)*(AH$4:AH$503-BJ$4:BJ$503))/MAX(1,COUNTIF(AH$4:AH$503,"<"&BJ31+0.01)),BJ31)) -> 5621.5026 | ... CB31: =IF(AL31>=BN31,0,IFERROR(BN31+SUMPRODUCT((AL$4:AL$503>=BN$4:BN$503)*(AL$4:AL$503-BN$4:BN$503))/MAX(1,COUNTIF(AL$4:AL$503,"<"&BN31+0.01)),BN31)) -> 3597.2615 | CC31: =IF(AO31="🟢","VERDE",IF(AO31="🟡","AMARELO",IF(AO31="🟠","VERMELHO",IF(AO31="🔴","VERMELHO","ROXO")))) -> VERMELHO | CD31: 🌎 REGIÕES | CE31: SEM REDE
A32: 37974794000102 | B32: CRISTIANE NIETO ARANTES LTDA - ME | C32: SUL | D32: HEMANUELE DITZEL (MANU) | E32: PR | F32: =IFERROR(VLOOKUP(C32,$AS$3:$AT$10,2,FALSE()),IFERROR(VLOOKUP(C32,$AS$15:$AT$22,2,FALSE()),"")) -> 132 | G32: =IFERROR(VLOOKUP(C32,$AS$3:$AX$10,6,FALSE()),IFERROR(VLOOKUP(C32,$AS$15:$AX$22,6,FALSE()),"")) -> 0.46819018 | H32: =IFERROR(VLOOKUP(C32,$AS$3:$AY$10,7,FALSE()),IFERROR(VLOOKUP(C32,$AS$15:$AY$22,7,FALSE()),"")) -> 🟡 AMARELO | I32: =IFERROR(VLOOKUP(C32,$AS$3:$AZ$10,8,FALSE()),IFERROR(VLOOKUP(C32,$AS$15:$AZ$22,8,FALSE()),"")) -> Sell Out | K32: SUL | L32: 30595.29 | M32: 2150.02 | N32: 2246.7 | O32: 2300.83 | P32: 2360.77 | Q32: 2438.11 | R32: 2501.92 | S32: 2598.59 | T32: 2662.39 | U32: 2722.33 | V32: 2790 | W32: 2863.48 | X32: 2960.15 | Y32: . | Z32: =SUM(AA32:AL32) -> 12542.07 | AE32: 6050.52 | AG32: 6491.55 | AM32: . | AN32: =IF(L32=0,0,Z32/L32) -> 0.40993467 | AO32: =IF(AN32="","",IF(AN32>=0.9,"🟢",IF(AN32>=0.7,"🟡",IF(AN32>=0.5,"🟠","🔴")))) -> 🔴 | AP32: =IF(L32=0,0,L32-Z32) -> 18053.22 | AQ32: =IF(AP32=0,"",RANK(AP32,AP$4:AP$503,0)) -> 28 | AR32: . | BA32: . | BB32: =SUM(L$4:L$503)/COUNTA(A$4:A$503) -> 9494.3999 | BC32: =SUM(M$4:M$503)/COUNTA(A$4:A$503) -> 667.20008 | BD32: =SUM(N$4:N$503)/COUNTA(A$4:A$503) -> 697.19996 | BE32: =SUM(O$4:O$503)/COUNTA(A$4:A$503) -> 713.9999 | BF32: =SUM(P$4:P$503)/COUNTA(A$4:A$503) -> 732.59984 | BG32: =SUM(Q$4:Q$503)/COUNTA(A$4:A$503) -> 756.59992 | BH32: =SUM(R$4:R$503)/COUNTA(A$4:A$503) -> 776.40004 | BI32: =SUM(S$4:S$503)/COUNTA(A$4:A$503) -> 806.40012 | BJ32: =SUM(T$4:T$503)/COUNTA(A$4:A$503) -> 826.1999 | BK32: =SUM(U$4:U$503)/COUNTA(A$4:A$503) -> 844.8002 | BL32: =SUM(V$4:V$503)/COUNTA(A$4:A$503) -> 865.7998 | BM32: =SUM(W$4:W$503)/COUNTA(A$4:A$503) -> 888.59982 | BN32: =SUM(X$4:X$503)/COUNTA(A$4:A$503) -> 918.60034 | BO32: . | BP32: =IF(Z32>=BB32,0,IFERROR(BB32+(SUMPRODUCT((Z$4:Z$503>=BB$4:BB$503)*(Z$4:Z$503-BB$4:BB$503))/MAX(1,COUNTIF(Z$4:Z$503,"<"&BB32+0.01))),BB32)) -> 0 | BQ32: =IF(AA32>=BC32,0,IFERROR(BC32+SUMPRODUCT((AA$4:AA$503>=BC$4:BC$503)*(AA$4:AA$503-BC$4:BC$503))/MAX(1,COUNTIF(AA$4:AA$503,"<"&BC32+0.01)),BC32)) -> 2238.4659 | BR32: =IF(AB32>=BD32,0,IFERROR(BD32+SUMPRODUCT((AB$4:AB$503>=BD$4:BD$503)*(AB$4:AB$503-BD$4:BD$503))/MAX(1,COUNTIF(AB$4:AB$503,"<"&BD32+0.01)),BD32)) -> 3335.2938 | BS32: =IF(AC32>=BE32,0,IFERROR(BE32+SUMPRODUCT((AC$4:AC$503>=BE$4:BE$503)*(AC$4:AC$503-BE$4:BE$503))/MAX(1,COUNTIF(AC$4:AC$503,"<"&BE32+0.01)),BE32)) -> 6188.7335 | BT32: =IF(AD32>=BF32,0,IFERROR(BF32+SUMPRODUCT((AD$4:AD$503>=BF$4:BF$503)*(AD$4:AD$503-BF$4:BF$503))/MAX(1,COUNTIF(AD$4:AD$503,"<"&BF32+0.01)),BF32)) -> 11354.354 | BU32: =IF(AE32>=BG32,0,IFERROR(BG32+SUMPRODUCT((AE$4:AE$503>=BG$4:BG$503)*(AE$4:AE$503-BG$4:BG$503))/MAX(1,COUNTIF(AE$4:AE$503,"<"&BG32+0.01)),BG32)) -> 0 | BV32: =IF(AF32>=BH32,0,IFERROR(BH32+SUMPRODUCT((AF$4:AF$503>=BH$4:BH$503)*(AF$4:AF$503-BH$4:BH$503))/MAX(1,COUNTIF(AF$4:AF$503,"<"&BH32+0.01)),BH32)) -> 9942.6504 | BW32: =IF(AG32>=BI32,0,IFERROR(BI32+SUMPRODUCT((AG$4:AG$503>=BI$4:BI$503)*(AG$4:AG$503-BI$4:BI$503))/MAX(1,COUNTIF(AG$4:AG$503,"<"&BI32+0.01)),BI32)) -> 0 | BX32: =IF(AH32>=BJ32,0,IFERROR(BJ32+SUMPRODUCT((AH$4:AH$503>=BJ$4:BJ$503)*(AH$4:AH$503-BJ$4:BJ$503))/MAX(1,COUNTIF(AH$4:AH$503,"<"&BJ32+0.01)),BJ32)) -> 5621.5026 | ... CB32: =IF(AL32>=BN32,0,IFERROR(BN32+SUMPRODUCT((AL$4:AL$503>=BN$4:BN$503)*(AL$4:AL$503-BN$4:BN$503))/MAX(1,COUNTIF(AL$4:AL$503,"<"&BN32+0.01)),BN32)) -> 3597.2615 | CC32: =IF(AO32="🟢","VERDE",IF(AO32="🟡","AMARELO",IF(AO32="🟠","VERMELHO",IF(AO32="🔴","VERMELHO","ROXO")))) -> VERMELHO | CD32: 🌎 REGIÕES | CE32: SEM REDE
A33: 07316826000103 | B33: SUPERMERCADO S & V LTDA - EPP | C33: SEM GRUPO | D33: HEMANUELE DITZEL (MANU) | E33: . | F33: =IFERROR(VLOOKUP(C33,$AS$3:$AT$10,2,FALSE()),IFERROR(VLOOKUP(C33,$AS$15:$AT$22,2,FALSE()),"")) -> 49 | G33: =IFERROR(VLOOKUP(C33,$AS$3:$AX$10,6,FALSE()),IFERROR(VLOOKUP(C33,$AS$15:$AX$22,6,FALSE()),"")) -> 0.43639135 | H33: =IFERROR(VLOOKUP(C33,$AS$3:$AY$10,7,FALSE()),IFERROR(VLOOKUP(C33,$AS$15:$AY$22,7,FALSE()),"")) -> 🟡 AMARELO | I33: =IFERROR(VLOOKUP(C33,$AS$3:$AZ$10,8,FALSE()),IFERROR(VLOOKUP(C33,$AS$15:$AZ$22,8,FALSE()),"")) -> Sell Out | K33: . | L33: 29615.69 | M33: 2081.18 | N33: 2174.76 | O33: 2227.17 | P33: 2285.18 | Q33: 2360.05 | R33: 2421.81 | S33: 2515.39 | T33: 2577.15 | U33: 2635.17 | V33: 2700.67 | W33: 2771.79 | X33: 2865.37 | Y33: . | Z33: =SUM(AA33:AL33) -> 11972.27 | AG33: 3416.95 | AH33: 1514.06 | AI33: 1824.33 | AK33: 1871.82 | AL33: 3345.11 | AM33: . | AN33: =IF(L33=0,0,Z33/L33) -> 0.4042543 | AO33: =IF(AN33="","",IF(AN33>=0.9,"🟢",IF(AN33>=0.7,"🟡",IF(AN33>=0.5,"🟠","🔴")))) -> 🔴 | AP33: =IF(L33=0,0,L33-Z33) -> 17643.42 | AQ33: =IF(AP33=0,"",RANK(AP33,AP$4:AP$503,0)) -> 29 | AR33: . | AS33: 📋 LEGENDA | BA33: . | BB33: =SUM(L$4:L$503)/COUNTA(A$4:A$503) -> 9494.3999 | BC33: =SUM(M$4:M$503)/COUNTA(A$4:A$503) -> 667.20008 | BD33: =SUM(N$4:N$503)/COUNTA(A$4:A$503) -> 697.19996 | BE33: =SUM(O$4:O$503)/COUNTA(A$4:A$503) -> 713.9999 | BF33: =SUM(P$4:P$503)/COUNTA(A$4:A$503) -> 732.59984 | BG33: =SUM(Q$4:Q$503)/COUNTA(A$4:A$503) -> 756.59992 | BH33: =SUM(R$4:R$503)/COUNTA(A$4:A$503) -> 776.40004 | BI33: =SUM(S$4:S$503)/COUNTA(A$4:A$503) -> 806.40012 | BJ33: =SUM(T$4:T$503)/COUNTA(A$4:A$503) -> 826.1999 | BK33: =SUM(U$4:U$503)/COUNTA(A$4:A$503) -> 844.8002 | BL33: =SUM(V$4:V$503)/COUNTA(A$4:A$503) -> 865.7998 | BM33: =SUM(W$4:W$503)/COUNTA(A$4:A$503) -> 888.59982 | BN33: =SUM(X$4:X$503)/COUNTA(A$4:A$503) -> 918.60034 | BO33: . | BP33: =IF(Z33>=BB33,0,IFERROR(BB33+(SUMPRODUCT((Z$4:Z$503>=BB$4:BB$503)*(Z$4:Z$503-BB$4:BB$503))/MAX(1,COUNTIF(Z$4:Z$503,"<"&BB33+0.01))),BB33)) -> 0 | BQ33: =IF(AA33>=BC33,0,IFERROR(BC33+SUMPRODUCT((AA$4:AA$503>=BC$4:BC$503)*(AA$4:AA$503-BC$4:BC$503))/MAX(1,COUNTIF(AA$4:AA$503,"<"&BC33+0.01)),BC33)) -> 2238.4659 | BR33: =IF(AB33>=BD33,0,IFERROR(BD33+SUMPRODUCT((AB$4:AB$503>=BD$4:BD$503)*(AB$4:AB$503-BD$4:BD$503))/MAX(1,COUNTIF(AB$4:AB$503,"<"&BD33+0.01)),BD33)) -> 3335.2938 | BS33: =IF(AC33>=BE33,0,IFERROR(BE33+SUMPRODUCT((AC$4:AC$503>=BE$4:BE$503)*(AC$4:AC$503-BE$4:BE$503))/MAX(1,COUNTIF(AC$4:AC$503,"<"&BE33+0.01)),BE33)) -> 6188.7335 | BT33: =IF(AD33>=BF33,0,IFERROR(BF33+SUMPRODUCT((AD$4:AD$503>=BF$4:BF$503)*(AD$4:AD$503-BF$4:BF$503))/MAX(1,COUNTIF(AD$4:AD$503,"<"&BF33+0.01)),BF33)) -> 11354.354 | BU33: =IF(AE33>=BG33,0,IFERROR(BG33+SUMPRODUCT((AE$4:AE$503>=BG$4:BG$503)*(AE$4:AE$503-BG$4:BG$503))/MAX(1,COUNTIF(AE$4:AE$503,"<"&BG33+0.01)),BG33)) -> 7704.8592 | BV33: =IF(AF33>=BH33,0,IFERROR(BH33+SUMPRODUCT((AF$4:AF$503>=BH$4:BH$503)*(AF$4:AF$503-BH$4:BH$503))/MAX(1,COUNTIF(AF$4:AF$503,"<"&BH33+0.01)),BH33)) -> 9942.6504 | BW33: =IF(AG33>=BI33,0,IFERROR(BI33+SUMPRODUCT((AG$4:AG$503>=BI$4:BI$503)*(AG$4:AG$503-BI$4:BI$503))/MAX(1,COUNTIF(AG$4:AG$503,"<"&BI33+0.01)),BI33)) -> 0 | BX33: =IF(AH33>=BJ33,0,IFERROR(BJ33+SUMPRODUCT((AH$4:AH$503>=BJ$4:BJ$503)*(AH$4:AH$503-BJ$4:BJ$503))/MAX(1,COUNTIF(AH$4:AH$503,"<"&BJ33+0.01)),BJ33)) -> 0 | ... CB33: =IF(AL33>=BN33,0,IFERROR(BN33+SUMPRODUCT((AL$4:AL$503>=BN$4:BN$503)*(AL$4:AL$503-BN$4:BN$503))/MAX(1,COUNTIF(AL$4:AL$503,"<"&BN33+0.01)),BN33)) -> 0 | CC33: =IF(AO33="🟢","VERDE",IF(AO33="🟡","AMARELO",IF(AO33="🟠","VERMELHO",IF(AO33="🔴","VERMELHO","ROXO")))) -> VERMELHO | CD33: 🌎 REGIÕES | CE33: SEM REDE
A34: 49300020000177 | B34: BIOLIZ COMERCIO DE PRODUTOS NATURAIS LTD | C34: DIVINA TERRA | D34: DAIANE STAVICKI | E34: RS | F34: =IFERROR(VLOOKUP(C34,$AS$3:$AT$10,2,FALSE()),IFERROR(VLOOKUP(C34,$AS$15:$AT$22,2,FALSE()),"")) -> 15 | G34: =IFERROR(VLOOKUP(C34,$AS$3:$AX$10,6,FALSE()),IFERROR(VLOOKUP(C34,$AS$15:$AX$22,6,FALSE()),"")) -> 0.62111188 | H34: =IFERROR(VLOOKUP(C34,$AS$3:$AY$10,7,FALSE()),IFERROR(VLOOKUP(C34,$AS$15:$AY$22,7,FALSE()),"")) -> 🟢 VERDE | I34: =IFERROR(VLOOKUP(C34,$AS$3:$AZ$10,8,FALSE()),IFERROR(VLOOKUP(C34,$AS$15:$AZ$22,8,FALSE()),"")) -> JBP | K34: SUL | L34: 29329.53 | M34: 2061.07 | N34: 2153.75 | O34: 2205.65 | P34: 2263.1 | Q34: 2337.24 | R34: 2398.41 | S34: 2491.08 | T34: 2552.25 | U34: 2609.71 | V34: 2674.58 | W34: 2745.01 | X34: 2837.68 | Y34: . | Z34: =SUM(AA34:AL34) -> 20602.15 | AI34: 4972.49 | AJ34: 7929.84 | AK34: 7699.82 | AM34: . | AN34: =IF(L34=0,0,Z34/L34) -> 0.7024371 | AO34: =IF(AN34="","",IF(AN34>=0.9,"🟢",IF(AN34>=0.7,"🟡",IF(AN34>=0.5,"🟠","🔴")))) -> 🟡 | AP34: =IF(L34=0,0,L34-Z34) -> 8727.38 | AQ34: =IF(AP34=0,"",RANK(AP34,AP$4:AP$503,0)) -> 69 | AR34: . | AS34: 🟢 VERDE ≥60% → JBP | BA34: . | BB34: =SUM(L$4:L$503)/COUNTA(A$4:A$503) -> 9494.3999 | BC34: =SUM(M$4:M$503)/COUNTA(A$4:A$503) -> 667.20008 | BD34: =SUM(N$4:N$503)/COUNTA(A$4:A$503) -> 697.19996 | BE34: =SUM(O$4:O$503)/COUNTA(A$4:A$503) -> 713.9999 | BF34: =SUM(P$4:P$503)/COUNTA(A$4:A$503) -> 732.59984 | BG34: =SUM(Q$4:Q$503)/COUNTA(A$4:A$503) -> 756.59992 | BH34: =SUM(R$4:R$503)/COUNTA(A$4:A$503) -> 776.40004 | BI34: =SUM(S$4:S$503)/COUNTA(A$4:A$503) -> 806.40012 | BJ34: =SUM(T$4:T$503)/COUNTA(A$4:A$503) -> 826.1999 | BK34: =SUM(U$4:U$503)/COUNTA(A$4:A$503) -> 844.8002 | BL34: =SUM(V$4:V$503)/COUNTA(A$4:A$503) -> 865.7998 | BM34: =SUM(W$4:W$503)/COUNTA(A$4:A$503) -> 888.59982 | BN34: =SUM(X$4:X$503)/COUNTA(A$4:A$503) -> 918.60034 | BO34: . | BP34: =IF(Z34>=BB34,0,IFERROR(BB34+(SUMPRODUCT((Z$4:Z$503>=BB$4:BB$503)*(Z$4:Z$503-BB$4:BB$503))/MAX(1,COUNTIF(Z$4:Z$503,"<"&BB34+0.01))),BB34)) -> 0 | BQ34: =IF(AA34>=BC34,0,IFERROR(BC34+SUMPRODUCT((AA$4:AA$503>=BC$4:BC$503)*(AA$4:AA$503-BC$4:BC$503))/MAX(1,COUNTIF(AA$4:AA$503,"<"&BC34+0.01)),BC34)) -> 2238.4659 | BR34: =IF(AB34>=BD34,0,IFERROR(BD34+SUMPRODUCT((AB$4:AB$503>=BD$4:BD$503)*(AB$4:AB$503-BD$4:BD$503))/MAX(1,COUNTIF(AB$4:AB$503,"<"&BD34+0.01)),BD34)) -> 3335.2938 | BS34: =IF(AC34>=BE34,0,IFERROR(BE34+SUMPRODUCT((AC$4:AC$503>=BE$4:BE$503)*(AC$4:AC$503-BE$4:BE$503))/MAX(1,COUNTIF(AC$4:AC$503,"<"&BE34+0.01)),BE34)) -> 6188.7335 | BT34: =IF(AD34>=BF34,0,IFERROR(BF34+SUMPRODUCT((AD$4:AD$503>=BF$4:BF$503)*(AD$4:AD$503-BF$4:BF$503))/MAX(1,COUNTIF(AD$4:AD$503,"<"&BF34+0.01)),BF34)) -> 11354.354 | BU34: =IF(AE34>=BG34,0,IFERROR(BG34+SUMPRODUCT((AE$4:AE$503>=BG$4:BG$503)*(AE$4:AE$503-BG$4:BG$503))/MAX(1,COUNTIF(AE$4:AE$503,"<"&BG34+0.01)),BG34)) -> 7704.8592 | BV34: =IF(AF34>=BH34,0,IFERROR(BH34+SUMPRODUCT((AF$4:AF$503>=BH$4:BH$503)*(AF$4:AF$503-BH$4:BH$503))/MAX(1,COUNTIF(AF$4:AF$503,"<"&BH34+0.01)),BH34)) -> 9942.6504 | BW34: =IF(AG34>=BI34,0,IFERROR(BI34+SUMPRODUCT((AG$4:AG$503>=BI$4:BI$503)*(AG$4:AG$503-BI$4:BI$503))/MAX(1,COUNTIF(AG$4:AG$503,"<"&BI34+0.01)),BI34)) -> 9142.1587 | BX34: =IF(AH34>=BJ34,0,IFERROR(BJ34+SUMPRODUCT((AH$4:AH$503>=BJ$4:BJ$503)*(AH$4:AH$503-BJ$4:BJ$503))/MAX(1,COUNTIF(AH$4:AH$503,"<"&BJ34+0.01)),BJ34)) -> 5621.5026 | ... CB34: =IF(AL34>=BN34,0,IFERROR(BN34+SUMPRODUCT((AL$4:AL$503>=BN$4:BN$503)*(AL$4:AL$503-BN$4:BN$503))/MAX(1,COUNTIF(AL$4:AL$503,"<"&BN34+0.01)),BN34)) -> 3597.2615 | CC34: =IF(AO34="🟢","VERDE",IF(AO34="🟡","AMARELO",IF(AO34="🟠","VERMELHO",IF(AO34="🔴","VERMELHO","ROXO")))) -> AMARELO | CD34: 🏪 REDES | CE34: DIVINA TERRA
A35: 04755895000125 | B35: SUPERMERCADO CASTILHO DE CAFELANDIA LTDA | C35: SEM GRUPO | D35: LARISSA PADILHA | E35: . | F35: =IFERROR(VLOOKUP(C35,$AS$3:$AT$10,2,FALSE()),IFERROR(VLOOKUP(C35,$AS$15:$AT$22,2,FALSE()),"")) -> 49 | G35: =IFERROR(VLOOKUP(C35,$AS$3:$AX$10,6,FALSE()),IFERROR(VLOOKUP(C35,$AS$15:$AX$22,6,FALSE()),"")) -> 0.43639135 | H35: =IFERROR(VLOOKUP(C35,$AS$3:$AY$10,7,FALSE()),IFERROR(VLOOKUP(C35,$AS$15:$AY$22,7,FALSE()),"")) -> 🟡 AMARELO | I35: =IFERROR(VLOOKUP(C35,$AS$3:$AZ$10,8,FALSE()),IFERROR(VLOOKUP(C35,$AS$15:$AZ$22,8,FALSE()),"")) -> Sell Out | K35: . | L35: 28008.92 | M35: 1968.27 | N35: 2056.77 | O35: 2106.33 | P35: 2161.2 | Q35: 2232.01 | R35: 2290.42 | S35: 2378.92 | T35: 2437.33 | U35: 2492.2 | V35: 2554.15 | W35: 2621.41 | X35: 2709.91 | Y35: . | Z35: =SUM(AA35:AL35) -> 11806.55 | AB35: 2467.18 | AC35: 1269.48 | AD35: 1209.18 | AF35: 1343.43 | AG35: 1821.6 | AI35: 1215.54 | AJ35: 1173.83 | AK35: 1306.31 | AM35: . | AN35: =IF(L35=0,0,Z35/L35) -> 0.42152821 | AO35: =IF(AN35="","",IF(AN35>=0.9,"🟢",IF(AN35>=0.7,"🟡",IF(AN35>=0.5,"🟠","🔴")))) -> 🔴 | AP35: =IF(L35=0,0,L35-Z35) -> 16202.37 | AQ35: =IF(AP35=0,"",RANK(AP35,AP$4:AP$503,0)) -> 30 | AR35: . | AS35: 🟡 AMARELO 40-60% → Sell Out | BA35: . | BB35: =SUM(L$4:L$503)/COUNTA(A$4:A$503) -> 9494.3999 | BC35: =SUM(M$4:M$503)/COUNTA(A$4:A$503) -> 667.20008 | BD35: =SUM(N$4:N$503)/COUNTA(A$4:A$503) -> 697.19996 | BE35: =SUM(O$4:O$503)/COUNTA(A$4:A$503) -> 713.9999 | BF35: =SUM(P$4:P$503)/COUNTA(A$4:A$503) -> 732.59984 | BG35: =SUM(Q$4:Q$503)/COUNTA(A$4:A$503) -> 756.59992 | BH35: =SUM(R$4:R$503)/COUNTA(A$4:A$503) -> 776.40004 | BI35: =SUM(S$4:S$503)/COUNTA(A$4:A$503) -> 806.40012 | BJ35: =SUM(T$4:T$503)/COUNTA(A$4:A$503) -> 826.1999 | BK35: =SUM(U$4:U$503)/COUNTA(A$4:A$503) -> 844.8002 | BL35: =SUM(V$4:V$503)/COUNTA(A$4:A$503) -> 865.7998 | BM35: =SUM(W$4:W$503)/COUNTA(A$4:A$503) -> 888.59982 | BN35: =SUM(X$4:X$503)/COUNTA(A$4:A$503) -> 918.60034 | BO35: . | BP35: =IF(Z35>=BB35,0,IFERROR(BB35+(SUMPRODUCT((Z$4:Z$503>=BB$4:BB$503)*(Z$4:Z$503-BB$4:BB$503))/MAX(1,COUNTIF(Z$4:Z$503,"<"&BB35+0.01))),BB35)) -> 0 | BQ35: =IF(AA35>=BC35,0,IFERROR(BC35+SUMPRODUCT((AA$4:AA$503>=BC$4:BC$503)*(AA$4:AA$503-BC$4:BC$503))/MAX(1,COUNTIF(AA$4:AA$503,"<"&BC35+0.01)),BC35)) -> 2238.4659 | BR35: =IF(AB35>=BD35,0,IFERROR(BD35+SUMPRODUCT((AB$4:AB$503>=BD$4:BD$503)*(AB$4:AB$503-BD$4:BD$503))/MAX(1,COUNTIF(AB$4:AB$503,"<"&BD35+0.01)),BD35)) -> 0 | BS35: =IF(AC35>=BE35,0,IFERROR(BE35+SUMPRODUCT((AC$4:AC$503>=BE$4:BE$503)*(AC$4:AC$503-BE$4:BE$503))/MAX(1,COUNTIF(AC$4:AC$503,"<"&BE35+0.01)),BE35)) -> 0 | BT35: =IF(AD35>=BF35,0,IFERROR(BF35+SUMPRODUCT((AD$4:AD$503>=BF$4:BF$503)*(AD$4:AD$503-BF$4:BF$503))/MAX(1,COUNTIF(AD$4:AD$503,"<"&BF35+0.01)),BF35)) -> 0 | BU35: =IF(AE35>=BG35,0,IFERROR(BG35+SUMPRODUCT((AE$4:AE$503>=BG$4:BG$503)*(AE$4:AE$503-BG$4:BG$503))/MAX(1,COUNTIF(AE$4:AE$503,"<"&BG35+0.01)),BG35)) -> 7704.8592 | BV35: =IF(AF35>=BH35,0,IFERROR(BH35+SUMPRODUCT((AF$4:AF$503>=BH$4:BH$503)*(AF$4:AF$503-BH$4:BH$503))/MAX(1,COUNTIF(AF$4:AF$503,"<"&BH35+0.01)),BH35)) -> 0 | BW35: =IF(AG35>=BI35,0,IFERROR(BI35+SUMPRODUCT((AG$4:AG$503>=BI$4:BI$503)*(AG$4:AG$503-BI$4:BI$503))/MAX(1,COUNTIF(AG$4:AG$503,"<"&BI35+0.01)),BI35)) -> 0 | BX35: =IF(AH35>=BJ35,0,IFERROR(BJ35+SUMPRODUCT((AH$4:AH$503>=BJ$4:BJ$503)*(AH$4:AH$503-BJ$4:BJ$503))/MAX(1,COUNTIF(AH$4:AH$503,"<"&BJ35+0.01)),BJ35)) -> 5621.5026 | ... CB35: =IF(AL35>=BN35,0,IFERROR(BN35+SUMPRODUCT((AL$4:AL$503>=BN$4:BN$503)*(AL$4:AL$503-BN$4:BN$503))/MAX(1,COUNTIF(AL$4:AL$503,"<"&BN35+0.01)),BN35)) -> 3597.2615 | CC35: =IF(AO35="🟢","VERDE",IF(AO35="🟡","AMARELO",IF(AO35="🟠","VERMELHO",IF(AO35="🔴","VERMELHO","ROXO")))) -> VERMELHO | CD35: 🌎 REGIÕES | CE35: SEM REDE
A36: 49982339000120 | B36: MDORNELLAS PRODUTOS NATURAIS E SUPLEMENT | C36: FITLAND | D36: JULIO GADRET | E36: SC | F36: =IFERROR(VLOOKUP(C36,$AS$3:$AT$10,2,FALSE()),IFERROR(VLOOKUP(C36,$AS$15:$AT$22,2,FALSE()),"")) -> 44 | G36: =IFERROR(VLOOKUP(C36,$AS$3:$AX$10,6,FALSE()),IFERROR(VLOOKUP(C36,$AS$15:$AX$22,6,FALSE()),"")) -> 0.49683951 | H36: =IFERROR(VLOOKUP(C36,$AS$3:$AY$10,7,FALSE()),IFERROR(VLOOKUP(C36,$AS$15:$AY$22,7,FALSE()),"")) -> 🟡 AMARELO | I36: =IFERROR(VLOOKUP(C36,$AS$3:$AZ$10,8,FALSE()),IFERROR(VLOOKUP(C36,$AS$15:$AZ$22,8,FALSE()),"")) -> Sell Out | K36: SUL | L36: 26747.07 | M36: 1879.6 | N36: 1964.11 | O36: 2011.44 | P36: 2063.84 | Q36: 2131.45 | R36: 2187.23 | S36: 2271.74 | T36: 2327.52 | U36: 2379.92 | V36: 2439.08 | W36: 2503.31 | X36: 2587.83 | Y36: . | Z36: =SUM(AA36:AL36) -> 13868 | AF36: 2643.25 | AG36: 1678.98 | AH36: 4220.08 | AI36: 2074.89 | AJ36: 2035.8 | AK36: 1215 | AM36: . | AN36: =IF(L36=0,0,Z36/L36) -> 0.5184867 | AO36: =IF(AN36="","",IF(AN36>=0.9,"🟢",IF(AN36>=0.7,"🟡",IF(AN36>=0.5,"🟠","🔴")))) -> 🟠 | AP36: =IF(L36=0,0,L36-Z36) -> 12879.07 | AQ36: =IF(AP36=0,"",RANK(AP36,AP$4:AP$503,0)) -> 40 | AR36: . | AS36: 🔴 VERMELHO 1-40% → Ativação/Positivação | BA36: . | BB36: =SUM(L$4:L$503)/COUNTA(A$4:A$503) -> 9494.3999 | BC36: =SUM(M$4:M$503)/COUNTA(A$4:A$503) -> 667.20008 | BD36: =SUM(N$4:N$503)/COUNTA(A$4:A$503) -> 697.19996 | BE36: =SUM(O$4:O$503)/COUNTA(A$4:A$503) -> 713.9999 | BF36: =SUM(P$4:P$503)/COUNTA(A$4:A$503) -> 732.59984 | BG36: =SUM(Q$4:Q$503)/COUNTA(A$4:A$503) -> 756.59992 | BH36: =SUM(R$4:R$503)/COUNTA(A$4:A$503) -> 776.40004 | BI36: =SUM(S$4:S$503)/COUNTA(A$4:A$503) -> 806.40012 | BJ36: =SUM(T$4:T$503)/COUNTA(A$4:A$503) -> 826.1999 | BK36: =SUM(U$4:U$503)/COUNTA(A$4:A$503) -> 844.8002 | BL36: =SUM(V$4:V$503)/COUNTA(A$4:A$503) -> 865.7998 | BM36: =SUM(W$4:W$503)/COUNTA(A$4:A$503) -> 888.59982 | BN36: =SUM(X$4:X$503)/COUNTA(A$4:A$503) -> 918.60034 | BO36: . | BP36: =IF(Z36>=BB36,0,IFERROR(BB36+(SUMPRODUCT((Z$4:Z$503>=BB$4:BB$503)*(Z$4:Z$503-BB$4:BB$503))/MAX(1,COUNTIF(Z$4:Z$503,"<"&BB36+0.01))),BB36)) -> 0 | BQ36: =IF(AA36>=BC36,0,IFERROR(BC36+SUMPRODUCT((AA$4:AA$503>=BC$4:BC$503)*(AA$4:AA$503-BC$4:BC$503))/MAX(1,COUNTIF(AA$4:AA$503,"<"&BC36+0.01)),BC36)) -> 2238.4659 | BR36: =IF(AB36>=BD36,0,IFERROR(BD36+SUMPRODUCT((AB$4:AB$503>=BD$4:BD$503)*(AB$4:AB$503-BD$4:BD$503))/MAX(1,COUNTIF(AB$4:AB$503,"<"&BD36+0.01)),BD36)) -> 3335.2938 | BS36: =IF(AC36>=BE36,0,IFERROR(BE36+SUMPRODUCT((AC$4:AC$503>=BE$4:BE$503)*(AC$4:AC$503-BE$4:BE$503))/MAX(1,COUNTIF(AC$4:AC$503,"<"&BE36+0.01)),BE36)) -> 6188.7335 | BT36: =IF(AD36>=BF36,0,IFERROR(BF36+SUMPRODUCT((AD$4:AD$503>=BF$4:BF$503)*(AD$4:AD$503-BF$4:BF$503))/MAX(1,COUNTIF(AD$4:AD$503,"<"&BF36+0.01)),BF36)) -> 11354.354 | BU36: =IF(AE36>=BG36,0,IFERROR(BG36+SUMPRODUCT((AE$4:AE$503>=BG$4:BG$503)*(AE$4:AE$503-BG$4:BG$503))/MAX(1,COUNTIF(AE$4:AE$503,"<"&BG36+0.01)),BG36)) -> 7704.8592 | BV36: =IF(AF36>=BH36,0,IFERROR(BH36+SUMPRODUCT((AF$4:AF$503>=BH$4:BH$503)*(AF$4:AF$503-BH$4:BH$503))/MAX(1,COUNTIF(AF$4:AF$503,"<"&BH36+0.01)),BH36)) -> 0 | BW36: =IF(AG36>=BI36,0,IFERROR(BI36+SUMPRODUCT((AG$4:AG$503>=BI$4:BI$503)*(AG$4:AG$503-BI$4:BI$503))/MAX(1,COUNTIF(AG$4:AG$503,"<"&BI36+0.01)),BI36)) -> 0 | BX36: =IF(AH36>=BJ36,0,IFERROR(BJ36+SUMPRODUCT((AH$4:AH$503>=BJ$4:BJ$503)*(AH$4:AH$503-BJ$4:BJ$503))/MAX(1,COUNTIF(AH$4:AH$503,"<"&BJ36+0.01)),BJ36)) -> 0 | ... CB36: =IF(AL36>=BN36,0,IFERROR(BN36+SUMPRODUCT((AL$4:AL$503>=BN$4:BN$503)*(AL$4:AL$503-BN$4:BN$503))/MAX(1,COUNTIF(AL$4:AL$503,"<"&BN36+0.01)),BN36)) -> 3597.2615 | CC36: =IF(AO36="🟢","VERDE",IF(AO36="🟡","AMARELO",IF(AO36="🟠","VERMELHO",IF(AO36="🔴","VERMELHO","ROXO")))) -> VERMELHO | CD36: 🏪 REDES | CE36: FITLAND
A37: 58072623000150 | B37: KLOSTERMANN NUTRICAO LTDA | C37: FITLAND | D37: JULIO GADRET | E37: SC | F37: =IFERROR(VLOOKUP(C37,$AS$3:$AT$10,2,FALSE()),IFERROR(VLOOKUP(C37,$AS$15:$AT$22,2,FALSE()),"")) -> 44 | G37: =IFERROR(VLOOKUP(C37,$AS$3:$AX$10,6,FALSE()),IFERROR(VLOOKUP(C37,$AS$15:$AX$22,6,FALSE()),"")) -> 0.49683951 | H37: =IFERROR(VLOOKUP(C37,$AS$3:$AY$10,7,FALSE()),IFERROR(VLOOKUP(C37,$AS$15:$AY$22,7,FALSE()),"")) -> 🟡 AMARELO | I37: =IFERROR(VLOOKUP(C37,$AS$3:$AZ$10,8,FALSE()),IFERROR(VLOOKUP(C37,$AS$15:$AZ$22,8,FALSE()),"")) -> Sell Out | K37: SUL | L37: 26033.3 | M37: 1829.44 | N37: 1911.7 | O37: 1957.76 | P37: 2008.76 | Q37: 2074.57 | R37: 2128.86 | S37: 2211.12 | T37: 2265.41 | U37: 2316.41 | V37: 2373.99 | W37: 2436.51 | X37: 2518.77 | Y37: . | Z37: =SUM(AA37:AL37) -> 10628.53 | AC37: 2366.06 | AE37: 686.12 | AG37: 1437.64 | AH37: 906.11 | AI37: 2748.6 | AJ37: 2484 | AM37: . | AN37: =IF(L37=0,0,Z37/L37) -> 0.40826672 | AO37: =IF(AN37="","",IF(AN37>=0.9,"🟢",IF(AN37>=0.7,"🟡",IF(AN37>=0.5,"🟠","🔴")))) -> 🔴 | AP37: =IF(L37=0,0,L37-Z37) -> 15404.77 | AQ37: =IF(AP37=0,"",RANK(AP37,AP$4:AP$503,0)) -> 32 | AR37: . | AS37: 🟣 ROXO <1% → Prospecção | BA37: . | BB37: =SUM(L$4:L$503)/COUNTA(A$4:A$503) -> 9494.3999 | BC37: =SUM(M$4:M$503)/COUNTA(A$4:A$503) -> 667.20008 | BD37: =SUM(N$4:N$503)/COUNTA(A$4:A$503) -> 697.19996 | BE37: =SUM(O$4:O$503)/COUNTA(A$4:A$503) -> 713.9999 | BF37: =SUM(P$4:P$503)/COUNTA(A$4:A$503) -> 732.59984 | BG37: =SUM(Q$4:Q$503)/COUNTA(A$4:A$503) -> 756.59992 | BH37: =SUM(R$4:R$503)/COUNTA(A$4:A$503) -> 776.40004 | BI37: =SUM(S$4:S$503)/COUNTA(A$4:A$503) -> 806.40012 | BJ37: =SUM(T$4:T$503)/COUNTA(A$4:A$503) -> 826.1999 | BK37: =SUM(U$4:U$503)/COUNTA(A$4:A$503) -> 844.8002 | BL37: =SUM(V$4:V$503)/COUNTA(A$4:A$503) -> 865.7998 | BM37: =SUM(W$4:W$503)/COUNTA(A$4:A$503) -> 888.59982 | BN37: =SUM(X$4:X$503)/COUNTA(A$4:A$503) -> 918.60034 | BO37: . | BP37: =IF(Z37>=BB37,0,IFERROR(BB37+(SUMPRODUCT((Z$4:Z$503>=BB$4:BB$503)*(Z$4:Z$503-BB$4:BB$503))/MAX(1,COUNTIF(Z$4:Z$503,"<"&BB37+0.01))),BB37)) -> 0 | BQ37: =IF(AA37>=BC37,0,IFERROR(BC37+SUMPRODUCT((AA$4:AA$503>=BC$4:BC$503)*(AA$4:AA$503-BC$4:BC$503))/MAX(1,COUNTIF(AA$4:AA$503,"<"&BC37+0.01)),BC37)) -> 2238.4659 | BR37: =IF(AB37>=BD37,0,IFERROR(BD37+SUMPRODUCT((AB$4:AB$503>=BD$4:BD$503)*(AB$4:AB$503-BD$4:BD$503))/MAX(1,COUNTIF(AB$4:AB$503,"<"&BD37+0.01)),BD37)) -> 3335.2938 | BS37: =IF(AC37>=BE37,0,IFERROR(BE37+SUMPRODUCT((AC$4:AC$503>=BE$4:BE$503)*(AC$4:AC$503-BE$4:BE$503))/MAX(1,COUNTIF(AC$4:AC$503,"<"&BE37+0.01)),BE37)) -> 0 | BT37: =IF(AD37>=BF37,0,IFERROR(BF37+SUMPRODUCT((AD$4:AD$503>=BF$4:BF$503)*(AD$4:AD$503-BF$4:BF$503))/MAX(1,COUNTIF(AD$4:AD$503,"<"&BF37+0.01)),BF37)) -> 11354.354 | BU37: =IF(AE37>=BG37,0,IFERROR(BG37+SUMPRODUCT((AE$4:AE$503>=BG$4:BG$503)*(AE$4:AE$503-BG$4:BG$503))/MAX(1,COUNTIF(AE$4:AE$503,"<"&BG37+0.01)),BG37)) -> 7704.8592 | BV37: =IF(AF37>=BH37,0,IFERROR(BH37+SUMPRODUCT((AF$4:AF$503>=BH$4:BH$503)*(AF$4:AF$503-BH$4:BH$503))/MAX(1,COUNTIF(AF$4:AF$503,"<"&BH37+0.01)),BH37)) -> 9942.6504 | BW37: =IF(AG37>=BI37,0,IFERROR(BI37+SUMPRODUCT((AG$4:AG$503>=BI$4:BI$503)*(AG$4:AG$503-BI$4:BI$503))/MAX(1,COUNTIF(AG$4:AG$503,"<"&BI37+0.01)),BI37)) -> 0 | BX37: =IF(AH37>=BJ37,0,IFERROR(BJ37+SUMPRODUCT((AH$4:AH$503>=BJ$4:BJ$503)*(AH$4:AH$503-BJ$4:BJ$503))/MAX(1,COUNTIF(AH$4:AH$503,"<"&BJ37+0.01)),BJ37)) -> 0 | ... CB37: =IF(AL37>=BN37,0,IFERROR(BN37+SUMPRODUCT((AL$4:AL$503>=BN$4:BN$503)*(AL$4:AL$503-BN$4:BN$503))/MAX(1,COUNTIF(AL$4:AL$503,"<"&BN37+0.01)),BN37)) -> 3597.2615 | CC37: =IF(AO37="🟢","VERDE",IF(AO37="🟡","AMARELO",IF(AO37="🟠","VERMELHO",IF(AO37="🔴","VERMELHO","ROXO")))) -> VERMELHO | CD37: 🏪 REDES | CE37: FITLAND
A38: 40917018000177 | B38: EPC PRODUTOS NATURAIS E SUPLEMENTACAO LT | C38: FITLAND | D38: JULIO GADRET | E38: SC | F38: =IFERROR(VLOOKUP(C38,$AS$3:$AT$10,2,FALSE()),IFERROR(VLOOKUP(C38,$AS$15:$AT$22,2,FALSE()),"")) -> 44 | G38: =IFERROR(VLOOKUP(C38,$AS$3:$AX$10,6,FALSE()),IFERROR(VLOOKUP(C38,$AS$15:$AX$22,6,FALSE()),"")) -> 0.49683951 | H38: =IFERROR(VLOOKUP(C38,$AS$3:$AY$10,7,FALSE()),IFERROR(VLOOKUP(C38,$AS$15:$AY$22,7,FALSE()),"")) -> 🟡 AMARELO | I38: =IFERROR(VLOOKUP(C38,$AS$3:$AZ$10,8,FALSE()),IFERROR(VLOOKUP(C38,$AS$15:$AZ$22,8,FALSE()),"")) -> Sell Out | K38: SUL | L38: 25876 | M38: 1818.38 | N38: 1900.15 | O38: 1945.93 | P38: 1996.63 | Q38: 2062.03 | R38: 2116 | S38: 2197.76 | T38: 2251.72 | U38: 2302.41 | V38: 2359.65 | W38: 2421.79 | X38: 2503.55 | Y38: . | Z38: =SUM(AA38:AL38) -> 10742.12 | AF38: 2643.25 | AG38: 1867.12 | AH38: 2176.64 | AI38: 1347.96 | AJ38: 1558.71 | AL38: 1148.44 | AM38: . | AN38: =IF(L38=0,0,Z38/L38) -> 0.41513835 | AO38: =IF(AN38="","",IF(AN38>=0.9,"🟢",IF(AN38>=0.7,"🟡",IF(AN38>=0.5,"🟠","🔴")))) -> 🔴 | AP38: =IF(L38=0,0,L38-Z38) -> 15133.88 | AQ38: =IF(AP38=0,"",RANK(AP38,AP$4:AP$503,0)) -> 33 | AR38: . | BA38: . | BB38: =SUM(L$4:L$503)/COUNTA(A$4:A$503) -> 9494.3999 | BC38: =SUM(M$4:M$503)/COUNTA(A$4:A$503) -> 667.20008 | BD38: =SUM(N$4:N$503)/COUNTA(A$4:A$503) -> 697.19996 | BE38: =SUM(O$4:O$503)/COUNTA(A$4:A$503) -> 713.9999 | BF38: =SUM(P$4:P$503)/COUNTA(A$4:A$503) -> 732.59984 | BG38: =SUM(Q$4:Q$503)/COUNTA(A$4:A$503) -> 756.59992 | BH38: =SUM(R$4:R$503)/COUNTA(A$4:A$503) -> 776.40004 | BI38: =SUM(S$4:S$503)/COUNTA(A$4:A$503) -> 806.40012 | BJ38: =SUM(T$4:T$503)/COUNTA(A$4:A$503) -> 826.1999 | BK38: =SUM(U$4:U$503)/COUNTA(A$4:A$503) -> 844.8002 | BL38: =SUM(V$4:V$503)/COUNTA(A$4:A$503) -> 865.7998 | BM38: =SUM(W$4:W$503)/COUNTA(A$4:A$503) -> 888.59982 | BN38: =SUM(X$4:X$503)/COUNTA(A$4:A$503) -> 918.60034 | BO38: . | BP38: =IF(Z38>=BB38,0,IFERROR(BB38+(SUMPRODUCT((Z$4:Z$503>=BB$4:BB$503)*(Z$4:Z$503-BB$4:BB$503))/MAX(1,COUNTIF(Z$4:Z$503,"<"&BB38+0.01))),BB38)) -> 0 | BQ38: =IF(AA38>=BC38,0,IFERROR(BC38+SUMPRODUCT((AA$4:AA$503>=BC$4:BC$503)*(AA$4:AA$503-BC$4:BC$503))/MAX(1,COUNTIF(AA$4:AA$503,"<"&BC38+0.01)),BC38)) -> 2238.4659 | BR38: =IF(AB38>=BD38,0,IFERROR(BD38+SUMPRODUCT((AB$4:AB$503>=BD$4:BD$503)*(AB$4:AB$503-BD$4:BD$503))/MAX(1,COUNTIF(AB$4:AB$503,"<"&BD38+0.01)),BD38)) -> 3335.2938 | BS38: =IF(AC38>=BE38,0,IFERROR(BE38+SUMPRODUCT((AC$4:AC$503>=BE$4:BE$503)*(AC$4:AC$503-BE$4:BE$503))/MAX(1,COUNTIF(AC$4:AC$503,"<"&BE38+0.01)),BE38)) -> 6188.7335 | BT38: =IF(AD38>=BF38,0,IFERROR(BF38+SUMPRODUCT((AD$4:AD$503>=BF$4:BF$503)*(AD$4:AD$503-BF$4:BF$503))/MAX(1,COUNTIF(AD$4:AD$503,"<"&BF38+0.01)),BF38)) -> 11354.354 | BU38: =IF(AE38>=BG38,0,IFERROR(BG38+SUMPRODUCT((AE$4:AE$503>=BG$4:BG$503)*(AE$4:AE$503-BG$4:BG$503))/MAX(1,COUNTIF(AE$4:AE$503,"<"&BG38+0.01)),BG38)) -> 7704.8592 | BV38: =IF(AF38>=BH38,0,IFERROR(BH38+SUMPRODUCT((AF$4:AF$503>=BH$4:BH$503)*(AF$4:AF$503-BH$4:BH$503))/MAX(1,COUNTIF(AF$4:AF$503,"<"&BH38+0.01)),BH38)) -> 0 | BW38: =IF(AG38>=BI38,0,IFERROR(BI38+SUMPRODUCT((AG$4:AG$503>=BI$4:BI$503)*(AG$4:AG$503-BI$4:BI$503))/MAX(1,COUNTIF(AG$4:AG$503,"<"&BI38+0.01)),BI38)) -> 0 | BX38: =IF(AH38>=BJ38,0,IFERROR(BJ38+SUMPRODUCT((AH$4:AH$503>=BJ$4:BJ$503)*(AH$4:AH$503-BJ$4:BJ$503))/MAX(1,COUNTIF(AH$4:AH$503,"<"&BJ38+0.01)),BJ38)) -> 0 | ... CB38: =IF(AL38>=BN38,0,IFERROR(BN38+SUMPRODUCT((AL$4:AL$503>=BN$4:BN$503)*(AL$4:AL$503-BN$4:BN$503))/MAX(1,COUNTIF(AL$4:AL$503,"<"&BN38+0.01)),BN38)) -> 0 | CC38: =IF(AO38="🟢","VERDE",IF(AO38="🟡","AMARELO",IF(AO38="🟠","VERMELHO",IF(AO38="🔴","VERMELHO","ROXO")))) -> VERMELHO | CD38: 🏪 REDES | CE38: FITLAND
A39: 53304073000133 | B39: ECAMP PRODUTOS NATURAIS E SUPLEMENTOS LT | C39: FITLAND | D39: JULIO GADRET | E39: SC | F39: =IFERROR(VLOOKUP(C39,$AS$3:$AT$10,2,FALSE()),IFERROR(VLOOKUP(C39,$AS$15:$AT$22,2,FALSE()),"")) -> 44 | G39: =IFERROR(VLOOKUP(C39,$AS$3:$AX$10,6,FALSE()),IFERROR(VLOOKUP(C39,$AS$15:$AX$22,6,FALSE()),"")) -> 0.49683951 | H39: =IFERROR(VLOOKUP(C39,$AS$3:$AY$10,7,FALSE()),IFERROR(VLOOKUP(C39,$AS$15:$AY$22,7,FALSE()),"")) -> 🟡 AMARELO | I39: =IFERROR(VLOOKUP(C39,$AS$3:$AZ$10,8,FALSE()),IFERROR(VLOOKUP(C39,$AS$15:$AZ$22,8,FALSE()),"")) -> Sell Out | K39: SUL | L39: 25584.22 | M39: 1797.88 | N39: 1878.72 | O39: 1923.99 | P39: 1974.11 | Q39: 2038.78 | R39: 2092.14 | S39: 2172.98 | T39: 2226.33 | U39: 2276.45 | V39: 2333.04 | W39: 2394.48 | X39: 2475.32 | Y39: . | Z39: =SUM(AA39:AL39) -> 10545.53 | AA39: 384.07 | AF39: 2643.25 | AG39: 3899.13 | AJ39: 1886.58 | AL39: 1732.5 | AM39: . | AN39: =IF(L39=0,0,Z39/L39) -> 0.41218884 | AO39: =IF(AN39="","",IF(AN39>=0.9,"🟢",IF(AN39>=0.7,"🟡",IF(AN39>=0.5,"🟠","🔴")))) -> 🔴 | AP39: =IF(L39=0,0,L39-Z39) -> 15038.69 | AQ39: =IF(AP39=0,"",RANK(AP39,AP$4:AP$503,0)) -> 34 | AR39: . | AS39: SINALEIRO % = FAT REAL ÷ META SAP | BA39: . | BB39: =SUM(L$4:L$503)/COUNTA(A$4:A$503) -> 9494.3999 | BC39: =SUM(M$4:M$503)/COUNTA(A$4:A$503) -> 667.20008 | BD39: =SUM(N$4:N$503)/COUNTA(A$4:A$503) -> 697.19996 | BE39: =SUM(O$4:O$503)/COUNTA(A$4:A$503) -> 713.9999 | BF39: =SUM(P$4:P$503)/COUNTA(A$4:A$503) -> 732.59984 | BG39: =SUM(Q$4:Q$503)/COUNTA(A$4:A$503) -> 756.59992 | BH39: =SUM(R$4:R$503)/COUNTA(A$4:A$503) -> 776.40004 | BI39: =SUM(S$4:S$503)/COUNTA(A$4:A$503) -> 806.40012 | BJ39: =SUM(T$4:T$503)/COUNTA(A$4:A$503) -> 826.1999 | BK39: =SUM(U$4:U$503)/COUNTA(A$4:A$503) -> 844.8002 | BL39: =SUM(V$4:V$503)/COUNTA(A$4:A$503) -> 865.7998 | BM39: =SUM(W$4:W$503)/COUNTA(A$4:A$503) -> 888.59982 | BN39: =SUM(X$4:X$503)/COUNTA(A$4:A$503) -> 918.60034 | BO39: . | BP39: =IF(Z39>=BB39,0,IFERROR(BB39+(SUMPRODUCT((Z$4:Z$503>=BB$4:BB$503)*(Z$4:Z$503-BB$4:BB$503))/MAX(1,COUNTIF(Z$4:Z$503,"<"&BB39+0.01))),BB39)) -> 0 | BQ39: =IF(AA39>=BC39,0,IFERROR(BC39+SUMPRODUCT((AA$4:AA$503>=BC$4:BC$503)*(AA$4:AA$503-BC$4:BC$503))/MAX(1,COUNTIF(AA$4:AA$503,"<"&BC39+0.01)),BC39)) -> 2238.4659 | BR39: =IF(AB39>=BD39,0,IFERROR(BD39+SUMPRODUCT((AB$4:AB$503>=BD$4:BD$503)*(AB$4:AB$503-BD$4:BD$503))/MAX(1,COUNTIF(AB$4:AB$503,"<"&BD39+0.01)),BD39)) -> 3335.2938 | BS39: =IF(AC39>=BE39,0,IFERROR(BE39+SUMPRODUCT((AC$4:AC$503>=BE$4:BE$503)*(AC$4:AC$503-BE$4:BE$503))/MAX(1,COUNTIF(AC$4:AC$503,"<"&BE39+0.01)),BE39)) -> 6188.7335 | BT39: =IF(AD39>=BF39,0,IFERROR(BF39+SUMPRODUCT((AD$4:AD$503>=BF$4:BF$503)*(AD$4:AD$503-BF$4:BF$503))/MAX(1,COUNTIF(AD$4:AD$503,"<"&BF39+0.01)),BF39)) -> 11354.354 | BU39: =IF(AE39>=BG39,0,IFERROR(BG39+SUMPRODUCT((AE$4:AE$503>=BG$4:BG$503)*(AE$4:AE$503-BG$4:BG$503))/MAX(1,COUNTIF(AE$4:AE$503,"<"&BG39+0.01)),BG39)) -> 7704.8592 | BV39: =IF(AF39>=BH39,0,IFERROR(BH39+SUMPRODUCT((AF$4:AF$503>=BH$4:BH$503)*(AF$4:AF$503-BH$4:BH$503))/MAX(1,COUNTIF(AF$4:AF$503,"<"&BH39+0.01)),BH39)) -> 0 | BW39: =IF(AG39>=BI39,0,IFERROR(BI39+SUMPRODUCT((AG$4:AG$503>=BI$4:BI$503)*(AG$4:AG$503-BI$4:BI$503))/MAX(1,COUNTIF(AG$4:AG$503,"<"&BI39+0.01)),BI39)) -> 0 | BX39: =IF(AH39>=BJ39,0,IFERROR(BJ39+SUMPRODUCT((AH$4:AH$503>=BJ$4:BJ$503)*(AH$4:AH$503-BJ$4:BJ$503))/MAX(1,COUNTIF(AH$4:AH$503,"<"&BJ39+0.01)),BJ39)) -> 5621.5026 | ... CB39: =IF(AL39>=BN39,0,IFERROR(BN39+SUMPRODUCT((AL$4:AL$503>=BN$4:BN$503)*(AL$4:AL$503-BN$4:BN$503))/MAX(1,COUNTIF(AL$4:AL$503,"<"&BN39+0.01)),BN39)) -> 0 | CC39: =IF(AO39="🟢","VERDE",IF(AO39="🟡","AMARELO",IF(AO39="🟠","VERMELHO",IF(AO39="🔴","VERMELHO","ROXO")))) -> VERMELHO | CD39: 🏪 REDES | CE39: FITLAND
A40: 76726884000128 | B40: INSTITUICAO ADVENTISTA SUL BRASILEIRA DE | C40: SUL | D40: HEMANUELE DITZEL (MANU) | E40: PR | F40: =IFERROR(VLOOKUP(C40,$AS$3:$AT$10,2,FALSE()),IFERROR(VLOOKUP(C40,$AS$15:$AT$22,2,FALSE()),"")) -> 132 | G40: =IFERROR(VLOOKUP(C40,$AS$3:$AX$10,6,FALSE()),IFERROR(VLOOKUP(C40,$AS$15:$AX$22,6,FALSE()),"")) -> 0.46819018 | H40: =IFERROR(VLOOKUP(C40,$AS$3:$AY$10,7,FALSE()),IFERROR(VLOOKUP(C40,$AS$15:$AY$22,7,FALSE()),"")) -> 🟡 AMARELO | I40: =IFERROR(VLOOKUP(C40,$AS$3:$AZ$10,8,FALSE()),IFERROR(VLOOKUP(C40,$AS$15:$AZ$22,8,FALSE()),"")) -> Sell Out | K40: SUL | L40: 25437.01 | M40: 1787.54 | N40: 1867.91 | O40: 1912.92 | P40: 1962.75 | Q40: 2027.05 | R40: 2080.1 | S40: 2160.47 | T40: 2213.52 | U40: 2263.35 | V40: 2319.62 | W40: 2380.7 | X40: 2461.08 | Y40: . | Z40: =SUM(AA40:AL40) -> 11207.98 | AB40: 5053.32 | AD40: 5176.2 | AL40: 978.46 | AM40: . | AN40: =IF(L40=0,0,Z40/L40) -> 0.44061704 | AO40: =IF(AN40="","",IF(AN40>=0.9,"🟢",IF(AN40>=0.7,"🟡",IF(AN40>=0.5,"🟠","🔴")))) -> 🔴 | AP40: =IF(L40=0,0,L40-Z40) -> 14229.03 | AQ40: =IF(AP40=0,"",RANK(AP40,AP$4:AP$503,0)) -> 36 | AR40: . | AS40: Todas as fórmulas são dinâmicas (COUNTIF/SUMIF) | BA40: . | BB40: =SUM(L$4:L$503)/COUNTA(A$4:A$503) -> 9494.3999 | BC40: =SUM(M$4:M$503)/COUNTA(A$4:A$503) -> 667.20008 | BD40: =SUM(N$4:N$503)/COUNTA(A$4:A$503) -> 697.19996 | BE40: =SUM(O$4:O$503)/COUNTA(A$4:A$503) -> 713.9999 | BF40: =SUM(P$4:P$503)/COUNTA(A$4:A$503) -> 732.59984 | BG40: =SUM(Q$4:Q$503)/COUNTA(A$4:A$503) -> 756.59992 | BH40: =SUM(R$4:R$503)/COUNTA(A$4:A$503) -> 776.40004 | BI40: =SUM(S$4:S$503)/COUNTA(A$4:A$503) -> 806.40012 | BJ40: =SUM(T$4:T$503)/COUNTA(A$4:A$503) -> 826.1999 | BK40: =SUM(U$4:U$503)/COUNTA(A$4:A$503) -> 844.8002 | BL40: =SUM(V$4:V$503)/COUNTA(A$4:A$503) -> 865.7998 | BM40: =SUM(W$4:W$503)/COUNTA(A$4:A$503) -> 888.59982 | BN40: =SUM(X$4:X$503)/COUNTA(A$4:A$503) -> 918.60034 | BO40: . | BP40: =IF(Z40>=BB40,0,IFERROR(BB40+(SUMPRODUCT((Z$4:Z$503>=BB$4:BB$503)*(Z$4:Z$503-BB$4:BB$503))/MAX(1,COUNTIF(Z$4:Z$503,"<"&BB40+0.01))),BB40)) -> 0 | BQ40: =IF(AA40>=BC40,0,IFERROR(BC40+SUMPRODUCT((AA$4:AA$503>=BC$4:BC$503)*(AA$4:AA$503-BC$4:BC$503))/MAX(1,COUNTIF(AA$4:AA$503,"<"&BC40+0.01)),BC40)) -> 2238.4659 | BR40: =IF(AB40>=BD40,0,IFERROR(BD40+SUMPRODUCT((AB$4:AB$503>=BD$4:BD$503)*(AB$4:AB$503-BD$4:BD$503))/MAX(1,COUNTIF(AB$4:AB$503,"<"&BD40+0.01)),BD40)) -> 0 | BS40: =IF(AC40>=BE40,0,IFERROR(BE40+SUMPRODUCT((AC$4:AC$503>=BE$4:BE$503)*(AC$4:AC$503-BE$4:BE$503))/MAX(1,COUNTIF(AC$4:AC$503,"<"&BE40+0.01)),BE40)) -> 6188.7335 | BT40: =IF(AD40>=BF40,0,IFERROR(BF40+SUMPRODUCT((AD$4:AD$503>=BF$4:BF$503)*(AD$4:AD$503-BF$4:BF$503))/MAX(1,COUNTIF(AD$4:AD$503,"<"&BF40+0.01)),BF40)) -> 0 | BU40: =IF(AE40>=BG40,0,IFERROR(BG40+SUMPRODUCT((AE$4:AE$503>=BG$4:BG$503)*(AE$4:AE$503-BG$4:BG$503))/MAX(1,COUNTIF(AE$4:AE$503,"<"&BG40+0.01)),BG40)) -> 7704.8592 | BV40: =IF(AF40>=BH40,0,IFERROR(BH40+SUMPRODUCT((AF$4:AF$503>=BH$4:BH$503)*(AF$4:AF$503-BH$4:BH$503))/MAX(1,COUNTIF(AF$4:AF$503,"<"&BH40+0.01)),BH40)) -> 9942.6504 | BW40: =IF(AG40>=BI40,0,IFERROR(BI40+SUMPRODUCT((AG$4:AG$503>=BI$4:BI$503)*(AG$4:AG$503-BI$4:BI$503))/MAX(1,COUNTIF(AG$4:AG$503,"<"&BI40+0.01)),BI40)) -> 9142.1587 | BX40: =IF(AH40>=BJ40,0,IFERROR(BJ40+SUMPRODUCT((AH$4:AH$503>=BJ$4:BJ$503)*(AH$4:AH$503-BJ$4:BJ$503))/MAX(1,COUNTIF(AH$4:AH$503,"<"&BJ40+0.01)),BJ40)) -> 5621.5026 | ... CB40: =IF(AL40>=BN40,0,IFERROR(BN40+SUMPRODUCT((AL$4:AL$503>=BN$4:BN$503)*(AL$4:AL$503-BN$4:BN$503))/MAX(1,COUNTIF(AL$4:AL$503,"<"&BN40+0.01)),BN40)) -> 0 | CC40: =IF(AO40="🟢","VERDE",IF(AO40="🟡","AMARELO",IF(AO40="🟠","VERMELHO",IF(AO40="🔴","VERMELHO","ROXO")))) -> VERMELHO | CD40: 🌎 REGIÕES | CE40: SEM REDE
A41: 55699460000141 | B41: AGRANOLLA GRAOS DE SAUDE LTDA - ME | C41: RJ + ES + MG | D41: LARISSA PADILHA | E41: MG | F41: =IFERROR(VLOOKUP(C41,$AS$3:$AT$10,2,FALSE()),IFERROR(VLOOKUP(C41,$AS$15:$AT$22,2,FALSE()),"")) -> 49 | G41: =IFERROR(VLOOKUP(C41,$AS$3:$AX$10,6,FALSE()),IFERROR(VLOOKUP(C41,$AS$15:$AX$22,6,FALSE()),"")) -> 0.46396509 | H41: =IFERROR(VLOOKUP(C41,$AS$3:$AY$10,7,FALSE()),IFERROR(VLOOKUP(C41,$AS$15:$AY$22,7,FALSE()),"")) -> 🟡 AMARELO | I41: =IFERROR(VLOOKUP(C41,$AS$3:$AZ$10,8,FALSE()),IFERROR(VLOOKUP(C41,$AS$15:$AZ$22,8,FALSE()),"")) -> Sell Out | K41: RJ + ES + MG | L41: 24833.31 | M41: 1745.11 | N41: 1823.58 | O41: 1867.52 | P41: 1916.17 | Q41: 1978.94 | R41: 2030.73 | S41: 2109.2 | T41: 2160.99 | U41: 2209.64 | V41: 2264.56 | W41: 2324.2 | X41: 2402.67 | Y41: . | Z41: =SUM(AA41:AL41) -> 11312.87 | AK41: 5953.14 | AL41: 5359.73 | AM41: . | AN41: =IF(L41=0,0,Z41/L41) -> 0.45555224 | AO41: =IF(AN41="","",IF(AN41>=0.9,"🟢",IF(AN41>=0.7,"🟡",IF(AN41>=0.5,"🟠","🔴")))) -> 🔴 | AP41: =IF(L41=0,0,L41-Z41) -> 13520.44 | AQ41: =IF(AP41=0,"",RANK(AP41,AP$4:AP$503,0)) -> 38 | AR41: . | AS41: Atualiza automaticamente conforme entra faturamento | BA41: . | BB41: =SUM(L$4:L$503)/COUNTA(A$4:A$503) -> 9494.3999 | BC41: =SUM(M$4:M$503)/COUNTA(A$4:A$503) -> 667.20008 | BD41: =SUM(N$4:N$503)/COUNTA(A$4:A$503) -> 697.19996 | BE41: =SUM(O$4:O$503)/COUNTA(A$4:A$503) -> 713.9999 | BF41: =SUM(P$4:P$503)/COUNTA(A$4:A$503) -> 732.59984 | BG41: =SUM(Q$4:Q$503)/COUNTA(A$4:A$503) -> 756.59992 | BH41: =SUM(R$4:R$503)/COUNTA(A$4:A$503) -> 776.40004 | BI41: =SUM(S$4:S$503)/COUNTA(A$4:A$503) -> 806.40012 | BJ41: =SUM(T$4:T$503)/COUNTA(A$4:A$503) -> 826.1999 | BK41: =SUM(U$4:U$503)/COUNTA(A$4:A$503) -> 844.8002 | BL41: =SUM(V$4:V$503)/COUNTA(A$4:A$503) -> 865.7998 | BM41: =SUM(W$4:W$503)/COUNTA(A$4:A$503) -> 888.59982 | BN41: =SUM(X$4:X$503)/COUNTA(A$4:A$503) -> 918.60034 | BO41: . | BP41: =IF(Z41>=BB41,0,IFERROR(BB41+(SUMPRODUCT((Z$4:Z$503>=BB$4:BB$503)*(Z$4:Z$503-BB$4:BB$503))/MAX(1,COUNTIF(Z$4:Z$503,"<"&BB41+0.01))),BB41)) -> 0 | BQ41: =IF(AA41>=BC41,0,IFERROR(BC41+SUMPRODUCT((AA$4:AA$503>=BC$4:BC$503)*(AA$4:AA$503-BC$4:BC$503))/MAX(1,COUNTIF(AA$4:AA$503,"<"&BC41+0.01)),BC41)) -> 2238.4659 | BR41: =IF(AB41>=BD41,0,IFERROR(BD41+SUMPRODUCT((AB$4:AB$503>=BD$4:BD$503)*(AB$4:AB$503-BD$4:BD$503))/MAX(1,COUNTIF(AB$4:AB$503,"<"&BD41+0.01)),BD41)) -> 3335.2938 | BS41: =IF(AC41>=BE41,0,IFERROR(BE41+SUMPRODUCT((AC$4:AC$503>=BE$4:BE$503)*(AC$4:AC$503-BE$4:BE$503))/MAX(1,COUNTIF(AC$4:AC$503,"<"&BE41+0.01)),BE41)) -> 6188.7335 | BT41: =IF(AD41>=BF41,0,IFERROR(BF41+SUMPRODUCT((AD$4:AD$503>=BF$4:BF$503)*(AD$4:AD$503-BF$4:BF$503))/MAX(1,COUNTIF(AD$4:AD$503,"<"&BF41+0.01)),BF41)) -> 11354.354 | BU41: =IF(AE41>=BG41,0,IFERROR(BG41+SUMPRODUCT((AE$4:AE$503>=BG$4:BG$503)*(AE$4:AE$503-BG$4:BG$503))/MAX(1,COUNTIF(AE$4:AE$503,"<"&BG41+0.01)),BG41)) -> 7704.8592 | BV41: =IF(AF41>=BH41,0,IFERROR(BH41+SUMPRODUCT((AF$4:AF$503>=BH$4:BH$503)*(AF$4:AF$503-BH$4:BH$503))/MAX(1,COUNTIF(AF$4:AF$503,"<"&BH41+0.01)),BH41)) -> 9942.6504 | BW41: =IF(AG41>=BI41,0,IFERROR(BI41+SUMPRODUCT((AG$4:AG$503>=BI$4:BI$503)*(AG$4:AG$503-BI$4:BI$503))/MAX(1,COUNTIF(AG$4:AG$503,"<"&BI41+0.01)),BI41)) -> 9142.1587 | BX41: =IF(AH41>=BJ41,0,IFERROR(BJ41+SUMPRODUCT((AH$4:AH$503>=BJ$4:BJ$503)*(AH$4:AH$503-BJ$4:BJ$503))/MAX(1,COUNTIF(AH$4:AH$503,"<"&BJ41+0.01)),BJ41)) -> 5621.5026 | ... CB41: =IF(AL41>=BN41,0,IFERROR(BN41+SUMPRODUCT((AL$4:AL$503>=BN$4:BN$503)*(AL$4:AL$503-BN$4:BN$503))/MAX(1,COUNTIF(AL$4:AL$503,"<"&BN41+0.01)),BN41)) -> 0 | CC41: =IF(AO41="🟢","VERDE",IF(AO41="🟡","AMARELO",IF(AO41="🟠","VERMELHO",IF(AO41="🔴","VERMELHO","ROXO")))) -> VERMELHO | CD41: 🌎 REGIÕES | CE41: SEM REDE
A42: 41069473000122 | B42: MERCADO FIT & GRANEL PRODUTOS NATURAIS L | C42: RJ + ES + MG | D42: LARISSA PADILHA | E42: MG | F42: =IFERROR(VLOOKUP(C42,$AS$3:$AT$10,2,FALSE()),IFERROR(VLOOKUP(C42,$AS$15:$AT$22,2,FALSE()),"")) -> 49 | G42: =IFERROR(VLOOKUP(C42,$AS$3:$AX$10,6,FALSE()),IFERROR(VLOOKUP(C42,$AS$15:$AX$22,6,FALSE()),"")) -> 0.46396509 | H42: =IFERROR(VLOOKUP(C42,$AS$3:$AY$10,7,FALSE()),IFERROR(VLOOKUP(C42,$AS$15:$AY$22,7,FALSE()),"")) -> 🟡 AMARELO | I42: =IFERROR(VLOOKUP(C42,$AS$3:$AZ$10,8,FALSE()),IFERROR(VLOOKUP(C42,$AS$15:$AZ$22,8,FALSE()),"")) -> Sell Out | K42: RJ + ES + MG | L42: 24609.98 | M42: 1729.42 | N42: 1807.18 | O42: 1850.72 | P42: 1898.94 | Q42: 1961.15 | R42: 2012.47 | S42: 2090.23 | T42: 2141.55 | U42: 2189.76 | V42: 2244.2 | W42: 2303.3 | X42: 2381.06 | Y42: . | Z42: =SUM(AA42:AL42) -> 12725.16 | AE42: 1769.43 | AF42: 1656.12 | AG42: 3274.26 | AH42: 2426.28 | AI42: 1680.08 | AL42: 1918.99 | AM42: . | AN42: =IF(L42=0,0,Z42/L42) -> 0.51707315 | AO42: =IF(AN42="","",IF(AN42>=0.9,"🟢",IF(AN42>=0.7,"🟡",IF(AN42>=0.5,"🟠","🔴")))) -> 🟠 | AP42: =IF(L42=0,0,L42-Z42) -> 11884.82 | AQ42: =IF(AP42=0,"",RANK(AP42,AP$4:AP$503,0)) -> 47 | AR42: . | BA42: . | BB42: =SUM(L$4:L$503)/COUNTA(A$4:A$503) -> 9494.3999 | BC42: =SUM(M$4:M$503)/COUNTA(A$4:A$503) -> 667.20008 | BD42: =SUM(N$4:N$503)/COUNTA(A$4:A$503) -> 697.19996 | BE42: =SUM(O$4:O$503)/COUNTA(A$4:A$503) -> 713.9999 | BF42: =SUM(P$4:P$503)/COUNTA(A$4:A$503) -> 732.59984 | BG42: =SUM(Q$4:Q$503)/COUNTA(A$4:A$503) -> 756.59992 | BH42: =SUM(R$4:R$503)/COUNTA(A$4:A$503) -> 776.40004 | BI42: =SUM(S$4:S$503)/COUNTA(A$4:A$503) -> 806.40012 | BJ42: =SUM(T$4:T$503)/COUNTA(A$4:A$503) -> 826.1999 | BK42: =SUM(U$4:U$503)/COUNTA(A$4:A$503) -> 844.8002 | BL42: =SUM(V$4:V$503)/COUNTA(A$4:A$503) -> 865.7998 | BM42: =SUM(W$4:W$503)/COUNTA(A$4:A$503) -> 888.59982 | BN42: =SUM(X$4:X$503)/COUNTA(A$4:A$503) -> 918.60034 | BO42: . | BP42: =IF(Z42>=BB42,0,IFERROR(BB42+(SUMPRODUCT((Z$4:Z$503>=BB$4:BB$503)*(Z$4:Z$503-BB$4:BB$503))/MAX(1,COUNTIF(Z$4:Z$503,"<"&BB42+0.01))),BB42)) -> 0 | BQ42: =IF(AA42>=BC42,0,IFERROR(BC42+SUMPRODUCT((AA$4:AA$503>=BC$4:BC$503)*(AA$4:AA$503-BC$4:BC$503))/MAX(1,COUNTIF(AA$4:AA$503,"<"&BC42+0.01)),BC42)) -> 2238.4659 | BR42: =IF(AB42>=BD42,0,IFERROR(BD42+SUMPRODUCT((AB$4:AB$503>=BD$4:BD$503)*(AB$4:AB$503-BD$4:BD$503))/MAX(1,COUNTIF(AB$4:AB$503,"<"&BD42+0.01)),BD42)) -> 3335.2938 | BS42: =IF(AC42>=BE42,0,IFERROR(BE42+SUMPRODUCT((AC$4:AC$503>=BE$4:BE$503)*(AC$4:AC$503-BE$4:BE$503))/MAX(1,COUNTIF(AC$4:AC$503,"<"&BE42+0.01)),BE42)) -> 6188.7335 | BT42: =IF(AD42>=BF42,0,IFERROR(BF42+SUMPRODUCT((AD$4:AD$503>=BF$4:BF$503)*(AD$4:AD$503-BF$4:BF$503))/MAX(1,COUNTIF(AD$4:AD$503,"<"&BF42+0.01)),BF42)) -> 11354.354 | BU42: =IF(AE42>=BG42,0,IFERROR(BG42+SUMPRODUCT((AE$4:AE$503>=BG$4:BG$503)*(AE$4:AE$503-BG$4:BG$503))/MAX(1,COUNTIF(AE$4:AE$503,"<"&BG42+0.01)),BG42)) -> 0 | BV42: =IF(AF42>=BH42,0,IFERROR(BH42+SUMPRODUCT((AF$4:AF$503>=BH$4:BH$503)*(AF$4:AF$503-BH$4:BH$503))/MAX(1,COUNTIF(AF$4:AF$503,"<"&BH42+0.01)),BH42)) -> 0 | BW42: =IF(AG42>=BI42,0,IFERROR(BI42+SUMPRODUCT((AG$4:AG$503>=BI$4:BI$503)*(AG$4:AG$503-BI$4:BI$503))/MAX(1,COUNTIF(AG$4:AG$503,"<"&BI42+0.01)),BI42)) -> 0 | BX42: =IF(AH42>=BJ42,0,IFERROR(BJ42+SUMPRODUCT((AH$4:AH$503>=BJ$4:BJ$503)*(AH$4:AH$503-BJ$4:BJ$503))/MAX(1,COUNTIF(AH$4:AH$503,"<"&BJ42+0.01)),BJ42)) -> 0 | ... CB42: =IF(AL42>=BN42,0,IFERROR(BN42+SUMPRODUCT((AL$4:AL$503>=BN$4:BN$503)*(AL$4:AL$503-BN$4:BN$503))/MAX(1,COUNTIF(AL$4:AL$503,"<"&BN42+0.01)),BN42)) -> 0 | CC42: =IF(AO42="🟢","VERDE",IF(AO42="🟡","AMARELO",IF(AO42="🟠","VERMELHO",IF(AO42="🔴","VERMELHO","ROXO")))) -> VERMELHO | CD42: 🌎 REGIÕES | CE42: SEM REDE
A43: 16762003000100 | B43: VITA PRODUTOS NATURAIS GTBA LTDA - ME | C43: CENTRO OESTE | D43: LARISSA PADILHA | E43: GO | F43: =IFERROR(VLOOKUP(C43,$AS$3:$AT$10,2,FALSE()),IFERROR(VLOOKUP(C43,$AS$15:$AT$22,2,FALSE()),"")) -> 33 | G43: =IFERROR(VLOOKUP(C43,$AS$3:$AX$10,6,FALSE()),IFERROR(VLOOKUP(C43,$AS$15:$AX$22,6,FALSE()),"")) -> 0.34149404 | H43: =IFERROR(VLOOKUP(C43,$AS$3:$AY$10,7,FALSE()),IFERROR(VLOOKUP(C43,$AS$15:$AY$22,7,FALSE()),"")) -> 🔴 VERMELHO | I43: =IFERROR(VLOOKUP(C43,$AS$3:$AZ$10,8,FALSE()),IFERROR(VLOOKUP(C43,$AS$15:$AZ$22,8,FALSE()),"")) -> Positivação + Expandir | K43: CENTRO OESTE | L43: 24463.87 | M43: 1719.15 | N43: 1796.45 | O43: 1839.74 | P43: 1887.66 | Q43: 1949.5 | R43: 2000.52 | S43: 2077.82 | T43: 2128.84 | U43: 2176.77 | V43: 2230.88 | W43: 2289.62 | X43: 2366.92 | Y43: . | Z43: =SUM(AA43:AL43) -> 13191.97 | AD43: 2185.57 | AF43: 2798.08 | AH43: 1859.19 | AJ43: 3150.05 | AK43: 3199.08 | AM43: . | AN43: =IF(L43=0,0,Z43/L43) -> 0.53924297 | AO43: =IF(AN43="","",IF(AN43>=0.9,"🟢",IF(AN43>=0.7,"🟡",IF(AN43>=0.5,"🟠","🔴")))) -> 🟠 | AP43: =IF(L43=0,0,L43-Z43) -> 11271.9 | AQ43: =IF(AP43=0,"",RANK(AP43,AP$4:AP$503,0)) -> 52 | AR43: . | BA43: . | BB43: =SUM(L$4:L$503)/COUNTA(A$4:A$503) -> 9494.3999 | BC43: =SUM(M$4:M$503)/COUNTA(A$4:A$503) -> 667.20008 | BD43: =SUM(N$4:N$503)/COUNTA(A$4:A$503) -> 697.19996 | BE43: =SUM(O$4:O$503)/COUNTA(A$4:A$503) -> 713.9999 | BF43: =SUM(P$4:P$503)/COUNTA(A$4:A$503) -> 732.59984 | BG43: =SUM(Q$4:Q$503)/COUNTA(A$4:A$503) -> 756.59992 | BH43: =SUM(R$4:R$503)/COUNTA(A$4:A$503) -> 776.40004 | BI43: =SUM(S$4:S$503)/COUNTA(A$4:A$503) -> 806.40012 | BJ43: =SUM(T$4:T$503)/COUNTA(A$4:A$503) -> 826.1999 | BK43: =SUM(U$4:U$503)/COUNTA(A$4:A$503) -> 844.8002 | BL43: =SUM(V$4:V$503)/COUNTA(A$4:A$503) -> 865.7998 | BM43: =SUM(W$4:W$503)/COUNTA(A$4:A$503) -> 888.59982 | BN43: =SUM(X$4:X$503)/COUNTA(A$4:A$503) -> 918.60034 | BO43: . | BP43: =IF(Z43>=BB43,0,IFERROR(BB43+(SUMPRODUCT((Z$4:Z$503>=BB$4:BB$503)*(Z$4:Z$503-BB$4:BB$503))/MAX(1,COUNTIF(Z$4:Z$503,"<"&BB43+0.01))),BB43)) -> 0 | BQ43: =IF(AA43>=BC43,0,IFERROR(BC43+SUMPRODUCT((AA$4:AA$503>=BC$4:BC$503)*(AA$4:AA$503-BC$4:BC$503))/MAX(1,COUNTIF(AA$4:AA$503,"<"&BC43+0.01)),BC43)) -> 2238.4659 | BR43: =IF(AB43>=BD43,0,IFERROR(BD43+SUMPRODUCT((AB$4:AB$503>=BD$4:BD$503)*(AB$4:AB$503-BD$4:BD$503))/MAX(1,COUNTIF(AB$4:AB$503,"<"&BD43+0.01)),BD43)) -> 3335.2938 | BS43: =IF(AC43>=BE43,0,IFERROR(BE43+SUMPRODUCT((AC$4:AC$503>=BE$4:BE$503)*(AC$4:AC$503-BE$4:BE$503))/MAX(1,COUNTIF(AC$4:AC$503,"<"&BE43+0.01)),BE43)) -> 6188.7335 | BT43: =IF(AD43>=BF43,0,IFERROR(BF43+SUMPRODUCT((AD$4:AD$503>=BF$4:BF$503)*(AD$4:AD$503-BF$4:BF$503))/MAX(1,COUNTIF(AD$4:AD$503,"<"&BF43+0.01)),BF43)) -> 0 | BU43: =IF(AE43>=BG43,0,IFERROR(BG43+SUMPRODUCT((AE$4:AE$503>=BG$4:BG$503)*(AE$4:AE$503-BG$4:BG$503))/MAX(1,COUNTIF(AE$4:AE$503,"<"&BG43+0.01)),BG43)) -> 7704.8592 | BV43: =IF(AF43>=BH43,0,IFERROR(BH43+SUMPRODUCT((AF$4:AF$503>=BH$4:BH$503)*(AF$4:AF$503-BH$4:BH$503))/MAX(1,COUNTIF(AF$4:AF$503,"<"&BH43+0.01)),BH43)) -> 0 | BW43: =IF(AG43>=BI43,0,IFERROR(BI43+SUMPRODUCT((AG$4:AG$503>=BI$4:BI$503)*(AG$4:AG$503-BI$4:BI$503))/MAX(1,COUNTIF(AG$4:AG$503,"<"&BI43+0.01)),BI43)) -> 9142.1587 | BX43: =IF(AH43>=BJ43,0,IFERROR(BJ43+SUMPRODUCT((AH$4:AH$503>=BJ$4:BJ$503)*(AH$4:AH$503-BJ$4:BJ$503))/MAX(1,COUNTIF(AH$4:AH$503,"<"&BJ43+0.01)),BJ43)) -> 0 | ... CB43: =IF(AL43>=BN43,0,IFERROR(BN43+SUMPRODUCT((AL$4:AL$503>=BN$4:BN$503)*(AL$4:AL$503-BN$4:BN$503))/MAX(1,COUNTIF(AL$4:AL$503,"<"&BN43+0.01)),BN43)) -> 3597.2615 | CC43: =IF(AO43="🟢","VERDE",IF(AO43="🟡","AMARELO",IF(AO43="🟠","VERMELHO",IF(AO43="🔴","VERMELHO","ROXO")))) -> VERMELHO | CD43: 🌎 REGIÕES | CE43: SEM REDE
A44: 30880916000144 | B44: ALEXANDRE VIEIRA KISNER - ALIMENTOS - ME | C44: SUL | D44: HEMANUELE DITZEL (MANU) | E44: PR | F44: =IFERROR(VLOOKUP(C44,$AS$3:$AT$10,2,FALSE()),IFERROR(VLOOKUP(C44,$AS$15:$AT$22,2,FALSE()),"")) -> 132 | G44: =IFERROR(VLOOKUP(C44,$AS$3:$AX$10,6,FALSE()),IFERROR(VLOOKUP(C44,$AS$15:$AX$22,6,FALSE()),"")) -> 0.46819018 | H44: =IFERROR(VLOOKUP(C44,$AS$3:$AY$10,7,FALSE()),IFERROR(VLOOKUP(C44,$AS$15:$AY$22,7,FALSE()),"")) -> 🟡 AMARELO | I44: =IFERROR(VLOOKUP(C44,$AS$3:$AZ$10,8,FALSE()),IFERROR(VLOOKUP(C44,$AS$15:$AZ$22,8,FALSE()),"")) -> Sell Out | K44: SUL | L44: 24450.52 | M44: 1718.21 | N44: 1795.47 | O44: 1838.73 | P44: 1886.63 | Q44: 1948.44 | R44: 1999.43 | S44: 2076.69 | T44: 2127.68 | U44: 2175.58 | V44: 2229.66 | W44: 2288.37 | X44: 2365.63 | Y44: . | Z44: =SUM(AA44:AL44) -> 10200.37 | AF44: 10200.37 | AM44: . | AN44: =IF(L44=0,0,Z44/L44) -> 0.41718417 | AO44: =IF(AN44="","",IF(AN44>=0.9,"🟢",IF(AN44>=0.7,"🟡",IF(AN44>=0.5,"🟠","🔴")))) -> 🔴 | AP44: =IF(L44=0,0,L44-Z44) -> 14250.15 | AQ44: =IF(AP44=0,"",RANK(AP44,AP$4:AP$503,0)) -> 35 | AR44: . | BA44: . | BB44: =SUM(L$4:L$503)/COUNTA(A$4:A$503) -> 9494.3999 | BC44: =SUM(M$4:M$503)/COUNTA(A$4:A$503) -> 667.20008 | BD44: =SUM(N$4:N$503)/COUNTA(A$4:A$503) -> 697.19996 | BE44: =SUM(O$4:O$503)/COUNTA(A$4:A$503) -> 713.9999 | BF44: =SUM(P$4:P$503)/COUNTA(A$4:A$503) -> 732.59984 | BG44: =SUM(Q$4:Q$503)/COUNTA(A$4:A$503) -> 756.59992 | BH44: =SUM(R$4:R$503)/COUNTA(A$4:A$503) -> 776.40004 | BI44: =SUM(S$4:S$503)/COUNTA(A$4:A$503) -> 806.40012 | BJ44: =SUM(T$4:T$503)/COUNTA(A$4:A$503) -> 826.1999 | BK44: =SUM(U$4:U$503)/COUNTA(A$4:A$503) -> 844.8002 | BL44: =SUM(V$4:V$503)/COUNTA(A$4:A$503) -> 865.7998 | BM44: =SUM(W$4:W$503)/COUNTA(A$4:A$503) -> 888.59982 | BN44: =SUM(X$4:X$503)/COUNTA(A$4:A$503) -> 918.60034 | BO44: . | BP44: =IF(Z44>=BB44,0,IFERROR(BB44+(SUMPRODUCT((Z$4:Z$503>=BB$4:BB$503)*(Z$4:Z$503-BB$4:BB$503))/MAX(1,COUNTIF(Z$4:Z$503,"<"&BB44+0.01))),BB44)) -> 0 | BQ44: =IF(AA44>=BC44,0,IFERROR(BC44+SUMPRODUCT((AA$4:AA$503>=BC$4:BC$503)*(AA$4:AA$503-BC$4:BC$503))/MAX(1,COUNTIF(AA$4:AA$503,"<"&BC44+0.01)),BC44)) -> 2238.4659 | BR44: =IF(AB44>=BD44,0,IFERROR(BD44+SUMPRODUCT((AB$4:AB$503>=BD$4:BD$503)*(AB$4:AB$503-BD$4:BD$503))/MAX(1,COUNTIF(AB$4:AB$503,"<"&BD44+0.01)),BD44)) -> 3335.2938 | BS44: =IF(AC44>=BE44,0,IFERROR(BE44+SUMPRODUCT((AC$4:AC$503>=BE$4:BE$503)*(AC$4:AC$503-BE$4:BE$503))/MAX(1,COUNTIF(AC$4:AC$503,"<"&BE44+0.01)),BE44)) -> 6188.7335 | BT44: =IF(AD44>=BF44,0,IFERROR(BF44+SUMPRODUCT((AD$4:AD$503>=BF$4:BF$503)*(AD$4:AD$503-BF$4:BF$503))/MAX(1,COUNTIF(AD$4:AD$503,"<"&BF44+0.01)),BF44)) -> 11354.354 | BU44: =IF(AE44>=BG44,0,IFERROR(BG44+SUMPRODUCT((AE$4:AE$503>=BG$4:BG$503)*(AE$4:AE$503-BG$4:BG$503))/MAX(1,COUNTIF(AE$4:AE$503,"<"&BG44+0.01)),BG44)) -> 7704.8592 | BV44: =IF(AF44>=BH44,0,IFERROR(BH44+SUMPRODUCT((AF$4:AF$503>=BH$4:BH$503)*(AF$4:AF$503-BH$4:BH$503))/MAX(1,COUNTIF(AF$4:AF$503,"<"&BH44+0.01)),BH44)) -> 0 | BW44: =IF(AG44>=BI44,0,IFERROR(BI44+SUMPRODUCT((AG$4:AG$503>=BI$4:BI$503)*(AG$4:AG$503-BI$4:BI$503))/MAX(1,COUNTIF(AG$4:AG$503,"<"&BI44+0.01)),BI44)) -> 9142.1587 | BX44: =IF(AH44>=BJ44,0,IFERROR(BJ44+SUMPRODUCT((AH$4:AH$503>=BJ$4:BJ$503)*(AH$4:AH$503-BJ$4:BJ$503))/MAX(1,COUNTIF(AH$4:AH$503,"<"&BJ44+0.01)),BJ44)) -> 5621.5026 | ... CB44: =IF(AL44>=BN44,0,IFERROR(BN44+SUMPRODUCT((AL$4:AL$503>=BN$4:BN$503)*(AL$4:AL$503-BN$4:BN$503))/MAX(1,COUNTIF(AL$4:AL$503,"<"&BN44+0.01)),BN44)) -> 3597.2615 | CC44: =IF(AO44="🟢","VERDE",IF(AO44="🟡","AMARELO",IF(AO44="🟠","VERMELHO",IF(AO44="🔴","VERMELHO","ROXO")))) -> VERMELHO | CD44: 🌎 REGIÕES | CE44: SEM REDE
A45: 51213425000110 | B45: JARDIM DO GRANEL COMERCIO DE ALIMENTOS L | C45: SUL | D45: HEMANUELE DITZEL (MANU) | E45: PR | F45: =IFERROR(VLOOKUP(C45,$AS$3:$AT$10,2,FALSE()),IFERROR(VLOOKUP(C45,$AS$15:$AT$22,2,FALSE()),"")) -> 132 | G45: =IFERROR(VLOOKUP(C45,$AS$3:$AX$10,6,FALSE()),IFERROR(VLOOKUP(C45,$AS$15:$AX$22,6,FALSE()),"")) -> 0.46819018 | H45: =IFERROR(VLOOKUP(C45,$AS$3:$AY$10,7,FALSE()),IFERROR(VLOOKUP(C45,$AS$15:$AY$22,7,FALSE()),"")) -> 🟡 AMARELO | I45: =IFERROR(VLOOKUP(C45,$AS$3:$AZ$10,8,FALSE()),IFERROR(VLOOKUP(C45,$AS$15:$AZ$22,8,FALSE()),"")) -> Sell Out | K45: SUL | L45: 24021.26 | M45: 1688.05 | N45: 1763.95 | O45: 1806.45 | P45: 1853.51 | Q45: 1914.23 | R45: 1964.33 | S45: 2040.23 | T45: 2090.32 | U45: 2137.38 | V45: 2190.51 | W45: 2248.2 | X45: 2324.1 | Y45: . | Z45: =SUM(AA45:AL45) -> 11358.43 | AF45: 11358.43 | AM45: . | AN45: =IF(L45=0,0,Z45/L45) -> 0.47284905 | AO45: =IF(AN45="","",IF(AN45>=0.9,"🟢",IF(AN45>=0.7,"🟡",IF(AN45>=0.5,"🟠","🔴")))) -> 🔴 | AP45: =IF(L45=0,0,L45-Z45) -> 12662.83 | AQ45: =IF(AP45=0,"",RANK(AP45,AP$4:AP$503,0)) -> 41 | AR45: . | BA45: . | BB45: =SUM(L$4:L$503)/COUNTA(A$4:A$503) -> 9494.3999 | BC45: =SUM(M$4:M$503)/COUNTA(A$4:A$503) -> 667.20008 | BD45: =SUM(N$4:N$503)/COUNTA(A$4:A$503) -> 697.19996 | BE45: =SUM(O$4:O$503)/COUNTA(A$4:A$503) -> 713.9999 | BF45: =SUM(P$4:P$503)/COUNTA(A$4:A$503) -> 732.59984 | BG45: =SUM(Q$4:Q$503)/COUNTA(A$4:A$503) -> 756.59992 | BH45: =SUM(R$4:R$503)/COUNTA(A$4:A$503) -> 776.40004 | BI45: =SUM(S$4:S$503)/COUNTA(A$4:A$503) -> 806.40012 | BJ45: =SUM(T$4:T$503)/COUNTA(A$4:A$503) -> 826.1999 | BK45: =SUM(U$4:U$503)/COUNTA(A$4:A$503) -> 844.8002 | BL45: =SUM(V$4:V$503)/COUNTA(A$4:A$503) -> 865.7998 | BM45: =SUM(W$4:W$503)/COUNTA(A$4:A$503) -> 888.59982 | BN45: =SUM(X$4:X$503)/COUNTA(A$4:A$503) -> 918.60034 | BO45: . | BP45: =IF(Z45>=BB45,0,IFERROR(BB45+(SUMPRODUCT((Z$4:Z$503>=BB$4:BB$503)*(Z$4:Z$503-BB$4:BB$503))/MAX(1,COUNTIF(Z$4:Z$503,"<"&BB45+0.01))),BB45)) -> 0 | BQ45: =IF(AA45>=BC45,0,IFERROR(BC45+SUMPRODUCT((AA$4:AA$503>=BC$4:BC$503)*(AA$4:AA$503-BC$4:BC$503))/MAX(1,COUNTIF(AA$4:AA$503,"<"&BC45+0.01)),BC45)) -> 2238.4659 | BR45: =IF(AB45>=BD45,0,IFERROR(BD45+SUMPRODUCT((AB$4:AB$503>=BD$4:BD$503)*(AB$4:AB$503-BD$4:BD$503))/MAX(1,COUNTIF(AB$4:AB$503,"<"&BD45+0.01)),BD45)) -> 3335.2938 | BS45: =IF(AC45>=BE45,0,IFERROR(BE45+SUMPRODUCT((AC$4:AC$503>=BE$4:BE$503)*(AC$4:AC$503-BE$4:BE$503))/MAX(1,COUNTIF(AC$4:AC$503,"<"&BE45+0.01)),BE45)) -> 6188.7335 | BT45: =IF(AD45>=BF45,0,IFERROR(BF45+SUMPRODUCT((AD$4:AD$503>=BF$4:BF$503)*(AD$4:AD$503-BF$4:BF$503))/MAX(1,COUNTIF(AD$4:AD$503,"<"&BF45+0.01)),BF45)) -> 11354.354 | BU45: =IF(AE45>=BG45,0,IFERROR(BG45+SUMPRODUCT((AE$4:AE$503>=BG$4:BG$503)*(AE$4:AE$503-BG$4:BG$503))/MAX(1,COUNTIF(AE$4:AE$503,"<"&BG45+0.01)),BG45)) -> 7704.8592 | BV45: =IF(AF45>=BH45,0,IFERROR(BH45+SUMPRODUCT((AF$4:AF$503>=BH$4:BH$503)*(AF$4:AF$503-BH$4:BH$503))/MAX(1,COUNTIF(AF$4:AF$503,"<"&BH45+0.01)),BH45)) -> 0 | BW45: =IF(AG45>=BI45,0,IFERROR(BI45+SUMPRODUCT((AG$4:AG$503>=BI$4:BI$503)*(AG$4:AG$503-BI$4:BI$503))/MAX(1,COUNTIF(AG$4:AG$503,"<"&BI45+0.01)),BI45)) -> 9142.1587 | BX45: =IF(AH45>=BJ45,0,IFERROR(BJ45+SUMPRODUCT((AH$4:AH$503>=BJ$4:BJ$503)*(AH$4:AH$503-BJ$4:BJ$503))/MAX(1,COUNTIF(AH$4:AH$503,"<"&BJ45+0.01)),BJ45)) -> 5621.5026 | ... CB45: =IF(AL45>=BN45,0,IFERROR(BN45+SUMPRODUCT((AL$4:AL$503>=BN$4:BN$503)*(AL$4:AL$503-BN$4:BN$503))/MAX(1,COUNTIF(AL$4:AL$503,"<"&BN45+0.01)),BN45)) -> 3597.2615 | CC45: =IF(AO45="🟢","VERDE",IF(AO45="🟡","AMARELO",IF(AO45="🟠","VERMELHO",IF(AO45="🔴","VERMELHO","ROXO")))) -> VERMELHO | CD45: 🌎 REGIÕES | CE45: SEM REDE
A46: 07523884000108 | B46: COMERCIAL DE ALIMENTOS SIQUEIRA LTDA - M | C46: SEM GRUPO | D46: HEMANUELE DITZEL (MANU) | E46: . | F46: =IFERROR(VLOOKUP(C46,$AS$3:$AT$10,2,FALSE()),IFERROR(VLOOKUP(C46,$AS$15:$AT$22,2,FALSE()),"")) -> 49 | G46: =IFERROR(VLOOKUP(C46,$AS$3:$AX$10,6,FALSE()),IFERROR(VLOOKUP(C46,$AS$15:$AX$22,6,FALSE()),"")) -> 0.43639135 | H46: =IFERROR(VLOOKUP(C46,$AS$3:$AY$10,7,FALSE()),IFERROR(VLOOKUP(C46,$AS$15:$AY$22,7,FALSE()),"")) -> 🟡 AMARELO | I46: =IFERROR(VLOOKUP(C46,$AS$3:$AZ$10,8,FALSE()),IFERROR(VLOOKUP(C46,$AS$15:$AZ$22,8,FALSE()),"")) -> Sell Out | K46: . | L46: 23125.65 | M46: 1625.11 | N46: 1698.18 | O46: 1739.1 | P46: 1784.4 | Q46: 1842.86 | R46: 1891.09 | S46: 1964.16 | T46: 2012.39 | U46: 2057.69 | V46: 2108.84 | W46: 2164.38 | X46: 2237.45 | Y46: . | Z46: =SUM(AA46:AL46) -> 9404.71 | AF46: 9404.71 | AM46: . | AN46: =IF(L46=0,0,Z46/L46) -> 0.40667873 | AO46: =IF(AN46="","",IF(AN46>=0.9,"🟢",IF(AN46>=0.7,"🟡",IF(AN46>=0.5,"🟠","🔴")))) -> 🔴 | AP46: =IF(L46=0,0,L46-Z46) -> 13720.94 | AQ46: =IF(AP46=0,"",RANK(AP46,AP$4:AP$503,0)) -> 37 | AR46: . | BA46: . | BB46: =SUM(L$4:L$503)/COUNTA(A$4:A$503) -> 9494.3999 | BC46: =SUM(M$4:M$503)/COUNTA(A$4:A$503) -> 667.20008 | BD46: =SUM(N$4:N$503)/COUNTA(A$4:A$503) -> 697.19996 | BE46: =SUM(O$4:O$503)/COUNTA(A$4:A$503) -> 713.9999 | BF46: =SUM(P$4:P$503)/COUNTA(A$4:A$503) -> 732.59984 | BG46: =SUM(Q$4:Q$503)/COUNTA(A$4:A$503) -> 756.59992 | BH46: =SUM(R$4:R$503)/COUNTA(A$4:A$503) -> 776.40004 | BI46: =SUM(S$4:S$503)/COUNTA(A$4:A$503) -> 806.40012 | BJ46: =SUM(T$4:T$503)/COUNTA(A$4:A$503) -> 826.1999 | BK46: =SUM(U$4:U$503)/COUNTA(A$4:A$503) -> 844.8002 | BL46: =SUM(V$4:V$503)/COUNTA(A$4:A$503) -> 865.7998 | BM46: =SUM(W$4:W$503)/COUNTA(A$4:A$503) -> 888.59982 | BN46: =SUM(X$4:X$503)/COUNTA(A$4:A$503) -> 918.60034 | BO46: . | BP46: =IF(Z46>=BB46,0,IFERROR(BB46+(SUMPRODUCT((Z$4:Z$503>=BB$4:BB$503)*(Z$4:Z$503-BB$4:BB$503))/MAX(1,COUNTIF(Z$4:Z$503,"<"&BB46+0.01))),BB46)) -> 10695.543 | BQ46: =IF(AA46>=BC46,0,IFERROR(BC46+SUMPRODUCT((AA$4:AA$503>=BC$4:BC$503)*(AA$4:AA$503-BC$4:BC$503))/MAX(1,COUNTIF(AA$4:AA$503,"<"&BC46+0.01)),BC46)) -> 2238.4659 | BR46: =IF(AB46>=BD46,0,IFERROR(BD46+SUMPRODUCT((AB$4:AB$503>=BD$4:BD$503)*(AB$4:AB$503-BD$4:BD$503))/MAX(1,COUNTIF(AB$4:AB$503,"<"&BD46+0.01)),BD46)) -> 3335.2938 | BS46: =IF(AC46>=BE46,0,IFERROR(BE46+SUMPRODUCT((AC$4:AC$503>=BE$4:BE$503)*(AC$4:AC$503-BE$4:BE$503))/MAX(1,COUNTIF(AC$4:AC$503,"<"&BE46+0.01)),BE46)) -> 6188.7335 | BT46: =IF(AD46>=BF46,0,IFERROR(BF46+SUMPRODUCT((AD$4:AD$503>=BF$4:BF$503)*(AD$4:AD$503-BF$4:BF$503))/MAX(1,COUNTIF(AD$4:AD$503,"<"&BF46+0.01)),BF46)) -> 11354.354 | BU46: =IF(AE46>=BG46,0,IFERROR(BG46+SUMPRODUCT((AE$4:AE$503>=BG$4:BG$503)*(AE$4:AE$503-BG$4:BG$503))/MAX(1,COUNTIF(AE$4:AE$503,"<"&BG46+0.01)),BG46)) -> 7704.8592 | BV46: =IF(AF46>=BH46,0,IFERROR(BH46+SUMPRODUCT((AF$4:AF$503>=BH$4:BH$503)*(AF$4:AF$503-BH$4:BH$503))/MAX(1,COUNTIF(AF$4:AF$503,"<"&BH46+0.01)),BH46)) -> 0 | BW46: =IF(AG46>=BI46,0,IFERROR(BI46+SUMPRODUCT((AG$4:AG$503>=BI$4:BI$503)*(AG$4:AG$503-BI$4:BI$503))/MAX(1,COUNTIF(AG$4:AG$503,"<"&BI46+0.01)),BI46)) -> 9142.1587 | BX46: =IF(AH46>=BJ46,0,IFERROR(BJ46+SUMPRODUCT((AH$4:AH$503>=BJ$4:BJ$503)*(AH$4:AH$503-BJ$4:BJ$503))/MAX(1,COUNTIF(AH$4:AH$503,"<"&BJ46+0.01)),BJ46)) -> 5621.5026 | ... CB46: =IF(AL46>=BN46,0,IFERROR(BN46+SUMPRODUCT((AL$4:AL$503>=BN$4:BN$503)*(AL$4:AL$503-BN$4:BN$503))/MAX(1,COUNTIF(AL$4:AL$503,"<"&BN46+0.01)),BN46)) -> 3597.2615 | CC46: =IF(AO46="🟢","VERDE",IF(AO46="🟡","AMARELO",IF(AO46="🟠","VERMELHO",IF(AO46="🔴","VERMELHO","ROXO")))) -> VERMELHO | CD46: 🌎 REGIÕES | CE46: SEM REDE
A47: 15428647000196 | B47: R DOS SANTOS COSTA CAMATTI LTDA - EPP | C47: CENTRO OESTE | D47: LARISSA PADILHA | E47: MT | F47: =IFERROR(VLOOKUP(C47,$AS$3:$AT$10,2,FALSE()),IFERROR(VLOOKUP(C47,$AS$15:$AT$22,2,FALSE()),"")) -> 33 | G47: =IFERROR(VLOOKUP(C47,$AS$3:$AX$10,6,FALSE()),IFERROR(VLOOKUP(C47,$AS$15:$AX$22,6,FALSE()),"")) -> 0.34149404 | H47: =IFERROR(VLOOKUP(C47,$AS$3:$AY$10,7,FALSE()),IFERROR(VLOOKUP(C47,$AS$15:$AY$22,7,FALSE()),"")) -> 🔴 VERMELHO | I47: =IFERROR(VLOOKUP(C47,$AS$3:$AZ$10,8,FALSE()),IFERROR(VLOOKUP(C47,$AS$15:$AZ$22,8,FALSE()),"")) -> Positivação + Expandir | K47: CENTRO OESTE | L47: 22066.5 | M47: 1550.68 | N47: 1620.4 | O47: 1659.45 | P47: 1702.68 | Q47: 1758.46 | R47: 1804.48 | S47: 1874.2 | T47: 1920.22 | U47: 1963.45 | V47: 2012.26 | W47: 2065.25 | X47: 2134.97 | Y47: . | Z47: =SUM(AA47:AL47) -> 8874.06 | AD47: 5667.06 | AG47: 2232 | AH47: 975 | AM47: . | AN47: =IF(L47=0,0,Z47/L47) -> 0.40215077 | AO47: =IF(AN47="","",IF(AN47>=0.9,"🟢",IF(AN47>=0.7,"🟡",IF(AN47>=0.5,"🟠","🔴")))) -> 🔴 | AP47: =IF(L47=0,0,L47-Z47) -> 13192.44 | AQ47: =IF(AP47=0,"",RANK(AP47,AP$4:AP$503,0)) -> 39 | AR47: . | BA47: . | BB47: =SUM(L$4:L$503)/COUNTA(A$4:A$503) -> 9494.3999 | BC47: =SUM(M$4:M$503)/COUNTA(A$4:A$503) -> 667.20008 | BD47: =SUM(N$4:N$503)/COUNTA(A$4:A$503) -> 697.19996 | BE47: =SUM(O$4:O$503)/COUNTA(A$4:A$503) -> 713.9999 | BF47: =SUM(P$4:P$503)/COUNTA(A$4:A$503) -> 732.59984 | BG47: =SUM(Q$4:Q$503)/COUNTA(A$4:A$503) -> 756.59992 | BH47: =SUM(R$4:R$503)/COUNTA(A$4:A$503) -> 776.40004 | BI47: =SUM(S$4:S$503)/COUNTA(A$4:A$503) -> 806.40012 | BJ47: =SUM(T$4:T$503)/COUNTA(A$4:A$503) -> 826.1999 | BK47: =SUM(U$4:U$503)/COUNTA(A$4:A$503) -> 844.8002 | BL47: =SUM(V$4:V$503)/COUNTA(A$4:A$503) -> 865.7998 | BM47: =SUM(W$4:W$503)/COUNTA(A$4:A$503) -> 888.59982 | BN47: =SUM(X$4:X$503)/COUNTA(A$4:A$503) -> 918.60034 | BO47: . | BP47: =IF(Z47>=BB47,0,IFERROR(BB47+(SUMPRODUCT((Z$4:Z$503>=BB$4:BB$503)*(Z$4:Z$503-BB$4:BB$503))/MAX(1,COUNTIF(Z$4:Z$503,"<"&BB47+0.01))),BB47)) -> 10695.543 | BQ47: =IF(AA47>=BC47,0,IFERROR(BC47+SUMPRODUCT((AA$4:AA$503>=BC$4:BC$503)*(AA$4:AA$503-BC$4:BC$503))/MAX(1,COUNTIF(AA$4:AA$503,"<"&BC47+0.01)),BC47)) -> 2238.4659 | BR47: =IF(AB47>=BD47,0,IFERROR(BD47+SUMPRODUCT((AB$4:AB$503>=BD$4:BD$503)*(AB$4:AB$503-BD$4:BD$503))/MAX(1,COUNTIF(AB$4:AB$503,"<"&BD47+0.01)),BD47)) -> 3335.2938 | BS47: =IF(AC47>=BE47,0,IFERROR(BE47+SUMPRODUCT((AC$4:AC$503>=BE$4:BE$503)*(AC$4:AC$503-BE$4:BE$503))/MAX(1,COUNTIF(AC$4:AC$503,"<"&BE47+0.01)),BE47)) -> 6188.7335 | BT47: =IF(AD47>=BF47,0,IFERROR(BF47+SUMPRODUCT((AD$4:AD$503>=BF$4:BF$503)*(AD$4:AD$503-BF$4:BF$503))/MAX(1,COUNTIF(AD$4:AD$503,"<"&BF47+0.01)),BF47)) -> 0 | BU47: =IF(AE47>=BG47,0,IFERROR(BG47+SUMPRODUCT((AE$4:AE$503>=BG$4:BG$503)*(AE$4:AE$503-BG$4:BG$503))/MAX(1,COUNTIF(AE$4:AE$503,"<"&BG47+0.01)),BG47)) -> 7704.8592 | BV47: =IF(AF47>=BH47,0,IFERROR(BH47+SUMPRODUCT((AF$4:AF$503>=BH$4:BH$503)*(AF$4:AF$503-BH$4:BH$503))/MAX(1,COUNTIF(AF$4:AF$503,"<"&BH47+0.01)),BH47)) -> 9942.6504 | BW47: =IF(AG47>=BI47,0,IFERROR(BI47+SUMPRODUCT((AG$4:AG$503>=BI$4:BI$503)*(AG$4:AG$503-BI$4:BI$503))/MAX(1,COUNTIF(AG$4:AG$503,"<"&BI47+0.01)),BI47)) -> 0 | BX47: =IF(AH47>=BJ47,0,IFERROR(BJ47+SUMPRODUCT((AH$4:AH$503>=BJ$4:BJ$503)*(AH$4:AH$503-BJ$4:BJ$503))/MAX(1,COUNTIF(AH$4:AH$503,"<"&BJ47+0.01)),BJ47)) -> 0 | ... CB47: =IF(AL47>=BN47,0,IFERROR(BN47+SUMPRODUCT((AL$4:AL$503>=BN$4:BN$503)*(AL$4:AL$503-BN$4:BN$503))/MAX(1,COUNTIF(AL$4:AL$503,"<"&BN47+0.01)),BN47)) -> 3597.2615 | CC47: =IF(AO47="🟢","VERDE",IF(AO47="🟡","AMARELO",IF(AO47="🟠","VERMELHO",IF(AO47="🔴","VERMELHO","ROXO")))) -> VERMELHO | CD47: 🌎 REGIÕES | CE47: SEM REDE
A48: 30289781000147 | B48: BATEL GOURMET ARMAZEM, EMPORIO E HORTIFR | C48: SUL | D48: HEMANUELE DITZEL (MANU) | E48: PR | F48: =IFERROR(VLOOKUP(C48,$AS$3:$AT$10,2,FALSE()),IFERROR(VLOOKUP(C48,$AS$15:$AT$22,2,FALSE()),"")) -> 132 | G48: =IFERROR(VLOOKUP(C48,$AS$3:$AX$10,6,FALSE()),IFERROR(VLOOKUP(C48,$AS$15:$AX$22,6,FALSE()),"")) -> 0.46819018 | H48: =IFERROR(VLOOKUP(C48,$AS$3:$AY$10,7,FALSE()),IFERROR(VLOOKUP(C48,$AS$15:$AY$22,7,FALSE()),"")) -> 🟡 AMARELO | I48: =IFERROR(VLOOKUP(C48,$AS$3:$AZ$10,8,FALSE()),IFERROR(VLOOKUP(C48,$AS$15:$AZ$22,8,FALSE()),"")) -> Sell Out | K48: SUL | L48: 21054.33 | M48: 1479.55 | N48: 1546.08 | O48: 1583.33 | P48: 1624.58 | Q48: 1677.8 | R48: 1721.71 | S48: 1788.23 | T48: 1832.14 | U48: 1873.39 | V48: 1919.96 | W48: 1970.52 | X48: 2037.04 | Y48: . | Z48: =SUM(AA48:AL48) -> 10486.11 | AD48: 3522.82 | AF48: 757.99 | AG48: 1624.59 | AH48: 913.8 | AJ48: 3666.91 | AM48: . | AN48: =IF(L48=0,0,Z48/L48) -> 0.49805004 | AO48: =IF(AN48="","",IF(AN48>=0.9,"🟢",IF(AN48>=0.7,"🟡",IF(AN48>=0.5,"🟠","🔴")))) -> 🔴 | AP48: =IF(L48=0,0,L48-Z48) -> 10568.22 | AQ48: =IF(AP48=0,"",RANK(AP48,AP$4:AP$503,0)) -> 57 | AR48: . | BA48: . | BB48: =SUM(L$4:L$503)/COUNTA(A$4:A$503) -> 9494.3999 | BC48: =SUM(M$4:M$503)/COUNTA(A$4:A$503) -> 667.20008 | BD48: =SUM(N$4:N$503)/COUNTA(A$4:A$503) -> 697.19996 | BE48: =SUM(O$4:O$503)/COUNTA(A$4:A$503) -> 713.9999 | BF48: =SUM(P$4:P$503)/COUNTA(A$4:A$503) -> 732.59984 | BG48: =SUM(Q$4:Q$503)/COUNTA(A$4:A$503) -> 756.59992 | BH48: =SUM(R$4:R$503)/COUNTA(A$4:A$503) -> 776.40004 | BI48: =SUM(S$4:S$503)/COUNTA(A$4:A$503) -> 806.40012 | BJ48: =SUM(T$4:T$503)/COUNTA(A$4:A$503) -> 826.1999 | BK48: =SUM(U$4:U$503)/COUNTA(A$4:A$503) -> 844.8002 | BL48: =SUM(V$4:V$503)/COUNTA(A$4:A$503) -> 865.7998 | BM48: =SUM(W$4:W$503)/COUNTA(A$4:A$503) -> 888.59982 | BN48: =SUM(X$4:X$503)/COUNTA(A$4:A$503) -> 918.60034 | BO48: . | BP48: =IF(Z48>=BB48,0,IFERROR(BB48+(SUMPRODUCT((Z$4:Z$503>=BB$4:BB$503)*(Z$4:Z$503-BB$4:BB$503))/MAX(1,COUNTIF(Z$4:Z$503,"<"&BB48+0.01))),BB48)) -> 0 | BQ48: =IF(AA48>=BC48,0,IFERROR(BC48+SUMPRODUCT((AA$4:AA$503>=BC$4:BC$503)*(AA$4:AA$503-BC$4:BC$503))/MAX(1,COUNTIF(AA$4:AA$503,"<"&BC48+0.01)),BC48)) -> 2238.4659 | BR48: =IF(AB48>=BD48,0,IFERROR(BD48+SUMPRODUCT((AB$4:AB$503>=BD$4:BD$503)*(AB$4:AB$503-BD$4:BD$503))/MAX(1,COUNTIF(AB$4:AB$503,"<"&BD48+0.01)),BD48)) -> 3335.2938 | BS48: =IF(AC48>=BE48,0,IFERROR(BE48+SUMPRODUCT((AC$4:AC$503>=BE$4:BE$503)*(AC$4:AC$503-BE$4:BE$503))/MAX(1,COUNTIF(AC$4:AC$503,"<"&BE48+0.01)),BE48)) -> 6188.7335 | BT48: =IF(AD48>=BF48,0,IFERROR(BF48+SUMPRODUCT((AD$4:AD$503>=BF$4:BF$503)*(AD$4:AD$503-BF$4:BF$503))/MAX(1,COUNTIF(AD$4:AD$503,"<"&BF48+0.01)),BF48)) -> 0 | BU48: =IF(AE48>=BG48,0,IFERROR(BG48+SUMPRODUCT((AE$4:AE$503>=BG$4:BG$503)*(AE$4:AE$503-BG$4:BG$503))/MAX(1,COUNTIF(AE$4:AE$503,"<"&BG48+0.01)),BG48)) -> 7704.8592 | BV48: =IF(AF48>=BH48,0,IFERROR(BH48+SUMPRODUCT((AF$4:AF$503>=BH$4:BH$503)*(AF$4:AF$503-BH$4:BH$503))/MAX(1,COUNTIF(AF$4:AF$503,"<"&BH48+0.01)),BH48)) -> 9942.6504 | BW48: =IF(AG48>=BI48,0,IFERROR(BI48+SUMPRODUCT((AG$4:AG$503>=BI$4:BI$503)*(AG$4:AG$503-BI$4:BI$503))/MAX(1,COUNTIF(AG$4:AG$503,"<"&BI48+0.01)),BI48)) -> 0 | BX48: =IF(AH48>=BJ48,0,IFERROR(BJ48+SUMPRODUCT((AH$4:AH$503>=BJ$4:BJ$503)*(AH$4:AH$503-BJ$4:BJ$503))/MAX(1,COUNTIF(AH$4:AH$503,"<"&BJ48+0.01)),BJ48)) -> 0 | ... CB48: =IF(AL48>=BN48,0,IFERROR(BN48+SUMPRODUCT((AL$4:AL$503>=BN$4:BN$503)*(AL$4:AL$503-BN$4:BN$503))/MAX(1,COUNTIF(AL$4:AL$503,"<"&BN48+0.01)),BN48)) -> 3597.2615 | CC48: =IF(AO48="🟢","VERDE",IF(AO48="🟡","AMARELO",IF(AO48="🟠","VERMELHO",IF(AO48="🔴","VERMELHO","ROXO")))) -> VERMELHO | CD48: 🌎 REGIÕES | CE48: SEM REDE
A49: 09185428000392 | B49: NATURVIDA MERCADO SAUDAVEL LTDA - ME | C49: NATURVIDA | D49: HEMANUELE DITZEL (MANU) | E49: . | F49: =IFERROR(VLOOKUP(C49,$AS$3:$AT$10,2,FALSE()),IFERROR(VLOOKUP(C49,$AS$15:$AT$22,2,FALSE()),"")) | G49: =IFERROR(VLOOKUP(C49,$AS$3:$AX$10,6,FALSE()),IFERROR(VLOOKUP(C49,$AS$15:$AX$22,6,FALSE()),"")) | H49: =IFERROR(VLOOKUP(C49,$AS$3:$AY$10,7,FALSE()),IFERROR(VLOOKUP(C49,$AS$15:$AY$22,7,FALSE()),"")) | I49: =IFERROR(VLOOKUP(C49,$AS$3:$AZ$10,8,FALSE()),IFERROR(VLOOKUP(C49,$AS$15:$AZ$22,8,FALSE()),"")) | K49: . | L49: 21031.27 | M49: 1477.93 | N49: 1544.38 | O49: 1581.6 | P49: 1622.8 | Q49: 1675.96 | R49: 1719.82 | S49: 1786.28 | T49: 1830.14 | U49: 1871.34 | V49: 1917.85 | W49: 1968.36 | X49: 2034.81 | Y49: . | Z49: =SUM(AA49:AL49) -> 8467.75 | AF49: 1321.01 | AH49: 3054.31 | AI49: 1562.38 | AJ49: 1658.12 | AL49: 871.93 | AM49: . | AN49: =IF(L49=0,0,Z49/L49) -> 0.40262666 | AO49: =IF(AN49="","",IF(AN49>=0.9,"🟢",IF(AN49>=0.7,"🟡",IF(AN49>=0.5,"🟠","🔴")))) -> 🔴 | AP49: =IF(L49=0,0,L49-Z49) -> 12563.52 | AQ49: =IF(AP49=0,"",RANK(AP49,AP$4:AP$503,0)) -> 42 | AR49: . | BA49: . | BB49: =SUM(L$4:L$503)/COUNTA(A$4:A$503) -> 9494.3999 | BC49: =SUM(M$4:M$503)/COUNTA(A$4:A$503) -> 667.20008 | BD49: =SUM(N$4:N$503)/COUNTA(A$4:A$503) -> 697.19996 | BE49: =SUM(O$4:O$503)/COUNTA(A$4:A$503) -> 713.9999 | BF49: =SUM(P$4:P$503)/COUNTA(A$4:A$503) -> 732.59984 | BG49: =SUM(Q$4:Q$503)/COUNTA(A$4:A$503) -> 756.59992 | BH49: =SUM(R$4:R$503)/COUNTA(A$4:A$503) -> 776.40004 | BI49: =SUM(S$4:S$503)/COUNTA(A$4:A$503) -> 806.40012 | BJ49: =SUM(T$4:T$503)/COUNTA(A$4:A$503) -> 826.1999 | BK49: =SUM(U$4:U$503)/COUNTA(A$4:A$503) -> 844.8002 | BL49: =SUM(V$4:V$503)/COUNTA(A$4:A$503) -> 865.7998 | BM49: =SUM(W$4:W$503)/COUNTA(A$4:A$503) -> 888.59982 | BN49: =SUM(X$4:X$503)/COUNTA(A$4:A$503) -> 918.60034 | BO49: . | BP49: =IF(Z49>=BB49,0,IFERROR(BB49+(SUMPRODUCT((Z$4:Z$503>=BB$4:BB$503)*(Z$4:Z$503-BB$4:BB$503))/MAX(1,COUNTIF(Z$4:Z$503,"<"&BB49+0.01))),BB49)) -> 10695.543 | BQ49: =IF(AA49>=BC49,0,IFERROR(BC49+SUMPRODUCT((AA$4:AA$503>=BC$4:BC$503)*(AA$4:AA$503-BC$4:BC$503))/MAX(1,COUNTIF(AA$4:AA$503,"<"&BC49+0.01)),BC49)) -> 2238.4659 | BR49: =IF(AB49>=BD49,0,IFERROR(BD49+SUMPRODUCT((AB$4:AB$503>=BD$4:BD$503)*(AB$4:AB$503-BD$4:BD$503))/MAX(1,COUNTIF(AB$4:AB$503,"<"&BD49+0.01)),BD49)) -> 3335.2938 | BS49: =IF(AC49>=BE49,0,IFERROR(BE49+SUMPRODUCT((AC$4:AC$503>=BE$4:BE$503)*(AC$4:AC$503-BE$4:BE$503))/MAX(1,COUNTIF(AC$4:AC$503,"<"&BE49+0.01)),BE49)) -> 6188.7335 | BT49: =IF(AD49>=BF49,0,IFERROR(BF49+SUMPRODUCT((AD$4:AD$503>=BF$4:BF$503)*(AD$4:AD$503-BF$4:BF$503))/MAX(1,COUNTIF(AD$4:AD$503,"<"&BF49+0.01)),BF49)) -> 11354.354 | BU49: =IF(AE49>=BG49,0,IFERROR(BG49+SUMPRODUCT((AE$4:AE$503>=BG$4:BG$503)*(AE$4:AE$503-BG$4:BG$503))/MAX(1,COUNTIF(AE$4:AE$503,"<"&BG49+0.01)),BG49)) -> 7704.8592 | BV49: =IF(AF49>=BH49,0,IFERROR(BH49+SUMPRODUCT((AF$4:AF$503>=BH$4:BH$503)*(AF$4:AF$503-BH$4:BH$503))/MAX(1,COUNTIF(AF$4:AF$503,"<"&BH49+0.01)),BH49)) -> 0 | BW49: =IF(AG49>=BI49,0,IFERROR(BI49+SUMPRODUCT((AG$4:AG$503>=BI$4:BI$503)*(AG$4:AG$503-BI$4:BI$503))/MAX(1,COUNTIF(AG$4:AG$503,"<"&BI49+0.01)),BI49)) -> 9142.1587 | BX49: =IF(AH49>=BJ49,0,IFERROR(BJ49+SUMPRODUCT((AH$4:AH$503>=BJ$4:BJ$503)*(AH$4:AH$503-BJ$4:BJ$503))/MAX(1,COUNTIF(AH$4:AH$503,"<"&BJ49+0.01)),BJ49)) -> 0 | ... CB49: =IF(AL49>=BN49,0,IFERROR(BN49+SUMPRODUCT((AL$4:AL$503>=BN$4:BN$503)*(AL$4:AL$503-BN$4:BN$503))/MAX(1,COUNTIF(AL$4:AL$503,"<"&BN49+0.01)),BN49)) -> 3597.2615 | CC49: =IF(AO49="🟢","VERDE",IF(AO49="🟡","AMARELO",IF(AO49="🟠","VERMELHO",IF(AO49="🔴","VERMELHO","ROXO")))) -> VERMELHO | CD49: 🏪 REDES | CE49: NATURVIDA
A50: 55483453000108 | B50: MADOR PRODUTOS NATURAIS E SUPLEMENTOS LT | C50: FITLAND | D50: JULIO GADRET | E50: SC | F50: =IFERROR(VLOOKUP(C50,$AS$3:$AT$10,2,FALSE()),IFERROR(VLOOKUP(C50,$AS$15:$AT$22,2,FALSE()),"")) -> 44 | G50: =IFERROR(VLOOKUP(C50,$AS$3:$AX$10,6,FALSE()),IFERROR(VLOOKUP(C50,$AS$15:$AX$22,6,FALSE()),"")) -> 0.49683951 | H50: =IFERROR(VLOOKUP(C50,$AS$3:$AY$10,7,FALSE()),IFERROR(VLOOKUP(C50,$AS$15:$AY$22,7,FALSE()),"")) -> 🟡 AMARELO | I50: =IFERROR(VLOOKUP(C50,$AS$3:$AZ$10,8,FALSE()),IFERROR(VLOOKUP(C50,$AS$15:$AZ$22,8,FALSE()),"")) -> Sell Out | K50: SUL | L50: 20559.44 | M50: 1444.77 | N50: 1509.74 | O50: 1546.12 | P50: 1586.39 | Q50: 1638.36 | R50: 1681.24 | S50: 1746.2 | T50: 1789.08 | U50: 1829.35 | V50: 1874.83 | W50: 1924.2 | X50: 1989.16 | Y50: . | Z50: =SUM(AA50:AL50) -> 8547.05 | AF50: 1889.7 | AI50: 2126.48 | AJ50: 2829.87 | AL50: 1701 | AM50: . | AN50: =IF(L50=0,0,Z50/L50) -> 0.41572387 | AO50: =IF(AN50="","",IF(AN50>=0.9,"🟢",IF(AN50>=0.7,"🟡",IF(AN50>=0.5,"🟠","🔴")))) -> 🔴 | AP50: =IF(L50=0,0,L50-Z50) -> 12012.39 | AQ50: =IF(AP50=0,"",RANK(AP50,AP$4:AP$503,0)) -> 44 | AR50: . | BA50: . | BB50: =SUM(L$4:L$503)/COUNTA(A$4:A$503) -> 9494.3999 | BC50: =SUM(M$4:M$503)/COUNTA(A$4:A$503) -> 667.20008 | BD50: =SUM(N$4:N$503)/COUNTA(A$4:A$503) -> 697.19996 | BE50: =SUM(O$4:O$503)/COUNTA(A$4:A$503) -> 713.9999 | BF50: =SUM(P$4:P$503)/COUNTA(A$4:A$503) -> 732.59984 | BG50: =SUM(Q$4:Q$503)/COUNTA(A$4:A$503) -> 756.59992 | BH50: =SUM(R$4:R$503)/COUNTA(A$4:A$503) -> 776.40004 | BI50: =SUM(S$4:S$503)/COUNTA(A$4:A$503) -> 806.40012 | BJ50: =SUM(T$4:T$503)/COUNTA(A$4:A$503) -> 826.1999 | BK50: =SUM(U$4:U$503)/COUNTA(A$4:A$503) -> 844.8002 | BL50: =SUM(V$4:V$503)/COUNTA(A$4:A$503) -> 865.7998 | BM50: =SUM(W$4:W$503)/COUNTA(A$4:A$503) -> 888.59982 | BN50: =SUM(X$4:X$503)/COUNTA(A$4:A$503) -> 918.60034 | BO50: . | BP50: =IF(Z50>=BB50,0,IFERROR(BB50+(SUMPRODUCT((Z$4:Z$503>=BB$4:BB$503)*(Z$4:Z$503-BB$4:BB$503))/MAX(1,COUNTIF(Z$4:Z$503,"<"&BB50+0.01))),BB50)) -> 10695.543 | BQ50: =IF(AA50>=BC50,0,IFERROR(BC50+SUMPRODUCT((AA$4:AA$503>=BC$4:BC$503)*(AA$4:AA$503-BC$4:BC$503))/MAX(1,COUNTIF(AA$4:AA$503,"<"&BC50+0.01)),BC50)) -> 2238.4659 | BR50: =IF(AB50>=BD50,0,IFERROR(BD50+SUMPRODUCT((AB$4:AB$503>=BD$4:BD$503)*(AB$4:AB$503-BD$4:BD$503))/MAX(1,COUNTIF(AB$4:AB$503,"<"&BD50+0.01)),BD50)) -> 3335.2938 | BS50: =IF(AC50>=BE50,0,IFERROR(BE50+SUMPRODUCT((AC$4:AC$503>=BE$4:BE$503)*(AC$4:AC$503-BE$4:BE$503))/MAX(1,COUNTIF(AC$4:AC$503,"<"&BE50+0.01)),BE50)) -> 6188.7335 | BT50: =IF(AD50>=BF50,0,IFERROR(BF50+SUMPRODUCT((AD$4:AD$503>=BF$4:BF$503)*(AD$4:AD$503-BF$4:BF$503))/MAX(1,COUNTIF(AD$4:AD$503,"<"&BF50+0.01)),BF50)) -> 11354.354 | BU50: =IF(AE50>=BG50,0,IFERROR(BG50+SUMPRODUCT((AE$4:AE$503>=BG$4:BG$503)*(AE$4:AE$503-BG$4:BG$503))/MAX(1,COUNTIF(AE$4:AE$503,"<"&BG50+0.01)),BG50)) -> 7704.8592 | BV50: =IF(AF50>=BH50,0,IFERROR(BH50+SUMPRODUCT((AF$4:AF$503>=BH$4:BH$503)*(AF$4:AF$503-BH$4:BH$503))/MAX(1,COUNTIF(AF$4:AF$503,"<"&BH50+0.01)),BH50)) -> 0 | BW50: =IF(AG50>=BI50,0,IFERROR(BI50+SUMPRODUCT((AG$4:AG$503>=BI$4:BI$503)*(AG$4:AG$503-BI$4:BI$503))/MAX(1,COUNTIF(AG$4:AG$503,"<"&BI50+0.01)),BI50)) -> 9142.1587 | BX50: =IF(AH50>=BJ50,0,IFERROR(BJ50+SUMPRODUCT((AH$4:AH$503>=BJ$4:BJ$503)*(AH$4:AH$503-BJ$4:BJ$503))/MAX(1,COUNTIF(AH$4:AH$503,"<"&BJ50+0.01)),BJ50)) -> 5621.5026 | ... CB50: =IF(AL50>=BN50,0,IFERROR(BN50+SUMPRODUCT((AL$4:AL$503>=BN$4:BN$503)*(AL$4:AL$503-BN$4:BN$503))/MAX(1,COUNTIF(AL$4:AL$503,"<"&BN50+0.01)),BN50)) -> 0 | CC50: =IF(AO50="🟢","VERDE",IF(AO50="🟡","AMARELO",IF(AO50="🟠","VERMELHO",IF(AO50="🔴","VERMELHO","ROXO")))) -> VERMELHO | CD50: 🏪 REDES | CE50: FITLAND
A51: 07621230000117 | B51: CASA MISSAO COMERCIO DE PRODUTOS NATURAI | C51: SEM GRUPO | D51: LARISSA PADILHA | E51: . | F51: =IFERROR(VLOOKUP(C51,$AS$3:$AT$10,2,FALSE()),IFERROR(VLOOKUP(C51,$AS$15:$AT$22,2,FALSE()),"")) -> 49 | G51: =IFERROR(VLOOKUP(C51,$AS$3:$AX$10,6,FALSE()),IFERROR(VLOOKUP(C51,$AS$15:$AX$22,6,FALSE()),"")) -> 0.43639135 | H51: =IFERROR(VLOOKUP(C51,$AS$3:$AY$10,7,FALSE()),IFERROR(VLOOKUP(C51,$AS$15:$AY$22,7,FALSE()),"")) -> 🟡 AMARELO | I51: =IFERROR(VLOOKUP(C51,$AS$3:$AZ$10,8,FALSE()),IFERROR(VLOOKUP(C51,$AS$15:$AZ$22,8,FALSE()),"")) -> Sell Out | K51: . | L51: 20487.34 | M51: 1439.71 | N51: 1504.44 | O51: 1540.69 | P51: 1580.83 | Q51: 1632.62 | R51: 1675.34 | S51: 1740.08 | T51: 1782.8 | U51: 1822.94 | V51: 1868.25 | W51: 1917.45 | X51: 1982.19 | Y51: . | Z51: =SUM(AA51:AL51) -> 8524 | AC51: 1197.28 | AE51: 1681.04 | AG51: 1500 | AH51: 1742.36 | AJ51: 2403.32 | AM51: . | AN51: =IF(L51=0,0,Z51/L51) -> 0.41606182 | AO51: =IF(AN51="","",IF(AN51>=0.9,"🟢",IF(AN51>=0.7,"🟡",IF(AN51>=0.5,"🟠","🔴")))) -> 🔴 | AP51: =IF(L51=0,0,L51-Z51) -> 11963.34 | AQ51: =IF(AP51=0,"",RANK(AP51,AP$4:AP$503,0)) -> 45 | AR51: . | BA51: . | BB51: =SUM(L$4:L$503)/COUNTA(A$4:A$503) -> 9494.3999 | BC51: =SUM(M$4:M$503)/COUNTA(A$4:A$503) -> 667.20008 | BD51: =SUM(N$4:N$503)/COUNTA(A$4:A$503) -> 697.19996 | BE51: =SUM(O$4:O$503)/COUNTA(A$4:A$503) -> 713.9999 | BF51: =SUM(P$4:P$503)/COUNTA(A$4:A$503) -> 732.59984 | BG51: =SUM(Q$4:Q$503)/COUNTA(A$4:A$503) -> 756.59992 | BH51: =SUM(R$4:R$503)/COUNTA(A$4:A$503) -> 776.40004 | BI51: =SUM(S$4:S$503)/COUNTA(A$4:A$503) -> 806.40012 | BJ51: =SUM(T$4:T$503)/COUNTA(A$4:A$503) -> 826.1999 | BK51: =SUM(U$4:U$503)/COUNTA(A$4:A$503) -> 844.8002 | BL51: =SUM(V$4:V$503)/COUNTA(A$4:A$503) -> 865.7998 | BM51: =SUM(W$4:W$503)/COUNTA(A$4:A$503) -> 888.59982 | BN51: =SUM(X$4:X$503)/COUNTA(A$4:A$503) -> 918.60034 | BO51: . | BP51: =IF(Z51>=BB51,0,IFERROR(BB51+(SUMPRODUCT((Z$4:Z$503>=BB$4:BB$503)*(Z$4:Z$503-BB$4:BB$503))/MAX(1,COUNTIF(Z$4:Z$503,"<"&BB51+0.01))),BB51)) -> 10695.543 | BQ51: =IF(AA51>=BC51,0,IFERROR(BC51+SUMPRODUCT((AA$4:AA$503>=BC$4:BC$503)*(AA$4:AA$503-BC$4:BC$503))/MAX(1,COUNTIF(AA$4:AA$503,"<"&BC51+0.01)),BC51)) -> 2238.4659 | BR51: =IF(AB51>=BD51,0,IFERROR(BD51+SUMPRODUCT((AB$4:AB$503>=BD$4:BD$503)*(AB$4:AB$503-BD$4:BD$503))/MAX(1,COUNTIF(AB$4:AB$503,"<"&BD51+0.01)),BD51)) -> 3335.2938 | BS51: =IF(AC51>=BE51,0,IFERROR(BE51+SUMPRODUCT((AC$4:AC$503>=BE$4:BE$503)*(AC$4:AC$503-BE$4:BE$503))/MAX(1,COUNTIF(AC$4:AC$503,"<"&BE51+0.01)),BE51)) -> 0 | BT51: =IF(AD51>=BF51,0,IFERROR(BF51+SUMPRODUCT((AD$4:AD$503>=BF$4:BF$503)*(AD$4:AD$503-BF$4:BF$503))/MAX(1,COUNTIF(AD$4:AD$503,"<"&BF51+0.01)),BF51)) -> 11354.354 | BU51: =IF(AE51>=BG51,0,IFERROR(BG51+SUMPRODUCT((AE$4:AE$503>=BG$4:BG$503)*(AE$4:AE$503-BG$4:BG$503))/MAX(1,COUNTIF(AE$4:AE$503,"<"&BG51+0.01)),BG51)) -> 0 | BV51: =IF(AF51>=BH51,0,IFERROR(BH51+SUMPRODUCT((AF$4:AF$503>=BH$4:BH$503)*(AF$4:AF$503-BH$4:BH$503))/MAX(1,COUNTIF(AF$4:AF$503,"<"&BH51+0.01)),BH51)) -> 9942.6504 | BW51: =IF(AG51>=BI51,0,IFERROR(BI51+SUMPRODUCT((AG$4:AG$503>=BI$4:BI$503)*(AG$4:AG$503-BI$4:BI$503))/MAX(1,COUNTIF(AG$4:AG$503,"<"&BI51+0.01)),BI51)) -> 0 | BX51: =IF(AH51>=BJ51,0,IFERROR(BJ51+SUMPRODUCT((AH$4:AH$503>=BJ$4:BJ$503)*(AH$4:AH$503-BJ$4:BJ$503))/MAX(1,COUNTIF(AH$4:AH$503,"<"&BJ51+0.01)),BJ51)) -> 0 | ... CB51: =IF(AL51>=BN51,0,IFERROR(BN51+SUMPRODUCT((AL$4:AL$503>=BN$4:BN$503)*(AL$4:AL$503-BN$4:BN$503))/MAX(1,COUNTIF(AL$4:AL$503,"<"&BN51+0.01)),BN51)) -> 3597.2615 | CC51: =IF(AO51="🟢","VERDE",IF(AO51="🟡","AMARELO",IF(AO51="🟠","VERMELHO",IF(AO51="🔴","VERMELHO","ROXO")))) -> VERMELHO | CD51: 🌎 REGIÕES | CE51: SEM REDE
A52: 24583557000322 | B52: SHOPPER COMERCIO ALIMENTICIO LTDA | C52: SP CAPITAL | D52: LARISSA PADILHA | E52: SP | F52: =IFERROR(VLOOKUP(C52,$AS$3:$AT$10,2,FALSE()),IFERROR(VLOOKUP(C52,$AS$15:$AT$22,2,FALSE()),"")) -> 29 | G52: =IFERROR(VLOOKUP(C52,$AS$3:$AX$10,6,FALSE()),IFERROR(VLOOKUP(C52,$AS$15:$AX$22,6,FALSE()),"")) -> 0.42584507 | H52: =IFERROR(VLOOKUP(C52,$AS$3:$AY$10,7,FALSE()),IFERROR(VLOOKUP(C52,$AS$15:$AY$22,7,FALSE()),"")) -> 🟡 AMARELO | I52: =IFERROR(VLOOKUP(C52,$AS$3:$AZ$10,8,FALSE()),IFERROR(VLOOKUP(C52,$AS$15:$AZ$22,8,FALSE()),"")) -> Sell Out | K52: SP CAPITAL | L52: 20475.4 | M52: 1438.87 | N52: 1503.56 | O52: 1539.8 | P52: 1579.91 | Q52: 1631.67 | R52: 1674.37 | S52: 1739.06 | T52: 1781.76 | U52: 1821.88 | V52: 1867.16 | W52: 1916.33 | X52: 1981.03 | Y52: . | Z52: =SUM(AA52:AL52) -> 8234.2 | AA52: 1721.4 | AC52: 1630.8 | AE52: 3311 | AJ52: 1571 | AM52: . | AN52: =IF(L52=0,0,Z52/L52) -> 0.40215087 | AO52: =IF(AN52="","",IF(AN52>=0.9,"🟢",IF(AN52>=0.7,"🟡",IF(AN52>=0.5,"🟠","🔴")))) -> 🔴 | AP52: =IF(L52=0,0,L52-Z52) -> 12241.2 | AQ52: =IF(AP52=0,"",RANK(AP52,AP$4:AP$503,0)) -> 43 | AR52: . | BA52: . | BB52: =SUM(L$4:L$503)/COUNTA(A$4:A$503) -> 9494.3999 | BC52: =SUM(M$4:M$503)/COUNTA(A$4:A$503) -> 667.20008 | BD52: =SUM(N$4:N$503)/COUNTA(A$4:A$503) -> 697.19996 | BE52: =SUM(O$4:O$503)/COUNTA(A$4:A$503) -> 713.9999 | BF52: =SUM(P$4:P$503)/COUNTA(A$4:A$503) -> 732.59984 | BG52: =SUM(Q$4:Q$503)/COUNTA(A$4:A$503) -> 756.59992 | BH52: =SUM(R$4:R$503)/COUNTA(A$4:A$503) -> 776.40004 | BI52: =SUM(S$4:S$503)/COUNTA(A$4:A$503) -> 806.40012 | BJ52: =SUM(T$4:T$503)/COUNTA(A$4:A$503) -> 826.1999 | BK52: =SUM(U$4:U$503)/COUNTA(A$4:A$503) -> 844.8002 | BL52: =SUM(V$4:V$503)/COUNTA(A$4:A$503) -> 865.7998 | BM52: =SUM(W$4:W$503)/COUNTA(A$4:A$503) -> 888.59982 | BN52: =SUM(X$4:X$503)/COUNTA(A$4:A$503) -> 918.60034 | BO52: . | BP52: =IF(Z52>=BB52,0,IFERROR(BB52+(SUMPRODUCT((Z$4:Z$503>=BB$4:BB$503)*(Z$4:Z$503-BB$4:BB$503))/MAX(1,COUNTIF(Z$4:Z$503,"<"&BB52+0.01))),BB52)) -> 10695.543 | BQ52: =IF(AA52>=BC52,0,IFERROR(BC52+SUMPRODUCT((AA$4:AA$503>=BC$4:BC$503)*(AA$4:AA$503-BC$4:BC$503))/MAX(1,COUNTIF(AA$4:AA$503,"<"&BC52+0.01)),BC52)) -> 0 | BR52: =IF(AB52>=BD52,0,IFERROR(BD52+SUMPRODUCT((AB$4:AB$503>=BD$4:BD$503)*(AB$4:AB$503-BD$4:BD$503))/MAX(1,COUNTIF(AB$4:AB$503,"<"&BD52+0.01)),BD52)) -> 3335.2938 | BS52: =IF(AC52>=BE52,0,IFERROR(BE52+SUMPRODUCT((AC$4:AC$503>=BE$4:BE$503)*(AC$4:AC$503-BE$4:BE$503))/MAX(1,COUNTIF(AC$4:AC$503,"<"&BE52+0.01)),BE52)) -> 0 | BT52: =IF(AD52>=BF52,0,IFERROR(BF52+SUMPRODUCT((AD$4:AD$503>=BF$4:BF$503)*(AD$4:AD$503-BF$4:BF$503))/MAX(1,COUNTIF(AD$4:AD$503,"<"&BF52+0.01)),BF52)) -> 11354.354 | BU52: =IF(AE52>=BG52,0,IFERROR(BG52+SUMPRODUCT((AE$4:AE$503>=BG$4:BG$503)*(AE$4:AE$503-BG$4:BG$503))/MAX(1,COUNTIF(AE$4:AE$503,"<"&BG52+0.01)),BG52)) -> 0 | BV52: =IF(AF52>=BH52,0,IFERROR(BH52+SUMPRODUCT((AF$4:AF$503>=BH$4:BH$503)*(AF$4:AF$503-BH$4:BH$503))/MAX(1,COUNTIF(AF$4:AF$503,"<"&BH52+0.01)),BH52)) -> 9942.6504 | BW52: =IF(AG52>=BI52,0,IFERROR(BI52+SUMPRODUCT((AG$4:AG$503>=BI$4:BI$503)*(AG$4:AG$503-BI$4:BI$503))/MAX(1,COUNTIF(AG$4:AG$503,"<"&BI52+0.01)),BI52)) -> 9142.1587 | BX52: =IF(AH52>=BJ52,0,IFERROR(BJ52+SUMPRODUCT((AH$4:AH$503>=BJ$4:BJ$503)*(AH$4:AH$503-BJ$4:BJ$503))/MAX(1,COUNTIF(AH$4:AH$503,"<"&BJ52+0.01)),BJ52)) -> 5621.5026 | ... CB52: =IF(AL52>=BN52,0,IFERROR(BN52+SUMPRODUCT((AL$4:AL$503>=BN$4:BN$503)*(AL$4:AL$503-BN$4:BN$503))/MAX(1,COUNTIF(AL$4:AL$503,"<"&BN52+0.01)),BN52)) -> 3597.2615 | CC52: =IF(AO52="🟢","VERDE",IF(AO52="🟡","AMARELO",IF(AO52="🟠","VERMELHO",IF(AO52="🔴","VERMELHO","ROXO")))) -> VERMELHO | CD52: 🌎 REGIÕES | CE52: SEM REDE
A53: 58434075000160 | B53: MISTER GRAOS SS MOCOQUINHA LTDA - ME | C53: RJ + ES + MG | D53: LARISSA PADILHA | E53: MG | F53: =IFERROR(VLOOKUP(C53,$AS$3:$AT$10,2,FALSE()),IFERROR(VLOOKUP(C53,$AS$15:$AT$22,2,FALSE()),"")) -> 49 | G53: =IFERROR(VLOOKUP(C53,$AS$3:$AX$10,6,FALSE()),IFERROR(VLOOKUP(C53,$AS$15:$AX$22,6,FALSE()),"")) -> 0.46396509 | H53: =IFERROR(VLOOKUP(C53,$AS$3:$AY$10,7,FALSE()),IFERROR(VLOOKUP(C53,$AS$15:$AY$22,7,FALSE()),"")) -> 🟡 AMARELO | I53: =IFERROR(VLOOKUP(C53,$AS$3:$AZ$10,8,FALSE()),IFERROR(VLOOKUP(C53,$AS$15:$AZ$22,8,FALSE()),"")) -> Sell Out | K53: RJ + ES + MG | L53: 20181.87 | M53: 1418.24 | N53: 1482.01 | O53: 1517.72 | P53: 1557.26 | Q53: 1608.28 | R53: 1650.36 | S53: 1714.13 | T53: 1756.22 | U53: 1795.76 | V53: 1840.4 | W53: 1888.86 | X53: 1952.63 | Y53: . | Z53: =SUM(AA53:AL53) -> 8808.36 | AC53: 5098.15 | AF53: 1593.85 | AH53: 2116.36 | AM53: . | AN53: =IF(L53=0,0,Z53/L53) -> 0.43644915 | AO53: =IF(AN53="","",IF(AN53>=0.9,"🟢",IF(AN53>=0.7,"🟡",IF(AN53>=0.5,"🟠","🔴")))) -> 🔴 | AP53: =IF(L53=0,0,L53-Z53) -> 11373.51 | AQ53: =IF(AP53=0,"",RANK(AP53,AP$4:AP$503,0)) -> 51 | AR53: . | BA53: . | BB53: =SUM(L$4:L$503)/COUNTA(A$4:A$503) -> 9494.3999 | BC53: =SUM(M$4:M$503)/COUNTA(A$4:A$503) -> 667.20008 | BD53: =SUM(N$4:N$503)/COUNTA(A$4:A$503) -> 697.19996 | BE53: =SUM(O$4:O$503)/COUNTA(A$4:A$503) -> 713.9999 | BF53: =SUM(P$4:P$503)/COUNTA(A$4:A$503) -> 732.59984 | BG53: =SUM(Q$4:Q$503)/COUNTA(A$4:A$503) -> 756.59992 | BH53: =SUM(R$4:R$503)/COUNTA(A$4:A$503) -> 776.40004 | BI53: =SUM(S$4:S$503)/COUNTA(A$4:A$503) -> 806.40012 | BJ53: =SUM(T$4:T$503)/COUNTA(A$4:A$503) -> 826.1999 | BK53: =SUM(U$4:U$503)/COUNTA(A$4:A$503) -> 844.8002 | BL53: =SUM(V$4:V$503)/COUNTA(A$4:A$503) -> 865.7998 | BM53: =SUM(W$4:W$503)/COUNTA(A$4:A$503) -> 888.59982 | BN53: =SUM(X$4:X$503)/COUNTA(A$4:A$503) -> 918.60034 | BO53: . | BP53: =IF(Z53>=BB53,0,IFERROR(BB53+(SUMPRODUCT((Z$4:Z$503>=BB$4:BB$503)*(Z$4:Z$503-BB$4:BB$503))/MAX(1,COUNTIF(Z$4:Z$503,"<"&BB53+0.01))),BB53)) -> 10695.543 | BQ53: =IF(AA53>=BC53,0,IFERROR(BC53+SUMPRODUCT((AA$4:AA$503>=BC$4:BC$503)*(AA$4:AA$503-BC$4:BC$503))/MAX(1,COUNTIF(AA$4:AA$503,"<"&BC53+0.01)),BC53)) -> 2238.4659 | BR53: =IF(AB53>=BD53,0,IFERROR(BD53+SUMPRODUCT((AB$4:AB$503>=BD$4:BD$503)*(AB$4:AB$503-BD$4:BD$503))/MAX(1,COUNTIF(AB$4:AB$503,"<"&BD53+0.01)),BD53)) -> 3335.2938 | BS53: =IF(AC53>=BE53,0,IFERROR(BE53+SUMPRODUCT((AC$4:AC$503>=BE$4:BE$503)*(AC$4:AC$503-BE$4:BE$503))/MAX(1,COUNTIF(AC$4:AC$503,"<"&BE53+0.01)),BE53)) -> 0 | BT53: =IF(AD53>=BF53,0,IFERROR(BF53+SUMPRODUCT((AD$4:AD$503>=BF$4:BF$503)*(AD$4:AD$503-BF$4:BF$503))/MAX(1,COUNTIF(AD$4:AD$503,"<"&BF53+0.01)),BF53)) -> 11354.354 | BU53: =IF(AE53>=BG53,0,IFERROR(BG53+SUMPRODUCT((AE$4:AE$503>=BG$4:BG$503)*(AE$4:AE$503-BG$4:BG$503))/MAX(1,COUNTIF(AE$4:AE$503,"<"&BG53+0.01)),BG53)) -> 7704.8592 | BV53: =IF(AF53>=BH53,0,IFERROR(BH53+SUMPRODUCT((AF$4:AF$503>=BH$4:BH$503)*(AF$4:AF$503-BH$4:BH$503))/MAX(1,COUNTIF(AF$4:AF$503,"<"&BH53+0.01)),BH53)) -> 0 | BW53: =IF(AG53>=BI53,0,IFERROR(BI53+SUMPRODUCT((AG$4:AG$503>=BI$4:BI$503)*(AG$4:AG$503-BI$4:BI$503))/MAX(1,COUNTIF(AG$4:AG$503,"<"&BI53+0.01)),BI53)) -> 9142.1587 | BX53: =IF(AH53>=BJ53,0,IFERROR(BJ53+SUMPRODUCT((AH$4:AH$503>=BJ$4:BJ$503)*(AH$4:AH$503-BJ$4:BJ$503))/MAX(1,COUNTIF(AH$4:AH$503,"<"&BJ53+0.01)),BJ53)) -> 0 | ... CB53: =IF(AL53>=BN53,0,IFERROR(BN53+SUMPRODUCT((AL$4:AL$503>=BN$4:BN$503)*(AL$4:AL$503-BN$4:BN$503))/MAX(1,COUNTIF(AL$4:AL$503,"<"&BN53+0.01)),BN53)) -> 3597.2615 | CC53: =IF(AO53="🟢","VERDE",IF(AO53="🟡","AMARELO",IF(AO53="🟠","VERMELHO",IF(AO53="🔴","VERMELHO","ROXO")))) -> VERMELHO | CD53: 🌎 REGIÕES | CE53: SEM REDE
A54: 34404590000130 | B54: JOAO COSTA SOARES E CIA LTDA | C54: NORDESTE (SEM MA) | D54: LARISSA PADILHA | E54: BA | F54: =IFERROR(VLOOKUP(C54,$AS$3:$AT$10,2,FALSE()),IFERROR(VLOOKUP(C54,$AS$15:$AT$22,2,FALSE()),"")) -> 29 | G54: =IFERROR(VLOOKUP(C54,$AS$3:$AX$10,6,FALSE()),IFERROR(VLOOKUP(C54,$AS$15:$AX$22,6,FALSE()),"")) -> 0.45856407 | H54: =IFERROR(VLOOKUP(C54,$AS$3:$AY$10,7,FALSE()),IFERROR(VLOOKUP(C54,$AS$15:$AY$22,7,FALSE()),"")) -> 🟡 AMARELO | I54: =IFERROR(VLOOKUP(C54,$AS$3:$AZ$10,8,FALSE()),IFERROR(VLOOKUP(C54,$AS$15:$AZ$22,8,FALSE()),"")) -> Sell Out | K54: NORDESTE (SEM MA) | L54: 19979.22 | M54: 1404 | N54: 1467.13 | O54: 1502.48 | P54: 1541.62 | Q54: 1592.13 | R54: 1633.79 | S54: 1696.92 | T54: 1738.59 | U54: 1777.73 | V54: 1821.92 | W54: 1869.89 | X54: 1933.02 | Y54: . | Z54: =SUM(AA54:AL54) -> 8034.66 | AA54: 4212.18 | AI54: 3822.48 | AM54: . | AN54: =IF(L54=0,0,Z54/L54) -> 0.40215083 | AO54: =IF(AN54="","",IF(AN54>=0.9,"🟢",IF(AN54>=0.7,"🟡",IF(AN54>=0.5,"🟠","🔴")))) -> 🔴 | AP54: =IF(L54=0,0,L54-Z54) -> 11944.56 | AQ54: =IF(AP54=0,"",RANK(AP54,AP$4:AP$503,0)) -> 46 | AR54: . | BA54: . | BB54: =SUM(L$4:L$503)/COUNTA(A$4:A$503) -> 9494.3999 | BC54: =SUM(M$4:M$503)/COUNTA(A$4:A$503) -> 667.20008 | BD54: =SUM(N$4:N$503)/COUNTA(A$4:A$503) -> 697.19996 | BE54: =SUM(O$4:O$503)/COUNTA(A$4:A$503) -> 713.9999 | BF54: =SUM(P$4:P$503)/COUNTA(A$4:A$503) -> 732.59984 | BG54: =SUM(Q$4:Q$503)/COUNTA(A$4:A$503) -> 756.59992 | BH54: =SUM(R$4:R$503)/COUNTA(A$4:A$503) -> 776.40004 | BI54: =SUM(S$4:S$503)/COUNTA(A$4:A$503) -> 806.40012 | BJ54: =SUM(T$4:T$503)/COUNTA(A$4:A$503) -> 826.1999 | BK54: =SUM(U$4:U$503)/COUNTA(A$4:A$503) -> 844.8002 | BL54: =SUM(V$4:V$503)/COUNTA(A$4:A$503) -> 865.7998 | BM54: =SUM(W$4:W$503)/COUNTA(A$4:A$503) -> 888.59982 | BN54: =SUM(X$4:X$503)/COUNTA(A$4:A$503) -> 918.60034 | BO54: . | BP54: =IF(Z54>=BB54,0,IFERROR(BB54+(SUMPRODUCT((Z$4:Z$503>=BB$4:BB$503)*(Z$4:Z$503-BB$4:BB$503))/MAX(1,COUNTIF(Z$4:Z$503,"<"&BB54+0.01))),BB54)) -> 10695.543 | BQ54: =IF(AA54>=BC54,0,IFERROR(BC54+SUMPRODUCT((AA$4:AA$503>=BC$4:BC$503)*(AA$4:AA$503-BC$4:BC$503))/MAX(1,COUNTIF(AA$4:AA$503,"<"&BC54+0.01)),BC54)) -> 0 | BR54: =IF(AB54>=BD54,0,IFERROR(BD54+SUMPRODUCT((AB$4:AB$503>=BD$4:BD$503)*(AB$4:AB$503-BD$4:BD$503))/MAX(1,COUNTIF(AB$4:AB$503,"<"&BD54+0.01)),BD54)) -> 3335.2938 | BS54: =IF(AC54>=BE54,0,IFERROR(BE54+SUMPRODUCT((AC$4:AC$503>=BE$4:BE$503)*(AC$4:AC$503-BE$4:BE$503))/MAX(1,COUNTIF(AC$4:AC$503,"<"&BE54+0.01)),BE54)) -> 6188.7335 | BT54: =IF(AD54>=BF54,0,IFERROR(BF54+SUMPRODUCT((AD$4:AD$503>=BF$4:BF$503)*(AD$4:AD$503-BF$4:BF$503))/MAX(1,COUNTIF(AD$4:AD$503,"<"&BF54+0.01)),BF54)) -> 11354.354 | BU54: =IF(AE54>=BG54,0,IFERROR(BG54+SUMPRODUCT((AE$4:AE$503>=BG$4:BG$503)*(AE$4:AE$503-BG$4:BG$503))/MAX(1,COUNTIF(AE$4:AE$503,"<"&BG54+0.01)),BG54)) -> 7704.8592 | BV54: =IF(AF54>=BH54,0,IFERROR(BH54+SUMPRODUCT((AF$4:AF$503>=BH$4:BH$503)*(AF$4:AF$503-BH$4:BH$503))/MAX(1,COUNTIF(AF$4:AF$503,"<"&BH54+0.01)),BH54)) -> 9942.6504 | BW54: =IF(AG54>=BI54,0,IFERROR(BI54+SUMPRODUCT((AG$4:AG$503>=BI$4:BI$503)*(AG$4:AG$503-BI$4:BI$503))/MAX(1,COUNTIF(AG$4:AG$503,"<"&BI54+0.01)),BI54)) -> 9142.1587 | BX54: =IF(AH54>=BJ54,0,IFERROR(BJ54+SUMPRODUCT((AH$4:AH$503>=BJ$4:BJ$503)*(AH$4:AH$503-BJ$4:BJ$503))/MAX(1,COUNTIF(AH$4:AH$503,"<"&BJ54+0.01)),BJ54)) -> 5621.5026 | ... CB54: =IF(AL54>=BN54,0,IFERROR(BN54+SUMPRODUCT((AL$4:AL$503>=BN$4:BN$503)*(AL$4:AL$503-BN$4:BN$503))/MAX(1,COUNTIF(AL$4:AL$503,"<"&BN54+0.01)),BN54)) -> 3597.2615 | CC54: =IF(AO54="🟢","VERDE",IF(AO54="🟡","AMARELO",IF(AO54="🟠","VERMELHO",IF(AO54="🔴","VERMELHO","ROXO")))) -> VERMELHO | CD54: 🌎 REGIÕES | CE54: SEM REDE
