Workbook

Sheet Draft
A1: Nome fantasia | B1: CNPJ/CPF | C1: Estado | D1: Vendedor do último pedido | E1: Data do último pedido | F1: Valor do último pedido | G1: Dias sem comprar | H1: Ciclo médio de compra | I1: Situação
A2: BANCA12 ARMAZEM DE PRODUTOS NATURAIS LTDA | B2: 92.916.360/0002-37 | C2: RS | D2: Manu Ditzel | E2: 07/10/2025 | F2: 2075.26 | I2: Ativo
A3: GRAO VIDA | B3: 31.599.810/0001-30 | C3: SP | D3: Larissa Padilha | E3: 06/10/2025 | F3: 3508.11 | G3: 1 | H3: 46.6667 | I3: Ativo
A4: SUPERMERCADOS PAGOTO LTDA | B4: 27.277.961/0001-02 | C4: ES | D4: Larissa Padilha | E4: 06/10/2025 | F4: 1215.8 | G4: 1 | I4: Ativo
A5: GRAO E VIDA | B5: 43.590.125/0001-21 | C5: MG | D5: Larissa Padilha | E5: 06/10/2025 | F5: 3075.94 | G5: 1 | I5: Ativo
A6: LARISSA DA SILVA PADILHA | B6: 42.149.466/0001-01 | C6: SC | D6: Larissa Padilha | E6: 01/10/2025 | F6: 675.8 | G6: 6 | I6: Ativo
A7: 49.844.222 LUIS CARLOS VIEIRA | B7: 49.844.222/0001-80 | C7: SP | D7: Larissa Padilha | E7: 01/10/2025 | F7: 659.66 | G7: 6 | H7: 62.5 | I7: Ativo
A8: MS NUTRICAO | B8: 53.191.899/0001-33 | C8: SC | D8: Julio Gadret | E8: 01/10/2025 | F8: 1076.41 | G8: 6 | H8: 97 | I8: Ativo
A9: VIDA LEVE BARIGUI | B9: 54.423.411/0001-19 | C9: PR | D9: Central - Daiane | E9: 01/10/2025 | F9: 603 | G9: 6 | H9: 64 | I9: Ativo
A10: GAN NUTRICAO | B10: 34.313.930/0001-17 | C10: SC | D10: Julio Gadret | E10: 01/10/2025 | F10: 1593.58 | G10: 6 | I10: Ativo
A11: VALDECI APARECIDO DE NICOLAI | B11: 37.633.350/0001-03 | C11: SP | D11: Larissa Padilha | E11: 01/10/2025 | F11: 1142.96 | G11: 6 | I11: Ativo
A12: MUNDO VERDE VOCE MAIS SAUDAVEL | B12: 28.019.593/0001-57 | C12: SP | D12: Central - Daiane | E12: 30/09/2025 | F12: 1928.84 | G12: 7 | H12: 55 | I12: Ativo
A13: LOJA VIDA LEVE VILA ARENS | B13: 62.004.109/0001-54 | C13: SP | D13: Central - Daiane | E13: 30/09/2025 | F13: 1570.68 | G13: 7 | I13: Ativo
A14: VIDA NATURAL FSA | B14: 62.617.017/0001-40 | C14: BA | D14: Central - Daiane | E14: 30/09/2025 | F14: 1567.26 | G14: 7 | I14: Ativo
A15: VIDA NATURAL | B15: 61.791.187/0001-83 | C15: PA | D15: Central - Daiane | E15: 30/09/2025 | F15: 1567.26 | G15: 7 | I15: Ativo
A16: C.CORREA LTDA | B16: 62.106.171/0001-57 | C16: PR | D16: Central - Daiane | E16: 30/09/2025 | F16: 1618.97 | G16: 7 | I16: Ativo
A17: AVILA SUPLEMENTOS | B17: 16.966.212/0001-68 | C17: SC | D17: Julio Gadret | E17: 29/09/2025 | F17: 678 | G17: 8 | I17: Ativo
A18: Ávila Natural | B18: 76.384.908/0001-08 | C18: SC | D18: Julio Gadret | E18: 29/09/2025 | F18: 658.76 | G18: 8 | I18: Ativo
A19: FRANQUIA FITLAND BLUMENAU | B19: 40.917.018/0001-77 | C19: SC | D19: Julio Gadret | E19: 29/09/2025 | F19: 1347.96 | G19: 8 | H19: 27.5 | I19: Ativo
A20: FIT LAGES COMERCIO DE SUPLEMENTOS E PRODUTOS NATURAIS | B20: 52.607.036/0001-31 | C20: SC | D20: Julio Gadret | E20: 29/09/2025 | F20: 774.24 | G20: 8 | H20: 34 | I20: Ativo
A21: FIT SJB | B21: 43.732.530/0001-37 | C21: SC | D21: Julio Gadret | E21: 29/09/2025 | F21: 1304.15 | G21: 8 | H21: 44.3333 | I21: Ativo
A22: L & M NUTRICAO | B22: 52.261.228/0002-10 | C22: SC | D22: Julio Gadret | E22: 29/09/2025 | F22: 1216.76 | G22: 8 | H22: 51.5 | I22: Ativo
A23: FITLAND BLUMENAU AGUA VERDE | B23: 49.982.339/0001-20 | C23: SC | D23: Julio Gadret | E23: 29/09/2025 | F23: 2074.89 | G23: 8 | H23: 27.5 | I23: Ativo
A24: L.A. PRODUTOS NATURAIS | B24: 56.174.184/0001-60 | C24: SC | D24: Julio Gadret | E24: 29/09/2025 | F24: 1254.11 | G24: 8 | I24: Ativo
A25: MS DISTRIBUIDORA | B25: 37.790.248/0001-03 | C25: PR | D25: Manu Ditzel | E25: 29/09/2025 | F25: 985.5 | G25: 8 | I25: Ativo
A26: MUNDO VERDE | B26: 72.500.887/0001-98 | C26: RJ | D26: Manu Ditzel | E26: 29/09/2025 | F26: 1226.35 | G26: 8 | H26: 96 | I26: Ativo
A27: FIT PEDRA BRANCA | B27: 60.546.169/0001-73 | C27: SC | D27: Julio Gadret | E27: 29/09/2025 | F27: 1016.3 | G27: 8 | H27: 109 | I27: Ativo
A28: CPQ BRASIL S/A - EM RECUPERACAO JUDICIAL | B28: 74.552.068/0001-10 | C28: SP | D28: Larissa Padilha | E28: 29/09/2025 | F28: 2015.52 | G28: 8 | I28: Ativo
A29: HENRI G. VALCARENGHI LTDA | B29: 57.963.322/0001-53 | C29: RS | D29: Central - Daiane | E29: 29/09/2025 | F29: 871.91 | G29: 8 | I29: Ativo
A30: PICADO'S DA TERRA PRODUTOS NATURAIS | B30: 37.680.783/0002-92 | C30: SC | D30: Julio Gadret | E30: 26/09/2025 | F30: 3353.25 | G30: 11 | I30: Ativo
A31: CSJ BRASIL ALIMENTOS LTDA | B31: 58.363.567/0001-02 | C31: SC | D31: Julio Gadret | E31: 26/09/2025 | F31: 2710.89 | G31: 11 | I31: Ativo
A32: ASSOCIACAO DOS FENILCETONURICOS E HOMOCISTINURICOS DO PARANA - AFEH-PR | B32: 72.326.119/0001-60 | C32: PR | D32: Manu Ditzel | E32: 26/09/2025 | F32: 1388.52 | G32: 11 | H32: 133 | I32: Ativo
A33: MARILIA RAFAELA FERREIRA DA LUZ LTDA | B33: 61.746.555/0001-71 | C33: PR | D33: Central - Daiane | E33: 26/09/2025 | F33: 681.47 | G33: 11 | H33: 32 | I33: Ativo
A34: UNIMED JARAGUA DO SUL | B34: 03.855.214/0002-19 | C34: SC | D34: Manu Ditzel | E34: 26/09/2025 | F34: 433.84 | G34: 11 | I34: Ativo
A35: PICADOS DA TERRA | B35: 59.633.825/0001-96 | C35: SC | D35: Julio Gadret | E35: 26/09/2025 | F35: 3353.25 | G35: 11 | I35: Ativo
A36: TUDO EM GRAOS COMERCIO DE ALIMENTOS LTDA | B36: 20.474.456/0001-09 | C36: RS | D36: Central - Daiane | E36: 25/09/2025 | F36: 859.47 | G36: 12 | I36: Ativo
A37: VILLA DOS GRAOS | B37: 31.118.319/0001-40 | C37: SC | D37: Julio Gadret | E37: 25/09/2025 | F37: 2421.99 | G37: 12 | I37: Ativo
A38: EMPORIO POMAR URBANO | B38: 22.332.946/0001-98 | C38: SC | D38: Manu Ditzel | E38: 25/09/2025 | F38: 1354.15 | G38: 12 | H38: 41 | I38: Ativo
A39: VERCATTO BOUTIQUE SÁUDAVEL | B39: 41.711.232/0001-35 | C39: PR | D39: Central - Daiane | E39: 25/09/2025 | F39: 945 | G39: 12 | H39: 22 | I39: Ativo
A40: CAPITAL FITNESS - 2/3 | B40: 43.922.481/0002-86 | C40: TO | D40: Larissa Padilha | E40: 25/09/2025 | F40: 2013.98 | G40: 12 | H40: 94 | I40: Ativo
A41: VIVA PORTO DE GALINHAS RESORT | B41: 00.939.085/0001-78 | C41: PE | D41: Manu Ditzel | E41: 25/09/2025 | F41: 5260.84 | G41: 12 | H41: 77 | I41: Ativo
A42: SUPERACAO & VIDA SAUDAVEL | B42: 34.060.666/0001-57 | C42: SP | D42: Manu Ditzel | E42: 25/09/2025 | F42: 1781.13 | G42: 12 | H42: 23.25 | I42: Ativo
A43: DOCE PUDIM | B43: 29.619.670/0001-72 | C43: GO | D43: Manu Ditzel | E43: 25/09/2025 | F43: 1648.08 | G43: 12 | I43: Ativo
A44: VILLA DOS GRAOS | B44: 60.822.789/0001-98 | C44: SC | D44: Julio Gadret | E44: 25/09/2025 | F44: 2421.99 | G44: 12 | I44: Ativo
A45: SUPERMERCADO MERCOCENTRO | B45: 05.382.867/0002-53 | C45: SC | D45: Manu Ditzel | E45: 25/09/2025 | F45: 2794.2 | G45: 12 | I45: Ativo
A46: NATURHAUS | B46: 08.626.347/0001-56 | C46: SC | D46: Manu Ditzel | E46: 24/09/2025 | F46: 1025.88 | G46: 13 | H46: 100 | I46: Ativo
A47: CHOKOLATEN | B47: 41.887.017/0001-90 | C47: SC | D47: Manu Ditzel | E47: 24/09/2025 | F47: 6573.58 | G47: 13 | H47: 32 | I47: Ativo
A48: ACADEMIA LIFE ENERGY | B48: 13.154.456/0002-39 | C48: PR | D48: Manu Ditzel | E48: 24/09/2025 | F48: 798 | G48: 13 | H48: 49 | I48: Ativo
A49: EXPRESSO CEREALISTA | B49: 49.366.518/0001-32 | C49: RJ | D49: Larissa Padilha | E49: 23/09/2025 | F49: 2174.72 | G49: 14 | H49: 69.5 | I49: Ativo
A50: Vida leve Barreiras | B50: 52.169.809/0001-45 | C50: BA | D50: Central - Daiane | E50: 23/09/2025 | F50: 1603.62 | G50: 14 | I50: Ativo
A51: KORIN | B51: 18.885.226/0001-82 | C51: RJ | D51: Larissa Padilha | E51: 23/09/2025 | F51: 1269.85 | G51: 14 | H51: 83.5 | I51: Ativo
A52: PRO FIT SUPLEMENTOS | B52: 57.701.048/0001-44 | C52: SC | D52: Central - Daiane | E52: 23/09/2025 | F52: 1393.62 | G52: 14 | H52: 88 | I52: Ativo
A53: SUPERMERCADO OFERTAO | B53: 07.316.826/0001-03 | C53: SC | D53: Manu Ditzel | E53: 23/09/2025 | F53: 1824.33 | G53: 14 | H53: 38 | I53: Ativo
A54: LAURA ISABEL RICARDO OCHOA | B54: 52.655.585/0001-81 | C54: BA | D54: Larissa Padilha | E54: 23/09/2025 | F54: 727.86 | G54: 14 | H54: 19 | I54: Ativo
A55: CONVENIENCIA D-PORT | B55: 42.627.934/0001-06 | C55: SP | D55: Larissa Padilha | E55: 23/09/2025 | F55: 1809 | G55: 14 | I55: Ativo
A56: MAGOGA HORTIFRUTI LTDA | B56: 54.211.982/0001-90 | C56: SP | D56: Larissa Padilha | E56: 22/09/2025 | F56: 1879.39 | G56: 15 | H56: 34.2 | I56: Ativo
A57: CATIMBAU | B57: 47.725.529/0001-36 | C57: SP | D57: Manu Ditzel | E57: 22/09/2025 | F57: 681.48 | G57: 15 | I57: Ativo
A58: MENEGAZ SUPERMERCADO 2 | B58: 95.772.216/0002-62 | C58: SC | D58: Manu Ditzel | E58: 22/09/2025 | F58: 2525.84 | G58: 15 | I58: Ativo
A59: EMPÓRIO GAIA | B59: 28.180.051/0001-61 | C59: RS | D59: Manu Ditzel | E59: 19/09/2025 | F59: 658.4 | G59: 18 | H59: 85 | I59: Ativo
A60: 55.274.946 MARCELO FERREIRA BASTOS JUNIOR | B60: 55.274.946/0001-38 | C60: BA | D60: Larissa Padilha | E60: 18/09/2025 | F60: 1427.88 | G60: 19 | H60: 66 | I60: Ativo
A61: TROPICAL SUPERMERCADOS | B61: 23.014.826/0001-05 | C61: MT | D61: Larissa Padilha | E61: 18/09/2025 | F61: 5299.97 | G61: 19 | H61: 29 | I61: Ativo
A62: SUPERMERCADO SERVE BEM | B62: 02.672.868/0001-63 | C62: MG | D62: Larissa Padilha | E62: 18/09/2025 | F62: 1542.37 | G62: 19 | H62: 80 | I62: Ativo
A63: POSTO LP | B63: 03.207.136/0001-65 | C63: SC | D63: Manu Ditzel | E63: 18/09/2025 | F63: 692.03 | G63: 19 | H63: 49 | I63: Ativo
A64: Divina Terra Capão da Canoa | B64: 49.300.020/0001-77 | C64: RS | D64: Central - Daiane | E64: 17/09/2025 | F64: 4972.49 | G64: 20 | I64: Ativo
A65: FORCE SUPLEMENTOS | B65: 26.240.684/0002-73 | C65: SC | D65: Manu Ditzel | E65: 17/09/2025 | F65: 2129.81 | G65: 20 | H65: 22 | I65: Ativo
A66: FIT & GRANEL | B66: 41.069.473/0001-22 | C66: MG | D66: Larissa Padilha | E66: 17/09/2025 | F66: 1680.08 | G66: 20 | H66: 28 | I66: Ativo
A67: CEREALISSIMA MGV | B67: 28.825.262/0001-04 | C67: GO | D67: Larissa Padilha | E67: 17/09/2025 | F67: 1442.87 | G67: 20 | H67: 40 | I67: Ativo
A68: Pro Abelha Comercio e Ind Prod Alimentcios LTDA | B68: 31.983.992/0001-48 | C68: RJ | D68: Manu Ditzel | E68: 17/09/2025 | F68: 6510.59 | G68: 20 | I68: Ativo
A69: SUPERMERCADO REDEPAS | B69: 04.755.895/0001-25 | C69: SP | D69: Larissa Padilha | E69: 17/09/2025 | F69: 1215.54 | G69: 20 | H69: 79 | I69: Ativo
A70: SWEET AND FIT ATELIER | B70: 37.370.567/0001-60 | C70: SP | D70: Manu Ditzel | E70: 17/09/2025 | F70: 3231.74 | G70: 20 | H70: 32 | I70: Ativo
A71: 51.599.613 GENESIO PAIXAO DE JESUS | B71: 51.599.613/0001-28 | C71: SP | D71: Manu Ditzel | E71: 17/09/2025 | F71: 687.6 | G71: 20 | I71: Ativo
A72: NEM PEIXE | B72: 56.608.812/0001-79 | C72: RS | D72: Manu Ditzel | E72: 17/09/2025 | F72: 683.35 | G72: 20 | H72: 33 | I72: Ativo
A73: ESSENCIAS E FESTAS CONFEITARIA | B73: 46.894.141/0001-04 | C73: PI | D73: Manu Ditzel | E73: 17/09/2025 | F73: 2682.5 | G73: 20 | I73: Ativo
A74: MINHA QUITANDINHA | B74: 59.087.175/0001-20 | C74: RJ | D74: Manu Ditzel | E74: 17/09/2025 | F74: 668.57 | G74: 20 | I74: Ativo
A75: DIVINA TERRA - BLUMENAU | B75: 62.341.898/0001-19 | C75: SC | D75: Central - Daiane | E75: 17/09/2025 | F75: 1204.22 | G75: 20 | I75: Ativo
A76: MIX TUDO COMERCIO DE ALIMENTOS E SERVICOS | B76: 26.249.561/0004-65 | C76: ES | D76: Larissa Padilha | E76: 16/09/2025 | F76: 1206.12 | G76: 21 | H76: 166 | I76: Ativo
A77: NATURVIDA | B77: 09.185.428/0004-73 | C77: RS | D77: Manu Ditzel | E77: 16/09/2025 | F77: 1310.86 | G77: 21 | H77: 45 | I77: Ativo
A78: NATURVIDA | B78: 09.185.428/0001-20 | C78: RS | D78: Manu Ditzel | E78: 16/09/2025 | F78: 908.9 | G78: 21 | H78: 45 | I78: Ativo
A79: NATURVIDA MERCADO SAUDAVEL LTDA | B79: 09.185.428/0003-92 | C79: RS | D79: Manu Ditzel | E79: 16/09/2025 | F79: 2887.26 | G79: 21 | H79: 45 | I79: Ativo
A80: NATUREZA EM KILO | B80: 00.211.115/0002-06 | C80: PR | D80: Manu Ditzel | E80: 16/09/2025 | F80: 731.55 | G80: 21 | H80: 19 | I80: Ativo
A81: FRANQUIA FITLAND BLUMENAU SALTO WEISSBACH | B81: 55.483.453/0001-08 | C81: SC | D81: Central - Daiane | E81: 15/09/2025 | F81: 2126.48 | G81: 22 | H81: 96 | I81: Ativo
A82: CASAL MONSTRO SUPLEMENTOS | B82: 29.301.639/0001-99 | C82: RJ | D82: Central - Daiane | E82: 15/09/2025 | F82: 655.21 | G82: 22 | I82: Ativo
A83: MINHA QUITANDINHA | B83: 57.609.477/0001-96 | C83: RS | D83: Manu Ditzel | E83: 15/09/2025 | F83: 773.69 | G83: 22 | I83: Ativo
A84: PRODUTOS DA TERRA | B84: 13.975.801/0001-14 | C84: RS | D84: Central - Daiane | E84: 12/09/2025 | F84: 961.38 | G84: 25 | I84: Ativo
A85: KLOSTERMANN NUTRICAO | B85: 58.072.623/0001-50 | C85: SC | D85: Central - Daiane | E85: 12/09/2025 | F85: 2748.6 | G85: 25 | H85: 42.3333 | I85: Ativo
A86: EVOLUCAO FIT NUTRICAO | B86: 62.555.863/0001-82 | C86: PR | D86: Central - Daiane | E86: 12/09/2025 | F86: 1025.66 | G86: 25 | I86: Ativo
A87: RADISSON HOTEL CURITIBA | B87: 03.554.611/0003-31 | C87: PR | D87: Manu Ditzel | E87: 11/09/2025 | F87: 1106.63 | G87: 26 | H87: 42.5 | I87: Ativo
A88: MERCADO FERREIRA | B88: 14.419.497/0001-91 | C88: SC | D88: Manu Ditzel | E88: 11/09/2025 | F88: 1267.11 | G88: 26 | H88: 35.5 | I88: Ativo
A89: GRANUM CAFE | B89: 18.010.232/0001-96 | C89: SP | D89: Manu Ditzel | E89: 11/09/2025 | F89: 1134 | G89: 26 | I89: Ativo
A90: SUPERMERCADOS OSANA | B90: 06.982.791/0006-93 | C90: RS | D90: Manu Ditzel | E90: 11/09/2025 | F90: 5187.15 | G90: 26 | I90: Ativo
A91: MERCADINHO PAULISTA I I | B91: 34.404.590/0003-00 | C91: BA | D91: Manu Ditzel | E91: 11/09/2025 | F91: 3343 | G91: 26 | I91: Ativo
A92: MERCADINHO PAULISTA I | B92: 34.404.590/0001-30 | C92: BA | D92: Manu Ditzel | E92: 11/09/2025 | F92: 3863.5 | G92: 26 | I92: Ativo
A93: ALICE NO PAIS DOS GRAOS COMERCIO DE ALIMENTOS | B93: 41.626.544/0001-40 | C93: RS | D93: Larissa Padilha | E93: 10/09/2025 | F93: 2088.7 | G93: 27 | H93: 17.5 | I93: Ativo
A94: NATURALIS PRODUTOS NATURAIS | B94: 31.545.180/0001-10 | C94: SC | D94: Manu Ditzel | E94: 10/09/2025 | F94: 1188.55 | G94: 27 | H94: 46 | I94: Ativo
A95: UNIAO SUL BRASILEIRA DA IGREJA ADVENTISTA DO SETIMO DIA | B95: 79.080.602/0001-56 | C95: PR | D95: Manu Ditzel | E95: 10/09/2025 | F95: 691.39 | G95: 27 | H95: 117 | I95: Ativo
A96: BUFFET PARTHENON | B96: 01.005.782/0001-14 | C96: MG | D96: Manu Ditzel | E96: 09/09/2025 | F96: 16230.4 | G96: 28 | I96: Ativo
A97: INTENSE CACAU | B97: 12.886.112/0001-70 | C97: PR | D97: Manu Ditzel | E97: 05/09/2025 | F97: 795.71 | G97: 32 | H97: 134 | I97: Ativo
A98: SOLAR PORTO DE GALINHAS | B98: 08.895.369/0001-11 | C98: PE | D98: Manu Ditzel | E98: 05/09/2025 | F98: 5970 | G98: 32 | H98: 33.5 | I98: Ativo
A99: ITALO ZILMER BEDERODE LTDA | B99: 53.754.257/0001-03 | C99: RS | D99: Manu Ditzel | E99: 05/09/2025 | F99: 1560.86 | G99: 32 | I99: Ativo
A100: A CEREALISSIMA | B100: 15.265.760/0001-06 | C100: GO | D100: Manu Ditzel | E100: 04/09/2025 | F100: 5983.46 | G100: 33 | H100: 20 | I100: Ativo
...

Sheet Base Mercos
C2: Nome fantasia | D2: CNPJ/CPF | E2: Estado | F2: Vendedor do último pedido | G2: Data do último pedido | H2: Valor do último pedido | I2: Dias sem comprar | J2: Ciclo médio de compra | K2: Situação | L2: Coluna1 | M2: status | N2: ULTIMO CONTATO | O2: RESULTADO ATUAL | P2: AÇÃO | Q2: Coluna12 | R2: FOLLOW UP
C3: NATUREZA EM KILO | D3: 00.211.115/0002-06 | E3: PR | F3: Manu Ditzel | G3: 16/09/2025 | H3: 731.55 | I3: 21 | J3: 19 | K3: ATIVO | M3: =IF(OR(J3<=0,J3=""),"","Recompra") -> Recompra | N3: =IFERROR(IF(Tabela1[[#This Row],[Nome fantasia]]="","",_xlfn.XLOOKUP($C3,Log!D:D,Log!B:B,,,-1)),"") -> 46006 | O3: =IFERROR(_xlfn.XLOOKUP($C3,Log!D:D,Log!W:W,,,-1),"") -> EM ATENDIMENTO | P3: =IFERROR(_xlfn.XLOOKUP($C3,Log!D:D,Log!Y:Y,,,-1),"") -> FORÇANDO RECOMPRA | R3: =IFERROR(IF(Tabela1[[#This Row],[Nome fantasia]]="","",_xlfn.XLOOKUP($C3,Log!D:D,Log!X:X,,,-1)),"") -> 46008
C4: EMPORIO GOURMET | D4: * | E4: SC | F4: Manu Ditzel | G4: * | H4: * | I4: * | J4: * | K4: LEAD | M4: =IF(OR(J4<=0,J4=""),"","Recompra") -> Recompra | N4: =IFERROR(IF(Tabela1[[#This Row],[Nome fantasia]]="","",_xlfn.XLOOKUP($C4,Log!D:D,Log!B:B,,,-1)),"") -> 45922 | O4: =IFERROR(_xlfn.XLOOKUP($C4,Log!D:D,Log!W:W,,,-1),"") -> EM ATENDIMENTO | P4: =IFERROR(_xlfn.XLOOKUP($C4,Log!D:D,Log!Y:Y,,,-1),"") -> LIGOU PARA INFORMAÇÔES | R4: =IFERROR(IF(Tabela1[[#This Row],[Nome fantasia]]="","",_xlfn.XLOOKUP($C4,Log!D:D,Log!X:X,,,-1)),"") -> 0
C5: NATHALIA DE JESUS SILVA COSTA LTDA | D5: 59.244.884/0001-72 | E5: SP | F5: Manu Ditzel | G5: 27/08/2025 | H5: 650.3 | I5: 41 | J5: 0 | K5: ATIVO | M5: =IF(OR(J5<=0,J5=""),"","Recompra") | N5: =IFERROR(IF(Tabela1[[#This Row],[Nome fantasia]]="","",_xlfn.XLOOKUP($C5,Log!D:D,Log!B:B,,,-1)),"") -> 45896 | O5: =IFERROR(_xlfn.XLOOKUP($C5,Log!D:D,Log!W:W,,,-1),"") -> EM ATENDIMENTO | P5: =IFERROR(_xlfn.XLOOKUP($C5,Log!D:D,Log!Y:Y,,,-1),"") -> LIGAÇÃO | R5: =IFERROR(IF(Tabela1[[#This Row],[Nome fantasia]]="","",_xlfn.XLOOKUP($C5,Log!D:D,Log!X:X,,,-1)),"") -> 45894
C6: ERICA BALDIN | D6: * | E6: PR | F6: Manu Ditzel | G6: * | H6: * | I6: * | J6: * | K6: LEAD | M6: =IF(OR(J6<=0,J6=""),"","Recompra") -> Recompra | N6: =IFERROR(IF(Tabela1[[#This Row],[Nome fantasia]]="","",_xlfn.XLOOKUP($C6,Log!D:D,Log!B:B,,,-1)),"") -> 45915 | O6: =IFERROR(_xlfn.XLOOKUP($C6,Log!D:D,Log!W:W,,,-1),"") -> ORÇAMENTO | P6: =IFERROR(_xlfn.XLOOKUP($C6,Log!D:D,Log!Y:Y,,,-1),"") -> LICITAÇÃO | R6: =IFERROR(IF(Tabela1[[#This Row],[Nome fantasia]]="","",_xlfn.XLOOKUP($C6,Log!D:D,Log!X:X,,,-1)),"") -> 45916
C7: F & G VITALIDADE NATURAL | D7: 58.319.253/0001-02 | F7: Manu Ditzel | G7: * | H7: * | I7: * | J7: * | K7: LEAD | M7: =IF(OR(J7<=0,J7=""),"","Recompra") -> Recompra | N7: =IFERROR(IF(Tabela1[[#This Row],[Nome fantasia]]="","",_xlfn.XLOOKUP($C7,Log!D:D,Log!B:B,,,-1)),"") -> 45915 | O7: =IFERROR(_xlfn.XLOOKUP($C7,Log!D:D,Log!W:W,,,-1),"") -> ORÇAMENTO | P7: =IFERROR(_xlfn.XLOOKUP($C7,Log!D:D,Log!Y:Y,,,-1),"") -> E-COMMERCE EM ANDAMENTO | R7: =IFERROR(IF(Tabela1[[#This Row],[Nome fantasia]]="","",_xlfn.XLOOKUP($C7,Log!D:D,Log!X:X,,,-1)),"") -> 45916
C8: EMBALEME | D8: 00.458.459/0001-33 | E8: SP | F8: Manu Ditzel | G8: * | H8: * | I8: * | J8: * | K8: LEAD | M8: =IF(OR(J8<=0,J8=""),"","Recompra") -> Recompra | N8: =IFERROR(IF(Tabela1[[#This Row],[Nome fantasia]]="","",_xlfn.XLOOKUP($C8,Log!D:D,Log!B:B,,,-1)),"") -> 45915 | O8: =IFERROR(_xlfn.XLOOKUP($C8,Log!D:D,Log!W:W,,,-1),"") -> EM ATENDIMENTO | P8: =IFERROR(_xlfn.XLOOKUP($C8,Log!D:D,Log!Y:Y,,,-1),"") -> VARIOS ORÇAMENTOS | R8: =IFERROR(IF(Tabela1[[#This Row],[Nome fantasia]]="","",_xlfn.XLOOKUP($C8,Log!D:D,Log!X:X,,,-1)),"") -> 45917
C9: EMBALEME | D9: 00.458.459/0001-33 | E9: SP | F9: Manu Ditzel | G9: * | H9: * | I9: * | J9: * | K9: LEAD | M9: =IF(OR(J9<=0,J9=""),"","Recompra") -> Recompra | N9: =IFERROR(IF(Tabela1[[#This Row],[Nome fantasia]]="","",_xlfn.XLOOKUP($C9,Log!D:D,Log!B:B,,,-1)),"") -> 45915 | O9: =IFERROR(_xlfn.XLOOKUP($C9,Log!D:D,Log!W:W,,,-1),"") -> EM ATENDIMENTO | P9: =IFERROR(_xlfn.XLOOKUP($C9,Log!D:D,Log!Y:Y,,,-1),"") -> VARIOS ORÇAMENTOS | R9: =IFERROR(IF(Tabela1[[#This Row],[Nome fantasia]]="","",_xlfn.XLOOKUP($C9,Log!D:D,Log!X:X,,,-1)),"") -> 45917
C10: CEREALISSIMA MGV | D10: 28.825.262/0001-04 | E10: GO | F10: Helder Brunkow | G10: 17/09/2025 | H10: 1442.87 | I10: 20 | J10: 40 | K10: ATIVO | M10: =IF(OR(J10<=0,J10=""),"","Recompra") -> Recompra | N10: =IFERROR(IF(Tabela1[[#This Row],[Nome fantasia]]="","",_xlfn.XLOOKUP($C10,Log!D:D,Log!B:B,,,-1)),"") -> 45877 | O10: =IFERROR(_xlfn.XLOOKUP($C10,Log!D:D,Log!W:W,,,-1),"") -> VENDA | P10: =IFERROR(_xlfn.XLOOKUP($C10,Log!D:D,Log!Y:Y,,,-1),"") -> RECOMPRA | R10: =IFERROR(IF(Tabela1[[#This Row],[Nome fantasia]]="","",_xlfn.XLOOKUP($C10,Log!D:D,Log!X:X,,,-1)),"") -> 45940
C11: ASSOCIACAO DE PAIS E AMIGOS DOS EXCEPCIONAIS DE S PAULO | D11: 60.502.242/0001-05 | E11: SP | F11: Helder Brunkow | G11: 08/08/2025 | H11: 2040.89 | I11: 60 | J11: 91 | K11: ATIVO | M11: =IF(OR(J11<=0,J11=""),"","Recompra") -> Recompra | N11: =IFERROR(IF(Tabela1[[#This Row],[Nome fantasia]]="","",_xlfn.XLOOKUP($C11,Log!D:D,Log!B:B,,,-1)),"") -> 45877 | O11: =IFERROR(_xlfn.XLOOKUP($C11,Log!D:D,Log!W:W,,,-1),"") -> VENDA | P11: =IFERROR(_xlfn.XLOOKUP($C11,Log!D:D,Log!Y:Y,,,-1),"") -> RECOMPRA | R11: =IFERROR(IF(Tabela1[[#This Row],[Nome fantasia]]="","",_xlfn.XLOOKUP($C11,Log!D:D,Log!X:X,,,-1)),"") -> 45940
C12: NOSSO GREEN MARKET | D12: 52.916.686/0001-69 | E12: PE | F12: Helder Brunkow | G12: 08/08/2025 | H12: 1009.9 | I12: 60 | J12: 59 | K12: ATIVO | M12: =IF(OR(J12<=0,J12=""),"","Recompra") -> Recompra | N12: =IFERROR(IF(Tabela1[[#This Row],[Nome fantasia]]="","",_xlfn.XLOOKUP($C12,Log!D:D,Log!B:B,,,-1)),"") -> 45877 | O12: =IFERROR(_xlfn.XLOOKUP($C12,Log!D:D,Log!W:W,,,-1),"") -> VENDA | P12: =IFERROR(_xlfn.XLOOKUP($C12,Log!D:D,Log!Y:Y,,,-1),"") -> RECOMPRA | R12: =IFERROR(IF(Tabela1[[#This Row],[Nome fantasia]]="","",_xlfn.XLOOKUP($C12,Log!D:D,Log!X:X,,,-1)),"") -> 45940
C13: PORTONUTRY ALIMENTACAO SAUDAVEL | D13: 61.668.179/0001-44 | E13: BA | F13: Larissa Padilha | G13: 07/08/2025 | H13: 1021.87 | I13: 61 | J13: 0 | K13: ATIVO | M13: =IF(OR(J13<=0,J13=""),"","Recompra") | N13: =IFERROR(IF(Tabela1[[#This Row],[Nome fantasia]]="","",_xlfn.XLOOKUP($C13,Log!D:D,Log!B:B,,,-1)),"") -> 45876 | O13: =IFERROR(_xlfn.XLOOKUP($C13,Log!D:D,Log!W:W,,,-1),"") -> VENDA | P13: =IFERROR(_xlfn.XLOOKUP($C13,Log!D:D,Log!Y:Y,,,-1),"") -> RECOMPRA | R13: =IFERROR(IF(Tabela1[[#This Row],[Nome fantasia]]="","",_xlfn.XLOOKUP($C13,Log!D:D,Log!X:X,,,-1)),"") -> 45939
C14: EMPORIO MULTI ARMAZEM | D14: 59.182.148/0001-37 | E14: DF | F14: Larissa Padilha | G14: 07/08/2025 | H14: 1215.54 | I14: 61 | J14: 0 | K14: ATIVO | M14: =IF(OR(J14<=0,J14=""),"","Recompra") | N14: =IFERROR(IF(Tabela1[[#This Row],[Nome fantasia]]="","",_xlfn.XLOOKUP($C14,Log!D:D,Log!B:B,,,-1)),"") -> 45876 | O14: =IFERROR(_xlfn.XLOOKUP($C14,Log!D:D,Log!W:W,,,-1),"") -> VENDA | P14: =IFERROR(_xlfn.XLOOKUP($C14,Log!D:D,Log!Y:Y,,,-1),"") -> RECOMPRA | R14: =IFERROR(IF(Tabela1[[#This Row],[Nome fantasia]]="","",_xlfn.XLOOKUP($C14,Log!D:D,Log!X:X,,,-1)),"") -> 45939
C15: DIVINA TERRA | D15: 42.415.997/0001-90 | E15: PR | F15: Central - Daiane | G15: 06/08/2025 | H15: 1036.87 | I15: 62 | J15: 0 | K15: ATIVO | M15: =IF(OR(J15<=0,J15=""),"","Recompra") | N15: =IFERROR(IF(Tabela1[[#This Row],[Nome fantasia]]="","",_xlfn.XLOOKUP($C15,Log!D:D,Log!B:B,,,-1)),"") -> 45875 | O15: =IFERROR(_xlfn.XLOOKUP($C15,Log!D:D,Log!W:W,,,-1),"") -> VENDA | P15: =IFERROR(_xlfn.XLOOKUP($C15,Log!D:D,Log!Y:Y,,,-1),"") -> RECOMPRA | R15: =IFERROR(IF(Tabela1[[#This Row],[Nome fantasia]]="","",_xlfn.XLOOKUP($C15,Log!D:D,Log!X:X,,,-1)),"") -> 45938
C16: MUNDO FIT | D16: 29.402.498/0001-09 | E16: MG | F16: Helder Brunkow | G16: 06/08/2025 | H16: 1745.52 | I16: 62 | J16: 0 | K16: ATIVO | M16: =IF(OR(J16<=0,J16=""),"","Recompra") | N16: =IFERROR(IF(Tabela1[[#This Row],[Nome fantasia]]="","",_xlfn.XLOOKUP($C16,Log!D:D,Log!B:B,,,-1)),"") -> 45875 | O16: =IFERROR(_xlfn.XLOOKUP($C16,Log!D:D,Log!W:W,,,-1),"") -> VENDA | P16: =IFERROR(_xlfn.XLOOKUP($C16,Log!D:D,Log!Y:Y,,,-1),"") -> RECOMPRA | R16: =IFERROR(IF(Tabela1[[#This Row],[Nome fantasia]]="","",_xlfn.XLOOKUP($C16,Log!D:D,Log!X:X,,,-1)),"") -> 45938
C17: SUPERMERCADO PEDROSA | D17: 11.322.507/0001-88 | E17: PE | F17: Helder Brunkow | G17: 06/08/2025 | H17: 4108.73 | I17: 62 | J17: 0 | K17: ATIVO | M17: =IF(OR(J17<=0,J17=""),"","Recompra") | N17: =IFERROR(IF(Tabela1[[#This Row],[Nome fantasia]]="","",_xlfn.XLOOKUP($C17,Log!D:D,Log!B:B,,,-1)),"") -> 45875 | O17: =IFERROR(_xlfn.XLOOKUP($C17,Log!D:D,Log!W:W,,,-1),"") -> VENDA | P17: =IFERROR(_xlfn.XLOOKUP($C17,Log!D:D,Log!Y:Y,,,-1),"") -> RECOMPRA | R17: =IFERROR(IF(Tabela1[[#This Row],[Nome fantasia]]="","",_xlfn.XLOOKUP($C17,Log!D:D,Log!X:X,,,-1)),"") -> 45938
C18: CARIMBO ACAI E BEBIDAS DO NORTE | D18: 26.176.117/0001-14 | E18: MG | F18: Helder Brunkow | G18: 06/08/2025 | H18: 658.55 | I18: 62 | J18: 0 | K18: ATIVO | M18: =IF(OR(J18<=0,J18=""),"","Recompra") | N18: =IFERROR(IF(Tabela1[[#This Row],[Nome fantasia]]="","",_xlfn.XLOOKUP($C18,Log!D:D,Log!B:B,,,-1)),"") -> 45875 | O18: =IFERROR(_xlfn.XLOOKUP($C18,Log!D:D,Log!W:W,,,-1),"") -> SUPORTE | P18: =IFERROR(_xlfn.XLOOKUP($C18,Log!D:D,Log!Y:Y,,,-1),"") -> ENTREGA | R18: =IFERROR(IF(Tabela1[[#This Row],[Nome fantasia]]="","",_xlfn.XLOOKUP($C18,Log!D:D,Log!X:X,,,-1)),"") -> 0
C19: SWEET AND FIT ATELIER | D19: 37.370.567/0001-60 | E19: SP | F19: Manu Ditzel | G19: 17/09/2025 | H19: 3231.74 | I19: 20 | J19: 32 | K19: ATIVO | M19: =IF(OR(J19<=0,J19=""),"","Recompra") -> Recompra | N19: =IFERROR(IF(Tabela1[[#This Row],[Nome fantasia]]="","",_xlfn.XLOOKUP($C19,Log!D:D,Log!B:B,,,-1)),"") -> 45917 | O19: =IFERROR(_xlfn.XLOOKUP($C19,Log!D:D,Log!W:W,,,-1),"") -> ORÇAMENTO | P19: =IFERROR(_xlfn.XLOOKUP($C19,Log!D:D,Log!Y:Y,,,-1),"") -> ORÇAMENTO | R19: =IFERROR(IF(Tabela1[[#This Row],[Nome fantasia]]="","",_xlfn.XLOOKUP($C19,Log!D:D,Log!X:X,,,-1)),"") -> 45918
C20: SHOPPING NATURAL | D20: 15.428.647/0001-96 | E20: MT | F20: Manu Ditzel | G20: 28/08/2025 | H20: 998.4 | I20: 40 | J20: 60.5 | K20: ATIVO | M20: =IF(OR(J20<=0,J20=""),"","Recompra") -> Recompra | N20: =IFERROR(IF(Tabela1[[#This Row],[Nome fantasia]]="","",_xlfn.XLOOKUP($C20,Log!D:D,Log!B:B,,,-1)),"") -> 45897 | O20: =IFERROR(_xlfn.XLOOKUP($C20,Log!D:D,Log!W:W,,,-1),"") -> FOLLOW UP | P20: =IFERROR(_xlfn.XLOOKUP($C20,Log!D:D,Log!Y:Y,,,-1),"") -> ENTREGA | R20: =IFERROR(IF(Tabela1[[#This Row],[Nome fantasia]]="","",_xlfn.XLOOKUP($C20,Log!D:D,Log!X:X,,,-1)),"") -> 45919
C21: RAIZES E SABORES | D21: 35.031.254/0001-51 | E21: SP | F21: Manu Ditzel | G21: 26/08/2025 | H21: 936.23 | I21: 42 | J21: 21 | K21: ATIVO | M21: =IF(OR(J21<=0,J21=""),"","Recompra") -> Recompra | N21: =IFERROR(IF(Tabela1[[#This Row],[Nome fantasia]]="","",_xlfn.XLOOKUP($C21,Log!D:D,Log!B:B,,,-1)),"") -> 45895 | O21: =IFERROR(_xlfn.XLOOKUP($C21,Log!D:D,Log!W:W,,,-1),"") -> FOLLOW UP | P21: =IFERROR(_xlfn.XLOOKUP($C21,Log!D:D,Log!Y:Y,,,-1),"") -> ENTREGA | R21: =IFERROR(IF(Tabela1[[#This Row],[Nome fantasia]]="","",_xlfn.XLOOKUP($C21,Log!D:D,Log!X:X,,,-1)),"") -> 45919
C22: 49.844.222 LUIS CARLOS VIEIRA | D22: 49.844.222/0001-80 | E22: SP | F22: Helder Brunkow | G22: 01/10/2025 | H22: 659.66 | I22: 6 | J22: 62.5 | K22: ATIVO | M22: =IF(OR(J22<=0,J22=""),"","Recompra") -> Recompra | N22: =IFERROR(IF(Tabela1[[#This Row],[Nome fantasia]]="","",_xlfn.XLOOKUP($C22,Log!D:D,Log!B:B,,,-1)),"") -> 45873 | O22: =IFERROR(_xlfn.XLOOKUP($C22,Log!D:D,Log!W:W,,,-1),"") -> VENDA | P22: =IFERROR(_xlfn.XLOOKUP($C22,Log!D:D,Log!Y:Y,,,-1),"") -> RECOMPRA | R22: =IFERROR(IF(Tabela1[[#This Row],[Nome fantasia]]="","",_xlfn.XLOOKUP($C22,Log!D:D,Log!X:X,,,-1)),"") -> 45936
C23: CB CURITIBA COMERCIO DE ALIMENTOS | D23: 23.502.037/0001-13 | E23: PR | F23: Manu Ditzel | G23: * | H23: * | I23: * | J23: * | K23: LEAD | M23: =IF(OR(J23<=0,J23=""),"","Recompra") -> Recompra | N23: =IFERROR(IF(Tabela1[[#This Row],[Nome fantasia]]="","",_xlfn.XLOOKUP($C23,Log!D:D,Log!B:B,,,-1)),"") -> 45917 | O23: =IFERROR(_xlfn.XLOOKUP($C23,Log!D:D,Log!W:W,,,-1),"") -> EM ATENDIMENTO | P23: =IFERROR(_xlfn.XLOOKUP($C23,Log!D:D,Log!Y:Y,,,-1),"") -> TRANFERIDO ATENDIMENTO | R23: =IFERROR(IF(Tabela1[[#This Row],[Nome fantasia]]="","",_xlfn.XLOOKUP($C23,Log!D:D,Log!X:X,,,-1)),"") -> 45919
C24: RAYNARA PAULINA ROCHA FRANCO - JUSTGO | D24: 61.819.408/0001-84 | E24: MG | F24: Helder Brunkow | G24: 31/07/2025 | H24: 747.14 | I24: 68 | J24: 0 | K24: ATIVO | M24: =IF(OR(J24<=0,J24=""),"","Recompra") | N24: =IFERROR(IF(Tabela1[[#This Row],[Nome fantasia]]="","",_xlfn.XLOOKUP($C24,Log!D:D,Log!B:B,,,-1)),"") -> 45869 | O24: =IFERROR(_xlfn.XLOOKUP($C24,Log!D:D,Log!W:W,,,-1),"") -> SUPORTE | P24: =IFERROR(_xlfn.XLOOKUP($C24,Log!D:D,Log!Y:Y,,,-1),"") -> RASTREIO | R24: =IFERROR(IF(Tabela1[[#This Row],[Nome fantasia]]="","",_xlfn.XLOOKUP($C24,Log!D:D,Log!X:X,,,-1)),"") -> 0
C25: VIDA LEVE BARIGUI | D25: 54.423.411/0001-19 | E25: PR | F25: Manu Ditzel | G25: 01/10/2025 | H25: 603 | I25: 6 | J25: 64 | K25: ATIVO | M25: =IF(OR(J25<=0,J25=""),"","Recompra") -> Recompra | N25: =IFERROR(IF(Tabela1[[#This Row],[Nome fantasia]]="","",_xlfn.XLOOKUP($C25,Log!D:D,Log!B:B,,,-1)),"") -> 45918 | O25: =IFERROR(_xlfn.XLOOKUP($C25,Log!D:D,Log!W:W,,,-1),"") -> EM ATENDIMENTO | P25: =IFERROR(_xlfn.XLOOKUP($C25,Log!D:D,Log!Y:Y,,,-1),"") -> MENSAGEM | R25: =IFERROR(IF(Tabela1[[#This Row],[Nome fantasia]]="","",_xlfn.XLOOKUP($C25,Log!D:D,Log!X:X,,,-1)),"") -> 45922
C26: VIPI SUPERMERCADOS E BONNO ATACADO E VAREJO | D26: 78.516.440/0006-06 | E26: PR | F26: Manu Ditzel | G26: 07/08/2025 | H26: 1033.22 | I26: 61 | J26: 59 | K26: ATIVO | M26: =IF(OR(J26<=0,J26=""),"","Recompra") -> Recompra | N26: =IFERROR(IF(Tabela1[[#This Row],[Nome fantasia]]="","",_xlfn.XLOOKUP($C26,Log!D:D,Log!B:B,,,-1)),"") -> 45918 | O26: =IFERROR(_xlfn.XLOOKUP($C26,Log!D:D,Log!W:W,,,-1),"") -> EM ATENDIMENTO | P26: =IFERROR(_xlfn.XLOOKUP($C26,Log!D:D,Log!Y:Y,,,-1),"") -> AGUARDANDO CLIENTE | R26: =IFERROR(IF(Tabela1[[#This Row],[Nome fantasia]]="","",_xlfn.XLOOKUP($C26,Log!D:D,Log!X:X,,,-1)),"") -> 45922
C27: MAIS NATURAL COMERCIO DE PRODUTOS NATURAIS | D27: 17.880.439/0002-30 | E27: RS | F27: Manu Ditzel | G27: 05/08/2025 | H27: 1547.8 | I27: 63 | J27: 65.5 | K27: ATIVO | M27: =IF(OR(J27<=0,J27=""),"","Recompra") -> Recompra | N27: =IFERROR(IF(Tabela1[[#This Row],[Nome fantasia]]="","",_xlfn.XLOOKUP($C27,Log!D:D,Log!B:B,,,-1)),"") -> 45918 | O27: =IFERROR(_xlfn.XLOOKUP($C27,Log!D:D,Log!W:W,,,-1),"") -> EM ATENDIMENTO | P27: =IFERROR(_xlfn.XLOOKUP($C27,Log!D:D,Log!Y:Y,,,-1),"") -> MENSAGEM | R27: =IFERROR(IF(Tabela1[[#This Row],[Nome fantasia]]="","",_xlfn.XLOOKUP($C27,Log!D:D,Log!X:X,,,-1)),"") -> 45922
C28: NICE STORE PRESENTES | D28: 32.940.804/0001-67 | E28: SC | F28: Manu Ditzel | G28: 05/08/2025 | H28: 667.16 | I28: 63 | J28: 18 | K28: ATIVO | M28: =IF(OR(J28<=0,J28=""),"","Recompra") -> Recompra | N28: =IFERROR(IF(Tabela1[[#This Row],[Nome fantasia]]="","",_xlfn.XLOOKUP($C28,Log!D:D,Log!B:B,,,-1)),"") -> 45994 | O28: =IFERROR(_xlfn.XLOOKUP($C28,Log!D:D,Log!W:W,,,-1),"") -> VENDA | P28: =IFERROR(_xlfn.XLOOKUP($C28,Log!D:D,Log!Y:Y,,,-1),"") -> VENDA FINALIZADA | R28: =IFERROR(IF(Tabela1[[#This Row],[Nome fantasia]]="","",_xlfn.XLOOKUP($C28,Log!D:D,Log!X:X,,,-1)),"") -> 46057
C29: BATEL GOURMET HORTIFRUTI E EMPORIO | D29: 30.289.781/0001-47 | E29: PR | F29: Manu Ditzel | G29: 31/07/2025 | H29: 944.22 | I29: 68 | J29: 35.3333 | K29: ATIVO | M29: =IF(OR(J29<=0,J29=""),"","Recompra") -> Recompra | N29: =IFERROR(IF(Tabela1[[#This Row],[Nome fantasia]]="","",_xlfn.XLOOKUP($C29,Log!D:D,Log!B:B,,,-1)),"") -> 46001 | O29: =IFERROR(_xlfn.XLOOKUP($C29,Log!D:D,Log!W:W,,,-1),"") -> EM ATENDIMENTO | P29: =IFERROR(_xlfn.XLOOKUP($C29,Log!D:D,Log!Y:Y,,,-1),"") -> NÃO ATENDEU, MANDEI MENSAGEM | R29: =IFERROR(IF(Tabela1[[#This Row],[Nome fantasia]]="","",_xlfn.XLOOKUP($C29,Log!D:D,Log!X:X,,,-1)),"") -> 46003
C30: MAGOGA HORTIFRUTI LTDA | D30: 54.211.982/0001-90 | E30: SP | F30: Helder Brunkow | G30: 22/09/2025 | H30: 1879.39 | I30: 15 | J30: 34.2 | K30: ATIVO | M30: =IF(OR(J30<=0,J30=""),"","Recompra") -> Recompra | N30: =IFERROR(IF(Tabela1[[#This Row],[Nome fantasia]]="","",_xlfn.XLOOKUP($C30,Log!D:D,Log!B:B,,,-1)),"") -> 45863 | O30: =IFERROR(_xlfn.XLOOKUP($C30,Log!D:D,Log!W:W,,,-1),"") -> FOLLOW UP | P30: =IFERROR(_xlfn.XLOOKUP($C30,Log!D:D,Log!Y:Y,,,-1),"") -> MENSAGEM | R30: =IFERROR(IF(Tabela1[[#This Row],[Nome fantasia]]="","",_xlfn.XLOOKUP($C30,Log!D:D,Log!X:X,,,-1)),"") -> 45916
C31: FAZENDINHA SALU.D LTDA | D31: 45.100.604/0001-48 | E31: SC | F31: Manu Ditzel | G31: 30/07/2025 | H31: 671.86 | I31: 69 | J31: 0 | K31: ATIVO | M31: =IF(OR(J31<=0,J31=""),"","Recompra") | N31: =IFERROR(IF(Tabela1[[#This Row],[Nome fantasia]]="","",_xlfn.XLOOKUP($C31,Log!D:D,Log!B:B,,,-1)),"") -> 45918 | O31: =IFERROR(_xlfn.XLOOKUP($C31,Log!D:D,Log!W:W,,,-1),"") -> EM ATENDIMENTO | P31: =IFERROR(_xlfn.XLOOKUP($C31,Log!D:D,Log!Y:Y,,,-1),"") -> AINDA TEM ESTOQUE | R31: =IFERROR(IF(Tabela1[[#This Row],[Nome fantasia]]="","",_xlfn.XLOOKUP($C31,Log!D:D,Log!X:X,,,-1)),"") -> 45922
C32: RIKATI PRODUTOS NATURAIS | D32: 59.876.252/0001-21 | E32: SC | F32: Manu Ditzel | G32: 25/07/2025 | H32: 1253.13 | I32: 74 | J32: 0 | K32: ATIVO | M32: =IF(OR(J32<=0,J32=""),"","Recompra") | N32: =IFERROR(IF(Tabela1[[#This Row],[Nome fantasia]]="","",_xlfn.XLOOKUP($C32,Log!D:D,Log!B:B,,,-1)),"") -> 45994 | O32: =IFERROR(_xlfn.XLOOKUP($C32,Log!D:D,Log!W:W,,,-1),"") -> EM ATENDIMENTO | P32: =IFERROR(_xlfn.XLOOKUP($C32,Log!D:D,Log!Y:Y,,,-1),"") -> MENSAGEM PARA NOVO RELACIOMENTO | R32: =IFERROR(IF(Tabela1[[#This Row],[Nome fantasia]]="","",_xlfn.XLOOKUP($C32,Log!D:D,Log!X:X,,,-1)),"") -> 45996
C33: KF - COMPRAS ANDRE | D33: * | E33: PR | F33: Manu Ditzel | G33: * | H33: * | I33: * | J33: * | K33: LEAD | M33: =IF(OR(J33<=0,J33=""),"","Recompra") -> Recompra | N33: =IFERROR(IF(Tabela1[[#This Row],[Nome fantasia]]="","",_xlfn.XLOOKUP($C33,Log!D:D,Log!B:B,,,-1)),"") -> 45918 | O33: =IFERROR(_xlfn.XLOOKUP($C33,Log!D:D,Log!W:W,,,-1),"") -> FOLLOW UP 7 | P33: =IFERROR(_xlfn.XLOOKUP($C33,Log!D:D,Log!Y:Y,,,-1),"") -> NÃO TIVE MAIS RETORNO | R33: =IFERROR(IF(Tabela1[[#This Row],[Nome fantasia]]="","",_xlfn.XLOOKUP($C33,Log!D:D,Log!X:X,,,-1)),"") -> 45922
C34: MACHADAO ATACADISTA | D34: 03.790.904/0004-07 | E34: MT | F34: Helder Brunkow | G34: 14/07/2025 | H34: 1452.42 | I34: 85 | J34: 53 | K34: ATIVO | M34: =IF(OR(J34<=0,J34=""),"","Recompra") -> Recompra | N34: =IFERROR(IF(Tabela1[[#This Row],[Nome fantasia]]="","",_xlfn.XLOOKUP($C34,Log!D:D,Log!B:B,,,-1)),"") -> 45852 | O34: =IFERROR(_xlfn.XLOOKUP($C34,Log!D:D,Log!W:W,,,-1),"") -> VENDA | P34: =IFERROR(_xlfn.XLOOKUP($C34,Log!D:D,Log!Y:Y,,,-1),"") -> RECOMPRA | R34: =IFERROR(IF(Tabela1[[#This Row],[Nome fantasia]]="","",_xlfn.XLOOKUP($C34,Log!D:D,Log!X:X,,,-1)),"") -> 45923
C35: MACHADAO ATACADISTA | D35: 03.790.904/0005-80 | E35: MT | F35: Helder Brunkow | G35: 14/07/2025 | H35: 4460.93 | I35: 85 | J35: 53 | K35: ATIVO | M35: =IF(OR(J35<=0,J35=""),"","Recompra") -> Recompra | N35: =IFERROR(IF(Tabela1[[#This Row],[Nome fantasia]]="","",_xlfn.XLOOKUP($C35,Log!D:D,Log!B:B,,,-1)),"") -> 45852 | O35: =IFERROR(_xlfn.XLOOKUP($C35,Log!D:D,Log!W:W,,,-1),"") -> VENDA | P35: =IFERROR(_xlfn.XLOOKUP($C35,Log!D:D,Log!Y:Y,,,-1),"") -> RECOMPRA | R35: =IFERROR(IF(Tabela1[[#This Row],[Nome fantasia]]="","",_xlfn.XLOOKUP($C35,Log!D:D,Log!X:X,,,-1)),"") -> 45923
C36: MACHADAO ATACADISTA | D36: 13.338.712/0002-48 | E36: MT | F36: Helder Brunkow | G36: 14/07/2025 | H36: 1453.67 | I36: 85 | J36: 53 | K36: ATIVO | M36: =IF(OR(J36<=0,J36=""),"","Recompra") -> Recompra | N36: =IFERROR(IF(Tabela1[[#This Row],[Nome fantasia]]="","",_xlfn.XLOOKUP($C36,Log!D:D,Log!B:B,,,-1)),"") -> 45852 | O36: =IFERROR(_xlfn.XLOOKUP($C36,Log!D:D,Log!W:W,,,-1),"") -> VENDA | P36: =IFERROR(_xlfn.XLOOKUP($C36,Log!D:D,Log!Y:Y,,,-1),"") -> RECOMPRA | R36: =IFERROR(IF(Tabela1[[#This Row],[Nome fantasia]]="","",_xlfn.XLOOKUP($C36,Log!D:D,Log!X:X,,,-1)),"") -> 45923
C37: MACHADAO ATACADISTA | D37: 13.338.712/0004-00 | E37: MT | F37: Helder Brunkow | G37: 14/07/2025 | H37: 1392.8 | I37: 85 | J37: 53 | K37: ATIVO | M37: =IF(OR(J37<=0,J37=""),"","Recompra") -> Recompra | N37: =IFERROR(IF(Tabela1[[#This Row],[Nome fantasia]]="","",_xlfn.XLOOKUP($C37,Log!D:D,Log!B:B,,,-1)),"") -> 45852 | O37: =IFERROR(_xlfn.XLOOKUP($C37,Log!D:D,Log!W:W,,,-1),"") -> VENDA | P37: =IFERROR(_xlfn.XLOOKUP($C37,Log!D:D,Log!Y:Y,,,-1),"") -> RECOMPRA | R37: =IFERROR(IF(Tabela1[[#This Row],[Nome fantasia]]="","",_xlfn.XLOOKUP($C37,Log!D:D,Log!X:X,,,-1)),"") -> 45923
C38: NATURE PRODUTOS NATURAIS | D38: 46.814.160/0001-75 | E38: PA | F38: Helder Brunkow | G38: 11/07/2025 | H38: 7216.91 | I38: 88 | J38: 102 | K38: INATIVO RECENTE | M38: =IF(OR(J38<=0,J38=""),"","Recompra") -> Recompra | N38: =IFERROR(IF(Tabela1[[#This Row],[Nome fantasia]]="","",_xlfn.XLOOKUP($C38,Log!D:D,Log!B:B,,,-1)),"") -> 45849 | O38: =IFERROR(_xlfn.XLOOKUP($C38,Log!D:D,Log!W:W,,,-1),"") -> EM ATENDIMENTO | P38: =IFERROR(_xlfn.XLOOKUP($C38,Log!D:D,Log!Y:Y,,,-1),"") -> 0 | R38: =IFERROR(IF(Tabela1[[#This Row],[Nome fantasia]]="","",_xlfn.XLOOKUP($C38,Log!D:D,Log!X:X,,,-1)),"") -> 45853
C39: SUPERMERCADO SERVE BEM | D39: 02.672.868/0001-63 | E39: MG | F39: Helder Brunkow | G39: 18/09/2025 | H39: 1542.37 | I39: 19 | J39: 80 | K39: INATIVO RECENTE | M39: =IF(OR(J39<=0,J39=""),"","Recompra") -> Recompra | N39: =IFERROR(IF(Tabela1[[#This Row],[Nome fantasia]]="","",_xlfn.XLOOKUP($C39,Log!D:D,Log!B:B,,,-1)),"") -> 45838 | O39: =IFERROR(_xlfn.XLOOKUP($C39,Log!D:D,Log!W:W,,,-1),"") -> SUPORTE | P39: =IFERROR(_xlfn.XLOOKUP($C39,Log!D:D,Log!Y:Y,,,-1),"") -> ESTOQUE | R39: =IFERROR(IF(Tabela1[[#This Row],[Nome fantasia]]="","",_xlfn.XLOOKUP($C39,Log!D:D,Log!X:X,,,-1)),"") -> 45919
C40: GRANO DI FELICITÁ | D40: 50.853.004/0001-90 | E40: PR | F40: Manu Ditzel | G40: * | H40: * | I40: * | J40: * | K40: LEAD | M40: =IF(OR(J40<=0,J40=""),"","Recompra") -> Recompra | N40: =IFERROR(IF(Tabela1[[#This Row],[Nome fantasia]]="","",_xlfn.XLOOKUP($C40,Log!D:D,Log!B:B,,,-1)),"") -> 45915 | O40: =IFERROR(_xlfn.XLOOKUP($C40,Log!D:D,Log!W:W,,,-1),"") -> FOLLOW UP 7 | P40: =IFERROR(_xlfn.XLOOKUP($C40,Log!D:D,Log!Y:Y,,,-1),"") -> LIGAÇÃO | R40: =IFERROR(IF(Tabela1[[#This Row],[Nome fantasia]]="","",_xlfn.XLOOKUP($C40,Log!D:D,Log!X:X,,,-1)),"") -> 45924
C41: KLOSTERMANN SUPLEMENTOS | D41: 56.157.640/0001-64 | E41: SC | F41: Central - Daiane | G41: 24/06/2025 | H41: 2350.33 | I41: 105 | J41: 0 | K41: INATIVO RECENTE | M41: =IF(OR(J41<=0,J41=""),"","Recompra") | N41: =IFERROR(IF(Tabela1[[#This Row],[Nome fantasia]]="","",_xlfn.XLOOKUP($C41,Log!D:D,Log!B:B,,,-1)),"") -> 45832 | O41: =IFERROR(_xlfn.XLOOKUP($C41,Log!D:D,Log!W:W,,,-1),"") -> VENDA | P41: =IFERROR(_xlfn.XLOOKUP($C41,Log!D:D,Log!Y:Y,,,-1),"") -> Cliente precisa com urgencia do pedido, pois sumiu o pedido dele do sistema | R41: =IFERROR(IF(Tabela1[[#This Row],[Nome fantasia]]="","",_xlfn.XLOOKUP($C41,Log!D:D,Log!X:X,,,-1)),"") -> 0
C42: EQUILLIBRIUN | D42: 12.165.772/0001-62 | E42: RN | F42: Helder Brunkow | G42: 16/06/2025 | H42: 2212.34 | I42: 113 | J42: 48 | K42: INATIVO ANTIGO | M42: =IF(OR(J42<=0,J42=""),"","Recompra") -> Recompra | N42: =IFERROR(IF(Tabela1[[#This Row],[Nome fantasia]]="","",_xlfn.XLOOKUP($C42,Log!D:D,Log!B:B,,,-1)),"") -> 45824 | O42: =IFERROR(_xlfn.XLOOKUP($C42,Log!D:D,Log!W:W,,,-1),"") -> FOLLOW UP | P42: =IFERROR(_xlfn.XLOOKUP($C42,Log!D:D,Log!Y:Y,,,-1),"") -> SAIDA DOS PRODUTOS | R42: =IFERROR(IF(Tabela1[[#This Row],[Nome fantasia]]="","",_xlfn.XLOOKUP($C42,Log!D:D,Log!X:X,,,-1)),"") -> 45919
C43: GRANO DI FELICITÁ | D43: 50.853.004/0001-90 | E43: PR | F43: Manu Ditzel | G43: * | H43: * | I43: * | J43: * | K43: LEAD | M43: =IF(OR(J43<=0,J43=""),"","Recompra") -> Recompra | N43: =IFERROR(IF(Tabela1[[#This Row],[Nome fantasia]]="","",_xlfn.XLOOKUP($C43,Log!D:D,Log!B:B,,,-1)),"") -> 45915 | O43: =IFERROR(_xlfn.XLOOKUP($C43,Log!D:D,Log!W:W,,,-1),"") -> FOLLOW UP 7 | P43: =IFERROR(_xlfn.XLOOKUP($C43,Log!D:D,Log!Y:Y,,,-1),"") -> LIGAÇÃO | R43: =IFERROR(IF(Tabela1[[#This Row],[Nome fantasia]]="","",_xlfn.XLOOKUP($C43,Log!D:D,Log!X:X,,,-1)),"") -> 45924
C44: QUESTAO DE GOSTO | D44: 04.048.449/0001-80 | E44: SC | F44: Manu Ditzel | G44: * | H44: * | I44: * | J44: * | K44: LEAD | M44: =IF(OR(J44<=0,J44=""),"","Recompra") -> Recompra | N44: =IFERROR(IF(Tabela1[[#This Row],[Nome fantasia]]="","",_xlfn.XLOOKUP($C44,Log!D:D,Log!B:B,,,-1)),"") -> 45915 | O44: =IFERROR(_xlfn.XLOOKUP($C44,Log!D:D,Log!W:W,,,-1),"") -> FOLLOW UP 7 | P44: =IFERROR(_xlfn.XLOOKUP($C44,Log!D:D,Log!Y:Y,,,-1),"") -> LIGAÇÃO | R44: =IFERROR(IF(Tabela1[[#This Row],[Nome fantasia]]="","",_xlfn.XLOOKUP($C44,Log!D:D,Log!X:X,,,-1)),"") -> 45924
C45: QUESTAO DE GOSTO | D45: 04.048.449/0001-80 | E45: SC | F45: Manu Ditzel | G45: * | H45: * | I45: * | J45: * | K45: LEAD | M45: =IF(OR(J45<=0,J45=""),"","Recompra") -> Recompra | N45: =IFERROR(IF(Tabela1[[#This Row],[Nome fantasia]]="","",_xlfn.XLOOKUP($C45,Log!D:D,Log!B:B,,,-1)),"") -> 45915 | O45: =IFERROR(_xlfn.XLOOKUP($C45,Log!D:D,Log!W:W,,,-1),"") -> FOLLOW UP 7 | P45: =IFERROR(_xlfn.XLOOKUP($C45,Log!D:D,Log!Y:Y,,,-1),"") -> LIGAÇÃO | R45: =IFERROR(IF(Tabela1[[#This Row],[Nome fantasia]]="","",_xlfn.XLOOKUP($C45,Log!D:D,Log!X:X,,,-1)),"") -> 45924
C46: BIO MUNDO | D46: 33.950.384/0001-62 | E46: PE | F46: Helder Brunkow | G46: 21/05/2025 | H46: 657.21 | I46: 139 | J46: 41 | K46: INATIVO ANTIGO | M46: =IF(OR(J46<=0,J46=""),"","Recompra") -> Recompra | N46: =IFERROR(IF(Tabela1[[#This Row],[Nome fantasia]]="","",_xlfn.XLOOKUP($C46,Log!D:D,Log!B:B,,,-1)),"") -> 45798 | O46: =IFERROR(_xlfn.XLOOKUP($C46,Log!D:D,Log!W:W,,,-1),"") -> FOLLOW UP | P46: =IFERROR(_xlfn.XLOOKUP($C46,Log!D:D,Log!Y:Y,,,-1),"") -> RECOMPRA | R46: =IFERROR(IF(Tabela1[[#This Row],[Nome fantasia]]="","",_xlfn.XLOOKUP($C46,Log!D:D,Log!X:X,,,-1)),"") -> 45919
C47: SUPERMERCADOS OSANA | D47: 06.982.791/0001-89 | E47: RS | F47: Central - Daiane | G47: 12/05/2025 | H47: 1558.74 | I47: 148 | J47: 0 | K47: INATIVO ANTIGO | M47: =IF(OR(J47<=0,J47=""),"","Recompra") | N47: =IFERROR(IF(Tabela1[[#This Row],[Nome fantasia]]="","",_xlfn.XLOOKUP($C47,Log!D:D,Log!B:B,,,-1)),"") -> 45951 | O47: =IFERROR(_xlfn.XLOOKUP($C47,Log!D:D,Log!W:W,,,-1),"") -> EM ATENDIMENTO | P47: =IFERROR(_xlfn.XLOOKUP($C47,Log!D:D,Log!Y:Y,,,-1),"") -> ENTRANDO EM CONTATO NOVAMENTE COM A CLIENTE ! | R47: =IFERROR(IF(Tabela1[[#This Row],[Nome fantasia]]="","",_xlfn.XLOOKUP($C47,Log!D:D,Log!X:X,,,-1)),"") -> 45953
C48: COMPANHIA TERMA DO RIO QUENTE | D48: 01.540.533/0001-29 | E48: GO | F48: Manu Ditzel | G48: * | H48: * | I48: * | J48: * | K48: LEAD | M48: =IF(OR(J48<=0,J48=""),"","Recompra") -> Recompra | N48: =IFERROR(IF(Tabela1[[#This Row],[Nome fantasia]]="","",_xlfn.XLOOKUP($C48,Log!D:D,Log!B:B,,,-1)),"") -> 45915 | O48: =IFERROR(_xlfn.XLOOKUP($C48,Log!D:D,Log!W:W,,,-1),"") -> FOLLOW UP 7 | P48: =IFERROR(_xlfn.XLOOKUP($C48,Log!D:D,Log!Y:Y,,,-1),"") -> AMOSTRAS | R48: =IFERROR(IF(Tabela1[[#This Row],[Nome fantasia]]="","",_xlfn.XLOOKUP($C48,Log!D:D,Log!X:X,,,-1)),"") -> 45924
C49: BIO MUNDO | D49: 33.016.679/0001-66 | E49: GO | F49: Helder Brunkow | G49: 25/04/2025 | H49: 1526 | I49: 165 | J49: 0 | K49: INATIVO ANTIGO | M49: =IF(OR(J49<=0,J49=""),"","Recompra") | N49: =IFERROR(IF(Tabela1[[#This Row],[Nome fantasia]]="","",_xlfn.XLOOKUP($C49,Log!D:D,Log!B:B,,,-1)),"") -> 45798 | O49: =IFERROR(_xlfn.XLOOKUP($C49,Log!D:D,Log!W:W,,,-1),"") -> FOLLOW UP | P49: =IFERROR(_xlfn.XLOOKUP($C49,Log!D:D,Log!Y:Y,,,-1),"") -> RECOMPRA | R49: =IFERROR(IF(Tabela1[[#This Row],[Nome fantasia]]="","",_xlfn.XLOOKUP($C49,Log!D:D,Log!X:X,,,-1)),"") -> 45919
C50: BIO MUNDO | D50: 40.724.765/0001-99 | E50: GO | F50: Helder Brunkow | G50: 17/04/2025 | H50: 1090.05 | I50: 173 | J50: 0 | K50: INATIVO ANTIGO | M50: =IF(OR(J50<=0,J50=""),"","Recompra") | N50: =IFERROR(IF(Tabela1[[#This Row],[Nome fantasia]]="","",_xlfn.XLOOKUP($C50,Log!D:D,Log!B:B,,,-1)),"") -> 45798 | O50: =IFERROR(_xlfn.XLOOKUP($C50,Log!D:D,Log!W:W,,,-1),"") -> FOLLOW UP | P50: =IFERROR(_xlfn.XLOOKUP($C50,Log!D:D,Log!Y:Y,,,-1),"") -> RECOMPRA | R50: =IFERROR(IF(Tabela1[[#This Row],[Nome fantasia]]="","",_xlfn.XLOOKUP($C50,Log!D:D,Log!X:X,,,-1)),"") -> 45919
C51: DIVINA TERRA | D51: 36.030.744/0001-04 | E51: RS | K51: LEAD | M51: =IF(OR(J51<=0,J51=""),"","Recompra") | N51: =IFERROR(IF(Tabela1[[#This Row],[Nome fantasia]]="","",_xlfn.XLOOKUP($C51,Log!D:D,Log!B:B,,,-1)),"") -> 45875 | O51: =IFERROR(_xlfn.XLOOKUP($C51,Log!D:D,Log!W:W,,,-1),"") -> VENDA | P51: =IFERROR(_xlfn.XLOOKUP($C51,Log!D:D,Log!Y:Y,,,-1),"") -> RECOMPRA | R51: =IFERROR(IF(Tabela1[[#This Row],[Nome fantasia]]="","",_xlfn.XLOOKUP($C51,Log!D:D,Log!X:X,,,-1)),"") -> 45938
C52: SABOR NATURAL | D52: 13.152.698/0001-02 | E52: RS | K52: LEAD | M52: =IF(OR(J52<=0,J52=""),"","Recompra") | N52: =IFERROR(IF(Tabela1[[#This Row],[Nome fantasia]]="","",_xlfn.XLOOKUP($C52,Log!D:D,Log!B:B,,,-1)),"") -> 45929 | O52: =IFERROR(_xlfn.XLOOKUP($C52,Log!D:D,Log!W:W,,,-1),"") -> EM ATENDIMENTO | P52: =IFERROR(_xlfn.XLOOKUP($C52,Log!D:D,Log!Y:Y,,,-1),"") -> TENTAR REATIVAR | R52: =IFERROR(IF(Tabela1[[#This Row],[Nome fantasia]]="","",_xlfn.XLOOKUP($C52,Log!D:D,Log!X:X,,,-1)),"") -> 45931
C53: MAIS NATURAL COMERCIO DE PRODUTOS NATURAIS | D53: 17.880.439/0001-59 | E53: RS | K53: LEAD | M53: =IF(OR(J53<=0,J53=""),"","Recompra") | N53: =IFERROR(IF(Tabela1[[#This Row],[Nome fantasia]]="","",_xlfn.XLOOKUP($C53,Log!D:D,Log!B:B,,,-1)),"") -> 45918 | O53: =IFERROR(_xlfn.XLOOKUP($C53,Log!D:D,Log!W:W,,,-1),"") -> EM ATENDIMENTO | P53: =IFERROR(_xlfn.XLOOKUP($C53,Log!D:D,Log!Y:Y,,,-1),"") -> MENSAGEM | R53: =IFERROR(IF(Tabela1[[#This Row],[Nome fantasia]]="","",_xlfn.XLOOKUP($C53,Log!D:D,Log!X:X,,,-1)),"") -> 45922
C54: BELLA VITA | D54: 53.015.172/0001-03 | E54: SC | K54: LEAD | M54: =IF(OR(J54<=0,J54=""),"","Recompra") | N54: =IFERROR(IF(Tabela1[[#This Row],[Nome fantasia]]="","",_xlfn.XLOOKUP($C54,Log!D:D,Log!B:B,,,-1)),"") -> 45923 | O54: =IFERROR(_xlfn.XLOOKUP($C54,Log!D:D,Log!W:W,,,-1),"") -> FOLLOW UP 7 | P54: =IFERROR(_xlfn.XLOOKUP($C54,Log!D:D,Log!Y:Y,,,-1),"") -> CONTATO PARA ENTENDER SAIDA | R54: =IFERROR(IF(Tabela1[[#This Row],[Nome fantasia]]="","",_xlfn.XLOOKUP($C54,Log!D:D,Log!X:X,,,-1)),"") -> 45932
C55: DIVINA TERRA | D55: 29.011.720/0001-34 | E55: RS | K55: LEAD | M55: =IF(OR(J55<=0,J55=""),"","Recompra") | N55: =IFERROR(IF(Tabela1[[#This Row],[Nome fantasia]]="","",_xlfn.XLOOKUP($C55,Log!D:D,Log!B:B,,,-1)),"") -> 45875 | O55: =IFERROR(_xlfn.XLOOKUP($C55,Log!D:D,Log!W:W,,,-1),"") -> VENDA | P55: =IFERROR(_xlfn.XLOOKUP($C55,Log!D:D,Log!Y:Y,,,-1),"") -> RECOMPRA | R55: =IFERROR(IF(Tabela1[[#This Row],[Nome fantasia]]="","",_xlfn.XLOOKUP($C55,Log!D:D,Log!X:X,,,-1)),"") -> 45938
C56: SABOR NATURAL | D56: 30.041.434/0001-09 | E56: SC | K56: LEAD | M56: =IF(OR(J56<=0,J56=""),"","Recompra") | N56: =IFERROR(IF(Tabela1[[#This Row],[Nome fantasia]]="","",_xlfn.XLOOKUP($C56,Log!D:D,Log!B:B,,,-1)),"") -> 45929 | O56: =IFERROR(_xlfn.XLOOKUP($C56,Log!D:D,Log!W:W,,,-1),"") -> EM ATENDIMENTO | P56: =IFERROR(_xlfn.XLOOKUP($C56,Log!D:D,Log!Y:Y,,,-1),"") -> TENTAR REATIVAR | R56: =IFERROR(IF(Tabela1[[#This Row],[Nome fantasia]]="","",_xlfn.XLOOKUP($C56,Log!D:D,Log!X:X,,,-1)),"") -> 45931
C57: SABOR NATURAL | D57: 05.488.121/0001-48 | E57: PR | K57: LEAD | M57: =IF(OR(J57<=0,J57=""),"","Recompra") | N57: =IFERROR(IF(Tabela1[[#This Row],[Nome fantasia]]="","",_xlfn.XLOOKUP($C57,Log!D:D,Log!B:B,,,-1)),"") -> 45929 | O57: =IFERROR(_xlfn.XLOOKUP($C57,Log!D:D,Log!W:W,,,-1),"") -> EM ATENDIMENTO | P57: =IFERROR(_xlfn.XLOOKUP($C57,Log!D:D,Log!Y:Y,,,-1),"") -> TENTAR REATIVAR | R57: =IFERROR(IF(Tabela1[[#This Row],[Nome fantasia]]="","",_xlfn.XLOOKUP($C57,Log!D:D,Log!X:X,,,-1)),"") -> 45931
C58: SABOR NATURAL | D58: 23.181.735/0001-64 | E58: SC | K58: LEAD | M58: =IF(OR(J58<=0,J58=""),"","Recompra") | N58: =IFERROR(IF(Tabela1[[#This Row],[Nome fantasia]]="","",_xlfn.XLOOKUP($C58,Log!D:D,Log!B:B,,,-1)),"") -> 45929 | O58: =IFERROR(_xlfn.XLOOKUP($C58,Log!D:D,Log!W:W,,,-1),"") -> EM ATENDIMENTO | P58: =IFERROR(_xlfn.XLOOKUP($C58,Log!D:D,Log!Y:Y,,,-1),"") -> TENTAR REATIVAR | R58: =IFERROR(IF(Tabela1[[#This Row],[Nome fantasia]]="","",_xlfn.XLOOKUP($C58,Log!D:D,Log!X:X,,,-1)),"") -> 45931
C59: KAUCLINICAL CARE | D59: 54.406.218/0001-70 | E59: PR | K59: LEAD | M59: =IF(OR(J59<=0,J59=""),"","Recompra") | N59: =IFERROR(IF(Tabela1[[#This Row],[Nome fantasia]]="","",_xlfn.XLOOKUP($C59,Log!D:D,Log!B:B,,,-1)),"") -> 45930 | O59: =IFERROR(_xlfn.XLOOKUP($C59,Log!D:D,Log!W:W,,,-1),"") -> EM ATENDIMENTO | P59: =IFERROR(_xlfn.XLOOKUP($C59,Log!D:D,Log!Y:Y,,,-1),"") -> CLIENTE ESTA DE FAZER CARRINHO NO E-COMMERCE | R59: =IFERROR(IF(Tabela1[[#This Row],[Nome fantasia]]="","",_xlfn.XLOOKUP($C59,Log!D:D,Log!X:X,,,-1)),"") -> 45932
C60: SKINA SUPERMERCADO | D60: * | E60: SC | F60: Manu Ditzel | G60: * | H60: * | I60: * | J60: * | K60: LEAD | M60: =IF(OR(J60<=0,J60=""),"","Recompra") -> Recompra | N60: =IFERROR(IF(Tabela1[[#This Row],[Nome fantasia]]="","",_xlfn.XLOOKUP($C60,Log!D:D,Log!B:B,,,-1)),"") -> 45922 | O60: =IFERROR(_xlfn.XLOOKUP($C60,Log!D:D,Log!W:W,,,-1),"") -> EM ATENDIMENTO | P60: =IFERROR(_xlfn.XLOOKUP($C60,Log!D:D,Log!Y:Y,,,-1),"") -> MERCADO REGIÃO PRAIA, COMPRAVA COM A BDL | R60: =IFERROR(IF(Tabela1[[#This Row],[Nome fantasia]]="","",_xlfn.XLOOKUP($C60,Log!D:D,Log!X:X,,,-1)),"") -> 45924
C61: COMPLEX NUTRITION | D61: 34.316.966/0001-54 | E61: RS | F61: Manu Ditzel | G61: 11/08/2025 | H61: 801.51 | I61: 57 | J61: 0 | K61: ATIVO | M61: =IF(OR(J61<=0,J61=""),"","Recompra") | N61: =IFERROR(IF(Tabela1[[#This Row],[Nome fantasia]]="","",_xlfn.XLOOKUP($C61,Log!D:D,Log!B:B,,,-1)),"") -> 45918 | O61: =IFERROR(_xlfn.XLOOKUP($C61,Log!D:D,Log!W:W,,,-1),"") -> FOLLOW UP 7 | P61: =IFERROR(_xlfn.XLOOKUP($C61,Log!D:D,Log!Y:Y,,,-1),"") -> MENSAGEM | R61: =IFERROR(IF(Tabela1[[#This Row],[Nome fantasia]]="","",_xlfn.XLOOKUP($C61,Log!D:D,Log!X:X,,,-1)),"") -> 45929
C62: VARIEDEX | D62: * | E62: SP | F62: Manu Ditzel | G62: * | H62: * | I62: * | J62: * | K62: LEAD | M62: =IF(OR(J62<=0,J62=""),"","Recompra") -> Recompra | N62: =IFERROR(IF(Tabela1[[#This Row],[Nome fantasia]]="","",_xlfn.XLOOKUP($C62,Log!D:D,Log!B:B,,,-1)),"") -> 45918 | O62: =IFERROR(_xlfn.XLOOKUP($C62,Log!D:D,Log!W:W,,,-1),"") -> FOLLOW UP 7 | P62: =IFERROR(_xlfn.XLOOKUP($C62,Log!D:D,Log!Y:Y,,,-1),"") -> LEAD | R62: =IFERROR(IF(Tabela1[[#This Row],[Nome fantasia]]="","",_xlfn.XLOOKUP($C62,Log!D:D,Log!X:X,,,-1)),"") -> 45929
C63: C J LIFE LTDA - ME | D63: 58.258.680/0001-28 | E63: PI | F63: Manu Ditzel | G63: * | H63: * | I63: * | J63: * | K63: LEAD | M63: =IF(OR(J63<=0,J63=""),"","Recompra") -> Recompra | N63: =IFERROR(IF(Tabela1[[#This Row],[Nome fantasia]]="","",_xlfn.XLOOKUP($C63,Log!D:D,Log!B:B,,,-1)),"") -> 45925 | O63: =IFERROR(_xlfn.XLOOKUP($C63,Log!D:D,Log!W:W,,,-1),"") -> EM ATENDIMENTO | P63: =IFERROR(_xlfn.XLOOKUP($C63,Log!D:D,Log!Y:Y,,,-1),"") -> REDE VIDA LEVE | R63: =IFERROR(IF(Tabela1[[#This Row],[Nome fantasia]]="","",_xlfn.XLOOKUP($C63,Log!D:D,Log!X:X,,,-1)),"") -> 45929
C64: EMPORIUM COMERCIO DE ALIMENTOS - ME | D64: 45.663.004/0001-98 | E64: RS | F64: Manu Ditzel | G64: * | H64: * | I64: * | J64: * | K64: LEAD | M64: =IF(OR(J64<=0,J64=""),"","Recompra") -> Recompra | N64: =IFERROR(IF(Tabela1[[#This Row],[Nome fantasia]]="","",_xlfn.XLOOKUP($C64,Log!D:D,Log!B:B,,,-1)),"") -> 45925 | O64: =IFERROR(_xlfn.XLOOKUP($C64,Log!D:D,Log!W:W,,,-1),"") -> EM ATENDIMENTO | P64: =IFERROR(_xlfn.XLOOKUP($C64,Log!D:D,Log!Y:Y,,,-1),"") -> FEITO CONTATO PARA AVALIAR PARCERIA | R64: =IFERROR(IF(Tabela1[[#This Row],[Nome fantasia]]="","",_xlfn.XLOOKUP($C64,Log!D:D,Log!X:X,,,-1)),"") -> 45929
C65: UVA PASSA PRODUTOS NATURAIS LTDA - ME | D65: 42.956.843/0001-06 | E65: RS | F65: Manu Ditzel | G65: * | H65: * | I65: * | J65: * | K65: LEAD | M65: =IF(OR(J65<=0,J65=""),"","Recompra") -> Recompra | N65: =IFERROR(IF(Tabela1[[#This Row],[Nome fantasia]]="","",_xlfn.XLOOKUP($C65,Log!D:D,Log!B:B,,,-1)),"") -> 45925 | O65: =IFERROR(_xlfn.XLOOKUP($C65,Log!D:D,Log!W:W,,,-1),"") -> EM ATENDIMENTO | P65: =IFERROR(_xlfn.XLOOKUP($C65,Log!D:D,Log!Y:Y,,,-1),"") -> FEITO CONTATO PARA AVALIAR PARCERIA | R65: =IFERROR(IF(Tabela1[[#This Row],[Nome fantasia]]="","",_xlfn.XLOOKUP($C65,Log!D:D,Log!X:X,,,-1)),"") -> 45929
C66: NADAI CONFORT HOTEL & SPA | D66: 75.608.620/0001-07 | E66: PR | F66: Manu Ditzel | K66: LEAD | M66: =IF(OR(J66<=0,J66=""),"","Recompra") | N66: =IFERROR(IF(Tabela1[[#This Row],[Nome fantasia]]="","",_xlfn.XLOOKUP($C66,Log!D:D,Log!B:B,,,-1)),"") -> 45925 | O66: =IFERROR(_xlfn.XLOOKUP($C66,Log!D:D,Log!W:W,,,-1),"") -> CADASTRO | P66: =IFERROR(_xlfn.XLOOKUP($C66,Log!D:D,Log!Y:Y,,,-1),"") -> AMOSTRAS | R66: =IFERROR(IF(Tabela1[[#This Row],[Nome fantasia]]="","",_xlfn.XLOOKUP($C66,Log!D:D,Log!X:X,,,-1)),"") -> 45929
C67: C J LIFE LTDA - ME | D67: 58.258.680/0001-28 | E67: PI | F67: Manu Ditzel | K67: LEAD | M67: =IF(OR(J67<=0,J67=""),"","Recompra") | N67: =IFERROR(IF(Tabela1[[#This Row],[Nome fantasia]]="","",_xlfn.XLOOKUP($C67,Log!D:D,Log!B:B,,,-1)),"") -> 45925 | O67: =IFERROR(_xlfn.XLOOKUP($C67,Log!D:D,Log!W:W,,,-1),"") -> EM ATENDIMENTO | P67: =IFERROR(_xlfn.XLOOKUP($C67,Log!D:D,Log!Y:Y,,,-1),"") -> REDE VIDA LEVE | R67: =IFERROR(IF(Tabela1[[#This Row],[Nome fantasia]]="","",_xlfn.XLOOKUP($C67,Log!D:D,Log!X:X,,,-1)),"") -> 45929
C68: I.B.A.C. INDUSTRIA BRASILEIRA DE ALIMENT | D68: 61.472.205/0001-64 | E68: SP | F68: Manu Ditzel | K68: LEAD | M68: =IF(OR(J68<=0,J68=""),"","Recompra") | N68: =IFERROR(IF(Tabela1[[#This Row],[Nome fantasia]]="","",_xlfn.XLOOKUP($C68,Log!D:D,Log!B:B,,,-1)),"") -> 45925 | O68: =IFERROR(_xlfn.XLOOKUP($C68,Log!D:D,Log!W:W,,,-1),"") -> EM ATENDIMENTO | P68: =IFERROR(_xlfn.XLOOKUP($C68,Log!D:D,Log!Y:Y,,,-1),"") -> PROSPECÇÃO, CACAU SHOW, FOI ENVIADO AMOSTRA, AGUARDANDO ... | R68: =IFERROR(IF(Tabela1[[#This Row],[Nome fantasia]]="","",_xlfn.XLOOKUP($C68,Log!D:D,Log!X:X,,,-1)),"") -> 45929
C69: NUTRIFIT RIO DO SUL LTDA - ME | D69: 57.369.293/0001-04 | E69: SC | F69: Manu Ditzel | K69: LEAD | M69: =IF(OR(J69<=0,J69=""),"","Recompra") | N69: =IFERROR(IF(Tabela1[[#This Row],[Nome fantasia]]="","",_xlfn.XLOOKUP($C69,Log!D:D,Log!B:B,,,-1)),"") -> 45925 | O69: =IFERROR(_xlfn.XLOOKUP($C69,Log!D:D,Log!W:W,,,-1),"") -> EM ATENDIMENTO | P69: =IFERROR(_xlfn.XLOOKUP($C69,Log!D:D,Log!Y:Y,,,-1),"") -> FEITO CONTATO PARA AVALIAR PARCERIA | R69: =IFERROR(IF(Tabela1[[#This Row],[Nome fantasia]]="","",_xlfn.XLOOKUP($C69,Log!D:D,Log!X:X,,,-1)),"") -> 45929
C70: RDS ULTRA EMPORIO & SUPLEMENTOS LTDA - M | D70: 00.310.595/0001-81 | E70: SP | F70: Manu Ditzel | K70: LEAD | M70: =IF(OR(J70<=0,J70=""),"","Recompra") | N70: =IFERROR(IF(Tabela1[[#This Row],[Nome fantasia]]="","",_xlfn.XLOOKUP($C70,Log!D:D,Log!B:B,,,-1)),"") -> 45925 | O70: =IFERROR(_xlfn.XLOOKUP($C70,Log!D:D,Log!W:W,,,-1),"") -> EM ATENDIMENTO | P70: =IFERROR(_xlfn.XLOOKUP($C70,Log!D:D,Log!Y:Y,,,-1),"") -> FEITO CONTATO PARA AVALIAR PARCERIA | R70: =IFERROR(IF(Tabela1[[#This Row],[Nome fantasia]]="","",_xlfn.XLOOKUP($C70,Log!D:D,Log!X:X,,,-1)),"") -> 45929
C71: UVA PASSA PRODUTOS NATURAIS LTDA - ME | D71: 42.956.843/0001-06 | E71: RS | F71: Manu Ditzel | K71: LEAD | M71: =IF(OR(J71<=0,J71=""),"","Recompra") | N71: =IFERROR(IF(Tabela1[[#This Row],[Nome fantasia]]="","",_xlfn.XLOOKUP($C71,Log!D:D,Log!B:B,,,-1)),"") -> 45925 | O71: =IFERROR(_xlfn.XLOOKUP($C71,Log!D:D,Log!W:W,,,-1),"") -> EM ATENDIMENTO | P71: =IFERROR(_xlfn.XLOOKUP($C71,Log!D:D,Log!Y:Y,,,-1),"") -> FEITO CONTATO PARA AVALIAR PARCERIA | R71: =IFERROR(IF(Tabela1[[#This Row],[Nome fantasia]]="","",_xlfn.XLOOKUP($C71,Log!D:D,Log!X:X,,,-1)),"") -> 45929
C72: L. SENDESKI SCHUERMAN LTDA - EPP | D72: 04.999.525/0001-33 | E72: PR | F72: Manu Ditzel | K72: LEAD | M72: =IF(OR(J72<=0,J72=""),"","Recompra") | N72: =IFERROR(IF(Tabela1[[#This Row],[Nome fantasia]]="","",_xlfn.XLOOKUP($C72,Log!D:D,Log!B:B,,,-1)),"") -> 45925 | O72: =IFERROR(_xlfn.XLOOKUP($C72,Log!D:D,Log!W:W,,,-1),"") -> EM ATENDIMENTO | P72: =IFERROR(_xlfn.XLOOKUP($C72,Log!D:D,Log!Y:Y,,,-1),"") -> FEITO CONTATO PARA AVALIAR PARCERIA | R72: =IFERROR(IF(Tabela1[[#This Row],[Nome fantasia]]="","",_xlfn.XLOOKUP($C72,Log!D:D,Log!X:X,,,-1)),"") -> 45929
C73: ANDRESSA MARIA PEDON LTDA - ME | D73: 13.152.698/0001-02 | E73: RS | F73: Manu Ditzel | K73: LEAD | M73: =IF(OR(J73<=0,J73=""),"","Recompra") | N73: =IFERROR(IF(Tabela1[[#This Row],[Nome fantasia]]="","",_xlfn.XLOOKUP($C73,Log!D:D,Log!B:B,,,-1)),"") -> 45925 | O73: =IFERROR(_xlfn.XLOOKUP($C73,Log!D:D,Log!W:W,,,-1),"") -> EM ATENDIMENTO | P73: =IFERROR(_xlfn.XLOOKUP($C73,Log!D:D,Log!Y:Y,,,-1),"") -> FEITO CONTATO PARA AVALIAR PARCERIA | R73: =IFERROR(IF(Tabela1[[#This Row],[Nome fantasia]]="","",_xlfn.XLOOKUP($C73,Log!D:D,Log!X:X,,,-1)),"") -> 45929
C74: JOSE CARLOS ROSSA - EPP (MINIMERCADO ROSSA) | D74: 06.042.176/0001-92 | E74: SC | F74: Manu Ditzel | K74: LEAD | M74: =IF(OR(J74<=0,J74=""),"","Recompra") | N74: =IFERROR(IF(Tabela1[[#This Row],[Nome fantasia]]="","",_xlfn.XLOOKUP($C74,Log!D:D,Log!B:B,,,-1)),"") -> 45925 | O74: =IFERROR(_xlfn.XLOOKUP($C74,Log!D:D,Log!W:W,,,-1),"") -> EM ATENDIMENTO | P74: =IFERROR(_xlfn.XLOOKUP($C74,Log!D:D,Log!Y:Y,,,-1),"") -> FEITO CONTATO PARA AVALIAR PARCERIA | R74: =IFERROR(IF(Tabela1[[#This Row],[Nome fantasia]]="","",_xlfn.XLOOKUP($C74,Log!D:D,Log!X:X,,,-1)),"") -> 45929
C75: EMPORIUM COMERCIO DE ALIMENTOS - ME | D75: 45.663.004/0001-98 | E75: RS | F75: Manu Ditzel | K75: LEAD | M75: =IF(OR(J75<=0,J75=""),"","Recompra") | N75: =IFERROR(IF(Tabela1[[#This Row],[Nome fantasia]]="","",_xlfn.XLOOKUP($C75,Log!D:D,Log!B:B,,,-1)),"") -> 45925 | O75: =IFERROR(_xlfn.XLOOKUP($C75,Log!D:D,Log!W:W,,,-1),"") -> EM ATENDIMENTO | P75: =IFERROR(_xlfn.XLOOKUP($C75,Log!D:D,Log!Y:Y,,,-1),"") -> FEITO CONTATO PARA AVALIAR PARCERIA | R75: =IFERROR(IF(Tabela1[[#This Row],[Nome fantasia]]="","",_xlfn.XLOOKUP($C75,Log!D:D,Log!X:X,,,-1)),"") -> 45929
C76: MERCADO FABRIL | D76: * | E76: PR | F76: Manu Ditzel | G76: * | H76: * | I76: * | J76: * | K76: LEAD | M76: =IF(OR(J76<=0,J76=""),"","Recompra") -> Recompra | N76: =IFERROR(IF(Tabela1[[#This Row],[Nome fantasia]]="","",_xlfn.XLOOKUP($C76,Log!D:D,Log!B:B,,,-1)),"") -> 45926 | O76: =IFERROR(_xlfn.XLOOKUP($C76,Log!D:D,Log!W:W,,,-1),"") -> EM ATENDIMENTO | P76: =IFERROR(_xlfn.XLOOKUP($C76,Log!D:D,Log!Y:Y,,,-1),"") -> CLIENTE QUER REPRESENTATE | R76: =IFERROR(IF(Tabela1[[#This Row],[Nome fantasia]]="","",_xlfn.XLOOKUP($C76,Log!D:D,Log!X:X,,,-1)),"") -> 45930
C77: RAW MARKET ALIMENTOS SAUDAVEIS | D77: 40.607.315/0001-16 | E77: SC | F77: Manu Ditzel | G77: 30/06/2025 | H77: 1792.87 | I77: 99 | J77: 0 | K77: INATIVO RECENTE | M77: =IF(OR(J77<=0,J77=""),"","Recompra") | N77: =IFERROR(IF(Tabela1[[#This Row],[Nome fantasia]]="","",_xlfn.XLOOKUP($C77,Log!D:D,Log!B:B,,,-1)),"") -> 45994 | O77: =IFERROR(_xlfn.XLOOKUP($C77,Log!D:D,Log!W:W,,,-1),"") -> EM ATENDIMENTO | P77: =IFERROR(_xlfn.XLOOKUP($C77,Log!D:D,Log!Y:Y,,,-1),"") -> MENSAGEM PARA NOVO RELACIOMENTO | R77: =IFERROR(IF(Tabela1[[#This Row],[Nome fantasia]]="","",_xlfn.XLOOKUP($C77,Log!D:D,Log!X:X,,,-1)),"") -> 45996
C78: MARGHERITA | D78: 49.946.160/0001-17 | E78: PR | F78: Manu Ditzel | G78: * | H78: * | I78: * | J78: * | K78: LEAD | M78: =IF(OR(J78<=0,J78=""),"","Recompra") -> Recompra | N78: =IFERROR(IF(Tabela1[[#This Row],[Nome fantasia]]="","",_xlfn.XLOOKUP($C78,Log!D:D,Log!B:B,,,-1)),"") -> 45922 | O78: =IFERROR(_xlfn.XLOOKUP($C78,Log!D:D,Log!W:W,,,-1),"") -> FOLLOW UP 7 | P78: =IFERROR(_xlfn.XLOOKUP($C78,Log!D:D,Log!Y:Y,,,-1),"") -> VOLTANDO PARA VER SE A CLIENTE CONSEGUIU ACESSAR NOSSO E-COMMERCE | R78: =IFERROR(IF(Tabela1[[#This Row],[Nome fantasia]]="","",_xlfn.XLOOKUP($C78,Log!D:D,Log!X:X,,,-1)),"") -> 45931
C79: ULTRA SUPLEMENTOS | D79: 00.310.595/0001-81 | E79: SP | F79: Manu Ditzel | G79: * | H79: * | I79: * | J79: * | K79: LEAD | M79: =IF(OR(J79<=0,J79=""),"","Recompra") -> Recompra | N79: =IFERROR(IF(Tabela1[[#This Row],[Nome fantasia]]="","",_xlfn.XLOOKUP($C79,Log!D:D,Log!B:B,,,-1)),"") -> 45929 | O79: =IFERROR(_xlfn.XLOOKUP($C79,Log!D:D,Log!W:W,,,-1),"") -> EM ATENDIMENTO | P79: =IFERROR(_xlfn.XLOOKUP($C79,Log!D:D,Log!Y:Y,,,-1),"") -> FEITO INUMEROS CONTATOS | R79: =IFERROR(IF(Tabela1[[#This Row],[Nome fantasia]]="","",_xlfn.XLOOKUP($C79,Log!D:D,Log!X:X,,,-1)),"") -> 45931
C80: STYLO FARMA CURITIBA | D80: 55.795.646/0001-02 | E80: PR | F80: Manu Ditzel | G80: 16/06/2025 | H80: 699.03 | I80: 113 | J80: 0 | K80: INATIVO ANTIGO | M80: =IF(OR(J80<=0,J80=""),"","Recompra") | N80: =IFERROR(IF(Tabela1[[#This Row],[Nome fantasia]]="","",_xlfn.XLOOKUP($C80,Log!D:D,Log!B:B,,,-1)),"") -> 45923 | O80: =IFERROR(_xlfn.XLOOKUP($C80,Log!D:D,Log!W:W,,,-1),"") -> FOLLOW UP 7 | P80: =IFERROR(_xlfn.XLOOKUP($C80,Log!D:D,Log!Y:Y,,,-1),"") -> FEITO CONTATO PARA ENTENDER O MOTIVO DA NÃO VENDA | R80: =IFERROR(IF(Tabela1[[#This Row],[Nome fantasia]]="","",_xlfn.XLOOKUP($C80,Log!D:D,Log!X:X,,,-1)),"") -> 45932
C81: JARDIM DO GRANEL COMERCIO DE ALIMENTOS LTDA | D81: 51.213.425/0001-10 | E81: PR | F81: Manu Ditzel | G81: 09/06/2025 | H81: 11358.43 | I81: 120 | J81: 0 | K81: INATIVO ANTIGO | M81: =IF(OR(J81<=0,J81=""),"","Recompra") | N81: =IFERROR(IF(Tabela1[[#This Row],[Nome fantasia]]="","",_xlfn.XLOOKUP($C81,Log!D:D,Log!B:B,,,-1)),"") -> 45923 | O81: =IFERROR(_xlfn.XLOOKUP($C81,Log!D:D,Log!W:W,,,-1),"") -> FOLLOW UP 7 | P81: =IFERROR(_xlfn.XLOOKUP($C81,Log!D:D,Log!Y:Y,,,-1),"") -> CLIENTE TROCOU O COMPRAS | R81: =IFERROR(IF(Tabela1[[#This Row],[Nome fantasia]]="","",_xlfn.XLOOKUP($C81,Log!D:D,Log!X:X,,,-1)),"") -> 45932
C82: SUPERMERCADO TIO ANTONIO LTDA | D82: 16.693.613/0003-53 | E82: MG | F82: Manu Ditzel | G82: 22/05/2025 | H82: 1415.8 | I82: 138 | J82: 0 | K82: INATIVO ANTIGO | M82: =IF(OR(J82<=0,J82=""),"","Recompra") | N82: =IFERROR(IF(Tabela1[[#This Row],[Nome fantasia]]="","",_xlfn.XLOOKUP($C82,Log!D:D,Log!B:B,,,-1)),"") -> 45923 | O82: =IFERROR(_xlfn.XLOOKUP($C82,Log!D:D,Log!W:W,,,-1),"") -> FOLLOW UP 7 | P82: =IFERROR(_xlfn.XLOOKUP($C82,Log!D:D,Log!Y:Y,,,-1),"") -> FEITO CONTATO PARA ENTENDER O MOTIVO DA NÃO VENDA | R82: =IFERROR(IF(Tabela1[[#This Row],[Nome fantasia]]="","",_xlfn.XLOOKUP($C82,Log!D:D,Log!X:X,,,-1)),"") -> 45932
C83: HABITTUDE | D83: 44.238.838/0001-93 | E83: RS | F83: Manu Ditzel | G83: 28/04/2025 | H83: 838.45 | I83: 162 | J83: 0 | K83: INATIVO ANTIGO | M83: =IF(OR(J83<=0,J83=""),"","Recompra") | N83: =IFERROR(IF(Tabela1[[#This Row],[Nome fantasia]]="","",_xlfn.XLOOKUP($C83,Log!D:D,Log!B:B,,,-1)),"") -> 45999 | O83: =IFERROR(_xlfn.XLOOKUP($C83,Log!D:D,Log!W:W,,,-1),"") -> EM ATENDIMENTO | P83: =IFERROR(_xlfn.XLOOKUP($C83,Log!D:D,Log!Y:Y,,,-1),"") -> CLIENTE FICOU DE VER O PORTAL | R83: =IFERROR(IF(Tabela1[[#This Row],[Nome fantasia]]="","",_xlfn.XLOOKUP($C83,Log!D:D,Log!X:X,,,-1)),"") -> 46001
C84: KAUCLINICAL CARE | D84: 54.406.218/0001-70 | E84: PR | F84: Manu Ditzel | G84: * | H84: * | I84: * | J84: * | K84: LEAD | M84: =IF(OR(J84<=0,J84=""),"","Recompra") -> Recompra | N84: =IFERROR(IF(Tabela1[[#This Row],[Nome fantasia]]="","",_xlfn.XLOOKUP($C84,Log!D:D,Log!B:B,,,-1)),"") -> 45930 | O84: =IFERROR(_xlfn.XLOOKUP($C84,Log!D:D,Log!W:W,,,-1),"") -> EM ATENDIMENTO | P84: =IFERROR(_xlfn.XLOOKUP($C84,Log!D:D,Log!Y:Y,,,-1),"") -> CLIENTE ESTA DE FAZER CARRINHO NO E-COMMERCE | R84: =IFERROR(IF(Tabela1[[#This Row],[Nome fantasia]]="","",_xlfn.XLOOKUP($C84,Log!D:D,Log!X:X,,,-1)),"") -> 45932
C85: MOENDA DOS GRAOS PRODUTOS NATURAIS LTDA | D85: 17.352.028/0001-90 | E85: SC | F85: Manu Ditzel | K85: LEAD | M85: =IF(OR(J85<=0,J85=""),"","Recompra") | N85: =IFERROR(IF(Tabela1[[#This Row],[Nome fantasia]]="","",_xlfn.XLOOKUP($C85,Log!D:D,Log!B:B,,,-1)),"") -> 45930 | O85: =IFERROR(_xlfn.XLOOKUP($C85,Log!D:D,Log!W:W,,,-1),"") -> EM ATENDIMENTO | P85: =IFERROR(_xlfn.XLOOKUP($C85,Log!D:D,Log!Y:Y,,,-1),"") -> PROPECÇÃO BASE SAP | R85: =IFERROR(IF(Tabela1[[#This Row],[Nome fantasia]]="","",_xlfn.XLOOKUP($C85,Log!D:D,Log!X:X,,,-1)),"") -> 45932
C86: DENI | D86: * | E86: RS | F86: Manu Ditzel | K86: LEAD | M86: =IF(OR(J86<=0,J86=""),"","Recompra") | N86: =IFERROR(IF(Tabela1[[#This Row],[Nome fantasia]]="","",_xlfn.XLOOKUP($C86,Log!D:D,Log!B:B,,,-1)),"") -> 45930 | O86: =IFERROR(_xlfn.XLOOKUP($C86,Log!D:D,Log!W:W,,,-1),"") -> EM ATENDIMENTO | P86: =IFERROR(_xlfn.XLOOKUP($C86,Log!D:D,Log!Y:Y,,,-1),"") -> VEIO ATRAS DOS NOSSO GRANEL | R86: =IFERROR(IF(Tabela1[[#This Row],[Nome fantasia]]="","",_xlfn.XLOOKUP($C86,Log!D:D,Log!X:X,,,-1)),"") -> 45932
C87: OVNI VEGANO | D87: * | E87: RS | F87: Manu Ditzel | K87: LEAD | M87: =IF(OR(J87<=0,J87=""),"","Recompra") | N87: =IFERROR(IF(Tabela1[[#This Row],[Nome fantasia]]="","",_xlfn.XLOOKUP($C87,Log!D:D,Log!B:B,,,-1)),"") -> 45930 | O87: =IFERROR(_xlfn.XLOOKUP($C87,Log!D:D,Log!W:W,,,-1),"") -> EM ATENDIMENTO | P87: =IFERROR(_xlfn.XLOOKUP($C87,Log!D:D,Log!Y:Y,,,-1),"") -> VEIO ATRAS DAS LASCAS | R87: =IFERROR(IF(Tabela1[[#This Row],[Nome fantasia]]="","",_xlfn.XLOOKUP($C87,Log!D:D,Log!X:X,,,-1)),"") -> 45932
C88: KAUCLINICAL CARE | D88: 54.406.218/0001-70 | E88: PR | F88: Manu Ditzel | K88: LEAD | M88: =IF(OR(J88<=0,J88=""),"","Recompra") | N88: =IFERROR(IF(Tabela1[[#This Row],[Nome fantasia]]="","",_xlfn.XLOOKUP($C88,Log!D:D,Log!B:B,,,-1)),"") -> 45930 | O88: =IFERROR(_xlfn.XLOOKUP($C88,Log!D:D,Log!W:W,,,-1),"") -> EM ATENDIMENTO | P88: =IFERROR(_xlfn.XLOOKUP($C88,Log!D:D,Log!Y:Y,,,-1),"") -> CLIENTE ESTA DE FAZER CARRINHO NO E-COMMERCE | R88: =IFERROR(IF(Tabela1[[#This Row],[Nome fantasia]]="","",_xlfn.XLOOKUP($C88,Log!D:D,Log!X:X,,,-1)),"") -> 45932
C89: MAESTRIA VERDE | D89: * | E89: SC | F89: Manu Ditzel | K89: LEAD | M89: =IF(OR(J89<=0,J89=""),"","Recompra") | N89: =IFERROR(IF(Tabela1[[#This Row],[Nome fantasia]]="","",_xlfn.XLOOKUP($C89,Log!D:D,Log!B:B,,,-1)),"") -> 45924 | O89: =IFERROR(_xlfn.XLOOKUP($C89,Log!D:D,Log!W:W,,,-1),"") -> FOLLOW UP 7 | P89: =IFERROR(_xlfn.XLOOKUP($C89,Log!D:D,Log!Y:Y,,,-1),"") -> INDICAÇÃO MAICON | R89: =IFERROR(IF(Tabela1[[#This Row],[Nome fantasia]]="","",_xlfn.XLOOKUP($C89,Log!D:D,Log!X:X,,,-1)),"") -> 45933
C90: DIMANGIARE ALIMENTOS | D90: 15.415.386/0001-70 | E90: SC | F90: Manu Ditzel | K90: LEAD | M90: =IF(OR(J90<=0,J90=""),"","Recompra") | N90: =IFERROR(IF(Tabela1[[#This Row],[Nome fantasia]]="","",_xlfn.XLOOKUP($C90,Log!D:D,Log!B:B,,,-1)),"") -> 45932 | O90: =IFERROR(_xlfn.XLOOKUP($C90,Log!D:D,Log!W:W,,,-1),"") -> EM ATENDIMENTO | P90: =IFERROR(_xlfn.XLOOKUP($C90,Log!D:D,Log!Y:Y,,,-1),"") -> CLIENTE QUER GOTAS PARA CHOCOTONE | R90: =IFERROR(IF(Tabela1[[#This Row],[Nome fantasia]]="","",_xlfn.XLOOKUP($C90,Log!D:D,Log!X:X,,,-1)),"") -> 45936
C91: MJ PRODUTOS NATURAIS | D91: 60.670.819/0001-98 | E91: SC | F91: Manu Ditzel | G91: 05/08/2025 | H91: 1263.69 | I91: 63 | J91: 0 | K91: ATIVO | M91: =IF(OR(J91<=0,J91=""),"","Recompra") | N91: =IFERROR(IF(Tabela1[[#This Row],[Nome fantasia]]="","",_xlfn.XLOOKUP($C91,Log!D:D,Log!B:B,,,-1)),"") -> 45874 | O91: =IFERROR(_xlfn.XLOOKUP($C91,Log!D:D,Log!W:W,,,-1),"") -> VENDA | P91: =IFERROR(_xlfn.XLOOKUP($C91,Log!D:D,Log!Y:Y,,,-1),"") -> RECOMPRA | R91: =IFERROR(IF(Tabela1[[#This Row],[Nome fantasia]]="","",_xlfn.XLOOKUP($C91,Log!D:D,Log!X:X,,,-1)),"") -> 45937
C92: MUNDO VERDE VOCE MAIS SAUDAVEL | D92: 28.019.593/0001-57 | E92: SP | F92: Manu Ditzel | G92: 30/09/2025 | H92: 1928.84 | I92: 7 | J92: 55 | K92: ATIVO | M92: =IF(OR(J92<=0,J92=""),"","Recompra") -> Recompra | N92: =IFERROR(IF(Tabela1[[#This Row],[Nome fantasia]]="","",_xlfn.XLOOKUP($C92,Log!D:D,Log!B:B,,,-1)),"") -> 45875 | O92: =IFERROR(_xlfn.XLOOKUP($C92,Log!D:D,Log!W:W,,,-1),"") -> VENDA | P92: =IFERROR(_xlfn.XLOOKUP($C92,Log!D:D,Log!Y:Y,,,-1),"") -> RECOMPRA | R92: =IFERROR(IF(Tabela1[[#This Row],[Nome fantasia]]="","",_xlfn.XLOOKUP($C92,Log!D:D,Log!X:X,,,-1)),"") -> 45938
C93: CAMILA VEDOI - COMERCIO VAREJISTA DE ALI | D93: 42.080.716/0001-96 | E93: RS | F93: Manu Ditzel | K93: LEAD | M93: =IF(OR(J93<=0,J93=""),"","Recompra") | N93: =IFERROR(IF(Tabela1[[#This Row],[Nome fantasia]]="","",_xlfn.XLOOKUP($C93,Log!D:D,Log!B:B,,,-1)),"") -> 45937 | O93: =IFERROR(_xlfn.XLOOKUP($C93,Log!D:D,Log!W:W,,,-1),"") -> EM ATENDIMENTO | P93: =IFERROR(_xlfn.XLOOKUP($C93,Log!D:D,Log!Y:Y,,,-1),"") -> CLIENTES BASE SAP | R93: =IFERROR(IF(Tabela1[[#This Row],[Nome fantasia]]="","",_xlfn.XLOOKUP($C93,Log!D:D,Log!X:X,,,-1)),"") -> 45939
C94: R&B PRODUTOS NATURAIS LTDA - ME | D94: 06.128.069/0001-81 | E94: SC | F94: Manu Ditzel | K94: LEAD | M94: =IF(OR(J94<=0,J94=""),"","Recompra") | N94: =IFERROR(IF(Tabela1[[#This Row],[Nome fantasia]]="","",_xlfn.XLOOKUP($C94,Log!D:D,Log!B:B,,,-1)),"") -> 45937 | O94: =IFERROR(_xlfn.XLOOKUP($C94,Log!D:D,Log!W:W,,,-1),"") -> EM ATENDIMENTO | P94: =IFERROR(_xlfn.XLOOKUP($C94,Log!D:D,Log!Y:Y,,,-1),"") -> CLIENTES BASE SAP | R94: =IFERROR(IF(Tabela1[[#This Row],[Nome fantasia]]="","",_xlfn.XLOOKUP($C94,Log!D:D,Log!X:X,,,-1)),"") -> 45939
C95: SABORES & GRAOS PRODUTOS NATURAIS LTDA - | D95: 17.989.340/0001-90 | E95: SC | F95: Manu Ditzel | K95: LEAD | M95: =IF(OR(J95<=0,J95=""),"","Recompra") | N95: =IFERROR(IF(Tabela1[[#This Row],[Nome fantasia]]="","",_xlfn.XLOOKUP($C95,Log!D:D,Log!B:B,,,-1)),"") -> 45937 | O95: =IFERROR(_xlfn.XLOOKUP($C95,Log!D:D,Log!W:W,,,-1),"") -> EM ATENDIMENTO | P95: =IFERROR(_xlfn.XLOOKUP($C95,Log!D:D,Log!Y:Y,,,-1),"") -> CLIENTES BASE SAP | R95: =IFERROR(IF(Tabela1[[#This Row],[Nome fantasia]]="","",_xlfn.XLOOKUP($C95,Log!D:D,Log!X:X,,,-1)),"") -> 45939
C96: TONON COMERCIO DE PRODUTOS NATURAIS LTDA | D96: 30.741.171/0001-32 | E96: PR | F96: Manu Ditzel | K96: LEAD | M96: =IF(OR(J96<=0,J96=""),"","Recompra") | N96: =IFERROR(IF(Tabela1[[#This Row],[Nome fantasia]]="","",_xlfn.XLOOKUP($C96,Log!D:D,Log!B:B,,,-1)),"") -> 45937 | O96: =IFERROR(_xlfn.XLOOKUP($C96,Log!D:D,Log!W:W,,,-1),"") -> EM ATENDIMENTO | P96: =IFERROR(_xlfn.XLOOKUP($C96,Log!D:D,Log!Y:Y,,,-1),"") -> CLIENTES BASE SAP | R96: =IFERROR(IF(Tabela1[[#This Row],[Nome fantasia]]="","",_xlfn.XLOOKUP($C96,Log!D:D,Log!X:X,,,-1)),"") -> 45939
C97: PONTO NATURAL COMERCIO DE ALIMENTOS LTDA | D97: 32.040.626/0001-18 | E97: PR | F97: Manu Ditzel | K97: LEAD | M97: =IF(OR(J97<=0,J97=""),"","Recompra") | N97: =IFERROR(IF(Tabela1[[#This Row],[Nome fantasia]]="","",_xlfn.XLOOKUP($C97,Log!D:D,Log!B:B,,,-1)),"") -> 45937 | O97: =IFERROR(_xlfn.XLOOKUP($C97,Log!D:D,Log!W:W,,,-1),"") -> EM ATENDIMENTO | P97: =IFERROR(_xlfn.XLOOKUP($C97,Log!D:D,Log!Y:Y,,,-1),"") -> CLIENTES BASE SAP | R97: =IFERROR(IF(Tabela1[[#This Row],[Nome fantasia]]="","",_xlfn.XLOOKUP($C97,Log!D:D,Log!X:X,,,-1)),"") -> 45939
C98: ESTAR BEM PRODUTOS NATURAIS LTDA - ME | D98: 35.860.012/0001-70 | E98: PR | F98: Manu Ditzel | K98: LEAD | M98: =IF(OR(J98<=0,J98=""),"","Recompra") | N98: =IFERROR(IF(Tabela1[[#This Row],[Nome fantasia]]="","",_xlfn.XLOOKUP($C98,Log!D:D,Log!B:B,,,-1)),"") -> 45937 | O98: =IFERROR(_xlfn.XLOOKUP($C98,Log!D:D,Log!W:W,,,-1),"") -> EM ATENDIMENTO | P98: =IFERROR(_xlfn.XLOOKUP($C98,Log!D:D,Log!Y:Y,,,-1),"") -> CLIENTES BASE SAP | R98: =IFERROR(IF(Tabela1[[#This Row],[Nome fantasia]]="","",_xlfn.XLOOKUP($C98,Log!D:D,Log!X:X,,,-1)),"") -> 45939
C99: NUTRI LINDA LTDA - ME | D99: 13.226.373/0001-27 | E99: PR | F99: Manu Ditzel | K99: LEAD | M99: =IF(OR(J99<=0,J99=""),"","Recompra") | N99: =IFERROR(IF(Tabela1[[#This Row],[Nome fantasia]]="","",_xlfn.XLOOKUP($C99,Log!D:D,Log!B:B,,,-1)),"") -> 45937 | O99: =IFERROR(_xlfn.XLOOKUP($C99,Log!D:D,Log!W:W,,,-1),"") -> EM ATENDIMENTO | P99: =IFERROR(_xlfn.XLOOKUP($C99,Log!D:D,Log!Y:Y,,,-1),"") -> CLIENTES BASE SAP | R99: =IFERROR(IF(Tabela1[[#This Row],[Nome fantasia]]="","",_xlfn.XLOOKUP($C99,Log!D:D,Log!X:X,,,-1)),"") -> 45939
C100: EMPORIUM SAUDE PLENA LTDA - ME | D100: 35.622.295/0001-12 | E100: PR | F100: Manu Ditzel | K100: LEAD | M100: =IF(OR(J100<=0,J100=""),"","Recompra") | N100: =IFERROR(IF(Tabela1[[#This Row],[Nome fantasia]]="","",_xlfn.XLOOKUP($C100,Log!D:D,Log!B:B,,,-1)),"") -> 45937 | O100: =IFERROR(_xlfn.XLOOKUP($C100,Log!D:D,Log!W:W,,,-1),"") -> EM ATENDIMENTO | P100: =IFERROR(_xlfn.XLOOKUP($C100,Log!D:D,Log!Y:Y,,,-1),"") -> CLIENTES BASE SAP | R100: =IFERROR(IF(Tabela1[[#This Row],[Nome fantasia]]="","",_xlfn.XLOOKUP($C100,Log!D:D,Log!X:X,,,-1)),"") -> 45939
C101: E-labore | D101: 13.495.805/0001-03 | E101: SC | F101: Manu Ditzel | G101: 08/08/2025 | H101: 697.63 | I101: 60 | J101: 33.3333 | K101: ATIVO | M101: =IF(OR(J101<=0,J101=""),"","Recompra") -> Recompra | N101: =IFERROR(IF(Tabela1[[#This Row],[Nome fantasia]]="","",_xlfn.XLOOKUP($C101,Log!D:D,Log!B:B,,,-1)),"") -> 45940 | O101: =IFERROR(_xlfn.XLOOKUP($C101,Log!D:D,Log!W:W,,,-1),"") -> FOLLOW UP 15 | P101: =IFERROR(_xlfn.XLOOKUP($C101,Log!D:D,Log!Y:Y,,,-1),"") -> CLIENTE COM ESTOQUE MUITO ALTO | R101: =IFERROR(IF(Tabela1[[#This Row],[Nome fantasia]]="","",_xlfn.XLOOKUP($C101,Log!D:D,Log!X:X,,,-1)),"") -> 45961
...

Sheet Log
B2: DATA | D2: NOME FANTASIA | E2: CNPJ/CPF | F2: UF | G2: VENDEDOR DO ULTIMO PEDIDO | H2: DATA DE ULTIMO | I2: VALOR DE PEDIDO | J2: DIAS SEM COMPRAR | K2: CICLO MÉDIO DE COMPRA | L2: SITUAÇÃO | M2: Coluna1 | N2: STATUS | O2: ULTIMO CONTATO | P2: RESULTADO ATUAL | Q2: AÇÃO | R2: WHATSAPP | S2: LIGAÇÃO | T2: LIGAÇÃO ATENDIDA | U2: TIPO AÇÃO | V2: TIPO DO CONTATO | W2: RESULTADO | X2: FOLLOW-UP | Y2: AÇÃO | Z2: MERCOS ATUALIZADO | AA2: EXACTSALES ATUALIZADO | AB2: NOTA DO DIA / AÇÃO
B3: 45910 | D3: ALICE NO PAIS DOS GRAOS COMERCIO DE ALIMENTOS | E3: 41.626.544/0001-40 | F3: RS | G3: Larissa Padilha | H3: 10/09/2025 | I3: 2088.7 | J3: 1 | K3: 17.5 | L3: ATIVO | R3: SIM | S3: SIM | T3: NÃO | U3: ATIVO | V3: ATENDIMENTO CLIENTES ATIVOS | W3: VENDA | X3: =IFERROR(IF(W3="","",WORKDAY.INTL(B3,_xlfn.XLOOKUP(W3,Regras!$F$2:$F$11,Regras!$G$2:$G$11))),"") -> 45973 | Y3: RECOMPRA | Z3: SIM
B4: 45905 | D4: INTENSE CACAU | E4: 12.886.112/0001-70 | F4: PR | G4: Manu Ditzel | H4: 05/09/2025 | I4: 795.71 | J4: 6 | K4: 134 | L4: ATIVO | R4: SIM | S4: SIM | T4: SIM | U4: ATIVO | V4: ATENDIMENTO CLIENTES INATIVOS | W4: VENDA | X4: =IFERROR(IF(W4="","",WORKDAY.INTL(B4,_xlfn.XLOOKUP(W4,Regras!$F$2:$F$11,Regras!$G$2:$G$11))),"") -> 45968 | Y4: RECOMPRA | Z4: SIM
B5: 45905 | D5: ITALO ZILMER BEDERODE LTDA | E5: 53.754.257/0001-03 | F5: RS | G5: Manu Ditzel | H5: 05/09/2025 | I5: 1560.86 | J5: 6 | K5: * | L5: ATIVO | R5: SIM | S5: SIM | T5: SIM | U5: ATIVO | V5: PROSPECÇÃO NOVOS CLIENTES | W5: VENDA | X5: =IFERROR(IF(W5="","",WORKDAY.INTL(B5,_xlfn.XLOOKUP(W5,Regras!$F$2:$F$11,Regras!$G$2:$G$11))),"") -> 45968 | Y5: RECOMPRA | Z5: SIM
B6: 45905 | D6: SOLAR PORTO DE GALINHAS | E6: 08.895.369/0001-11 | F6: PE | G6: Manu Ditzel | H6: 05/09/2025 | I6: 5970 | J6: 6 | K6: 33.5 | L6: ATIVO | R6: SIM | S6: SIM | T6: NÃO | U6: ATIVO | V6: ATENDIMENTO CLIENTES ATIVOS | W6: VENDA | X6: =IFERROR(IF(W6="","",WORKDAY.INTL(B6,_xlfn.XLOOKUP(W6,Regras!$F$2:$F$11,Regras!$G$2:$G$11))),"") -> 45968 | Y6: RECOMPRA | Z6: SIM
B7: 45904 | D7: 50.342.650 PRISCILA LILIANE ROSSETO | E7: 50.342.650/0001-93 | F7: SP | G7: Manu Ditzel | H7: 04/09/2025 | I7: 769.47 | J7: 7 | K7: 30 | L7: ATIVO | R7: SIM | S7: SIM | T7: SIM | U7: ATIVO | V7: ATENDIMENTO CLIENTES ATIVOS | W7: VENDA | X7: =IFERROR(IF(W7="","",WORKDAY.INTL(B7,_xlfn.XLOOKUP(W7,Regras!$F$2:$F$11,Regras!$G$2:$G$11))),"") -> 45967 | Y7: RECOMPRA | Z7: SIM
B8: 45904 | D8: A CEREALISSIMA | E8: 15.265.760/0001-06 | F8: GO | G8: Central - Daiane | H8: 04/09/2025 | I8: 5983.46 | J8: 7 | K8: 20 | L8: ATIVO | R8: SIM | S8: SIM | T8: SIM | U8: ATIVO | V8: ATENDIMENTO CLIENTES ATIVOS | W8: VENDA | X8: =IFERROR(IF(W8="","",WORKDAY.INTL(B8,_xlfn.XLOOKUP(W8,Regras!$F$2:$F$11,Regras!$G$2:$G$11))),"") -> 45967 | Y8: RECOMPRA | Z8: SIM
B9: 45904 | D9: ARMAZÉM ESTIVA | E9: 38.614.942/0001-32 | F9: RJ | G9: Manu Ditzel | H9: 04/09/2025 | I9: 2873.11 | J9: 7 | K9: 90 | L9: ATIVO | R9: SIM | S9: SIM | T9: SIM | U9: ATIVO | V9: ATENDIMENTO CLIENTES ATIVOS | W9: VENDA | X9: =IFERROR(IF(W9="","",WORKDAY.INTL(B9,_xlfn.XLOOKUP(W9,Regras!$F$2:$F$11,Regras!$G$2:$G$11))),"") -> 45967 | Y9: RECOMPRA | Z9: SIM
B10: 45904 | D10: BIO MUNDO GURUPI | E10: 55.861.609/0001-47 | F10: TO | G10: Central - Daiane | H10: 04/09/2025 | I10: 675.96 | J10: 7 | K10: * | L10: ATIVO | R10: SIM | S10: SIM | T10: SIM | U10: ATIVO | V10: PROSPECÇÃO NOVOS CLIENTES | W10: VENDA | X10: =IFERROR(IF(W10="","",WORKDAY.INTL(B10,_xlfn.XLOOKUP(W10,Regras!$F$2:$F$11,Regras!$G$2:$G$11))),"") -> 45967 | Y10: RECOMPRA | Z10: SIM
B11: 45904 | D11: LAURA ISABEL RICARDO OCHOA | E11: 52.655.585/0001-81 | F11: BA | G11: Larissa Padilha | H11: 04/09/2025 | I11: 704.66 | J11: 7 | K11: * | L11: ATIVO | R11: SIM | S11: SIM | T11: NÃO | U11: ATIVO | V11: PROSPECÇÃO NOVOS CLIENTES | W11: VENDA | X11: =IFERROR(IF(W11="","",WORKDAY.INTL(B11,_xlfn.XLOOKUP(W11,Regras!$F$2:$F$11,Regras!$G$2:$G$11))),"") -> 45967 | Y11: RECOMPRA | Z11: SIM
B12: 45904 | D12: MINHA QUITANDINHA - AGUA VERDE - BLUMENAU | E12: 54.729.143/0001-68 | F12: SC | G12: Central - Daiane | H12: 04/09/2025 | I12: 775.04 | J12: 7 | K12: * | L12: ATIVO | R12: SIM | S12: SIM | T12: NÃO | U12: ATIVO | V12: PROSPECÇÃO NOVOS CLIENTES | W12: VENDA | X12: =IFERROR(IF(W12="","",WORKDAY.INTL(B12,_xlfn.XLOOKUP(W12,Regras!$F$2:$F$11,Regras!$G$2:$G$11))),"") -> 45967 | Y12: RECOMPRA | Z12: SIM
B13: 45904 | D13: PUDIMZERA | E13: 22.180.402/0001-58 | F13: SP | G13: Manu Ditzel | H13: 04/09/2025 | I13: 397.4 | J13: 7 | K13: 10.5 | L13: ATIVO | R13: SIM | S13: SIM | T13: NÃO | U13: ATIVO | V13: ATENDIMENTO CLIENTES ATIVOS | W13: VENDA | X13: =IFERROR(IF(W13="","",WORKDAY.INTL(B13,_xlfn.XLOOKUP(W13,Regras!$F$2:$F$11,Regras!$G$2:$G$11))),"") -> 45967 | Y13: RECOMPRA | Z13: SIM
B14: 45903 | D14: NATU & FIT | E14: 28.088.475/0001-09 | F14: ES | G14: Helder Brunkow | H14: 03/09/2025 | I14: 1572.57 | J14: 8 | K14: 53.5 | L14: ATIVO | R14: SIM | S14: SIM | T14: NÃO | U14: RECEPTIVO | V14: ATENDIMENTO CLIENTES ATIVOS | W14: VENDA | X14: =IFERROR(IF(W14="","",WORKDAY.INTL(B14,_xlfn.XLOOKUP(W14,Regras!$F$2:$F$11,Regras!$G$2:$G$11))),"") -> 45966 | Y14: RECOMPRA | Z14: SIM
B15: 45903 | D15: REDE NOVO TEMPO DE COMUNICACAO | E15: 01.385.423/0001-30 | F15: SP | G15: Manu Ditzel | H15: 03/09/2025 | I15: 1873.36 | J15: 8 | K15: 22 | L15: ATIVO | R15: SIM | S15: SIM | T15: NÃO | U15: ATIVO | V15: ATENDIMENTO CLIENTES ATIVOS | W15: VENDA | X15: =IFERROR(IF(W15="","",WORKDAY.INTL(B15,_xlfn.XLOOKUP(W15,Regras!$F$2:$F$11,Regras!$G$2:$G$11))),"") -> 45966 | Y15: RECOMPRA | Z15: SIM
B16: 45902 | D16: EMPORIO TRIBO VERDE | E16: 48.391.847/0001-70 | F16: GO | G16: Manu Ditzel | H16: 02/09/2025 | I16: 2021.53 | J16: 9 | K16: * | L16: ATIVO | R16: SIM | S16: SIM | T16: SIM | U16: ATIVO | V16: PROSPECÇÃO NOVOS CLIENTES | W16: VENDA | X16: =IFERROR(IF(W16="","",WORKDAY.INTL(B16,_xlfn.XLOOKUP(W16,Regras!$F$2:$F$11,Regras!$G$2:$G$11))),"") -> 45965 | Y16: RECOMPRA | Z16: SIM
B17: 45902 | D17: HERTZ NUTRITION | E17: 17.039.758/0001-36 | F17: RS | G17: Manu Ditzel | H17: 02/09/2025 | I17: 1387.75 | J17: 9 | K17: * | L17: ATIVO | R17: SIM | S17: SIM | T17: NÃO | U17: ATIVO | V17: PROSPECÇÃO NOVOS CLIENTES | W17: VENDA | X17: =IFERROR(IF(W17="","",WORKDAY.INTL(B17,_xlfn.XLOOKUP(W17,Regras!$F$2:$F$11,Regras!$G$2:$G$11))),"") -> 45965 | Y17: RECOMPRA | Z17: SIM
B18: 45902 | D18: KUWADA COMPANIA LTDA | E18: 18.997.672/0001-89 | F18: MT | G18: Manu Ditzel | H18: 02/09/2025 | I18: 1216.68 | J18: 9 | K18: 61 | L18: ATIVO | R18: SIM | S18: SIM | T18: SIM | U18: ATIVO | V18: ATENDIMENTO CLIENTES ATIVOS | W18: VENDA | X18: =IFERROR(IF(W18="","",WORKDAY.INTL(B18,_xlfn.XLOOKUP(W18,Regras!$F$2:$F$11,Regras!$G$2:$G$11))),"") -> 45965 | Y18: RECOMPRA | Z18: SIM
B19: 45901 | D19: PROSAUDE - NOVO PROGRESSO | E19: 22.081.589/0001-32 | F19: PA | G19: Larissa Padilha | H19: 01/09/2025 | I19: 858.48 | J19: 10 | K19: 153 | L19: ATIVO | R19: SIM | S19: SIM | T19: SIM | U19: ATIVO | V19: ATENDIMENTO CLIENTES INATIVOS | W19: VENDA | X19: =IFERROR(IF(W19="","",WORKDAY.INTL(B19,_xlfn.XLOOKUP(W19,Regras!$F$2:$F$11,Regras!$G$2:$G$11))),"") -> 45964 | Y19: RECOMPRA | Z19: SIM
B20: 45898 | D20: KLOSTERMANN NUTRICAO | E20: 58.072.623/0001-50 | F20: SC | G20: Larissa Padilha | H20: 29/08/2025 | I20: 906.11 | J20: 13 | K20: 56.5 | L20: ATIVO | R20: SIM | S20: SIM | T20: SIM | U20: ATIVO | V20: ATENDIMENTO CLIENTES INATIVOS | W20: VENDA | X20: =IFERROR(IF(W20="","",WORKDAY.INTL(B20,_xlfn.XLOOKUP(W20,Regras!$F$2:$F$11,Regras!$G$2:$G$11))),"") -> 45961 | Y20: RECOMPRA | Z20: SIM
B21: 45898 | D21: MERCADO FERREIRA | E21: 14.419.497/0001-91 | F21: SC | G21: Manu Ditzel | H21: 29/08/2025 | I21: 1267.11 | J21: 13 | K21: 58 | L21: ATIVO | R21: SIM | S21: SIM | T21: SIM | U21: ATIVO | V21: ATENDIMENTO CLIENTES INATIVOS | W21: VENDA | X21: =IFERROR(IF(W21="","",WORKDAY.INTL(B21,_xlfn.XLOOKUP(W21,Regras!$F$2:$F$11,Regras!$G$2:$G$11))),"") -> 45961 | Y21: RECOMPRA | Z21: SIM
B22: 45898 | D22: TEMPEROS & MEL | E22: 22.105.950/0001-13 | F22: DF | G22: Manu Ditzel | H22: 29/08/2025 | I22: 1715.21 | J22: 13 | K22: 88 | L22: ATIVO | R22: SIM | S22: SIM | T22: SIM | U22: ATIVO | V22: ATENDIMENTO CLIENTES ATIVOS | W22: VENDA | X22: =IFERROR(IF(W22="","",WORKDAY.INTL(B22,_xlfn.XLOOKUP(W22,Regras!$F$2:$F$11,Regras!$G$2:$G$11))),"") -> 45961 | Y22: RECOMPRA | Z22: SIM
B23: 45898 | D23: VIDA LEVE - CHAPADAO | E23: 61.327.765/0001-25 | F23: GO | G23: Manu Ditzel | H23: 29/08/2025 | I23: 3767.53 | J23: 13 | K23: * | L23: ATIVO | R23: SIM | S23: SIM | T23: NÃO | U23: ATIVO | V23: PROSPECÇÃO NOVOS CLIENTES | W23: VENDA | X23: =IFERROR(IF(W23="","",WORKDAY.INTL(B23,_xlfn.XLOOKUP(W23,Regras!$F$2:$F$11,Regras!$G$2:$G$11))),"") -> 45961 | Y23: RECOMPRA | Z23: SIM
B24: 45898 | D24: VIDA LEVE CANOAS | E24: 60.821.190/0001-30 | F24: RS | G24: Manu Ditzel | H24: 29/08/2025 | I24: 2969.26 | J24: 13 | K24: * | L24: ATIVO | R24: SIM | S24: SIM | T24: NÃO | U24: ATIVO | V24: PROSPECÇÃO NOVOS CLIENTES | W24: VENDA | X24: =IFERROR(IF(W24="","",WORKDAY.INTL(B24,_xlfn.XLOOKUP(W24,Regras!$F$2:$F$11,Regras!$G$2:$G$11))),"") -> 45961 | Y24: RECOMPRA | Z24: SIM
B25: 45897 | D25: DESTAQUE SHAPE | E25: 59.794.577/0001-65 | F25: SC | G25: Larissa Padilha | H25: 28/08/2025 | I25: 876.13 | J25: 14 | K25: 63 | L25: ATIVO | R25: SIM | S25: SIM | T25: NÃO | U25: ATIVO | V25: ATENDIMENTO CLIENTES INATIVOS | W25: VENDA | X25: =IFERROR(IF(W25="","",WORKDAY.INTL(B25,_xlfn.XLOOKUP(W25,Regras!$F$2:$F$11,Regras!$G$2:$G$11))),"") -> 45960 | Y25: RECOMPRA | Z25: SIM
B26: 45897 | D26: EMPORIO GAMBOA - ESPECIARIAS E PRODUTOS NATURAIS | E26: 23.143.632/0001-00 | F26: PE | G26: Larissa Padilha | H26: 28/08/2025 | I26: 1570.64 | J26: 14 | K26: * | L26: ATIVO | R26: SIM | S26: SIM | T26: NÃO | U26: RECEPTIVO | V26: PROSPECÇÃO NOVOS CLIENTES | W26: VENDA | X26: =IFERROR(IF(W26="","",WORKDAY.INTL(B26,_xlfn.XLOOKUP(W26,Regras!$F$2:$F$11,Regras!$G$2:$G$11))),"") -> 45960 | Y26: RECOMPRA | Z26: SIM
B27: 45897 | D27: NATURALIS PRODUTOS NATURAIS | E27: 31.545.180/0001-10 | F27: SC | G27: Manu Ditzel | H27: 28/08/2025 | I27: 5094 | J27: 14 | K27: 62.5 | L27: ATIVO | R27: SIM | S27: SIM | T27: NÃO | U27: ATIVO | V27: ATENDIMENTO CLIENTES INATIVOS | W27: VENDA | X27: =IFERROR(IF(W27="","",WORKDAY.INTL(B27,_xlfn.XLOOKUP(W27,Regras!$F$2:$F$11,Regras!$G$2:$G$11))),"") -> 45960 | Y27: RECOMPRA | Z27: SIM
B28: 45897 | D28: NATUREZA EM KILO | E28: 00.211.115/0002-06 | F28: PR | G28: Manu Ditzel | H28: 28/08/2025 | I28: 904.49 | J28: 14 | K28: * | L28: ATIVO | R28: SIM | S28: SIM | T28: SIM | U28: ATIVO | V28: PROSPECÇÃO NOVOS CLIENTES | W28: VENDA | X28: =IFERROR(IF(W28="","",WORKDAY.INTL(B28,_xlfn.XLOOKUP(W28,Regras!$F$2:$F$11,Regras!$G$2:$G$11))),"") -> 45960 | Y28: PRIMEIRO PEDIDO | Z28: SIM
B29: 45897 | D29: SHOPPING NATURAL | E29: 15.428.647/0001-96 | F29: MT | G29: Manu Ditzel | H29: 28/08/2025 | I29: 998.4 | J29: 14 | K29: 60.5 | L29: ATIVO | R29: SIM | S29: SIM | T29: NÃO | U29: ATIVO | V29: ATENDIMENTO CLIENTES INATIVOS | W29: VENDA | X29: =IFERROR(IF(W29="","",WORKDAY.INTL(B29,_xlfn.XLOOKUP(W29,Regras!$F$2:$F$11,Regras!$G$2:$G$11))),"") -> 45960 | Y29: RECOMPRA | Z29: SIM
B30: 45897 | D30: TROPICAL SUPERMERCADOS | E30: 23.014.826/0001-05 | F30: MT | G30: Manu Ditzel | H30: 28/08/2025 | I30: 8406.63 | J30: 14 | K30: 33 | L30: ATIVO | R30: SIM | S30: SIM | T30: SIM | U30: ATIVO | V30: ATENDIMENTO CLIENTES INATIVOS | W30: VENDA | X30: =IFERROR(IF(W30="","",WORKDAY.INTL(B30,_xlfn.XLOOKUP(W30,Regras!$F$2:$F$11,Regras!$G$2:$G$11))),"") -> 45960 | Y30: RECOMPRA | Z30: SIM
B31: 45897 | D31: SHOPPING NATURAL | E31: 15.428.647/0001-96 | F31: MT | G31: Manu Ditzel | H31: 28/08/2025 | I31: 998.4 | J31: 14 | K31: 60.5 | L31: ATIVO | R31: SIM | S31: NÃO | T31: NÃO | U31: ATIVO | V31: PÓS VENDA / RELACIONAMENTO | W31: FOLLOW UP | X31: 45919 | Y31: ENTREGA | Z31: SIM | AB31: QUESTIONANDO SE CHEGOU TUDO CERTO
B32: 45897 | D32: NATUREZA EM KILO | E32: 00.211.115/0002-06 | F32: PR | G32: Manu Ditzel | H32: 28/08/2025 | I32: 904.49 | J32: 14 | K32: * | L32: ATIVO | R32: SIM | S32: NÃO | T32: NÃO | U32: RECEPTIVO | V32: ATENDIMENTO CLIENTES ATIVOS | W32: VENDA | Y32: RECOMPRA | Z32: SIM | AB32: RECOMPRA/ CLIENTE DE VISITA
B33: 45896 | D33: CASA HIRATA - SUPERMERCADO | E33: 55.615.538/0002-83 | F33: SP | G33: Manu Ditzel | H33: 27/08/2025 | I33: 2571.82 | J33: 15 | K33: 91 | L33: ATIVO | R33: SIM | S33: SIM | T33: SIM | U33: RECEPTIVO | V33: ATENDIMENTO CLIENTES INATIVOS | W33: VENDA | X33: =IFERROR(IF(W33="","",WORKDAY.INTL(B33,_xlfn.XLOOKUP(W33,Regras!$F$2:$F$11,Regras!$G$2:$G$11))),"") -> 45959 | Y33: RECOMPRA | Z33: SIM
B34: 45896 | D34: CONTORNO ARMAZEM | E34: 29.466.137/0001-18 | F34: SP | G34: Manu Ditzel | H34: 27/08/2025 | I34: 901.53 | J34: 15 | K34: * | L34: ATIVO | R34: SIM | S34: SIM | T34: SIM | U34: ATIVO | V34: PROSPECÇÃO NOVOS CLIENTES | W34: VENDA | X34: =IFERROR(IF(W34="","",WORKDAY.INTL(B34,_xlfn.XLOOKUP(W34,Regras!$F$2:$F$11,Regras!$G$2:$G$11))),"") -> 45959 | Y34: RECOMPRA | Z34: SIM
B35: 45896 | D35: MINI MERCADO FAMILIA | E35: 35.743.795/0001-02 | F35: SC | G35: Manu Ditzel | H35: 27/08/2025 | I35: 2161.62 | J35: 15 | K35: * | L35: ATIVO | R35: SIM | S35: SIM | T35: NÃO | U35: RECEPTIVO | V35: PROSPECÇÃO NOVOS CLIENTES | W35: VENDA | X35: =IFERROR(IF(W35="","",WORKDAY.INTL(B35,_xlfn.XLOOKUP(W35,Regras!$F$2:$F$11,Regras!$G$2:$G$11))),"") -> 45959 | Y35: RECOMPRA | Z35: SIM
B36: 45896 | D36: NATHALIA DE JESUS SILVA COSTA LTDA | E36: 59.244.884/0001-72 | F36: SP | G36: Manu Ditzel | H36: 27/08/2025 | I36: 650.3 | J36: 15 | K36: * | L36: ATIVO | R36: SIM | S36: NÃO | T36: NÃO | U36: ATIVO | V36: PROSPECÇÃO NOVOS CLIENTES | W36: VENDA | X36: =IFERROR(IF(W36="","",WORKDAY.INTL(B36,_xlfn.XLOOKUP(W36,Regras!$F$2:$F$11,Regras!$G$2:$G$11))),"") -> 45959 | Y36: PRIMEIRA COMPRA | Z36: SIM
B37: 45896 | D37: SAFITA DOCES | E37: 43.023.380/0001-92 | F37: RJ | G37: Manu Ditzel | H37: 27/08/2025 | I37: 1490.4 | J37: 15 | K37: 72 | L37: ATIVO | R37: SIM | S37: SIM | T37: SIM | U37: RECEPTIVO | V37: ATENDIMENTO CLIENTES INATIVOS | W37: VENDA | X37: =IFERROR(IF(W37="","",WORKDAY.INTL(B37,_xlfn.XLOOKUP(W37,Regras!$F$2:$F$11,Regras!$G$2:$G$11))),"") -> 45959 | Y37: RECOMPRA | Z37: SIM
B38: 45896 | D38: SUPERMERCADO MERCOCENTRO | E38: 05.382.867/0001-72 | F38: SC | G38: Manu Ditzel | H38: 27/08/2025 | I38: 1148.79 | J38: 15 | K38: 21.5 | L38: ATIVO | R38: SIM | S38: SIM | T38: SIM | U38: RECEPTIVO | V38: ATENDIMENTO CLIENTES ATIVOS | W38: VENDA | X38: =IFERROR(IF(W38="","",WORKDAY.INTL(B38,_xlfn.XLOOKUP(W38,Regras!$F$2:$F$11,Regras!$G$2:$G$11))),"") -> 45959 | Y38: RECOMPRA | Z38: SIM
B39: 45896 | D39: WOLFI MACHINES | E39: 61.932.319/0001-40 | F39: RS | G39: Manu Ditzel | H39: 27/08/2025 | I39: 1199 | J39: 15 | K39: * | L39: ATIVO | R39: SIM | S39: SIM | T39: NÃO | U39: RECEPTIVO | V39: PROSPECÇÃO NOVOS CLIENTES | W39: VENDA | X39: =IFERROR(IF(W39="","",WORKDAY.INTL(B39,_xlfn.XLOOKUP(W39,Regras!$F$2:$F$11,Regras!$G$2:$G$11))),"") -> 45959 | Y39: RECOMPRA | Z39: SIM
B40: 45896 | D40: CASA HIRATA - SUPERMERCADO | E40: 55.615.538/0002-83 | F40: SP | G40: Manu Ditzel | H40: 27/08/2025 | I40: 2571.82 | J40: 15 | K40: 91 | L40: ATIVO | R40: SIM | S40: NÃO | T40: NÃO | U40: ATIVO | V40: PÓS VENDA / RELACIONAMENTO | W40: FOLLOW UP | X40: 45919 | Y40: RECOMPRA | Z40: SIM | AB40: VERIFICAR SE ESTA PRECISANDO DE PRODUTOS
B41: 45896 | D41: SAFITA DOCES | E41: 43.023.380/0001-92 | F41: RJ | G41: Manu Ditzel | H41: 27/08/2025 | I41: 1490.4 | J41: 15 | K41: 72 | L41: ATIVO | R41: SIM | S41: NÃO | T41: NÃO | U41: ATIVO | V41: PÓS VENDA / RELACIONAMENTO | W41: FOLLOW UP | X41: 45919 | Y41: ENTREGA | Z41: SIM | AB41: VERIFICANDO SE CHEGOU TUDO CERTO
B42: 45896 | D42: NATHALIA DE JESUS SILVA COSTA LTDA | E42: 59.244.884/0001-72 | F42: SP | G42: Manu Ditzel | H42: 27/08/2025 | I42: 650.3 | J42: 15 | K42: * | L42: ATIVO | R42: SIM | S42: SIM | T42: NÃO | U42: ATIVO | V42: PROSPECÇÃO NOVOS CLIENTES | W42: EM ATENDIMENTO | X42: 45894 | Y42: LIGAÇÃO | Z42: SIM | AB42: CLIENTE VEIO DO SITE, TEM INTERESSE NOS PRODUTOS A GRANEL PARA MATERIA PRIMA
B43: 45926 | D43: CASA HIRATA - SUPERMERCADO | E43: 55.615.538/0002-83 | F43: SP | G43: Manu Ditzel | H43: 27/08/2025 | I43: 2571.82 | J43: 15 | K43: 91 | L43: ATIVO | R43: SIM | S43: NÃO | T43: NÃO | U43: ATIVO | V43: ATENDIMENTO CLIENTES ATIVOS | W43: EM ATENDIMENTO | X43: =IFERROR(IF(W43="","",WORKDAY.INTL(B43,_xlfn.XLOOKUP(W43,Regras!$F$2:$F$11,Regras!$G$2:$G$11))),"") -> 45930 | Y43: FEITO CONTATO PARA REPOSIÇÃO | Z43: SIM | AB43: POSSIVEL RECOMPRA
B44: 45926 | D44: SAFITA DOCES | E44: 43.023.380/0001-92 | F44: RJ | G44: Manu Ditzel | H44: 27/08/2025 | I44: 1490.4 | J44: 15 | K44: 72 | L44: ATIVO | R44: NÃO | S44: NÃO | T44: NÃO | U44: ATIVO | V44: ATENDIMENTO CLIENTES ATIVOS | W44: FOLLOW UP 15 | X44: =IFERROR(IF(W44="","",WORKDAY.INTL(B44,_xlfn.XLOOKUP(W44,Regras!$F$2:$F$11,Regras!$G$2:$G$11))),"") -> 45947 | Y44: CLIENTE DE TAMARAS | Z44: SIM | AB44: CLIENTE SO COMPRA TAMARAS, AGUARDANDO CHEGAR CARGA NOVA
B45: 45930 | D45: CASA HIRATA - SUPERMERCADO | E45: 55.615.538/0002-83 | F45: SP | G45: Manu Ditzel | H45: 27/08/2025 | I45: 2571.82 | J45: 15 | K45: 91 | L45: ATIVO | R45: SIM | S45: NÃO | T45: NÃO | U45: ATIVO | V45: ATENDIMENTO CLIENTES ATIVOS | W45: EM ATENDIMENTO | X45: =IFERROR(IF(W45="","",WORKDAY.INTL(B45,_xlfn.XLOOKUP(W45,Regras!$F$2:$F$11,Regras!$G$2:$G$11))),"") -> 45932 | Y45: POSSIVEL RECOMPRA | Z45: SIM | AB45: FEITO CONTATO PARA RECOMPRA
B46: 45932 | D46: CASA HIRATA - SUPERMERCADO | E46: 55.615.538/0002-83 | F46: SP | G46: Manu Ditzel | H46: 27/08/2025 | I46: 2571.82 | J46: 15 | K46: 91 | L46: ATIVO | R46: SIM | S46: SIM | T46: NÃO | U46: ATIVO | V46: ATENDIMENTO CLIENTES ATIVOS | W46: FOLLOW UP 7 | X46: =IFERROR(IF(W46="","",WORKDAY.INTL(B46,_xlfn.XLOOKUP(W46,Regras!$F$2:$F$11,Regras!$G$2:$G$11))),"") -> 45943 | Y46: ENTRANDO EM CONTATO PARA POSSIVEL RECOMPRA | Z46: SIM | AB46: ENTRANDO EM CONTATO PARA POSSIVEL RECOMPRA
B47: 45895 | D47: FIT LAGES COMERCIO DE SUPLEMENTOS E PRODUTOS NATURAIS | E47: 52.607.036/0001-31 | F47: SC | G47: Larissa Padilha | H47: 26/08/2025 | I47: 1990.59 | J47: 16 | K47: * | L47: ATIVO | R47: SIM | S47: SIM | T47: NÃO | U47: RECEPTIVO | V47: PROSPECÇÃO NOVOS CLIENTES | W47: VENDA | X47: =IFERROR(IF(W47="","",WORKDAY.INTL(B47,_xlfn.XLOOKUP(W47,Regras!$F$2:$F$11,Regras!$G$2:$G$11))),"") -> 45958 | Y47: RECOMPRA | Z47: SIM
B48: 45895 | D48: FIT NUTRICAO | E48: 57.425.671/0001-11 | F48: RS | G48: Larissa Padilha | H48: 26/08/2025 | I48: 924.68 | J48: 16 | K48: * | L48: ATIVO | R48: SIM | S48: SIM | T48: SIM | U48: ATIVO | V48: PROSPECÇÃO NOVOS CLIENTES | W48: VENDA | X48: =IFERROR(IF(W48="","",WORKDAY.INTL(B48,_xlfn.XLOOKUP(W48,Regras!$F$2:$F$11,Regras!$G$2:$G$11))),"") -> 45958 | Y48: RECOMPRA | Z48: SIM
B49: 45895 | D49: FIT SJB | E49: 43.732.530/0001-37 | F49: SC | G49: Larissa Padilha | H49: 26/08/2025 | I49: 1566.56 | J49: 16 | K49: 49.5 | L49: ATIVO | R49: SIM | S49: SIM | T49: NÃO | U49: RECEPTIVO | V49: ATENDIMENTO CLIENTES INATIVOS | W49: VENDA | X49: =IFERROR(IF(W49="","",WORKDAY.INTL(B49,_xlfn.XLOOKUP(W49,Regras!$F$2:$F$11,Regras!$G$2:$G$11))),"") -> 45958 | Y49: RECOMPRA | Z49: SIM
B50: 45895 | D50: FITLAND BLUMENAU AGUA VERDE | E50: 49.982.339/0001-20 | F50: SC | G50: Larissa Padilha | H50: 26/08/2025 | I50: 4220.08 | J50: 16 | K50: 25.3333 | L50: ATIVO | R50: SIM | S50: SIM | T50: SIM | U50: RECEPTIVO | V50: ATENDIMENTO CLIENTES ATIVOS | W50: VENDA | X50: =IFERROR(IF(W50="","",WORKDAY.INTL(B50,_xlfn.XLOOKUP(W50,Regras!$F$2:$F$11,Regras!$G$2:$G$11))),"") -> 45958 | Y50: RECOMPRA | Z50: SIM
B51: 45895 | D51: NATERRA SLZ | E51: 09.088.606/0001-03 | F51: MA | G51: Manu Ditzel | H51: 26/08/2025 | I51: 2596.83 | J51: 16 | K51: 60 | L51: ATIVO | R51: SIM | S51: SIM | T51: SIM | U51: ATIVO | V51: ATENDIMENTO CLIENTES INATIVOS | W51: VENDA | X51: =IFERROR(IF(W51="","",WORKDAY.INTL(B51,_xlfn.XLOOKUP(W51,Regras!$F$2:$F$11,Regras!$G$2:$G$11))),"") -> 45958 | Y51: RECOMPRA | Z51: SIM
B52: 45895 | D52: POWER SUPLEMENTOS | E52: 48.606.158/0001-36 | F52: PA | G52: Manu Ditzel | H52: 26/08/2025 | I52: 1160.85 | J52: 16 | K52: * | L52: ATIVO | R52: SIM | S52: SIM | T52: SIM | U52: ATIVO | V52: PROSPECÇÃO NOVOS CLIENTES | W52: VENDA | X52: =IFERROR(IF(W52="","",WORKDAY.INTL(B52,_xlfn.XLOOKUP(W52,Regras!$F$2:$F$11,Regras!$G$2:$G$11))),"") -> 45958 | Y52: RECOMPRA | Z52: SIM
B53: 45895 | D53: RAIZES E SABORES | E53: 35.031.254/0001-51 | F53: SP | G53: Manu Ditzel | H53: 26/08/2025 | I53: 936.23 | J53: 16 | K53: 21 | L53: ATIVO | R53: SIM | S53: SIM | T53: SIM | U53: ATIVO | V53: ATENDIMENTO CLIENTES ATIVOS | W53: VENDA | X53: =IFERROR(IF(W53="","",WORKDAY.INTL(B53,_xlfn.XLOOKUP(W53,Regras!$F$2:$F$11,Regras!$G$2:$G$11))),"") -> 45958 | Y53: RECOMPRA | Z53: SIM
B54: 45895 | D54: SUPERACAO & VIDA SAUDAVEL | E54: 34.060.666/0001-57 | F54: SP | G54: Manu Ditzel | H54: 26/08/2025 | I54: 1068.6 | J54: 16 | K54: 21 | L54: ATIVO | R54: SIM | S54: SIM | T54: NÃO | U54: ATIVO | V54: ATENDIMENTO CLIENTES ATIVOS | W54: VENDA | X54: =IFERROR(IF(W54="","",WORKDAY.INTL(B54,_xlfn.XLOOKUP(W54,Regras!$F$2:$F$11,Regras!$G$2:$G$11))),"") -> 45958 | Y54: RECOMPRA | Z54: SIM
B55: 45895 | D55: VIDA LEVE ESPECIARIAS | E55: 32.203.302/0001-53 | F55: BA | G55: Manu Ditzel | H55: 26/08/2025 | I55: 4119.1 | J55: 16 | K55: * | L55: ATIVO | R55: SIM | S55: SIM | T55: SIM | U55: ATIVO | V55: PROSPECÇÃO NOVOS CLIENTES | W55: VENDA | X55: =IFERROR(IF(W55="","",WORKDAY.INTL(B55,_xlfn.XLOOKUP(W55,Regras!$F$2:$F$11,Regras!$G$2:$G$11))),"") -> 45958 | Y55: RECOMPRA | Z55: SIM
B56: 45895 | D56: RAIZES E SABORES | E56: 35.031.254/0001-51 | F56: SP | G56: Manu Ditzel | H56: 26/08/2025 | I56: 936.23 | J56: 16 | K56: 21 | L56: ATIVO | R56: SIM | S56: NÃO | T56: NÃO | U56: ATIVO | V56: PÓS VENDA / RELACIONAMENTO | W56: FOLLOW UP | X56: 45919 | Y56: ENTREGA | Z56: SIM | AB56: VERIFICANDO SE CHEGOU PEDIDO DA CLIENTE
B57: 45894 | D57: 40.185.487 ANTONIO JURANDI DA SILVA | E57: 40.185.487/0001-49 | F57: SP | G57: Manu Ditzel | H57: 25/08/2025 | I57: 812.27 | J57: 17 | K57: 73.5 | L57: ATIVO | R57: SIM | S57: SIM | T57: SIM | U57: ATIVO | V57: ATENDIMENTO CLIENTES INATIVOS | W57: VENDA | X57: =IFERROR(IF(W57="","",WORKDAY.INTL(B57,_xlfn.XLOOKUP(W57,Regras!$F$2:$F$11,Regras!$G$2:$G$11))),"") -> 45957 | Y57: RECOMPRA | Z57: SIM
B58: 45894 | D58: BIO SC COMERCIO DE ALIMENTOS | E58: 46.945.954/0001-78 | F58: SC | G58: Larissa Padilha | H58: 25/08/2025 | I58: 1377.68 | J58: 17 | K58: 61.5 | L58: ATIVO | R58: SIM | S58: SIM | T58: NÃO | U58: RECEPTIVO | V58: ATENDIMENTO CLIENTES INATIVOS | W58: VENDA | X58: =IFERROR(IF(W58="","",WORKDAY.INTL(B58,_xlfn.XLOOKUP(W58,Regras!$F$2:$F$11,Regras!$G$2:$G$11))),"") -> 45957 | Y58: RECOMPRA | Z58: SIM
B59: 45894 | D59: BISTROZINHO INFANTIL | E59: 52.575.072/0001-60 | F59: SP | G59: Manu Ditzel | H59: 25/08/2025 | I59: 658.02 | J59: 17 | K59: * | L59: ATIVO | R59: SIM | S59: SIM | T59: SIM | U59: ATIVO | V59: PROSPECÇÃO NOVOS CLIENTES | W59: VENDA | X59: =IFERROR(IF(W59="","",WORKDAY.INTL(B59,_xlfn.XLOOKUP(W59,Regras!$F$2:$F$11,Regras!$G$2:$G$11))),"") -> 45957 | Y59: RECOMPRA | Z59: SIM
B60: 45894 | D60: FIT & GRANEL | E60: 41.069.473/0001-22 | F60: MG | G60: Manu Ditzel | H60: 25/08/2025 | I60: 2426.28 | J60: 17 | K60: 29.6667 | L60: ATIVO | R60: SIM | S60: SIM | T60: NÃO | U60: ATIVO | V60: ATENDIMENTO CLIENTES ATIVOS | W60: VENDA | X60: =IFERROR(IF(W60="","",WORKDAY.INTL(B60,_xlfn.XLOOKUP(W60,Regras!$F$2:$F$11,Regras!$G$2:$G$11))),"") -> 45957 | Y60: RECOMPRA | Z60: SIM
B61: 45894 | D61: FRANQUIA FITLAND BLUMENAU | E61: 40.917.018/0001-77 | F61: SC | G61: Larissa Padilha | H61: 25/08/2025 | I61: 2176.64 | J61: 17 | K61: 25 | L61: ATIVO | R61: SIM | S61: SIM | T61: NÃO | U61: ATIVO | V61: ATENDIMENTO CLIENTES ATIVOS | W61: VENDA | X61: =IFERROR(IF(W61="","",WORKDAY.INTL(B61,_xlfn.XLOOKUP(W61,Regras!$F$2:$F$11,Regras!$G$2:$G$11))),"") -> 45957 | Y61: RECOMPRA | Z61: SIM
B62: 45894 | D62: FRANQUIA FITLAND POMERODE | E62: 55.717.635/0001-04 | F62: SC | G62: Larissa Padilha | H62: 25/08/2025 | I62: 2303.38 | J62: 17 | K62: 77 | L62: ATIVO | R62: SIM | S62: SIM | T62: NÃO | U62: RECEPTIVO | V62: ATENDIMENTO CLIENTES INATIVOS | W62: VENDA | X62: =IFERROR(IF(W62="","",WORKDAY.INTL(B62,_xlfn.XLOOKUP(W62,Regras!$F$2:$F$11,Regras!$G$2:$G$11))),"") -> 45957 | Y62: RECOMPRA | Z62: SIM
B63: 45894 | D63: MARILIA RAFAELA FERREIRA DA LUZ LTDA | E63: 61.746.555/0001-71 | F63: PR | G63: Manu Ditzel | H63: 25/08/2025 | I63: 689.46 | J63: 17 | K63: * | L63: ATIVO | R63: SIM | S63: SIM | T63: SIM | U63: ATIVO | V63: PROSPECÇÃO NOVOS CLIENTES | W63: VENDA | X63: =IFERROR(IF(W63="","",WORKDAY.INTL(B63,_xlfn.XLOOKUP(W63,Regras!$F$2:$F$11,Regras!$G$2:$G$11))),"") -> 45957 | Y63: RECOMPRA | Z63: SIM
B64: 45894 | D64: MERCADO KRAU'S | E64: 29.841.719/0001-37 | F64: MS | G64: Manu Ditzel | H64: 25/08/2025 | I64: 2363.33 | J64: 17 | K64: 144 | L64: ATIVO | R64: SIM | S64: SIM | T64: NÃO | U64: ATIVO | V64: ATENDIMENTO CLIENTES INATIVOS | W64: VENDA | X64: =IFERROR(IF(W64="","",WORKDAY.INTL(B64,_xlfn.XLOOKUP(W64,Regras!$F$2:$F$11,Regras!$G$2:$G$11))),"") -> 45957 | Y64: RECOMPRA | Z64: SIM
B65: 45894 | D65: MUNDO FITNESS | E65: 37.717.783/0001-39 | F65: MG | G65: Manu Ditzel | H65: 25/08/2025 | I65: 1556.38 | J65: 17 | K65: 82 | L65: ATIVO | R65: SIM | S65: SIM | T65: SIM | U65: ATIVO | V65: ATENDIMENTO CLIENTES INATIVOS | W65: VENDA | X65: =IFERROR(IF(W65="","",WORKDAY.INTL(B65,_xlfn.XLOOKUP(W65,Regras!$F$2:$F$11,Regras!$G$2:$G$11))),"") -> 45957 | Y65: RECOMPRA | Z65: SIM
B66: 45894 | D66: SACOLAO CURITIBA | E66: 04.846.161/0001-51 | F66: PR | G66: Manu Ditzel | H66: 25/08/2025 | I66: 665.76 | J66: 17 | K66: 26 | L66: ATIVO | R66: SIM | S66: SIM | T66: SIM | U66: ATIVO | V66: ATENDIMENTO CLIENTES ATIVOS | W66: VENDA | X66: =IFERROR(IF(W66="","",WORKDAY.INTL(B66,_xlfn.XLOOKUP(W66,Regras!$F$2:$F$11,Regras!$G$2:$G$11))),"") -> 45957 | Y66: RECOMPRA | Z66: SIM
B67: 45894 | D67: SONIA IOLANDA DUARTE | E67: 37.266.276/0001-26 | F67: RS | G67: Manu Ditzel | H67: 25/08/2025 | I67: 675.58 | J67: 17 | K67: 97 | L67: ATIVO | R67: SIM | S67: SIM | T67: NÃO | U67: ATIVO | V67: ATENDIMENTO CLIENTES INATIVOS | W67: VENDA | X67: =IFERROR(IF(W67="","",WORKDAY.INTL(B67,_xlfn.XLOOKUP(W67,Regras!$F$2:$F$11,Regras!$G$2:$G$11))),"") -> 45957 | Y67: RECOMPRA | Z67: SIM
B68: 45926 | D68: SACOLAO CURITIBA | E68: 04.846.161/0001-51 | F68: PR | G68: Manu Ditzel | H68: 25/08/2025 | I68: 665.76 | J68: 17 | K68: 26 | L68: ATIVO | R68: SIM | S68: SIM | T68: NÃO | U68: ATIVO | V68: ATENDIMENTO CLIENTES ATIVOS | W68: FOLLOW UP 15 | X68: =IFERROR(IF(W68="","",WORKDAY.INTL(B68,_xlfn.XLOOKUP(W68,Regras!$F$2:$F$11,Regras!$G$2:$G$11))),"") -> 45947 | Y68: FEITO CONTATO PARA REPOSIÇÃO | Z68: SIM | AB68: CLIENTE AINDA TEM PRODUTO
B69: 45926 | D69: MARILIA RAFAELA FERREIRA DA LUZ LTDA | E69: 61.746.555/0001-71 | F69: PR | G69: Manu Ditzel | H69: 25/08/2025 | I69: 689.46 | J69: 17 | K69: * | L69: ATIVO | R69: SIM | S69: SIM | T69: NÃO | U69: ATIVO | V69: ATENDIMENTO CLIENTES ATIVOS | W69: EM ATENDIMENTO | X69: =IFERROR(IF(W69="","",WORKDAY.INTL(B69,_xlfn.XLOOKUP(W69,Regras!$F$2:$F$11,Regras!$G$2:$G$11))),"") -> 45930 | Y69: FEITO CONTATO PARA REPOSIÇÃO | Z69: SIM | AB69: POSSIVEL RECOMPRA
B70: 45891 | D70: CECILIA DIAS SUPLEMENTOS | E70: 54.679.245/0001-16 | F70: SP | G70: Larissa Padilha | H70: 22/08/2025 | I70: 784.65 | J70: 20 | K70: 24 | L70: ATIVO | R70: SIM | S70: SIM | T70: NÃO | U70: ATIVO | V70: ATENDIMENTO CLIENTES ATIVOS | W70: VENDA | X70: =IFERROR(IF(W70="","",WORKDAY.INTL(B70,_xlfn.XLOOKUP(W70,Regras!$F$2:$F$11,Regras!$G$2:$G$11))),"") -> 45954 | Y70: RECOMPRA | Z70: SIM
B71: 45891 | D71: PROSAUDE | E71: 21.437.528/0001-00 | F71: RS | G71: Larissa Padilha | H71: 22/08/2025 | I71: 1233.66 | J71: 20 | K71: * | L71: ATIVO | R71: SIM | S71: SIM | T71: SIM | U71: ATIVO | V71: PROSPECÇÃO NOVOS CLIENTES | W71: VENDA | X71: =IFERROR(IF(W71="","",WORKDAY.INTL(B71,_xlfn.XLOOKUP(W71,Regras!$F$2:$F$11,Regras!$G$2:$G$11))),"") -> 45954 | Y71: RECOMPRA | Z71: SIM
B72: 45890 | D72: DIVINA TERRA SORRISO | E72: 50.772.174/0001-40 | F72: MT | G72: Manu Ditzel | H72: 21/08/2025 | I72: 1322.32 | J72: 21 | K72: * | L72: ATIVO | R72: SIM | S72: SIM | T72: NÃO | U72: ATIVO | V72: PROSPECÇÃO NOVOS CLIENTES | W72: VENDA | X72: =IFERROR(IF(W72="","",WORKDAY.INTL(B72,_xlfn.XLOOKUP(W72,Regras!$F$2:$F$11,Regras!$G$2:$G$11))),"") -> 45953 | Y72: RECOMPRA | Z72: SIM
B73: 45890 | D73: JAQUELINE MACHADO COUTO 08791417600 | E73: 45.120.770/0001-06 | F73: MG | G73: Manu Ditzel | H73: 21/08/2025 | I73: 933.42 | J73: 21 | K73: * | L73: ATIVO | R73: SIM | S73: SIM | T73: NÃO | U73: ATIVO | V73: PROSPECÇÃO NOVOS CLIENTES | W73: VENDA | X73: =IFERROR(IF(W73="","",WORKDAY.INTL(B73,_xlfn.XLOOKUP(W73,Regras!$F$2:$F$11,Regras!$G$2:$G$11))),"") -> 45953 | Y73: RECOMPRA | Z73: SIM
B74: 45890 | D74: MISTER GRAOS SS MOCOQUINHA LTDA | E74: 58.434.075/0001-60 | F74: MG | G74: Manu Ditzel | H74: 21/08/2025 | I74: 2116.36 | J74: 21 | K74: 52 | L74: ATIVO | R74: SIM | S74: SIM | T74: NÃO | U74: RECEPTIVO | V74: ATENDIMENTO CLIENTES INATIVOS | W74: VENDA | X74: =IFERROR(IF(W74="","",WORKDAY.INTL(B74,_xlfn.XLOOKUP(W74,Regras!$F$2:$F$11,Regras!$G$2:$G$11))),"") -> 45953 | Y74: RECOMPRA | Z74: SIM
B75: 45890 | D75: VITA PRODUTOS NATURAIS | E75: 16.762.003/0001-00 | F75: GO | G75: Manu Ditzel | H75: 21/08/2025 | I75: 1859.19 | J75: 21 | K75: 59.5 | L75: ATIVO | R75: SIM | S75: SIM | T75: NÃO | U75: RECEPTIVO | V75: ATENDIMENTO CLIENTES INATIVOS | W75: VENDA | X75: =IFERROR(IF(W75="","",WORKDAY.INTL(B75,_xlfn.XLOOKUP(W75,Regras!$F$2:$F$11,Regras!$G$2:$G$11))),"") -> 45953 | Y75: RECOMPRA | Z75: SIM
B76: 45889 | D76: EMPORIO VIDA E SAUDE | E76: 20.021.355/0001-74 | F76: PR | G76: Manu Ditzel | H76: 20/08/2025 | I76: 684.92 | J76: 22 | K76: * | L76: ATIVO | R76: SIM | S76: SIM | T76: NÃO | U76: ATIVO | V76: PROSPECÇÃO NOVOS CLIENTES | W76: VENDA | X76: =IFERROR(IF(W76="","",WORKDAY.INTL(B76,_xlfn.XLOOKUP(W76,Regras!$F$2:$F$11,Regras!$G$2:$G$11))),"") -> 45952 | Y76: RECOMPRA | Z76: SIM
B77: 45889 | D77: FORCE SUPLEMENTOS | E77: 26.240.684/0002-73 | F77: SC | G77: Manu Ditzel | H77: 20/08/2025 | I77: 1137.84 | J77: 22 | K77: 16 | L77: ATIVO | R77: SIM | S77: SIM | T77: SIM | U77: ATIVO | V77: ATENDIMENTO CLIENTES ATIVOS | W77: VENDA | X77: =IFERROR(IF(W77="","",WORKDAY.INTL(B77,_xlfn.XLOOKUP(W77,Regras!$F$2:$F$11,Regras!$G$2:$G$11))),"") -> 45952 | Y77: RECOMPRA | Z77: SIM
B78: 45889 | D78: TICO AUTO POSTO LOBATO | E78: 34.788.640/0001-20 | F78: PR | G78: Central - Daiane | H78: 20/08/2025 | I78: 1443.35 | J78: 22 | K78: * | L78: ATIVO | R78: SIM | S78: SIM | T78: SIM | U78: ATIVO | V78: PROSPECÇÃO NOVOS CLIENTES | W78: VENDA | X78: =IFERROR(IF(W78="","",WORKDAY.INTL(B78,_xlfn.XLOOKUP(W78,Regras!$F$2:$F$11,Regras!$G$2:$G$11))),"") -> 45952 | Y78: RECOMPRA | Z78: SIM
B79: 45926 | D79: EMPORIO VIDA E SAUDE | E79: 20.021.355/0001-74 | F79: PR | G79: Manu Ditzel | H79: 20/08/2025 | I79: 684.92 | J79: 22 | K79: * | L79: ATIVO | R79: SIM | S79: SIM | T79: NÃO | U79: ATIVO | V79: ATENDIMENTO CLIENTES ATIVOS | W79: FOLLOW UP 15 | X79: =IFERROR(IF(W79="","",WORKDAY.INTL(B79,_xlfn.XLOOKUP(W79,Regras!$F$2:$F$11,Regras!$G$2:$G$11))),"") -> 45947 | Y79: CLIENTE IRÁ FAZER O PEDIDO MAIS COMEÇO DO MÊS | Z79: SIM | AB79: CLIENTE IRÁ FAZER O PEDIDO MAIS FIM DO MÊS
B80: 45888 | D80: CENTRAL ATACAREJO | E80: 48.252.719/0001-46 | F80: DF | G80: Helder Brunkow | H80: 19/08/2025 | I80: 3912.71 | J80: 23 | K80: * | L80: ATIVO | R80: SIM | S80: SIM | T80: SIM | U80: ATIVO | V80: PROSPECÇÃO NOVOS CLIENTES | W80: VENDA | X80: =IFERROR(IF(W80="","",WORKDAY.INTL(B80,_xlfn.XLOOKUP(W80,Regras!$F$2:$F$11,Regras!$G$2:$G$11))),"") -> 45951 | Y80: RECOMPRA | Z80: SIM
B81: 45888 | D81: NUTRI LEVE | E81: 12.659.548/0001-27 | F81: SC | G81: Manu Ditzel | H81: 19/08/2025 | I81: 1508.79 | J81: 23 | K81: 48 | L81: ATIVO | R81: SIM | S81: SIM | T81: SIM | U81: ATIVO | V81: ATENDIMENTO CLIENTES INATIVOS | W81: VENDA | X81: =IFERROR(IF(W81="","",WORKDAY.INTL(B81,_xlfn.XLOOKUP(W81,Regras!$F$2:$F$11,Regras!$G$2:$G$11))),"") -> 45951 | Y81: RECOMPRA | Z81: SIM
B82: 45926 | D82: NUTRI LEVE | E82: 12.659.548/0001-27 | F82: SC | G82: Manu Ditzel | H82: 19/08/2025 | I82: 1508.79 | J82: 23 | K82: 48 | L82: ATIVO | R82: SIM | S82: SIM | T82: NÃO | U82: ATIVO | V82: ATENDIMENTO CLIENTES ATIVOS | W82: EM ATENDIMENTO | X82: =IFERROR(IF(W82="","",WORKDAY.INTL(B82,_xlfn.XLOOKUP(W82,Regras!$F$2:$F$11,Regras!$G$2:$G$11))),"") -> 45930 | Y82: CLIENTE COMPRA MENSAL | Z82: SIM | AB82: POSSIVEL RECOMPRA
B83: 45930 | D83: NUTRI LEVE | E83: 12.659.548/0001-27 | F83: SC | G83: Manu Ditzel | H83: 19/08/2025 | I83: 1508.79 | J83: 23 | K83: 48 | L83: ATIVO | R83: SIM | S83: SIM | T83: NÃO | U83: ATIVO | V83: ATENDIMENTO CLIENTES ATIVOS | W83: EM ATENDIMENTO | X83: =IFERROR(IF(W83="","",WORKDAY.INTL(B83,_xlfn.XLOOKUP(W83,Regras!$F$2:$F$11,Regras!$G$2:$G$11))),"") -> 45932 | Y83: POSSIVEL RECOMPRA | Z83: SIM | AB83: FEITO CONTATO PARA RECOMPRA
B84: 45932 | D84: NUTRI LEVE | E84: 12.659.548/0001-27 | F84: SC | G84: Manu Ditzel | H84: 19/08/2025 | I84: 1508.79 | J84: 23 | K84: 48 | L84: ATIVO | R84: SIM | S84: NÃO | T84: NÃO | U84: RECEPTIVO | V84: CONTATOS PASSIVO / SUPORTE | W84: SUPORTE | X84: =IFERROR(IF(W84="","",WORKDAY.INTL(B84,_xlfn.XLOOKUP(W84,Regras!$F$2:$F$11,Regras!$G$2:$G$11))),"") | Y84: PROBLEMAS COM BOLETO | Z84: SIM | AB84: PROBLEMAS COM BOLETO
B85: 45932 | D85: NUTRI LEVE | E85: 12.659.548/0001-27 | F85: SC | G85: Manu Ditzel | H85: 19/08/2025 | I85: 1508.79 | J85: 23 | K85: 48 | L85: ATIVO | R85: SIM | S85: SIM | T85: NÃO | U85: ATIVO | V85: ATENDIMENTO CLIENTES ATIVOS | W85: FOLLOW UP 7 | X85: =IFERROR(IF(W85="","",WORKDAY.INTL(B85,_xlfn.XLOOKUP(W85,Regras!$F$2:$F$11,Regras!$G$2:$G$11))),"") -> 45943 | Y85: ENTRANDO EM CONTATO PARA POSSIVEL RECOMPRA | Z85: SIM | AB85: ENTRANDO EM CONTATO PARA POSSIVEL RECOMPRA
B86: 45887 | D86: RAIZES COMERCIO DE PRODUTOS NATURAIS E INCLUSIVOS LTDA | E86: 32.093.388/0001-09 | F86: PA | G86: Helder Brunkow | H86: 18/08/2025 | I86: 2016.25 | J86: 24 | K86: * | L86: ATIVO | R86: SIM | S86: SIM | T86: SIM | U86: ATIVO | V86: PROSPECÇÃO NOVOS CLIENTES | W86: VENDA | X86: =IFERROR(IF(W86="","",WORKDAY.INTL(B86,_xlfn.XLOOKUP(W86,Regras!$F$2:$F$11,Regras!$G$2:$G$11))),"") -> 45950 | Y86: RECOMPRA | Z86: SIM
B87: 45884 | D87: 48.097.578 SALAH UD DIN ALE CHARKIE | E87: 48.097.578/0001-34 | F87: PR | G87: Manu Ditzel | H87: 15/08/2025 | I87: 940.5 | J87: 27 | K87: 33.8 | L87: ATIVO | R87: SIM | S87: SIM | T87: NÃO | U87: RECEPTIVO | V87: ATENDIMENTO CLIENTES ATIVOS | W87: VENDA | X87: =IFERROR(IF(W87="","",WORKDAY.INTL(B87,_xlfn.XLOOKUP(W87,Regras!$F$2:$F$11,Regras!$G$2:$G$11))),"") -> 45947 | Y87: RECOMPRA | Z87: SIM
B88: 45884 | D88: EMPORIO POMAR URBANO | E88: 22.332.946/0001-98 | F88: SC | G88: Larissa Padilha | H88: 15/08/2025 | I88: 674.68 | J88: 27 | K88: * | L88: ATIVO | R88: SIM | S88: SIM | T88: NÃO | U88: RECEPTIVO | V88: PROSPECÇÃO NOVOS CLIENTES | W88: VENDA | X88: =IFERROR(IF(W88="","",WORKDAY.INTL(B88,_xlfn.XLOOKUP(W88,Regras!$F$2:$F$11,Regras!$G$2:$G$11))),"") -> 45947 | Y88: RECOMPRA | Z88: SIM
B89: 45884 | D89: LM NUTRICAO BOMBINHAS | E89: 54.904.619/0001-50 | F89: SC | G89: Larissa Padilha | H89: 15/08/2025 | I89: 820.8 | J89: 27 | K89: 52 | L89: ATIVO | R89: SIM | S89: SIM | T89: SIM | U89: ATIVO | V89: ATENDIMENTO CLIENTES INATIVOS | W89: VENDA | X89: =IFERROR(IF(W89="","",WORKDAY.INTL(B89,_xlfn.XLOOKUP(W89,Regras!$F$2:$F$11,Regras!$G$2:$G$11))),"") -> 45947 | Y89: RECOMPRA | Z89: SIM
B90: 45884 | D90: NEM PEIXE | E90: 56.608.812/0001-79 | F90: RS | G90: Manu Ditzel | H90: 15/08/2025 | I90: 490.02 | J90: 27 | K90: * | L90: ATIVO | R90: SIM | S90: SIM | T90: SIM | U90: ATIVO | V90: PROSPECÇÃO NOVOS CLIENTES | W90: VENDA | X90: =IFERROR(IF(W90="","",WORKDAY.INTL(B90,_xlfn.XLOOKUP(W90,Regras!$F$2:$F$11,Regras!$G$2:$G$11))),"") -> 45947 | Y90: RECOMPRA | Z90: SIM
B91: 45884 | D91: PADOCA DA BAXA | E91: 55.906.608/0001-71 | F91: RS | G91: Manu Ditzel | H91: 15/08/2025 | I91: 2105.6 | J91: 27 | K91: * | L91: ATIVO | R91: SIM | S91: SIM | T91: SIM | U91: ATIVO | V91: PROSPECÇÃO NOVOS CLIENTES | W91: VENDA | X91: =IFERROR(IF(W91="","",WORKDAY.INTL(B91,_xlfn.XLOOKUP(W91,Regras!$F$2:$F$11,Regras!$G$2:$G$11))),"") -> 45947 | Y91: RECOMPRA | Z91: SIM
B92: 45884 | D92: SUPERMERCADO OFERTAO | E92: 07.316.826/0001-03 | F92: SC | G92: Manu Ditzel | H92: 15/08/2025 | I92: 1514.06 | J92: 27 | K92: 37 | L92: ATIVO | R92: SIM | S92: SIM | T92: NÃO | U92: ATIVO | V92: ATENDIMENTO CLIENTES ATIVOS | W92: VENDA | X92: =IFERROR(IF(W92="","",WORKDAY.INTL(B92,_xlfn.XLOOKUP(W92,Regras!$F$2:$F$11,Regras!$G$2:$G$11))),"") -> 45947 | Y92: RECOMPRA | Z92: SIM
B93: 45884 | D93: NEM PEIXE | E93: 56.608.812/0001-79 | F93: RS | G93: Manu Ditzel | H93: 15/08/2025 | I93: 490.02 | J93: 27 | K93: * | L93: ATIVO | R93: SIM | S93: NÃO | T93: NÃO | U93: ATIVO | V93: ATENDIMENTO CLIENTES ATIVOS | W93: VENDA | Y93: RECOMPRA | Z93: SIM | AB93: FEITO RECOMPRA
B94: 45926 | D94: PADOCA DA BAXA | E94: 55.906.608/0001-71 | F94: RS | G94: Manu Ditzel | H94: 15/08/2025 | I94: 2105.6 | J94: 27 | K94: * | L94: ATIVO | R94: SIM | S94: NÃO | T94: NÃO | U94: ATIVO | V94: ATENDIMENTO CLIENTES INATIVOS | W94: FOLLOW UP 15 | X94: =IFERROR(IF(W94="","",WORKDAY.INTL(B94,_xlfn.XLOOKUP(W94,Regras!$F$2:$F$11,Regras!$G$2:$G$11))),"") -> 45947 | Y94: CLIENTE ABRIU PARCIAL A LOJA | Z94: SIM | AB94: CLIENTE ABRIU PARCIAL A LOJA
B95: 45926 | D95: MINI MERCADO FAMILIA | E95: 35.743.795/0001-02 | F95: SC | G95: Manu Ditzel | H95: 27/08/2025 | I95: 2161.62 | J95: 27 | K95: * | L95: ATIVO | R95: SIM | S95: SIM | T95: SIM | U95: ATIVO | V95: ATENDIMENTO CLIENTES ATIVOS | W95: FOLLOW UP 15 | X95: =IFERROR(IF(W95="","",WORKDAY.INTL(B95,_xlfn.XLOOKUP(W95,Regras!$F$2:$F$11,Regras!$G$2:$G$11))),"") -> 45947 | Y95: CLIENTE PEDIR RETORNO MAIS METADE DO MÊS | Z95: SIM | AB95: CLIENTE PEDIR RETORNO MAIS METADE DO MÊS
B96: 45883 | D96: LAKOSKI MERCEARIA SEM GLUTEN | E96: 60.484.125/0001-66 | F96: PR | G96: Manu Ditzel | H96: 14/08/2025 | I96: 653 | J96: 28 | K96: * | L96: ATIVO | R96: SIM | S96: SIM | T96: SIM | U96: RECEPTIVO | V96: PROSPECÇÃO NOVOS CLIENTES | W96: VENDA | X96: =IFERROR(IF(W96="","",WORKDAY.INTL(B96,_xlfn.XLOOKUP(W96,Regras!$F$2:$F$11,Regras!$G$2:$G$11))),"") -> 45946 | Y96: RECOMPRA | Z96: SIM
B97: 45883 | D97: MENEGAZ SUPERMERCADO | E97: 95.772.216/0001-81 | F97: SC | G97: Manu Ditzel | H97: 14/08/2025 | I97: 2505.43 | J97: 28 | K97: * | L97: ATIVO | R97: SIM | S97: SIM | T97: SIM | U97: RECEPTIVO | V97: PROSPECÇÃO NOVOS CLIENTES | W97: VENDA | X97: =IFERROR(IF(W97="","",WORKDAY.INTL(B97,_xlfn.XLOOKUP(W97,Regras!$F$2:$F$11,Regras!$G$2:$G$11))),"") -> 45946 | Y97: RECOMPRA | Z97: SIM
B98: 45883 | D98: SWEET AND FIT ATELIER | E98: 37.370.567/0001-60 | F98: SP | G98: Manu Ditzel | H98: 14/08/2025 | I98: 3448 | J98: 28 | K98: 30 | L98: ATIVO | R98: SIM | S98: SIM | T98: SIM | U98: ATIVO | V98: ATENDIMENTO CLIENTES ATIVOS | W98: VENDA | X98: =IFERROR(IF(W98="","",WORKDAY.INTL(B98,_xlfn.XLOOKUP(W98,Regras!$F$2:$F$11,Regras!$G$2:$G$11))),"") -> 45946 | Y98: RECOMPRA | Z98: SIM | AB98: RECOMPRA
B99: 45883 | D99: MENEGAZ SUPERMERCADO | E99: 95.772.216/0001-81 | F99: SC | G99: Manu Ditzel | H99: 14/08/2025 | I99: 2505.43 | J99: 28 | K99: * | L99: ATIVO | R99: SIM | S99: NÃO | T99: NÃO | U99: ATIVO | V99: CONTATOS PASSIVO / SUPORTE | W99: SUPORTE | Y99: ENTREGA | Z99: SIM | AB99: CD NÃO ESTAVA AUTORIZANDO ENTREGA, FOI RESOLVIDO. jÁ ESTÁ ENTREGUE
B100: 45919 | D100: SWEET AND FIT ATELIER | E100: 37.370.567/0001-60 | F100: SP | G100: Manu Ditzel | H100: 14/08/2025 | I100: 3448 | J100: 28 | K100: 30 | L100: ATIVO | R100: SIM | S100: NÃO | T100: NÃO | U100: ATIVO | V100: ATENDIMENTO CLIENTES ATIVOS | W100: VENDA | X100: =IFERROR(IF(W100="","",WORKDAY.INTL(B100,_xlfn.XLOOKUP(W100,Regras!$F$2:$F$11,Regras!$G$2:$G$11))),"") -> 45982 | Y100: RECOMPRA | Z100: SIM | AB100: RECOMPRA
B101: 45882 | D101: BV ALIMENTOS LTDA | E101: 60.475.933/0001-67 | F101: PE | G101: Helder Brunkow | H101: 13/08/2025 | I101: 2105.05 | J101: 29 | K101: * | L101: ATIVO | R101: SIM | S101: SIM | T101: SIM | U101: ATIVO | V101: PROSPECÇÃO NOVOS CLIENTES | W101: VENDA | X101: =IFERROR(IF(W101="","",WORKDAY.INTL(B101,_xlfn.XLOOKUP(W101,Regras!$F$2:$F$11,Regras!$G$2:$G$11))),"") -> 45945 | Y101: RECOMPRA | Z101: SIM
...

Sheet Planilha1
A1: VIDA LEVE - SÃO JOSE DO RIO PRETO
A2: PADOCA DA BAXA
A3: LAKOSKI MERCEARIA SEM GLUTEN
A4: 48.097.578 SALAH UD DIN ALE CHARKIE
A5: MINI MERCADO FAMILIA
A6: EMPORIO VIDA E SAUDE
A7: FORCE SUPLEMENTOS
A8: NATURALIS PRODUTOS NATURAIS
A9: MERCADO FERREIRA
A10: ITALO ZILMER BEDERODE LTDA
A11: NATURVIDA
A12: NATURVIDA
... A14: RADISSON HOTEL CURITIBA

Sheet CARTEIRA
A1: BASE TOTAL | B1: NOVOS CLIENTES 30 DIAS | C1: CLIENTES ATIVOS | D1: CLIENTES INATIVOS RECENTE | E1: CLIENTES INATIVO ANTIGO | G1: POSITIVAÇÃO ATIVA | H1: POSITIVAÇAO PASSIVA | I1: TOTAL
B2: Puxar direto do Mercos / exact

Sheet Base Novos Clientes
C2: NOME FANTASIA | D2: CNPJ | E2: UF | F2: VENDEDOR | G2: R$ - ULTIMO PEDIDO | H2: DIAS SEM COMPRAR | I2: CICLO MÉDIO | J2: DATA ULTIMA VENDA | K2: STATUS | L2: SITUAÇÃO ATUAL | M2: ULTIMO CONTATO | N2: RESULTADO ATUAL | O2: AÇÃO | P2: Coluna1 | Q2: FOLLOW UP | R2: NÃO ATENDE | S2: RECUSOU LIGAÇÃO | T2: NÃO RESPONDE
K3: =IF(J3="","NOVO",_xlfn.XLOOKUP(TODAY()-J3,Regras!$C$3:$C$10,Regras!$D$3:$D$10,,1)) -> NOVO | L3: =IF(OR(I3<=0,I3=""),"","Recompra") | M3: =IFERROR(IF(Tabela13[[#This Row],[NOME FANTASIA]]="","",_xlfn.XLOOKUP($C3,Log!D:D,Log!B:B,,,-1)),"") | N3: =IFERROR(_xlfn.XLOOKUP($C3,Log!D:D,Log!W:W,,,-1),"") | O3: =IFERROR(_xlfn.XLOOKUP($C3,Log!D:D,Log!Y:Y,,,-1),"") -> 0 | Q3: =IFERROR(IF(Tabela13[[#This Row],[NOME FANTASIA]]="","",_xlfn.XLOOKUP($C3,Log!D:D,Log!X:X,,,-1)),"") | R3: =COUNTIFS(Log!$D:$D,'Base Novos Clientes'!$C3,Log!$W:$W,'Base Novos Clientes'!R$2) -> 0 | S3: =COUNTIFS(Log!$D:$D,'Base Novos Clientes'!$C3,Log!$W:$W,'Base Novos Clientes'!S$2) -> 0 | T3: =COUNTIFS(Log!$D:$D,'Base Novos Clientes'!$C3,Log!$W:$W,'Base Novos Clientes'!T$2) -> 0
K4: =IF(J4="","NOVO",_xlfn.XLOOKUP(TODAY()-J4,Regras!$C$3:$C$10,Regras!$D$3:$D$10,,1)) -> NOVO | L4: =IF(OR(I4<=0,I4=""),"","Recompra") | M4: =IFERROR(IF(Tabela13[[#This Row],[NOME FANTASIA]]="","",_xlfn.XLOOKUP($C4,Log!D:D,Log!B:B,,,-1)),"") | N4: =IFERROR(_xlfn.XLOOKUP($C4,Log!D:D,Log!W:W,,,-1),"") | O4: =IFERROR(_xlfn.XLOOKUP($C4,Log!D:D,Log!Y:Y,,,-1),"") -> 0 | Q4: =IFERROR(IF(Tabela13[[#This Row],[NOME FANTASIA]]="","",_xlfn.XLOOKUP($C4,Log!D:D,Log!X:X,,,-1)),"") | R4: =COUNTIFS(Log!$D:$D,'Base Novos Clientes'!$C4,Log!$W:$W,'Base Novos Clientes'!R$2) -> 0 | S4: =COUNTIFS(Log!$D:$D,'Base Novos Clientes'!$C4,Log!$W:$W,'Base Novos Clientes'!S$2) -> 0 | T4: =COUNTIFS(Log!$D:$D,'Base Novos Clientes'!$C4,Log!$W:$W,'Base Novos Clientes'!T$2) -> 0
K5: =IF(J5="","NOVO",_xlfn.XLOOKUP(TODAY()-J5,Regras!$C$3:$C$10,Regras!$D$3:$D$10,,1)) -> NOVO | L5: =IF(OR(I5<=0,I5=""),"","Recompra") | M5: =IFERROR(IF(Tabela13[[#This Row],[NOME FANTASIA]]="","",_xlfn.XLOOKUP($C5,Log!D:D,Log!B:B,,,-1)),"") | N5: =IFERROR(_xlfn.XLOOKUP($C5,Log!D:D,Log!W:W,,,-1),"") | O5: =IFERROR(_xlfn.XLOOKUP($C5,Log!D:D,Log!Y:Y,,,-1),"") -> 0 | Q5: =IFERROR(IF(Tabela13[[#This Row],[NOME FANTASIA]]="","",_xlfn.XLOOKUP($C5,Log!D:D,Log!X:X,,,-1)),"") | R5: =COUNTIFS(Log!$D:$D,'Base Novos Clientes'!$C5,Log!$W:$W,'Base Novos Clientes'!R$2) -> 0 | S5: =COUNTIFS(Log!$D:$D,'Base Novos Clientes'!$C5,Log!$W:$W,'Base Novos Clientes'!S$2) -> 0 | T5: =COUNTIFS(Log!$D:$D,'Base Novos Clientes'!$C5,Log!$W:$W,'Base Novos Clientes'!T$2) -> 0
K6: =IF(J6="","NOVO",_xlfn.XLOOKUP(TODAY()-J6,Regras!$C$3:$C$10,Regras!$D$3:$D$10,,1)) -> NOVO | L6: =IF(OR(I6<=0,I6=""),"","Recompra") | M6: =IFERROR(IF(Tabela13[[#This Row],[NOME FANTASIA]]="","",_xlfn.XLOOKUP($C6,Log!D:D,Log!B:B,,,-1)),"") | N6: =IFERROR(_xlfn.XLOOKUP($C6,Log!D:D,Log!W:W,,,-1),"") | O6: =IFERROR(_xlfn.XLOOKUP($C6,Log!D:D,Log!Y:Y,,,-1),"") -> 0 | Q6: =IFERROR(IF(Tabela13[[#This Row],[NOME FANTASIA]]="","",_xlfn.XLOOKUP($C6,Log!D:D,Log!X:X,,,-1)),"") | R6: =COUNTIFS(Log!$D:$D,'Base Novos Clientes'!$C6,Log!$W:$W,'Base Novos Clientes'!R$2) -> 0 | S6: =COUNTIFS(Log!$D:$D,'Base Novos Clientes'!$C6,Log!$W:$W,'Base Novos Clientes'!S$2) -> 0 | T6: =COUNTIFS(Log!$D:$D,'Base Novos Clientes'!$C6,Log!$W:$W,'Base Novos Clientes'!T$2) -> 0
K7: =IF(J7="","NOVO",_xlfn.XLOOKUP(TODAY()-J7,Regras!$C$3:$C$10,Regras!$D$3:$D$10,,1)) -> NOVO | L7: =IF(OR(I7<=0,I7=""),"","Recompra") | M7: =IFERROR(IF(Tabela13[[#This Row],[NOME FANTASIA]]="","",_xlfn.XLOOKUP($C7,Log!D:D,Log!B:B,,,-1)),"") | N7: =IFERROR(_xlfn.XLOOKUP($C7,Log!D:D,Log!W:W,,,-1),"") | O7: =IFERROR(_xlfn.XLOOKUP($C7,Log!D:D,Log!Y:Y,,,-1),"") -> 0 | Q7: =IFERROR(IF(Tabela13[[#This Row],[NOME FANTASIA]]="","",_xlfn.XLOOKUP($C7,Log!D:D,Log!X:X,,,-1)),"") | R7: =COUNTIFS(Log!$D:$D,'Base Novos Clientes'!$C7,Log!$W:$W,'Base Novos Clientes'!R$2) -> 0 | S7: =COUNTIFS(Log!$D:$D,'Base Novos Clientes'!$C7,Log!$W:$W,'Base Novos Clientes'!S$2) -> 0 | T7: =COUNTIFS(Log!$D:$D,'Base Novos Clientes'!$C7,Log!$W:$W,'Base Novos Clientes'!T$2) -> 0
K8: =IF(J8="","NOVO",_xlfn.XLOOKUP(TODAY()-J8,Regras!$C$3:$C$10,Regras!$D$3:$D$10,,1)) -> NOVO | L8: =IF(OR(I8<=0,I8=""),"","Recompra") | M8: =IFERROR(IF(Tabela13[[#This Row],[NOME FANTASIA]]="","",_xlfn.XLOOKUP($C8,Log!D:D,Log!B:B,,,-1)),"") | N8: =IFERROR(_xlfn.XLOOKUP($C8,Log!D:D,Log!W:W,,,-1),"") | O8: =IFERROR(_xlfn.XLOOKUP($C8,Log!D:D,Log!Y:Y,,,-1),"") -> 0 | Q8: =IFERROR(IF(Tabela13[[#This Row],[NOME FANTASIA]]="","",_xlfn.XLOOKUP($C8,Log!D:D,Log!X:X,,,-1)),"") | R8: =COUNTIFS(Log!$D:$D,'Base Novos Clientes'!$C8,Log!$W:$W,'Base Novos Clientes'!R$2) -> 0 | S8: =COUNTIFS(Log!$D:$D,'Base Novos Clientes'!$C8,Log!$W:$W,'Base Novos Clientes'!S$2) -> 0 | T8: =COUNTIFS(Log!$D:$D,'Base Novos Clientes'!$C8,Log!$W:$W,'Base Novos Clientes'!T$2) -> 0
K9: =IF(J9="","NOVO",_xlfn.XLOOKUP(TODAY()-J9,Regras!$C$3:$C$10,Regras!$D$3:$D$10,,1)) -> NOVO | L9: =IF(OR(I9<=0,I9=""),"","Recompra") | M9: =IFERROR(IF(Tabela13[[#This Row],[NOME FANTASIA]]="","",_xlfn.XLOOKUP($C9,Log!D:D,Log!B:B,,,-1)),"") | N9: =IFERROR(_xlfn.XLOOKUP($C9,Log!D:D,Log!W:W,,,-1),"") | O9: =IFERROR(_xlfn.XLOOKUP($C9,Log!D:D,Log!Y:Y,,,-1),"") -> 0 | Q9: =IFERROR(IF(Tabela13[[#This Row],[NOME FANTASIA]]="","",_xlfn.XLOOKUP($C9,Log!D:D,Log!X:X,,,-1)),"") | R9: =COUNTIFS(Log!$D:$D,'Base Novos Clientes'!$C9,Log!$W:$W,'Base Novos Clientes'!R$2) -> 0 | S9: =COUNTIFS(Log!$D:$D,'Base Novos Clientes'!$C9,Log!$W:$W,'Base Novos Clientes'!S$2) -> 0 | T9: =COUNTIFS(Log!$D:$D,'Base Novos Clientes'!$C9,Log!$W:$W,'Base Novos Clientes'!T$2) -> 0
K10: =IF(J10="","NOVO",_xlfn.XLOOKUP(TODAY()-J10,Regras!$C$3:$C$10,Regras!$D$3:$D$10,,1)) -> NOVO | L10: =IF(OR(I10<=0,I10=""),"","Recompra") | M10: =IFERROR(IF(Tabela13[[#This Row],[NOME FANTASIA]]="","",_xlfn.XLOOKUP($C10,Log!D:D,Log!B:B,,,-1)),"") | N10: =IFERROR(_xlfn.XLOOKUP($C10,Log!D:D,Log!W:W,,,-1),"") | O10: =IFERROR(_xlfn.XLOOKUP($C10,Log!D:D,Log!Y:Y,,,-1),"") -> 0 | Q10: =IFERROR(IF(Tabela13[[#This Row],[NOME FANTASIA]]="","",_xlfn.XLOOKUP($C10,Log!D:D,Log!X:X,,,-1)),"") | R10: =COUNTIFS(Log!$D:$D,'Base Novos Clientes'!$C10,Log!$W:$W,'Base Novos Clientes'!R$2) -> 0 | S10: =COUNTIFS(Log!$D:$D,'Base Novos Clientes'!$C10,Log!$W:$W,'Base Novos Clientes'!S$2) -> 0 | T10: =COUNTIFS(Log!$D:$D,'Base Novos Clientes'!$C10,Log!$W:$W,'Base Novos Clientes'!T$2) -> 0
K11: =IF(J11="","NOVO",_xlfn.XLOOKUP(TODAY()-J11,Regras!$C$3:$C$10,Regras!$D$3:$D$10,,1)) -> NOVO | L11: =IF(OR(I11<=0,I11=""),"","Recompra") | M11: =IFERROR(IF(Tabela13[[#This Row],[NOME FANTASIA]]="","",_xlfn.XLOOKUP($C11,Log!D:D,Log!B:B,,,-1)),"") | N11: =IFERROR(_xlfn.XLOOKUP($C11,Log!D:D,Log!W:W,,,-1),"") | O11: =IFERROR(_xlfn.XLOOKUP($C11,Log!D:D,Log!Y:Y,,,-1),"") -> 0 | Q11: =IFERROR(IF(Tabela13[[#This Row],[NOME FANTASIA]]="","",_xlfn.XLOOKUP($C11,Log!D:D,Log!X:X,,,-1)),"") | R11: =COUNTIFS(Log!$D:$D,'Base Novos Clientes'!$C11,Log!$W:$W,'Base Novos Clientes'!R$2) -> 0 | S11: =COUNTIFS(Log!$D:$D,'Base Novos Clientes'!$C11,Log!$W:$W,'Base Novos Clientes'!S$2) -> 0 | T11: =COUNTIFS(Log!$D:$D,'Base Novos Clientes'!$C11,Log!$W:$W,'Base Novos Clientes'!T$2) -> 0
K12: =IF(J12="","NOVO",_xlfn.XLOOKUP(TODAY()-J12,Regras!$C$3:$C$10,Regras!$D$3:$D$10,,1)) -> NOVO | L12: =IF(OR(I12<=0,I12=""),"","Recompra") | M12: =IFERROR(IF(Tabela13[[#This Row],[NOME FANTASIA]]="","",_xlfn.XLOOKUP($C12,Log!D:D,Log!B:B,,,-1)),"") | N12: =IFERROR(_xlfn.XLOOKUP($C12,Log!D:D,Log!W:W,,,-1),"") | O12: =IFERROR(_xlfn.XLOOKUP($C12,Log!D:D,Log!Y:Y,,,-1),"") -> 0 | Q12: =IFERROR(IF(Tabela13[[#This Row],[NOME FANTASIA]]="","",_xlfn.XLOOKUP($C12,Log!D:D,Log!X:X,,,-1)),"") | R12: =COUNTIFS(Log!$D:$D,'Base Novos Clientes'!$C12,Log!$W:$W,'Base Novos Clientes'!R$2) -> 0 | S12: =COUNTIFS(Log!$D:$D,'Base Novos Clientes'!$C12,Log!$W:$W,'Base Novos Clientes'!S$2) -> 0 | T12: =COUNTIFS(Log!$D:$D,'Base Novos Clientes'!$C12,Log!$W:$W,'Base Novos Clientes'!T$2) -> 0
K13: =IF(J13="","NOVO",_xlfn.XLOOKUP(TODAY()-J13,Regras!$C$3:$C$10,Regras!$D$3:$D$10,,1)) -> NOVO | L13: =IF(OR(I13<=0,I13=""),"","Recompra") | M13: =IFERROR(IF(Tabela13[[#This Row],[NOME FANTASIA]]="","",_xlfn.XLOOKUP($C13,Log!D:D,Log!B:B,,,-1)),"") | N13: =IFERROR(_xlfn.XLOOKUP($C13,Log!D:D,Log!W:W,,,-1),"") | O13: =IFERROR(_xlfn.XLOOKUP($C13,Log!D:D,Log!Y:Y,,,-1),"") -> 0 | Q13: =IFERROR(IF(Tabela13[[#This Row],[NOME FANTASIA]]="","",_xlfn.XLOOKUP($C13,Log!D:D,Log!X:X,,,-1)),"") | R13: =COUNTIFS(Log!$D:$D,'Base Novos Clientes'!$C13,Log!$W:$W,'Base Novos Clientes'!R$2) -> 0 | S13: =COUNTIFS(Log!$D:$D,'Base Novos Clientes'!$C13,Log!$W:$W,'Base Novos Clientes'!S$2) -> 0 | T13: =COUNTIFS(Log!$D:$D,'Base Novos Clientes'!$C13,Log!$W:$W,'Base Novos Clientes'!T$2) -> 0
K14: =IF(J14="","NOVO",_xlfn.XLOOKUP(TODAY()-J14,Regras!$C$3:$C$10,Regras!$D$3:$D$10,,1)) -> NOVO | L14: =IF(OR(I14<=0,I14=""),"","Recompra") | M14: =IFERROR(IF(Tabela13[[#This Row],[NOME FANTASIA]]="","",_xlfn.XLOOKUP($C14,Log!D:D,Log!B:B,,,-1)),"") | N14: =IFERROR(_xlfn.XLOOKUP($C14,Log!D:D,Log!W:W,,,-1),"") | O14: =IFERROR(_xlfn.XLOOKUP($C14,Log!D:D,Log!Y:Y,,,-1),"") -> 0 | Q14: =IFERROR(IF(Tabela13[[#This Row],[NOME FANTASIA]]="","",_xlfn.XLOOKUP($C14,Log!D:D,Log!X:X,,,-1)),"") | R14: =COUNTIFS(Log!$D:$D,'Base Novos Clientes'!$C14,Log!$W:$W,'Base Novos Clientes'!R$2) -> 0 | S14: =COUNTIFS(Log!$D:$D,'Base Novos Clientes'!$C14,Log!$W:$W,'Base Novos Clientes'!S$2) -> 0 | T14: =COUNTIFS(Log!$D:$D,'Base Novos Clientes'!$C14,Log!$W:$W,'Base Novos Clientes'!T$2) -> 0
... K400: =IF(J400="","NOVO",_xlfn.XLOOKUP(TODAY()-J400,Regras!$C$3:$C$10,Regras!$D$3:$D$10,,1)) -> NOVO | L400: =IF(OR(I400<=0,I400=""),"","Recompra") | M400: =IFERROR(IF(Tabela13[[#This Row],[NOME FANTASIA]]="","",_xlfn.XLOOKUP($C400,Log!D:D,Log!B:B,,,-1)),"") | N400: =IFERROR(_xlfn.XLOOKUP($C400,Log!D:D,Log!W:W,,,-1),"") | O400: =IFERROR(_xlfn.XLOOKUP($C400,Log!D:D,Log!Y:Y,,,-1),"") -> 0 | Q400: =IFERROR(IF(Tabela13[[#This Row],[NOME FANTASIA]]="","",_xlfn.XLOOKUP($C400,Log!D:D,Log!X:X,,,-1)),"") | R400: =COUNTIFS(Log!$D:$D,'Base Novos Clientes'!$C400,Log!$W:$W,'Base Novos Clientes'!R$2) -> 0 | S400: =COUNTIFS(Log!$D:$D,'Base Novos Clientes'!$C400,Log!$W:$W,'Base Novos Clientes'!S$2) -> 0 | T400: =COUNTIFS(Log!$D:$D,'Base Novos Clientes'!$C400,Log!$W:$W,'Base Novos Clientes'!T$2) -> 0

Sheet Dash
C2: VENDEDOR | F2: PERIODO
C3: Manu Ditzel | F3: 46006 | G3: 46006
F4: ,
C5: TIPO DO CONTATO | D5: TOTAL | F5: CONTATOS REALIZADOS | K5: FUNIL DE VENDA | P5: RELACIONAMENTO | S5: NÃO VENDA
F6: CONTATO WHATSAPP | G6: LIGAÇÃO REALIZADAS | H6: LIGAÇÕES ATENDIDAS | I6: LIGAÇÕES NÃO ATENDIDAS | K6: EM ATENDIMENTO | L6: ORÇAMENTO | M6: CADASTRO | N6: VENDA | P6: FOLLOW UP | Q6: SUPORTE | S6: CLIENTE INATIVO | T6: PERDA / NÃO VENDA
C7: PROSPECÇÃO NOVOS CLIENTES | D7: =IF($C$3=Regras!$K$3,COUNTIFS(Log!$B:$B,">="&$F$3,Log!$B:$B,"<="&$G$3,Log!$V:$V,$C7),COUNTIFS(Log!$B:$B,">="&$F$3,Log!$B:$B,"<="&$G$3,Log!$G:$G,$C$3,Log!$V:$V,$C7)) -> 4 | F7: =IF($C$3=Regras!$K$3,COUNTIFS(Log!$B:$B,">="&$F$3,Log!$B:$B,"<="&$G$3,Log!$R:$R,"SIM",Log!$V:$V,$C7),COUNTIFS(Log!$B:$B,">="&$F$3,Log!$B:$B,"<="&$G$3,Log!$G:$G,$C$3,Log!$R:$R,"SIM",Log!$V:$V,$C7)) -> 4 | G7: =IF($C$3=Regras!$K$3,COUNTIFS(Log!$B:$B,">="&$F$3,Log!$B:$B,"<="&$G$3,Log!$S:$S,"SIM",Log!$V:$V,$C7),COUNTIFS(Log!$B:$B,">="&$F$3,Log!$B:$B,"<="&$G$3,Log!$G:$G,$C$3,Log!$S:$S,"SIM",Log!$V:$V,$C7)) -> 0 | H7: =IF($C$3=Regras!$K$3,COUNTIFS(Log!$B:$B,">="&$F$3,Log!$B:$B,"<="&$G$3,Log!$S:$S,"SIM",Log!$T:$T,"SIM",Log!$V:$V,$C7),COUNTIFS(Log!$B:$B,">="&$F$3,Log!$B:$B,"<="&$G$3,Log!$G:$G,$C$3,Log!$S:$S,"SIM",Log!$T:$T,"SIM",Log!$V:$V,$C7)) -> 0 | I7: =IF($C$3=Regras!$K$3,COUNTIFS(Log!$B:$B,">="&$F$3,Log!$B:$B,"<="&$G$3,Log!$S:$S,"SIM",Log!$T:$T,"NÃO",Log!$V:$V,$C7),COUNTIFS(Log!$B:$B,">="&$F$3,Log!$B:$B,"<="&$G$3,Log!$G:$G,$C$3,Log!$S:$S,"SIM",Log!$T:$T,"NÃO",Log!$V:$V,$C7)) -> 0 | K7: =IF($C$3=Regras!$K$3,COUNTIFS(Log!$B:$B,">="&$F$3,Log!$B:$B,"<="&$G$3,Log!$V:$V,$C7,Log!$W:$W,K$6),COUNTIFS(Log!$B:$B,">="&$F$3,Log!$B:$B,"<="&$G$3,Log!$G:$G,$C$3,Log!$V:$V,$C7,Log!$W:$W,K$6)) -> 1 | L7: =IF($C$3=Regras!$K$3,COUNTIFS(Log!$B:$B,">="&$F$3,Log!$B:$B,"<="&$G$3,Log!$V:$V,$C7,Log!$W:$W,L$6),COUNTIFS(Log!$B:$B,">="&$F$3,Log!$B:$B,"<="&$G$3,Log!$G:$G,$C$3,Log!$V:$V,$C7,Log!$W:$W,L$6)) -> 0 | M7: =IF($C$3=Regras!$K$3,COUNTIFS(Log!$B:$B,">="&$F$3,Log!$B:$B,"<="&$G$3,Log!$V:$V,$C7,Log!$W:$W,M$6),COUNTIFS(Log!$B:$B,">="&$F$3,Log!$B:$B,"<="&$G$3,Log!$G:$G,$C$3,Log!$V:$V,$C7,Log!$W:$W,M$6)) -> 0 | N7: =IF($C$3=Regras!$K$3,COUNTIFS(Log!$B:$B,">="&$F$3,Log!$B:$B,"<="&$G$3,Log!$V:$V,$C7,Log!$W:$W,N$6),COUNTIFS(Log!$B:$B,">="&$F$3,Log!$B:$B,"<="&$G$3,Log!$G:$G,$C$3,Log!$V:$V,$C7,Log!$W:$W,N$6)) -> 2 | P7: =IF($C$3=Regras!$K$3,COUNTIFS(Log!$B:$B,">="&$F$3,Log!$B:$B,"<="&$G$3,Log!$V:$V,$C7,Log!$W:$W,P$6&" 15")+ COUNTIFS(Log!$B:$B,">="&$F$3,Log!$B:$B,"<="&$G$3,Log!$V:$V,$C7,Log!$W:$W,P$6&" 7"), COUNTIFS(Log!$B:$B,">="&$F$3,Log!$B:$B,"<="&$G$3,Log!$G:$G,$C$3,Log!$V:$V,$C7,Log!$W:$W,P$6&" 7")+ COUNTIFS(Log!$B:$B,">="&$F$3,Log!$B:$B,"<="&$G$3,Log!$G:$G,$C$3,Log!$V:$V,$C7,Log!$W:$W,P$6&" 15")) -> 1 | Q7: =IF($C$3=Regras!$K$3,COUNTIFS(Log!$B:$B,">="&$F$3,Log!$B:$B,"<="&$G$3,Log!$V:$V,$C7,Log!$W:$W,Q$6),COUNTIFS(Log!$B:$B,">="&$F$3,Log!$B:$B,"<="&$G$3,Log!$G:$G,$C$3,Log!$V:$V,$C7,Log!$W:$W,Q$6)) -> 0 | S7: =IF($C$3=Regras!$K$3,COUNTIFS(Log!$B:$B,">="&$F$3,Log!$B:$B,"<="&$G$3,Log!$V:$V,$C7,Log!$W:$W,S$6),COUNTIFS(Log!$B:$B,">="&$F$3,Log!$B:$B,"<="&$G$3,Log!$G:$G,$C$3,Log!$V:$V,$C7,Log!$W:$W,S$6)) -> 0 | T7: =IF($C$3=Regras!$K$3,COUNTIFS(Log!$B:$B,">="&$F$3,Log!$B:$B,"<="&$G$3,Log!$V:$V,$C7,Log!$W:$W,T$6),COUNTIFS(Log!$B:$B,">="&$F$3,Log!$B:$B,"<="&$G$3,Log!$G:$G,$C$3,Log!$V:$V,$C7,Log!$W:$W,T$6)) -> 0
C8: ATENDIMENTO CLIENTES ATIVOS | D8: =IF($C$3=Regras!$K$3,COUNTIFS(Log!$B:$B,">="&$F$3,Log!$B:$B,"<="&$G$3,Log!$V:$V,$C8),COUNTIFS(Log!$B:$B,">="&$F$3,Log!$B:$B,"<="&$G$3,Log!$G:$G,$C$3,Log!$V:$V,$C8)) -> 19 | F8: =IF($C$3=Regras!$K$3,COUNTIFS(Log!$B:$B,">="&$F$3,Log!$B:$B,"<="&$G$3,Log!$R:$R,"SIM",Log!$V:$V,$C8),COUNTIFS(Log!$B:$B,">="&$F$3,Log!$B:$B,"<="&$G$3,Log!$G:$G,$C$3,Log!$R:$R,"SIM",Log!$V:$V,$C8)) -> 19 | G8: =IF($C$3=Regras!$K$3,COUNTIFS(Log!$B:$B,">="&$F$3,Log!$B:$B,"<="&$G$3,Log!$S:$S,"SIM",Log!$V:$V,$C8),COUNTIFS(Log!$B:$B,">="&$F$3,Log!$B:$B,"<="&$G$3,Log!$G:$G,$C$3,Log!$S:$S,"SIM",Log!$V:$V,$C8)) -> 2 | H8: =IF($C$3=Regras!$K$3,COUNTIFS(Log!$B:$B,">="&$F$3,Log!$B:$B,"<="&$G$3,Log!$S:$S,"SIM",Log!$T:$T,"SIM",Log!$V:$V,$C8),COUNTIFS(Log!$B:$B,">="&$F$3,Log!$B:$B,"<="&$G$3,Log!$G:$G,$C$3,Log!$S:$S,"SIM",Log!$T:$T,"SIM",Log!$V:$V,$C8)) -> 0 | I8: =IF($C$3=Regras!$K$3,COUNTIFS(Log!$B:$B,">="&$F$3,Log!$B:$B,"<="&$G$3,Log!$S:$S,"SIM",Log!$T:$T,"NÃO",Log!$V:$V,$C8),COUNTIFS(Log!$B:$B,">="&$F$3,Log!$B:$B,"<="&$G$3,Log!$G:$G,$C$3,Log!$S:$S,"SIM",Log!$T:$T,"NÃO",Log!$V:$V,$C8)) -> 2 | K8: =IF($C$3=Regras!$K$3,COUNTIFS(Log!$B:$B,">="&$F$3,Log!$B:$B,"<="&$G$3,Log!$V:$V,$C8,Log!$W:$W,K$6),COUNTIFS(Log!$B:$B,">="&$F$3,Log!$B:$B,"<="&$G$3,Log!$G:$G,$C$3,Log!$V:$V,$C8,Log!$W:$W,K$6)) -> 12 | L8: =IF($C$3=Regras!$K$3,COUNTIFS(Log!$B:$B,">="&$F$3,Log!$B:$B,"<="&$G$3,Log!$V:$V,$C8,Log!$W:$W,L$6),COUNTIFS(Log!$B:$B,">="&$F$3,Log!$B:$B,"<="&$G$3,Log!$G:$G,$C$3,Log!$V:$V,$C8,Log!$W:$W,L$6)) -> 1 | M8: =IF($C$3=Regras!$K$3,COUNTIFS(Log!$B:$B,">="&$F$3,Log!$B:$B,"<="&$G$3,Log!$V:$V,$C8,Log!$W:$W,M$6),COUNTIFS(Log!$B:$B,">="&$F$3,Log!$B:$B,"<="&$G$3,Log!$G:$G,$C$3,Log!$V:$V,$C8,Log!$W:$W,M$6)) -> 0 | N8: =IF($C$3=Regras!$K$3,COUNTIFS(Log!$B:$B,">="&$F$3,Log!$B:$B,"<="&$G$3,Log!$V:$V,$C8,Log!$W:$W,N$6),COUNTIFS(Log!$B:$B,">="&$F$3,Log!$B:$B,"<="&$G$3,Log!$G:$G,$C$3,Log!$V:$V,$C8,Log!$W:$W,N$6)) -> 0 | P8: =IF($C$3=Regras!$K$3,COUNTIFS(Log!$B:$B,">="&$F$3,Log!$B:$B,"<="&$G$3,Log!$V:$V,$C8,Log!$W:$W,P$6&" 15")+ COUNTIFS(Log!$B:$B,">="&$F$3,Log!$B:$B,"<="&$G$3,Log!$V:$V,$C8,Log!$W:$W,P$6&" 7"), COUNTIFS(Log!$B:$B,">="&$F$3,Log!$B:$B,"<="&$G$3,Log!$G:$G,$C$3,Log!$V:$V,$C8,Log!$W:$W,P$6&" 7")+ COUNTIFS(Log!$B:$B,">="&$F$3,Log!$B:$B,"<="&$G$3,Log!$G:$G,$C$3,Log!$V:$V,$C8,Log!$W:$W,P$6&" 15")) -> 6 | Q8: =IF($C$3=Regras!$K$3,COUNTIFS(Log!$B:$B,">="&$F$3,Log!$B:$B,"<="&$G$3,Log!$V:$V,$C8,Log!$W:$W,Q$6),COUNTIFS(Log!$B:$B,">="&$F$3,Log!$B:$B,"<="&$G$3,Log!$G:$G,$C$3,Log!$V:$V,$C8,Log!$W:$W,Q$6)) -> 0 | S8: =IF($C$3=Regras!$K$3,COUNTIFS(Log!$B:$B,">="&$F$3,Log!$B:$B,"<="&$G$3,Log!$V:$V,$C8,Log!$W:$W,S$6),COUNTIFS(Log!$B:$B,">="&$F$3,Log!$B:$B,"<="&$G$3,Log!$G:$G,$C$3,Log!$V:$V,$C8,Log!$W:$W,S$6)) -> 0 | T8: =IF($C$3=Regras!$K$3,COUNTIFS(Log!$B:$B,">="&$F$3,Log!$B:$B,"<="&$G$3,Log!$V:$V,$C8,Log!$W:$W,T$6),COUNTIFS(Log!$B:$B,">="&$F$3,Log!$B:$B,"<="&$G$3,Log!$G:$G,$C$3,Log!$V:$V,$C8,Log!$W:$W,T$6)) -> 0
C9: ATENDIMENTO CLIENTES INATIVOS | D9: =IF($C$3=Regras!$K$3,COUNTIFS(Log!$B:$B,">="&$F$3,Log!$B:$B,"<="&$G$3,Log!$V:$V,$C9),COUNTIFS(Log!$B:$B,">="&$F$3,Log!$B:$B,"<="&$G$3,Log!$G:$G,$C$3,Log!$V:$V,$C9)) -> 1 | F9: =IF($C$3=Regras!$K$3,COUNTIFS(Log!$B:$B,">="&$F$3,Log!$B:$B,"<="&$G$3,Log!$R:$R,"SIM",Log!$V:$V,$C9),COUNTIFS(Log!$B:$B,">="&$F$3,Log!$B:$B,"<="&$G$3,Log!$G:$G,$C$3,Log!$R:$R,"SIM",Log!$V:$V,$C9)) -> 1 | G9: =IF($C$3=Regras!$K$3,COUNTIFS(Log!$B:$B,">="&$F$3,Log!$B:$B,"<="&$G$3,Log!$S:$S,"SIM",Log!$V:$V,$C9),COUNTIFS(Log!$B:$B,">="&$F$3,Log!$B:$B,"<="&$G$3,Log!$G:$G,$C$3,Log!$S:$S,"SIM",Log!$V:$V,$C9)) -> 0 | H9: =IF($C$3=Regras!$K$3,COUNTIFS(Log!$B:$B,">="&$F$3,Log!$B:$B,"<="&$G$3,Log!$S:$S,"SIM",Log!$T:$T,"SIM",Log!$V:$V,$C9),COUNTIFS(Log!$B:$B,">="&$F$3,Log!$B:$B,"<="&$G$3,Log!$G:$G,$C$3,Log!$S:$S,"SIM",Log!$T:$T,"SIM",Log!$V:$V,$C9)) -> 0 | I9: =IF($C$3=Regras!$K$3,COUNTIFS(Log!$B:$B,">="&$F$3,Log!$B:$B,"<="&$G$3,Log!$S:$S,"SIM",Log!$T:$T,"NÃO",Log!$V:$V,$C9),COUNTIFS(Log!$B:$B,">="&$F$3,Log!$B:$B,"<="&$G$3,Log!$G:$G,$C$3,Log!$S:$S,"SIM",Log!$T:$T,"NÃO",Log!$V:$V,$C9)) -> 0 | K9: =IF($C$3=Regras!$K$3,COUNTIFS(Log!$B:$B,">="&$F$3,Log!$B:$B,"<="&$G$3,Log!$V:$V,$C9,Log!$W:$W,K$6),COUNTIFS(Log!$B:$B,">="&$F$3,Log!$B:$B,"<="&$G$3,Log!$G:$G,$C$3,Log!$V:$V,$C9,Log!$W:$W,K$6)) -> 0 | L9: =IF($C$3=Regras!$K$3,COUNTIFS(Log!$B:$B,">="&$F$3,Log!$B:$B,"<="&$G$3,Log!$V:$V,$C9,Log!$W:$W,L$6),COUNTIFS(Log!$B:$B,">="&$F$3,Log!$B:$B,"<="&$G$3,Log!$G:$G,$C$3,Log!$V:$V,$C9,Log!$W:$W,L$6)) -> 0 | M9: =IF($C$3=Regras!$K$3,COUNTIFS(Log!$B:$B,">="&$F$3,Log!$B:$B,"<="&$G$3,Log!$V:$V,$C9,Log!$W:$W,M$6),COUNTIFS(Log!$B:$B,">="&$F$3,Log!$B:$B,"<="&$G$3,Log!$G:$G,$C$3,Log!$V:$V,$C9,Log!$W:$W,M$6)) -> 0 | N9: =IF($C$3=Regras!$K$3,COUNTIFS(Log!$B:$B,">="&$F$3,Log!$B:$B,"<="&$G$3,Log!$V:$V,$C9,Log!$W:$W,N$6),COUNTIFS(Log!$B:$B,">="&$F$3,Log!$B:$B,"<="&$G$3,Log!$G:$G,$C$3,Log!$V:$V,$C9,Log!$W:$W,N$6)) -> 1 | P9: =IF($C$3=Regras!$K$3,COUNTIFS(Log!$B:$B,">="&$F$3,Log!$B:$B,"<="&$G$3,Log!$V:$V,$C9,Log!$W:$W,P$6&" 15")+ COUNTIFS(Log!$B:$B,">="&$F$3,Log!$B:$B,"<="&$G$3,Log!$V:$V,$C9,Log!$W:$W,P$6&" 7"), COUNTIFS(Log!$B:$B,">="&$F$3,Log!$B:$B,"<="&$G$3,Log!$G:$G,$C$3,Log!$V:$V,$C9,Log!$W:$W,P$6&" 7")+ COUNTIFS(Log!$B:$B,">="&$F$3,Log!$B:$B,"<="&$G$3,Log!$G:$G,$C$3,Log!$V:$V,$C9,Log!$W:$W,P$6&" 15")) -> 0 | Q9: =IF($C$3=Regras!$K$3,COUNTIFS(Log!$B:$B,">="&$F$3,Log!$B:$B,"<="&$G$3,Log!$V:$V,$C9,Log!$W:$W,Q$6),COUNTIFS(Log!$B:$B,">="&$F$3,Log!$B:$B,"<="&$G$3,Log!$G:$G,$C$3,Log!$V:$V,$C9,Log!$W:$W,Q$6)) -> 0 | S9: =IF($C$3=Regras!$K$3,COUNTIFS(Log!$B:$B,">="&$F$3,Log!$B:$B,"<="&$G$3,Log!$V:$V,$C9,Log!$W:$W,S$6),COUNTIFS(Log!$B:$B,">="&$F$3,Log!$B:$B,"<="&$G$3,Log!$G:$G,$C$3,Log!$V:$V,$C9,Log!$W:$W,S$6)) -> 0 | T9: =IF($C$3=Regras!$K$3,COUNTIFS(Log!$B:$B,">="&$F$3,Log!$B:$B,"<="&$G$3,Log!$V:$V,$C9,Log!$W:$W,T$6),COUNTIFS(Log!$B:$B,">="&$F$3,Log!$B:$B,"<="&$G$3,Log!$G:$G,$C$3,Log!$V:$V,$C9,Log!$W:$W,T$6)) -> 0
C10: PÓS VENDA / RELACIONAMENTO | D10: =IF($C$3=Regras!$K$3,COUNTIFS(Log!$B:$B,">="&$F$3,Log!$B:$B,"<="&$G$3,Log!$V:$V,$C10),COUNTIFS(Log!$B:$B,">="&$F$3,Log!$B:$B,"<="&$G$3,Log!$G:$G,$C$3,Log!$V:$V,$C10)) -> 1 | F10: =IF($C$3=Regras!$K$3,COUNTIFS(Log!$B:$B,">="&$F$3,Log!$B:$B,"<="&$G$3,Log!$R:$R,"SIM",Log!$V:$V,$C10),COUNTIFS(Log!$B:$B,">="&$F$3,Log!$B:$B,"<="&$G$3,Log!$G:$G,$C$3,Log!$R:$R,"SIM",Log!$V:$V,$C10)) -> 1 | G10: =IF($C$3=Regras!$K$3,COUNTIFS(Log!$B:$B,">="&$F$3,Log!$B:$B,"<="&$G$3,Log!$S:$S,"SIM",Log!$V:$V,$C10),COUNTIFS(Log!$B:$B,">="&$F$3,Log!$B:$B,"<="&$G$3,Log!$G:$G,$C$3,Log!$S:$S,"SIM",Log!$V:$V,$C10)) -> 0 | H10: =IF($C$3=Regras!$K$3,COUNTIFS(Log!$B:$B,">="&$F$3,Log!$B:$B,"<="&$G$3,Log!$S:$S,"SIM",Log!$T:$T,"SIM",Log!$V:$V,$C10),COUNTIFS(Log!$B:$B,">="&$F$3,Log!$B:$B,"<="&$G$3,Log!$G:$G,$C$3,Log!$S:$S,"SIM",Log!$T:$T,"SIM",Log!$V:$V,$C10)) -> 0 | I10: =IF($C$3=Regras!$K$3,COUNTIFS(Log!$B:$B,">="&$F$3,Log!$B:$B,"<="&$G$3,Log!$S:$S,"SIM",Log!$T:$T,"NÃO",Log!$V:$V,$C10),COUNTIFS(Log!$B:$B,">="&$F$3,Log!$B:$B,"<="&$G$3,Log!$G:$G,$C$3,Log!$S:$S,"SIM",Log!$T:$T,"NÃO",Log!$V:$V,$C10)) -> 0 | K10: =IF($C$3=Regras!$K$3,COUNTIFS(Log!$B:$B,">="&$F$3,Log!$B:$B,"<="&$G$3,Log!$V:$V,$C10,Log!$W:$W,K$6),COUNTIFS(Log!$B:$B,">="&$F$3,Log!$B:$B,"<="&$G$3,Log!$G:$G,$C$3,Log!$V:$V,$C10,Log!$W:$W,K$6)) -> 0 | L10: =IF($C$3=Regras!$K$3,COUNTIFS(Log!$B:$B,">="&$F$3,Log!$B:$B,"<="&$G$3,Log!$V:$V,$C10,Log!$W:$W,L$6),COUNTIFS(Log!$B:$B,">="&$F$3,Log!$B:$B,"<="&$G$3,Log!$G:$G,$C$3,Log!$V:$V,$C10,Log!$W:$W,L$6)) -> 0 | M10: =IF($C$3=Regras!$K$3,COUNTIFS(Log!$B:$B,">="&$F$3,Log!$B:$B,"<="&$G$3,Log!$V:$V,$C10,Log!$W:$W,M$6),COUNTIFS(Log!$B:$B,">="&$F$3,Log!$B:$B,"<="&$G$3,Log!$G:$G,$C$3,Log!$V:$V,$C10,Log!$W:$W,M$6)) -> 0 | N10: =IF($C$3=Regras!$K$3,COUNTIFS(Log!$B:$B,">="&$F$3,Log!$B:$B,"<="&$G$3,Log!$V:$V,$C10,Log!$W:$W,N$6),COUNTIFS(Log!$B:$B,">="&$F$3,Log!$B:$B,"<="&$G$3,Log!$G:$G,$C$3,Log!$V:$V,$C10,Log!$W:$W,N$6)) -> 0 | P10: =IF($C$3=Regras!$K$3,COUNTIFS(Log!$B:$B,">="&$F$3,Log!$B:$B,"<="&$G$3,Log!$V:$V,$C10,Log!$W:$W,P$6&" 15")+ COUNTIFS(Log!$B:$B,">="&$F$3,Log!$B:$B,"<="&$G$3,Log!$V:$V,$C10,Log!$W:$W,P$6&" 7"), COUNTIFS(Log!$B:$B,">="&$F$3,Log!$B:$B,"<="&$G$3,Log!$G:$G,$C$3,Log!$V:$V,$C10,Log!$W:$W,P$6&" 7")+ COUNTIFS(Log!$B:$B,">="&$F$3,Log!$B:$B,"<="&$G$3,Log!$G:$G,$C$3,Log!$V:$V,$C10,Log!$W:$W,P$6&" 15")) -> 1 | Q10: =IF($C$3=Regras!$K$3,COUNTIFS(Log!$B:$B,">="&$F$3,Log!$B:$B,"<="&$G$3,Log!$V:$V,$C10,Log!$W:$W,Q$6),COUNTIFS(Log!$B:$B,">="&$F$3,Log!$B:$B,"<="&$G$3,Log!$G:$G,$C$3,Log!$V:$V,$C10,Log!$W:$W,Q$6)) -> 0 | S10: =IF($C$3=Regras!$K$3,COUNTIFS(Log!$B:$B,">="&$F$3,Log!$B:$B,"<="&$G$3,Log!$V:$V,$C10,Log!$W:$W,S$6),COUNTIFS(Log!$B:$B,">="&$F$3,Log!$B:$B,"<="&$G$3,Log!$G:$G,$C$3,Log!$V:$V,$C10,Log!$W:$W,S$6)) -> 0 | T10: =IF($C$3=Regras!$K$3,COUNTIFS(Log!$B:$B,">="&$F$3,Log!$B:$B,"<="&$G$3,Log!$V:$V,$C10,Log!$W:$W,T$6),COUNTIFS(Log!$B:$B,">="&$F$3,Log!$B:$B,"<="&$G$3,Log!$G:$G,$C$3,Log!$V:$V,$C10,Log!$W:$W,T$6)) -> 0
C11: CONTATOS PASSIVO / SUPORTE | D11: =IF($C$3=Regras!$K$3,COUNTIFS(Log!$B:$B,">="&$F$3,Log!$B:$B,"<="&$G$3,Log!$V:$V,$C11),COUNTIFS(Log!$B:$B,">="&$F$3,Log!$B:$B,"<="&$G$3,Log!$G:$G,$C$3,Log!$V:$V,$C11)) -> 0 | F11: =IF($C$3=Regras!$K$3,COUNTIFS(Log!$B:$B,">="&$F$3,Log!$B:$B,"<="&$G$3,Log!$R:$R,"SIM",Log!$V:$V,$C11),COUNTIFS(Log!$B:$B,">="&$F$3,Log!$B:$B,"<="&$G$3,Log!$G:$G,$C$3,Log!$R:$R,"SIM",Log!$V:$V,$C11)) -> 0 | G11: =IF($C$3=Regras!$K$3,COUNTIFS(Log!$B:$B,">="&$F$3,Log!$B:$B,"<="&$G$3,Log!$S:$S,"SIM",Log!$V:$V,$C11),COUNTIFS(Log!$B:$B,">="&$F$3,Log!$B:$B,"<="&$G$3,Log!$G:$G,$C$3,Log!$S:$S,"SIM",Log!$V:$V,$C11)) -> 0 | H11: =IF($C$3=Regras!$K$3,COUNTIFS(Log!$B:$B,">="&$F$3,Log!$B:$B,"<="&$G$3,Log!$S:$S,"SIM",Log!$T:$T,"SIM",Log!$V:$V,$C11),COUNTIFS(Log!$B:$B,">="&$F$3,Log!$B:$B,"<="&$G$3,Log!$G:$G,$C$3,Log!$S:$S,"SIM",Log!$T:$T,"SIM",Log!$V:$V,$C11)) -> 0 | I11: =IF($C$3=Regras!$K$3,COUNTIFS(Log!$B:$B,">="&$F$3,Log!$B:$B,"<="&$G$3,Log!$S:$S,"SIM",Log!$T:$T,"NÃO",Log!$V:$V,$C11),COUNTIFS(Log!$B:$B,">="&$F$3,Log!$B:$B,"<="&$G$3,Log!$G:$G,$C$3,Log!$S:$S,"SIM",Log!$T:$T,"NÃO",Log!$V:$V,$C11)) -> 0 | K11: =IF($C$3=Regras!$K$3,COUNTIFS(Log!$B:$B,">="&$F$3,Log!$B:$B,"<="&$G$3,Log!$V:$V,$C11,Log!$W:$W,K$6),COUNTIFS(Log!$B:$B,">="&$F$3,Log!$B:$B,"<="&$G$3,Log!$G:$G,$C$3,Log!$V:$V,$C11,Log!$W:$W,K$6)) -> 0 | L11: =IF($C$3=Regras!$K$3,COUNTIFS(Log!$B:$B,">="&$F$3,Log!$B:$B,"<="&$G$3,Log!$V:$V,$C11,Log!$W:$W,L$6),COUNTIFS(Log!$B:$B,">="&$F$3,Log!$B:$B,"<="&$G$3,Log!$G:$G,$C$3,Log!$V:$V,$C11,Log!$W:$W,L$6)) -> 0 | M11: =IF($C$3=Regras!$K$3,COUNTIFS(Log!$B:$B,">="&$F$3,Log!$B:$B,"<="&$G$3,Log!$V:$V,$C11,Log!$W:$W,M$6),COUNTIFS(Log!$B:$B,">="&$F$3,Log!$B:$B,"<="&$G$3,Log!$G:$G,$C$3,Log!$V:$V,$C11,Log!$W:$W,M$6)) -> 0 | N11: =IF($C$3=Regras!$K$3,COUNTIFS(Log!$B:$B,">="&$F$3,Log!$B:$B,"<="&$G$3,Log!$V:$V,$C11,Log!$W:$W,N$6),COUNTIFS(Log!$B:$B,">="&$F$3,Log!$B:$B,"<="&$G$3,Log!$G:$G,$C$3,Log!$V:$V,$C11,Log!$W:$W,N$6)) -> 0 | P11: =IF($C$3=Regras!$K$3,COUNTIFS(Log!$B:$B,">="&$F$3,Log!$B:$B,"<="&$G$3,Log!$V:$V,$C11,Log!$W:$W,P$6&" 15")+ COUNTIFS(Log!$B:$B,">="&$F$3,Log!$B:$B,"<="&$G$3,Log!$V:$V,$C11,Log!$W:$W,P$6&" 7"), COUNTIFS(Log!$B:$B,">="&$F$3,Log!$B:$B,"<="&$G$3,Log!$G:$G,$C$3,Log!$V:$V,$C11,Log!$W:$W,P$6&" 7")+ COUNTIFS(Log!$B:$B,">="&$F$3,Log!$B:$B,"<="&$G$3,Log!$G:$G,$C$3,Log!$V:$V,$C11,Log!$W:$W,P$6&" 15")) -> 0 | Q11: =IF($C$3=Regras!$K$3,COUNTIFS(Log!$B:$B,">="&$F$3,Log!$B:$B,"<="&$G$3,Log!$V:$V,$C11,Log!$W:$W,Q$6),COUNTIFS(Log!$B:$B,">="&$F$3,Log!$B:$B,"<="&$G$3,Log!$G:$G,$C$3,Log!$V:$V,$C11,Log!$W:$W,Q$6)) -> 0 | S11: =IF($C$3=Regras!$K$3,COUNTIFS(Log!$B:$B,">="&$F$3,Log!$B:$B,"<="&$G$3,Log!$V:$V,$C11,Log!$W:$W,S$6),COUNTIFS(Log!$B:$B,">="&$F$3,Log!$B:$B,"<="&$G$3,Log!$G:$G,$C$3,Log!$V:$V,$C11,Log!$W:$W,S$6)) -> 0 | T11: =IF($C$3=Regras!$K$3,COUNTIFS(Log!$B:$B,">="&$F$3,Log!$B:$B,"<="&$G$3,Log!$V:$V,$C11,Log!$W:$W,T$6),COUNTIFS(Log!$B:$B,">="&$F$3,Log!$B:$B,"<="&$G$3,Log!$G:$G,$C$3,Log!$V:$V,$C11,Log!$W:$W,T$6)) -> 0
C12: ENVIO DE MATERIAL - MKT | D12: =IF($C$3=Regras!$K$3,COUNTIFS(Log!$B:$B,">="&$F$3,Log!$B:$B,"<="&$G$3,Log!$V:$V,$C12),COUNTIFS(Log!$B:$B,">="&$F$3,Log!$B:$B,"<="&$G$3,Log!$G:$G,$C$3,Log!$V:$V,$C12)) -> 0 | F12: =IF($C$3=Regras!$K$3,COUNTIFS(Log!$B:$B,">="&$F$3,Log!$B:$B,"<="&$G$3,Log!$R:$R,"SIM",Log!$V:$V,$C12),COUNTIFS(Log!$B:$B,">="&$F$3,Log!$B:$B,"<="&$G$3,Log!$G:$G,$C$3,Log!$R:$R,"SIM",Log!$V:$V,$C12)) -> 0 | G12: =IF($C$3=Regras!$K$3,COUNTIFS(Log!$B:$B,">="&$F$3,Log!$B:$B,"<="&$G$3,Log!$S:$S,"SIM",Log!$V:$V,$C12),COUNTIFS(Log!$B:$B,">="&$F$3,Log!$B:$B,"<="&$G$3,Log!$G:$G,$C$3,Log!$S:$S,"SIM",Log!$V:$V,$C12)) -> 0 | H12: =IF($C$3=Regras!$K$3,COUNTIFS(Log!$B:$B,">="&$F$3,Log!$B:$B,"<="&$G$3,Log!$S:$S,"SIM",Log!$T:$T,"SIM",Log!$V:$V,$C12),COUNTIFS(Log!$B:$B,">="&$F$3,Log!$B:$B,"<="&$G$3,Log!$G:$G,$C$3,Log!$S:$S,"SIM",Log!$T:$T,"SIM",Log!$V:$V,$C12)) -> 0 | I12: =IF($C$3=Regras!$K$3,COUNTIFS(Log!$B:$B,">="&$F$3,Log!$B:$B,"<="&$G$3,Log!$S:$S,"SIM",Log!$T:$T,"NÃO",Log!$V:$V,$C12),COUNTIFS(Log!$B:$B,">="&$F$3,Log!$B:$B,"<="&$G$3,Log!$G:$G,$C$3,Log!$S:$S,"SIM",Log!$T:$T,"NÃO",Log!$V:$V,$C12)) -> 0 | K12: =IF($C$3=Regras!$K$3,COUNTIFS(Log!$B:$B,">="&$F$3,Log!$B:$B,"<="&$G$3,Log!$V:$V,$C12,Log!$W:$W,K$6),COUNTIFS(Log!$B:$B,">="&$F$3,Log!$B:$B,"<="&$G$3,Log!$G:$G,$C$3,Log!$V:$V,$C12,Log!$W:$W,K$6)) -> 0 | L12: =IF($C$3=Regras!$K$3,COUNTIFS(Log!$B:$B,">="&$F$3,Log!$B:$B,"<="&$G$3,Log!$V:$V,$C12,Log!$W:$W,L$6),COUNTIFS(Log!$B:$B,">="&$F$3,Log!$B:$B,"<="&$G$3,Log!$G:$G,$C$3,Log!$V:$V,$C12,Log!$W:$W,L$6)) -> 0 | M12: =IF($C$3=Regras!$K$3,COUNTIFS(Log!$B:$B,">="&$F$3,Log!$B:$B,"<="&$G$3,Log!$V:$V,$C12,Log!$W:$W,M$6),COUNTIFS(Log!$B:$B,">="&$F$3,Log!$B:$B,"<="&$G$3,Log!$G:$G,$C$3,Log!$V:$V,$C12,Log!$W:$W,M$6)) -> 0 | N12: =IF($C$3=Regras!$K$3,COUNTIFS(Log!$B:$B,">="&$F$3,Log!$B:$B,"<="&$G$3,Log!$V:$V,$C12,Log!$W:$W,N$6),COUNTIFS(Log!$B:$B,">="&$F$3,Log!$B:$B,"<="&$G$3,Log!$G:$G,$C$3,Log!$V:$V,$C12,Log!$W:$W,N$6)) -> 0 | P12: =IF($C$3=Regras!$K$3,COUNTIFS(Log!$B:$B,">="&$F$3,Log!$B:$B,"<="&$G$3,Log!$V:$V,$C12,Log!$W:$W,P$6&" 15")+ COUNTIFS(Log!$B:$B,">="&$F$3,Log!$B:$B,"<="&$G$3,Log!$V:$V,$C12,Log!$W:$W,P$6&" 7"), COUNTIFS(Log!$B:$B,">="&$F$3,Log!$B:$B,"<="&$G$3,Log!$G:$G,$C$3,Log!$V:$V,$C12,Log!$W:$W,P$6&" 7")+ COUNTIFS(Log!$B:$B,">="&$F$3,Log!$B:$B,"<="&$G$3,Log!$G:$G,$C$3,Log!$V:$V,$C12,Log!$W:$W,P$6&" 15")) -> 0 | Q12: =IF($C$3=Regras!$K$3,COUNTIFS(Log!$B:$B,">="&$F$3,Log!$B:$B,"<="&$G$3,Log!$V:$V,$C12,Log!$W:$W,Q$6),COUNTIFS(Log!$B:$B,">="&$F$3,Log!$B:$B,"<="&$G$3,Log!$G:$G,$C$3,Log!$V:$V,$C12,Log!$W:$W,Q$6)) -> 0 | S12: =IF($C$3=Regras!$K$3,COUNTIFS(Log!$B:$B,">="&$F$3,Log!$B:$B,"<="&$G$3,Log!$V:$V,$C12,Log!$W:$W,S$6),COUNTIFS(Log!$B:$B,">="&$F$3,Log!$B:$B,"<="&$G$3,Log!$G:$G,$C$3,Log!$V:$V,$C12,Log!$W:$W,S$6)) -> 0 | T12: =IF($C$3=Regras!$K$3,COUNTIFS(Log!$B:$B,">="&$F$3,Log!$B:$B,"<="&$G$3,Log!$V:$V,$C12,Log!$W:$W,T$6),COUNTIFS(Log!$B:$B,">="&$F$3,Log!$B:$B,"<="&$G$3,Log!$G:$G,$C$3,Log!$V:$V,$C12,Log!$W:$W,T$6)) -> 0
C13: TOTAL | D13: =SUM(D7:D12) -> 25 | F13: =SUM(F7:F12) -> 25 | G13: =SUM(G7:G12) -> 2 | H13: =SUM(H7:H12) -> 0 | I13: =SUM(I7:I12) -> 2 | K13: =SUM(K7:K12) -> 13 | L13: =SUM(L7:L12) -> 1 | M13: =SUM(M7:M12) -> 0 | N13: =SUM(N7:N12) -> 3 | P13: =SUM(P7:P12) -> 8 | Q13: =SUM(Q7:Q12) -> 0 | S13: =SUM(S7:S12) -> 0 | T13: =SUM(T7:T12) -> 0

Sheet Regras
C2: TEMPO ULTIMA VENDA | D2: STATUS | F2: RESULTADO DO CONTATO | G2: FOLLOW UP | I2: TIPO DO CONTATO | K2: VENDEDOR
C3: 50 | D3: ATIVO | F3: EM ATENDIMENTO | G3: 2 | I3: PROSPECÇÃO NOVOS CLIENTES | K3: Time
C4: 60 | D4: EM RISCO | F4: ORÇAMENTO | G4: 1 | I4: ATENDIMENTO CLIENTES ATIVOS | K4: Manu Ditzel
C5: 90 | D5: INATIVO RECENTE | F5: CADASTRO | G5: 2 | I5: ATENDIMENTO CLIENTES INATIVOS | K5: Larissa Padilha
C6: 10000000 | D6: INATIVO ANTIGO | F6: VENDA | G6: 45 | I6: PÓS VENDA / RELACIONAMENTO | K6: Central - Daiane
D7: NOVO | F7: FOLLOW UP 7 | G7: 7 | I7: CONTATOS PASSIVO / SUPORTE | K7: Lorrany
D8: PROSPECT | F8: FOLLOW UP 15 | G8: 15 | I8: ENVIO DE MATERIAL - MKT | K8: Julio Gadret
D9: LEAD (DAI) | F9: SUPORTE | G9: NÃO
D10: LEAD | F10: CLIENTE INATIVO | G10: NÃO
F11: PERDA / NÃO VENDA | G11: NÃO
